Workbook
Name mos: '[1]Общие данные'!$C$23:$D$23
Name mulk: '[1]Общие данные'!$C$24:$W$24

Sheet umumiy_malumot
A1: =CONCATENATE(B65," olish uchun ariza") -> mikroqarz olish uchun ariza | B1: №3-BR
A2: =CONCATENATE(B65," olish uchun ariza sanasi QO’L BILAN KIRITILADI") -> mikroqarz olish uchun ariza sanasi QO’L BILAN KIRITILADI | B2: 06.01.2026 | D2: =180+B2 -> 46208
A4: Qarz oluvchi bo’yicha ma’lumotlar
A5: Ariza beruvchining FISh (kim? – Ibragimov Rustam Sadikovich) | B5: TURAYEV ISROIL BURIYEVICH
A6: agar o’zgarishlar bo’lgan bo’lsa oldingi FISh (Sadikov Rustam Sadikovich yoki yo’q) | B6: yo’q | C6: ha | D6: yo’q
A7: Ariza beruvchining FISh (kim? – Ibragimov R.S.) | B7: TURAYEV I.B.
A8: FISh (ariza kimdan? – Ibragimov Rustam Sadikovichdan) | B8: =B5 -> TURAYEV ISROIL BURIYEVICH
A9: FISh (kimdan? – Ibragimov R.S.dan) | B9: =B7 -> TURAYEV I.B.
A10: FISh (kimga? – Ibragimov Rustam Sadikovichga) | B10: =B8 -> TURAYEV ISROIL BURIYEVICH
A11: FISh (kimga? – Ibragimov R.S.ga) | B11: =B9 -> TURAYEV I.B.
A12: FISh (kim bilan? – Ibragimov Rustam Sadikovich bilan) | B12: =B10 -> TURAYEV ISROIL BURIYEVICH
A13: FISh (kim bilan? – Ibragimov R.S. bilan) | B13: =B11 -> TURAYEV I.B.
A14: Fuqaroligi (O’zbekiston Respublikasi) | B14: O’zbekiston Respublikasi
A15: Tug’ilgan sanasi (01.10.2011 yil) | B15: 14.11.1983 yil
A16: Pasport seriyasi (СА №1234567) | B16: AD 6760672
B17: IIV 61013 | D17: =TEXT(C17,"ДД.ММ.ГГГГ") -> 00.01.1900
B18: 45390 | C18: =TEXT(B18,"ДД.ММ.ГГГГ") -> 08.04.2024
B19: 49041 | C19: =TEXT(B19,"ДД.ММ.ГГГГ") -> 07.04.2034
A20: Kim va qachon berilgan (Toshkent shahri Chilonzor IIB tomonidan 2011 yil __.____) | B20: =""&B17&" tomonidan "&C18&" yilda berilgan" -> IIV 61013 tomonidan 08.04.2024 yilda berilgan | C20: =""&B17&" tomonidan "&C18&" yilda berilgan" -> IIV 61013 tomonidan 08.04.2024 yilda berilgan
A21: Pasportni amal qilish muddati (01.10.2011 yilgacha / yoki muddatsiz) | B21: =""&C19&" y." -> 07.04.2034 y. | C21: =""&C19&" yilgacha" -> 07.04.2034 yilgacha
A22: doimiy ro’yhatdan o’tgan joyi (Toshkent sh., Mirobod tumani, Nukus ko’chasi, 1 uy, 1 honadon) | B22: BUXORO VILOYATI KOGON SHAHRI ZAFAROBOD 17-UY | C22: =TEXT(B19,"ДД.ММ.ГГГГ") -> 07.04.2034
A23: doimiy ro’yhatdan o’tgan joyi haqiqatdagi turar joyi bilan mos keladi/mos kelmaydi | B23: mos keladi | C23: mos keladi | D23: mos kelmaydi
A24: Ro’yhatdan o’tish joyida yashash asosi | B24: Mulk huquqi | C24: Mulk huquqi | D24: ijara | F24: служебная | G24: другое | H24: -
A25: Telefon raqami kod bilan ((99871) 277 77 77) | B25: 91 923 50 54 MIJOZ
A26: Mo’ljal | B26: BGGK ZONA
B27: =IF(B23="mos keladi",B22,B28) -> BUXORO VILOYATI KOGON SHAHRI ZAFAROBOD 17-UY
A28: Haqiqatdagi yashash joyi (Toshkent sh., Mirobod tumani, Nukus ko’chasi, 1 uy, 1 honadon) | B28: BUXORO VILOYATI KOGON SHAHRI ZAFAROBOD 17-UY
A29: Haqiqatdagi yashash joyida turish asosi | B29: Mulk huquqi | C29: Mulk huquqi | D29: ijara | F29: xizmat | G29: boshqa | H29: -
A30: Mijozning jinsi | B30: erkak | C30: erkak | D30: ayol
A31: Tug’ilgan joyi (Toshkent) | B31: KOGON SHAHRI
A32: Fuqaroligi (O’zbekiston Respublikasi) | B32: O’zbekiston Respublikasi
A33: Telefon raqami kod bilan ((99871) 277 77 77)TEGILMASIN | B33: =B25 -> 91 923 50 54 MIJOZ
B34: =IF(B23="mos keladi",B26,B35) -> BGGK ZONA
A35: Mo’ljal
A36: Oilaviy ahvoli
A37: Oila a'zolari soni (jami):
A38: Ma’lumoti
A39: Mutaxassisligi
A40: Ish telefoni raqami kod bilan ((99890) 3270000)TEGILMASIN | B40: =B25 -> 91 923 50 54 MIJOZ
A41: Mobil telefon raqami kod bilan ((99890) 3270000) | B41: 50 377 80 88 OTASI TO'LOVCHI
A42: Ish telefoni raqami kod bilan ((99890) 3270000) | B42: 93 000 16 05 O'G'LI
A43: Mobil telefon raqami kod bilan ((99890) 3270000)
A44: Asosiy ish joyi | B44: Yakka tartibdagi tadbirkor | C44: Yakka tartibdagi tadbirkor | D44: O'Z O'ZINI BAND QILGAN FUQARO
B45: =IF(B44=D44,CONCATENATE("MA'LUMOTNOMA ",B47,B46),C44) -> Yakka tartibdagi tadbirkor
A46: O'Z O'ZINI BAND QILGAN BO'LSA, MA'LUMOTNOMA KIRITING
B47: =CONCATENATE(C47," ",B46) -> № | C47: №
A48: AGAR O'Z O'ZINI BAND QILGAN FUQARO BO'LSA FAOLIYAT TURINI KIRITING
A49: Lavozimi | B49: =IF(B44=C44,C44,B48) -> Yakka tartibdagi tadbirkor
A50: Tashkilotning haqiqiy manzili (Toshkent sh., Mirobod tumani, Nukus ko’chasi, 1 uy, 1 honadon)
A51: Mo’ljal
A52: Ish staji, sanasidan (01.10.2011 yildan)
A53: Umumiy mehnat staji (3 yil/ 5 yil)
A54: Ish joyi telefon raqami
A55: Mijozning STIRi
A56: Mijozning unikal kodi | B56: 990000__
A57: QARZ OLUVCHINING ISH JOYI, LAVOZIMI VA O'RTACHA OYLIK DAROMADI
A58: Ish joyi | B58: =IF(B44=C44,C44,CONCATENATE(B44," ",B47)) -> Yakka tartibdagi tadbirkor
A59: Lavozimi | B59: =B49 -> Yakka tartibdagi tadbirkor
A60: O’rtacha oylik daromadi | B60: 5000000 | C60: =C63/B75 -> 0.47934551
A61: Mijozning boshqa daromadlari | B61: 5000000 | C61: Йиллик фоиз(50% ошмаган холда)
A62: Ishning davomiyligi | B62: =B53 -> 0
A63: Ish joyidan ma’lumotnomaning raqami va sanasi | C63: =SUM(grafik!E9:E20) -> 15818402
A64: Kredit bo’yicha parametrlar | C64: =PROPER(B65) -> Mikroqarz | D64: =UPPER(B65) -> MIKROQARZ
A65: Kredit turi | B65: =IF(B75>100000001,"mikrokredit",IF(B75<100000001,"mikroqarz",0)) -> mikroqarz | C65: =DATE(YEAR(B67),MONTH(B67)+B81,DAY(B67)) -> 47124
A66: Kredit shartnomasi raqami | B66: =B1 -> №3-BR | C66: =MONTH(C65) -> 1 | D66: =IF(C66=C68,C70,IF(C66=D68,D70,IF(C66=F68,F70,IF(C66=G68,G70,IF(C66=H68,H70,IF(C66=I68,I70,IF(C66=J68,J70,IF(C66=K68,K70,IF(C66=L68,L70,IF(C66=M68,M70,IF(C66=N68,N70,IF(C66=O68,O70,)))))))))))) -> yanvar | F66: =DAY(C65) -> 6 | G66: =YEAR(C65) -> 2029 | H66: =MONTH(C65) -> 1 | I66: =IF(C66=C68,C71,IF(C66=D68,D71,IF(C66=F68,F71,IF(C66=G68,G71,IF(C66=H68,H71,IF(C66=I68,I71,IF(C66=J68,J71,IF(C66=K68,K71,IF(C66=L68,L71,IF(C66=M68,M71,IF(C66=N68,N71,IF(C66=O68,O71,)))))))))))) -> yanvar | J66: =YEAR(C65) -> 2029
A67: Kredit shartnomasi sanasi (14.10.2011) | B67: =B2 -> 06.01.2026 | C67: =MONTH(B67) -> 1 | D67: =IF(C67=C68,C70,IF(C67=D68,D70,IF(C67=F68,F70,IF(C67=G68,G70,IF(C67=H68,H70,IF(C67=I68,I70,IF(C67=J68,J70,IF(C67=K68,K70,IF(C67=L68,L70,IF(C67=M68,M70,IF(C67=N68,N70,IF(C67=O68,O70,)))))))))))) -> yanvar | F67: =DAY(B67) -> 6 | G67: =YEAR(B67) -> 2026 | H67: =MONTH(B67) -> 1 | I67: =IF(C67=C68,C71,IF(C67=D68,D71,IF(C67=F68,F71,IF(C67=G68,G71,IF(C67=H68,H71,IF(C67=I68,I71,IF(C67=J68,J71,IF(C67=K68,K71,IF(C67=L68,L71,IF(C67=M68,M71,IF(C67=N68,N71,IF(C67=O68,O71,)))))))))))) -> yanvar | J67: =YEAR(B67) -> 2026
A68: Kredit shartnomasi sanasi (14.10.2011 y.) | B68: =""&F67&" "&D67&" "&G67&" y." -> 6 yanvar 2026 y. | C68: 1 | D68: 2 | F68: 3 | G68: 4 | H68: 5 | I68: 6 | J68: 7 | K68: 8 | L68: 9 | M68: 10 | N68: 11 | O68: 12
B69: =""&F67&" "&I67&" "&G67&" y." -> 6 yanvar 2026 y.
B70: =B68 -> 6 yanvar 2026 y. | C70: yanvar | D70: fevral | F70: mart | G70: aprel | H70: may | I70: iyun | J70: iyul | K70: avgust | L70: sentabr | M70: oktabr | N70: noyabr | O70: dekabr
B71: =B69 -> 6 yanvar 2026 y. | C71: yanvar | D71: fevral | F71: mart | G71: aprel | H71: may | I71: iyun | J71: iyul | K71: avgust | L71: sentabr | M71: oktabr | N71: noyabr | O71: dekabr
A72: Tugash sanasi QO’L BILAN KIRITILADI | B72: =""&F66&" "&D66&" "&G66&" y." -> 6 yanvar 2029 y.
B73: =""&F66&" "&I66&" "&G66&" y." -> 6 yanvar 2029 y.
A74: Kredit shartnomasi raqami va sanasi | B74: =""&B68&"dan "&B66&"" -> 6 yanvar 2026 y.dan №3-BR
A75: =CONCATENATE(B65," miqdori (summasi)") -> mikroqarz miqdori (summasi) | B75: 33000000 | C75: Uzbek tilida
A76: TEGILMASIN | B76: =""&SUBSTITUTE(SUBSTITUTE(SUBSTITUTE(TRIM(SUBSTITUTE(SUBSTITUTE(SUBSTITUTE(SUBSTITUTE(SUBSTITUTE(SUBSTITUTE(SUBSTITUTE(SUBSTITUTE(SUBSTITUTE(SUBSTITUTE(SUBSTITUTE(SUBSTITUTE(SUBSTITUTE(SUBSTITUTE(SUBSTITUTE(SUBSTITUTE(SUBSTITUTE(SUBSTITUTE(SUBSTITUTE(SUBSTITUTE(SUBSTITUTE(SUBSTITUTE(SUBSTITUTE(SUBSTITUTE(SUBSTITUTE(SUBSTITUTE(SUBSTITUTE(SUBSTITUTE(SUBSTITUTE(SUBSTITUTE(SUBSTITUTE(SUBSTITUTE(SUBSTITUTE(SUBSTITUTE(SUBSTITUTE(SUBSTITUTE(SUBSTITUTE(SUBSTITUTE(SUBSTITUTE(SUBSTITUTE(SUBSTITUTE(SUBSTITUTE(SUBSTITUTE(SUBSTITUTE(IF(LEN(INT(B75))>6,ROMAN(MID(INT(B75),1,LEN(INT(B75))-6)+0)&" million "&ROMAN(MID(INT(B75),LEN(INT(B75))-5,3)+0)&" ming "&ROMAN(MID(INT(B75),LEN(INT(B75))-2,3)+0),IF(LEN(INT(B75))>3,ROMAN(MID(INT(B75),1,LEN(INT(B75))-3)+0)&" ming "&ROMAN(MID(INT(B75),LEN(INT(B75))-2,3)+0),ROMAN(INT(B75)))),"DCCC"," sakkiz yuz"),"DCC"," yetti yuz"),"DC"," olti yuz"),"CD"," to'rt yuz"),"XC"," to'qson"),"CCC"," uch yuz"),"CC"," ikki yuz"),"D"," besh yuz"),"CM"," to'qqiz yuz"),"C"," yuz"),"XL"," qirq"),"LXXX"," sakson"),"LXX"," yetmish"),"LX"," oltmish"),"L"," ellik"),"XXX"," o'ttiz"),"XX"," yigirma"),"XIX"," o'n toqqiz"),"XVIII"," o'n sakkiz"),"XVII"," o'n yetti"),"XVI"," o'n olti"),"XV"," o'n besh"),"XIV"," o'n to'rt"),"XIII"," o'n uch"),"XII"," o'n ikki"),"XI"," o'n bir"),"IX"," to'qqiz"),"X"," o'n"),"VIII"," sakkiz"),"VII"," yetti"),"VI"," olti"),"IV"," to'rt"),"V"," besh"),"III"," uch"),"II"," ikki"),"I"," bir"),"bir ming","bir ming"),"ikki ming","ikki ming"),"uch ming","uch ming"),"to'rt ming","to'rt ming"),"bir million","bir million"),"ikki million","ikki million"),"uch million","uch million"),"to'rt million","to'rt million")),"million ming","million"),"million ming","million"),"million ming","million")&" so'm" -> o'ttiz uch million so'm | C76: =UPPER(LEFT(SUBSTITUTE(SUBSTITUTE(SUBSTITUTE(TRIM(SUBSTITUTE(SUBSTITUTE(SUBSTITUTE(SUBSTITUTE(SUBSTITUTE(SUBSTITUTE(SUBSTITUTE(SUBSTITUTE(SUBSTITUTE(SUBSTITUTE(SUBSTITUTE(SUBSTITUTE(SUBSTITUTE(SUBSTITUTE(SUBSTITUTE(SUBSTITUTE(SUBSTITUTE(SUBSTITUTE(SUBSTITUTE(SUBSTITUTE(SUBSTITUTE(SUBSTITUTE(SUBSTITUTE(SUBSTITUTE(SUBSTITUTE(SUBSTITUTE(SUBSTITUTE(SUBSTITUTE(SUBSTITUTE(SUBSTITUTE(SUBSTITUTE(SUBSTITUTE(SUBSTITUTE(SUBSTITUTE(SUBSTITUTE(SUBSTITUTE(SUBSTITUTE(SUBSTITUTE(SUBSTITUTE(SUBSTITUTE(SUBSTITUTE(SUBSTITUTE(SUBSTITUTE(SUBSTITUTE(SUBSTITUTE(SUBSTITUTE(SUBSTITUTE(SUBSTITUTE(IF(LEN(ROUNDDOWN(B75,0))>6,ROMAN(MID(ROUNDDOWN(B75,0),1,LEN(ROUNDDOWN(B75,0))-6)+0)&" million "&ROMAN(MID(ROUNDDOWN(B75,0),LEN(ROUNDDOWN(B75,0))-5,3)+0)&" ming "&ROMAN(MID(ROUNDDOWN(B75,0),LEN(ROUNDDOWN(B75,0))-2,3)+0)&" so'm",IF(LEN(ROUNDDOWN(B75,0))>3,ROMAN(MID(ROUNDDOWN(B75,0),1,LEN(ROUNDDOWN(B75,0))-3)+0)&" ming "&ROMAN(MID(ROUNDDOWN(B75,0),LEN(ROUNDDOWN(B75,0))-2,3)+0)&" so'm",ROMAN(ROUNDDOWN(B75,0))&" so'm")),"DCCC"," sakkiz yuz"),"DCC"," yetti yuz"),"DC"," olti yuz"),"CD"," to'rt yuz"),"XC"," to'qson"),"CCC"," uch yuz"),"CC"," ikki yuz"),"D"," besh yuz"),"CM"," to'qqiz yuz"),"C"," yuz"),"XL"," qiriq"),"LXXX"," sakson"),"LXX"," yetmish"),"LX"," oltmish"),"L"," ellik"),"XXX"," o'ttiz"),"XX"," yigirma"),"XIX"," o'n tiqqiz"),"XVIII"," o'n sakkiz"),"XVII"," o'n yetti"),"XVI"," o'n olti"),"XV"," o'n besh"),"XIV"," o'n to'rt"),"XIII"," o'n uch"),"XII"," o'n ikki"),"XI"," o'n bir"),"IX"," to'qqiz"),"X"," o'n"),"VIII"," sakkiz"),"VII"," yetti"),"VI"," olti"),"IV"," to'rt"),"V"," besh"),"III"," uch"),"II"," ikki"),"I"," bir"),"bir ming","bir ming"),"ikki ming","ikki ming"),"uch ming","uch ming"),"to'rt ming","to'rt ming"),"bir million","bir million"),"ikki million","ikki million"),"uch million","uch million"),"to'rt million","to'rt million"),"bir so'm","bir so'm"),"ikki so'm","ikki so'm"),"uch so'm","uch so'm"),"to'rt so'm","to'rt so'm")),"ming million","million"),"ming million","million"),"ming million","million"),1))&MID(SUBSTITUTE(SUBSTITUTE(SUBSTITUTE(TRIM(SUBSTITUTE(SUBSTITUTE(SUBSTITUTE(SUBSTITUTE(SUBSTITUTE(SUBSTITUTE(SUBSTITUTE(SUBSTITUTE(SUBSTITUTE(SUBSTITUTE(SUBSTITUTE(SUBSTITUTE(SUBSTITUTE(SUBSTITUTE(SUBSTITUTE(SUBSTITUTE(SUBSTITUTE(SUBSTITUTE(SUBSTITUTE(SUBSTITUTE(SUBSTITUTE(SUBSTITUTE(SUBSTITUTE(SUBSTITUTE(SUBSTITUTE(SUBSTITUTE(SUBSTITUTE(SUBSTITUTE(SUBSTITUTE(SUBSTITUTE(SUBSTITUTE(SUBSTITUTE(SUBSTITUTE(SUBSTITUTE(SUBSTITUTE(SUBSTITUTE(SUBSTITUTE(SUBSTITUTE(SUBSTITUTE(SUBSTITUTE(SUBSTITUTE(SUBSTITUTE(SUBSTITUTE(SUBSTITUTE(SUBSTITUTE(SUBSTITUTE(SUBSTITUTE(SUBSTITUTE(IF(LEN(ROUNDDOWN(B75,0))>6,ROMAN(MID(ROUNDDOWN(B75,0),1,LEN(ROUNDDOWN(B75,0))-6)+0)&" million "&ROMAN(MID(ROUNDDOWN(B75,0),LEN(ROUNDDOWN(B75,0))-5,3)+0)&" "&ROMAN(MID(ROUNDDOWN(B75,0),LEN(ROUNDDOWN(B75,0))-2,3)+0)&" so'm",IF(LEN(ROUNDDOWN(B75,0))>3,ROMAN(MID(ROUNDDOWN(B75,0),1,LEN(ROUNDDOWN(B75,0))-3)+0)&" ming "&ROMAN(MID(ROUNDDOWN(B75,0),LEN(ROUNDDOWN(B75,0))-2,3)+0)&" so'm",ROMAN(ROUNDDOWN(B75,0))&" so'm")),"DCCC"," sakkiz yuz"),"DCC"," yetti yuz"),"DC"," olti yuz"),"CD"," to'rt yuz"),"XC"," to'qson"),"CCC"," uch yuz"),"CC"," ikki yuz"),"D"," besh yuz"),"CM"," to'qqiz yuz"),"C"," yuz"),"XL"," qirq"),"LXXX"," sakson"),"LXX"," yetmish"),"LX"," oltmish"),"L"," ellik"),"XXX"," o'ttiz"),"XX"," yigirma"),"XIX"," o'n to'qqiz"),"XVIII"," o'n sakkiz"),"XVII"," o'n yetti"),"XVI"," o'n olti"),"XV"," o'n besh"),"XIV"," o'n to'rt"),"XIII"," o'n uch"),"XII"," o'n ikki"),"XI"," o'n bir"),"IX"," to'qqiz"),"X"," o'n"),"VIII"," sakkiz"),"VII"," yetti"),"VI"," olti"),"IV"," to'rt"),"V"," besh"),"III"," uch"),"II"," ikki"),"I"," bir"),"bir ming","bir ming"),"ikki ming","ikki ming"),"uch ming","uch ming"),"to'rt ming","to'rt ming"),"bir million","bir million"),"ikki million","ikki million"),"uch million","uch million"),"to'rt million","to'rt million"),"bir so'm","bir so'm"),"ikki so'm","ikki so'm"),"uch so'm","uch so'm"),"to'rt so'm","to'rt so'm")),"ming million","million"),"ming million","million"),"ming million","million"),2,200)&"" -> O'ttiz uch million so'm
A77: Grafik turi | B77: differensial | C77: differensial | D77: annuitet
A78: =CONCATENATE(B65,"ni to'lash sanasi (14.10.2011)") -> mikroqarzni to'lash sanasi (14.10.2011) | B78: 15 | C78: =DATE(YEAR(B67),MONTH(B67)+1,DAY(B78)) -> 46068 | D78: Пн | F78: Вт | G78: Ср | H78: Чт | I78: Пт | J78: Сб | K78: Вс
A79: =CONCATENATE(B65,"ni to'lash sanasi (14.10.2011 y.) QO’L BILAN KIRITILADI") -> mikroqarzni to'lash sanasi (14.10.2011 y.) QO’L BILAN KIRITILADI | B79: =DATE(YEAR(B67),MONTH(B67)+1,DAY(B78+C80)) -> 46069 | C79: =TEXT(C78,"ддд") -> Вс | D79: Пн | F79: Вт | G79: Ср | H79: Чт | I79: Пт | J79: Сб | K79: Вс
A80: Mikroqarzni to'lash sanasi (14.10.2011 y.) QO’L BILAN KIRITILADI | B80: =B79 -> 46069 | C80: =IF(C79=J79,2,IF(C79=K79,1,0)) -> 1
A81: =CONCATENATE(B65," muddati") -> mikroqarz muddati | B81: 36 | C81: 6 | D81: 12 | E81: 16 | F81: 18 | G81: 24 | H81: 28 | I81: 30 | J81: 36 | M81: 48
A82: =CONCATENATE(B65," TEGILMASIN") -> mikroqarz TEGILMASIN | B82: =IF(B81=C81,"olti",IF(B81=D81,"o'n ikki",IF(B81=E81,"o'n sakkiz",IF(B81=F81,"o'n sakkiz",IF(B81=G81,"yigirma to'rt",IF(B81=H81,"yigirma sakkiz",IF(B81=I81,"o'ttiz",IF(B81=J81,"o'ttiz olti",IF(B81=M81,"qirq sakkiz",0))))))))) -> o'ttiz olti | C82: o'lti | D82: o'n ikki | E82: o'n olti | F82: o'n sakkiz | G82: yigirma to'rt | H82: yigirma sakkiz | I82: o'ttiz | J82: o'ttiz olti | M82: qirq sakkiz
A83: Imtiyozli davr | B83: 0 | BK83: 1 | BL83: 0
A84: =CONCATENATE(B65," stavkasi") -> mikroqarz stavkasi | B84: 0.55
A85: =CONCATENATE(B65," stavkasi") -> mikroqarz stavkasi | B85: 55
A86: =CONCATENATE(B65," stavkasi (so’z bilan)") -> mikroqarz stavkasi (so’z bilan) | B86: ellik besh | C86: Ellik besh
A87: =CONCATENATE("Muddati o'tgan ",B65," bo’yicha stavka") -> Muddati o'tgan mikroqarz bo’yicha stavka | B87: 1.05
A88: QO’L BILAN KIRITILADI | B88: 105
A89: =CONCATENATE("Muddati o'tgan ",B65," bo’yicha stavka") -> Muddati o'tgan mikroqarz bo’yicha stavka | B89: bir yuz besh | C89: bir yuz besh
A90: Oylik to'lov | B90: =IF(B77=C77,LARGE(grafik!F9:F26,1),ROUND(PMT(B84/12,B81,-B75,0),-3)) -> 2955433.9
A91: GAROV BO’YICHA MA’LUMOTLAR
B92: Birlamchi | C92: Birlamchi | D92: navbatdagi garov
A93: Garovga beruvchi mulkdormi? | B93: yo’q | C93: Ha | D93: yo’q
A94: Agar garovga beruvchi qarz oluvchi bo'lmasa, garovga kim qo'yganligini ko'rsating | B94: Bosh ishonchnoma bo’yicha boshqa shaxs | C94: Garovga beruvchining o’zi | D94: Bosh ishonchnoma bo’yicha boshqa shaxs
A95: Bosh ishonchnoma bo’yicha bo’lsa FIShni ko’rsating | B95: USMONOV NURIDDID IXTIYOROVICH
A96: Bosh ishonchnoma bo’yicha bo’lsa FIShni ko’rsating qisqacha | B96: USMONOV N.I.
A98: Notarius manzili (Toshkent shahri, Olmazor tumani) | B98: BUXORO VILOYATI BUXORO SHAHRI ASHXOBOD KO'CHASI 1/3-UY
A99: Kim tomonidan berilgan (Notariusning FISh – Eshkabilov X.B.) | B99: SHARIPOV ZAFAR JO'RABOYEVICH
A100: Ishonchnoma reestr raqami | B100: 202602386000102
A101: Ishonchnoma berilgan sana | B101: 46028
B102: =TEXT(B101,"ДД.ММ.ГГГГ") -> 06.01.2026
...

Sheet muqova
B2: =umumiy_malumot!B148 -> «PULLOL BUSINESS MIKROMOLIYA TASHKILOTI» MChJ
B12: =umumiy_malumot!B5 -> TURAYEV ISROIL BURIYEVICH
B19: =""&umumiy_malumot!C64&" shartnoma "&umumiy_malumot!B74&"" -> Mikroqarz shartnoma 6 yanvar 2026 y.dan №3-BR
B24: =" Foiz stavkasi: "&umumiy_malumot!B85&"%" -> Foiz stavkasi: 55%
B25: =" "&umumiy_malumot!C64&" muddati: "&umumiy_malumot!B81&" oy" -> Mikroqarz muddati: 36 oy
B26: =" "&umumiy_malumot!C64&" miqdori: "&FIXED(umumiy_malumot!B75,2)&" so'm" -> Mikroqarz miqdori: 33 000 000,00 so'm
B40: ="Toshkent sh., "&umumiy_malumot!B70&"" -> Toshkent sh., 6 yanvar 2026 y.

Sheet anketa
A2: ANKETA
E3: =umumiy_malumot!B68 -> 6 yanvar 2026 y.
A5: Mijozning to'liq ismi sharifi | C5: =umumiy_malumot!B8 -> TURAYEV ISROIL BURIYEVICH
A7: Siz ommaviy mansabdor shaxsmisiz? | D7: Ha
D8: Yo'q
A9: Yaqin qarindoshlaringiz orasida ommaviy mansabdor shaxslar bormi? | D9: Ha
D10: Yo'q
A11: Do'stlaringiz yoki yaqinlaringizdan birontasi ommaviy mansabdor shaxsmi? | D11: Ha
D12: Yo'q
A13: Yuqoridagi savollardan biriga «Ha» deb javob bergan bo'lsangiz, javobingizni qisqacha tushuntirib bering:
A18: Siz bank amaliyotlarini amalga oshirishda uchinchi shaxsning manfaatlarini ifodalaysizmi? | D18: Ha
D19: Yo'q
A20: Agar oldingi savolga «HA» deb javob bergan bo'lsangiz, bank operatsiyalarini bajarich uchun ishonchnomangiz bormi? | D20: Ha
D21: Yo'q
A23: Agar oldingi savolga «YO'Q» deb javob bergan bo'lsangiz, javobingizni qisqacha tushuntirib bering:
A28: Ommaviy mansabdor shaxslar — doimiy, vaqtincha yoki maxsus vakolatli organ tomonidan tayinlangan yoki saylangan, tashkiliy-maʼmuriy funktsiyalarni bajaruvchi hamda xorijiy davlatning qonun chiqaruvchi, ijro etuvchi, maʼmuriy yoki sud organida yoxud xalqaro tashkilotda yuridik ahamiyatga molik harakatlarni amalga oshirishga vakolatli shaxslar, shuningdek xorijiy davlatlar korxonalarining yuqori martabali rahbarlari, taniqli siyosatchilar va xorijiy davlatlar siyosiy partiyalarining taniqli a'zolari.
A30: Anketadagi barcha ma'lumotlar to'g'ri, agar o'zgarishlar bo'lsa, men bu haqida xabardor qilish majburiyatini o'z zimmamga olaman.
A33: =C5 -> TURAYEV ISROIL BURIYEVICH

Sheet mijoz_anketasi
A1: MIJOZNING ANKETASI
A2: Anketa kredit menejeri tomonidan mijozning javoblarini kiritish orqali to'ldiriladi, kerak bo'lganda, Mijoz tomonidan tanlangan javob variantlarini belgilash orqali amalga oshiriladi
A3: 1. MIJOZ HAQIDA MA'LUMOTLAR:
A4: =xulosa!A4:E4 -> Mijozning to'liq ismi sharifi: TURAYEV ISROIL BURIYEVICH
A5: =xulosa!A5:E5 -> Tug'ilgan sanasi: 14.11.1983 yil
A6: =xulosa!A6:E6 -> Pasport seriyasi AD 6760672 IIV 61013 tomonidan 08.04.2024 yilda berilgan, amal qilish muddati - 07.04.2034 y.
A7: ="Fuqaroligi: "&umumiy_malumot!B32&"" -> Fuqaroligi: O’zbekiston Respublikasi
A8: =xulosa!A7:E7 -> Ro‘yxatdan o‘tgan manzili: BUXORO VILOYATI KOGON SHAHRI ZAFAROBOD 17-UY, mo'ljal: BGGK ZONA
A9: =IF(umumiy_malumot!B23="mos keladi"," ",mijoz_anketasi!A10:F10)
A10: ="Haqiqatdan yashash joy manzili: "&umumiy_malumot!B28&"" -> Haqiqatdan yashash joy manzili: BUXORO VILOYATI KOGON SHAHRI ZAFAROBOD 17-UY
A11: =xulosa!A8:E8 -> Ish joyi: lavozimi Yakka tartibdagi tadbirkorda Yakka tartibdagi tadbirkor
A12: 2. Mijoz bilan ulanich uchun aloqa ma'lumotlari:
A13: ="Uy telefoni raqami: "&umumiy_malumot!B40&"" -> Uy telefoni raqami: 91 923 50 54 MIJOZ
A14: ="Uyali telefon raqami: "&umumiy_malumot!B41&"" -> Uyali telefon raqami: 50 377 80 88 OTASI TO'LOVCHI
A15: ="Uyali telefon raqami: "&umumiy_malumot!B42&"" -> Uyali telefon raqami: 93 000 16 05 O'G'LI
A16: ="Uyali telefon raqami: "&umumiy_malumot!B42&"" -> Uyali telefon raqami: 93 000 16 05 O'G'LI
A17: ="Ish telefoni raqami: "&umumiy_malumot!B43&"" -> Ish telefoni raqami:
A18: 3. MIJOZNING ISH JOYI HAQIDA MA'LUMOT:
A19: ="Muassasa nomlanishi:"&umumiy_malumot!B58&"" -> Muassasa nomlanishi:Yakka tartibdagi tadbirkor
A20: ="Ro‘yxatdan o‘tish manzili:"&umumiy_malumot!B50&"" -> Ro‘yxatdan o‘tish manzili:
A21: ="Lavozimi: "&umumiy_malumot!B59&"" -> Lavozimi: Yakka tartibdagi tadbirkor
A22: 4. MIJOZNING OYLIK DAROMADLARI VA XARAJATLARI HAQIDA MA'LUMOT
A23: Daromad manbalari | B23: Mijoz | C23: Turmush o'rtog'i | D23: Boshqa oila a'zolari | E23: Xarajatlar | F23: Мiqdori
A24: ish haqi (asosiy ish) | B24: =umumiy_malumot!B60 -> 5000000 | C24: 0 | D24: 0 | E24: uy-joy va kommunal xizmatlar uchun to'lov | F24: 700000
A25: ish haqi (o‘rindoshlik) | B25: 0 | C25: 0 | D25: 0 | E25: oilaviy xarajatlar | F25: 500000
A26: boshqa daromadlar | B26: =umumiy_malumot!B61 -> 5000000 | C26: 0 | D26: 0 | E26: boshqa xarajatlar | F26: 500000
A27: JAMI | B27: =B24+B25+B26 -> 10000000 | C27: =SUM(C24:C26) -> 0 | D27: =SUM(D24:D26) -> 0 | F27: =SUM(F24:F26) -> 1700000
A28: ="Men, "&umumiy_malumot!B5&", ushbu anketada ko‘rsatilgan barcha ma'lumotlar anketa to'ldirilgan sanada to'g'ri va aniq ekanligini tasdiqlayman." -> Men, TURAYEV ISROIL BURIYEVICH, ushbu anketada ko‘rsatilgan barcha ma'lumotlar anketa to'ldirilgan sanada to'g'ri va aniq ekanligini tasdiqlayman.
A29: ="Men, "&umumiy_malumot!B5&", quyidagilarni tan olaman va roziman::" -> Men, TURAYEV ISROIL BURIYEVICH, quyidagilarni tan olaman va roziman::
A30: ="1. Ushbu anketada ko‘rsatilgan har qanday ma’lumot "&umumiy_malumot!B147&", uning xodimlari va huquqiy vorislari tomonidan istalgan manbaa va ma’lumotlardan foydalangan holda istalgan vaqtda tekshirilishi va qayta tekshirilishi mumkin." -> 1. Ushbu anketada ko‘rsatilgan har qanday ma’lumot «PULLOL BUSINESS MIKROMOLIYA TASHKILOTI» MChJ, uning xodimlari va huquqiy vorislari tomonidan istalgan manbaa va ma’lumotlardan foydalangan holda istalgan vaqtda tekshirilishi va qayta tekshirilishi mumkin.
A31: ="2. Mazkur anketaning "&umumiy_malumot!B147&" tomonidan qabul qilinishi «PULLOL BUSINESS MIKROMOLIYA TASHKILOTI» MChJ tomonidan menga "&umumiy_malumot!B65&" berish majburiyatini yuklamaydi." -> 2. Mazkur anketaning «PULLOL BUSINESS MIKROMOLIYA TASHKILOTI» MChJ tomonidan qabul qilinishi «PULLOL BUSINESS MIKROMOLIYA TASHKILOTI» MChJ tomonidan menga mikroqarz berish majburiyatini yuklamaydi.
A32: Men, _________________________________________________________________ (to'liq ismi sharifi), ushbu anketadagi barcha ma'lumotlar anketa to'ldirilgan sanada to'g'ri ekanligini tasdiqlayman va ushbu anketaning 1- va 2-bandlarini tan olaman va ularga rozilik bildiraman. Mazkur anketaning 4-bo'limida ko'rsatilgan daromadlarim haqidagi ma'lumotlarni qabul qilishingizni va moliyaviy tahlilda foydalanishingizni so’rayman.
A34: Mijozning to'liq ismi sharifi | D34: Sana | E34: Imzo
D35: =umumiy_malumot!B2 -> 06.01.2026

Sheet kredit_ariza
C1: =""&umumiy_malumot!B147&"ning "&umumiy_malumot!A150&"" -> «PULLOL BUSINESS MIKROMOLIYA TASHKILOTI» MChJning Buxoro filiali boshlig'i
D2: =""&umumiy_malumot!B150&"ga" -> IKROMOV B.A.ga
A4: =""&umumiy_malumot!C64&" olish uchun Ariza" -> Mikroqarz olish uchun Ariza
A6: =""&umumiy_malumot!B28&".-da yashovchi O‘zbekiston Respublikasi fuqarosi "&umumiy_malumot!B8&"dan. " -> BUXORO VILOYATI KOGON SHAHRI ZAFAROBOD 17-UY.-da yashovchi O‘zbekiston Respublikasi fuqarosi TURAYEV ISROIL BURIYEVICHdan.
A7: ="Tug'ilgan kuni: "&umumiy_malumot!B15&"" -> Tug'ilgan kuni: 14.11.1983 yil
A8: ="Pasport seriyasi: "&umumiy_malumot!B16&" "&umumiy_malumot!B20&"" -> Pasport seriyasi: AD 6760672 IIV 61013 tomonidan 08.04.2024 yilda berilgan
A9: ="Asosiy ish joyi : "&umumiy_malumot!B58&"" -> Asosiy ish joyi : Yakka tartibdagi tadbirkor
A10: ="Lavozimi: "&umumiy_malumot!B59&"" -> Lavozimi: Yakka tartibdagi tadbirkor
A11: ="O’rtacha oylik daromadi: "&FIXED(mijoz_anketasi!B27,2)&" so'm." -> O’rtacha oylik daromadi: 10 000 000,00 so'm.
A12: ="Menga quyidagi shartlarda "&umumiy_malumot!B65&" berishingizni so’rayman:" -> Menga quyidagi shartlarda mikroqarz berishingizni so’rayman:
A13: =""&umumiy_malumot!C64&" summasi: "&FIXED(umumiy_malumot!B75,2)&" ("&umumiy_malumot!B76&") so'm." -> Mikroqarz summasi: 33 000 000,00 (o'ttiz uch million so'm) so'm.
A14: =""&umumiy_malumot!C64&" muddati: "&umumiy_malumot!B81&" ("&umumiy_malumot!B82&") oy." -> Mikroqarz muddati: 36 (o'ttiz olti) oy.
A15: =""&umumiy_malumot!C64&"dan foydalanganlik uchun foiz stavkasi: yillik "&umumiy_malumot!B85&"% ("&umumiy_malumot!B86&") foiz" -> Mikroqarzdan foydalanganlik uchun foiz stavkasi: yillik 55% (ellik besh) foiz
A16: =""&umumiy_malumot!C64&" bo'yicha asosiy qarz va foizlarni to'lash:" -> Mikroqarz bo'yicha asosiy qarz va foizlarni to'lash:
A17: =" - "&umumiy_malumot!B65&" shartnomasi bo'yicha har oy differensial to'lovlari amalga oshiriladi" -> - mikroqarz shartnomasi bo'yicha har oy differensial to'lovlari amalga oshiriladi
A18: =" - "&umumiy_malumot!B65&" shartnomasi bo'yicha har oy annuitet to'lovlari amalga oshiriladi" -> - mikroqarz shartnomasi bo'yicha har oy annuitet to'lovlari amalga oshiriladi
A19: =IF(umumiy_malumot!B77=umumiy_malumot!C77,kredit_ariza!A17:D17,IF(umumiy_malumot!B77=umumiy_malumot!D77,kredit_ariza!A18:D18)) -> - mikroqarz shartnomasi bo'yicha har oy differensial to'lovlari amalga oshiriladi
A20: =IF(DAY(umumiy_malumot!F67)<15," "," Oxirgi yakuniy to'lov "&umumiy_malumot!B65&" shartnomasi tuzilgan kundan boshlab oxirgi oyning oxirgi kunida amalga oshiriladi")
A21: =""&umumiy_malumot!C64&" ta’minoti::" -> Mikroqarz ta’minoti::
A22: =IF(umumiy_malumot!B103="Avtotransport",A26,A23) -> Egalik huquqi USMONOV NURIDDID IXTIYOROVICHga tegishli bo'lgan garovga olingan avtomobil markasi COBALT, rangi - OQ OLIMPIYSKAYA BELAYA, ishlab chiqarilgan yili - 2016, davlat raqam belgisi 80G291QA, kuzov turi - YENGIL SEDAN, kuzov raqami XWBJF69VEGA010429, dvigatel raqami B15D211163412DJCX0337, shassi raqami - RAKAMSIZ
A23: =IF(umumiy_malumot!B92=umumiy_malumot!C92,A25,IF(umumiy_malumot!B92=umumiy_malumot!D92,A24,0)) -> Egalik huquqi 0ga tegishli bo'lgan umumiy maydoni - 72,13 va yashash maydoni - 37,39 3 - xonali yakka tartibdagi uy-joy, SAMARQAND VILOYATI TAYLOQ TUMANI CHAROG'BON MFY YANGI TAYLOQ QISHLOG'I 6 TURAR JOY 12 QAVAT 58 XONADON
A24: =" - Navbatdagi garov (ipoteka) Egalik huquqi asosida "&umumiy_malumot!C117&"ga "&umumiy_malumot!C126&", umumiy maydoni - "&umumiy_malumot!C130&" va yashash maydoni - "&umumiy_malumot!C133&", manzili: "&umumiy_malumot!C123&"." -> - Navbatdagi garov (ipoteka) Egalik huquqi asosida 0ga 3 - xonali yakka tartibdagi uy-joy, umumiy maydoni - 72,13 va yashash maydoni - 37,39, manzili: SAMARQAND VILOYATI TAYLOQ TUMANI CHAROG'BON MFY YANGI TAYLOQ QISHLOG'I 6 TURAR JOY 12 QAVAT 58 XONADON.
A25: =" Egalik huquqi "&umumiy_malumot!C117&"ga tegishli bo'lgan umumiy maydoni - "&umumiy_malumot!C130&" va yashash maydoni - "&umumiy_malumot!C133&" "&umumiy_malumot!C126&", "&umumiy_malumot!C123&" " -> Egalik huquqi 0ga tegishli bo'lgan umumiy maydoni - 72,13 va yashash maydoni - 37,39 3 - xonali yakka tartibdagi uy-joy, SAMARQAND VILOYATI TAYLOQ TUMANI CHAROG'BON MFY YANGI TAYLOQ QISHLOG'I 6 TURAR JOY 12 QAVAT 58 XONADON
A26: =IF(umumiy_malumot!B92=umumiy_malumot!C92,kredit_ariza!A28:D28,IF(umumiy_malumot!B92=umumiy_malumot!D92,kredit_ariza!A27:D27,0)) -> Egalik huquqi USMONOV NURIDDID IXTIYOROVICHga tegishli bo'lgan garovga olingan avtomobil markasi COBALT, rangi - OQ OLIMPIYSKAYA BELAYA, ishlab chiqarilgan yili - 2016, davlat raqam belgisi 80G291QA, kuzov turi - YENGIL SEDAN, kuzov raqami XWBJF69VEGA010429, dvigatel raqami B15D211163412DJCX0337, shassi raqami - RAKAMSIZ
A27: =" Egalik huquqi "&umumiy_malumot!B117&"ga tegishli bo'lgan "&umumiy_malumot!B125&", "&umumiy_malumot!B133&", davlat raqam belgisi "&umumiy_malumot!B126&", "&umumiy_malumot!B127&", "&umumiy_malumot!B130&" avtotransport vositasi " -> Egalik huquqi USMONOV NURIDDID IXTIYOROVICHga tegishli bo'lgan COBALT, rangi - OQ OLIMPIYSKAYA BELAYA, ishlab chiqarilgan yili - 2016, davlat raqam belgisi 80G291QA, kuzov turi - YENGIL SEDAN, kuzov raqami XWBJF69VEGA010429, dvigatel raqami B15D211163412DJCX0337, shassi raqami - RAKAMSIZ avtotransport vositasi
A28: =" Egalik huquqi "&umumiy_malumot!B117&"ga tegishli bo'lgan garovga olingan avtomobil markasi "&umumiy_malumot!B125&", "&umumiy_malumot!B133&", davlat raqam belgisi "&umumiy_malumot!B126&", "&umumiy_malumot!B127&", "&umumiy_malumot!B130&"" -> Egalik huquqi USMONOV NURIDDID IXTIYOROVICHga tegishli bo'lgan garovga olingan avtomobil markasi COBALT, rangi - OQ OLIMPIYSKAYA BELAYA, ishlab chiqarilgan yili - 2016, davlat raqam belgisi 80G291QA, kuzov turi - YENGIL SEDAN, kuzov raqami XWBJF69VEGA010429, dvigatel raqami B15D211163412DJCX0337, shassi raqami - RAKAMSIZ
A30: ="Mazkur ariza bilan "&umumiy_malumot!B147&"ga men va soʻralayotgan "&umumiy_malumot!B65&" boʻyicha barcha zarur maʼlumotlarni quyida ko’rsatilgan tashkilotlarga taqdim etish va olishga roziligimni bildirib, ushbu amaliyotlarni o’tkazish uchun huquq beraman:" -> Mazkur ariza bilan «PULLOL BUSINESS MIKROMOLIYA TASHKILOTI» MChJga men va soʻralayotgan mikroqarz boʻyicha barcha zarur maʼlumotlarni quyida ko’rsatilgan tashkilotlarga taqdim etish va olishga roziligimni bildirib, ushbu amaliyotlarni o’tkazish uchun huquq beraman:
A31: □ O‘zbekiston Respublikasi Markaziy banki huzuridagi kredit axborotining davlat reestri;
A32: □ Kredit-axborot tahliliy markazi «O‘zbekiston Respublikasi kredit byurosi» MChJ;
A33: □ Garov reestri taqdim etilgan garov mulki haqida.
A34: ="Ariza berilgan sana: "&TEXT(umumiy_malumot!B2,"ДД.ММ.ГГГГ")&"y." -> Ariza berilgan sana: 06.01.2026y.
A36: Ariza berilgan kuniga barcha ma'lumotlar ishonchligini tasdiqlab, ushbu arizani imzolayman
A39: =umumiy_malumot!B5 -> TURAYEV ISROIL BURIYEVICH | D39: P________________
D40: (imzo)

Sheet majburiyatnoma
A3: MAJBURIYATNOMA
A4: =" Men, fuqaro "&umumiy_malumot!B5&" "&umumiy_malumot!B149&" bilan "&umumiy_malumot!B69&" sanasidagi "&umumiy_malumot!B66&"-sonli shartnomaning garov ta'minoti sifatida taqdim etilayotgan mulk "&umumiy_malumot!B125&" rusumli avtotransport vositasini qonunga xilof ravishda o‘zlashtirmaslikka, yashirmaslikka, nobud qilmaslikka yoki unga shikast yetkazmaslik majburiyatini olaman." -> Men, fuqaro TURAYEV ISROIL BURIYEVICH «PULLOL BUSINESS MIKROMOLIYA TASHKILOTI» MChJ bilan 6 yanvar 2026 y. sanasidagi №3-BR-sonli shartnomaning garov ta'minoti sifatida taqdim etilayotgan mulk COBALT rusumli avtotransport vositasini qonunga xilof ravishda o‘zlashtirmaslikka, yashirmaslikka, nobud qilmaslikka yoki unga shikast yetkazmaslik majburiyatini olaman.
A5: Ushbu majburiyatlarimni bajarmagan taqdirimda O'zbekiston Respublikasi jinoyat kodeksining 233-moddasi talablari asosida javobgarlik tog'risida ogohlantrildim.
A7: =umumiy_malumot!B5 -> TURAYEV ISROIL BURIYEVICH | B7: Imzo_____________
A9: =umumiy_malumot!B105 -> USMONOV NURIDDID IXTIYOROVICH | B9: Imzo_____________
A11: ="sana: "&TEXT(umumiy_malumot!B2,"ДД.ММ.ГГГГ")&" y." -> sana: 06.01.2026 y.

Sheet garov_ariza
B6: =umumiy_malumot!B148 -> «PULLOL BUSINESS MIKROMOLIYA TASHKILOTI» MChJ
B7: =""&umumiy_malumot!A150&" "&umumiy_malumot!B150&"ga" -> Buxoro filiali boshlig'i IKROMOV B.A.ga
B8: =""&umumiy_malumot!B111&"dan" -> USMONOV NURIDDID IXTIYOROVICHdan
B9: =umumiy_malumot!B111 -> USMONOV NURIDDID IXTIYOROVICH
B10: =umumiy_malumot!C111 -> 0
B11: dan
A13: =IF(umumiy_malumot!B103="Avtotransport",A14,A15) -> TURAYEV ISROIL BURIYEVICH tomonidan so’ralayotgan 36 (o'ttiz olti) oy muddatga, 33 000 000 (o'ttiz uch million so'm) miqdoridagi mikroqarzning ta’minoti sifatida menga mulk huquqi asosida tegishli bo’lgan COBALT, kuzov turi - YENGIL SEDAN, kuzov raqami XWBJF69VEGA010429, dvigatel raqami B15D211163412DJCX0337, shassi raqami - RAKAMSIZ, rangi - OQ OLIMPIYSKAYA BELAYA, ishlab chiqarilgan yili - 2016, avtotransport vositasini qabul qilishingizni so’rayman:
A14: =""&umumiy_malumot!B12&" tomonidan so’ralayotgan "&umumiy_malumot!B81&" ("&umumiy_malumot!B82&") oy muddatga, "&FIXED(umumiy_malumot!B75,0)&" ("&umumiy_malumot!B76&") miqdoridagi "&umumiy_malumot!B65&"ning ta’minoti sifatida menga mulk huquqi asosida tegishli bo’lgan "&umumiy_malumot!B125&", "&umumiy_malumot!B127&", "&umumiy_malumot!B130&", "&umumiy_malumot!B133&", avtotransport vositasini qabul qilishingizni so’rayman:" -> TURAYEV ISROIL BURIYEVICH tomonidan so’ralayotgan 36 (o'ttiz olti) oy muddatga, 33 000 000 (o'ttiz uch million so'm) miqdoridagi mikroqarzning ta’minoti sifatida menga mulk huquqi asosida tegishli bo’lgan COBALT, kuzov turi - YENGIL SEDAN, kuzov raqami XWBJF69VEGA010429, dvigatel raqami B15D211163412DJCX0337, shassi raqami - RAKAMSIZ, rangi - OQ OLIMPIYSKAYA BELAYA, ishlab chiqarilgan yili - 2016, avtotransport vositasini qabul qilishingizni so’rayman:
A15: =""&umumiy_malumot!B12&" tomonidan so’ralayotgan "&umumiy_malumot!B81&" ("&umumiy_malumot!B82&") oy muddatga, "&FIXED(umumiy_malumot!B75,0)&" ("&umumiy_malumot!B76&") miqdoridagi "&umumiy_malumot!B65&"ning ta’minoti sifatida menga mulk huquqi asosida tegishli bo’lgan "&umumiy_malumot!C126&", umumiy maydoni "&umumiy_malumot!C130&" va yashash maydoni "&umumiy_malumot!C133&" "&umumiy_malumot!C123&" manzilda joylashgan ko'chmas mulkni qabul qilishingizni so’rayman:" -> TURAYEV ISROIL BURIYEVICH tomonidan so’ralayotgan 36 (o'ttiz olti) oy muddatga, 33 000 000 (o'ttiz uch million so'm) miqdoridagi mikroqarzning ta’minoti sifatida menga mulk huquqi asosida tegishli bo’lgan 3 - xonali yakka tartibdagi uy-joy, umumiy maydoni 72,13 va yashash maydoni 37,39 SAMARQAND VILOYATI TAYLOQ TUMANI CHAROG'BON MFY YANGI TAYLOQ QISHLOG'I 6 TURAR JOY 12 QAVAT 58 XONADON manzilda joylashgan ko'chmas mulkni qabul qilishingizni so’rayman:
B18: Sana:
A19: =IF(umumiy_malumot!B94=umumiy_malumot!C94,umumiy_malumot!B112,umumiy_malumot!B7) -> TURAYEV I.B. | B19: =umumiy_malumot!B2 -> 06.01.2026
A20: =IF(umumiy_malumot!B94=umumiy_malumot!D94,CONCATENATE(A23," ",A28,A22),"") -> №202602386000102 06.01.2026 sanasidan xususiy faoliyat ko'rsatuvchi notarius tomonidan BUXORO VILOYATI BUXORO SHAHRI ASHXOBOD KO'CHASI 1/3-UY SHARIPOV ZAFAR JO'RABOYEVICH berilgan ishonchnomaga asosan
A22: =" xususiy faoliyat ko'rsatuvchi notarius tomonidan "&umumiy_malumot!B98&" "&umumiy_malumot!B99&" berilgan ishonchnomaga asosan " -> xususiy faoliyat ko'rsatuvchi notarius tomonidan BUXORO VILOYATI BUXORO SHAHRI ASHXOBOD KO'CHASI 1/3-UY SHARIPOV ZAFAR JO'RABOYEVICH berilgan ishonchnomaga asosan
A23: ="№"&umumiy_malumot!B100& "" -> №202602386000102
A25: =umumiy_malumot!B102 -> 06.01.2026
A26: =TEXT(A25,"ДД.ММ.ГГГГ") -> 06.01.2026
A27: sanasidan
A28: =CONCATENATE(A26,A27) -> 06.01.2026 sanasidan

Sheet xulosa
A1: =""&umumiy_malumot!B147&" mikromoliya tashkilotining Xulosasi" -> «PULLOL BUSINESS MIKROMOLIYA TASHKILOTI» MChJ mikromoliya tashkilotining Xulosasi
A3: MIJOZ HAQIDA MA'LUMOTLAR
A4: ="Mijozning to'liq ismi sharifi: "&umumiy_malumot!B5&"" -> Mijozning to'liq ismi sharifi: TURAYEV ISROIL BURIYEVICH
A5: ="Tug'ilgan sanasi: "&umumiy_malumot!B15&"" -> Tug'ilgan sanasi: 14.11.1983 yil
A6: ="Pasport seriyasi "&umumiy_malumot!B16&" "&umumiy_malumot!B20&", amal qilish muddati - "&umumiy_malumot!B21&"" -> Pasport seriyasi AD 6760672 IIV 61013 tomonidan 08.04.2024 yilda berilgan, amal qilish muddati - 07.04.2034 y.
A7: ="Ro‘yxatdan o‘tgan manzili: "&umumiy_malumot!B28&", mo'ljal: "&umumiy_malumot!B26&"" -> Ro‘yxatdan o‘tgan manzili: BUXORO VILOYATI KOGON SHAHRI ZAFAROBOD 17-UY, mo'ljal: BGGK ZONA
A8: ="Ish joyi: "&umumiy_malumot!B52&" lavozimi "&umumiy_malumot!B49&"da "&umumiy_malumot!B44&"" -> Ish joyi: lavozimi Yakka tartibdagi tadbirkorda Yakka tartibdagi tadbirkor
A10: ="Mijoz tomonidan so’ralgan "&umumiy_malumot!B65&" shartlari:" -> Mijoz tomonidan so’ralgan mikroqarz shartlari:
A11: =kredit_ariza!A13:D13 -> Mikroqarz summasi: 33 000 000,00 (o'ttiz uch million so'm) so'm.
A12: =kredit_ariza!A14:D14 -> Mikroqarz muddati: 36 (o'ttiz olti) oy.
A13: =kredit_ariza!A15:D15 -> Mikroqarzdan foydalanganlik uchun foiz stavkasi: yillik 55% (ellik besh) foiz
A14: =kredit_ariza!A16:D16 -> Mikroqarz bo'yicha asosiy qarz va foizlarni to'lash:
A15: =kredit_ariza!A19:D19 -> - mikroqarz shartnomasi bo'yicha har oy differensial to'lovlari amalga oshiriladi
A16: =kredit_ariza!A20:D20
A17: =kredit_ariza!A21:D21 -> Mikroqarz ta’minoti::
A18: =kredit_ariza!A22:D22 -> Egalik huquqi USMONOV NURIDDID IXTIYOROVICHga tegishli bo'lgan garovga olingan avtomobil markasi COBALT, rangi - OQ OLIMPIYSKAYA BELAYA, ishlab chiqarilgan yili - 2016, davlat raqam belgisi 80G291QA, kuzov turi - YENGIL SEDAN, kuzov raqami XWBJF69VEGA010429, dvigatel raqami B15D211163412DJCX0337, shassi raqami - RAKAMSIZ
A19: Mijozning moliyaviy holati
A20: ="Anketaga muvofiq "&umumiy_malumot!B9&"ning o‘rtacha oylik daromadi "&FIXED(mijoz_anketasi!B27)&" so‘mni tashkil etdi." -> Anketaga muvofiq TURAYEV I.B.ning o‘rtacha oylik daromadi 10 000 000,00 so‘mni tashkil etdi.
A21: ="Mijozning o'rtacha oylik xarajatlari "&FIXED(mijoz_anketasi!F27)&" so'mni tashkil etdi" -> Mijozning o'rtacha oylik xarajatlari 1 700 000,00 so'mni tashkil etdi
A22: =IF(umumiy_malumot!B77=umumiy_malumot!C77,xulosa!A23:E23,xulosa!A24:E24) -> Mikroqarz shartnomasi bo'yicha birinchi oy uchun to'lov 2 955 433,90 so'mni tashkil etadi.
A23: =""&umumiy_malumot!C64&" shartnomasi bo'yicha birinchi oy uchun to'lov "&FIXED(umumiy_malumot!B90)&" so'mni tashkil etadi." -> Mikroqarz shartnomasi bo'yicha birinchi oy uchun to'lov 2 955 433,90 so'mni tashkil etadi.
A24: =""&umumiy_malumot!C64&" bo‘yicha oylik "&umumiy_malumot!B77&" to‘lovi miqdori "&FIXED(umumiy_malumot!B90)&" so‘mni tashkil etadi." -> Mikroqarz bo‘yicha oylik differensial to‘lovi miqdori 2 955 433,90 so‘mni tashkil etadi.
A25: Mijoz quyidagi majburiyatlarga ega: "TOShKENT Sh., АT XАLQ BАNKI BOSh АMАLIYOTLАR BOShQАRMАSI 9 320 690.00 so'm, DENGI VPERED" MCHJ QO'SHMA KORXONA MIKROMOLIYA TASHKILOTI 710 640.00., Ayni paytda muddati o'tgan qarzdorligi mavjud emas. O‘rtacha oylik to‘lov 2 005 011.07 so‘mni tashkil qiladi.
A26: =""&umumiy_malumot!C64&" bo’yicha ta’minot:" -> Mikroqarz bo’yicha ta’minot:
A27: =" - "&umumiy_malumot!B117&" ga mulk huquqi asosida tegishli avtotransport vositasi "&umumiy_malumot!B125&" , quyidagi tafsilotlarga muvofiq:" -> - USMONOV NURIDDID IXTIYOROVICH ga mulk huquqi asosida tegishli avtotransport vositasi COBALT , quyidagi tafsilotlarga muvofiq:
A28: =" - "&umumiy_malumot!C117&" ga mulk huquqi asosida tegishli ko'chmas mulk shaklida "&umumiy_malumot!C126&", manzili: "&umumiy_malumot!C123&", quyidagi tafsilotlarga muvofiq:" -> - 0 ga mulk huquqi asosida tegishli ko'chmas mulk shaklida 3 - xonali yakka tartibdagi uy-joy, manzili: SAMARQAND VILOYATI TAYLOQ TUMANI CHAROG'BON MFY YANGI TAYLOQ QISHLOG'I 6 TURAR JOY 12 QAVAT 58 XONADON, quyidagi tafsilotlarga muvofiq:
A29: =IF(umumiy_malumot!B103="Avtotransport",xulosa!A27:E27,xulosa!A28:E28) -> - USMONOV NURIDDID IXTIYOROVICH ga mulk huquqi asosida tegishli avtotransport vositasi COBALT , quyidagi tafsilotlarga muvofiq:
A30: =dalolatnoma!A29 -> Nomi | B30: =dalolatnoma!B29 -> Kuzov turi va kuzov raqami* | C30: =dalolatnoma!C29 -> Dvigatel va shassi raqami* | D30: =dalolatnoma!D29 -> Ishlab chiqarilgan yili va rangi* | E30: =dalolatnoma!E29 -> Kelishilgan garov qiymati, so'm
A31: =dalolatnoma!A30 -> COBALT | B31: =dalolatnoma!B30 -> kuzov turi - YENGIL SEDAN, kuzov raqami XWBJF69VEGA010429 | C31: =dalolatnoma!C30 -> dvigatel raqami B15D211163412DJCX0337, shassi raqami - RAKAMSIZ | D31: =dalolatnoma!D30 -> rangi - OQ OLIMPIYSKAYA BELAYA, ishlab chiqarilgan yili - 2016 | E31: =dalolatnoma!E30 -> 46 200 000,00 (qirq olti million ikki yuz ming so'm)
A32: =dalolatnoma!A22 -> -* avtotransport egasi: USMONOV NURIDDID IXTIYOROVICH
A33: =dalolatnoma!A23 -> -* texnik pasport: AAF 2401056 01.12.2020 y.
A34: =dalolatnoma!A24 -> -* roʻyxatdan oʻtgan manzili/garaj manzili: BUXORO VILOYATI BUXORO SHAHRI CHO'LPON KO'CHASI 22-A-UY
A35: =dalolatnoma!A25 -> -* davlat raqami: 80G291QA
A37: =""&umumiy_malumot!B147&" mikromoliya tashkilotining Xulosasi" -> «PULLOL BUSINESS MIKROMOLIYA TASHKILOTI» MChJ mikromoliya tashkilotining Xulosasi
A38: =""&umumiy_malumot!B147&" kredit qo‘mitasining xulosasiga quyidagi shartlarda "&umumiy_malumot!B10&"ga "&umumiy_malumot!B65&" berish masalasi kiritiladi:" -> «PULLOL BUSINESS MIKROMOLIYA TASHKILOTI» MChJ kredit qo‘mitasining xulosasiga quyidagi shartlarda TURAYEV ISROIL BURIYEVICHga mikroqarz berish masalasi kiritiladi:
A39: =A11 -> Mikroqarz summasi: 33 000 000,00 (o'ttiz uch million so'm) so'm.
A40: =A12 -> Mikroqarz muddati: 36 (o'ttiz olti) oy.
A41: =A13 -> Mikroqarzdan foydalanganlik uchun foiz stavkasi: yillik 55% (ellik besh) foiz
A42: =A14 -> Mikroqarz bo'yicha asosiy qarz va foizlarni to'lash:
A43: =A15 -> - mikroqarz shartnomasi bo'yicha har oy differensial to'lovlari amalga oshiriladi
A44: =A16
A45: =A17 -> Mikroqarz ta’minoti::
A46: =A18 -> Egalik huquqi USMONOV NURIDDID IXTIYOROVICHga tegishli bo'lgan garovga olingan avtomobil markasi COBALT, rangi - OQ OLIMPIYSKAYA BELAYA, ishlab chiqarilgan yili - 2016, davlat raqam belgisi 80G291QA, kuzov turi - YENGIL SEDAN, kuzov raqami XWBJF69VEGA010429, dvigatel raqami B15D211163412DJCX0337, shassi raqami - RAKAMSIZ
A48: =""&umumiy_malumot!B147&" mikromoliya tashkilotining xulosasi "&TEXT(umumiy_malumot!B2,"ДД.ММ.ГГГГ")&" y. tayyorlangan" -> «PULLOL BUSINESS MIKROMOLIYA TASHKILOTI» MChJ mikromoliya tashkilotining xulosasi 06.01.2026 y. tayyorlangan
A51: =umumiy_malumot!A161 -> Buxoro filiali boshlig’i | E51: =umumiy_malumot!B161 -> IKROMOV B.A.
A53: =""&umumiy_malumot!B147&" mikromoliya tashkilotining Kredit qo‘mitasi a’zolari "&umumiy_malumot!B147&" mikromoliya tashkilotining xulosasi va Mijoz tomonidan taqdim etilgan ma’lumotlar bilan tanishdilar:" -> «PULLOL BUSINESS MIKROMOLIYA TASHKILOTI» MChJ mikromoliya tashkilotining Kredit qo‘mitasi a’zolari «PULLOL BUSINESS MIKROMOLIYA TASHKILOTI» MChJ mikromoliya tashkilotining xulosasi va Mijoz tomonidan taqdim etilgan ma’lumotlar bilan tanishdilar:
A55: Obidov A. Sh.
A57: =umumiy_malumot!B159 -> Akramov R.N.
A59: Eshbekov S.O.

Sheet qaror
A1: =""&umumiy_malumot!B147&" mikromoliya tashkiloti Kredit qo‘mitasining yig‘ilishi" -> «PULLOL BUSINESS MIKROMOLIYA TASHKILOTI» MChJ mikromoliya tashkiloti Kredit qo‘mitasining yig‘ilishi
A2: =""&H7&" protokolidan ko'chirma" -> №3-BR protokolidan ko'chirma
A3: Toshkent shahri | E3: =umumiy_malumot!B68 -> 6 yanvar 2026 y.
B4: KUN TARTIBI:
A5: =" "&H8&"."&umumiy_malumot!B5&" ga "&umumiy_malumot!B65&" berish masalasini ko‘rib chiqish to‘g‘risida." -> 1.TURAYEV ISROIL BURIYEVICH ga mikroqarz berish masalasini ko‘rib chiqish to‘g‘risida.
A7: =" "&H9&" masala yuzasidan: «PULLOL BUSINESS MIKROMOLIYA TASHKILOTI» MChJ mikromoliya tashkiloti kredit bo‘yicha menejeri "&umumiy_malumot!B5&"ga "&FIXED(umumiy_malumot!B75)&" ("&umumiy_malumot!B76&") so‘m miqdorida, muddati "&umumiy_malumot!B81&" ("&umumiy_malumot!B82&") oyga va yillik "&umumiy_malumot!B85&"% ("&umumiy_malumot!B86&") foiz miqdorida "&umumiy_malumot!B65&" berich bo‘yicha "&umumiy_malumot!B5&"ning kredit arizasi va "&umumiy_malumot!B147&"ning xulosasi bilan ishtirokchilarni tanishtirdi." -> Birinchi masala yuzasidan: «PULLOL BUSINESS MIKROMOLIYA TASHKILOTI» MChJ mikromoliya tashkiloti kredit bo‘yicha menejeri TURAYEV ISROIL BURIYEVICHga 33 000 000,00 (o'ttiz uch million so'm) so‘m miqdorida, muddati 36 (o'ttiz olti) oyga va yillik 55% (ellik besh) foiz miqdorida mikroqarz berich bo‘yicha TURAYEV ISROIL BURIYEVICHning kredit arizasi va «PULLOL BUSINESS MIKROMOLIYA TASHKILOTI» MChJning xulosasi bilan ishtirokchilarni tanishtirdi. | G7: Protokol raqami | H7: =umumiy_malumot!B1 -> №3-BR
G8: Savol raqami | H8: 1 | I8: 1 | J8: 2 | K8: 3 | L8: 4 | M8: 5 | N8: 6 | O8: 7 | P8: 8 | Q8: 9 | R8: 10 | S8: 11 | T8: 12 | U8: 13 | V8: 14 | W8: 15 | X8: 16 | Y8: 17 | Z8: 18 | AA8: 19 | AB8: 20 | AC8: 21 | AD8: 22 | AE8: 23 | AF8: 24 | AG8: 25
G9: Savol raqami qol bilan | H9: =IF(H8=I8,I9,IF(H8=J8,J9,IF(H8=K8,K9,IF(H8=L8,L9,IF(H8=M8,M9,IF(H8=N8,N9,IF(H8=O8,O9,IF(H8=P8,P9,IF(H8=Q8,Q9,IF(H8=R8,R9,IF(H8=S8,S9,IF(H8=T8,T9,IF(H8=U8,U9,IF(H8=V8,V9,IF(H8=W8,W9,IF(H8=X8,X9,IF(H8=Y8,Y9,IF(H8=Z8,Z9,IF(H8=AA8,AA9,IF(H8=AB8,AB9,IF(H8=AC8,AC9,IF(H8=AD8,AD9,IF(H8=AE8,AE9,IF(H8=AF8,AF9,IF(H8=AG8,AG9))))))))))))))))))))))))) -> Birinchi | I9: Birinchi | J9: Ikkinchi | K9: Uchinchi | L9: To'rtinchi | M9: Beshinchi | N9: O'ltinchi | O9: Yettinchi | P9: Sakkizinchi | Q9: Tuqqizinchi | R9: O'ninchi | S9: O'n birinchi | T9: O'n ikkinchi | U9: O'n uchinchi | V9: O'n to'rtinchi | W9: O'n beshinchi | X9: O'n oltinchi | Y9: O'n yettinchi | Z9: O'n sakkizinchi | AA9: O'n tuqqizinchi | AB9: Yigirmanchi | AC9: Yigirma birinchi | AD9: Yigizma ikkinchi | AE9: Yigirma uchinchi | AF9: Yigirma to'rtinchi | AG9: Yigirma beshinchi
A14: =""&umumiy_malumot!C64&" ta’minoti:" -> Mikroqarz ta’minoti:
A16: =xulosa!A18:E18 -> Egalik huquqi USMONOV NURIDDID IXTIYOROVICHga tegishli bo'lgan garovga olingan avtomobil markasi COBALT, rangi - OQ OLIMPIYSKAYA BELAYA, ishlab chiqarilgan yili - 2016, davlat raqam belgisi 80G291QA, kuzov turi - YENGIL SEDAN, kuzov raqami XWBJF69VEGA010429, dvigatel raqami B15D211163412DJCX0337, shassi raqami - RAKAMSIZ
C17: masala yuzasidan berilgan ma’lumotlarni muhokama qilib, Kredit qo‘mitasi a’zolariga taqdim etilgan zarur hujjatlarni o‘rganib, majlisda ishtirok etgan Kredit qo‘mitasi a’zolarining taklif va mulohazalarini inobatga olgan holda | D17: =""&umumiy_malumot!B147&" kredit qo‘mitasi" -> «PULLOL BUSINESS MIKROMOLIYA TASHKILOTI» MChJ kredit qo‘mitasi | E17: =CONCATENATE(C17,D17) -> masala yuzasidan berilgan ma’lumotlarni muhokama qilib, Kredit qo‘mitasi a’zolariga taqdim etilgan zarur hujjatlarni o‘rganib, majlisda ishtirok etgan Kredit qo‘mitasi a’zolarining taklif va mulohazalarini inobatga olgan holda «PULLOL BUSINESS MIKROMOLIYA TASHKILOTI» MChJ kredit qo‘mitasi
A18: =CONCATENATE(H9,E17) -> Birinchi masala yuzasidan berilgan ma’lumotlarni muhokama qilib, Kredit qo‘mitasi a’zolariga taqdim etilgan zarur hujjatlarni o‘rganib, majlisda ishtirok etgan Kredit qo‘mitasi a’zolarining taklif va mulohazalarini inobatga olgan holda «PULLOL BUSINESS MIKROMOLIYA TASHKILOTI» MChJ kredit qo‘mitasi
A19: QAROR QILADI:
A20: =" "&umumiy_malumot!B5&"ga quyidagi shartlarda "&umumiy_malumot!B65&" berish masalasi ma’qullansin:" -> TURAYEV ISROIL BURIYEVICHga quyidagi shartlarda mikroqarz berish masalasi ma’qullansin:
A21: ="1. "&umumiy_malumot!C64&" summasi: "&FIXED(umumiy_malumot!B75)&" ("&umumiy_malumot!B76&") so'm." -> 1. Mikroqarz summasi: 33 000 000,00 (o'ttiz uch million so'm) so'm.
A22: ="2. "&umumiy_malumot!C64&" muddati: "&umumiy_malumot!B81&" ("&umumiy_malumot!B82&") oy " -> 2. Mikroqarz muddati: 36 (o'ttiz olti) oy
A23: ="3. "&umumiy_malumot!C64&"dan foydalanganlik uchun foiz stavkasi:yillik "&umumiy_malumot!B85&"% ("&umumiy_malumot!B86&") foiz." -> 3. Mikroqarzdan foydalanganlik uchun foiz stavkasi:yillik 55% (ellik besh) foiz.
A24: ="4. "&umumiy_malumot!C64&" bo‘yicha asosiy qarz va foizlarni to‘lash:" -> 4. Mikroqarz bo‘yicha asosiy qarz va foizlarni to‘lash:
A25: =kredit_ariza!A19:D19 -> - mikroqarz shartnomasi bo'yicha har oy differensial to'lovlari amalga oshiriladi
A26: ="5. "&umumiy_malumot!C64&" bo‘yicha garov "&xulosa!A29:E29&"" -> 5. Mikroqarz bo‘yicha garov - USMONOV NURIDDID IXTIYOROVICH ga mulk huquqi asosida tegishli avtotransport vositasi COBALT , quyidagi tafsilotlarga muvofiq:
A27: =dalolatnoma!A29 -> Nomi | B27: =dalolatnoma!B29 -> Kuzov turi va kuzov raqami* | C27: =dalolatnoma!C29 -> Dvigatel va shassi raqami* | D27: =dalolatnoma!D29 -> Ishlab chiqarilgan yili va rangi* | E27: =dalolatnoma!E29 -> Kelishilgan garov qiymati, so'm
A28: =dalolatnoma!A30 -> COBALT | B28: =dalolatnoma!B30 -> kuzov turi - YENGIL SEDAN, kuzov raqami XWBJF69VEGA010429 | C28: =dalolatnoma!C30 -> dvigatel raqami B15D211163412DJCX0337, shassi raqami - RAKAMSIZ | D28: =dalolatnoma!D30 -> rangi - OQ OLIMPIYSKAYA BELAYA, ishlab chiqarilgan yili - 2016 | E28: =dalolatnoma!E30 -> 46 200 000,00 (qirq olti million ikki yuz ming so'm)
A29: =dalolatnoma!A22:E22 -> -* avtotransport egasi: USMONOV NURIDDID IXTIYOROVICH
A30: =dalolatnoma!A23:E23 -> -* texnik pasport: AAF 2401056 01.12.2020 y.
A31: =dalolatnoma!A24:E24 -> -* roʻyxatdan oʻtgan manzili/garaj manzili: BUXORO VILOYATI BUXORO SHAHRI CHO'LPON KO'CHASI 22-A-UY
A32: =dalolatnoma!A25:E25 -> -* davlat raqami: 80G291QA
A34: 6. Boshqa shartlar – avtotransport vositasi shaklida garov ta'minlangandan keyin mikroqarz berish.
A36: Qaror bir ovozdan qabul qilindi.
A37: 1. Obidov Abdullo Shokir og'li
A38: 2. Akramov R.N.
A39: 3. Eshbekov S.O.

Sheet Данные для послед. Залога
A1: № | B1: - | E1: ФИО | F1: дата | L1: № договора | M1: Сог. Сумма | N1: сог. Сумма (пропис.)
A2: 1 | B2: ha | C2: yoq | D2: ha | E2: TULYAGANOV XODJIAKBAR IRGASHEVICH | F2: 44207 | G2: =MONTH(F2) -> 1 | H2: =IF(G2=$A$26,$A$28,IF(G2=$B$26,$B$28,IF(G2=$C$26,$C$28,IF(G2=$D$26,$D$28,IF(G2=$E$26,$E$28,IF(G2=$F$26,$F$28,IF(G2=$K$26,$K$28,IF(G2=$L$26,$L$28,IF(G2=$M$26,$M$28,IF(G2=$N$26,$N$28,IF(G2=$O$26,$O$28,IF(G2=$P$26,$P$28,0)))))))))))) -> yanvar | I2: =DAY(F2) -> 11 | J2: =YEAR(F2) -> 2021 | K2: =""&I2&" "&H2&" "&J2&" г." -> 11 yanvar 2021 г. | L2: 5 | M2: 15000000 | N2: on besh million | O2: ="- №"&L2&" от "&K2&", заключенного с ООО «Clever Mikrokredit Tashkiloti» и "&E2&", по согласованной залоговой стоимость - "&FIXED(M2)&" ("&N2&") сум." -> - №5 от 11 yanvar 2021 г., заключенного с ООО «Clever Mikrokredit Tashkiloti» и TULYAGANOV XODJIAKBAR IRGASHEVICH, по согласованной залоговой стоимость - 15 000 000,00 (on besh million) сум. | P2: =IF(D2=$B$2,O2,IF(D2=$C$2,$B$1)) -> - №5 от 11 yanvar 2021 г., заключенного с ООО «Clever Mikrokredit Tashkiloti» и TULYAGANOV XODJIAKBAR IRGASHEVICH, по согласованной залоговой стоимость - 15 000 000,00 (on besh million) сум. | W2: =""&P2&" "&P3&" "&P4&" "&P5&" "&P6&" "&P7&" "&P8&" "&P9&" "&P10&" "&P11&" "&P12&" "&P13&" "&P14&" "&P15&" "&P16&" "&P17&" "&P18&" "&P19&" "&P20&" "&P21&"" -> - №5 от 11 yanvar 2021 г., заключенного с ООО «Clever Mikrokredit Tashkiloti» и TULYAGANOV XODJIAKBAR IRGASHEVICH, по согласованной залоговой стоимость - 15 000 000,00 (on besh million) сум. - №386 от 6 noyabr 2019 г., заключенного с ООО «Clever Mikrokredit Tashkiloti» и YUNUSOVA ZALOXAT MIRSULTANOVNA, по согласованной залоговой стоимость - 15 000 000,00 (on besh million) сум. - №33 от 21 yanvar 2021 г., заключенного с ООО «Clever Mikrokredit Tashkiloti» и YUNUSOVA ZALOXAT MIRSULTANOVNA, по согласованной залоговой стоимость - 15 000 000,00 (on besh million) сум. 0 0 0 0 0 0 0 0 0 0 0 0 0 0 0 0 0
A3: 2 | D3: ha | E3: YUNUSOVA ZALOXAT MIRSULTANOVNA | F3: 43775 | G3: =MONTH(F3) -> 11 | H3: =IF(G3=$A$26,$A$28,IF(G3=$B$26,$B$28,IF(G3=$C$26,$C$28,IF(G3=$D$26,$D$28,IF(G3=$E$26,$E$28,IF(G3=$F$26,$F$28,IF(G3=$K$26,$K$28,IF(G3=$L$26,$L$28,IF(G3=$M$26,$M$28,IF(G3=$N$26,$N$28,IF(G3=$O$26,$O$28,IF(G3=$P$26,$P$28,0)))))))))))) -> noyabr | I3: =DAY(F3) -> 6 | J3: =YEAR(F3) -> 2019 | K3: =""&I3&" "&H3&" "&J3&" г." -> 6 noyabr 2019 г. | L3: 386 | M3: 15000000 | N3: on besh million | O3: ="- №"&L3&" от "&K3&", заключенного с ООО «Clever Mikrokredit Tashkiloti» и "&E3&", по согласованной залоговой стоимость - "&FIXED(M3)&" ("&N3&") сум." -> - №386 от 6 noyabr 2019 г., заключенного с ООО «Clever Mikrokredit Tashkiloti» и YUNUSOVA ZALOXAT MIRSULTANOVNA, по согласованной залоговой стоимость - 15 000 000,00 (on besh million) сум. | P3: =IF(D3=$B$2,O3,IF(D3=$C$2,$B$1)) -> - №386 от 6 noyabr 2019 г., заключенного с ООО «Clever Mikrokredit Tashkiloti» и YUNUSOVA ZALOXAT MIRSULTANOVNA, по согласованной залоговой стоимость - 15 000 000,00 (on besh million) сум.
A4: 3 | D4: ha | E4: YUNUSOVA ZALOXAT MIRSULTANOVNA | F4: 44217 | G4: =MONTH(F4) -> 1 | H4: =IF(G4=$A$26,$A$28,IF(G4=$B$26,$B$28,IF(G4=$C$26,$C$28,IF(G4=$D$26,$D$28,IF(G4=$E$26,$E$28,IF(G4=$F$26,$F$28,IF(G4=$K$26,$K$28,IF(G4=$L$26,$L$28,IF(G4=$M$26,$M$28,IF(G4=$N$26,$N$28,IF(G4=$O$26,$O$28,IF(G4=$P$26,$P$28,0)))))))))))) -> yanvar | I4: =DAY(F4) -> 21 | J4: =YEAR(F4) -> 2021 | K4: =""&I4&" "&H4&" "&J4&" г." -> 21 yanvar 2021 г. | L4: 33 | M4: 15000000 | N4: on besh million | O4: ="- №"&L4&" от "&K4&", заключенного с ООО «Clever Mikrokredit Tashkiloti» и "&E4&", по согласованной залоговой стоимость - "&FIXED(M4)&" ("&N4&") сум." -> - №33 от 21 yanvar 2021 г., заключенного с ООО «Clever Mikrokredit Tashkiloti» и YUNUSOVA ZALOXAT MIRSULTANOVNA, по согласованной залоговой стоимость - 15 000 000,00 (on besh million) сум. | P4: =IF(D4=$B$2,O4,IF(D4=$C$2,$B$1)) -> - №33 от 21 yanvar 2021 г., заключенного с ООО «Clever Mikrokredit Tashkiloti» и YUNUSOVA ZALOXAT MIRSULTANOVNA, по согласованной залоговой стоимость - 15 000 000,00 (on besh million) сум.
A5: 4 | D5: ha | G5: =MONTH(F5) -> 1 | H5: =IF(G5=$A$26,$A$28,IF(G5=$B$26,$B$28,IF(G5=$C$26,$C$28,IF(G5=$D$26,$D$28,IF(G5=$E$26,$E$28,IF(G5=$F$26,$F$28,IF(G5=$K$26,$K$28,IF(G5=$L$26,$L$28,IF(G5=$M$26,$M$28,IF(G5=$N$26,$N$28,IF(G5=$O$26,$O$28,IF(G5=$P$26,$P$28,0)))))))))))) -> yanvar | I5: =DAY(F5) -> 0 | J5: =YEAR(F5) -> 1900 | K5: =""&I5&" "&H5&" "&J5&" г." -> 0 yanvar 1900 г. | P5: =IF(D5=$B$2,O5,IF(D5=$C$2,$B$1)) -> 0
A6: 5 | D6: ha | G6: =MONTH(F6) -> 1 | H6: =IF(G6=$A$26,$A$28,IF(G6=$B$26,$B$28,IF(G6=$C$26,$C$28,IF(G6=$D$26,$D$28,IF(G6=$E$26,$E$28,IF(G6=$F$26,$F$28,IF(G6=$K$26,$K$28,IF(G6=$L$26,$L$28,IF(G6=$M$26,$M$28,IF(G6=$N$26,$N$28,IF(G6=$O$26,$O$28,IF(G6=$P$26,$P$28,0)))))))))))) -> yanvar | I6: =DAY(F6) -> 0 | J6: =YEAR(F6) -> 1900 | K6: =""&I6&" "&H6&" "&J6&" г." -> 0 yanvar 1900 г. | P6: =IF(D6=$B$2,O6,IF(D6=$C$2,$B$1)) -> 0
A7: 6 | D7: ha | G7: =MONTH(F7) -> 1 | H7: =IF(G7=$A$26,$A$28,IF(G7=$B$26,$B$28,IF(G7=$C$26,$C$28,IF(G7=$D$26,$D$28,IF(G7=$E$26,$E$28,IF(G7=$F$26,$F$28,IF(G7=$K$26,$K$28,IF(G7=$L$26,$L$28,IF(G7=$M$26,$M$28,IF(G7=$N$26,$N$28,IF(G7=$O$26,$O$28,IF(G7=$P$26,$P$28,0)))))))))))) -> yanvar | I7: =DAY(F7) -> 0 | J7: =YEAR(F7) -> 1900 | K7: =""&I7&" "&H7&" "&J7&" г." -> 0 yanvar 1900 г. | P7: =IF(D7=$B$2,O7,IF(D7=$C$2,$B$1)) -> 0
A8: 7 | D8: ha | G8: =MONTH(F8) -> 1 | H8: =IF(G8=$A$26,$A$28,IF(G8=$B$26,$B$28,IF(G8=$C$26,$C$28,IF(G8=$D$26,$D$28,IF(G8=$E$26,$E$28,IF(G8=$F$26,$F$28,IF(G8=$K$26,$K$28,IF(G8=$L$26,$L$28,IF(G8=$M$26,$M$28,IF(G8=$N$26,$N$28,IF(G8=$O$26,$O$28,IF(G8=$P$26,$P$28,0)))))))))))) -> yanvar | I8: =DAY(F8) -> 0 | J8: =YEAR(F8) -> 1900 | K8: =""&I8&" "&H8&" "&J8&" г." -> 0 yanvar 1900 г. | P8: =IF(D8=$B$2,O8,IF(D8=$C$2,$B$1)) -> 0
A9: 8 | D9: ha | G9: =MONTH(F9) -> 1 | H9: =IF(G9=$A$26,$A$28,IF(G9=$B$26,$B$28,IF(G9=$C$26,$C$28,IF(G9=$D$26,$D$28,IF(G9=$E$26,$E$28,IF(G9=$F$26,$F$28,IF(G9=$K$26,$K$28,IF(G9=$L$26,$L$28,IF(G9=$M$26,$M$28,IF(G9=$N$26,$N$28,IF(G9=$O$26,$O$28,IF(G9=$P$26,$P$28,0)))))))))))) -> yanvar | I9: =DAY(F9) -> 0 | J9: =YEAR(F9) -> 1900 | K9: =""&I9&" "&H9&" "&J9&" г." -> 0 yanvar 1900 г. | P9: =IF(D9=$B$2,O9,IF(D9=$C$2,$B$1)) -> 0
A10: 9 | D10: ha | G10: =MONTH(F10) -> 1 | H10: =IF(G10=$A$26,$A$28,IF(G10=$B$26,$B$28,IF(G10=$C$26,$C$28,IF(G10=$D$26,$D$28,IF(G10=$E$26,$E$28,IF(G10=$F$26,$F$28,IF(G10=$K$26,$K$28,IF(G10=$L$26,$L$28,IF(G10=$M$26,$M$28,IF(G10=$N$26,$N$28,IF(G10=$O$26,$O$28,IF(G10=$P$26,$P$28,0)))))))))))) -> yanvar | I10: =DAY(F10) -> 0 | J10: =YEAR(F10) -> 1900 | K10: =""&I10&" "&H10&" "&J10&" г." -> 0 yanvar 1900 г. | P10: =IF(D10=$B$2,O10,IF(D10=$C$2,$B$1)) -> 0
A11: 10 | D11: ha | G11: =MONTH(F11) -> 1 | H11: =IF(G11=$A$26,$A$28,IF(G11=$B$26,$B$28,IF(G11=$C$26,$C$28,IF(G11=$D$26,$D$28,IF(G11=$E$26,$E$28,IF(G11=$F$26,$F$28,IF(G11=$K$26,$K$28,IF(G11=$L$26,$L$28,IF(G11=$M$26,$M$28,IF(G11=$N$26,$N$28,IF(G11=$O$26,$O$28,IF(G11=$P$26,$P$28,0)))))))))))) -> yanvar | I11: =DAY(F11) -> 0 | J11: =YEAR(F11) -> 1900 | K11: =""&I11&" "&H11&" "&J11&" г." -> 0 yanvar 1900 г. | P11: =IF(D11=$B$2,O11,IF(D11=$C$2,$B$1)) -> 0
A12: 11 | D12: ha | G12: =MONTH(F12) -> 1 | H12: =IF(G12=$A$26,$A$28,IF(G12=$B$26,$B$28,IF(G12=$C$26,$C$28,IF(G12=$D$26,$D$28,IF(G12=$E$26,$E$28,IF(G12=$F$26,$F$28,IF(G12=$K$26,$K$28,IF(G12=$L$26,$L$28,IF(G12=$M$26,$M$28,IF(G12=$N$26,$N$28,IF(G12=$O$26,$O$28,IF(G12=$P$26,$P$28,0)))))))))))) -> yanvar | I12: =DAY(F12) -> 0 | J12: =YEAR(F12) -> 1900 | K12: =""&I12&" "&H12&" "&J12&" г." -> 0 yanvar 1900 г. | P12: =IF(D12=$B$2,O12,IF(D12=$C$2,$B$1)) -> 0
A13: 12 | D13: ha | G13: =MONTH(F13) -> 1 | H13: =IF(G13=$A$26,$A$28,IF(G13=$B$26,$B$28,IF(G13=$C$26,$C$28,IF(G13=$D$26,$D$28,IF(G13=$E$26,$E$28,IF(G13=$F$26,$F$28,IF(G13=$K$26,$K$28,IF(G13=$L$26,$L$28,IF(G13=$M$26,$M$28,IF(G13=$N$26,$N$28,IF(G13=$O$26,$O$28,IF(G13=$P$26,$P$28,0)))))))))))) -> yanvar | I13: =DAY(F13) -> 0 | J13: =YEAR(F13) -> 1900 | K13: =""&I13&" "&H13&" "&J13&" г." -> 0 yanvar 1900 г. | P13: =IF(D13=$B$2,O13,IF(D13=$C$2,$B$1)) -> 0
A14: 13 | D14: ha | G14: =MONTH(F14) -> 1 | H14: =IF(G14=$A$26,$A$28,IF(G14=$B$26,$B$28,IF(G14=$C$26,$C$28,IF(G14=$D$26,$D$28,IF(G14=$E$26,$E$28,IF(G14=$F$26,$F$28,IF(G14=$K$26,$K$28,IF(G14=$L$26,$L$28,IF(G14=$M$26,$M$28,IF(G14=$N$26,$N$28,IF(G14=$O$26,$O$28,IF(G14=$P$26,$P$28,0)))))))))))) -> yanvar | I14: =DAY(F14) -> 0 | J14: =YEAR(F14) -> 1900 | K14: =""&I14&" "&H14&" "&J14&" г." -> 0 yanvar 1900 г. | P14: =IF(D14=$B$2,O14,IF(D14=$C$2,$B$1)) -> 0
A15: 14 | D15: ha | G15: =MONTH(F15) -> 1 | H15: =IF(G15=$A$26,$A$28,IF(G15=$B$26,$B$28,IF(G15=$C$26,$C$28,IF(G15=$D$26,$D$28,IF(G15=$E$26,$E$28,IF(G15=$F$26,$F$28,IF(G15=$K$26,$K$28,IF(G15=$L$26,$L$28,IF(G15=$M$26,$M$28,IF(G15=$N$26,$N$28,IF(G15=$O$26,$O$28,IF(G15=$P$26,$P$28,0)))))))))))) -> yanvar | I15: =DAY(F15) -> 0 | J15: =YEAR(F15) -> 1900 | K15: =""&I15&" "&H15&" "&J15&" г." -> 0 yanvar 1900 г. | P15: =IF(D15=$B$2,O15,IF(D15=$C$2,$B$1)) -> 0
A16: 15 | D16: ha | G16: =MONTH(F16) -> 1 | H16: =IF(G16=$A$26,$A$28,IF(G16=$B$26,$B$28,IF(G16=$C$26,$C$28,IF(G16=$D$26,$D$28,IF(G16=$E$26,$E$28,IF(G16=$F$26,$F$28,IF(G16=$K$26,$K$28,IF(G16=$L$26,$L$28,IF(G16=$M$26,$M$28,IF(G16=$N$26,$N$28,IF(G16=$O$26,$O$28,IF(G16=$P$26,$P$28,0)))))))))))) -> yanvar | I16: =DAY(F16) -> 0 | J16: =YEAR(F16) -> 1900 | K16: =""&I16&" "&H16&" "&J16&" г." -> 0 yanvar 1900 г. | P16: =IF(D16=$B$2,O16,IF(D16=$C$2,$B$1)) -> 0
... A21: 20 | D21: ha | G21: =MONTH(F21) -> 1 | H21: =IF(G21=$A$26,$A$28,IF(G21=$B$26,$B$28,IF(G21=$C$26,$C$28,IF(G21=$D$26,$D$28,IF(G21=$E$26,$E$28,IF(G21=$F$26,$F$28,IF(G21=$K$26,$K$28,IF(G21=$L$26,$L$28,IF(G21=$M$26,$M$28,IF(G21=$N$26,$N$28,IF(G21=$O$26,$O$28,IF(G21=$P$26,$P$28,0)))))))))))) -> yanvar | I21: =DAY(F21) -> 0 | J21: =YEAR(F21) -> 1900 | K21: =""&I21&" "&H21&" "&J21&" г." -> 0 yanvar 1900 г. | P21: =IF(D21=$B$2,O21,IF(D21=$C$2,$B$1)) -> 0
M22: =SUM(M2:M21)+umumiy_malumot!B136 -> 91200000 | Q22: ottiz yetti million besh yuz ming
A25: =MONTH(F2) -> 1 | B25: =IF(A25=A26,A28,IF(A25=B26,B28,IF(A25=C26,C28,IF(A25=D26,D28,IF(A25=E26,E28,IF(A25=F26,F28,IF(A25=K26,K28,IF(A25=L26,L28,IF(A25=M26,M28,IF(A25=N26,N28,IF(A25=O26,O28,IF(A25=#REF!,#REF!,)))))))))))) -> yanvar | C25: =DAY(F2) -> 11 | D25: =YEAR(F2) -> 2021
A26: 1 | B26: 2 | C26: 3 | D26: 4 | E26: 5 | F26: 6 | K26: 7 | L26: 8 | M26: 9 | N26: 10 | O26: 11 | P26: 12
A28: yanvar | B28: fevral | C28: mart | D28: aprel | E28: may | F28: iyun | K28: июля | L28: avgust | M28: sentyabr | N28: oktyabr | O28: noyabr | P28: dekabr
A29: yanvar | B29: fevral | C29: mart | D29: aprel | E29: may | F29: iyun | K29: июль | L29: avgust | M29: sentyabr | N29: oktyabr | O29: noyabr | P29: dekabr

Sheet График аннуитет.
E1: Приложение №1
F2: ="к договору микрозайма "&umumiy_malumot!B74&"" -> к договору микрозайма 6 yanvar 2026 y.dan №3-BR
A4: График погашения
A6: № | B6: Дата погашения | C6: Остаток основного долга | D6: Сумма погашения, сум
D7: основного долга | E7: процентов* | F7: всего*
A8: 1 | B8: ='График дифференц'!B8 -> 46069 | C8: =umumiy_malumot!B75 -> 33000000 | D8: =IF(A8<umumiy_malumot!$B$81,'График аннуитет.'!F8-'График аннуитет.'!E8,'График аннуитет.'!C8) -> 916666.67 | E8: =ROUND(C8*umumiy_malumot!$B$84/H8,2)*'График аннуитет.'!G8 -> 2038767.2 | F8: =umumiy_malumot!B90 -> 2955433.9 | G8: =B8-umumiy_malumot!B67 -> 41 | H8: =DATE(YEAR(B8),12,31)-DATE(YEAR(B8),1,1)+1 -> 365
A9: 2 | B9: ='График дифференц'!B9 -> 46097 | C9: =C8-D8 -> 32083333 | D9: =IF(A9<umumiy_malumot!$B$81,'График аннуитет.'!F9-'График аннуитет.'!E9,'График аннуитет.'!C9) -> 1601780.9 | E9: =ROUND(C9*umumiy_malumot!$B$84/H9,2)*'График аннуитет.'!G9 -> 1353653 | F9: =IF(A9<umumiy_malumot!$B$81,'График аннуитет.'!F8,'График аннуитет.'!D9+'График аннуитет.'!E9) -> 2955433.9 | G9: =B9-B8 -> 28 | H9: =DATE(YEAR(B9),12,31)-DATE(YEAR(B9),1,1)+1 -> 365
A10: 3 | B10: ='График дифференц'!B10 -> 46127 | C10: =C9-D9 -> 30481552 | D10: =IF(A10<umumiy_malumot!$B$81,'График аннуитет.'!F10-'График аннуитет.'!E10,'График аннуитет.'!C10) -> 1577500.6 | E10: =ROUND(C10*umumiy_malumot!$B$84/H10,2)*'График аннуитет.'!G10 -> 1377933.3 | F10: =IF(A10<umumiy_malumot!$B$81,'График аннуитет.'!F9,'График аннуитет.'!D10+'График аннуитет.'!E10) -> 2955433.9 | G10: =B10-B9 -> 30 | H10: =DATE(YEAR(B10),12,31)-DATE(YEAR(B10),1,1)+1 -> 365
A11: 4 | B11: ='График дифференц'!B11 -> 46157 | C11: =C10-D10 -> 28904052 | D11: =IF(A11<umumiy_malumot!$B$81,'График аннуитет.'!F11-'График аннуитет.'!E11,'График аннуитет.'!C11) -> 1648812.4 | E11: =ROUND(C11*umumiy_malumot!$B$84/H11,2)*'График аннуитет.'!G11 -> 1306621.5 | F11: =IF(A11<umumiy_malumot!$B$81,'График аннуитет.'!F10,'График аннуитет.'!D11+'График аннуитет.'!E11) -> 2955433.9 | G11: =B11-B10 -> 30 | H11: =DATE(YEAR(B11),12,31)-DATE(YEAR(B11),1,1)+1 -> 365
A12: 5 | B12: ='График дифференц'!B12 -> 46188 | C12: =C11-D11 -> 27255239 | D12: =IF(A12<umumiy_malumot!$B$81,'График аннуитет.'!F12-'График аннуитет.'!E12,'График аннуитет.'!C12) -> 1682278.2 | E12: =ROUND(C12*umumiy_malumot!$B$84/H12,2)*'График аннуитет.'!G12 -> 1273155.7 | F12: =IF(A12<umumiy_malumot!$B$81,'График аннуитет.'!F11,'График аннуитет.'!D12+'График аннуитет.'!E12) -> 2955433.9 | G12: =B12-B11 -> 31 | H12: =DATE(YEAR(B12),12,31)-DATE(YEAR(B12),1,1)+1 -> 365
A13: 6 | B13: ='График дифференц'!B13 -> 46218 | C13: =C12-D12 -> 25572961 | D13: =IF(A13<umumiy_malumot!$B$81,'График аннуитет.'!F13-'График аннуитет.'!E13,'График аннуитет.'!C13) -> 1799395.9 | E13: =ROUND(C13*umumiy_malumot!$B$84/H13,2)*'График аннуитет.'!G13 -> 1156038 | F13: =IF(A13<umumiy_malumot!$B$81,'График аннуитет.'!F12,'График аннуитет.'!D13+'График аннуитет.'!E13) -> 2955433.9 | G13: =B13-B12 -> 30 | H13: =DATE(YEAR(B13),12,31)-DATE(YEAR(B13),1,1)+1 -> 365
A14: 7 | B14: ='График дифференц'!B14 -> 46251 | C14: =C13-D13 -> 23773565 | D14: =IF(A14<umumiy_malumot!$B$81,'График аннуитет.'!F14-'График аннуитет.'!E14,'График аннуитет.'!C14) -> 1773269 | E14: =ROUND(C14*umumiy_malumot!$B$84/H14,2)*'График аннуитет.'!G14 -> 1182164.9 | F14: =IF(A14<umumiy_malumot!$B$81,'График аннуитет.'!F13,'График аннуитет.'!D14+'График аннуитет.'!E14) -> 2955433.9 | G14: =B14-B13 -> 33 | H14: =DATE(YEAR(B14),12,31)-DATE(YEAR(B14),1,1)+1 -> 365
A15: 8 | B15: ='График дифференц'!B15 -> 46280 | C15: =C14-D14 -> 22000296 | D15: =IF(A15<umumiy_malumot!$B$81,'График аннуитет.'!F15-'График аннуитет.'!E15,'График аннуитет.'!C15) -> 1994051.1 | E15: =ROUND(C15*umumiy_malumot!$B$84/H15,2)*'График аннуитет.'!G15 -> 961382.77 | F15: =IF(A15<umumiy_malumot!$B$81,'График аннуитет.'!F14,'График аннуитет.'!D15+'График аннуитет.'!E15) -> 2955433.9 | G15: =B15-B14 -> 29 | H15: =DATE(YEAR(B15),12,31)-DATE(YEAR(B15),1,1)+1 -> 365
A16: 9 | B16: ='График дифференц'!B16 -> 46310 | C16: =C15-D15 -> 20006245 | D16: =IF(A16<umumiy_malumot!$B$81,'График аннуитет.'!F16-'График аннуитет.'!E16,'График аннуитет.'!C16) -> 2051041.9 | E16: =ROUND(C16*umumiy_malumot!$B$84/H16,2)*'График аннуитет.'!G16 -> 904392 | F16: =IF(A16<umumiy_malumot!$B$81,'График аннуитет.'!F15,'График аннуитет.'!D16+'График аннуитет.'!E16) -> 2955433.9 | G16: =B16-B15 -> 30 | H16: =DATE(YEAR(B16),12,31)-DATE(YEAR(B16),1,1)+1 -> 365
A17: 10 | B17: ='График дифференц'!B17 -> 46342 | C17: =C16-D16 -> 17955203 | D17: =IF(A17<umumiy_malumot!$B$81,'График аннуитет.'!F17-'График аннуитет.'!E17,'График аннуитет.'!C17) -> 2089648.6 | E17: =ROUND(C17*umumiy_malumot!$B$84/H17,2)*'График аннуитет.'!G17 -> 865785.28 | F17: =IF(A17<umumiy_malumot!$B$81,'График аннуитет.'!F16,'График аннуитет.'!D17+'График аннуитет.'!E17) -> 2955433.9 | G17: =B17-B16 -> 32 | H17: =DATE(YEAR(B17),12,31)-DATE(YEAR(B17),1,1)+1 -> 365
A18: 11 | B18: ='График дифференц'!B18 -> 46371 | C18: =C17-D17 -> 15865555 | D18: =IF(A18<umumiy_malumot!$B$81,'График аннуитет.'!F18-'График аннуитет.'!E18,'График аннуитет.'!C18) -> 2262130.9 | E18: =ROUND(C18*umumiy_malumot!$B$84/H18,2)*'График аннуитет.'!G18 -> 693303 | F18: =IF(A18<umumiy_malumot!$B$81,'График аннуитет.'!F17,'График аннуитет.'!D18+'График аннуитет.'!E18) -> 2955433.9 | G18: =B18-B17 -> 29 | H18: =DATE(YEAR(B18),12,31)-DATE(YEAR(B18),1,1)+1 -> 365
A19: 12 | B19: ='График дифференц'!B19 -> 46402 | C19: =C18-D18 -> 13603424 | D19: =IF(A19<umumiy_malumot!$B$81,'График аннуитет.'!F19-'График аннуитет.'!E19,'График аннуитет.'!C19) -> 2319986.3 | E19: =ROUND(C19*umumiy_malumot!$B$84/H19,2)*'График аннуитет.'!G19 -> 635447.61 | F19: =IF(A19<umumiy_malumot!$B$81,'График аннуитет.'!F18,'График аннуитет.'!D19+'График аннуитет.'!E19) -> 2955433.9 | G19: =B19-B18 -> 31 | H19: =DATE(YEAR(B19),12,31)-DATE(YEAR(B19),1,1)+1 -> 365
A20: 13 | B20: ='График дифференц'!B20 -> 46433 | C20: =C19-D19 -> 11283438 | D20: =IF(A20<umumiy_malumot!$B$81,'График аннуитет.'!F20-'График аннуитет.'!E20,'График аннуитет.'!C20) -> 2428358.3 | E20: =ROUND(C20*umumiy_malumot!$B$84/H20,2)*'График аннуитет.'!G20 -> 527075.64 | F20: =IF(A20<umumiy_malumot!$B$81,'График аннуитет.'!F19,'График аннуитет.'!D20+'График аннуитет.'!E20) -> 2955433.9 | G20: =B20-B19 -> 31 | H20: =DATE(YEAR(B20),12,31)-DATE(YEAR(B20),1,1)+1 -> 365
... A31: 24 | B31: ='График дифференц'!B31 -> 46769 | C31: =C30-D30 -> -22628423 | D31: =IF(A31<umumiy_malumot!$B$81,'График аннуитет.'!F31-'График аннуитет.'!E31,'График аннуитет.'!C31) -> 4077581.1 | E31: =ROUND(C31*umumiy_malumot!$B$84/H31,2)*'График аннуитет.'!G31 -> -1122147.2 | F31: =IF(A31<umumiy_malumot!$B$81,'График аннуитет.'!F30,'График аннуитет.'!D31+'График аннуитет.'!E31) -> 2955433.9 | G31: =B31-B30 -> 33 | H31: =DATE(YEAR(B31),12,31)-DATE(YEAR(B31),1,1)+1 -> 366
A32: =1+A31 -> 25 | B32: ='График дифференц'!B32 -> 46798 | C32: =C31-D31 -> -26706004 | D32: =IF(A32<umumiy_malumot!$B$81,'График аннуитет.'!F32-'График аннуитет.'!E32,'График аннуитет.'!C32) -> 4119261 | E32: =ROUND(C32*umumiy_malumot!$B$84/H32,2)*'График аннуитет.'!G32 -> -1163827.1 | F32: =IF(A32<umumiy_malumot!$B$81,'График аннуитет.'!F31,'График аннуитет.'!D32+'График аннуитет.'!E32) -> 2955433.9 | G32: =B32-B31 -> 29 | H32: =DATE(YEAR(B32),12,31)-DATE(YEAR(B32),1,1)+1 -> 366
A33: =1+A32 -> 26 | B33: ='График дифференц'!B33 -> 46827 | C33: =C32-D32 -> -30825265 | D33: =IF(A33<umumiy_malumot!$B$81,'График аннуитет.'!F33-'График аннуитет.'!E33,'График аннуитет.'!C33) -> 4298775.4 | E33: =ROUND(C33*umumiy_malumot!$B$84/H33,2)*'График аннуитет.'!G33 -> -1343341.5 | F33: =IF(A33<umumiy_malumot!$B$81,'График аннуитет.'!F32,'График аннуитет.'!D33+'График аннуитет.'!E33) -> 2955433.9 | G33: =B33-B32 -> 29 | H33: =DATE(YEAR(B33),12,31)-DATE(YEAR(B33),1,1)+1 -> 366
A34: =1+A33 -> 27 | B34: ='График дифференц'!B34 -> 46860 | C34: =C33-D33 -> -35124040 | D34: =IF(A34<umumiy_malumot!$B$81,'График аннуитет.'!F34-'График аннуитет.'!E34,'График аннуитет.'!C34) -> 4697240.9 | E34: =ROUND(C34*umumiy_malumot!$B$84/H34,2)*'График аннуитет.'!G34 -> -1741807 | F34: =IF(A34<umumiy_malumot!$B$81,'График аннуитет.'!F33,'График аннуитет.'!D34+'График аннуитет.'!E34) -> 2955433.9 | G34: =B34-B33 -> 33 | H34: =DATE(YEAR(B34),12,31)-DATE(YEAR(B34),1,1)+1 -> 366
A35: =1+A34 -> 28 | B35: ='График дифференц'!B35 -> 46888 | C35: =C34-D34 -> -39821281 | D35: =IF(A35<umumiy_malumot!$B$81,'График аннуитет.'!F35-'График аннуитет.'!E35,'График аннуитет.'!C35) -> 4630974.1 | E35: =ROUND(C35*umumiy_malumot!$B$84/H35,2)*'График аннуитет.'!G35 -> -1675540.2 | F35: =IF(A35<umumiy_malumot!$B$81,'График аннуитет.'!F34,'График аннуитет.'!D35+'График аннуитет.'!E35) -> 2955433.9 | G35: =B35-B34 -> 28 | H35: =DATE(YEAR(B35),12,31)-DATE(YEAR(B35),1,1)+1 -> 366
A36: =1+A35 -> 29 | B36: ='График дифференц'!B36 -> 46919 | C36: =C35-D35 -> -44452255 | D36: =IF(A36<umumiy_malumot!$B$81,'График аннуитет.'!F36-'График аннуитет.'!E36,'График аннуитет.'!C36) -> 5026228.9 | E36: =ROUND(C36*umumiy_malumot!$B$84/H36,2)*'График аннуитет.'!G36 -> -2070795 | F36: =IF(A36<umumiy_malumot!$B$81,'График аннуитет.'!F35,'График аннуитет.'!D36+'График аннуитет.'!E36) -> 2955433.9 | G36: =B36-B35 -> 31 | H36: =DATE(YEAR(B36),12,31)-DATE(YEAR(B36),1,1)+1 -> 366
A37: =1+A36 -> 30 | B37: ='График дифференц'!B37 -> 46951 | C37: =C36-D36 -> -49478484 | D37: =IF(A37<umumiy_malumot!$B$81,'График аннуитет.'!F37-'График аннуитет.'!E37,'График аннуитет.'!C37) -> 5334727 | E37: =ROUND(C37*umumiy_malumot!$B$84/H37,2)*'График аннуитет.'!G37 -> -2379293.1 | F37: =IF(A37<umumiy_malumot!$B$81,'График аннуитет.'!F36,'График аннуитет.'!D37+'График аннуитет.'!E37) -> 2955433.9 | G37: =B37-B36 -> 32 | H37: =DATE(YEAR(B37),12,31)-DATE(YEAR(B37),1,1)+1 -> 366
A38: =1+A37 -> 31 | B38: ='График дифференц'!B38 -> 46980 | C38: =C37-D37 -> -54813211 | D38: =IF(A38<umumiy_malumot!$B$81,'График аннуитет.'!F38-'График аннуитет.'!E38,'График аннуитет.'!C38) -> 5344151.7 | E38: =ROUND(C38*umumiy_malumot!$B$84/H38,2)*'График аннуитет.'!G38 -> -2388717.8 | F38: =IF(A38<umumiy_malumot!$B$81,'График аннуитет.'!F37,'График аннуитет.'!D38+'График аннуитет.'!E38) -> 2955433.9 | G38: =B38-B37 -> 29 | H38: =DATE(YEAR(B38),12,31)-DATE(YEAR(B38),1,1)+1 -> 366
A39: =1+A38 -> 32 | B39: ='График дифференц'!B39 -> 47011 | C39: =C38-D38 -> -60157363 | D39: =IF(A39<umumiy_malumot!$B$81,'График аннуитет.'!F39-'График аннуитет.'!E39,'График аннуитет.'!C39) -> 5757846.6 | E39: =ROUND(C39*umumiy_malumot!$B$84/H39,2)*'График аннуитет.'!G39 -> -2802412.7 | F39: =IF(A39<umumiy_malumot!$B$81,'График аннуитет.'!F38,'График аннуитет.'!D39+'График аннуитет.'!E39) -> 2955433.9 | G39: =B39-B38 -> 31 | H39: =DATE(YEAR(B39),12,31)-DATE(YEAR(B39),1,1)+1 -> 366
A40: =1+A39 -> 33 | B40: ='График дифференц'!B40 -> 47042 | C40: =C39-D39 -> -65915210 | D40: =IF(A40<umumiy_malumot!$B$81,'График аннуитет.'!F40-'График аннуитет.'!E40,'График аннуитет.'!C40) -> 6026074.1 | E40: =ROUND(C40*umumiy_malumot!$B$84/H40,2)*'График аннуитет.'!G40 -> -3070640.2 | F40: =IF(A40<umumiy_malumot!$B$81,'График аннуитет.'!F39,'График аннуитет.'!D40+'График аннуитет.'!E40) -> 2955433.9 | G40: =B40-B39 -> 31 | H40: =DATE(YEAR(B40),12,31)-DATE(YEAR(B40),1,1)+1 -> 366
A41: =1+A40 -> 34 | B41: ='График дифференц'!B41 -> 47072 | C41: =C40-D40 -> -71941284 | D41: =IF(A41<umumiy_malumot!$B$81,'График аннуитет.'!F41-'График аннуитет.'!E41,'График аннуитет.'!C41) -> 6198688.6 | E41: =ROUND(C41*umumiy_malumot!$B$84/H41,2)*'График аннуитет.'!G41 -> -3243254.7 | F41: =IF(A41<umumiy_malumot!$B$81,'График аннуитет.'!F40,'График аннуитет.'!D41+'График аннуитет.'!E41) -> 2955433.9 | G41: =B41-B40 -> 30 | H41: =DATE(YEAR(B41),12,31)-DATE(YEAR(B41),1,1)+1 -> 366
A42: =1+A41 -> 35 | B42: ='График дифференц'!B42 -> 47102 | C42: =C41-D41 -> -78139972 | D42: =IF(A42<umumiy_malumot!$B$81,'График аннуитет.'!F42-'График аннуитет.'!E42,'График аннуитет.'!C42) -> 6478137.7 | E42: =ROUND(C42*umumiy_malumot!$B$84/H42,2)*'График аннуитет.'!G42 -> -3522703.8 | F42: =IF(A42<umumiy_malumot!$B$81,'График аннуитет.'!F41,'График аннуитет.'!D42+'График аннуитет.'!E42) -> 2955433.9 | G42: =B42-B41 -> 30 | H42: =DATE(YEAR(B42),12,31)-DATE(YEAR(B42),1,1)+1 -> 366
A43: =1+A42 -> 36 | B43: ='График дифференц'!B43 -> 47124 | C43: =C42-D42 -> -84618110 | D43: =IF(A43<umumiy_malumot!$B$81,'График аннуитет.'!F43-'График аннуитет.'!E43,'График аннуитет.'!C43) -> -84618110 | E43: =ROUND(C43*umumiy_malumot!$B$84/H43,2)*'График аннуитет.'!G43 -> -2805148.3 | F43: =IF(A43<umumiy_malumot!$B$81,'График аннуитет.'!F42,'График аннуитет.'!D43+'График аннуитет.'!E43) -> -87423258 | G43: =B43-B42 -> 22 | H43: =DATE(YEAR(B43),12,31)-DATE(YEAR(B43),1,1)+1 -> 365
... A55: =1+A54 -> 48 | B55: ='График дифференц'!B55 -> FALSE | C55: =C54-D54 -> 0 | D55: =IF(A55<umumiy_malumot!$B$81,'График аннуитет.'!F55-'График аннуитет.'!E55,'График аннуитет.'!C55) -> 0 | E55: =ROUND(C55*umumiy_malumot!$B$84/H55,2)*'График аннуитет.'!G55 -> 0 | F55: =IF(A55<umumiy_malumot!$B$81,'График аннуитет.'!F54,'График аннуитет.'!D55+'График аннуитет.'!E55) -> 0 | G55: =B55-B54 -> 0 | H55: =DATE(YEAR(B55),12,31)-DATE(YEAR(B55),1,1)+1 -> 366
B56: ИТОГО | D56: =SUM(D8:D43) -> 33000000 | E56: =SUM(E8:E43) -> -16983072 | F56: =SUM(F8:F43) -> 16016928
A58: *В случае осуществления погашения платежей по кредиту в даты, отличные от указанных в графике погашения, сумма платежа меняется на сумму процентов, которые начисляются на сумму остатка долга по микрозайму в соответствии с п.п. 2.2. настоящего договора.
A60: =#REF! -> #REF! | D60: =#REF! -> #REF!
A62: =#REF! -> #REF! | D62: =#REF! -> #REF!
A63: =#REF! -> #REF! | D63: =#REF! -> #REF!
A64: =#REF! -> #REF! | D64: ="паспорт серии "&umumiy_malumot!B16&", "&umumiy_malumot!B20&"" -> паспорт серии AD 6760672, IIV 61013 tomonidan 08.04.2024 yilda berilgan
A65: =#REF! -> #REF!
A66: =#REF! -> #REF! | D66: =#REF! -> #REF!
A67: =#REF! -> #REF! | D67: =#REF! -> #REF!
A68: =#REF! -> #REF! | D68: =#REF! -> #REF!
A70: =#REF! -> #REF! | D70: =#REF! -> #REF!
A72: =#REF! -> #REF! | D72: =#REF! -> #REF!

Sheet shartnoma
A1: =""&umumiy_malumot!C64&" shartnoma "&umumiy_malumot!B66&"" -> Mikroqarz shartnoma №3-BR
A3: ="Toshkent shahri "&umumiy_malumot!B70&"" -> Toshkent shahri 6 yanvar 2026 y.
A5: =""&umumiy_malumot!B147&", bundan buyon «Mikromoliya tashkiloti» deb nomlanuvchi, ishonchnoma asosida xarakat qiluvchi "&umumiy_malumot!A150&" "&umumiy_malumot!B150&" bir tomondan va o‘z manfaati yo‘lida hamda o‘z nomidan harakat qiluvchi O‘zbekiston Respublikasi fuqarosi "&umumiy_malumot!B5&" (pasport raqami "&umumiy_malumot!B16&", "&umumiy_malumot!C20&" ), bundan buyon «Qarz oluvchi» deb nomlanuvchi, boshqa tomondan, birgalikda “Tomonlar” yoki alohida “Tomon” deb nomlanuvchilar, Qarz oluvchi tomonidan "&TEXT(umumiy_malumot!B2,"ДД.ММ.ГГГГ")&" yil,"&umumiy_malumot!B65&" olish uchun ariza berilganligini hisobga olib, ushbu "&umumiy_malumot!C64&" shartnomasini (bundan keyin – «Shartnoma») quyidagilar haqida tuzdilar:" -> «PULLOL BUSINESS MIKROMOLIYA TASHKILOTI» MChJ, bundan buyon «Mikromoliya tashkiloti» deb nomlanuvchi, ishonchnoma asosida xarakat qiluvchi Buxoro filiali boshlig'i IKROMOV B.A. bir tomondan va o‘z manfaati yo‘lida hamda o‘z nomidan harakat qiluvchi O‘zbekiston Respublikasi fuqarosi TURAYEV ISROIL BURIYEVICH (pasport raqami AD 6760672, IIV 61013 tomonidan 08.04.2024 yilda berilgan ), bundan buyon «Qarz oluvchi» deb nomlanuvchi, boshqa tomondan, birgalikda “Tomonlar” yoki alohida “Tomon” deb nomlanuvchilar, Qarz oluvchi tomonidan 06.01.2026 yil,mikroqarz olish uchun ariza berilganligini hisobga olib, ushbu Mikroqarz shartnomasini (bundan keyin – «Shartnoma») quyidagilar haqida tuzdilar:
A7: 1. SHARTNOMA PREDMETI
A8: ="1.1. Mikromoliya tashkiloti Qarz oluvchiga umumiy miqdori "&FIXED(umumiy_malumot!B75,2)&" ("&umumiy_malumot!C76&") bo‘lgan "&umumiy_malumot!B65&"ni "&umumiy_malumot!B71&" dan "&umumiy_malumot!B73&" gacha bo'lgan muddatga naqd pul va/yoki o'tkazmasi shaklida ajratadi." -> 1.1. Mikromoliya tashkiloti Qarz oluvchiga umumiy miqdori 33 000 000,00 (O'ttiz uch million so'm) bo‘lgan mikroqarzni 6 yanvar 2026 y. dan 6 yanvar 2029 y. gacha bo'lgan muddatga naqd pul va/yoki o'tkazmasi shaklida ajratadi.
A9: ="1.2. Qarz oluvchi to‘lovlilik, muddatlilik va ta’minlanganlik tamoyillariga amal qilgan holda "&umumiy_malumot!B65&"dan foydalanish majburiyatini o‘z zimmasiga oladi." -> 1.2. Qarz oluvchi to‘lovlilik, muddatlilik va ta’minlanganlik tamoyillariga amal qilgan holda mikroqarzdan foydalanish majburiyatini o‘z zimmasiga oladi.
A11: ="2. "&umumiy_malumot!D64&" BERISH VA QAYTARISH TARTIBI" -> 2. MIKROQARZ BERISH VA QAYTARISH TARTIBI
A12: ="2.1. Ushbu Shartnomaning 1.1.-bandida ko‘rsatilgan summa miqdoridagi "&umumiy_malumot!B65&" Mikromoliya tashkiloti kassasidan naqd pul shaklida va/yoki plastik kartaga o‘tkazish yuli bilan beriladi." -> 2.1. Ushbu Shartnomaning 1.1.-bandida ko‘rsatilgan summa miqdoridagi mikroqarz Mikromoliya tashkiloti kassasidan naqd pul shaklida va/yoki plastik kartaga o‘tkazish yuli bilan beriladi.
A13: ="2.2. "&umumiy_malumot!C64&" berish ushbu Shartnoma tuzilgan va Qarz oluvchi tomonidan ushbu shartnomaning 3-bo‘limiga muvofiq garov ta'minoti ta'minlangandan so‘ng 10 kalendar kundan kechiktirmay amalga oshiriladi." -> 2.2. Mikroqarz berish ushbu Shartnoma tuzilgan va Qarz oluvchi tomonidan ushbu shartnomaning 3-bo‘limiga muvofiq garov ta'minoti ta'minlangandan so‘ng 10 kalendar kundan kechiktirmay amalga oshiriladi.
A14: ="2.3. "&umumiy_malumot!C64&" Qarz oluvchi tomonidan ushbu Shartnomaning ajralmas qismi hisoblanadigan 1-ilovasida ko‘rsatilgan to‘lov jadvalida (bundan keyin - To‘lov jadvali) belgilangan miqdor, tartib va muddatlarda qaytariladi." -> 2.3. Mikroqarz Qarz oluvchi tomonidan ushbu Shartnomaning ajralmas qismi hisoblanadigan 1-ilovasida ko‘rsatilgan to‘lov jadvalida (bundan keyin - To‘lov jadvali) belgilangan miqdor, tartib va muddatlarda qaytariladi.
A15: ="2.4. Mikromoliya tashkiloti, "&umumiy_malumot!B65&" berilgan vaqtdan boshlab, "&umumiy_malumot!B65&" miqdorining qoldiq summasiga "&umumiy_malumot!B85&"% ("&umumiy_malumot!C86&") foiz yillik va yiliga 365/366 kunlik hisobidan foizlar hisoblaydi. To'lov jadvaliga muvofiq asosiy qarz bo'yicha navbatdagi to'lov buzilgan hollarda, "&"foiz stavkasi oshiriladi va Mikromoliya tashkiloti "&umumiy_malumot!B65&"ning muddati o'tgan asosiy qarz summasiga yillik "&umumiy_malumot!B88&" ("&umumiy_malumot!B89&") foiz miqdorida foizlar hisoblaydi." -> 2.4. Mikromoliya tashkiloti, mikroqarz berilgan vaqtdan boshlab, mikroqarz miqdorining qoldiq summasiga 55% (Ellik besh) foiz yillik va yiliga 365/366 kunlik hisobidan foizlar hisoblaydi. To'lov jadvaliga muvofiq asosiy qarz bo'yicha navbatdagi to'lov buzilgan hollarda, foiz stavkasi oshiriladi va Mikromoliya tashkiloti mikroqarzning muddati o'tgan asosiy qarz summasiga yillik 105 (bir yuz besh) foiz miqdorida foizlar hisoblaydi.
A16: 2.4.1 Qarz oluvchining xisob raqamlaridan shartnomaning 4.1.2 bandida ko‘rsatilgan tartibda yechib olingan pul mablag‘lari yechib olinganidan so‘ng mijoz tomonidan kredit qarzdorligini so‘ndirish uchun bank kassalari orqali to‘langan pul mablag‘lari yoki mijoz tomonidan kredit qarzdorligini so‘ndirish uchun bank kassalari orqali to‘langandan so‘ng qarz oluvchining xisob raqamlaridan shartnomaning 4.1.2 bandida ko‘rsatilgan tartibda yechib olingan pul mablag‘larining bir oylik kredit to‘lovini so‘ndirishga yo‘naltirilgan miqdoridan ortiqcha qismi qarz oluvchining to‘lov amalga oshirilgan kundan boshlab 3 bank ish kuni ichida yo‘llagan arizasiga asosan qarz oluvchiga qaytarilishi mumkun. 2.5. Foizlar To‘lov jadvaliga muvofiq asosiy qarzni qaytarish uchun belgilangan sanada to‘lanadi. 2.5.1 Qarz oluvchi tomonidan shartnomaning 2.4 bandida ko‘rsatilgan muddatda ortiqcha to‘langan pul mablag‘larini qaytarish to‘g‘risida ariza berilmagan taqdirda to‘langan ortiqcha pul mablag‘lari mijozning asosiy qarzdorligini so‘ndirishga yo‘naltiriladi.
A17: =CONCATENATE(C17,H17,I17) -> 2.6 Qarz oluvchi tomonidan to‘lov jadvalida ko‘rsatilgan muddatdan oldin xamda to‘lov jadvalida ko‘rsatilgan oylik kredit qarzdorligini so‘ndirish miqdoridan ko‘p miqdorda to‘lovni amalga oshirib, to‘langan pul mablag‘larini asosiy kredit qarzdorligini so‘ndirishga yo‘naltirilishini so‘ralganda qarz oluvchining kredit qarzdorligini so‘ndirish uchun to‘lagan pul mablag‘laridan kredit qarzdorligi to‘langan oy uchun to‘lov jadvali bo‘yicha so‘ndirilishi lozim bo‘lgan foiz qarzdorligi summasi, to‘lov jadvalida foiz qarzdorligi so‘ndirilishi ko‘rsatilgan muddatga qadar tashkilotning xisob raqamida saqlanib to‘lov jadvalida ko‘rsatilgan sanada oylik foiz qarzdorligini so‘ndirishga yo‘naltiriladi. 2.6.1. Qarz oluvchi tomonidan olingan mikroqarzni va undan foydalanganlik uchun foizlarni qaytarish bo‘yicha muddati o‘tgan qarzdorlik hosil bo‘lganda Qarz oluvchi tomonidan ko‘rsatilgan qarzdorlikni to‘lash hisobiga to‘lanadigan summalar quyidagi tartibda hisobga olinadi: | C17: 2.6 Qarz oluvchi tomonidan to‘lov jadvalida ko‘rsatilgan muddatdan oldin xamda to‘lov jadvalida ko‘rsatilgan oylik kredit qarzdorligini so‘ndirish miqdoridan ko‘p miqdorda to‘lovni amalga oshirib, to‘langan pul mablag‘larini asosiy kredit qarzdorligini so‘ndirishga yo‘naltirilishini so‘ralganda qarz oluvchining kredit qarzdorligini so‘ndirish uchun to‘lagan pul mablag‘laridan kredit qarzdorligi to‘langan oy uchun to‘lov jadvali bo‘yicha so‘ndirilishi lozim bo‘lgan foiz qarzdorligi summasi, to‘lov jadvalida foiz qarzdorligi so‘ndirilishi ko‘rsatilgan muddatga qadar tashkilotning xisob raqamida saqlanib to‘lov jadvalida ko‘rsatilgan sanada oylik foiz qarzdorligini so‘ndirishga yo‘naltiriladi. 2.6.1. Qarz oluvchi tomonidan olingan | H17: =umumiy_malumot!B65 -> mikroqarz | I17: ni va undan foydalanganlik uchun foizlarni qaytarish bo‘yicha muddati o‘tgan qarzdorlik hosil bo‘lganda Qarz oluvchi tomonidan ko‘rsatilgan qarzdorlikni to‘lash hisobiga to‘lanadigan summalar quyidagi tartibda hisobga olinadi:
A18: - jarima sanksiyalarni to‘lash; - to‘lov muddati o‘tgan foizlarni to‘lash; - to‘lov muddati o‘tgan asosiy qarzni to‘lash; - muddatli qarz bo‘yicha hisoblangan foizlarni to‘lash; - muddatli asosiy qarzni to‘lash; - Mikromoliya tashkilotning boshqa zararlarini qoplash.
A19: ="2.7. Qarz oluvchi Mikromoliya tashkilotining "&umumiy_malumot!B65&" bo‘yicha asosiy summasi, hisoblangan foizlarni, penya va boshqa moliyaviy talablarini ham naqd pul shaklida, ham naqdsiz shaklda qaytarib beradi." -> 2.7. Qarz oluvchi Mikromoliya tashkilotining mikroqarz bo‘yicha asosiy summasi, hisoblangan foizlarni, penya va boshqa moliyaviy talablarini ham naqd pul shaklida, ham naqdsiz shaklda qaytarib beradi.
A20: ="2.8. Qarz oluvchi "&umumiy_malumot!B65&" miqdorini muddatidan oldin qaytarish, shuningdek, bu haqida Mikromoliya tashkilotini albatta ogohlantirgan holda ulardan aniq foydalangan muddat uchun hisoblangan foizlarni to‘lash huquqiga ega." -> 2.8. Qarz oluvchi mikroqarz miqdorini muddatidan oldin qaytarish, shuningdek, bu haqida Mikromoliya tashkilotini albatta ogohlantirgan holda ulardan aniq foydalangan muddat uchun hisoblangan foizlarni to‘lash huquqiga ega.
A21: =CONCATENATE(C21,H21,I21) -> 2.9. Qarz oluvchi jismoniy shaxslarning kreditlar (mikroqarzlar) bo‘yicha qarz yukini hisoblash tartibi, qarz yukining ruxsat etilgan miqdori, shuningdek qarz yuki o‘sishini cheklash to‘g‘risidagi Nizomga muvofiq (O’zbekiston Respublikasi Adliya vazirligi tomonidan 19.12.2019 y. 3205-son bilan ro‘yxatga olingan Markaziy bank Boshqaruvining 28.09.2019 y. 24/5-son qarori bilan tasdiqlangan), qarz yuki ko‘rsatkichi har bir qarz oluvchiga qarz beruvchi tomonidan mikroqarz ajratishda uning summasi va qarz oluvchining amaldagi kredit (mikroqarz) shartnomalari bo‘yicha asosiy qarz qoldig‘i yig‘indisi bazaviy hisoblash miqdorining 50 baravaridan oshganda hisoblanadi. | C21: ="2.9. Qarz oluvchi jismoniy shaxslarning kreditlar ("&umumiy_malumot!B65&"lar) bo‘yicha qarz yukini hisoblash tartibi, qarz yukining ruxsat etilgan miqdori, shuningdek qarz yuki o‘sishini cheklash to‘g‘risidagi Nizomga muvofiq (O’zbekiston Respublikasi Adliya vazirligi tomonidan 19.12.2019 y. 3205-son bilan ro‘yxatga " -> 2.9. Qarz oluvchi jismoniy shaxslarning kreditlar (mikroqarzlar) bo‘yicha qarz yukini hisoblash tartibi, qarz yukining ruxsat etilgan miqdori, shuningdek qarz yuki o‘sishini cheklash to‘g‘risidagi Nizomga muvofiq (O’zbekiston Respublikasi Adliya vazirligi tomonidan 19.12.2019 y. 3205-son bilan ro‘yxatga | H21: ="olingan Markaziy bank Boshqaruvining 28.09.2019 y. 24/5-son qarori bilan tasdiqlangan), qarz yuki ko‘rsatkichi har bir qarz oluvchiga qarz beruvchi tomonidan "&umumiy_malumot!B65&" ajratishda uning summasi va " -> olingan Markaziy bank Boshqaruvining 28.09.2019 y. 24/5-son qarori bilan tasdiqlangan), qarz yuki ko‘rsatkichi har bir qarz oluvchiga qarz beruvchi tomonidan mikroqarz ajratishda uning summasi va | I21: ="qarz oluvchining amaldagi kredit ("&umumiy_malumot!B65&") shartnomalari bo‘yicha asosiy qarz qoldig‘i yig‘indisi bazaviy hisoblash miqdorining 50 baravaridan oshganda hisoblanadi." -> qarz oluvchining amaldagi kredit (mikroqarz) shartnomalari bo‘yicha asosiy qarz qoldig‘i yig‘indisi bazaviy hisoblash miqdorining 50 baravaridan oshganda hisoblanadi.
A22: ="3. "&umumiy_malumot!D64&" TA'MINOTI BO‘YICHA " -> 3. MIKROQARZ TA'MINOTI BO‘YICHA
A23: ="3.1. Ushbu Shartnoma bo‘yicha taqdim etilgan "&umumiy_malumot!C64&" quyidagi garov bilan ta'minlanadi:" -> 3.1. Ushbu Shartnoma bo‘yicha taqdim etilgan Mikroqarz quyidagi garov bilan ta'minlanadi:
A24: =IF(umumiy_malumot!B103=umumiy_malumot!C103,shartnoma!A28,IF(umumiy_malumot!B103=umumiy_malumot!D103,shartnoma!A25,0)) -> 3.1.1. Mikromoliya tashkiloti, Qarz oluvchi va USMONOV NURIDDID IXTIYOROVICH (06.01.2026y. sanasidagi reestr raqami №202602386000102 bo'lgan Ishonchnomaga asosan) tomonidan 2026 yil 6 yanvarda imzolangan 1-sonli garov predmeti qiymatini tasdiqlash dalolatnomasiga muvofiq OQ OLIMPIYSKAYA BELAYA rangli, ishlab chiqarilgan yili – 2016 yil, dvigatel raqami B15D211163412DJCX0337, shassi - RAKAMSIZ, kuzov turi - YENGIL SEDAN, kuzov raqami №XWBJF69VEGA010429, davlat raqam belgisi 80G291QA bo'lgan COBALT rusumli avtomashinasi (bundan keyin “Garov predmeti”), egalik huquqiga ega USMONOV NURIDDID IXTIYOROVICHga tegishli va kelishilgan garov qiymati 2026 yil 6 yanvarda imzolangan 1-sonli Garov predmeti qiymatini tasdiqlash dalolatnomasiga muvifiq 46 200 000,00 (qirq olti million ikki yuz ming so'm) so'mni tashkil qiladi. Garov garovining aniq shartlari tegishli notarial rasmiylashtirilgan garov shartnomasi bilan belgilanadi.
A25: =IF(umumiy_malumot!B92=umumiy_malumot!C92,shartnoma!A27,IF(umumiy_malumot!B92=umumiy_malumot!D92,shartnoma!A26,0)) -> 3.1.1. Mikromoliya tashkiloti, Qarz oluvchi va USMONOV NURIDDID IXTIYOROVICH (06.01.2026y. sanasidagi reestr raqami №202602386000102 bo'lgan Ishonchnomaga asosan) tomonidan 2026 yil 6 yanvarda imzolangan 1-sonli Garov predmeti qiymatini tasdiqlash dalolatnomasiga muvofiq SAMARQAND VILOYATI TAYLOQ TUMANI CHAROG'BON MFY YANGI TAYLOQ QISHLOG'I 6 TURAR JOY 12 QAVAT 58 XONADON manzilida joylashgan, yer uchastkasi maydoni - , umumiy maydoni - 72,13, yashash maydoni - 37,39 bo'lgan, 3 - xonali yakka tartibdagi uy-joy ko'rinishidagi ko'chmas mulk (bundan keyin “Garov predmeti”), egalik huquqiga ko'ra 0ga tegishli va kelishilgan garov qiymati 2026 yil 6 yanvarda imzolangan 1-sonli Garov predmeti qiymatini tasdiqlash dalolatnomasiga muvofiq 46 200 000,00 (qirq olti million ikki yuz ming so'm) so'mni tashkil qiladi. Garovning aniq shartlari tegishli tarzda notarial tasdiqlangan garov shartnomasi bilan belgilangan.
A26: ="3.1.1. "&umumiy_malumot!O126&" tomonidan "&umumiy_malumot!B143&" yil "&umumiy_malumot!B145&" "&umumiy_malumot!B144&"da imzolangan 1-sonli navbatdagi garov predmeti qiymatini tasdiqlash dalolatnomasiga muvofiq "&umumiy_malumot!C123&" manzilida joylashgan, "&umumiy_malumot!F126&" bo'lgan, "&umumiy_malumot!F125&" ko'rinishidagi ko'chmas mulk (bundan keyin “navbatdagi garov predmeti”), egalik huquqiga ko'ra "&umumiy_malumot!C117&"ga tegishli va kelishilgan garov qiymati "&umumiy_malumot!B143&" yil "&umumiy_malumot!B145&" "&umumiy_malumot!B144&"da imzolangan 1-sonli Garov predmeti qiymatini tasdiqlash dalolatnomasiga muvofiq "&FIXED(umumiy_malumot!B136,2)&" ("&umumiy_malumot!B138&") so'mni tashkil qiladi. Garovning aniq shartlari tegishli tarzda notarial tasdiqlangan garov shartnomasi bilan belgilangan." -> 3.1.1. Mikromoliya tashkiloti, Qarz oluvchi va USMONOV NURIDDID IXTIYOROVICH (06.01.2026y. sanasidagi reestr raqami №202602386000102 bo'lgan Ishonchnomaga asosan) tomonidan 2026 yil 6 yanvarda imzolangan 1-sonli navbatdagi garov predmeti qiymatini tasdiqlash dalolatnomasiga muvofiq SAMARQAND VILOYATI TAYLOQ TUMANI CHAROG'BON MFY YANGI TAYLOQ QISHLOG'I 6 TURAR JOY 12 QAVAT 58 XONADON manzilida joylashgan, yer uchastkasi maydoni - , umumiy maydoni - 72,13, yashash maydoni - 37,39 bo'lgan, 3 - xonali yakka tartibdagi uy-joy ko'rinishidagi ko'chmas mulk (bundan keyin “navbatdagi garov predmeti”), egalik huquqiga ko'ra 0ga tegishli va kelishilgan garov qiymati 2026 yil 6 yanvarda imzolangan 1-sonli Garov predmeti qiymatini tasdiqlash dalolatnomasiga muvofiq 46 200 000,00 (qirq olti million ikki yuz ming so'm) so'mni tashkil qiladi. Garovning aniq shartlari tegishli tarzda notarial tasdiqlangan garov shartnomasi bilan belgilangan.
A27: ="3.1.1. "&umumiy_malumot!O126&" tomonidan "&umumiy_malumot!B143&" yil "&umumiy_malumot!B145&" "&umumiy_malumot!B144&"da imzolangan 1-sonli Garov predmeti qiymatini tasdiqlash dalolatnomasiga muvofiq "&umumiy_malumot!C123&" manzilida joylashgan, "&umumiy_malumot!F126&" bo'lgan, "&umumiy_malumot!F125&" ko'rinishidagi ko'chmas mulk (bundan keyin “Garov predmeti”), egalik huquqiga ko'ra "&umumiy_malumot!C117&"ga tegishli va kelishilgan garov qiymati "&umumiy_malumot!B143&" yil "&umumiy_malumot!B145&" "&umumiy_malumot!B144&"da imzolangan 1-sonli Garov predmeti qiymatini tasdiqlash dalolatnomasiga muvofiq "&FIXED(umumiy_malumot!B136,2)&" ("&umumiy_malumot!B138&") so'mni tashkil qiladi. Garovning aniq shartlari tegishli tarzda notarial tasdiqlangan garov shartnomasi bilan belgilangan." -> 3.1.1. Mikromoliya tashkiloti, Qarz oluvchi va USMONOV NURIDDID IXTIYOROVICH (06.01.2026y. sanasidagi reestr raqami №202602386000102 bo'lgan Ishonchnomaga asosan) tomonidan 2026 yil 6 yanvarda imzolangan 1-sonli Garov predmeti qiymatini tasdiqlash dalolatnomasiga muvofiq SAMARQAND VILOYATI TAYLOQ TUMANI CHAROG'BON MFY YANGI TAYLOQ QISHLOG'I 6 TURAR JOY 12 QAVAT 58 XONADON manzilida joylashgan, yer uchastkasi maydoni - , umumiy maydoni - 72,13, yashash maydoni - 37,39 bo'lgan, 3 - xonali yakka tartibdagi uy-joy ko'rinishidagi ko'chmas mulk (bundan keyin “Garov predmeti”), egalik huquqiga ko'ra 0ga tegishli va kelishilgan garov qiymati 2026 yil 6 yanvarda imzolangan 1-sonli Garov predmeti qiymatini tasdiqlash dalolatnomasiga muvofiq 46 200 000,00 (qirq olti million ikki yuz ming so'm) so'mni tashkil qiladi. Garovning aniq shartlari tegishli tarzda notarial tasdiqlangan garov shartnomasi bilan belgilangan.
A28: =IF(umumiy_malumot!B92=umumiy_malumot!C92,A29,IF(umumiy_malumot!B92=umumiy_malumot!D92,A30,0)) -> 3.1.1. Mikromoliya tashkiloti, Qarz oluvchi va USMONOV NURIDDID IXTIYOROVICH (06.01.2026y. sanasidagi reestr raqami №202602386000102 bo'lgan Ishonchnomaga asosan) tomonidan 2026 yil 6 yanvarda imzolangan 1-sonli garov predmeti qiymatini tasdiqlash dalolatnomasiga muvofiq OQ OLIMPIYSKAYA BELAYA rangli, ishlab chiqarilgan yili – 2016 yil, dvigatel raqami B15D211163412DJCX0337, shassi - RAKAMSIZ, kuzov turi - YENGIL SEDAN, kuzov raqami №XWBJF69VEGA010429, davlat raqam belgisi 80G291QA bo'lgan COBALT rusumli avtomashinasi (bundan keyin “Garov predmeti”), egalik huquqiga ega USMONOV NURIDDID IXTIYOROVICHga tegishli va kelishilgan garov qiymati 2026 yil 6 yanvarda imzolangan 1-sonli Garov predmeti qiymatini tasdiqlash dalolatnomasiga muvifiq 46 200 000,00 (qirq olti million ikki yuz ming so'm) so'mni tashkil qiladi. Garov garovining aniq shartlari tegishli notarial rasmiylashtirilgan garov shartnomasi bilan belgilanadi.
A29: ="3.1.1. "&umumiy_malumot!O126&" tomonidan "&umumiy_malumot!B143&" yil "&umumiy_malumot!B145&" "&umumiy_malumot!B144&"da imzolangan 1-sonli garov predmeti qiymatini tasdiqlash dalolatnomasiga muvofiq "&umumiy_malumot!B134&" rangli, ishlab chiqarilgan yili – "&umumiy_malumot!B135&" yil, dvigatel raqami "&umumiy_malumot!B131&", shassi - "&umumiy_malumot!B132&", kuzov turi - "&umumiy_malumot!B128&", kuzov raqami №"&umumiy_malumot!B129&", davlat raqam belgisi "&umumiy_malumot!B126&" bo'lgan "&umumiy_malumot!B125&" rusumli avtomashinasi (bundan keyin “Garov predmeti”), egalik huquqiga ega "&umumiy_malumot!B117&"ga tegishli va kelishilgan garov qiymati "&umumiy_malumot!B143&" yil "&umumiy_malumot!B145&" "&umumiy_malumot!B144&"da imzolangan 1-sonli Garov predmeti qiymatini tasdiqlash dalolatnomasiga muvifiq "&FIXED(umumiy_malumot!B136,2)&" ("&umumiy_malumot!B138&") so'mni tashkil qiladi. Garov garovining aniq shartlari tegishli notarial rasmiylashtirilgan garov shartnomasi bilan belgilanadi." -> 3.1.1. Mikromoliya tashkiloti, Qarz oluvchi va USMONOV NURIDDID IXTIYOROVICH (06.01.2026y. sanasidagi reestr raqami №202602386000102 bo'lgan Ishonchnomaga asosan) tomonidan 2026 yil 6 yanvarda imzolangan 1-sonli garov predmeti qiymatini tasdiqlash dalolatnomasiga muvofiq OQ OLIMPIYSKAYA BELAYA rangli, ishlab chiqarilgan yili – 2016 yil, dvigatel raqami B15D211163412DJCX0337, shassi - RAKAMSIZ, kuzov turi - YENGIL SEDAN, kuzov raqami №XWBJF69VEGA010429, davlat raqam belgisi 80G291QA bo'lgan COBALT rusumli avtomashinasi (bundan keyin “Garov predmeti”), egalik huquqiga ega USMONOV NURIDDID IXTIYOROVICHga tegishli va kelishilgan garov qiymati 2026 yil 6 yanvarda imzolangan 1-sonli Garov predmeti qiymatini tasdiqlash dalolatnomasiga muvifiq 46 200 000,00 (qirq olti million ikki yuz ming so'm) so'mni tashkil qiladi. Garov garovining aniq shartlari tegishli notarial rasmiylashtirilgan garov shartnomasi bilan belgilanadi.
A30: ="3.1.1. "&umumiy_malumot!O126&" tomonidan "&umumiy_malumot!B143&" yil "&umumiy_malumot!B145&" "&umumiy_malumot!B144&"da imzolangan 1-sonli navbatdagi garov predmeti qiymatini tasdiqlash dalolatnomasiga muvofiq "&umumiy_malumot!B134&" rangli, ishlab chiqarilgan yili – "&umumiy_malumot!B135&" yil, dvigatel raqami "&umumiy_malumot!B131&", shassi - "&umumiy_malumot!B132&", kuzov turi - "&umumiy_malumot!B128&", kuzov raqami №"&umumiy_malumot!B129&", davlat raqam belgisi "&umumiy_malumot!B126&" bo'lgan "&umumiy_malumot!B125&" rusumli avtomashinasi (bundan keyin “navbatdagi garov predmeti”), egalik huquqiga ega "&umumiy_malumot!B117&"ga tegishli va kelishilgan garov qiymati "&umumiy_malumot!B143&" yil "&umumiy_malumot!B145&" "&umumiy_malumot!B144&"da imzolangan 1-sonli Garov predmeti qiymatini tasdiqlash dalolatnomasiga muvifiq "&FIXED(umumiy_malumot!B136,2)&" ("&umumiy_malumot!B138&") so'mni tashkil qiladi. Garov garovining aniq shartlari tegishli notarial rasmiylashtirilgan garov shartnomasi bilan belgilanadi." -> 3.1.1. Mikromoliya tashkiloti, Qarz oluvchi va USMONOV NURIDDID IXTIYOROVICH (06.01.2026y. sanasidagi reestr raqami №202602386000102 bo'lgan Ishonchnomaga asosan) tomonidan 2026 yil 6 yanvarda imzolangan 1-sonli navbatdagi garov predmeti qiymatini tasdiqlash dalolatnomasiga muvofiq OQ OLIMPIYSKAYA BELAYA rangli, ishlab chiqarilgan yili – 2016 yil, dvigatel raqami B15D211163412DJCX0337, shassi - RAKAMSIZ, kuzov turi - YENGIL SEDAN, kuzov raqami №XWBJF69VEGA010429, davlat raqam belgisi 80G291QA bo'lgan COBALT rusumli avtomashinasi (bundan keyin “navbatdagi garov predmeti”), egalik huquqiga ega USMONOV NURIDDID IXTIYOROVICHga tegishli va kelishilgan garov qiymati 2026 yil 6 yanvarda imzolangan 1-sonli Garov predmeti qiymatini tasdiqlash dalolatnomasiga muvifiq 46 200 000,00 (qirq olti million ikki yuz ming so'm) so'mni tashkil qiladi. Garov garovining aniq shartlari tegishli notarial rasmiylashtirilgan garov shartnomasi bilan belgilanadi.
A31: =CONCATENATE(A32,B32) -> 3.2. Qonun hujjatlariga muvofiq rasmiylashtirilgan, “Garov predmeti” hisoblangan notarial tasdiqlangan garov shartnomasi, shu jumladan “Garov predmeti”ga taʼqiq quyilganligi tasdiqlovchi xujjat Qarz oluvchi tomonidan ushbu shartnoma tuzilgandan so‘ng 10 bank kuni mobaynida Mikromoliya tashkilotiga taqdim etilishi lozim. Garov shartnomasi belgilangan muddatda taqdim etilmagan hollarda, Mikromoliya tashkiloti Qarz oluvchining manziliga yozma bildirishnoma yuborish orqali mikroqarz berishni rad etish va / yoki ushbu shartnomani bir tomonlama bekor qilish huquqiga egadir. Bunda ushbu shartnoma Qarz oluvchi tomonidan talabnoma olingan vaqtda yoki talabnoma pochta xizmati orqali yuborilgandan keyin uchinchi kuni bekor qilingan hisoblanadi.
A32: 3.2. Qonun hujjatlariga muvofiq rasmiylashtirilgan, “Garov predmeti” hisoblangan notarial tasdiqlangan garov shartnomasi, shu jumladan “Garov predmeti”ga taʼqiq quyilganligi tasdiqlovchi xujjat Qarz oluvchi tomonidan ushbu shartnoma tuzilgandan so‘ng 10 bank kuni mobaynida | B32: =CONCATENATE(A33,B33) -> Mikromoliya tashkilotiga taqdim etilishi lozim. Garov shartnomasi belgilangan muddatda taqdim etilmagan hollarda, Mikromoliya tashkiloti Qarz oluvchining manziliga yozma bildirishnoma yuborish orqali mikroqarz berishni rad etish va / yoki ushbu shartnomani bir tomonlama bekor qilish huquqiga egadir. Bunda ushbu shartnoma Qarz oluvchi tomonidan talabnoma olingan vaqtda yoki talabnoma pochta xizmati orqali yuborilgandan keyin uchinchi kuni bekor qilingan hisoblanadi.
A33: =" Mikromoliya tashkilotiga taqdim etilishi lozim. Garov shartnomasi belgilangan muddatda taqdim etilmagan hollarda, Mikromoliya tashkiloti Qarz oluvchining manziliga yozma bildirishnoma yuborish orqali "&umumiy_malumot!B65&"" -> Mikromoliya tashkilotiga taqdim etilishi lozim. Garov shartnomasi belgilangan muddatda taqdim etilmagan hollarda, Mikromoliya tashkiloti Qarz oluvchining manziliga yozma bildirishnoma yuborish orqali mikroqarz | B33: berishni rad etish va / yoki ushbu shartnomani bir tomonlama bekor qilish huquqiga egadir. Bunda ushbu shartnoma Qarz oluvchi tomonidan talabnoma olingan vaqtda yoki talabnoma pochta xizmati orqali yuborilgandan keyin uchinchi kuni bekor qilingan hisoblanadi.
A34: 3.3. Asosiy qarzni, foizlar yoki ushbu shartnoma bo‘yicha belgilangan muddatdan kechiktirilganligi bo‘yicha penyalarni qaytarish muddati kechiktirilishi yuzaga kelganda va/yoki ushbu shartnoma bo‘yicha boshqa majburiyatlar buzilishi holatlarida Mikromoliya tashkiloti O‘zbekiston Respublikasining amaldagi qonunchiligiga muvofiq qarzni undirish uchun qaytarib olinmaydigan va muqarrar tartibda unidirishni garov ob'ektiga qaratish huquqiga ega bo‘ladi.
A35: 3.4. O‘zbekiston Respublikasi "Garov to‘g‘risida" gi Qonunining 27-moddasiga muvofiq Garov predmeti sug‘urtalanmaydi. Lekin Mikromoliya tashkiloti Qarz oluvchidan Mikromoliya tashkiloti foydasiga Garov obʼektini ushbu Shartnomaning to‘liq amal qilish muddatiga har turli xavflardan sug‘urta qilishni talab qilish huquqiga ega. Bunda, sug‘urta xavflari ro‘yxati, shuningdek, sug‘urta kompaniyasi Mikromoliya tashkilotining xohishiga ko‘ra belgilanadi. Sug‘urta hodisasi yuz berganda Foyda oluvchi Mikromoliya tashkiloti bo‘lishi kerak.
A37: 4. MIKROMOLIYA TASHKILOTINING HUQUQ VA MAJBURIYATLARI
A38: 4.1. Mikromoliya tashkiloti quyidagi huquqlarga ega:
A39: =CONCATENATE(C39,H39) -> 4.1.1. Ushbu Shartnomada ko‘rsatilgan asoslar bo‘yicha Qarz oluvchiga Shartnomada ko‘zda tutilgan mikroqarz summasini berilishini to‘liq yoki qisman rad etish. 4.1.2 “Mikromoliya Tashkiloti” qarz oluvchining nomidagi barcha plastik kartalaridan, xozirgi kunda mavjud va bundan so‘ng ochiladigan barcha xisob raqamlaridan (talab qilib olguncha, depozit jamg‘arib boriladigan plastik va boshqa istalgan xisob raqamlaridan) kredit to‘lovini kredit qaytarish jadvaliga asosan oyning kredit qarzdorligi qaytarilishi ko‘rsatilgan kuni akseptsiz tarzda yechib olish xuquqiga ega. | C39: ="4.1.1. Ushbu Shartnomada ko‘rsatilgan asoslar bo‘yicha Qarz oluvchiga Shartnomada ko‘zda tutilgan "&umumiy_malumot!B65&"" -> 4.1.1. Ushbu Shartnomada ko‘rsatilgan asoslar bo‘yicha Qarz oluvchiga Shartnomada ko‘zda tutilgan mikroqarz | H39: summasini berilishini to‘liq yoki qisman rad etish. 4.1.2 “Mikromoliya Tashkiloti” qarz oluvchining nomidagi barcha plastik kartalaridan, xozirgi kunda mavjud va bundan so‘ng ochiladigan barcha xisob raqamlaridan (talab qilib olguncha, depozit jamg‘arib boriladigan plastik va boshqa istalgan xisob raqamlaridan) kredit to‘lovini kredit qaytarish jadvaliga asosan oyning kredit qarzdorligi qaytarilishi ko‘rsatilgan kuni akseptsiz tarzda yechib olish xuquqiga ega.
A40: ="4.1.2.1. "&umumiy_malumot!C64&" bo‘yicha qolgan barcha qarzdorlik, foiz to‘lovlarining muddatidan oldin qaytarilishini talab qilish, shuningdek, quyidagi holatlardan biri yuzaga kelganda undirishni garov ta'minotiga qaratish:" -> 4.1.2.1. Mikroqarz bo‘yicha qolgan barcha qarzdorlik, foiz to‘lovlarining muddatidan oldin qaytarilishini talab qilish, shuningdek, quyidagi holatlardan biri yuzaga kelganda undirishni garov ta'minotiga qaratish:
A41: a) ta'minotisiz qarzdorlik yuzaga kelganda;
A42: ="b) "&umumiy_malumot!B65&" summasiga hisoblanadigan asosiy qarz bo‘yicha muddati o‘tgan qarzdorlik va/yoki foizlarning yuzaga kelishi;" -> b) mikroqarz summasiga hisoblanadigan asosiy qarz bo‘yicha muddati o‘tgan qarzdorlik va/yoki foizlarning yuzaga kelishi;
A43: с) Qarz oluvchini qonun hujjatlarida belgilangan tartibda to‘lov qobiliyatiga ega emas, muomalaga layoqatli emas yoki muomalaga layoqati cheklangan deb e'lon qilish;
A44: d) Mikromoliya tashkilotiga ushbu Shartnomaning 3.1.-bandida ko‘zda tutilgan hisobotlar, axborotlar va boshqa ma'lumotlarni o‘z vaqtida taqdim etmaslik, shuningdek, moliya-xo‘jalik faoliyat va daromad to‘g‘risidagi hisobotning ishonchsizligi holatlari aniqlanganda;
A45: e) Qarz oluvchi tomonidan ushbu shartnoma shartlariga amal qilmaslik;
A46: ="f) Qarz oluvchi "&umumiy_malumot!B65&" summasini olish uchun Mikromoliya tashkilotiga "&umumiy_malumot!B65&" taqdim etilishi to‘g‘risida ijobiy qaror qabul qilinishi uchun muhim hisoblangan masalalar bo‘yicha yolg‘on yoki to‘liq bo‘lmagan ma'lumotlarni taqdim etganligi aniqlanganda." -> f) Qarz oluvchi mikroqarz summasini olish uchun Mikromoliya tashkilotiga mikroqarz taqdim etilishi to‘g‘risida ijobiy qaror qabul qilinishi uchun muhim hisoblangan masalalar bo‘yicha yolg‘on yoki to‘liq bo‘lmagan ma'lumotlarni taqdim etganligi aniqlanganda.
A47: 4.1.3. Ushbu shartnomaning amal qilish jarayonida Qarz oluvchining moliyaviy holatini tekshirish va Qarz oluvchi tomonidan o‘z zimmasiga olgan majburiyatlarning bajarilishini nazorat qilish.
A48: 4.1.4. Qarz oluvchi tomonidan yoki ushbu Shartnoma bo‘yicha uchinchi shaxs tomonidan ta'minot sifatida garovga qo‘yilgan mol-mulkning tegishli holatdaligi va ulardan foydalanish bo‘yicha tekshiruvlar o‘tkazish.
A49: 4.1.5. Garovga qo‘yuvchi tomonidan garovga qo‘yilgan mol-mulk buzilgan yoki belgilangan maqsadda foydalanish uchun yaroqsiz holga kelganda, bu esa Mikromoliya tashkilotining ushbu Shartnoma bo‘yicha moliyaviy talablarini qondirishga qodir bo‘lgan bozor qiymatiga ma'lum darajada ta'sir ko‘rsatganda, yoki uchinchi shaxsning (kafil) moliyaviy holatining yomonlashuvi sababli ushbu Shartnomadan kelib chiqqan majburiyatlar bo‘yicha javob berish qobiliyatiga ega bo‘lmay qolgan holatlarda Qarz oluvchidan ta'minotning qo‘shimcha turini taqdim etish yoki almashtirishni talab qilish.
A50: 4.1.6. Qonun hujjatlariga muvofiq, Qarz oluvchi tomonidan ushbu Shartnoma bo‘yicha asosiy qarz, foizlar, penya va boshqa pul majburiyatlarini o‘z vaqtida to‘lamaslik holatlarida Qarz oluvchining bank hisobvaraqlaridagi pul mablag‘larini akseptsiz tartibda yechib olish to‘g‘risida to‘lov talabnomasini berish va bunga Qarz oluvchi qaytarib olinmaydigan va so‘zsiz rozilik bildiradi.
A51: ="4.1.7. Qarz oluvchini oldindan ogohlantirmasdan "&umumiy_malumot!B65&"ni qaytarish uchun haqiqatdan ham garov ta'minoti mavjudligini tekshirishni amalga oshirish." -> 4.1.7. Qarz oluvchini oldindan ogohlantirmasdan mikroqarzni qaytarish uchun haqiqatdan ham garov ta'minoti mavjudligini tekshirishni amalga oshirish.
A52: 4.1.8. Ushbu shartnoma doirasida o‘z majburiyatlarini bajarish uchun uchinchi shaxslarga barcha zarur ma'lumotlarni yetkazish.
A53: 4.1.9. Istalgan vaqtda Qarz oluvchining avvaldan roziligini olmasdan turib ushbu Shartnoma bo‘yicha uchinchi tomonga da'vo qilish huquqini berish yoki uning foydasiga voz kechish.
A54: =CONCATENATE(C54,H54) -> 4.1.10. Qarz oluvchi taqdim etilgan mikroqarzdan Shartnoma tuzilgan kundan boshlab 1 (bir) oy davomida foydalanmagan holatlarda, bu haqda Qarz oluvchini yozma ravishda xabardor qilib, Shartnoma bir tomonlama bekor qilish. Yozma xabarni jo‘natish sanasi uni taqdim etish yoki pochta orqali jo‘natish sanasi hisoblanadi. | C54: ="4.1.10. Qarz oluvchi taqdim etilgan "&umumiy_malumot!B65&"dan Shartnoma tuzilgan kundan boshlab 1 (bir) oy davomida foydalanmagan" -> 4.1.10. Qarz oluvchi taqdim etilgan mikroqarzdan Shartnoma tuzilgan kundan boshlab 1 (bir) oy davomida foydalanmagan | H54: holatlarda, bu haqda Qarz oluvchini yozma ravishda xabardor qilib, Shartnoma bir tomonlama bekor qilish. Yozma xabarni jo‘natish sanasi uni taqdim etish yoki pochta orqali jo‘natish sanasi hisoblanadi.
A55: ="4.1.11. Oldingi "&umumiy_malumot!B65&" to‘liq to‘lanmagunga qadar yangi "&umumiy_malumot!B65&" berishni rad etish." -> 4.1.11. Oldingi mikroqarz to‘liq to‘lanmagunga qadar yangi mikroqarz berishni rad etish.
A57: 5. QARZ OLUVCHINING HUQUQ VA MAJBURIYATLARI
A58: 5.1. Qarz oluvchi quyidagi huquqlarga ega:
A59: ="5.1.1. Ushbu shartnomada nazarda tutilgan shartlar bo‘yicha "&umumiy_malumot!B65&" olish, shuningdek, Mikromoliya tashkiloti tomonidan ko‘rsatiladigan pullik xizmatlardan foydalanish." -> 5.1.1. Ushbu shartnomada nazarda tutilgan shartlar bo‘yicha mikroqarz olish, shuningdek, Mikromoliya tashkiloti tomonidan ko‘rsatiladigan pullik xizmatlardan foydalanish.
A60: ="5.1.2. Shartnoma tuzilgan kundan boshlab 2 (ikki) hafta mobaynida Mikromoliya tashkilotiga bu haqda yozma xabarnoma yo‘llash orqali "&umumiy_malumot!B65&"ning foydalanilmagan summasidan voz kechish." -> 5.1.2. Shartnoma tuzilgan kundan boshlab 2 (ikki) hafta mobaynida Mikromoliya tashkilotiga bu haqda yozma xabarnoma yo‘llash orqali mikroqarzning foydalanilmagan summasidan voz kechish.
A61: ="5.1.3. "&umumiy_malumot!C64&" xizmatlari ko‘rsatish qoidalari bilan tanishish." -> 5.1.3. Mikroqarz xizmatlari ko‘rsatish qoidalari bilan tanishish.
A62: ="5.1.4. O‘z huquq va majburiyatlari, shu jumladan "&umumiy_malumot!B65&" xizmatlari ko‘rsatish bilan bog‘liq barcha xarajatlar haqida aniq va to‘liq ma'lumot olish." -> 5.1.4. O‘z huquq va majburiyatlari, shu jumladan mikroqarz xizmatlari ko‘rsatish bilan bog‘liq barcha xarajatlar haqida aniq va to‘liq ma'lumot olish.
A63: 5.1.5. Shartnoma bo‘yicha Mikromoliya tashkilotining majburiyatlarini bajarmaslik yoki tegishli darajada bajarmaslik natijasida yuzaga kelgan zararlarni qoplashni talab qilish.
A64: 5.2. Qarz oluvchining majburiyatlari:
A65: ="5.2.1. Mikromoliya tashkilotining birinchi talabi bilan zarur hujjatlar, shuningdek "&umumiy_malumot!B65&"dan foydalanishning butun davri davomida uning moliyaviy holati va to‘lash qobiliyatiga tegishli bo‘lgan ma'lumotlarni taqdim etish." -> 5.2.1. Mikromoliya tashkilotining birinchi talabi bilan zarur hujjatlar, shuningdek mikroqarzdan foydalanishning butun davri davomida uning moliyaviy holati va to‘lash qobiliyatiga tegishli bo‘lgan ma'lumotlarni taqdim etish.
A66: 5.2.2. Ushbu shartnomada nazarda tutilgan hollarda garov ta'minotini almashtirish yoki qo‘shimcha ta'minot turini taqdim etish bo‘yicha Mikromoliya tashkiloti talablarini bajarish.
A67: ="5.2.3. To‘lov jadvaliga muvofiq "&umumiy_malumot!B65&", shuningdek hisoblangan foizlar to‘lovlarini amalga oshirish." -> 5.2.3. To‘lov jadvaliga muvofiq mikroqarz, shuningdek hisoblangan foizlar to‘lovlarini amalga oshirish.
A68: =CONCATENATE(C68,H68) -> 5.2.4. Mikromoliya tashkiloti vakillariga o‘zlarining moliyaviy holati, yashash joyini tekshirishga, Mikromoliya tashkiloti foydasiga garovga qo‘yilgan mol-mulk saqlanishini tekshirishga ruxsat berish, shuningdek Qarz oluvchi ob'ektlaridan istalganiga tashrif buyurish va har qanday bino, inshoot, mol-mulk, asbob-uskunalar, tovarlar va xizmatlar, shuningdek ularning mikroqarz mablag‘lari hisobiga moliyalashtirilgan hujjatlarni ko‘zdan kechirish va Mikromoliya tashkiloti tomonidan ushbu huquqni amalga oshirishga to‘sqinlik qilmaslik majburiyatini oladi. | C68: 5.2.4. Mikromoliya tashkiloti vakillariga o‘zlarining moliyaviy holati, yashash joyini tekshirishga, Mikromoliya tashkiloti foydasiga garovga qo‘yilgan mol-mulk saqlanishini tekshirishga ruxsat berish, shuningdek Qarz oluvchi ob'ektlaridan istalganiga tashrif buyurish va har qanday bino, inshoot, mol-mulk, asbob-uskunalar, tovarlar va xizmatlar, shuningdek ularning | H68: =" "&umumiy_malumot!B65&" mablag‘lari hisobiga moliyalashtirilgan hujjatlarni ko‘zdan kechirish va Mikromoliya tashkiloti tomonidan ushbu huquqni amalga oshirishga to‘sqinlik qilmaslik majburiyatini oladi." -> mikroqarz mablag‘lari hisobiga moliyalashtirilgan hujjatlarni ko‘zdan kechirish va Mikromoliya tashkiloti tomonidan ushbu huquqni amalga oshirishga to‘sqinlik qilmaslik majburiyatini oladi.
A69: 5.2.5. Qarz oluvchining moliyaviy ahvoli yomonlashuvi va ushbu shartnoma bo‘yicha Qarz oluvchining Mikromoliya tashkiloti oldidagi majburiyatlarining bajarilmasligi va/yoki tegishli darajada bajarilmaslik xavfi yuzaga kelishiga olib keluvchi hech qanday majburiyat va choralarni o‘z zimmasiga olmaslik;
A70: ="5.2.6. Quyidagi holatlarda Mikromoliya tashkilotning birinchi talabi bilan "&umumiy_malumot!B65&" qaytarilishi bo‘yicha qo‘shimcha garov ta'minotini taqdim etish: " -> 5.2.6. Quyidagi holatlarda Mikromoliya tashkilotning birinchi talabi bilan mikroqarz qaytarilishi bo‘yicha qo‘shimcha garov ta'minotini taqdim etish:
A71: - Qarz oluvchining moliyaviy holatining yomonlashuvi; - Garov ob'ekti va/yoki uning bir qismining yo‘q qilinishi, qiymatining pasayishi, qisman yoki to‘liq yo‘qotilishi; - qarz qaytarilmaslik xavfini ko‘paytiruvchi boshqa omillarning paydo bo‘lishi;
A72: ="5.2.7. Sud qarori asosida Qarz oluvchi – jismoniy shaxsning muomalaga layoqatsizligi yoki muomalaga layoqati cheklangan yoxud to‘lash qobiliyatiga ega emasligi (bankrotligi) tan olinganda, uning vasiysi yoki homiysi "&umumiy_malumot!B65&"ning asosiy summa bo‘yicha qarzdorlikni "&umumiy_malumot!B65&"dan aniq foydalanish muddati uchun foizlar bilan kechiktirmasdan to‘liq to‘lashi shart." -> 5.2.7. Sud qarori asosida Qarz oluvchi – jismoniy shaxsning muomalaga layoqatsizligi yoki muomalaga layoqati cheklangan yoxud to‘lash qobiliyatiga ega emasligi (bankrotligi) tan olinganda, uning vasiysi yoki homiysi mikroqarzning asosiy summa bo‘yicha qarzdorlikni mikroqarzdan aniq foydalanish muddati uchun foizlar bilan kechiktirmasdan to‘liq to‘lashi shart.
A73: ="5.2.8. Mikromoliya tashkilotining "&umumiy_malumot!B65&" umumiy summasi va hisoblangan foizlarni muddatidan oldin qaytarish to‘g‘risidagi talabini kechiktirmasdan bajarish." -> 5.2.8. Mikromoliya tashkilotining mikroqarz umumiy summasi va hisoblangan foizlarni muddatidan oldin qaytarish to‘g‘risidagi talabini kechiktirmasdan bajarish. | H73: "&'Общие данные'!B59&"
A74: =CONCATENATE(C74,H74) -> 5.2.9. Mikromoliya tashkilotining talabi bo‘yicha Mikromoliya tashkiloti ko‘rgan, shu jumladan mikroqarz bo‘yicha (asosiy qarz, foizlar va boshqalar) qarzdorlikni majburiy va/yoki muddatidan oldin qaytarish bo‘yicha qabul qilingan choralar bilan bog‘liq bo‘lgan barcha xarajatlari va zararlarni qoplash, shuningdek ushbu shartnoma doirasida unidruvni taqdim etilgan garov ta'minotiga qaratish. | C74: ="5.2.9. Mikromoliya tashkilotining talabi bo‘yicha Mikromoliya tashkiloti ko‘rgan, shu jumladan "&umumiy_malumot!B65&" bo‘yicha (asosiy qarz, foizlar va boshqalar)" -> 5.2.9. Mikromoliya tashkilotining talabi bo‘yicha Mikromoliya tashkiloti ko‘rgan, shu jumladan mikroqarz bo‘yicha (asosiy qarz, foizlar va boshqalar) | H74: qarzdorlikni majburiy va/yoki muddatidan oldin qaytarish bo‘yicha qabul qilingan choralar bilan bog‘liq bo‘lgan barcha xarajatlari va zararlarni qoplash, shuningdek ushbu shartnoma doirasida unidruvni taqdim etilgan garov ta'minotiga qaratish.
A76: 6. TOMONLARNING JAVOBGARLIGI
A77: =CONCATENATE(C77,H77) -> 6.1. Mikromoliya tashkiloti tomonidan Qarz oluvchiga pul mablag‘larini ajratib berish bo‘yicha o‘z zimmasiga olgan majburiyatlarning Shartnomaning 1.1.-bandida keltirilgan summa va muddatlarda bajarilmaslik yoki tegishli tarzda bajarilmaslik holatlarida Mikromoliya tashkiloti muddatidan o‘tgan har bir kalendar kun uchun kechiktirilgan to‘lov summasining 0,1% miqdorida, biroq ushbu Shartnomaning 1.1.-bandida ko‘rsatilgan mikroqarz miqdori umumiy summasining 50% dan ko‘p bo‘lmagan miqdorda penya ko‘rinishidagi neustoyka to‘lash majburiyatini o‘z zimmasiga oladi. | C77: 6.1. Mikromoliya tashkiloti tomonidan Qarz oluvchiga pul mablag‘larini ajratib berish bo‘yicha o‘z zimmasiga olgan majburiyatlarning Shartnomaning 1.1.-bandida keltirilgan summa va muddatlarda bajarilmaslik yoki tegishli tarzda bajarilmaslik holatlarida Mikromoliya tashkiloti muddatidan o‘tgan har bir kalendar kun uchun kechiktirilgan to‘lov summasining 0,1% miqdorida, biroq ushbu Shartnomaning 1.1.-bandida ko‘rsatilgan | H77: =""&umumiy_malumot!B65&" miqdori umumiy summasining 50% dan ko‘p bo‘lmagan miqdorda penya ko‘rinishidagi neustoyka to‘lash majburiyatini o‘z zimmasiga oladi." -> mikroqarz miqdori umumiy summasining 50% dan ko‘p bo‘lmagan miqdorda penya ko‘rinishidagi neustoyka to‘lash majburiyatini o‘z zimmasiga oladi.
A78: 6.2. Jarima sanksiyalarni to‘lash Tomonlarni ushbu Shartnomada ko‘zda tutilgan zimmalaridagi majburiyatlarini bajarishdan ozod qilmaydi.
A79: 6.3. Tomonlarning ushbu Shartnomada nazarda tutilmagan javobgarligi O‘zbekiston Respublikasining amaldagi qonunchiligiga muvofiq belgilanadi.
A80: 6.4. Tomonlar O‘zbekiston Respublikasi Fuqarolik kodeksining 325-moddasiga muvofiq aybdor tomondan yetkazilgan zararni neustoykadan tashqari to‘la hajmda undirish huquqiga egadirlar.
A82: 7. FORS-MAJOR
A83: 7.1. Agar Tomonlar ular zimmasidagi majburiyatlarni tegishli darajada bajarishi yengib bo‘lmas kuch (fors-major) oqibatida mumkin bo‘lmay qolgan bo‘lsa, ya'ni aniq vaqt davri davomida aniq sharoitlarda favqulodda va oldini olib bo‘lmaydigan holatlar ekanligini isbotlay olmasalar, Shartnoma bo‘yicha o‘z majburiyatlarini bajarmagan yoki tegishli darajada bajarmagan Tomon uning shartlarini bajarishda javobgar hisoblanadi. Ushbu Shartnoma Tomonlari yengilmas kuch holatlariga quyidagilarni kiritadi: tabiiy ofat (zilzila, suv toshqini, chaqmoq chaqishi, vulqon otilishi, sel kelishi, ko‘chki, sunami va hokazo), Shartnoma bo‘yicha majburiyatlar bajarilish joyida temperatura – harorat, shamol kuchi va yog‘ingarchilik darajasining inson hayotiy faoliyati normasidan ortiq bo‘lishi; hokimiyat va boshqaruv organlari moratoriysi; qonuniy belgilangan tartibda tashkil etilgan ish tashlashlar va majburiyatlarning tegishli darajada bajarilishi uchun Shartnoma Tomonlari tarafidan yengib bo‘lmas kuch sifatida belgilangan boshqa holatlar.
A84: 7.2. Fors-major holati ta'sirida qolgan Tomon, bunday holatlar yuzaga kelgan kundan boshlab 7 (etti) kalendar kundan kechiktirmasdan boshqa Tomonni xabardor qilishi shart.
A85: 7.3. Fors-major holati boshlanganligi to‘g‘risida xabar qilmaslik yoki o‘z vaqtida xabar bermaslik fors-major holati boshlanganda Shartnoma bo‘yicha o‘z majburiyatlarini bajarish imkoniyatiga vaj qilib keltirish huquqiga ega emas.
A86: 7.4. Fors-major holati boshlanganligini vaj qilib ko‘rsatish huquqidan mahrum etilgan Tomon amaldagi qonun hujjatlariga muvofiq javobgar bo‘ladi.
A88: 8. NIZOLARNI HAL QILISH TARTIBI
A89: 8.1. Ushbu Shartnomadan kelib chiqadigan tomonlar o‘rtasidagi barcha nizolar va undan kelib chiqadigan majburiyatlar, shu jumladan shartnoma bajarilmasligi oqibatida yuzaga kelgan bajarilishi, o‘zgartirilishi, bekor qilinishi, tugatilishi Mikromoliya tashkilot joylashgan yerdagi taalluqli sudda yoki «CONSILIO» Mas'uliyati cheklangan jamiyat qoshidagi Hakamlik sudida, O‘zbekiston Respublikasining amaldagi qonun hujjatlari va uning reglamentiga muvofiq Hakamlik sudi raisi tomonidan tayinlangan, yakka tartibdagi hakamlik sudyasi tomonidan, sud ishlarini sud majlisi bayonnomasi tuzmasdan ko‘rib chiqilishi kerak bo‘ladi. U yoki bu sudga murojaat qilish huquqi da'vogarda qoladi.
A90: Qarzni undirish va garovdagi mol-mulkiga qaratish ham sud tartibida, ham suddan tashqari tartibda, shu jumladan notariusning ijro yozuvini olish yo‘li bilan amalga oshirilishi mumkin.
A91: ="8.2. Mikromoliya tashkiloti sud organlariga murojaat qilganidan keyin Qarz oluvchi tomonidan "&umumiy_malumot!B65&" bo‘yicha muddati o‘tgan qarzdorlikning to‘lanishi Mikromoliya tashkilotning "&umumiy_malumot!B65&" bo‘yicha qarzdorlikni muddatidan avval undirish, shu jumladan undiruvni garovdagi mol-mulkka qaratish yo‘li bilan undirish huquqidan mahrum qilmaydi." -> 8.2. Mikromoliya tashkiloti sud organlariga murojaat qilganidan keyin Qarz oluvchi tomonidan mikroqarz bo‘yicha muddati o‘tgan qarzdorlikning to‘lanishi Mikromoliya tashkilotning mikroqarz bo‘yicha qarzdorlikni muddatidan avval undirish, shu jumladan undiruvni garovdagi mol-mulkka qaratish yo‘li bilan undirish huquqidan mahrum qilmaydi.
A93: 9. SHARTNOMA SHARTLARI VA AMAL QILISH MUDDATI
A94: 9.1. Ushbu Shartnoma Tomonlar tarafidan imzolangandan keyin kuchga kiradi.
A95: ="9.2. Shartnomaning amal qilish muddati Qarz oluvchi "&umumiy_malumot!B65&"ni to‘liq qaytargan, hisoblangan foizlar, penya va boshqa pul majburiyatlarini to‘lagan kunda yakunlanadi." -> 9.2. Shartnomaning amal qilish muddati Qarz oluvchi mikroqarzni to‘liq qaytargan, hisoblangan foizlar, penya va boshqa pul majburiyatlarini to‘lagan kunda yakunlanadi.
A96: 9.3. Ushbu Shartnomaga kiritiladigan barcha o‘zgartirish va qo‘shimchalar, ushbu Shartnomada kelishilgan holatlardan tashqari, ikkala Tomon tarafidan qo‘shimcha bitimni yozma shaklda imzolagan holda amalga oshiriladi.
A98: 10. SHAXSIY MA'LUMOTLARNI QAYTA ISHLASH
A99: 10.1. Ushbu shartnomani tuzish bilan, Qarz oluvchi Mikromoliya tashkilotiga uning shaxsiy ma'lumotlari, shu jumladan, familiyasi, ismi, otasining ismi, pasport ma'lumotlari (shu jumladan, pasport raqami, berilgan vaqti va sanasi, ro‘yxatdan o‘tgan manzili va boshqalar); aloqaga chiqish uchun ma'lumotlar (shu jumladan, telefon raqami, e-mail, pochta manzili va boshqalar); STIR, ushbu shartnoma maqsadiga tegishli bo‘lgan boshqa ma'lumotlarni har qanday maqsadda ishlov berishga rozilik beradi.
A100: 10.2. Rozilik, shu jumladan shahsiy ma'lumotlar bilan quyidagi harakatlarni amalga oshirishga beriladi: yig‘ish, tizimlashtirish, to‘plash, saqlash, aniqlashtirish (yangilash, o‘zgartirish), foydalanish; O‘zbekiston Respublikasi qonun hujjatlarida nazarda tutilgan hollar va darajada tarqatish, shu jumladan davlat organlari va boshqa tashkilotlarga taqdim etish, shaxsiy ma'lumotlarning egasizlantirish, blokirovka va yo‘q qilish.
A101: 10.3. Qarz oluvchi, shuningdek, Mikromoliya tashkiloti shartnoma doirasida olingan ma'lumotlarni kredit byurosi va garov reestri, skoring kompaniyasi, uyali aloqa operatori, sug‘urta kompaniyasi, reklama ishlab chiqaruvchilari va tarqatuvchilari, shuningdek Mikromoliya tashkilotining boshqa hamkorlariga taqdim etishga roziligini bildiradi.
A103: 11. BOSHQA SHARTLAR
A104: 11.1. Ushbu shartnoma kuchga kirganidan keyin, o‘zaro munosabatlarga aloqador barcha yozishmalar yoki kelishuvlar, o‘z kuchini yo‘qotadi.
A105: 11.2. Ushbu shartnomani bajarish, o‘zgartirish va bekor qilish bilan bog‘liq barcha yozishma va xabarnomalar Tomonlarning ushbu shartnomaning yakuniy qismida ko‘rsatilgan pochta manzillariga yuboriladi.
A106: 11.3. Ushbu shartnomani bajarish uchun zarur bo‘lgan ismi (nomlanishi), ro‘yxatdan o‘tgan joyi, haqiqiy yashash joyi, manzili (joylashgan yeri), bank rekvizitlari va boshqa ma'lumotlar o‘zgargan holatlarda, Tomonlarning har biri bunday o‘zgarishlar amalga oshgan kundan boshlab 5 (besh) kalendar kun ichida boshqa Tomonni bunday o‘zgarishlar haqida yozma ravishda xabardor qilishi shart.
A107: 11.4. Ushbu bitimni amalga oshirish bilan, Qarz oluvchi kelishuvning muhimligi va uni tuzishning yuridik oqibatlarini to‘liq tushunib yetishi, shu sababli Shartnomani tuzish yanglishishlar, aldov, zo‘ravonlik, tahdidlar, yomon niyatli bitim yoki murakkab holatlar (tutqinlik) ta'sirida emasligini tasdiqlaydi.
A108: 11.5. Ushbu shartnomada ko‘zda tutilmagan holatlarda Tomonlar O‘zbekiston Respublikasining amaldagi qonunchiligiga amal qiladilar.
A109: 11.6. Qarz oluvchi Mikromoliya tashkilotining oldindan yozma roziligini olmasdan turib o‘z majburiyatlari yoki huquqlarini uchinchi shaxslarga o‘tkaza olmaydi.
... A113: 12. TOMONLARNING YURIDIK MANZILLARI VA REKVIZITLARI:
A115: «Mikromoliya tashkiloti» | B115: «Qarz oluvchi»
A117: =umumiy_malumot!B148 -> «PULLOL BUSINESS MIKROMOLIYA TASHKILOTI» MChJ | B117: =umumiy_malumot!B5 -> TURAYEV ISROIL BURIYEVICH
...

Sheet grafik
E3: =""&umumiy_malumot!B74&" "&umumiy_malumot!B65&" shartnomasiga 1 sonli ilova" -> 6 yanvar 2026 y.dan №3-BR mikroqarz shartnomasiga 1 sonli ilova
A5: To'lov jadvali
A7: № | B7: To'lov muddati | C7: Asosiy qarz qoldig'i | D7: To'lov miqdori, so'm
D8: asosiy qarz | E8: foizlar | F8: jami*
A9: 1 | B9: =IF('График дифференц'!B8=FALSE,"",'График дифференц'!B8) -> 46069 | C9: =IF(umumiy_malumot!$B$77=umumiy_malumot!$C$77,'График дифференц'!C8,IF(umumiy_malumot!$B$77=umumiy_malumot!$D$77,'График аннуитет.'!C8)) -> 33000000 | D9: =IF(umumiy_malumot!$B$77=umumiy_malumot!$C$77,'График дифференц'!D8,IF(umumiy_malumot!$B$77=umumiy_malumot!$D$77,'График аннуитет.'!D8)) -> 916666.67 | E9: =IF(umumiy_malumot!$B$77=umumiy_malumot!$C$77,'График дифференц'!E8,IF(umumiy_malumot!$B$77=umumiy_malumot!$D$77,'График аннуитет.'!E8)) -> 2038767.2 | F9: =IF(umumiy_malumot!$B$77=umumiy_malumot!$C$77,'График дифференц'!F8,IF(umumiy_malumot!$B$77=umumiy_malumot!$D$77,'График аннуитет.'!F8)) -> 2955433.9
A10: 2 | B10: =IF('График дифференц'!B9=FALSE,"",'График дифференц'!B9) -> 46097 | C10: =IF(umumiy_malumot!$B$77=umumiy_malumot!$C$77,'График дифференц'!C9,IF(umumiy_malumot!$B$77=umumiy_malumot!$D$77,'График аннуитет.'!C9)) -> 32083333 | D10: =IF(umumiy_malumot!$B$77=umumiy_malumot!$C$77,'График дифференц'!D9,IF(umumiy_malumot!$B$77=umumiy_malumot!$D$77,'График аннуитет.'!D9)) -> 916666.67 | E10: =IF(umumiy_malumot!$B$77=umumiy_malumot!$C$77,'График дифференц'!E9,IF(umumiy_malumot!$B$77=umumiy_malumot!$D$77,'График аннуитет.'!E9)) -> 1353653 | F10: =IF(umumiy_malumot!$B$77=umumiy_malumot!$C$77,'График дифференц'!F9,IF(umumiy_malumot!$B$77=umumiy_malumot!$D$77,'График аннуитет.'!F9)) -> 2270319.7
A11: 3 | B11: =IF('График дифференц'!B10=FALSE,"",'График дифференц'!B10) -> 46127 | C11: =IF(umumiy_malumot!$B$77=umumiy_malumot!$C$77,'График дифференц'!C10,IF(umumiy_malumot!$B$77=umumiy_malumot!$D$77,'График аннуитет.'!C10)) -> 31166667 | D11: =IF(umumiy_malumot!$B$77=umumiy_malumot!$C$77,'График дифференц'!D10,IF(umumiy_malumot!$B$77=umumiy_malumot!$D$77,'График аннуитет.'!D10)) -> 916666.67 | E11: =IF(umumiy_malumot!$B$77=umumiy_malumot!$C$77,'График дифференц'!E10,IF(umumiy_malumot!$B$77=umumiy_malumot!$D$77,'График аннуитет.'!E10)) -> 1408904.1 | F11: =IF(umumiy_malumot!$B$77=umumiy_malumot!$C$77,'График дифференц'!F10,IF(umumiy_malumot!$B$77=umumiy_malumot!$D$77,'График аннуитет.'!F10)) -> 2325570.8
A12: 4 | B12: =IF('График дифференц'!B11=FALSE,"",'График дифференц'!B11) -> 46157 | C12: =IF(umumiy_malumot!$B$77=umumiy_malumot!$C$77,'График дифференц'!C11,IF(umumiy_malumot!$B$77=umumiy_malumot!$D$77,'График аннуитет.'!C11)) -> 30250000 | D12: =IF(umumiy_malumot!$B$77=umumiy_malumot!$C$77,'График дифференц'!D11,IF(umumiy_malumot!$B$77=umumiy_malumot!$D$77,'График аннуитет.'!D11)) -> 916666.67 | E12: =IF(umumiy_malumot!$B$77=umumiy_malumot!$C$77,'График дифференц'!E11,IF(umumiy_malumot!$B$77=umumiy_malumot!$D$77,'График аннуитет.'!E11)) -> 1367465.7 | F12: =IF(umumiy_malumot!$B$77=umumiy_malumot!$C$77,'График дифференц'!F11,IF(umumiy_malumot!$B$77=umumiy_malumot!$D$77,'График аннуитет.'!F11)) -> 2284132.4 | H12: GRAFIKTA BO'SH JOY BO'LSA SKRIT' QILIB TASHLANG!!!
A13: 5 | B13: =IF('График дифференц'!B12=FALSE,"",'График дифференц'!B12) -> 46188 | C13: =IF(umumiy_malumot!$B$77=umumiy_malumot!$C$77,'График дифференц'!C12,IF(umumiy_malumot!$B$77=umumiy_malumot!$D$77,'График аннуитет.'!C12)) -> 29333333 | D13: =IF(umumiy_malumot!$B$77=umumiy_malumot!$C$77,'График дифференц'!D12,IF(umumiy_malumot!$B$77=umumiy_malumot!$D$77,'График аннуитет.'!D12)) -> 916666.67 | E13: =IF(umumiy_malumot!$B$77=umumiy_malumot!$C$77,'График дифференц'!E12,IF(umumiy_malumot!$B$77=umumiy_malumot!$D$77,'График аннуитет.'!E12)) -> 1370228.2 | F13: =IF(umumiy_malumot!$B$77=umumiy_malumot!$C$77,'График дифференц'!F12,IF(umumiy_malumot!$B$77=umumiy_malumot!$D$77,'График аннуитет.'!F12)) -> 2286894.9
A14: 6 | B14: =IF('График дифференц'!B13=FALSE,"",'График дифференц'!B13) -> 46218 | C14: =IF(umumiy_malumot!$B$77=umumiy_malumot!$C$77,'График дифференц'!C13,IF(umumiy_malumot!$B$77=umumiy_malumot!$D$77,'График аннуитет.'!C13)) -> 28416667 | D14: =IF(umumiy_malumot!$B$77=umumiy_malumot!$C$77,'График дифференц'!D13,IF(umumiy_malumot!$B$77=umumiy_malumot!$D$77,'График аннуитет.'!D13)) -> 916666.67 | E14: =IF(umumiy_malumot!$B$77=umumiy_malumot!$C$77,'График дифференц'!E13,IF(umumiy_malumot!$B$77=umumiy_malumot!$D$77,'График аннуитет.'!E13)) -> 1284588.9 | F14: =IF(umumiy_malumot!$B$77=umumiy_malumot!$C$77,'График дифференц'!F13,IF(umumiy_malumot!$B$77=umumiy_malumot!$D$77,'График аннуитет.'!F13)) -> 2201255.6
A15: 7 | B15: =IF('График дифференц'!B14=FALSE,"",'График дифференц'!B14) -> 46251 | C15: =IF(umumiy_malumot!$B$77=umumiy_malumot!$C$77,'График дифференц'!C14,IF(umumiy_malumot!$B$77=umumiy_malumot!$D$77,'График аннуитет.'!C14)) -> 27500000 | D15: =IF(umumiy_malumot!$B$77=umumiy_malumot!$C$77,'График дифференц'!D14,IF(umumiy_malumot!$B$77=umumiy_malumot!$D$77,'График аннуитет.'!D14)) -> 916666.67 | E15: =IF(umumiy_malumot!$B$77=umumiy_malumot!$C$77,'График дифференц'!E14,IF(umumiy_malumot!$B$77=umumiy_malumot!$D$77,'График аннуитет.'!E14)) -> 1367465.9 | F15: =IF(umumiy_malumot!$B$77=umumiy_malumot!$C$77,'График дифференц'!F14,IF(umumiy_malumot!$B$77=umumiy_malumot!$D$77,'График аннуитет.'!F14)) -> 2284132.6
A16: 8 | B16: =IF('График дифференц'!B15=FALSE,"",'График дифференц'!B15) -> 46280 | C16: =IF(umumiy_malumot!$B$77=umumiy_malumot!$C$77,'График дифференц'!C15,IF(umumiy_malumot!$B$77=umumiy_malumot!$D$77,'График аннуитет.'!C15)) -> 26583333 | D16: =IF(umumiy_malumot!$B$77=umumiy_malumot!$C$77,'График дифференц'!D15,IF(umumiy_malumot!$B$77=umumiy_malumot!$D$77,'График аннуитет.'!D15)) -> 916666.67 | E16: =IF(umumiy_malumot!$B$77=umumiy_malumot!$C$77,'График дифференц'!E15,IF(umumiy_malumot!$B$77=umumiy_malumot!$D$77,'График аннуитет.'!E15)) -> 1161655.3 | F16: =IF(umumiy_malumot!$B$77=umumiy_malumot!$C$77,'График дифференц'!F15,IF(umumiy_malumot!$B$77=umumiy_malumot!$D$77,'График аннуитет.'!F15)) -> 2078322
A17: 9 | B17: =IF('График дифференц'!B16=FALSE,"",'График дифференц'!B16) -> 46310 | C17: =IF(umumiy_malumot!$B$77=umumiy_malumot!$C$77,'График дифференц'!C16,IF(umumiy_malumot!$B$77=umumiy_malumot!$D$77,'График аннуитет.'!C16)) -> 25666667 | D17: =IF(umumiy_malumot!$B$77=umumiy_malumot!$C$77,'График дифференц'!D16,IF(umumiy_malumot!$B$77=umumiy_malumot!$D$77,'График аннуитет.'!D16)) -> 916666.67 | E17: =IF(umumiy_malumot!$B$77=umumiy_malumot!$C$77,'График дифференц'!E16,IF(umumiy_malumot!$B$77=umumiy_malumot!$D$77,'График аннуитет.'!E16)) -> 1160274 | F17: =IF(umumiy_malumot!$B$77=umumiy_malumot!$C$77,'График дифференц'!F16,IF(umumiy_malumot!$B$77=umumiy_malumot!$D$77,'График аннуитет.'!F16)) -> 2076940.7
A18: 10 | B18: =IF('График дифференц'!B17=FALSE,"",'График дифференц'!B17) -> 46342 | C18: =IF(umumiy_malumot!$B$77=umumiy_malumot!$C$77,'График дифференц'!C17,IF(umumiy_malumot!$B$77=umumiy_malumot!$D$77,'График аннуитет.'!C17)) -> 24750000 | D18: =IF(umumiy_malumot!$B$77=umumiy_malumot!$C$77,'График дифференц'!D17,IF(umumiy_malumot!$B$77=umumiy_malumot!$D$77,'График аннуитет.'!D17)) -> 916666.67 | E18: =IF(umumiy_malumot!$B$77=umumiy_malumot!$C$77,'График дифференц'!E17,IF(umumiy_malumot!$B$77=umumiy_malumot!$D$77,'График аннуитет.'!E17)) -> 1193424.6 | F18: =IF(umumiy_malumot!$B$77=umumiy_malumot!$C$77,'График дифференц'!F17,IF(umumiy_malumot!$B$77=umumiy_malumot!$D$77,'График аннуитет.'!F17)) -> 2110091.3
A19: 11 | B19: =IF('График дифференц'!B18=FALSE,"",'График дифференц'!B18) -> 46371 | C19: =IF(umumiy_malumot!$B$77=umumiy_malumot!$C$77,'График дифференц'!C18,IF(umumiy_malumot!$B$77=umumiy_malumot!$D$77,'График аннуитет.'!C18)) -> 23833333 | D19: =IF(umumiy_malumot!$B$77=umumiy_malumot!$C$77,'График дифференц'!D18,IF(umumiy_malumot!$B$77=umumiy_malumot!$D$77,'График аннуитет.'!D18)) -> 916666.67 | E19: =IF(umumiy_malumot!$B$77=umumiy_malumot!$C$77,'График дифференц'!E18,IF(umumiy_malumot!$B$77=umumiy_malumot!$D$77,'График аннуитет.'!E18)) -> 1041484 | F19: =IF(umumiy_malumot!$B$77=umumiy_malumot!$C$77,'График дифференц'!F18,IF(umumiy_malumot!$B$77=umumiy_malumot!$D$77,'График аннуитет.'!F18)) -> 1958150.6
A20: 12 | B20: =IF('График дифференц'!B19=FALSE,"",'График дифференц'!B19) -> 46402 | C20: =IF(umumiy_malumot!$B$77=umumiy_malumot!$C$77,'График дифференц'!C19,IF(umumiy_malumot!$B$77=umumiy_malumot!$D$77,'График аннуитет.'!C19)) -> 22916667 | D20: =IF(umumiy_malumot!$B$77=umumiy_malumot!$C$77,'График дифференц'!D19,IF(umumiy_malumot!$B$77=umumiy_malumot!$D$77,'График аннуитет.'!D19)) -> 916666.67 | E20: =IF(umumiy_malumot!$B$77=umumiy_malumot!$C$77,'График дифференц'!E19,IF(umumiy_malumot!$B$77=umumiy_malumot!$D$77,'График аннуитет.'!E19)) -> 1070490.8 | F20: =IF(umumiy_malumot!$B$77=umumiy_malumot!$C$77,'График дифференц'!F19,IF(umumiy_malumot!$B$77=umumiy_malumot!$D$77,'График аннуитет.'!F19)) -> 1987157.4
A21: 13 | B21: =IF('График дифференц'!B20=FALSE,"",'График дифференц'!B20) -> 46433 | C21: =IF(umumiy_malumot!$B$77=umumiy_malumot!$C$77,'График дифференц'!C20,IF(umumiy_malumot!$B$77=umumiy_malumot!$D$77,'График аннуитет.'!C20)) -> 22000000 | D21: =IF(umumiy_malumot!$B$77=umumiy_malumot!$C$77,'График дифференц'!D20,IF(umumiy_malumot!$B$77=umumiy_malumot!$D$77,'График аннуитет.'!D20)) -> 916666.67 | E21: =IF(umumiy_malumot!$B$77=umumiy_malumot!$C$77,'График дифференц'!E20,IF(umumiy_malumot!$B$77=umumiy_malumot!$D$77,'График аннуитет.'!E20)) -> 1027671.1 | F21: =IF(umumiy_malumot!$B$77=umumiy_malumot!$C$77,'График дифференц'!F20,IF(umumiy_malumot!$B$77=umumiy_malumot!$D$77,'График аннуитет.'!F20)) -> 1944337.8
A22: 14 | B22: =IF('График дифференц'!B21=FALSE,"",'График дифференц'!B21) -> 46461 | C22: =IF(umumiy_malumot!$B$77=umumiy_malumot!$C$77,'График дифференц'!C21,IF(umumiy_malumot!$B$77=umumiy_malumot!$D$77,'График аннуитет.'!C21)) -> 21083333 | D22: =IF(umumiy_malumot!$B$77=umumiy_malumot!$C$77,'График дифференц'!D21,IF(umumiy_malumot!$B$77=umumiy_malumot!$D$77,'График аннуитет.'!D21)) -> 916666.67 | E22: =IF(umumiy_malumot!$B$77=umumiy_malumot!$C$77,'График дифференц'!E21,IF(umumiy_malumot!$B$77=umumiy_malumot!$D$77,'График аннуитет.'!E21)) -> 889543.48 | F22: =IF(umumiy_malumot!$B$77=umumiy_malumot!$C$77,'График дифференц'!F21,IF(umumiy_malumot!$B$77=umumiy_malumot!$D$77,'График аннуитет.'!F21)) -> 1806210.1
A23: 15 | B23: =IF('График дифференц'!B22=FALSE,"",'График дифференц'!B22) -> 46492 | C23: =IF(umumiy_malumot!$B$77=umumiy_malumot!$C$77,'График дифференц'!C22,IF(umumiy_malumot!$B$77=umumiy_malumot!$D$77,'График аннуитет.'!C22)) -> 20166667 | D23: =IF(umumiy_malumot!$B$77=umumiy_malumot!$C$77,'График дифференц'!D22,IF(umumiy_malumot!$B$77=umumiy_malumot!$D$77,'График аннуитет.'!D22)) -> 916666.67 | E23: =IF(umumiy_malumot!$B$77=umumiy_malumot!$C$77,'График дифференц'!E22,IF(umumiy_malumot!$B$77=umumiy_malumot!$D$77,'График аннуитет.'!E22)) -> 942032.03 | F23: =IF(umumiy_malumot!$B$77=umumiy_malumot!$C$77,'График дифференц'!F22,IF(umumiy_malumot!$B$77=umumiy_malumot!$D$77,'График аннуитет.'!F22)) -> 1858698.7
A24: 16 | B24: =IF('График дифференц'!B23=FALSE,"",'График дифференц'!B23) -> 46524 | C24: =IF(umumiy_malumot!$B$77=umumiy_malumot!$C$77,'График дифференц'!C23,IF(umumiy_malumot!$B$77=umumiy_malumot!$D$77,'График аннуитет.'!C23)) -> 19250000 | D24: =IF(umumiy_malumot!$B$77=umumiy_malumot!$C$77,'График дифференц'!D23,IF(umumiy_malumot!$B$77=umumiy_malumot!$D$77,'График аннуитет.'!D23)) -> 916666.67 | E24: =IF(umumiy_malumot!$B$77=umumiy_malumot!$C$77,'График дифференц'!E23,IF(umumiy_malumot!$B$77=umumiy_malumot!$D$77,'График аннуитет.'!E23)) -> 928219.2 | F24: =IF(umumiy_malumot!$B$77=umumiy_malumot!$C$77,'График дифференц'!F23,IF(umumiy_malumot!$B$77=umumiy_malumot!$D$77,'График аннуитет.'!F23)) -> 1844885.9
... A26: 18 | B26: =IF('График дифференц'!B25=FALSE,"",'График дифференц'!B25) -> 46583 | C26: =IF(umumiy_malumot!$B$77=umumiy_malumot!$C$77,'График дифференц'!C25,IF(umumiy_malumot!$B$77=umumiy_malumot!$D$77,'График аннуитет.'!C25)) -> 17416667 | D26: =IF(umumiy_malumot!$B$77=umumiy_malumot!$C$77,'График дифференц'!D25,IF(umumiy_malumot!$B$77=umumiy_malumot!$D$77,'График аннуитет.'!D25)) -> 916666.67 | E26: =IF(umumiy_malumot!$B$77=umumiy_malumot!$C$77,'График дифференц'!E25,IF(umumiy_malumot!$B$77=umumiy_malumot!$D$77,'График аннуитет.'!E25)) -> 787328.7 | F26: =IF(umumiy_malumot!$B$77=umumiy_malumot!$C$77,'График дифференц'!F25,IF(umumiy_malumot!$B$77=umumiy_malumot!$D$77,'График аннуитет.'!F25)) -> 1703995.4
A27: =1+A26 -> 19 | B27: =IF('График дифференц'!B26=FALSE,"",'График дифференц'!B26) -> 46615 | C27: =IF(umumiy_malumot!$B$77=umumiy_malumot!$C$77,'График дифференц'!C26,IF(umumiy_malumot!$B$77=umumiy_malumot!$D$77,'График аннуитет.'!C26)) -> 16500000 | D27: =IF(umumiy_malumot!$B$77=umumiy_malumot!$C$77,'График дифференц'!D26,IF(umumiy_malumot!$B$77=umumiy_malumot!$D$77,'График аннуитет.'!D26)) -> 916666.67 | E27: =IF(umumiy_malumot!$B$77=umumiy_malumot!$C$77,'График дифференц'!E26,IF(umumiy_malumot!$B$77=umumiy_malumot!$D$77,'График аннуитет.'!E26)) -> 795616.32 | F27: =IF(umumiy_malumot!$B$77=umumiy_malumot!$C$77,'График дифференц'!F26,IF(umumiy_malumot!$B$77=umumiy_malumot!$D$77,'График аннуитет.'!F26)) -> 1712283
A28: =1+A27 -> 20 | B28: =IF('График дифференц'!B27=FALSE,"",'График дифференц'!B27) -> 46645 | C28: =IF(umumiy_malumot!$B$77=umumiy_malumot!$C$77,'График дифференц'!C27,IF(umumiy_malumot!$B$77=umumiy_malumot!$D$77,'График аннуитет.'!C27)) -> 15583333 | D28: =IF(umumiy_malumot!$B$77=umumiy_malumot!$C$77,'График дифференц'!D27,IF(umumiy_malumot!$B$77=umumiy_malumot!$D$77,'График аннуитет.'!D27)) -> 916666.67 | E28: =IF(umumiy_malumot!$B$77=umumiy_malumot!$C$77,'График дифференц'!E27,IF(umumiy_malumot!$B$77=umumiy_malumot!$D$77,'График аннуитет.'!E27)) -> 704452.2 | F28: =IF(umumiy_malumot!$B$77=umumiy_malumot!$C$77,'График дифференц'!F27,IF(umumiy_malumot!$B$77=umumiy_malumot!$D$77,'График аннуитет.'!F27)) -> 1621118.9
A29: =1+A28 -> 21 | B29: =IF('График дифференц'!B28=FALSE,"",'График дифференц'!B28) -> 46675 | C29: =IF(umumiy_malumot!$B$77=umumiy_malumot!$C$77,'График дифференц'!C28,IF(umumiy_malumot!$B$77=umumiy_malumot!$D$77,'График аннуитет.'!C28)) -> 14666667 | D29: =IF(umumiy_malumot!$B$77=umumiy_malumot!$C$77,'График дифференц'!D28,IF(umumiy_malumot!$B$77=umumiy_malumot!$D$77,'График аннуитет.'!D28)) -> 916666.67 | E29: =IF(umumiy_malumot!$B$77=umumiy_malumot!$C$77,'График дифференц'!E28,IF(umumiy_malumot!$B$77=umumiy_malumot!$D$77,'График аннуитет.'!E28)) -> 663013.8 | F29: =IF(umumiy_malumot!$B$77=umumiy_malumot!$C$77,'График дифференц'!F28,IF(umumiy_malumot!$B$77=umumiy_malumot!$D$77,'График аннуитет.'!F28)) -> 1579680.5
A30: =1+A29 -> 22 | B30: =IF('График дифференц'!B29=FALSE,"",'График дифференц'!B29) -> 46706 | C30: =IF(umumiy_malumot!$B$77=umumiy_malumot!$C$77,'График дифференц'!C29,IF(umumiy_malumot!$B$77=umumiy_malumot!$D$77,'График аннуитет.'!C29)) -> 13750000 | D30: =IF(umumiy_malumot!$B$77=umumiy_malumot!$C$77,'График дифференц'!D29,IF(umumiy_malumot!$B$77=umumiy_malumot!$D$77,'График аннуитет.'!D29)) -> 916666.67 | E30: =IF(umumiy_malumot!$B$77=umumiy_malumot!$C$77,'График дифференц'!E29,IF(umumiy_malumot!$B$77=umumiy_malumot!$D$77,'График аннуитет.'!E29)) -> 642294.58 | F30: =IF(umumiy_malumot!$B$77=umumiy_malumot!$C$77,'График дифференц'!F29,IF(umumiy_malumot!$B$77=umumiy_malumot!$D$77,'График аннуитет.'!F29)) -> 1558961.2
A31: =1+A30 -> 23 | B31: =IF('График дифференц'!B30=FALSE,"",'График дифференц'!B30) -> 46736 | C31: =IF(umumiy_malumot!$B$77=umumiy_malumot!$C$77,'График дифференц'!C30,IF(umumiy_malumot!$B$77=umumiy_malumot!$D$77,'График аннуитет.'!C30)) -> 12833333 | D31: =IF(umumiy_malumot!$B$77=umumiy_malumot!$C$77,'График дифференц'!D30,IF(umumiy_malumot!$B$77=umumiy_malumot!$D$77,'График аннуитет.'!D30)) -> 916666.67 | E31: =IF(umumiy_malumot!$B$77=umumiy_malumot!$C$77,'График дифференц'!E30,IF(umumiy_malumot!$B$77=umumiy_malumot!$D$77,'График аннуитет.'!E30)) -> 580137 | F31: =IF(umumiy_malumot!$B$77=umumiy_malumot!$C$77,'График дифференц'!F30,IF(umumiy_malumot!$B$77=umumiy_malumot!$D$77,'График аннуитет.'!F30)) -> 1496803.7
A32: =1+A31 -> 24 | B32: =IF('График дифференц'!B31=FALSE,"",'График дифференц'!B31) -> 46769 | C32: =IF(umumiy_malumot!$B$77=umumiy_malumot!$C$77,'График дифференц'!C31,IF(umumiy_malumot!$B$77=umumiy_malumot!$D$77,'График аннуитет.'!C31)) -> 11916667 | D32: =IF(umumiy_malumot!$B$77=umumiy_malumot!$C$77,'График дифференц'!D31,IF(umumiy_malumot!$B$77=umumiy_malumot!$D$77,'График аннуитет.'!D31)) -> 916666.67 | E32: =IF(umumiy_malumot!$B$77=umumiy_malumot!$C$77,'График дифференц'!E31,IF(umumiy_malumot!$B$77=umumiy_malumot!$D$77,'График аннуитет.'!E31)) -> 590949.48 | F32: =IF(umumiy_malumot!$B$77=umumiy_malumot!$C$77,'График дифференц'!F31,IF(umumiy_malumot!$B$77=umumiy_malumot!$D$77,'График аннуитет.'!F31)) -> 1507616.2
A33: =1+A32 -> 25 | B33: =IF('График дифференц'!B32=FALSE,"",'График дифференц'!B32) -> 46798 | C33: =IF(umumiy_malumot!$B$77=umumiy_malumot!$C$77,'График дифференц'!C32,IF(umumiy_malumot!$B$77=umumiy_malumot!$D$77,'График аннуитет.'!C32)) -> 11000000 | D33: =IF(umumiy_malumot!$B$77=umumiy_malumot!$C$77,'График дифференц'!D32,IF(umumiy_malumot!$B$77=umumiy_malumot!$D$77,'График аннуитет.'!D32)) -> 916666.67 | E33: =IF(umumiy_malumot!$B$77=umumiy_malumot!$C$77,'График дифференц'!E32,IF(umumiy_malumot!$B$77=umumiy_malumot!$D$77,'График аннуитет.'!E32)) -> 479371.45 | F33: =IF(umumiy_malumot!$B$77=umumiy_malumot!$C$77,'График дифференц'!F32,IF(umumiy_malumot!$B$77=umumiy_malumot!$D$77,'График аннуитет.'!F32)) -> 1396038.1
A34: =1+A33 -> 26 | B34: =IF('График дифференц'!B33=FALSE,"",'График дифференц'!B33) -> 46827 | C34: =IF(umumiy_malumot!$B$77=umumiy_malumot!$C$77,'График дифференц'!C33,IF(umumiy_malumot!$B$77=umumiy_malumot!$D$77,'График аннуитет.'!C33)) -> 10083333 | D34: =IF(umumiy_malumot!$B$77=umumiy_malumot!$C$77,'График дифференц'!D33,IF(umumiy_malumot!$B$77=umumiy_malumot!$D$77,'График аннуитет.'!D33)) -> 916666.67 | E34: =IF(umumiy_malumot!$B$77=umumiy_malumot!$C$77,'График дифференц'!E33,IF(umumiy_malumot!$B$77=umumiy_malumot!$D$77,'График аннуитет.'!E33)) -> 439423.95 | F34: =IF(umumiy_malumot!$B$77=umumiy_malumot!$C$77,'График дифференц'!F33,IF(umumiy_malumot!$B$77=umumiy_malumot!$D$77,'График аннуитет.'!F33)) -> 1356090.6
A35: =1+A34 -> 27 | B35: =IF('График дифференц'!B34=FALSE,"",'График дифференц'!B34) -> 46860 | C35: =IF(umumiy_malumot!$B$77=umumiy_malumot!$C$77,'График дифференц'!C34,IF(umumiy_malumot!$B$77=umumiy_malumot!$D$77,'График аннуитет.'!C34)) -> 9166666.6 | D35: =IF(umumiy_malumot!$B$77=umumiy_malumot!$C$77,'График дифференц'!D34,IF(umumiy_malumot!$B$77=umumiy_malumot!$D$77,'График аннуитет.'!D34)) -> 916666.67 | E35: =IF(umumiy_malumot!$B$77=umumiy_malumot!$C$77,'График дифференц'!E34,IF(umumiy_malumot!$B$77=umumiy_malumot!$D$77,'График аннуитет.'!E34)) -> 454576.65 | F35: =IF(umumiy_malumot!$B$77=umumiy_malumot!$C$77,'График дифференц'!F34,IF(umumiy_malumot!$B$77=umumiy_malumot!$D$77,'График аннуитет.'!F34)) -> 1371243.3
A36: =1+A35 -> 28 | B36: =IF('График дифференц'!B35=FALSE,"",'График дифференц'!B35) -> 46888 | C36: =IF(umumiy_malumot!$B$77=umumiy_malumot!$C$77,'График дифференц'!C35,IF(umumiy_malumot!$B$77=umumiy_malumot!$D$77,'График аннуитет.'!C35)) -> 8249999.9 | D36: =IF(umumiy_malumot!$B$77=umumiy_malumot!$C$77,'График дифференц'!D35,IF(umumiy_malumot!$B$77=umumiy_malumot!$D$77,'График аннуитет.'!D35)) -> 916666.67 | E36: =IF(umumiy_malumot!$B$77=umumiy_malumot!$C$77,'График дифференц'!E35,IF(umumiy_malumot!$B$77=umumiy_malumot!$D$77,'График аннуитет.'!E35)) -> 347131.12 | F36: =IF(umumiy_malumot!$B$77=umumiy_malumot!$C$77,'График дифференц'!F35,IF(umumiy_malumot!$B$77=umumiy_malumot!$D$77,'График аннуитет.'!F35)) -> 1263797.8
A37: =1+A36 -> 29 | B37: =IF('График дифференц'!B36=FALSE,"",'График дифференц'!B36) -> 46919 | C37: =IF(umumiy_malumot!$B$77=umumiy_malumot!$C$77,'График дифференц'!C36,IF(umumiy_malumot!$B$77=umumiy_malumot!$D$77,'График аннуитет.'!C36)) -> 7333333.2 | D37: =IF(umumiy_malumot!$B$77=umumiy_malumot!$C$77,'График дифференц'!D36,IF(umumiy_malumot!$B$77=umumiy_malumot!$D$77,'График аннуитет.'!D36)) -> 916666.67 | E37: =IF(umumiy_malumot!$B$77=umumiy_malumot!$C$77,'График дифференц'!E36,IF(umumiy_malumot!$B$77=umumiy_malumot!$D$77,'График аннуитет.'!E36)) -> 341621.24 | F37: =IF(umumiy_malumot!$B$77=umumiy_malumot!$C$77,'График дифференц'!F36,IF(umumiy_malumot!$B$77=umumiy_malumot!$D$77,'График аннуитет.'!F36)) -> 1258287.9
A38: =1+A37 -> 30 | B38: =IF('График дифференц'!B37=FALSE,"",'График дифференц'!B37) -> 46951 | C38: =IF(umumiy_malumot!$B$77=umumiy_malumot!$C$77,'График дифференц'!C37,IF(umumiy_malumot!$B$77=umumiy_malumot!$D$77,'График аннуитет.'!C37)) -> 6416666.6 | D38: =IF(umumiy_malumot!$B$77=umumiy_malumot!$C$77,'График дифференц'!D37,IF(umumiy_malumot!$B$77=umumiy_malumot!$D$77,'График аннуитет.'!D37)) -> 916666.67 | E38: =IF(umumiy_malumot!$B$77=umumiy_malumot!$C$77,'График дифференц'!E37,IF(umumiy_malumot!$B$77=umumiy_malumot!$D$77,'График аннуитет.'!E37)) -> 308560.96 | F38: =IF(umumiy_malumot!$B$77=umumiy_malumot!$C$77,'График дифференц'!F37,IF(umumiy_malumot!$B$77=umumiy_malumot!$D$77,'График аннуитет.'!F37)) -> 1225227.6
... A56: =1+A55 -> 48 | B56: =IF('График дифференц'!B55=FALSE,"",'График дифференц'!B55) | C56: =IF(umumiy_malumot!$B$77=umumiy_malumot!$C$77,'График дифференц'!C55,IF(umumiy_malumot!$B$77=umumiy_malumot!$D$77,'График аннуитет.'!C55)) -> 0 | D56: =IF(umumiy_malumot!$B$77=umumiy_malumot!$C$77,'График дифференц'!D55,IF(umumiy_malumot!$B$77=umumiy_malumot!$D$77,'График аннуитет.'!D55)) -> 0 | E56: =IF(umumiy_malumot!$B$77=umumiy_malumot!$C$77,'График дифференц'!E55,IF(umumiy_malumot!$B$77=umumiy_malumot!$D$77,'График аннуитет.'!E55)) -> 0 | F56: =IF(umumiy_malumot!$B$77=umumiy_malumot!$C$77,'График дифференц'!F55,IF(umumiy_malumot!$B$77=umumiy_malumot!$D$77,'График аннуитет.'!F55)) -> 0
B57: JAMI | D57: =SUM(D9:D56) -> 33000000 | E57: =SUM(E9:E56) -> 28402510 | F57: =SUM(F9:F56) -> 61402510
A59: ="*"&umumiy_malumot!C64&" bo‘yicha to‘lovlar to‘lov jadvalida ko‘rsatilmagan sanalarda to‘langan taqdirda, to‘lov summasi mikroqarz shartnomasining 2.4.-bandiga muvofiq "&umumiy_malumot!B65&" qoldig‘iga hisoblangan foizlar summasiga o‘zgartiriladi." -> *Mikroqarz bo‘yicha to‘lovlar to‘lov jadvalida ko‘rsatilmagan sanalarda to‘langan taqdirda, to‘lov summasi mikroqarz shartnomasining 2.4.-bandiga muvofiq mikroqarz qoldig‘iga hisoblangan foizlar summasiga o‘zgartiriladi.
A61: «Mikromoliya tashkiloti » | D61: «Qarz oluvchi»
A63: =shartnoma!A117 -> «PULLOL BUSINESS MIKROMOLIYA TASHKILOTI» MChJ | D63: =shartnoma!B117 -> TURAYEV ISROIL BURIYEVICH
A64: =shartnoma!A119 -> Manzil: Toshkent shahri, Yakkasaroy tumani, Rakat ko'chasi, 10-uy, 18 xonadon | D64: =shartnoma!B119 -> Manzil: BUXORO VILOYATI KOGON SHAHRI ZAFAROBOD 17-UY
A65: =shartnoma!A120 -> h/r: № 20208000405643889001 | D65: =shartnoma!B121 -> pasport seriyasi: AD 6760672, IIV 61013 tomonidan 08.04.2024 yilda berilgan
A66: =shartnoma!A121 -> MFO: №01088 в ATB “Kapitalbank” Markaziy amaliyotlar bo'limi
A67: =shartnoma!A122 -> STIR: 310430149 | D67: =shartnoma!B122 -> Tel: 91 923 50 54 MIJOZ
A68: =shartnoma!A123 -> Tel: (55) 510 02 16 | D68: =shartnoma!B123 -> 50 377 80 88 OTASI TO'LOVCHI
A69: =shartnoma!A124 -> (97) 714 14 17 | D69: =shartnoma!B124 -> 93 000 16 05 O'G'LI
A70: =shartnoma!A125 -> (97) 706 96 65 | D70: =IF(shartnoma!B125=0,"",shartnoma!B125)
A71: =umumiy_malumot!A150 -> Buxoro filiali boshlig'i | D71: =shartnoma!B127 -> TURAYEV I.B. __________________
A73: =shartnoma!A129 -> IKROMOV B.A. __________________

Sheet dalolatnoma
A2: ="GAROV PREDMETI QIYMATINI KELISHISH №"&umumiy_malumot!B141&" SONLI DALOLATNOMASI " -> GAROV PREDMETI QIYMATINI KELISHISH №1 SONLI DALOLATNOMASI
A4: Toshkent shahri | E4: =umumiy_malumot!B142 -> 6 yanvar 2026 y.
A6: =IF(umumiy_malumot!B103="avtotransport",dalolatnoma!A10:E10,dalolatnoma!A7:E7) -> «PULLOL BUSINESS MIKROMOLIYA TASHKILOTI» MChJning (1-tomon) vakili bo‘lgan Buxoro filiali boshlig'i IKROMOV B.A., O‘zbekiston Respublikasi fuqarosi TURAYEV ISROIL BURIYEVICH (2-tomon) va garovga beruvchi O‘zbekiston Respublikasi fuqarosi USMONOV NURIDDID IXTIYOROVICH (3-tomon) o’rtalarida, 6 yanvar 2026 y.dan №3-BR-sonli Mikroqarz shartnomasiga muvofiq 1-tomon 2-tomonga berilgan mikroqarz bo‘yicha ta’minot sifatida taqdim etilgan, 3-tomonga mulk huquqi asosida tegishli bo‘lgan mulkning garov qiymatini kelishish muzokaralari o’tkazildi.
A7: =IF(umumiy_malumot!B93="ha",dalolatnoma!A9:E9,dalolatnoma!A8:E8) -> «PULLOL BUSINESS MIKROMOLIYA TASHKILOTI» MChJning (1-tomon) vakili bo‘lgan Buxoro filiali boshlig'i IKROMOV B.A., va O‘zbekiston Respublikasi fuqarosi TURAYEV ISROIL BURIYEVICH (2-tomon) va garov egasi 0 (3-tomon) 6 yanvar 2026 y.dan №3-BR Mikroqarz shartnomasiga muvofiq 1-tomon 2-tomonga berilgan mikroqarz bo‘yicha ta’minot sifatida taqdim etilgan, 2-tomonga mulk huquqi asosida tegishli bo‘lgan mulkning garov qiymatini kelishish muzokaralari o’tkazildi.
A8: =""&umumiy_malumot!B147&"ning (1-tomon) vakili bo‘lgan "&umumiy_malumot!A150&" "&umumiy_malumot!B150&", va O‘zbekiston Respublikasi fuqarosi "&umumiy_malumot!B5&" (2-tomon) va garov egasi "&umumiy_malumot!C117&" (3-tomon) "&umumiy_malumot!B74&" "&umumiy_malumot!C64&" shartnomasiga muvofiq 1-tomon 2-tomonga berilgan "&umumiy_malumot!B65&" bo‘yicha ta’minot sifatida taqdim etilgan, 2-tomonga mulk huquqi asosida tegishli bo‘lgan mulkning garov qiymatini kelishish muzokaralari o’tkazildi. " -> «PULLOL BUSINESS MIKROMOLIYA TASHKILOTI» MChJning (1-tomon) vakili bo‘lgan Buxoro filiali boshlig'i IKROMOV B.A., va O‘zbekiston Respublikasi fuqarosi TURAYEV ISROIL BURIYEVICH (2-tomon) va garov egasi 0 (3-tomon) 6 yanvar 2026 y.dan №3-BR Mikroqarz shartnomasiga muvofiq 1-tomon 2-tomonga berilgan mikroqarz bo‘yicha ta’minot sifatida taqdim etilgan, 2-tomonga mulk huquqi asosida tegishli bo‘lgan mulkning garov qiymatini kelishish muzokaralari o’tkazildi.
A9: =""&umumiy_malumot!B147&"ning (1-tomon) vakili bo‘lgan "&umumiy_malumot!A150&" "&umumiy_malumot!B150&", va O‘zbekiston Respublikasi fuqarosi "&umumiy_malumot!B5&" (2-tomon) va garov egasi "&umumiy_malumot!C117&" (3-tomon) "&umumiy_malumot!B74&" "&umumiy_malumot!C64&" shartnomasiga muvofiq 1-tomon 2-tomonga berilgan "&umumiy_malumot!B65&" bo‘yicha ta’minot sifatida taqdim etilgan, 2-tomonga mulk huquqi asosida tegishli bo‘lgan mulkning garov qiymatini kelishish muzokaralari o’tkazildi. " -> «PULLOL BUSINESS MIKROMOLIYA TASHKILOTI» MChJning (1-tomon) vakili bo‘lgan Buxoro filiali boshlig'i IKROMOV B.A., va O‘zbekiston Respublikasi fuqarosi TURAYEV ISROIL BURIYEVICH (2-tomon) va garov egasi 0 (3-tomon) 6 yanvar 2026 y.dan №3-BR Mikroqarz shartnomasiga muvofiq 1-tomon 2-tomonga berilgan mikroqarz bo‘yicha ta’minot sifatida taqdim etilgan, 2-tomonga mulk huquqi asosida tegishli bo‘lgan mulkning garov qiymatini kelishish muzokaralari o’tkazildi.
A10: =IF(umumiy_malumot!B93="ha",dalolatnoma!A12:E12,dalolatnoma!A11:E11) -> «PULLOL BUSINESS MIKROMOLIYA TASHKILOTI» MChJning (1-tomon) vakili bo‘lgan Buxoro filiali boshlig'i IKROMOV B.A., O‘zbekiston Respublikasi fuqarosi TURAYEV ISROIL BURIYEVICH (2-tomon) va garovga beruvchi O‘zbekiston Respublikasi fuqarosi USMONOV NURIDDID IXTIYOROVICH (3-tomon) o’rtalarida, 6 yanvar 2026 y.dan №3-BR-sonli Mikroqarz shartnomasiga muvofiq 1-tomon 2-tomonga berilgan mikroqarz bo‘yicha ta’minot sifatida taqdim etilgan, 3-tomonga mulk huquqi asosida tegishli bo‘lgan mulkning garov qiymatini kelishish muzokaralari o’tkazildi.
A11: =""&umumiy_malumot!B147&"ning (1-tomon) vakili bo‘lgan "&umumiy_malumot!A150&" "&umumiy_malumot!B150&", O‘zbekiston Respublikasi fuqarosi "&umumiy_malumot!B5&" (2-tomon) va garovga beruvchi O‘zbekiston Respublikasi fuqarosi "&umumiy_malumot!B117&" (3-tomon) o’rtalarida, "&umumiy_malumot!B74&"-sonli "&umumiy_malumot!C64&" shartnomasiga muvofiq 1-tomon 2-tomonga berilgan "&umumiy_malumot!B65&" bo‘yicha ta’minot sifatida taqdim etilgan, 3-tomonga mulk huquqi asosida tegishli bo‘lgan mulkning garov qiymatini kelishish muzokaralari o’tkazildi." -> «PULLOL BUSINESS MIKROMOLIYA TASHKILOTI» MChJning (1-tomon) vakili bo‘lgan Buxoro filiali boshlig'i IKROMOV B.A., O‘zbekiston Respublikasi fuqarosi TURAYEV ISROIL BURIYEVICH (2-tomon) va garovga beruvchi O‘zbekiston Respublikasi fuqarosi USMONOV NURIDDID IXTIYOROVICH (3-tomon) o’rtalarida, 6 yanvar 2026 y.dan №3-BR-sonli Mikroqarz shartnomasiga muvofiq 1-tomon 2-tomonga berilgan mikroqarz bo‘yicha ta’minot sifatida taqdim etilgan, 3-tomonga mulk huquqi asosida tegishli bo‘lgan mulkning garov qiymatini kelishish muzokaralari o’tkazildi.
A12: =""&umumiy_malumot!B147&"ning (1-tomon) vakili bo‘lgan "&umumiy_malumot!A150&" "&umumiy_malumot!B150&", O‘zbekiston Respublikasi fuqarosi va garovga beruvchi "&umumiy_malumot!B5&" (2-tomon) o’rtalarida, "&umumiy_malumot!B74&"-sonli "&umumiy_malumot!C64&" shartnomasiga muvofiq 1-tomon 2-tomonga berilgan "&umumiy_malumot!B65&" bo‘yicha ta’minot sifatida taqdim etilgan, 2-tomonga mulk huquqi asosida tegishli bo‘lgan mulkning garov qiymatini kelishish muzokaralari o’tkazildi." -> «PULLOL BUSINESS MIKROMOLIYA TASHKILOTI» MChJning (1-tomon) vakili bo‘lgan Buxoro filiali boshlig'i IKROMOV B.A., O‘zbekiston Respublikasi fuqarosi va garovga beruvchi TURAYEV ISROIL BURIYEVICH (2-tomon) o’rtalarida, 6 yanvar 2026 y.dan №3-BR-sonli Mikroqarz shartnomasiga muvofiq 1-tomon 2-tomonga berilgan mikroqarz bo‘yicha ta’minot sifatida taqdim etilgan, 2-tomonga mulk huquqi asosida tegishli bo‘lgan mulkning garov qiymatini kelishish muzokaralari o’tkazildi.
A13: ="Garov predmeti sifatida "&umumiy_malumot!B125&", 3-tomonga egalik huquqi tegishli bo'lgan, quyidagi tafsilotlarga ega avtotransport vositasi taqdim etiladi:" -> Garov predmeti sifatida COBALT, 3-tomonga egalik huquqi tegishli bo'lgan, quyidagi tafsilotlarga ega avtotransport vositasi taqdim etiladi:
A14: ="Garov predmeti sifatida "&umumiy_malumot!B125&", 2-tomonga egalik huquqi tegishli bo'lgan, quyidagi tafsilotlarga ega avtotransport vositasi taqdim etiladi:" -> Garov predmeti sifatida COBALT, 2-tomonga egalik huquqi tegishli bo'lgan, quyidagi tafsilotlarga ega avtotransport vositasi taqdim etiladi:
A15: =IF(umumiy_malumot!B93="ha",dalolatnoma!A14:E14,dalolatnoma!A13:E13) -> Garov predmeti sifatida COBALT, 3-tomonga egalik huquqi tegishli bo'lgan, quyidagi tafsilotlarga ega avtotransport vositasi taqdim etiladi:
A16: ="Garov predmeti sifatida "&umumiy_malumot!C126&", 2-tomonga egalik huquqi tegishli bo'lgan, quyidagi tafsilotlarga ega ko'chmas mulk taqdim etiladi:" -> Garov predmeti sifatida 3 - xonali yakka tartibdagi uy-joy, 2-tomonga egalik huquqi tegishli bo'lgan, quyidagi tafsilotlarga ega ko'chmas mulk taqdim etiladi:
A17: ="Garov predmeti sifatida "&umumiy_malumot!C126&", 3-tomonga egalik huquqi tegishli bo'lgan, quyidagi tafsilotlarga ega ko'chmas mulk taqdim etiladi:" -> Garov predmeti sifatida 3 - xonali yakka tartibdagi uy-joy, 3-tomonga egalik huquqi tegishli bo'lgan, quyidagi tafsilotlarga ega ko'chmas mulk taqdim etiladi:
A18: =IF(umumiy_malumot!B93="ha",dalolatnoma!A16:E16,dalolatnoma!A17:E17) -> Garov predmeti sifatida 3 - xonali yakka tartibdagi uy-joy, 3-tomonga egalik huquqi tegishli bo'lgan, quyidagi tafsilotlarga ega ko'chmas mulk taqdim etiladi:
A19: =IF(umumiy_malumot!B103="Avtotransport",dalolatnoma!A15:E15,dalolatnoma!A18:E18) -> Garov predmeti sifatida COBALT, 3-tomonga egalik huquqi tegishli bo'lgan, quyidagi tafsilotlarga ega avtotransport vositasi taqdim etiladi:
A20: Nomi | B20: =IF(umumiy_malumot!B103=umumiy_malumot!C103,"Kuzov turi va kuzov raqami*","Foydali maydoni") -> Kuzov turi va kuzov raqami* | D20: =IF(umumiy_malumot!B103=umumiy_malumot!C103,"Dvigatel va shassi raqami*","Yashash maydoni") -> Dvigatel va shassi raqami* | E20: =IF(umumiy_malumot!B103=umumiy_malumot!C103,"Ishlab chiqarilgan yili va rangi**","Umumiy maydoni") -> Ishlab chiqarilgan yili va rangi**
A21: =IF(umumiy_malumot!B103=umumiy_malumot!C103,umumiy_malumot!B125,umumiy_malumot!C125) -> COBALT | B21: =IF(umumiy_malumot!B103=umumiy_malumot!C103,umumiy_malumot!B127,CONCATENATE(umumiy_malumot!G130," ","kv.m")) -> kuzov turi - YENGIL SEDAN, kuzov raqami XWBJF69VEGA010429 | D21: =IF(umumiy_malumot!B103=umumiy_malumot!C103,umumiy_malumot!B130,umumiy_malumot!F133) -> dvigatel raqami B15D211163412DJCX0337, shassi raqami - RAKAMSIZ | E21: =IF(umumiy_malumot!B103=umumiy_malumot!C103,umumiy_malumot!B133,umumiy_malumot!F130) -> rangi - OQ OLIMPIYSKAYA BELAYA, ishlab chiqarilgan yili - 2016
A22: ="-* "&IF(umumiy_malumot!B103=umumiy_malumot!C103,"avtotransport "&"egasi: "&umumiy_malumot!B117&"","ko'chmas mulk"&" egasi: "&umumiy_malumot!B117&"") -> -* avtotransport egasi: USMONOV NURIDDID IXTIYOROVICH
A23: =IF(umumiy_malumot!B103=umumiy_malumot!C103,"-* texnik pasport: "&umumiy_malumot!B124&"","-* reest raqami: "&umumiy_malumot!C124&"") -> -* texnik pasport: AAF 2401056 01.12.2020 y.
A24: =IF(umumiy_malumot!B103=umumiy_malumot!C103,"-* roʻyxatdan oʻtgan manzili/garaj manzili: "&umumiy_malumot!B122&"","-* kadastr raqami: "&umumiy_malumot!C127&"") -> -* roʻyxatdan oʻtgan manzili/garaj manzili: BUXORO VILOYATI BUXORO SHAHRI CHO'LPON KO'CHASI 22-A-UY
A25: =IF(umumiy_malumot!B103=umumiy_malumot!C103,"-* davlat raqami: "&umumiy_malumot!B126&"","-* manzili: "&umumiy_malumot!C123&"") -> -* davlat raqami: 80G291QA
A26: =IF(umumiy_malumot!B93="ha",dalolatnoma!A28:E28,dalolatnoma!A27:E27) -> Tomonlar o’rtasida o’tkazilgan muzokaralar natijalariga ko‘ra, 2-tomon ta’minot sifatida quyidagi tafsilotlarga ega bo’lgan garov predmetini taqdim etadi, 1-tomon esa ushbu garov predmetini 6 yanvar 2026 y.dan №3-BR mikroqarz shartnomasi bo‘yicha berilgan mikroqarz bo‘yicha 46 200 000,00 (qirq olti million ikki yuz ming so'm) so’m bo‘lgan kelishilgan garov qiymatida qabul qiladi::
A27: ="Tomonlar o’rtasida o’tkazilgan muzokaralar natijalariga ko‘ra, 2-tomon ta’minot sifatida quyidagi tafsilotlarga ega bo’lgan garov predmetini taqdim etadi, 1-tomon esa ushbu garov predmetini "&umumiy_malumot!B74&" "&umumiy_malumot!B65&" shartnomasi bo‘yicha berilgan "&umumiy_malumot!B65&" bo‘yicha "&FIXED(umumiy_malumot!B136,2)&" ("&umumiy_malumot!B137&") so’m bo‘lgan kelishilgan garov qiymatida qabul qiladi::" -> Tomonlar o’rtasida o’tkazilgan muzokaralar natijalariga ko‘ra, 2-tomon ta’minot sifatida quyidagi tafsilotlarga ega bo’lgan garov predmetini taqdim etadi, 1-tomon esa ushbu garov predmetini 6 yanvar 2026 y.dan №3-BR mikroqarz shartnomasi bo‘yicha berilgan mikroqarz bo‘yicha 46 200 000,00 (qirq olti million ikki yuz ming so'm) so’m bo‘lgan kelishilgan garov qiymatida qabul qiladi::
A28: ="Tomonlar o’rtasida o’tkazilgan muzokaralar natijalariga ko‘ra, 2-tomon ta’minot sifatida quyidagi tafsilotlarga ega bo’lgan garov predmetini taqdim etadi, 1-tomon esa ushbu garov predmetini "&umumiy_malumot!B74&" "&umumiy_malumot!C64&" shartnomasi bo‘yicha berilgan "&umumiy_malumot!B65&" bo‘yicha "&FIXED(umumiy_malumot!B136,2)&" ("&umumiy_malumot!B137&") so’m bo‘lgan kelishilgan garov qiymatida qabul qiladi::" -> Tomonlar o’rtasida o’tkazilgan muzokaralar natijalariga ko‘ra, 2-tomon ta’minot sifatida quyidagi tafsilotlarga ega bo’lgan garov predmetini taqdim etadi, 1-tomon esa ushbu garov predmetini 6 yanvar 2026 y.dan №3-BR Mikroqarz shartnomasi bo‘yicha berilgan mikroqarz bo‘yicha 46 200 000,00 (qirq olti million ikki yuz ming so'm) so’m bo‘lgan kelishilgan garov qiymatida qabul qiladi::
A29: Nomi | B29: =B20 -> Kuzov turi va kuzov raqami* | C29: =D20 -> Dvigatel va shassi raqami* | D29: =IF(umumiy_malumot!B103=umumiy_malumot!C103,"Ishlab chiqarilgan yili va rangi*","Foydalanishga topshirilgan sanasi") -> Ishlab chiqarilgan yili va rangi* | E29: Kelishilgan garov qiymati, so'm
A30: =A21 -> COBALT | B30: =B21 -> kuzov turi - YENGIL SEDAN, kuzov raqami XWBJF69VEGA010429 | C30: =D21 -> dvigatel raqami B15D211163412DJCX0337, shassi raqami - RAKAMSIZ | D30: =IF(umumiy_malumot!B103=umumiy_malumot!C103,E21,TEXT(umumiy_malumot!C135,"ДД.ММ.ГГГГ")) -> rangi - OQ OLIMPIYSKAYA BELAYA, ishlab chiqarilgan yili - 2016 | E30: =""&FIXED(umumiy_malumot!B136,2)&" ("&umumiy_malumot!B137&")" -> 46 200 000,00 (qirq olti million ikki yuz ming so'm)
A32: Наименование | B32: Полезная площадь | C32: Жилая площадь | D32: Общая площадь | E32: Согласованная залоговая стоимость, сум
A33: =#REF! -> #REF! | B33: =#REF! -> #REF! | C33: =#REF! -> #REF! | D33: =#REF! -> #REF! | E33: =""&FIXED(umumiy_malumot!C136,2)&" ("&umumiy_malumot!B137&")" -> 46 200 000,00 (qirq olti million ikki yuz ming so'm)
A35: =#REF! -> #REF! | B35: =#REF! -> #REF! | C35: =#REF! -> #REF! | D35: =#REF! -> #REF!
A36: =#REF! -> #REF! | B36: =#REF! -> #REF! | C36: =#REF! -> #REF! | D36: =#REF! -> #REF!
A37: =#REF! -> #REF! | B37: =#REF! -> #REF! | C37: =#REF! -> #REF! | D37: =#REF! -> #REF!
A38: =#REF! -> #REF! | B38: =#REF! -> #REF! | C38: =#REF! -> #REF! | D38: =#REF! -> #REF!
A39: =#REF! -> #REF! | B39: =#REF! -> #REF! | C39: =#REF! -> #REF! | D39: =#REF! -> #REF!
A40: =#REF! -> #REF! | B40: =#REF! -> #REF! | C40: =#REF! -> #REF! | D40: =#REF! -> #REF!
A41: =#REF! -> #REF! | B41: =#REF! -> #REF! | C41: =#REF! -> #REF! | D41: =#REF! -> #REF!
A42: =#REF! -> #REF! | B42: =#REF! -> #REF! | C42: =#REF! -> #REF! | D42: =#REF! -> #REF!
A43: =#REF! -> #REF! | B43: =#REF! -> #REF! | C43: =#REF! -> #REF! | D43: =#REF! -> #REF!
A44: =#REF! -> #REF! | B44: =#REF! -> #REF! | C44: =#REF! -> #REF! | D44: =#REF! -> #REF! | E44: =FIXED(umumiy_malumot!C136,2) -> 46 200 000,00
A46: ="“Birinchi talabga ko‘ra, yuqoridagi avtomobil Mikrokredit shartnomasi bo‘yicha garovga qo‘yilgan edi:: "&'Данные для послед. Залога'!W2&"" -> “Birinchi talabga ko‘ra, yuqoridagi avtomobil Mikrokredit shartnomasi bo‘yicha garovga qo‘yilgan edi:: - №5 от 11 yanvar 2021 г., заключенного с ООО «Clever Mikrokredit Tashkiloti» и TULYAGANOV XODJIAKBAR IRGASHEVICH, по согласованной залоговой стоимость - 15 000 000,00 (on besh million) сум. - №386 от 6 noyabr 2019 г., заключенного с ООО «Clever Mikrokredit Tashkiloti» и YUNUSOVA ZALOXAT MIRSULTANOVNA, по согласованной залоговой стоимость - 15 000 000,00 (on besh million) сум. - №33 от 21 yanvar 2021 г., заключенного с ООО «Clever Mikrokredit Tashkiloti» и YUNUSOVA ZALOXAT MIRSULTANOVNA, по согласованной залоговой стоимость - 15 000 000,00 (on besh million) сум. 0 0 0 0 0 0 0 0 0 0 0 0 0 0 0 0 0
A47: Shu bilan birga, garov predmetining kelishilgan garov qiymati deganda ushbu mulk garov sifatida taqdim etilgan/qabul qilingan qiymati tushuniladi.
A48: ="Shunday qilib, garov predmetining kelishilgan garov qiymati "&FIXED(umumiy_malumot!B136)&" ("&umumiy_malumot!B137&") so‘mni tashkil etadi." -> Shunday qilib, garov predmetining kelishilgan garov qiymati 46 200 000,00 (qirq olti million ikki yuz ming so'm) so‘mni tashkil etadi.
D49: =IF(umumiy_malumot!B92=umumiy_malumot!C92,umumiy_malumot!C136,IF(umumiy_malumot!B92=umumiy_malumot!D92,'Данные для послед. Залога'!M22,0)) -> 46200000 | E49: =IF(umumiy_malumot!B92=umumiy_malumot!C92,umumiy_malumot!B137,IF(umumiy_malumot!B92=umumiy_malumot!D92,'Данные для послед. Залога'!Q22,0)) -> qirq olti million ikki yuz ming so'm
A50: 1-tomondan:
A51: =umumiy_malumot!B148 -> «PULLOL BUSINESS MIKROMOLIYA TASHKILOTI» MChJ
A52: =""&umumiy_malumot!A150&"" -> Buxoro filiali boshlig'i | D52: ="_______________ "&umumiy_malumot!B150&"" -> _______________ IKROMOV B.A.
A55: Начальник отдела кредитования
A56: =umumiy_malumot!B148 -> «PULLOL BUSINESS MIKROMOLIYA TASHKILOTI» MChJ | D56: ="_______________ "&umumiy_malumot!B159&"" -> _______________ Akramov R.N.
A58: 2-tomondan:
A59: O'zbekiston Respublikasi fuqarosi | D59: ="_______________ "&umumiy_malumot!B7&"" -> _______________ TURAYEV I.B.
D60: =IF(umumiy_malumot!B93="да","",umumiy_malumot!B118) -> USMONOV N.I.
A61: =+IF(umumiy_malumot!B93="ha"," ","3-tomondan:") -> 3-tomondan: | F61: =IF(umumiy_malumot!B94=umumiy_malumot!D94,B7,"") -> 0
A62: =+IF(umumiy_malumot!B93="ha"," ","O'zbekiston Respublikasi fuqarosi") -> O'zbekiston Respublikasi fuqarosi | D62: =IF(umumiy_malumot!B93=umumiy_malumot!C93,"",A63) -> _______________ TURAYEV I.B.
A63: =IF(umumiy_malumot!B94=umumiy_malumot!C94,"_______________ "&umumiy_malumot!B112&"","_______________ "&umumiy_malumot!B7&"") -> _______________ TURAYEV I.B. | C63: =garov_ariza!A20 -> №202602386000102 06.01.2026 sanasidan xususiy faoliyat ko'rsatuvchi notarius tomonidan BUXORO VILOYATI BUXORO SHAHRI ASHXOBOD KO'CHASI 1/3-UY SHARIPOV ZAFAR JO'RABOYEVICH berilgan ishonchnomaga asosan

Sheet buyruq
A4: =""&umumiy_malumot!B147&" direktorining "&umumiy_malumot!B165&"dagi "&umumiy_malumot!B164&"-sonli buyrug‘i" -> «PULLOL BUSINESS MIKROMOLIYA TASHKILOTI» MChJ direktorining 6 yanvar 2026 y.dagi №3-BR-sonli buyrug‘i
A8: ="Men, Obidov Abdullo Shokir og'li "&umumiy_malumot!B147&" direktori, jismoniy shaxs "&umumiy_malumot!B10&"ga quyidagi shartlarda "&umumiy_malumot!B65&" berishni buyuraman:" -> Men, Obidov Abdullo Shokir og'li «PULLOL BUSINESS MIKROMOLIYA TASHKILOTI» MChJ direktori, jismoniy shaxs TURAYEV ISROIL BURIYEVICHga quyidagi shartlarda mikroqarz berishni buyuraman:
A9: =kredit_ariza!A13:D13 -> Mikroqarz summasi: 33 000 000,00 (o'ttiz uch million so'm) so'm.
A10: =kredit_ariza!A14:D14 -> Mikroqarz muddati: 36 (o'ttiz olti) oy.
A11: =kredit_ariza!A15:D15 -> Mikroqarzdan foydalanganlik uchun foiz stavkasi: yillik 55% (ellik besh) foiz
A12: =kredit_ariza!A16:D16 -> Mikroqarz bo'yicha asosiy qarz va foizlarni to'lash:
A13: =kredit_ariza!A17:D17 -> - mikroqarz shartnomasi bo'yicha har oy differensial to'lovlari amalga oshiriladi
A14: =kredit_ariza!A19:D19 -> - mikroqarz shartnomasi bo'yicha har oy differensial to'lovlari amalga oshiriladi
A15: =IF(umumiy_malumot!B103="Avtotransport",buyruq!A14:E14,buyruq!A13:E13) -> - mikroqarz shartnomasi bo'yicha har oy differensial to'lovlari amalga oshiriladi
A16: =IF(umumiy_malumot!B103=umumiy_malumot!D103,""&umumiy_malumot!C117&"ga tegishli "&umumiy_malumot!C126&" ko'rinishidagi ko'chmas mulkni quyidagi ma'lumotlarga muvofiq garovga qabul qilinsin:",""&umumiy_malumot!B117&"ga tegishli "&umumiy_malumot!B125&" ko'rinishidagi transport vositasini quyidagi ma'lumotlarga muvofiq garovga qabul qilinsin:") -> USMONOV NURIDDID IXTIYOROVICHga tegishli COBALT ko'rinishidagi transport vositasini quyidagi ma'lumotlarga muvofiq garovga qabul qilinsin:
A17: =""&umumiy_malumot!C117&"ga tegishli "&umumiy_malumot!C126&" ko'rinishidagi ko'chmas mulkni quyidagi ma'lumotlarga muvofiq garovga qabul qilinsin:" -> 0ga tegishli 3 - xonali yakka tartibdagi uy-joy ko'rinishidagi ko'chmas mulkni quyidagi ma'lumotlarga muvofiq garovga qabul qilinsin:
A18: =""&umumiy_malumot!B117&"ga tegishli "&umumiy_malumot!B125&" ko'rinishidagi transport vositasini quyidagi ma'lumotlarga muvofiq garovga qabul qilinsin:" -> USMONOV NURIDDID IXTIYOROVICHga tegishli COBALT ko'rinishidagi transport vositasini quyidagi ma'lumotlarga muvofiq garovga qabul qilinsin:
A19: =dalolatnoma!A29 -> Nomi | B19: =dalolatnoma!B29 -> Kuzov turi va kuzov raqami* | C19: =dalolatnoma!C29 -> Dvigatel va shassi raqami* | D19: =dalolatnoma!D29 -> Ishlab chiqarilgan yili va rangi* | E19: =dalolatnoma!E29 -> Kelishilgan garov qiymati, so'm
A20: =dalolatnoma!A30 -> COBALT | B20: =dalolatnoma!B30 -> kuzov turi - YENGIL SEDAN, kuzov raqami XWBJF69VEGA010429 | C20: =dalolatnoma!C30 -> dvigatel raqami B15D211163412DJCX0337, shassi raqami - RAKAMSIZ | D20: =dalolatnoma!D30 -> rangi - OQ OLIMPIYSKAYA BELAYA, ishlab chiqarilgan yili - 2016 | E20: =dalolatnoma!E30 -> 46 200 000,00 (qirq olti million ikki yuz ming so'm)
A21: =dalolatnoma!A22:E22 -> -* avtotransport egasi: USMONOV NURIDDID IXTIYOROVICH
A22: =dalolatnoma!A23:E23 -> -* texnik pasport: AAF 2401056 01.12.2020 y.
A23: =dalolatnoma!A24:E24 -> -* roʻyxatdan oʻtgan manzili/garaj manzili: BUXORO VILOYATI BUXORO SHAHRI CHO'LPON KO'CHASI 22-A-UY
A24: =dalolatnoma!A25:E25 -> -* davlat raqami: 80G291QA
A26: Nomi | B26: Yashash maydoni | C26: Yordamchi maydoni | D26: Umumiy maydoni | E26: =dalolatnoma!E29 -> Kelishilgan garov qiymati, so'm
A27: =dalolatnoma!A33 -> #REF! | B27: =dalolatnoma!B33 -> #REF! | C27: =dalolatnoma!C33 -> #REF! | D27: =dalolatnoma!D33 -> #REF! | E27: =dalolatnoma!E33 -> 46 200 000,00 (qirq olti million ikki yuz ming so'm)
A28: =dalolatnoma!A34 -> 0 | B28: =dalolatnoma!B34 -> 0 | C28: =dalolatnoma!C34 -> 0 | D28: =dalolatnoma!D34 -> 0
A29: =dalolatnoma!A35 -> #REF! | B29: =dalolatnoma!B35 -> #REF! | C29: =dalolatnoma!C35 -> #REF! | D29: =dalolatnoma!D35 -> #REF!
A30: =dalolatnoma!A36 -> #REF! | B30: =dalolatnoma!B36 -> #REF! | C30: =dalolatnoma!C36 -> #REF! | D30: =dalolatnoma!D36 -> #REF!
A31: =dalolatnoma!A37 -> #REF! | B31: =dalolatnoma!B37 -> #REF! | C31: =dalolatnoma!C37 -> #REF! | D31: =dalolatnoma!D37 -> #REF!
A32: =dalolatnoma!A38 -> #REF! | B32: =dalolatnoma!B38 -> #REF! | C32: =dalolatnoma!C38 -> #REF! | D32: =dalolatnoma!D38 -> #REF!
A33: =dalolatnoma!A39 -> #REF! | B33: =dalolatnoma!B39 -> #REF! | C33: =dalolatnoma!C39 -> #REF! | D33: =dalolatnoma!D39 -> #REF!
A34: =dalolatnoma!A40 -> #REF! | B34: =dalolatnoma!B40 -> #REF! | C34: =dalolatnoma!C40 -> #REF! | D34: =dalolatnoma!D40 -> #REF!
A35: =dalolatnoma!A41 -> #REF! | B35: =dalolatnoma!B41 -> #REF! | C35: =dalolatnoma!C41 -> #REF! | D35: =dalolatnoma!D41 -> #REF!
A36: =dalolatnoma!A42 -> #REF! | B36: =dalolatnoma!B42 -> #REF! | C36: =dalolatnoma!C42 -> #REF! | D36: =dalolatnoma!D42 -> #REF!
A37: =dalolatnoma!A43 -> #REF! | B37: =dalolatnoma!B43 -> #REF! | C37: =dalolatnoma!C43 -> #REF! | D37: =dalolatnoma!D43 -> #REF!
A38: =dalolatnoma!A44 -> #REF! | B38: =dalolatnoma!B44 -> #REF! | C38: =dalolatnoma!C44 -> #REF! | D38: =dalolatnoma!D44 -> #REF! | E38: =dalolatnoma!E44 -> 46 200 000,00
A39: =_xlfn.SINGLE(dalolatnoma!#REF!) -> #REF!
A40: =_xlfn.SINGLE(dalolatnoma!#REF!) -> #REF!
A41: =_xlfn.SINGLE(dalolatnoma!#REF!) -> #REF!
A42: =_xlfn.SINGLE(dalolatnoma!#REF!) -> #REF!
A48: «PULLOL BUSINESS MIKROMOLIYA TASHKILOTI» MChJ
A49: direktori | D49: Obidov A. Sh.

Sheet monitoring_1
A2: =""&" "&umumiy_malumot!B74&"-sonli "&" "&umumiy_malumot!C64&" shartnomasi bo‘yicha garovga qo‘yilgan mol-mulkni tekshirish bo’yicha "&umumiy_malumot!B5&" bilan tuzilgan dalolatnomasi" -> 6 yanvar 2026 y.dan №3-BR-sonli Mikroqarz shartnomasi bo‘yicha garovga qo‘yilgan mol-mulkni tekshirish bo’yicha TURAYEV ISROIL BURIYEVICH bilan tuzilgan dalolatnomasi
A5: Toshkent shahri | H5: =TEXT(umumiy_malumot!D2,"ДД.ММ.ГГГГ") -> 05.07.2026
A7: =" Men, «PULLOL BUSINESS MIKROMOLIYA TASHKILOTI» MChJ” "&umumiy_malumot!A150&"i "&umumiy_malumot!B150&", jismoniy shaxs "&" "&umumiy_malumot!B5&" "&" "&umumiy_malumot!B74&"-sonli "&umumiy_malumot!B65&" shartnomasi bo‘yicha garovga qo‘yilgan mol-mulkni ko‘zdan kechirdim" -> Men, «PULLOL BUSINESS MIKROMOLIYA TASHKILOTI» MChJ” Buxoro filiali boshlig'ii IKROMOV B.A., jismoniy shaxs TURAYEV ISROIL BURIYEVICH 6 yanvar 2026 y.dan №3-BR-sonli mikroqarz shartnomasi bo‘yicha garovga qo‘yilgan mol-mulkni ko‘zdan kechirdim
A8: Garov sifatida quyida ko’rsatilgan mulk qabul qilinadi:
A9: =dalolatnoma!A20 -> Nomi | C9: =dalolatnoma!B20 -> Kuzov turi va kuzov raqami* | E9: =dalolatnoma!D20 -> Dvigatel va shassi raqami* | G9: =dalolatnoma!E20 -> Ishlab chiqarilgan yili va rangi**
A10: =dalolatnoma!A21 -> COBALT | C10: =dalolatnoma!B21 -> kuzov turi - YENGIL SEDAN, kuzov raqami XWBJF69VEGA010429 | E10: =dalolatnoma!D21 -> dvigatel raqami B15D211163412DJCX0337, shassi raqami - RAKAMSIZ | G10: =dalolatnoma!E21 -> rangi - OQ OLIMPIYSKAYA BELAYA, ishlab chiqarilgan yili - 2016
A11: =dalolatnoma!A22:E22 -> -* avtotransport egasi: USMONOV NURIDDID IXTIYOROVICH
A12: =dalolatnoma!A23:E23 -> -* texnik pasport: AAF 2401056 01.12.2020 y.
A13: =dalolatnoma!A24:E24 -> -* roʻyxatdan oʻtgan manzili/garaj manzili: BUXORO VILOYATI BUXORO SHAHRI CHO'LPON KO'CHASI 22-A-UY
A14: =dalolatnoma!A25:E25 -> -* davlat raqami: 80G291QA
A15: =+"Shu bilan birga, yuqoridagi mulkning kelishilgan garov qiymati "&dalolatnoma!E30 -> Shu bilan birga, yuqoridagi mulkning kelishilgan garov qiymati 46 200 000,00 (qirq olti million ikki yuz ming so'm)
A17: Garovga qo‘yilgan mol-mulkni ko‘zdan kechirish natijasida ushbu mulk qoniqarli holatda ekanligi ma’lum bo‘ldi va bu haqida mazkur dalolatnoma tuzildi
A22: =umumiy_malumot!A150 -> Buxoro filiali boshlig'i | H22: =umumiy_malumot!B150 -> IKROMOV B.A.
A24: Monitoring bo'limi boshlig'i | H24: =umumiy_malumot!B160 -> 0
A26: Jismoniy shaxs, qarzdor | H26: =umumiy_malumot!B7 -> TURAYEV I.B.

Sheet monitoring_2
A2: =""&" "&umumiy_malumot!B74&"-sonli "&" "&umumiy_malumot!C64&" shartnomasi bo‘yicha garovga qo‘yilgan mol-mulkni tekshirish bo’yicha "&umumiy_malumot!B5&" bilan tuzilgan dalolatnomasi" -> 6 yanvar 2026 y.dan №3-BR-sonli Mikroqarz shartnomasi bo‘yicha garovga qo‘yilgan mol-mulkni tekshirish bo’yicha TURAYEV ISROIL BURIYEVICH bilan tuzilgan dalolatnomasi
A5: Toshkent shahri | H5: =TEXT(+umumiy_malumot!B2+360,"ДД.ММ.ГГГГ") -> 01.01.2027
A7: =" Men, "&umumiy_malumot!B147&" "&umumiy_malumot!A150&"i "&umumiy_malumot!B150&", jismoniy shaxs "&" "&umumiy_malumot!B5&" "&" "&umumiy_malumot!B74&"-sonli "&umumiy_malumot!C64&" shartnomasi bo‘yicha garovga qo‘yilgan mol-mulkni ko‘zdan kechirdim" -> Men, «PULLOL BUSINESS MIKROMOLIYA TASHKILOTI» MChJ Buxoro filiali boshlig'ii IKROMOV B.A., jismoniy shaxs TURAYEV ISROIL BURIYEVICH 6 yanvar 2026 y.dan №3-BR-sonli Mikroqarz shartnomasi bo‘yicha garovga qo‘yilgan mol-mulkni ko‘zdan kechirdim
A8: Garov sifatida quyida ko’rsatilgan mulk qabul qilinadi:
A9: =monitoring_1!A9 -> Nomi | C9: =monitoring_1!C9 -> Kuzov turi va kuzov raqami* | E9: =monitoring_1!E9 -> Dvigatel va shassi raqami* | G9: =monitoring_1!G9 -> Ishlab chiqarilgan yili va rangi**
A10: =monitoring_1!A10 -> COBALT | C10: =monitoring_1!C10 -> kuzov turi - YENGIL SEDAN, kuzov raqami XWBJF69VEGA010429 | E10: =monitoring_1!E10 -> dvigatel raqami B15D211163412DJCX0337, shassi raqami - RAKAMSIZ | G10: =monitoring_1!G10 -> rangi - OQ OLIMPIYSKAYA BELAYA, ishlab chiqarilgan yili - 2016
A11: =dalolatnoma!A22:E22 -> -* avtotransport egasi: USMONOV NURIDDID IXTIYOROVICH
A12: =dalolatnoma!A23:E23 -> -* texnik pasport: AAF 2401056 01.12.2020 y.
A13: =dalolatnoma!A24:E24 -> -* roʻyxatdan oʻtgan manzili/garaj manzili: BUXORO VILOYATI BUXORO SHAHRI CHO'LPON KO'CHASI 22-A-UY
A14: =dalolatnoma!A25:E25 -> -* davlat raqami: 80G291QA
A15: =+"Shu bilan birga, yuqoridagi mulkning kelishilgan garov qiymati "&dalolatnoma!E30 -> Shu bilan birga, yuqoridagi mulkning kelishilgan garov qiymati 46 200 000,00 (qirq olti million ikki yuz ming so'm)
A17: Garovga qo‘yilgan mol-mulkni ko‘zdan kechirish natijasida ushbu mulk qoniqarli holatda ekanligi ma’lum bo‘ldi va bu haqida mazkur dalolatnoma tuzildi
A22: =umumiy_malumot!A150 -> Buxoro filiali boshlig'i | H22: =umumiy_malumot!B150 -> IKROMOV B.A.
A24: Monitoring bo'limi boshlig'i | H24: =umumiy_malumot!B160 -> 0
A26: Jismoniy shaxs, qarzdor | H26: =umumiy_malumot!B7 -> TURAYEV I.B.

Sheet monitoring_3
A2: =""&" "&umumiy_malumot!B74&"-sonli "&" "&umumiy_malumot!C64&" shartnomasi bo‘yicha garovga qo‘yilgan mol-mulkni tekshirish bo’yicha "&umumiy_malumot!B5&" bilan tuzilgan dalolatnomasi" -> 6 yanvar 2026 y.dan №3-BR-sonli Mikroqarz shartnomasi bo‘yicha garovga qo‘yilgan mol-mulkni tekshirish bo’yicha TURAYEV ISROIL BURIYEVICH bilan tuzilgan dalolatnomasi
A5: Toshkent shahri | H5: =TEXT(+umumiy_malumot!B2+540,"ДД.ММ.ГГГГ") -> 30.06.2027
A7: =" Men, "&umumiy_malumot!B147&" "&umumiy_malumot!A150&"i "&umumiy_malumot!B150&", jismoniy shaxs "&" "&umumiy_malumot!B5&" "&" "&umumiy_malumot!B74&"-sonli "&umumiy_malumot!C64&" shartnomasi bo‘yicha garovga qo‘yilgan mol-mulkni ko‘zdan kechirdim" -> Men, «PULLOL BUSINESS MIKROMOLIYA TASHKILOTI» MChJ Buxoro filiali boshlig'ii IKROMOV B.A., jismoniy shaxs TURAYEV ISROIL BURIYEVICH 6 yanvar 2026 y.dan №3-BR-sonli Mikroqarz shartnomasi bo‘yicha garovga qo‘yilgan mol-mulkni ko‘zdan kechirdim
A8: Garov sifatida quyida ko’rsatilgan mulk qabul qilinadi:
A9: =monitoring_1!A9 -> Nomi | C9: =monitoring_1!C9 -> Kuzov turi va kuzov raqami* | E9: =monitoring_1!E9 -> Dvigatel va shassi raqami* | G9: =monitoring_1!G9 -> Ishlab chiqarilgan yili va rangi**
A10: =monitoring_1!A10 -> COBALT | C10: =monitoring_1!C10 -> kuzov turi - YENGIL SEDAN, kuzov raqami XWBJF69VEGA010429 | E10: =monitoring_1!E10 -> dvigatel raqami B15D211163412DJCX0337, shassi raqami - RAKAMSIZ | G10: =monitoring_1!G10 -> rangi - OQ OLIMPIYSKAYA BELAYA, ishlab chiqarilgan yili - 2016
A11: =dalolatnoma!A22:E22 -> -* avtotransport egasi: USMONOV NURIDDID IXTIYOROVICH
A12: =dalolatnoma!A23:E23 -> -* texnik pasport: AAF 2401056 01.12.2020 y.
A13: =dalolatnoma!A24:E24 -> -* roʻyxatdan oʻtgan manzili/garaj manzili: BUXORO VILOYATI BUXORO SHAHRI CHO'LPON KO'CHASI 22-A-UY
A14: =dalolatnoma!A25:E25 -> -* davlat raqami: 80G291QA
A15: =+"Shu bilan birga, yuqoridagi mulkning kelishilgan garov qiymati "&dalolatnoma!E30 -> Shu bilan birga, yuqoridagi mulkning kelishilgan garov qiymati 46 200 000,00 (qirq olti million ikki yuz ming so'm)
A17: Garovga qo‘yilgan mol-mulkni ko‘zdan kechirish natijasida ushbu mulk qoniqarli holatda ekanligi ma’lum bo‘ldi va bu haqida mazkur dalolatnoma tuzildi
A22: =umumiy_malumot!A150 -> Buxoro filiali boshlig'i | H22: =umumiy_malumot!B150 -> IKROMOV B.A.
A24: Monitoring bo'limi boshlig'i | H24: =umumiy_malumot!B160 -> 0
A26: Jismoniy shaxs, qarzdor | H26: =umumiy_malumot!B7 -> TURAYEV I.B.

Sheet monitoring_4
A2: =""&" "&umumiy_malumot!B74&"-sonli "&" "&umumiy_malumot!C64&" shartnomasi bo‘yicha garovga qo‘yilgan mol-mulkni tekshirish bo’yicha "&umumiy_malumot!B5&" bilan tuzilgan dalolatnomasi" -> 6 yanvar 2026 y.dan №3-BR-sonli Mikroqarz shartnomasi bo‘yicha garovga qo‘yilgan mol-mulkni tekshirish bo’yicha TURAYEV ISROIL BURIYEVICH bilan tuzilgan dalolatnomasi
A5: Toshkent shahri | H5: =TEXT(+umumiy_malumot!B2+720,"ДД.ММ.ГГГГ") -> 27.12.2027
A7: =" Men, "&umumiy_malumot!B147&" "&umumiy_malumot!A150&"i "&umumiy_malumot!B150&", jismoniy shaxs "&" "&umumiy_malumot!B5&" "&" "&umumiy_malumot!B74&"-sonli "&umumiy_malumot!C64&" shartnomasi bo‘yicha garovga qo‘yilgan mol-mulkni ko‘zdan kechirdim" -> Men, «PULLOL BUSINESS MIKROMOLIYA TASHKILOTI» MChJ Buxoro filiali boshlig'ii IKROMOV B.A., jismoniy shaxs TURAYEV ISROIL BURIYEVICH 6 yanvar 2026 y.dan №3-BR-sonli Mikroqarz shartnomasi bo‘yicha garovga qo‘yilgan mol-mulkni ko‘zdan kechirdim
A8: Garov sifatida quyida ko’rsatilgan mulk qabul qilinadi:
A9: =monitoring_1!A9 -> Nomi | C9: =monitoring_1!C9 -> Kuzov turi va kuzov raqami* | E9: =monitoring_1!E9 -> Dvigatel va shassi raqami* | G9: =monitoring_1!G9 -> Ishlab chiqarilgan yili va rangi**
A10: =monitoring_1!A10 -> COBALT | C10: =monitoring_1!C10 -> kuzov turi - YENGIL SEDAN, kuzov raqami XWBJF69VEGA010429 | E10: =monitoring_1!E10 -> dvigatel raqami B15D211163412DJCX0337, shassi raqami - RAKAMSIZ | G10: =monitoring_1!G10 -> rangi - OQ OLIMPIYSKAYA BELAYA, ishlab chiqarilgan yili - 2016
A11: =dalolatnoma!A22:E22 -> -* avtotransport egasi: USMONOV NURIDDID IXTIYOROVICH
A12: =dalolatnoma!A23:E23 -> -* texnik pasport: AAF 2401056 01.12.2020 y.
A13: =dalolatnoma!A24:E24 -> -* roʻyxatdan oʻtgan manzili/garaj manzili: BUXORO VILOYATI BUXORO SHAHRI CHO'LPON KO'CHASI 22-A-UY
A14: =dalolatnoma!A25:E25 -> -* davlat raqami: 80G291QA
A15: =+"Shu bilan birga, yuqoridagi mulkning kelishilgan garov qiymati "&dalolatnoma!E30 -> Shu bilan birga, yuqoridagi mulkning kelishilgan garov qiymati 46 200 000,00 (qirq olti million ikki yuz ming so'm)
A17: Garovga qo‘yilgan mol-mulkni ko‘zdan kechirish natijasida ushbu mulk qoniqarli holatda ekanligi ma’lum bo‘ldi va bu haqida mazkur dalolatnoma tuzildi
A22: =umumiy_malumot!A150 -> Buxoro filiali boshlig'i | H22: =umumiy_malumot!B150 -> IKROMOV B.A.
A24: Monitoring bo'limi boshlig'i | H24: =umumiy_malumot!B160 -> 0
A26: Jismoniy shaxs, qarzdor | H26: =umumiy_malumot!B7 -> TURAYEV I.B.

Sheet График дифференц
E1: Приложение №1
F2: ="к договору микрозайма "&umumiy_malumot!B74&"" -> к договору микрозайма 6 yanvar 2026 y.dan №3-BR
A4: График погашения
L5: =umumiy_malumot!B81 -> 36
A6: № | B6: Дата погашения | C6: Остаток основного долга | D6: Сумма погашения, сум
D7: основного долга | E7: процентов* | F7: всего*
A8: 1 | B8: =umumiy_malumot!B79 -> 46069 | C8: =umumiy_malumot!B75 -> 33000000 | D8: =IF(IF(C8=0,L8,IF(C8>1,I8))="",0,(IF(C8=0,L8,IF(C8>1,I8)))) -> 916666.67 | E8: =IF(C8=0,N6,IF(C8>1,L8)) -> 2038767.2 | F8: =IF(C8=0,O6,IF(C8>1,M8)) -> 2955433.9 | G8: =B8-umumiy_malumot!B67 -> 41 | H8: =DATE(YEAR(B8),12,31)-DATE(YEAR(B8),1,1)+1 -> 365 | I8: =IF(umumiy_malumot!B83=0,ROUND(C8/L5,2),"") -> 916666.67 | L8: =ROUND(C8*umumiy_malumot!$B$84/H8,2)*G8 -> 2038767.2 | M8: =D8+E8 -> 2955433.9 | O8: =TEXT(B8,"ддд") -> Пн | P8: =IF(O8=$U$8,2,IF(O8=$V$8,1,0)) -> 0 | Q8: =DAY(umumiy_malumot!$B$78)+P8 -> 15 | S8: Чт | T8: Пт | U8: Сб | V8: Вс
A9: 2 | B9: =IF(A9<=umumiy_malumot!$B$81,DATE(YEAR(R9),MONTH(R9),DAY(IF(A9=umumiy_malumot!$B$81,umumiy_malumot!$B$67,IF(A9<umumiy_malumot!$B$81,(Q9),IF(A9>umumiy_malumot!$B$81,$H$56,0)))))) -> 46097 | C9: =C8-D8 -> 32083333 | D9: =IF(C9=0,L9,IF(C9>1,I9)) -> 916666.67 | E9: =IF(C9=0,N8,IF(C9>1,L9)) -> 1353653 | F9: =IF(C9=0,N8,IF(C9>1,M9)) -> 2270319.7 | G9: =B9-B8 -> 28 | H9: =DATE(YEAR(B9),12,31)-DATE(YEAR(B9),1,1)+1 -> 365 | I9: =IF(I8="",ROUND(C8/(L5-1),2),I8) -> 916666.67 | L9: =ROUND(C9*umumiy_malumot!$B$84/H9,2)*G9 -> 1353653 | M9: =D9+E9 -> 2270319.7 | O9: =TEXT(R9,"ддд") -> Вс | P9: =IF(O9=$U$8,2,IF(O9=$V$8,1,0)) -> 1 | Q9: =DAY(umumiy_malumot!$B$78)+P9 -> 16 | R9: =IF(A9<=umumiy_malumot!$B$81,DATE(YEAR($B$8),MONTH($B$8)+A8,DAY(umumiy_malumot!$B$78)),0) -> 46096
A10: 3 | B10: =IF(A10<=umumiy_malumot!$B$81,DATE(YEAR(R10),MONTH(R10),DAY(IF(A10=umumiy_malumot!$B$81,umumiy_malumot!$B$67,IF(A10<umumiy_malumot!$B$81,(Q10),IF(A10>umumiy_malumot!$B$81,$H$56,0)))))) -> 46127 | C10: =C9-D9 -> 31166667 | D10: =IF(C10=0,L10,IF(C10>1,I10)) -> 916666.67 | E10: =IF(C10=0,N9,IF(C10>1,L10)) -> 1408904.1 | F10: =IF(C10=0,N9,IF(C10>1,M10)) -> 2325570.8 | G10: =B10-B9 -> 30 | H10: =DATE(YEAR(B10),12,31)-DATE(YEAR(B10),1,1)+1 -> 365 | I10: =I9 -> 916666.67 | L10: =ROUND(C10*umumiy_malumot!$B$84/H10,2)*G10 -> 1408904.1 | M10: =D10+E10 -> 2325570.8 | O10: =TEXT(R10,"ддд") -> Ср | P10: =IF(O10=$U$8,2,IF(O10=$V$8,1,0)) -> 0 | Q10: =DAY(umumiy_malumot!$B$78)+P10 -> 15 | R10: =IF(A10<=umumiy_malumot!$B$81,DATE(YEAR($B$8),MONTH($B$8)+A9,DAY(umumiy_malumot!$B$78)),0) -> 46127
A11: 4 | B11: =IF(A11<=umumiy_malumot!$B$81,DATE(YEAR(R11),MONTH(R11),DAY(IF(A11=umumiy_malumot!$B$81,umumiy_malumot!$B$67,IF(A11<umumiy_malumot!$B$81,(Q11),IF(A11>umumiy_malumot!$B$81,$H$56,0)))))) -> 46157 | C11: =C10-D10 -> 30250000 | D11: =IF(C11=0,L11,IF(C11>1,I11)) -> 916666.67 | E11: =IF(C11=0,N10,IF(C11>1,L11)) -> 1367465.7 | F11: =IF(C11=0,N10,IF(C11>1,M11)) -> 2284132.4 | G11: =B11-B10 -> 30 | H11: =DATE(YEAR(B11),12,31)-DATE(YEAR(B11),1,1)+1 -> 365 | I11: =I10 -> 916666.67 | L11: =ROUND(C11*umumiy_malumot!$B$84/H11,2)*G11 -> 1367465.7 | M11: =D11+E11 -> 2284132.4 | O11: =TEXT(R11,"ддд") -> Пт | P11: =IF(O11=$U$8,2,IF(O11=$V$8,1,0)) -> 0 | Q11: =DAY(umumiy_malumot!$B$78)+P11 -> 15 | R11: =IF(A11<=umumiy_malumot!$B$81,DATE(YEAR($B$8),MONTH($B$8)+A10,DAY(umumiy_malumot!$B$78)),0) -> 46157
A12: 5 | B12: =IF(A12<=umumiy_malumot!$B$81,DATE(YEAR(R12),MONTH(R12),DAY(IF(A12=umumiy_malumot!$B$81,umumiy_malumot!$B$67,IF(A12<umumiy_malumot!$B$81,(Q12),IF(A12>umumiy_malumot!$B$81,$H$56,0)))))) -> 46188 | C12: =C11-D11 -> 29333333 | D12: =IF(C12=0,L12,IF(C12>1,I12)) -> 916666.67 | E12: =IF(C12=0,N11,IF(C12>1,L12)) -> 1370228.2 | F12: =IF(C12=0,N11,IF(C12>1,M12)) -> 2286894.9 | G12: =B12-B11 -> 31 | H12: =DATE(YEAR(B12),12,31)-DATE(YEAR(B12),1,1)+1 -> 365 | I12: =I11 -> 916666.67 | J12: =umumiy_malumot!B75 -> 33000000 | L12: =ROUND(C12*umumiy_malumot!$B$84/H12,2)*G12 -> 1370228.2 | M12: =D12+E12 -> 2286894.9 | O12: =TEXT(R12,"ддд") -> Пн | P12: =IF(O12=$U$8,2,IF(O12=$V$8,1,0)) -> 0 | Q12: =DAY(umumiy_malumot!$B$78)+P12 -> 15 | R12: =IF(A12<=umumiy_malumot!$B$81,DATE(YEAR($B$8),MONTH($B$8)+A11,DAY(umumiy_malumot!$B$78)),0) -> 46188
A13: 6 | B13: =IF(A13<=umumiy_malumot!$B$81,DATE(YEAR(R13),MONTH(R13),DAY(IF(A13=umumiy_malumot!$B$81,umumiy_malumot!$B$67,IF(A13<umumiy_malumot!$B$81,(Q13),IF(A13>umumiy_malumot!$B$81,$H$56,0)))))) -> 46218 | C13: =C12-D12 -> 28416667 | D13: =IF(C13=0,L13,IF(C13>1,I13)) -> 916666.67 | E13: =IF(C13=0,N12,IF(C13>1,L13)) -> 1284588.9 | F13: =IF(C13=0,N12,IF(C13>1,M13)) -> 2201255.6 | G13: =B13-B12 -> 30 | H13: =DATE(YEAR(B13),12,31)-DATE(YEAR(B13),1,1)+1 -> 365 | I13: =IF(L5=H1,K13,IF(L5>H1,I12)) -> 916666.67 | J13: =SUM($I$8:I12) -> 4583333.4 | K13: =$J$12-J13 -> 28416667 | L13: =ROUND(C13*umumiy_malumot!$B$84/H13,2)*G13 -> 1284588.9 | M13: =D13+E13 -> 2201255.6 | O13: =TEXT(R13,"ддд") -> Ср | P13: =IF(O13=$U$8,2,IF(O13=$V$8,1,0)) -> 0 | Q13: =DAY(umumiy_malumot!$B$78)+P13 -> 15 | R13: =IF(A13<=umumiy_malumot!$B$81,DATE(YEAR($B$8),MONTH($B$8)+A12,DAY(umumiy_malumot!$B$78)),0) -> 46218
A14: 7 | B14: =IF(A14<=umumiy_malumot!$B$81,DATE(YEAR(R14),MONTH(R14),DAY(IF(A14=umumiy_malumot!$B$81,umumiy_malumot!$B$67,IF(A14<umumiy_malumot!$B$81,(Q14),IF(A14>umumiy_malumot!$B$81,$H$56,0)))))) -> 46251 | C14: =C13-D13 -> 27500000 | D14: =IF(C14=0,L14,IF(C14>1,I14)) -> 916666.67 | E14: =IF(C14=0,N13,IF(C14>1,L14)) -> 1367465.9 | F14: =IF(C14=0,N13,IF(C14>1,M14)) -> 2284132.6 | G14: =B14-B13 -> 33 | H14: =DATE(YEAR(B14),12,31)-DATE(YEAR(B14),1,1)+1 -> 365 | I14: =IF($L$5=A14,K14,IF($L$5>A14,I13)) -> 916666.67 | J14: =SUM($I$8:I13) -> 5500000 | K14: =$J$12-J14 -> 27500000 | L14: =ROUND(C14*umumiy_malumot!$B$84/H14,2)*G14 -> 1367465.9 | M14: =D14+E14 -> 2284132.6 | O14: =TEXT(R14,"ддд") -> Сб | P14: =IF(O14=$U$8,2,IF(O14=$V$8,1,0)) -> 2 | Q14: =DAY(umumiy_malumot!$B$78)+P14 -> 17 | R14: =IF(A14<=umumiy_malumot!$B$81,DATE(YEAR($B$8),MONTH($B$8)+A13,DAY(umumiy_malumot!$B$78)),0) -> 46249
A15: 8 | B15: =IF(A15<=umumiy_malumot!$B$81,DATE(YEAR(R15),MONTH(R15),DAY(IF(A15=umumiy_malumot!$B$81,umumiy_malumot!$B$67,IF(A15<umumiy_malumot!$B$81,(Q15),IF(A15>umumiy_malumot!$B$81,$H$56,0)))))) -> 46280 | C15: =C14-D14 -> 26583333 | D15: =IF(C15=0,L15,IF(C15>1,I15)) -> 916666.67 | E15: =IF(C15=0,N14,IF(C15>1,L15)) -> 1161655.3 | F15: =IF(C15=0,N14,IF(C15>1,M15)) -> 2078322 | G15: =B15-B14 -> 29 | H15: =DATE(YEAR(B15),12,31)-DATE(YEAR(B15),1,1)+1 -> 365 | I15: =IF($L$5=A15,K15,IF($L$5>A15,I14)) -> 916666.67 | J15: =SUM($I$8:I14) -> 6416666.7 | K15: =$J$12-J15 -> 26583333 | L15: =ROUND(C15*umumiy_malumot!$B$84/H15,2)*G15 -> 1161655.3 | M15: =D15+E15 -> 2078322 | O15: =TEXT(R15,"ддд") -> Вт | P15: =IF(O15=$U$8,2,IF(O15=$V$8,1,0)) -> 0 | Q15: =DAY(umumiy_malumot!$B$78)+P15 -> 15 | R15: =IF(A15<=umumiy_malumot!$B$81,DATE(YEAR($B$8),MONTH($B$8)+A14,DAY(umumiy_malumot!$B$78)),0) -> 46280
A16: 9 | B16: =IF(A16<=umumiy_malumot!$B$81,DATE(YEAR(R16),MONTH(R16),DAY(IF(A16=umumiy_malumot!$B$81,umumiy_malumot!$B$67,IF(A16<umumiy_malumot!$B$81,(Q16),IF(A16>umumiy_malumot!$B$81,$H$56,0)))))) -> 46310 | C16: =C15-D15 -> 25666667 | D16: =IF(C16=0,L16,IF(C16>1,I16)) -> 916666.67 | E16: =IF(C16=0,N15,IF(C16>1,L16)) -> 1160274 | F16: =IF(C16=0,N15,IF(C16>1,M16)) -> 2076940.7 | G16: =B16-B15 -> 30 | H16: =DATE(YEAR(B16),12,31)-DATE(YEAR(B16),1,1)+1 -> 365 | I16: =IF($L$5=A16,K16,IF($L$5>A16,I15)) -> 916666.67 | J16: =SUM($I$8:I15) -> 7333333.4 | K16: =$J$12-J16 -> 25666667 | L16: =ROUND(C16*umumiy_malumot!$B$84/H16,2)*G16 -> 1160274 | M16: =D16+E16 -> 2076940.7 | O16: =TEXT(R16,"ддд") -> Чт | P16: =IF(O16=$U$8,2,IF(O16=$V$8,1,0)) -> 0 | Q16: =DAY(umumiy_malumot!$B$78)+P16 -> 15 | R16: =IF(A16<=umumiy_malumot!$B$81,DATE(YEAR($B$8),MONTH($B$8)+A15,DAY(umumiy_malumot!$B$78)),0) -> 46310
A17: 10 | B17: =IF(A17<=umumiy_malumot!$B$81,DATE(YEAR(R17),MONTH(R17),DAY(IF(A17=umumiy_malumot!$B$81,umumiy_malumot!$B$67,IF(A17<umumiy_malumot!$B$81,(Q17),IF(A17>umumiy_malumot!$B$81,$H$56,0)))))) -> 46342 | C17: =C16-D16 -> 24750000 | D17: =IF(C17=0,L17,IF(C17>1,I17)) -> 916666.67 | E17: =IF(C17=0,N16,IF(C17>1,L17)) -> 1193424.6 | F17: =IF(C17=0,N16,IF(C17>1,M17)) -> 2110091.3 | G17: =B17-B16 -> 32 | H17: =DATE(YEAR(B17),12,31)-DATE(YEAR(B17),1,1)+1 -> 365 | I17: =IF($L$5=A17,K17,IF($L$5>A17,I16)) -> 916666.67 | J17: =SUM($I$8:I16) -> 8250000 | K17: =$J$12-J17 -> 24750000 | L17: =ROUND(C17*umumiy_malumot!$B$84/H17,2)*G17 -> 1193424.6 | M17: =D17+E17 -> 2110091.3 | O17: =TEXT(R17,"ддд") -> Вс | P17: =IF(O17=$U$8,2,IF(O17=$V$8,1,0)) -> 1 | Q17: =DAY(umumiy_malumot!$B$78)+P17 -> 16 | R17: =IF(A17<=umumiy_malumot!$B$81,DATE(YEAR($B$8),MONTH($B$8)+A16,DAY(umumiy_malumot!$B$78)),0) -> 46341
A18: 11 | B18: =IF(A18<=umumiy_malumot!$B$81,DATE(YEAR(R18),MONTH(R18),DAY(IF(A18=umumiy_malumot!$B$81,umumiy_malumot!$B$67,IF(A18<umumiy_malumot!$B$81,(Q18),IF(A18>umumiy_malumot!$B$81,$H$56,0)))))) -> 46371 | C18: =C17-D17 -> 23833333 | D18: =IF(C18=0,L18,IF(C18>1,I18)) -> 916666.67 | E18: =IF(C18=0,N17,IF(C18>1,L18)) -> 1041484 | F18: =IF(C18=0,N17,IF(C18>1,M18)) -> 1958150.6 | G18: =B18-B17 -> 29 | H18: =DATE(YEAR(B18),12,31)-DATE(YEAR(B18),1,1)+1 -> 365 | I18: =IF($L$5=A18,K18,IF($L$5>A18,I17)) -> 916666.67 | J18: =SUM($I$8:I17) -> 9166666.7 | K18: =$J$12-J18 -> 23833333 | L18: =ROUND(C18*umumiy_malumot!$B$84/H18,2)*G18 -> 1041484 | M18: =D18+E18 -> 1958150.6 | O18: =TEXT(R18,"ддд") -> Вт | P18: =IF(O18=$U$8,2,IF(O18=$V$8,1,0)) -> 0 | Q18: =DAY(umumiy_malumot!$B$78)+P18 -> 15 | R18: =IF(A18<=umumiy_malumot!$B$81,DATE(YEAR($B$8),MONTH($B$8)+A17,DAY(umumiy_malumot!$B$78)),0) -> 46371
A19: 12 | B19: =IF(A19<=umumiy_malumot!$B$81,DATE(YEAR(R19),MONTH(R19),DAY(IF(A19=umumiy_malumot!$B$81,umumiy_malumot!$B$67,IF(A19<umumiy_malumot!$B$81,(Q19),IF(A19>umumiy_malumot!$B$81,$H$56,0)))))) -> 46402 | C19: =C18-D18 -> 22916667 | D19: =IF(C19=0,L19,IF(C19>1,I19)) -> 916666.67 | E19: =IF(C19=0,N18,IF(C19>1,L19)) -> 1070490.8 | F19: =IF(C19=0,N18,IF(C19>1,M19)) -> 1987157.4 | G19: =B19-B18 -> 31 | H19: =DATE(YEAR(B19),12,31)-DATE(YEAR(B19),1,1)+1 -> 365 | I19: =IF($L$5=A19,K19,IF($L$5>A19,I18)) -> 916666.67 | J19: =SUM($I$8:I18) -> 10083333 | K19: =$J$12-J19 -> 22916667 | L19: =ROUND(C19*umumiy_malumot!$B$84/H19,2)*G19 -> 1070490.8 | M19: =D19+E19 -> 1987157.4 | O19: =TEXT(R19,"ддд") -> Пт | P19: =IF(O19=$U$8,2,IF(O19=$V$8,1,0)) -> 0 | Q19: =DAY(umumiy_malumot!$B$78)+P19 -> 15 | R19: =IF(A19<=umumiy_malumot!$B$81,DATE(YEAR($B$8),MONTH($B$8)+A18,DAY(umumiy_malumot!$B$78)),0) -> 46402
A20: 13 | B20: =IF(A20<=umumiy_malumot!$B$81,DATE(YEAR(R20),MONTH(R20),DAY(IF(A20=umumiy_malumot!$B$81,umumiy_malumot!$B$67,IF(A20<umumiy_malumot!$B$81,(Q20),IF(A20>umumiy_malumot!$B$81,$H$56,0)))))) -> 46433 | C20: =C19-D19 -> 22000000 | D20: =IF(C20=0,L20,IF(C20>1,I20)) -> 916666.67 | E20: =IF(C20=0,N19,IF(C20>1,L20)) -> 1027671.1 | F20: =IF(C20=0,N19,IF(C20>1,M20)) -> 1944337.8 | G20: =B20-B19 -> 31 | H20: =DATE(YEAR(B20),12,31)-DATE(YEAR(B20),1,1)+1 -> 365 | I20: =IF($L$5=A20,K20,IF($L$5>A20,I19)) -> 916666.67 | J20: =SUM($I$8:I19) -> 11000000 | K20: =$J$12-J20 -> 22000000 | L20: =ROUND(C20*umumiy_malumot!$B$84/H20,2)*G20 -> 1027671.1 | M20: =D20+E20 -> 1944337.8 | O20: =TEXT(R20,"ддд") -> Пн | P20: =IF(O20=$U$8,2,IF(O20=$V$8,1,0)) -> 0 | Q20: =DAY(umumiy_malumot!$B$78)+P20 -> 15 | R20: =IF(A20<=umumiy_malumot!$B$81,DATE(YEAR($B$8),MONTH($B$8)+A19,DAY(umumiy_malumot!$B$78)),0) -> 46433
A21: 14 | B21: =IF(A21<=umumiy_malumot!$B$81,DATE(YEAR(R21),MONTH(R21),DAY(IF(A21=umumiy_malumot!$B$81,umumiy_malumot!$B$67,IF(A21<umumiy_malumot!$B$81,(Q21),IF(A21>umumiy_malumot!$B$81,$H$56,0)))))) -> 46461 | C21: =C20-D20 -> 21083333 | D21: =IF(C21=0,L21,IF(C21>1,I21)) -> 916666.67 | E21: =IF(C21=0,N20,IF(C21>1,L21)) -> 889543.48 | F21: =IF(C21=0,N20,IF(C21>1,M21)) -> 1806210.1 | G21: =B21-B20 -> 28 | H21: =DATE(YEAR(B21),12,31)-DATE(YEAR(B21),1,1)+1 -> 365 | I21: =IF($L$5=A21,K21,IF($L$5>A21,I20)) -> 916666.67 | J21: =SUM($I$8:I20) -> 11916667 | K21: =$J$12-J21 -> 21083333 | L21: =ROUND(C21*umumiy_malumot!$B$84/H21,2)*G21 -> 889543.48 | M21: =D21+E21 -> 1806210.1 | O21: =TEXT(R21,"ддд") -> Пн | P21: =IF(O21=$U$8,2,IF(O21=$V$8,1,0)) -> 0 | Q21: =DAY(umumiy_malumot!$B$78)+P21 -> 15 | R21: =IF(A21<=umumiy_malumot!$B$81,DATE(YEAR($B$8),MONTH($B$8)+A20,DAY(umumiy_malumot!$B$78)),0) -> 46461
A22: 15 | B22: =IF(A22<=umumiy_malumot!$B$81,DATE(YEAR(R22),MONTH(R22),DAY(IF(A22=umumiy_malumot!$B$81,umumiy_malumot!$B$67,IF(A22<umumiy_malumot!$B$81,(Q22),IF(A22>umumiy_malumot!$B$81,$H$56,0)))))) -> 46492 | C22: =C21-D21 -> 20166667 | D22: =IF(C22=0,L22,IF(C22>1,I22)) -> 916666.67 | E22: =IF(C22=0,N21,IF(C22>1,L22)) -> 942032.03 | F22: =IF(C22=0,N21,IF(C22>1,M22)) -> 1858698.7 | G22: =B22-B21 -> 31 | H22: =DATE(YEAR(B22),12,31)-DATE(YEAR(B22),1,1)+1 -> 365 | I22: =IF($L$5=A22,K22,IF($L$5>A22,I21)) -> 916666.67 | J22: =SUM($I$8:I21) -> 12833333 | K22: =$J$12-J22 -> 20166667 | L22: =ROUND(C22*umumiy_malumot!$B$84/H22,2)*G22 -> 942032.03 | M22: =D22+E22 -> 1858698.7 | O22: =TEXT(R22,"ддд") -> Чт | P22: =IF(O22=$U$8,2,IF(O22=$V$8,1,0)) -> 0 | Q22: =DAY(umumiy_malumot!$B$78)+P22 -> 15 | R22: =IF(A22<=umumiy_malumot!$B$81,DATE(YEAR($B$8),MONTH($B$8)+A21,DAY(umumiy_malumot!$B$78)),0) -> 46492
A23: 16 | B23: =IF(A23<=umumiy_malumot!$B$81,DATE(YEAR(R23),MONTH(R23),DAY(IF(A23=umumiy_malumot!$B$81,umumiy_malumot!$B$67,IF(A23<umumiy_malumot!$B$81,(Q23),IF(A23>umumiy_malumot!$B$81,$H$56,0)))))) -> 46524 | C23: =C22-D22 -> 19250000 | D23: =IF(C23=0,L23,IF(C23>1,I23)) -> 916666.67 | E23: =IF(C23=0,N22,IF(C23>1,L23)) -> 928219.2 | F23: =IF(C23=0,N22,IF(C23>1,M23)) -> 1844885.9 | G23: =B23-B22 -> 32 | H23: =DATE(YEAR(B23),12,31)-DATE(YEAR(B23),1,1)+1 -> 365 | I23: =IF($L$5=A23,K23,IF($L$5>A23,I22)) -> 916666.67 | J23: =SUM($I$8:I22) -> 13750000 | K23: =$J$12-J23 -> 19250000 | L23: =ROUND(C23*umumiy_malumot!$B$84/H23,2)*G23 -> 928219.2 | M23: =D23+E23 -> 1844885.9 | O23: =TEXT(R23,"ддд") -> Сб | P23: =IF(O23=$U$8,2,IF(O23=$V$8,1,0)) -> 2 | Q23: =DAY(umumiy_malumot!$B$78)+P23 -> 17 | R23: =IF(A23<=umumiy_malumot!$B$81,DATE(YEAR($B$8),MONTH($B$8)+A22,DAY(umumiy_malumot!$B$78)),0) -> 46522
A24: 17 | B24: =IF(A24<=umumiy_malumot!$B$81,DATE(YEAR(R24),MONTH(R24),DAY(IF(A24=umumiy_malumot!$B$81,umumiy_malumot!$B$67,IF(A24<umumiy_malumot!$B$81,(Q24),IF(A24>umumiy_malumot!$B$81,$H$56,0)))))) -> 46553 | C24: =C23-D23 -> 18333333 | D24: =IF(C24=0,L24,IF(C24>1,I24)) -> 916666.67 | E24: =IF(C24=0,N23,IF(C24>1,L24)) -> 801141.53 | F24: =IF(C24=0,N23,IF(C24>1,M24)) -> 1717808.2 | G24: =B24-B23 -> 29 | H24: =DATE(YEAR(B24),12,31)-DATE(YEAR(B24),1,1)+1 -> 365 | I24: =IF($L$5=A24,K24,IF($L$5>A24,I23)) -> 916666.67 | J24: =SUM($I$8:I23) -> 14666667 | K24: =$J$12-J24 -> 18333333 | L24: =ROUND(C24*umumiy_malumot!$B$84/H24,2)*G24 -> 801141.53 | M24: =D24+E24 -> 1717808.2 | O24: =TEXT(R24,"ддд") -> Вт | P24: =IF(O24=$U$8,2,IF(O24=$V$8,1,0)) -> 0 | Q24: =DAY(umumiy_malumot!$B$78)+P24 -> 15 | R24: =IF(A24<=umumiy_malumot!$B$81,DATE(YEAR($B$8),MONTH($B$8)+A23,DAY(umumiy_malumot!$B$78)),0) -> 46553
A25: 18 | B25: =IF(A25<=umumiy_malumot!$B$81,DATE(YEAR(R25),MONTH(R25),DAY(IF(A25=umumiy_malumot!$B$81,umumiy_malumot!$B$67,IF(A25<umumiy_malumot!$B$81,(Q25),IF(A25>umumiy_malumot!$B$81,$H$56,0)))))) -> 46583 | C25: =C24-D24 -> 17416667 | D25: =IF(C25=0,L25,IF(C25>1,I25)) -> 916666.67 | E25: =IF(C25=0,N24,IF(C25>1,L25)) -> 787328.7 | F25: =IF(C25=0,N24,IF(C25>1,M25)) -> 1703995.4 | G25: =B25-B24 -> 30 | H25: =DATE(YEAR(B25),12,31)-DATE(YEAR(B25),1,1)+1 -> 365 | I25: =IF($L$5=A25,K25,IF($L$5>A25,I24)) -> 916666.67 | J25: =SUM($I$8:I24) -> 15583333 | K25: =$J$12-J25 -> 17416667 | L25: =ROUND(C25*umumiy_malumot!$B$84/H25,2)*G25 -> 787328.7 | M25: =D25+E25 -> 1703995.4 | O25: =TEXT(R25,"ддд") -> Чт | P25: =IF(O25=$U$8,2,IF(O25=$V$8,1,0)) -> 0 | Q25: =DAY(umumiy_malumot!$B$78)+P25 -> 15 | R25: =IF(A25<=umumiy_malumot!$B$81,DATE(YEAR($B$8),MONTH($B$8)+A24,DAY(umumiy_malumot!$B$78)),0) -> 46583
... A31: 24 | B31: =IF(A31<=umumiy_malumot!$B$81,DATE(YEAR(R31),MONTH(R31),DAY(IF(A31=umumiy_malumot!$B$81,umumiy_malumot!$B$67,IF(A31<umumiy_malumot!$B$81,(Q31),IF(A31>umumiy_malumot!$B$81,$H$56,0)))))) -> 46769 | C31: =C30-D30 -> 11916667 | D31: =IF(C31=0,L31,IF(C31>1,I31)) -> 916666.67 | E31: =IF(C31=0,N30,IF(C31>1,L31)) -> 590949.48 | F31: =IF(C31=0,N30,IF(C31>1,M31)) -> 1507616.2 | G31: =B31-B30 -> 33 | H31: =DATE(YEAR(B31),12,31)-DATE(YEAR(B31),1,1)+1 -> 366 | I31: =IF($L$5=A31,K31,IF($L$5>A31,I30)) -> 916666.67 | J31: =SUM($I$8:I30) -> 21083333 | K31: =$J$12-J31 -> 11916667 | L31: =ROUND(C31*umumiy_malumot!$B$84/H31,2)*G31 -> 590949.48 | M31: =D31+E31 -> 1507616.2 | O31: =TEXT(R31,"ддд") -> Сб | P31: =IF(O31=$U$8,2,IF(O31=$V$8,1,0)) -> 2 | Q31: =DAY(umumiy_malumot!$B$78)+P31 -> 17 | R31: =IF(A31<=umumiy_malumot!$B$81,DATE(YEAR($B$8),MONTH($B$8)+A30,DAY(umumiy_malumot!$B$78)),0) -> 46767
A32: =1+A31 -> 25 | B32: =IF(A32<=umumiy_malumot!$B$81,DATE(YEAR(R32),MONTH(R32),DAY(IF(A32=umumiy_malumot!$B$81,umumiy_malumot!$B$67,IF(A32<umumiy_malumot!$B$81,(Q32),IF(A32>umumiy_malumot!$B$81,$H$56,0)))))) -> 46798 | C32: =C31-D31 -> 11000000 | D32: =IF(C32=0,L32,IF(C32>1,I32)) -> 916666.67 | E32: =IF(C32=0,N31,IF(C32>1,L32)) -> 479371.45 | F32: =IF(C32=0,N31,IF(C32>1,M32)) -> 1396038.1 | G32: =B32-B31 -> 29 | H32: =DATE(YEAR(B32),12,31)-DATE(YEAR(B32),1,1)+1 -> 366 | I32: =IF($L$5=A32,K32,IF($L$5>A32,I31)) -> 916666.67 | J32: =SUM($I$8:I31) -> 22000000 | K32: =$J$12-J32 -> 11000000 | L32: =ROUND(C32*umumiy_malumot!$B$84/H32,2)*G32 -> 479371.45 | M32: =D32+E32 -> 1396038.1 | O32: =TEXT(R32,"ддд") -> Вт | P32: =IF(O32=$U$8,2,IF(O32=$V$8,1,0)) -> 0 | Q32: =DAY(umumiy_malumot!$B$78)+P32 -> 15 | R32: =IF(A32<=umumiy_malumot!$B$81,DATE(YEAR($B$8),MONTH($B$8)+A31,DAY(umumiy_malumot!$B$78)),0) -> 46798
A33: =1+A32 -> 26 | B33: =IF(A33<=umumiy_malumot!$B$81,DATE(YEAR(R33),MONTH(R33),DAY(IF(A33=umumiy_malumot!$B$81,umumiy_malumot!$B$67,IF(A33<umumiy_malumot!$B$81,(Q33),IF(A33>umumiy_malumot!$B$81,$H$56,0)))))) -> 46827 | C33: =C32-D32 -> 10083333 | D33: =IF(C33=0,L33,IF(C33>1,I33)) -> 916666.67 | E33: =IF(C33=0,N32,IF(C33>1,L33)) -> 439423.95 | F33: =IF(C33=0,N32,IF(C33>1,M33)) -> 1356090.6 | G33: =B33-B32 -> 29 | H33: =DATE(YEAR(B33),12,31)-DATE(YEAR(B33),1,1)+1 -> 366 | I33: =IF($L$5=A33,K33,IF($L$5>A33,I32)) -> 916666.67 | J33: =SUM($I$8:I32) -> 22916667 | K33: =$J$12-J33 -> 10083333 | L33: =ROUND(C33*umumiy_malumot!$B$84/H33,2)*G33 -> 439423.95 | M33: =D33+E33 -> 1356090.6 | O33: =TEXT(R33,"ддд") -> Ср | P33: =IF(O33=$U$8,2,IF(O33=$V$8,1,0)) -> 0 | Q33: =DAY(umumiy_malumot!$B$78)+P33 -> 15 | R33: =IF(A33<=umumiy_malumot!$B$81,DATE(YEAR($B$8),MONTH($B$8)+A32,DAY(umumiy_malumot!$B$78)),0) -> 46827
A34: =1+A33 -> 27 | B34: =IF(A34<=umumiy_malumot!$B$81,DATE(YEAR(R34),MONTH(R34),DAY(IF(A34=umumiy_malumot!$B$81,umumiy_malumot!$B$67,IF(A34<umumiy_malumot!$B$81,(Q34),IF(A34>umumiy_malumot!$B$81,$H$56,0)))))) -> 46860 | C34: =C33-D33 -> 9166666.6 | D34: =IF(C34=0,L34,IF(C34>1,I34)) -> 916666.67 | E34: =IF(C34=0,N33,IF(C34>1,L34)) -> 454576.65 | F34: =IF(C34=0,N33,IF(C34>1,M34)) -> 1371243.3 | G34: =B34-B33 -> 33 | H34: =DATE(YEAR(B34),12,31)-DATE(YEAR(B34),1,1)+1 -> 366 | I34: =IF($L$5=A34,K34,IF($L$5>A34,I33)) -> 916666.67 | J34: =SUM($I$8:I33) -> 23833333 | K34: =$J$12-J34 -> 9166666.6 | L34: =ROUND(C34*umumiy_malumot!$B$84/H34,2)*G34 -> 454576.65 | M34: =D34+E34 -> 1371243.3 | O34: =TEXT(R34,"ддд") -> Сб | P34: =IF(O34=$U$8,2,IF(O34=$V$8,1,0)) -> 2 | Q34: =DAY(umumiy_malumot!$B$78)+P34 -> 17 | R34: =IF(A34<=umumiy_malumot!$B$81,DATE(YEAR($B$8),MONTH($B$8)+A33,DAY(umumiy_malumot!$B$78)),0) -> 46858
A35: =1+A34 -> 28 | B35: =IF(A35<=umumiy_malumot!$B$81,DATE(YEAR(R35),MONTH(R35),DAY(IF(A35=umumiy_malumot!$B$81,umumiy_malumot!$B$67,IF(A35<umumiy_malumot!$B$81,(Q35),IF(A35>umumiy_malumot!$B$81,$H$56,0)))))) -> 46888 | C35: =C34-D34 -> 8249999.9 | D35: =IF(C35=0,L35,IF(C35>1,I35)) -> 916666.67 | E35: =IF(C35=0,N34,IF(C35>1,L35)) -> 347131.12 | F35: =IF(C35=0,N34,IF(C35>1,M35)) -> 1263797.8 | G35: =B35-B34 -> 28 | H35: =DATE(YEAR(B35),12,31)-DATE(YEAR(B35),1,1)+1 -> 366 | I35: =IF($L$5=A35,K35,IF($L$5>A35,I34)) -> 916666.67 | J35: =SUM($I$8:I34) -> 24750000 | K35: =$J$12-J35 -> 8249999.9 | L35: =ROUND(C35*umumiy_malumot!$B$84/H35,2)*G35 -> 347131.12 | M35: =D35+E35 -> 1263797.8 | O35: =TEXT(R35,"ддд") -> Пн | P35: =IF(O35=$U$8,2,IF(O35=$V$8,1,0)) -> 0 | Q35: =DAY(umumiy_malumot!$B$78)+P35 -> 15 | R35: =IF(A35<=umumiy_malumot!$B$81,DATE(YEAR($B$8),MONTH($B$8)+A34,DAY(umumiy_malumot!$B$78)),0) -> 46888
A36: =1+A35 -> 29 | B36: =IF(A36<=umumiy_malumot!$B$81,DATE(YEAR(R36),MONTH(R36),DAY(IF(A36=umumiy_malumot!$B$81,umumiy_malumot!$B$67,IF(A36<umumiy_malumot!$B$81,(Q36),IF(A36>umumiy_malumot!$B$81,$H$56,0)))))) -> 46919 | C36: =C35-D35 -> 7333333.2 | D36: =IF(C36=0,L36,IF(C36>1,I36)) -> 916666.67 | E36: =IF(C36=0,N35,IF(C36>1,L36)) -> 341621.24 | F36: =IF(C36=0,N35,IF(C36>1,M36)) -> 1258287.9 | G36: =B36-B35 -> 31 | H36: =DATE(YEAR(B36),12,31)-DATE(YEAR(B36),1,1)+1 -> 366 | I36: =IF($L$5=A36,K36,IF($L$5>A36,I35)) -> 916666.67 | J36: =SUM($I$8:I35) -> 25666667 | K36: =$J$12-J36 -> 7333333.2 | L36: =ROUND(C36*umumiy_malumot!$B$84/H36,2)*G36 -> 341621.24 | M36: =D36+E36 -> 1258287.9 | O36: =TEXT(R36,"ддд") -> Чт | P36: =IF(O36=$U$8,2,IF(O36=$V$8,1,0)) -> 0 | Q36: =DAY(umumiy_malumot!$B$78)+P36 -> 15 | R36: =IF(A36<=umumiy_malumot!$B$81,DATE(YEAR($B$8),MONTH($B$8)+A35,DAY(umumiy_malumot!$B$78)),0) -> 46919
A37: =1+A36 -> 30 | B37: =IF(A37<=umumiy_malumot!$B$81,DATE(YEAR(R37),MONTH(R37),DAY(IF(A37=umumiy_malumot!$B$81,umumiy_malumot!$B$67,IF(A37<umumiy_malumot!$B$81,(Q37),IF(A37>umumiy_malumot!$B$81,$H$56,0)))))) -> 46951 | C37: =C36-D36 -> 6416666.6 | D37: =IF(C37=0,L37,IF(C37>1,I37)) -> 916666.67 | E37: =IF(C37=0,N36,IF(C37>1,L37)) -> 308560.96 | F37: =IF(C37=0,N36,IF(C37>1,M37)) -> 1225227.6 | G37: =B37-B36 -> 32 | H37: =DATE(YEAR(B37),12,31)-DATE(YEAR(B37),1,1)+1 -> 366 | I37: =IF($L$5=A37,K37,IF($L$5>A37,I36)) -> 916666.67 | J37: =SUM($I$8:I36) -> 26583333 | K37: =$J$12-J37 -> 6416666.6 | L37: =ROUND(C37*umumiy_malumot!$B$84/H37,2)*G37 -> 308560.96 | M37: =D37+E37 -> 1225227.6 | O37: =TEXT(R37,"ддд") -> Сб | P37: =IF(O37=$U$8,2,IF(O37=$V$8,1,0)) -> 2 | Q37: =DAY(umumiy_malumot!$B$78)+P37 -> 17 | R37: =IF(A37<=umumiy_malumot!$B$81,DATE(YEAR($B$8),MONTH($B$8)+A36,DAY(umumiy_malumot!$B$78)),0) -> 46949
A38: =1+A37 -> 31 | B38: =IF(A38<=umumiy_malumot!$B$81,DATE(YEAR(R38),MONTH(R38),DAY(IF(A38=umumiy_malumot!$B$81,umumiy_malumot!$B$67,IF(A38<umumiy_malumot!$B$81,(Q38),IF(A38>umumiy_malumot!$B$81,$H$56,0)))))) -> 46980 | C38: =C37-D37 -> 5499999.9 | D38: =IF(C38=0,L38,IF(C38>1,I38)) -> 916666.67 | E38: =IF(C38=0,N37,IF(C38>1,L38)) -> 239685.87 | F38: =IF(C38=0,N37,IF(C38>1,M38)) -> 1156352.5 | G38: =B38-B37 -> 29 | H38: =DATE(YEAR(B38),12,31)-DATE(YEAR(B38),1,1)+1 -> 366 | I38: =IF($L$5=A38,K38,IF($L$5>A38,I37)) -> 916666.67 | J38: =SUM($I$8:I37) -> 27500000 | K38: =$J$12-J38 -> 5499999.9 | L38: =ROUND(C38*umumiy_malumot!$B$84/H38,2)*G38 -> 239685.87 | M38: =D38+E38 -> 1156352.5 | O38: =TEXT(R38,"ддд") -> Вт | P38: =IF(O38=$U$8,2,IF(O38=$V$8,1,0)) -> 0 | Q38: =DAY(umumiy_malumot!$B$78)+P38 -> 15 | R38: =IF(A38<=umumiy_malumot!$B$81,DATE(YEAR($B$8),MONTH($B$8)+A37,DAY(umumiy_malumot!$B$78)),0) -> 46980
