Workbook
Name mos: '[1]Общие данные'!$C$23:$D$23
Name mulk: '[1]Общие данные'!$C$24:$W$24

Sheet Протокол  (2)
A1: =""&'Общие данные'!B147&" mikromoliya tashkiloti Kredit qo‘mitasining yig‘ilishi" -> «PULLOL BUSINESS MIKROMOLIYA TASHKILOTI» MChJ mikromoliya tashkiloti Kredit qo‘mitasining yig‘ilishi
A2: =""&I7&" protokolidan ko'chirma" -> №310-TR protokolidan ko'chirma
A3: Toshkent shahri | F3: ='Общие данные'!B68 -> 3 aprel 2026 y.
C4: KUN TARTIBI:
A5: =" "&I8&"."&'Общие данные'!B5&" ga "&'Общие данные'!B65&" berish masalasini ko‘rib chiqish to‘g‘risida." -> 1.ANNAZAROV KAXRAMAN SADULLAYEVICH ga Mikroqarz berish masalasini ko‘rib chiqish to‘g‘risida.
A7: =" "&I9&" masala yuzasidan: «PULLOL BUSINESS MIKROMOLIYA TASHKILOTI» MChJ kredit bo‘yicha menejeri, "&'Общие данные'!B5&"ga "&FIXED('Общие данные'!B75)&" ("&'Общие данные'!B76&") so‘m miqdorida, muddati "&'Общие данные'!B81&" ("&'Общие данные'!B82&") oyga va yillik "&'Общие данные'!B85&" ("&'Общие данные'!B86&") foiz miqdorida "&'Общие данные'!B65&" berich bo‘yicha "&'Общие данные'!B5&"ning kredit arizasi va "&'Общие данные'!B147&"ning xulosasi bilan ishtirokchilarni tanishtirdi." -> Birinchi masala yuzasidan: «PULLOL BUSINESS MIKROMOLIYA TASHKILOTI» MChJ kredit bo‘yicha menejeri, ANNAZAROV KAXRAMAN SADULLAYEVICHga 100 000 000,00 (Yuz million so'm) so‘m miqdorida, muddati 36 (Yigirma to'rt) oyga va yillik 55 (Ellik besh ) foiz miqdorida Mikroqarz berich bo‘yicha ANNAZAROV KAXRAMAN SADULLAYEVICHning kredit arizasi va «PULLOL BUSINESS MIKROMOLIYA TASHKILOTI» MChJning xulosasi bilan ishtirokchilarni tanishtirdi. | H7: Protokol raqami | I7: ='Общие данные'!B1 -> №310-TR
H8: Savol raqami | I8: 1 | J8: 1 | K8: 2 | L8: 3 | M8: 4 | N8: 5 | O8: 6 | P8: 7 | Q8: 8 | R8: 9 | S8: 10 | T8: 11 | U8: 12 | V8: 13 | W8: 14 | X8: 15 | Y8: 16 | Z8: 17 | AA8: 18 | AB8: 19 | AC8: 20 | AD8: 21 | AE8: 22 | AF8: 23 | AG8: 24 | AH8: 25
H9: Savol raqami qol bilan | I9: =IF(I8=J8,J9,IF(I8=K8,K9,IF(I8=L8,L9,IF(I8=M8,M9,IF(I8=N8,N9,IF(I8=O8,O9,IF(I8=P8,P9,IF(I8=Q8,Q9,IF(I8=R8,R9,IF(I8=S8,S9,IF(I8=T8,T9,IF(I8=U8,U9,IF(I8=V8,V9,IF(I8=W8,W9,IF(I8=X8,X9,IF(I8=Y8,Y9,IF(I8=Z8,Z9,IF(I8=AA8,AA9,IF(I8=AB8,AB9,IF(I8=AC8,AC9,IF(I8=AD8,AD9,IF(I8=AE8,AE9,IF(I8=AF8,AF9,IF(I8=AG8,AG9,IF(I8=AH8,AH9))))))))))))))))))))))))) -> Birinchi | J9: Birinchi | K9: Ikkinchi | L9: Uchinchi | M9: To'rtinchi | N9: Beshinchi | O9: O'ltinchi | P9: Yettinchi | Q9: Sakkizinchi | R9: Tuqqizinchi | S9: O'ninchi | T9: O'n birinchi | U9: O'n ikkinchi | V9: O'n uchinchi | W9: O'n to'rtinchi | X9: O'n beshinchi | Y9: O'n oltinchi | Z9: O'n yettinchi | AA9: O'n sakkizinchi | AB9: O'n tuqqizinchi | AC9: Yigirmanchi | AD9: Yigirma birinchi | AE9: Yigizma ikkinchi | AF9: Yigirma uchinchi | AG9: Yigirma to'rtinchi | AH9: Yigirma beshinchi
A14: =""&'Общие данные'!B65&" ta’minoti:" -> Mikroqarz ta’minoti:
A16: ='Заключение КК'!A18:F18 -> Egalik huquqi ANNAZAROV KAXRAMAN SADULLAYEVICHga tegishli bo'lgan umumiy yer maydoni, (m2) - 704, qurilish osti maydoni - 149,81, umumiy foydali maydoni - 213,72 va yashash maydoni - 108,36 Yakka tartibdagi uy-joy, QORAQALPOG'ISTON RESPUBLIKASI TO'RTKO'L TUMANI YOSHLIK MFY KALTAMINAR KO'CHASI 1B-UY
D17: masala yuzasidan berilgan ma’lumotlarni muhokama qilib, Kredit qo‘mitasi a’zolariga taqdim etilgan zarur hujjatlarni o‘rganib, majlisda ishtirok etgan Kredit qo‘mitasi a’zolarining taklif va mulohazalarini inobatga olgan holda | E17: =""&'Общие данные'!B147&" kredit qo‘mitasi" -> «PULLOL BUSINESS MIKROMOLIYA TASHKILOTI» MChJ kredit qo‘mitasi | F17: =CONCATENATE(D17,E17) -> masala yuzasidan berilgan ma’lumotlarni muhokama qilib, Kredit qo‘mitasi a’zolariga taqdim etilgan zarur hujjatlarni o‘rganib, majlisda ishtirok etgan Kredit qo‘mitasi a’zolarining taklif va mulohazalarini inobatga olgan holda «PULLOL BUSINESS MIKROMOLIYA TASHKILOTI» MChJ kredit qo‘mitasi
A18: =CONCATENATE(I9,F17) -> Birinchi masala yuzasidan berilgan ma’lumotlarni muhokama qilib, Kredit qo‘mitasi a’zolariga taqdim etilgan zarur hujjatlarni o‘rganib, majlisda ishtirok etgan Kredit qo‘mitasi a’zolarining taklif va mulohazalarini inobatga olgan holda «PULLOL BUSINESS MIKROMOLIYA TASHKILOTI» MChJ kredit qo‘mitasi
A19: QAROR QILADI:
A20: =" "&'Общие данные'!B5&"ga quyidagi shartlarda "&'Общие данные'!B65&" berish masalasi ma’qullansin:" -> ANNAZAROV KAXRAMAN SADULLAYEVICHga quyidagi shartlarda Mikroqarz berish masalasi ma’qullansin:
A21: ="1. "&'Общие данные'!B65&" summasi: "&FIXED('Общие данные'!B75)&" ("&'Общие данные'!B76&") so'm." -> 1. Mikroqarz summasi: 100 000 000,00 (Yuz million so'm) so'm.
A22: ="2. "&'Общие данные'!B65&" muddati: "&'Общие данные'!B81&" ("&'Общие данные'!B82&") oy " -> 2. Mikroqarz muddati: 36 (Yigirma to'rt) oy
A23: ="3. "&'Общие данные'!B65&"dan foydalanganlik uchun foiz stavkasi:yillik "&'Общие данные'!B85&"% ("&'Общие данные'!B86&") foiz." -> 3. Mikroqarzdan foydalanganlik uchun foiz stavkasi:yillik 55% (Ellik besh ) foiz.
A24: ="4. "&'Общие данные'!B65&" bo‘yicha asosiy qarz va foizlarni to‘lash:" -> 4. Mikroqarz bo‘yicha asosiy qarz va foizlarni to‘lash:
A25: ='Кредитная заявка'!A19:D19 -> - Mikroqarz shartnomasi bo'yicha har oy differensial to'lovlari amalga oshiriladi
A26: ="5. "&'Общие данные'!B65&" bo‘yicha garov "&'Заключение КК'!A29:F29&"" -> 5. Mikroqarz bo‘yicha garov - ANNAZAROV KAXRAMAN SADULLAYEVICH ga mulk huquqi asosida tegishli ko'chmas mulk shaklida Yakka tartibdagi uy-joy, manzili: QORAQALPOG'ISTON RESPUBLIKASI TO'RTKO'L TUMANI YOSHLIK MFY KALTAMINAR KO'CHASI 1B-UY, quyidagi tafsilotlarga muvofiq:
A27: ='Акт согласования'!A47 -> Nomi | B27: ='Акт согласования'!B47 -> Umumiy yer maydoni, (m2) | C27: ='Акт согласования'!C47 -> Qurilish osti maydoni, (m2) | D27: ='Акт согласования'!D47 -> Umumiy foydali maydoni, (m2) | E27: ='Акт согласования'!E47 -> Yashash maydoni, (m2) | F27: ='Акт согласования'!F47 -> Kelishilgan garov qiymati, so'm
A28: ='Акт согласования'!A48 -> Yakka tartibdagi uy-joy | B28: ='Акт согласования'!B48 -> 704 | C28: ='Акт согласования'!C48 -> 149.81 | D28: ='Акт согласования'!D48 -> 213.72 | E28: ='Акт согласования'!E48 -> 108.36 | F28: ='Акт согласования'!F48 -> 140 000 000,00 (yuz qirq million so'm)
A29: ='Акт согласования'!A22:F22 -> -* avtotransport egasi: ANNAZAROV KAXRAMAN SADULLAYEVICH
A30: ='Акт согласования'!A23:F23 -> -* texnik pasport:
A31: ='Акт согласования'!A24:F24 -> -* roʻyxatdan oʻtgan manzili/garaj manzili: QORAQALPOG'ISTON RESPUBLIKASI TO'RTKO'L TUMANI YOSHLIK MFY KALTAMINAR KO'CHASI 1B-UY
A32: ='Акт согласования'!A25:F25 -> -* davlat raqami:
A33: ='Акт согласования'!A50 -> Наименование | C33: ='Акт согласования'!C50 -> Полезная площадь | D33: ='Акт согласования'!D50 -> Жилая площадь | E33: ='Акт согласования'!E50 -> Общая площадь | F33: ='Акт согласования'!F50 -> Согласованная залоговая стоимость, сум
A34: ='Акт согласования'!A51 -> Yashash xona | C34: ='Акт согласования'!C51 -> 3 | D34: ='Акт согласования'!D51 -> 18.82 | E34: ='Акт согласования'!E51 -> 0 | F34: =""&FIXED('Общие данные'!C136,2)&" ("&'Общие данные'!B137&")" -> 140 000 000,00 (yuz qirq million so'm)
A35: ='Акт согласования'!A52 -> 0 | C35: ='Акт согласования'!C52 -> 0 | D35: ='Акт согласования'!D52 -> 0 | E35: ='Акт согласования'!E52 -> 0
A36: ='Акт согласования'!A53 -> Umumiy maydon | C36: ='Акт согласования'!C53 -> 43.96 | D36: ='Акт согласования'!D53 -> 18.82 | E36: ='Акт согласования'!E53 -> 43.96
A37: ='Акт согласования'!A54 -> 0 | C37: ='Акт согласования'!C54 -> 0 | D37: ='Акт согласования'!D54 -> 0 | E37: ='Акт согласования'!E54 -> 0
A38: ='Акт согласования'!A55 -> 0 | C38: ='Акт согласования'!C55 -> 0 | D38: ='Акт согласования'!D55 -> 0 | E38: ='Акт согласования'!E55 -> 0
A39: ='Акт согласования'!A56 -> 0 | C39: ='Акт согласования'!C56 -> 0 | D39: ='Акт согласования'!D56 -> 0 | E39: ='Акт согласования'!E56 -> 0
A40: ='Акт согласования'!A57 -> 0 | C40: ='Акт согласования'!C57 -> 0 | D40: ='Акт согласования'!D57 -> 0 | E40: ='Акт согласования'!E57 -> 0
A41: ='Акт согласования'!A58 -> 0 | C41: ='Акт согласования'!C58 -> 0 | D41: ='Акт согласования'!D58 -> 0 | E41: ='Акт согласования'!E58 -> 0
A42: ='Акт согласования'!A59 -> 0 | C42: ='Акт согласования'!C59 -> 0 | D42: ='Акт согласования'!D59 -> 0 | E42: ='Акт согласования'!E59 -> 0
A43: ='Акт согласования'!A60 -> 0 | C43: ='Акт согласования'!C60 -> 0 | D43: ='Акт согласования'!D60 -> 0 | E43: ='Акт согласования'!E60 -> 0
A44: ='Акт согласования'!A61 -> 0 | C44: ='Акт согласования'!C61 -> 0 | D44: ='Акт согласования'!D61 -> 0 | E44: ='Акт согласования'!E61 -> 0
A45: ='Акт согласования'!A62 -> JAMI | C45: ='Акт согласования'!C62 -> 43.96 | D45: ='Акт согласования'!D62 -> 18.82 | E45: ='Акт согласования'!E62 -> 43.96 | F45: =FIXED('Общие данные'!C136,2) -> 140 000 000,00
A46: ='Акт согласования'!A39:F39 -> -* ko'chmas mulk egasi: ANNAZAROV KAXRAMAN SADULLAYEVICH
A47: ='Акт согласования'!A40:F40 -> -* reestr raqami: №1735233/Y-26004624
A48: ='Акт согласования'!A41:F41 -> -* kadastr raqami: 01.04.2026 y. №23:08:40:01:04:0357
A49: ='Акт согласования'!A42:F42 -> -* manzil: QORAQALPOG'ISTON RESPUBLIKASI TO'RTKO'L TUMANI YOSHLIK MFY KALTAMINAR KO'CHASI 1B-UY
A51: 6. Boshqa shartlar – ko'chmas mulk vositasi shaklida garov ta'minlangandan keyin mikroqarz berish.
A53: Qaror bir ovozdan qabul qilindi.
A54: ="1. "&'Общие данные'!B151&"" -> 1. Obidov Abdullo Shokir o'g'li
A55: ="2. "&'Общие данные'!B159&"" -> 2. Akramov R.N.
A56: ="3. "&'Общие данные'!B161&"" -> 3. Eshbekov S.O.

Sheet График дифференц
E1: Приложение №1
F2: ="к договору микрозайма "&'Общие данные'!B74&"" -> к договору микрозайма 3 aprel 2026 y.dan №310-TR
A4: График погашения
L5: ='Общие данные'!B81 -> 36
A6: № | B6: Дата погашения | C6: Остаток основного долга | D6: Сумма погашения, сум
D7: основного долга | E7: процентов* | F7: всего*
A8: 1 | B8: ='Общие данные'!B79 -> 46147 | C8: ='Общие данные'!B75 -> 100000000 | D8: =IF(IF(C8=0,L8,IF(C8>1,I8))="",0,(IF(C8=0,L8,IF(C8>1,I8)))) -> 2777777.8 | E8: =IF(C8=0,N6,IF(C8>1,L8)) -> 4821917.8 | F8: =IF(C8=0,O6,IF(C8>1,M8)) -> 7599695.5 | G8: =B8-'Общие данные'!B67 -> 32 | H8: =DATE(YEAR(B8),12,31)-DATE(YEAR(B8),1,1)+1 -> 365 | I8: =IF('Общие данные'!B83=0,ROUND(C8/L5,2),"") -> 2777777.8 | L8: =ROUND(C8*'Общие данные'!$B$84/H8,2)*G8 -> 4821917.8 | M8: =D8+E8 -> 7599695.5 | O8: =TEXT(B8,"ддд") -> Вт | P8: =IF(O8=$U$8,2,IF(O8=$V$8,1,0)) -> 0 | Q8: =DAY('Общие данные'!$B$78)+P8 -> 5 | S8: Чт | T8: Пт | U8: Сб | V8: Вс
A9: 2 | B9: =IF(A9<='Общие данные'!$B$81,DATE(YEAR(R9),MONTH(R9),DAY(R9)+P9),0) -> 46178 | C9: =C8-D8 -> 97222222 | D9: =IF(C9=0,L9,IF(C9>1,I9)) -> 2777777.8 | E9: =IF(C9=0,N8,IF(C9>1,L9)) -> 4541476.4 | F9: =IF(C9=0,N8,IF(C9>1,M9)) -> 7319254.2 | G9: =B9-B8 -> 31 | H9: =DATE(YEAR(B9),12,31)-DATE(YEAR(B9),1,1)+1 -> 365 | I9: =IF(I8="",ROUND(C8/(L5-1),2),I8) -> 2777777.8 | L9: =ROUND(C9*'Общие данные'!$B$84/H9,2)*G9 -> 4541476.4 | M9: =D9+E9 -> 7319254.2 | O9: =TEXT(R9,"ддд") -> Пт | P9: =IF(O9=$U$8,2,IF(O9=$V$8,1,0)) -> 0 | Q9: =DAY('Общие данные'!$B$78)+P9 -> 5 | R9: =IF(A9<='Общие данные'!$B$81,DATE(YEAR($B$8),MONTH($B$8)+A8,DAY('Общие данные'!$B$78)),0) -> 46178
A10: 3 | B10: =IF(A10<='Общие данные'!$B$81,DATE(YEAR(R10),MONTH(R10),DAY(R10)+P10),0) -> 46209 | C10: =C9-D9 -> 94444444 | D10: =IF(C10=0,L10,IF(C10>1,I10)) -> 2777777.8 | E10: =IF(C10=0,N9,IF(C10>1,L10)) -> 4411720 | F10: =IF(C10=0,N9,IF(C10>1,M10)) -> 7189497.8 | G10: =B10-B9 -> 31 | H10: =DATE(YEAR(B10),12,31)-DATE(YEAR(B10),1,1)+1 -> 365 | I10: =I9 -> 2777777.8 | L10: =ROUND(C10*'Общие данные'!$B$84/H10,2)*G10 -> 4411720 | M10: =D10+E10 -> 7189497.8 | O10: =TEXT(R10,"ддд") -> Вс | P10: =IF(O10=$U$8,2,IF(O10=$V$8,1,0)) -> 1 | Q10: =DAY('Общие данные'!$B$78)+P10 -> 6 | R10: =IF(A10<='Общие данные'!$B$81,DATE(YEAR($B$8),MONTH($B$8)+A9,DAY('Общие данные'!$B$78)),0) -> 46208
A11: 4 | B11: =IF(A11<='Общие данные'!$B$81,DATE(YEAR(R11),MONTH(R11),DAY(R11)+P11),0) -> 46239 | C11: =C10-D10 -> 91666667 | D11: =IF(C11=0,L11,IF(C11>1,I11)) -> 2777777.8 | E11: =IF(C11=0,N10,IF(C11>1,L11)) -> 4143835.5 | F11: =IF(C11=0,N10,IF(C11>1,M11)) -> 6921613.3 | G11: =B11-B10 -> 30 | H11: =DATE(YEAR(B11),12,31)-DATE(YEAR(B11),1,1)+1 -> 365 | I11: =I10 -> 2777777.8 | L11: =ROUND(C11*'Общие данные'!$B$84/H11,2)*G11 -> 4143835.5 | M11: =D11+E11 -> 6921613.3 | O11: =TEXT(R11,"ддд") -> Ср | P11: =IF(O11=$U$8,2,IF(O11=$V$8,1,0)) -> 0 | Q11: =DAY('Общие данные'!$B$78)+P11 -> 5 | R11: =IF(A11<='Общие данные'!$B$81,DATE(YEAR($B$8),MONTH($B$8)+A10,DAY('Общие данные'!$B$78)),0) -> 46239
A12: 5 | B12: =IF(A12<='Общие данные'!$B$81,DATE(YEAR(R12),MONTH(R12),DAY(R12)+P12),0) -> 46272 | C12: =C11-D11 -> 88888889 | D12: =IF(C12=0,L12,IF(C12>1,I12)) -> 2777777.8 | E12: =IF(C12=0,N11,IF(C12>1,L12)) -> 4420091.3 | F12: =IF(C12=0,N11,IF(C12>1,M12)) -> 7197869.1 | G12: =B12-B11 -> 33 | H12: =DATE(YEAR(B12),12,31)-DATE(YEAR(B12),1,1)+1 -> 365 | I12: =I11 -> 2777777.8 | J12: ='Общие данные'!B75 -> 100000000 | L12: =ROUND(C12*'Общие данные'!$B$84/H12,2)*G12 -> 4420091.3 | M12: =D12+E12 -> 7197869.1 | O12: =TEXT(R12,"ддд") -> Сб | P12: =IF(O12=$U$8,2,IF(O12=$V$8,1,0)) -> 2 | Q12: =DAY('Общие данные'!$B$78)+P12 -> 7 | R12: =IF(A12<='Общие данные'!$B$81,DATE(YEAR($B$8),MONTH($B$8)+A11,DAY('Общие данные'!$B$78)),0) -> 46270
A13: 6 | B13: =IF(A13<='Общие данные'!$B$81,DATE(YEAR(R13),MONTH(R13),DAY(IF(A13='Общие данные'!$B$81,'Общие данные'!$B$67,IF(A13<'Общие данные'!$B$81,(Q13),IF(A13>'Общие данные'!$B$81,$H$56,0)))))) -> 46300 | C13: =C12-D12 -> 86111111 | D13: =IF(C13=0,L13,IF(C13>1,I13)) -> 2777777.8 | E13: =IF(C13=0,N12,IF(C13>1,L13)) -> 3633181.2 | F13: =IF(C13=0,N12,IF(C13>1,M13)) -> 6410958.9 | G13: =B13-B12 -> 28 | H13: =DATE(YEAR(B13),12,31)-DATE(YEAR(B13),1,1)+1 -> 365 | I13: =IF(L5=H1,K13,IF(L5>H1,I12)) -> 2777777.8 | J13: =SUM($I$8:I12) -> 13888889 | K13: =$J$12-J13 -> 86111111 | L13: =ROUND(C13*'Общие данные'!$B$84/H13,2)*G13 -> 3633181.2 | M13: =D13+E13 -> 6410958.9 | O13: =TEXT(R13,"ддд") -> Пн | P13: =IF(O13=$U$8,2,IF(O13=$V$8,1,0)) -> 0 | Q13: =DAY('Общие данные'!$B$78)+P13 -> 5 | R13: =IF(A13<='Общие данные'!$B$81,DATE(YEAR($B$8),MONTH($B$8)+A12,DAY('Общие данные'!$B$78)),0) -> 46300
A14: 7 | B14: =IF(A14<='Общие данные'!$B$81,DATE(YEAR(R14),MONTH(R14),DAY(IF(A14='Общие данные'!$B$81,'Общие данные'!$B$67,IF(A14<'Общие данные'!$B$81,(Q14),IF(A14>'Общие данные'!$B$81,$H$56,0)))))) -> 46331 | C14: =C13-D13 -> 83333333 | D14: =IF(C14=0,L14,IF(C14>1,I14)) -> 2777777.8 | E14: =IF(C14=0,N13,IF(C14>1,L14)) -> 3892694.2 | F14: =IF(C14=0,N13,IF(C14>1,M14)) -> 6670472 | G14: =B14-B13 -> 31 | H14: =DATE(YEAR(B14),12,31)-DATE(YEAR(B14),1,1)+1 -> 365 | I14: =IF($L$5=A14,K14,IF($L$5>A14,I13)) -> 2777777.8 | J14: =SUM($I$8:I13) -> 16666667 | K14: =$J$12-J14 -> 83333333 | L14: =ROUND(C14*'Общие данные'!$B$84/H14,2)*G14 -> 3892694.2 | M14: =D14+E14 -> 6670472 | O14: =TEXT(R14,"ддд") -> Чт | P14: =IF(O14=$U$8,2,IF(O14=$V$8,1,0)) -> 0 | Q14: =DAY('Общие данные'!$B$78)+P14 -> 5 | R14: =IF(A14<='Общие данные'!$B$81,DATE(YEAR($B$8),MONTH($B$8)+A13,DAY('Общие данные'!$B$78)),0) -> 46331
A15: 8 | B15: =IF(A15<='Общие данные'!$B$81,DATE(YEAR(R15),MONTH(R15),DAY(IF(A15='Общие данные'!$B$81,'Общие данные'!$B$67,IF(A15<'Общие данные'!$B$81,(Q15),IF(A15>'Общие данные'!$B$81,$H$56,0)))))) -> 46363 | C15: =C14-D14 -> 80555556 | D15: =IF(C15=0,L15,IF(C15>1,I15)) -> 2777777.8 | E15: =IF(C15=0,N14,IF(C15>1,L15)) -> 3884322.6 | F15: =IF(C15=0,N14,IF(C15>1,M15)) -> 6662100.3 | G15: =B15-B14 -> 32 | H15: =DATE(YEAR(B15),12,31)-DATE(YEAR(B15),1,1)+1 -> 365 | I15: =IF($L$5=A15,K15,IF($L$5>A15,I14)) -> 2777777.8 | J15: =SUM($I$8:I14) -> 19444444 | K15: =$J$12-J15 -> 80555556 | L15: =ROUND(C15*'Общие данные'!$B$84/H15,2)*G15 -> 3884322.6 | M15: =D15+E15 -> 6662100.3 | O15: =TEXT(R15,"ддд") -> Сб | P15: =IF(O15=$U$8,2,IF(O15=$V$8,1,0)) -> 2 | Q15: =DAY('Общие данные'!$B$78)+P15 -> 7 | R15: =IF(A15<='Общие данные'!$B$81,DATE(YEAR($B$8),MONTH($B$8)+A14,DAY('Общие данные'!$B$78)),0) -> 46361
A16: 9 | B16: =IF(A16<='Общие данные'!$B$81,DATE(YEAR(R16),MONTH(R16),DAY(IF(A16='Общие данные'!$B$81,'Общие данные'!$B$67,IF(A16<'Общие данные'!$B$81,(Q16),IF(A16>'Общие данные'!$B$81,$H$56,0)))))) -> 46392 | C16: =C15-D15 -> 77777778 | D16: =IF(C16=0,L16,IF(C16>1,I16)) -> 2777777.8 | E16: =IF(C16=0,N15,IF(C16>1,L16)) -> 3398782.3 | F16: =IF(C16=0,N15,IF(C16>1,M16)) -> 6176560.1 | G16: =B16-B15 -> 29 | H16: =DATE(YEAR(B16),12,31)-DATE(YEAR(B16),1,1)+1 -> 365 | I16: =IF($L$5=A16,K16,IF($L$5>A16,I15)) -> 2777777.8 | J16: =SUM($I$8:I15) -> 22222222 | K16: =$J$12-J16 -> 77777778 | L16: =ROUND(C16*'Общие данные'!$B$84/H16,2)*G16 -> 3398782.3 | M16: =D16+E16 -> 6176560.1 | O16: =TEXT(R16,"ддд") -> Вт | P16: =IF(O16=$U$8,2,IF(O16=$V$8,1,0)) -> 0 | Q16: =DAY('Общие данные'!$B$78)+P16 -> 5 | R16: =IF(A16<='Общие данные'!$B$81,DATE(YEAR($B$8),MONTH($B$8)+A15,DAY('Общие данные'!$B$78)),0) -> 46392
A17: 10 | B17: =IF(A17<='Общие данные'!$B$81,DATE(YEAR(R17),MONTH(R17),DAY(IF(A17='Общие данные'!$B$81,'Общие данные'!$B$67,IF(A17<'Общие данные'!$B$81,(Q17),IF(A17>'Общие данные'!$B$81,$H$56,0)))))) -> 46423 | C17: =C16-D16 -> 75000000 | D17: =IF(C17=0,L17,IF(C17>1,I17)) -> 2777777.8 | E17: =IF(C17=0,N16,IF(C17>1,L17)) -> 3503424.7 | F17: =IF(C17=0,N16,IF(C17>1,M17)) -> 6281202.5 | G17: =B17-B16 -> 31 | H17: =DATE(YEAR(B17),12,31)-DATE(YEAR(B17),1,1)+1 -> 365 | I17: =IF($L$5=A17,K17,IF($L$5>A17,I16)) -> 2777777.8 | J17: =SUM($I$8:I16) -> 25000000 | K17: =$J$12-J17 -> 75000000 | L17: =ROUND(C17*'Общие данные'!$B$84/H17,2)*G17 -> 3503424.7 | M17: =D17+E17 -> 6281202.5 | O17: =TEXT(R17,"ддд") -> Пт | P17: =IF(O17=$U$8,2,IF(O17=$V$8,1,0)) -> 0 | Q17: =DAY('Общие данные'!$B$78)+P17 -> 5 | R17: =IF(A17<='Общие данные'!$B$81,DATE(YEAR($B$8),MONTH($B$8)+A16,DAY('Общие данные'!$B$78)),0) -> 46423
A18: 11 | B18: =IF(A18<='Общие данные'!$B$81,DATE(YEAR(R18),MONTH(R18),DAY(IF(A18='Общие данные'!$B$81,'Общие данные'!$B$67,IF(A18<'Общие данные'!$B$81,(Q18),IF(A18>'Общие данные'!$B$81,$H$56,0)))))) -> 46451 | C18: =C17-D17 -> 72222222 | D18: =IF(C18=0,L18,IF(C18>1,I18)) -> 2777777.8 | E18: =IF(C18=0,N17,IF(C18>1,L18)) -> 3047184.3 | F18: =IF(C18=0,N17,IF(C18>1,M18)) -> 5824962.1 | G18: =B18-B17 -> 28 | H18: =DATE(YEAR(B18),12,31)-DATE(YEAR(B18),1,1)+1 -> 365 | I18: =IF($L$5=A18,K18,IF($L$5>A18,I17)) -> 2777777.8 | J18: =SUM($I$8:I17) -> 27777778 | K18: =$J$12-J18 -> 72222222 | L18: =ROUND(C18*'Общие данные'!$B$84/H18,2)*G18 -> 3047184.3 | M18: =D18+E18 -> 5824962.1 | O18: =TEXT(R18,"ддд") -> Пт | P18: =IF(O18=$U$8,2,IF(O18=$V$8,1,0)) -> 0 | Q18: =DAY('Общие данные'!$B$78)+P18 -> 5 | R18: =IF(A18<='Общие данные'!$B$81,DATE(YEAR($B$8),MONTH($B$8)+A17,DAY('Общие данные'!$B$78)),0) -> 46451
A19: 12 | B19: =IF(A19<='Общие данные'!$B$81,DATE(YEAR(R19),MONTH(R19),DAY(IF(A19='Общие данные'!$B$81,'Общие данные'!$B$67,IF(A19<'Общие данные'!$B$81,(Q19),IF(A19>'Общие данные'!$B$81,$H$56,0)))))) -> 46482 | C19: =C18-D18 -> 69444444 | D19: =IF(C19=0,L19,IF(C19>1,I19)) -> 2777777.8 | E19: =IF(C19=0,N18,IF(C19>1,L19)) -> 3243911.6 | F19: =IF(C19=0,N18,IF(C19>1,M19)) -> 6021689.4 | G19: =B19-B18 -> 31 | H19: =DATE(YEAR(B19),12,31)-DATE(YEAR(B19),1,1)+1 -> 365 | I19: =IF($L$5=A19,K19,IF($L$5>A19,I18)) -> 2777777.8 | J19: =SUM($I$8:I18) -> 30555556 | K19: =$J$12-J19 -> 69444444 | L19: =ROUND(C19*'Общие данные'!$B$84/H19,2)*G19 -> 3243911.6 | M19: =D19+E19 -> 6021689.4 | O19: =TEXT(R19,"ддд") -> Пн | P19: =IF(O19=$U$8,2,IF(O19=$V$8,1,0)) -> 0 | Q19: =DAY('Общие данные'!$B$78)+P19 -> 5 | R19: =IF(A19<='Общие данные'!$B$81,DATE(YEAR($B$8),MONTH($B$8)+A18,DAY('Общие данные'!$B$78)),0) -> 46482
A20: 13 | B20: =IF(A20<='Общие данные'!$B$81,DATE(YEAR(R20),MONTH(R20),DAY(IF(A20='Общие данные'!$B$81,'Общие данные'!$B$67,IF(A20<'Общие данные'!$B$81,(Q20),IF(A20>'Общие данные'!$B$81,$H$56,0)))))) -> 46512 | C20: =C19-D19 -> 66666667 | D20: =IF(C20=0,L20,IF(C20>1,I20)) -> 2777777.8 | E20: =IF(C20=0,N19,IF(C20>1,L20)) -> 3013698.6 | F20: =IF(C20=0,N19,IF(C20>1,M20)) -> 5791476.4 | G20: =B20-B19 -> 30 | H20: =DATE(YEAR(B20),12,31)-DATE(YEAR(B20),1,1)+1 -> 365 | I20: =IF($L$5=A20,K20,IF($L$5>A20,I19)) -> 2777777.8 | J20: =SUM($I$8:I19) -> 33333333 | K20: =$J$12-J20 -> 66666667 | L20: =ROUND(C20*'Общие данные'!$B$84/H20,2)*G20 -> 3013698.6 | M20: =D20+E20 -> 5791476.4 | O20: =TEXT(R20,"ддд") -> Ср | P20: =IF(O20=$U$8,2,IF(O20=$V$8,1,0)) -> 0 | Q20: =DAY('Общие данные'!$B$78)+P20 -> 5 | R20: =IF(A20<='Общие данные'!$B$81,DATE(YEAR($B$8),MONTH($B$8)+A19,DAY('Общие данные'!$B$78)),0) -> 46512
A21: 14 | B21: =IF(A21<='Общие данные'!$B$81,DATE(YEAR(R21),MONTH(R21),DAY(IF(A21='Общие данные'!$B$81,'Общие данные'!$B$67,IF(A21<'Общие данные'!$B$81,(Q21),IF(A21>'Общие данные'!$B$81,$H$56,0)))))) -> 46545 | C21: =C20-D20 -> 63888889 | D21: =IF(C21=0,L21,IF(C21>1,I21)) -> 2777777.8 | E21: =IF(C21=0,N20,IF(C21>1,L21)) -> 3176940.7 | F21: =IF(C21=0,N20,IF(C21>1,M21)) -> 5954718.5 | G21: =B21-B20 -> 33 | H21: =DATE(YEAR(B21),12,31)-DATE(YEAR(B21),1,1)+1 -> 365 | I21: =IF($L$5=A21,K21,IF($L$5>A21,I20)) -> 2777777.8 | J21: =SUM($I$8:I20) -> 36111111 | K21: =$J$12-J21 -> 63888889 | L21: =ROUND(C21*'Общие данные'!$B$84/H21,2)*G21 -> 3176940.7 | M21: =D21+E21 -> 5954718.5 | O21: =TEXT(R21,"ддд") -> Сб | P21: =IF(O21=$U$8,2,IF(O21=$V$8,1,0)) -> 2 | Q21: =DAY('Общие данные'!$B$78)+P21 -> 7 | R21: =IF(A21<='Общие данные'!$B$81,DATE(YEAR($B$8),MONTH($B$8)+A20,DAY('Общие данные'!$B$78)),0) -> 46543
A22: 15 | B22: =IF(A22<='Общие данные'!$B$81,DATE(YEAR(R22),MONTH(R22),DAY(IF(A22='Общие данные'!$B$81,'Общие данные'!$B$67,IF(A22<'Общие данные'!$B$81,(Q22),IF(A22>'Общие данные'!$B$81,$H$56,0)))))) -> 46573 | C22: =C21-D21 -> 61111111 | D22: =IF(C22=0,L22,IF(C22>1,I22)) -> 2777777.8 | E22: =IF(C22=0,N21,IF(C22>1,L22)) -> 2578386.7 | F22: =IF(C22=0,N21,IF(C22>1,M22)) -> 5356164.5 | G22: =B22-B21 -> 28 | H22: =DATE(YEAR(B22),12,31)-DATE(YEAR(B22),1,1)+1 -> 365 | I22: =IF($L$5=A22,K22,IF($L$5>A22,I21)) -> 2777777.8 | J22: =SUM($I$8:I21) -> 38888889 | K22: =$J$12-J22 -> 61111111 | L22: =ROUND(C22*'Общие данные'!$B$84/H22,2)*G22 -> 2578386.7 | M22: =D22+E22 -> 5356164.5 | O22: =TEXT(R22,"ддд") -> Пн | P22: =IF(O22=$U$8,2,IF(O22=$V$8,1,0)) -> 0 | Q22: =DAY('Общие данные'!$B$78)+P22 -> 5 | R22: =IF(A22<='Общие данные'!$B$81,DATE(YEAR($B$8),MONTH($B$8)+A21,DAY('Общие данные'!$B$78)),0) -> 46573
A23: 16 | B23: =IF(A23<='Общие данные'!$B$81,DATE(YEAR(R23),MONTH(R23),DAY(IF(A23='Общие данные'!$B$81,'Общие данные'!$B$67,IF(A23<'Общие данные'!$B$81,(Q23),IF(A23>'Общие данные'!$B$81,$H$56,0)))))) -> 46604 | C23: =C22-D22 -> 58333333 | D23: =IF(C23=0,L23,IF(C23>1,I23)) -> 2777777.8 | E23: =IF(C23=0,N22,IF(C23>1,L23)) -> 2724885.7 | F23: =IF(C23=0,N22,IF(C23>1,M23)) -> 5502663.5 | G23: =B23-B22 -> 31 | H23: =DATE(YEAR(B23),12,31)-DATE(YEAR(B23),1,1)+1 -> 365 | I23: =IF($L$5=A23,K23,IF($L$5>A23,I22)) -> 2777777.8 | J23: =SUM($I$8:I22) -> 41666667 | K23: =$J$12-J23 -> 58333333 | L23: =ROUND(C23*'Общие данные'!$B$84/H23,2)*G23 -> 2724885.7 | M23: =D23+E23 -> 5502663.5 | O23: =TEXT(R23,"ддд") -> Чт | P23: =IF(O23=$U$8,2,IF(O23=$V$8,1,0)) -> 0 | Q23: =DAY('Общие данные'!$B$78)+P23 -> 5 | R23: =IF(A23<='Общие данные'!$B$81,DATE(YEAR($B$8),MONTH($B$8)+A22,DAY('Общие данные'!$B$78)),0) -> 46604
A24: 17 | B24: =IF(A24<='Общие данные'!$B$81,DATE(YEAR(R24),MONTH(R24),DAY(IF(A24='Общие данные'!$B$81,'Общие данные'!$B$67,IF(A24<'Общие данные'!$B$81,(Q24),IF(A24>'Общие данные'!$B$81,$H$56,0)))))) -> 46636 | C24: =C23-D23 -> 55555556 | D24: =IF(C24=0,L24,IF(C24>1,I24)) -> 2777777.8 | E24: =IF(C24=0,N23,IF(C24>1,L24)) -> 2678843.2 | F24: =IF(C24=0,N23,IF(C24>1,M24)) -> 5456621 | G24: =B24-B23 -> 32 | H24: =DATE(YEAR(B24),12,31)-DATE(YEAR(B24),1,1)+1 -> 365 | I24: =IF($L$5=A24,K24,IF($L$5>A24,I23)) -> 2777777.8 | J24: =SUM($I$8:I23) -> 44444444 | K24: =$J$12-J24 -> 55555556 | L24: =ROUND(C24*'Общие данные'!$B$84/H24,2)*G24 -> 2678843.2 | M24: =D24+E24 -> 5456621 | O24: =TEXT(R24,"ддд") -> Вс | P24: =IF(O24=$U$8,2,IF(O24=$V$8,1,0)) -> 1 | Q24: =DAY('Общие данные'!$B$78)+P24 -> 6 | R24: =IF(A24<='Общие данные'!$B$81,DATE(YEAR($B$8),MONTH($B$8)+A23,DAY('Общие данные'!$B$78)),0) -> 46635
A25: 18 | B25: =IF(A25<='Общие данные'!$B$81,DATE(YEAR(R25),MONTH(R25),DAY(IF(A25='Общие данные'!$B$81,'Общие данные'!$B$67,IF(A25<'Общие данные'!$B$81,(Q25),IF(A25>'Общие данные'!$B$81,$H$56,0)))))) -> 46665 | C25: =C24-D24 -> 52777778 | D25: =IF(C25=0,L25,IF(C25>1,I25)) -> 2777777.8 | E25: =IF(C25=0,N24,IF(C25>1,L25)) -> 2306316.6 | F25: =IF(C25=0,N24,IF(C25>1,M25)) -> 5084094.4 | G25: =B25-B24 -> 29 | H25: =DATE(YEAR(B25),12,31)-DATE(YEAR(B25),1,1)+1 -> 365 | I25: =IF($L$5=A25,K25,IF($L$5>A25,I24)) -> 2777777.8 | J25: =SUM($I$8:I24) -> 47222222 | K25: =$J$12-J25 -> 52777778 | L25: =ROUND(C25*'Общие данные'!$B$84/H25,2)*G25 -> 2306316.6 | M25: =D25+E25 -> 5084094.4 | O25: =TEXT(R25,"ддд") -> Вт | P25: =IF(O25=$U$8,2,IF(O25=$V$8,1,0)) -> 0 | Q25: =DAY('Общие данные'!$B$78)+P25 -> 5 | R25: =IF(A25<='Общие данные'!$B$81,DATE(YEAR($B$8),MONTH($B$8)+A24,DAY('Общие данные'!$B$78)),0) -> 46665
... A31: 24 | B31: =IF(A31<='Общие данные'!$B$81,DATE(YEAR(R31),MONTH(R31),DAY(IF(A31='Общие данные'!$B$81,'Общие данные'!$B$67,IF(A31<'Общие данные'!$B$81,(Q31),IF(A31>'Общие данные'!$B$81,$H$56,0)))))) -> 46848 | C31: =C30-D30 -> 36111111 | D31: =IF(C31=0,L31,IF(C31>1,I31)) -> 2777777.8 | E31: =IF(C31=0,N30,IF(C31>1,L31)) -> 1627959.9 | F31: =IF(C31=0,N30,IF(C31>1,M31)) -> 4405737.7 | G31: =B31-B30 -> 30 | H31: =DATE(YEAR(B31),12,31)-DATE(YEAR(B31),1,1)+1 -> 366 | I31: =IF($L$5=A31,K31,IF($L$5>A31,I30)) -> 2777777.8 | J31: =SUM($I$8:I30) -> 63888889 | K31: =$J$12-J31 -> 36111111 | L31: =ROUND(C31*'Общие данные'!$B$84/H31,2)*G31 -> 1627959.9 | M31: =D31+E31 -> 4405737.7 | O31: =TEXT(R31,"ддд") -> Ср | P31: =IF(O31=$U$8,2,IF(O31=$V$8,1,0)) -> 0 | Q31: =DAY('Общие данные'!$B$78)+P31 -> 5 | R31: =IF(A31<='Общие данные'!$B$81,DATE(YEAR($B$8),MONTH($B$8)+A30,DAY('Общие данные'!$B$78)),0) -> 46848
A32: =1+A31 -> 25 | B32: =IF(A32<='Общие данные'!$B$81,DATE(YEAR(R32),MONTH(R32),DAY(IF(A32='Общие данные'!$B$81,'Общие данные'!$B$67,IF(A32<'Общие данные'!$B$81,(Q32),IF(A32>'Общие данные'!$B$81,$H$56,0)))))) -> 46878 | C32: =C31-D31 -> 33333333 | D32: =IF(C32=0,L32,IF(C32>1,I32)) -> 2777777.8 | E32: =IF(C32=0,N31,IF(C32>1,L32)) -> 1502732.1 | F32: =IF(C32=0,N31,IF(C32>1,M32)) -> 4280509.9 | G32: =B32-B31 -> 30 | H32: =DATE(YEAR(B32),12,31)-DATE(YEAR(B32),1,1)+1 -> 366 | I32: =IF($L$5=A32,K32,IF($L$5>A32,I31)) -> 2777777.8 | J32: =SUM($I$8:I31) -> 66666667 | K32: =$J$12-J32 -> 33333333 | L32: =ROUND(C32*'Общие данные'!$B$84/H32,2)*G32 -> 1502732.1 | M32: =D32+E32 -> 4280509.9 | O32: =TEXT(R32,"ддд") -> Пт | P32: =IF(O32=$U$8,2,IF(O32=$V$8,1,0)) -> 0 | Q32: =DAY('Общие данные'!$B$78)+P32 -> 5 | R32: =IF(A32<='Общие данные'!$B$81,DATE(YEAR($B$8),MONTH($B$8)+A31,DAY('Общие данные'!$B$78)),0) -> 46878
A33: =1+A32 -> 26 | B33: =IF(A33<='Общие данные'!$B$81,DATE(YEAR(R33),MONTH(R33),DAY(IF(A33='Общие данные'!$B$81,'Общие данные'!$B$67,IF(A33<'Общие данные'!$B$81,(Q33),IF(A33>'Общие данные'!$B$81,$H$56,0)))))) -> 46909 | C33: =C32-D32 -> 30555555 | D33: =IF(C33=0,L33,IF(C33>1,I33)) -> 2777777.8 | E33: =IF(C33=0,N32,IF(C33>1,L33)) -> 1423421.4 | F33: =IF(C33=0,N32,IF(C33>1,M33)) -> 4201199.2 | G33: =B33-B32 -> 31 | H33: =DATE(YEAR(B33),12,31)-DATE(YEAR(B33),1,1)+1 -> 366 | I33: =IF($L$5=A33,K33,IF($L$5>A33,I32)) -> 2777777.8 | J33: =SUM($I$8:I32) -> 69444445 | K33: =$J$12-J33 -> 30555555 | L33: =ROUND(C33*'Общие данные'!$B$84/H33,2)*G33 -> 1423421.4 | M33: =D33+E33 -> 4201199.2 | O33: =TEXT(R33,"ддд") -> Пн | P33: =IF(O33=$U$8,2,IF(O33=$V$8,1,0)) -> 0 | Q33: =DAY('Общие данные'!$B$78)+P33 -> 5 | R33: =IF(A33<='Общие данные'!$B$81,DATE(YEAR($B$8),MONTH($B$8)+A32,DAY('Общие данные'!$B$78)),0) -> 46909
A34: =1+A33 -> 27 | B34: =IF(A34<='Общие данные'!$B$81,DATE(YEAR(R34),MONTH(R34),DAY(IF(A34='Общие данные'!$B$81,'Общие данные'!$B$67,IF(A34<'Общие данные'!$B$81,(Q34),IF(A34>'Общие данные'!$B$81,$H$56,0)))))) -> 46939 | C34: =C33-D33 -> 27777778 | D34: =IF(C34=0,L34,IF(C34>1,I34)) -> 2777777.8 | E34: =IF(C34=0,N33,IF(C34>1,L34)) -> 1252276.8 | F34: =IF(C34=0,N33,IF(C34>1,M34)) -> 4030054.6 | G34: =B34-B33 -> 30 | H34: =DATE(YEAR(B34),12,31)-DATE(YEAR(B34),1,1)+1 -> 366 | I34: =IF($L$5=A34,K34,IF($L$5>A34,I33)) -> 2777777.8 | J34: =SUM($I$8:I33) -> 72222222 | K34: =$J$12-J34 -> 27777778 | L34: =ROUND(C34*'Общие данные'!$B$84/H34,2)*G34 -> 1252276.8 | M34: =D34+E34 -> 4030054.6 | O34: =TEXT(R34,"ддд") -> Ср | P34: =IF(O34=$U$8,2,IF(O34=$V$8,1,0)) -> 0 | Q34: =DAY('Общие данные'!$B$78)+P34 -> 5 | R34: =IF(A34<='Общие данные'!$B$81,DATE(YEAR($B$8),MONTH($B$8)+A33,DAY('Общие данные'!$B$78)),0) -> 46939
A35: =1+A34 -> 28 | B35: =IF(A35<='Общие данные'!$B$81,DATE(YEAR(R35),MONTH(R35),DAY(IF(A35='Общие данные'!$B$81,'Общие данные'!$B$67,IF(A35<'Общие данные'!$B$81,(Q35),IF(A35>'Общие данные'!$B$81,$H$56,0)))))) -> 46972 | C35: =C34-D34 -> 25000000 | D35: =IF(C35=0,L35,IF(C35>1,I35)) -> 2777777.8 | E35: =IF(C35=0,N34,IF(C35>1,L35)) -> 1239754.2 | F35: =IF(C35=0,N34,IF(C35>1,M35)) -> 4017532 | G35: =B35-B34 -> 33 | H35: =DATE(YEAR(B35),12,31)-DATE(YEAR(B35),1,1)+1 -> 366 | I35: =IF($L$5=A35,K35,IF($L$5>A35,I34)) -> 2777777.8 | J35: =SUM($I$8:I34) -> 75000000 | K35: =$J$12-J35 -> 25000000 | L35: =ROUND(C35*'Общие данные'!$B$84/H35,2)*G35 -> 1239754.2 | M35: =D35+E35 -> 4017532 | O35: =TEXT(R35,"ддд") -> Сб | P35: =IF(O35=$U$8,2,IF(O35=$V$8,1,0)) -> 2 | Q35: =DAY('Общие данные'!$B$78)+P35 -> 7 | R35: =IF(A35<='Общие данные'!$B$81,DATE(YEAR($B$8),MONTH($B$8)+A34,DAY('Общие данные'!$B$78)),0) -> 46970
A36: =1+A35 -> 29 | B36: =IF(A36<='Общие данные'!$B$81,DATE(YEAR(R36),MONTH(R36),DAY(IF(A36='Общие данные'!$B$81,'Общие данные'!$B$67,IF(A36<'Общие данные'!$B$81,(Q36),IF(A36>'Общие данные'!$B$81,$H$56,0)))))) -> 47001 | C36: =C35-D35 -> 22222222 | D36: =IF(C36=0,L36,IF(C36>1,I36)) -> 2777777.8 | E36: =IF(C36=0,N35,IF(C36>1,L36)) -> 968427.45 | F36: =IF(C36=0,N35,IF(C36>1,M36)) -> 3746205.2 | G36: =B36-B35 -> 29 | H36: =DATE(YEAR(B36),12,31)-DATE(YEAR(B36),1,1)+1 -> 366 | I36: =IF($L$5=A36,K36,IF($L$5>A36,I35)) -> 2777777.8 | J36: =SUM($I$8:I35) -> 77777778 | K36: =$J$12-J36 -> 22222222 | L36: =ROUND(C36*'Общие данные'!$B$84/H36,2)*G36 -> 968427.45 | M36: =D36+E36 -> 3746205.2 | O36: =TEXT(R36,"ддд") -> Вт | P36: =IF(O36=$U$8,2,IF(O36=$V$8,1,0)) -> 0 | Q36: =DAY('Общие данные'!$B$78)+P36 -> 5 | R36: =IF(A36<='Общие данные'!$B$81,DATE(YEAR($B$8),MONTH($B$8)+A35,DAY('Общие данные'!$B$78)),0) -> 47001
A37: =1+A36 -> 30 | B37: =IF(A37<='Общие данные'!$B$81,DATE(YEAR(R37),MONTH(R37),DAY(IF(A37='Общие данные'!$B$81,'Общие данные'!$B$67,IF(A37<'Общие данные'!$B$81,(Q37),IF(A37>'Общие данные'!$B$81,$H$56,0)))))) -> 47031 | C37: =C36-D36 -> 19444444 | D37: =IF(C37=0,L37,IF(C37>1,I37)) -> 2777777.8 | E37: =IF(C37=0,N36,IF(C37>1,L37)) -> 876593.7 | F37: =IF(C37=0,N36,IF(C37>1,M37)) -> 3654371.5 | G37: =B37-B36 -> 30 | H37: =DATE(YEAR(B37),12,31)-DATE(YEAR(B37),1,1)+1 -> 366 | I37: =IF($L$5=A37,K37,IF($L$5>A37,I36)) -> 2777777.8 | J37: =SUM($I$8:I36) -> 80555556 | K37: =$J$12-J37 -> 19444444 | L37: =ROUND(C37*'Общие данные'!$B$84/H37,2)*G37 -> 876593.7 | M37: =D37+E37 -> 3654371.5 | O37: =TEXT(R37,"ддд") -> Чт | P37: =IF(O37=$U$8,2,IF(O37=$V$8,1,0)) -> 0 | Q37: =DAY('Общие данные'!$B$78)+P37 -> 5 | R37: =IF(A37<='Общие данные'!$B$81,DATE(YEAR($B$8),MONTH($B$8)+A36,DAY('Общие данные'!$B$78)),0) -> 47031
A38: =1+A37 -> 31 | B38: =IF(A38<='Общие данные'!$B$81,DATE(YEAR(R38),MONTH(R38),DAY(IF(A38='Общие данные'!$B$81,'Общие данные'!$B$67,IF(A38<'Общие данные'!$B$81,(Q38),IF(A38>'Общие данные'!$B$81,$H$56,0)))))) -> 47063 | C38: =C37-D37 -> 16666667 | D38: =IF(C38=0,L38,IF(C38>1,I38)) -> 2777777.8 | E38: =IF(C38=0,N37,IF(C38>1,L38)) -> 801457.28 | F38: =IF(C38=0,N37,IF(C38>1,M38)) -> 3579235.1 | G38: =B38-B37 -> 32 | H38: =DATE(YEAR(B38),12,31)-DATE(YEAR(B38),1,1)+1 -> 366 | I38: =IF($L$5=A38,K38,IF($L$5>A38,I37)) -> 2777777.8 | J38: =SUM($I$8:I37) -> 83333333 | K38: =$J$12-J38 -> 16666667 | L38: =ROUND(C38*'Общие данные'!$B$84/H38,2)*G38 -> 801457.28 | M38: =D38+E38 -> 3579235.1 | O38: =TEXT(R38,"ддд") -> Вс | P38: =IF(O38=$U$8,2,IF(O38=$V$8,1,0)) -> 1 | Q38: =DAY('Общие данные'!$B$78)+P38 -> 6 | R38: =IF(A38<='Общие данные'!$B$81,DATE(YEAR($B$8),MONTH($B$8)+A37,DAY('Общие данные'!$B$78)),0) -> 47062
A39: =1+A38 -> 32 | B39: =IF(A39<='Общие данные'!$B$81,DATE(YEAR(R39),MONTH(R39),DAY(IF(A39='Общие данные'!$B$81,'Общие данные'!$B$67,IF(A39<'Общие данные'!$B$81,(Q39),IF(A39>'Общие данные'!$B$81,$H$56,0)))))) -> 47092 | C39: =C38-D38 -> 13888889 | D39: =IF(C39=0,L39,IF(C39>1,I39)) -> 2777777.8 | E39: =IF(C39=0,N38,IF(C39>1,L39)) -> 605267.12 | F39: =IF(C39=0,N38,IF(C39>1,M39)) -> 3383044.9 | G39: =B39-B38 -> 29 | H39: =DATE(YEAR(B39),12,31)-DATE(YEAR(B39),1,1)+1 -> 366 | I39: =IF($L$5=A39,K39,IF($L$5>A39,I38)) -> 2777777.8 | J39: =SUM($I$8:I38) -> 86111111 | K39: =$J$12-J39 -> 13888889 | L39: =ROUND(C39*'Общие данные'!$B$84/H39,2)*G39 -> 605267.12 | M39: =D39+E39 -> 3383044.9 | O39: =TEXT(R39,"ддд") -> Вт | P39: =IF(O39=$U$8,2,IF(O39=$V$8,1,0)) -> 0 | Q39: =DAY('Общие данные'!$B$78)+P39 -> 5 | R39: =IF(A39<='Общие данные'!$B$81,DATE(YEAR($B$8),MONTH($B$8)+A38,DAY('Общие данные'!$B$78)),0) -> 47092
A40: =1+A39 -> 33 | B40: =IF(A40<='Общие данные'!$B$81,DATE(YEAR(R40),MONTH(R40),DAY(IF(A40='Общие данные'!$B$81,'Общие данные'!$B$67,IF(A40<'Общие данные'!$B$81,(Q40),IF(A40>'Общие данные'!$B$81,$H$56,0)))))) -> 47123 | C40: =C39-D39 -> 11111111 | D40: =IF(C40=0,L40,IF(C40>1,I40)) -> 2777777.8 | E40: =IF(C40=0,N39,IF(C40>1,L40)) -> 519025.87 | F40: =IF(C40=0,N39,IF(C40>1,M40)) -> 3296803.6 | G40: =B40-B39 -> 31 | H40: =DATE(YEAR(B40),12,31)-DATE(YEAR(B40),1,1)+1 -> 365 | I40: =IF($L$5=A40,K40,IF($L$5>A40,I39)) -> 2777777.8 | J40: =SUM($I$8:I39) -> 88888889 | K40: =$J$12-J40 -> 11111111 | L40: =ROUND(C40*'Общие данные'!$B$84/H40,2)*G40 -> 519025.87 | M40: =D40+E40 -> 3296803.6 | O40: =TEXT(R40,"ддд") -> Пт | P40: =IF(O40=$U$8,2,IF(O40=$V$8,1,0)) -> 0 | Q40: =DAY('Общие данные'!$B$78)+P40 -> 5 | R40: =IF(A40<='Общие данные'!$B$81,DATE(YEAR($B$8),MONTH($B$8)+A39,DAY('Общие данные'!$B$78)),0) -> 47123
A41: =1+A40 -> 34 | B41: =IF(A41<='Общие данные'!$B$81,DATE(YEAR(R41),MONTH(R41),DAY(IF(A41='Общие данные'!$B$81,'Общие данные'!$B$67,IF(A41<'Общие данные'!$B$81,(Q41),IF(A41>'Общие данные'!$B$81,$H$56,0)))))) -> 47154 | C41: =C40-D40 -> 8333333.3 | D41: =IF(C41=0,L41,IF(C41>1,I41)) -> 2777777.8 | E41: =IF(C41=0,N40,IF(C41>1,L41)) -> 389269.48 | F41: =IF(C41=0,N40,IF(C41>1,M41)) -> 3167047.3 | G41: =B41-B40 -> 31 | H41: =DATE(YEAR(B41),12,31)-DATE(YEAR(B41),1,1)+1 -> 365 | I41: =IF($L$5=A41,K41,IF($L$5>A41,I40)) -> 2777777.8 | J41: =SUM($I$8:I40) -> 91666667 | K41: =$J$12-J41 -> 8333333.3 | L41: =ROUND(C41*'Общие данные'!$B$84/H41,2)*G41 -> 389269.48 | M41: =D41+E41 -> 3167047.3 | O41: =TEXT(R41,"ддд") -> Пн | P41: =IF(O41=$U$8,2,IF(O41=$V$8,1,0)) -> 0 | Q41: =DAY('Общие данные'!$B$78)+P41 -> 5 | R41: =IF(A41<='Общие данные'!$B$81,DATE(YEAR($B$8),MONTH($B$8)+A40,DAY('Общие данные'!$B$78)),0) -> 47154
A42: =1+A41 -> 35 | B42: =IF(A42<='Общие данные'!$B$81,DATE(YEAR(R42),MONTH(R42),DAY(IF(A42='Общие данные'!$B$81,'Общие данные'!$B$67,IF(A42<'Общие данные'!$B$81,(Q42),IF(A42>'Общие данные'!$B$81,$H$56,0)))))) -> 47182 | C42: =C41-D41 -> 5555555.5 | D42: =IF(C42=0,L42,IF(C42>1,I42)) -> 2777777.8 | E42: =IF(C42=0,N41,IF(C42>1,L42)) -> 234398.64 | F42: =IF(C42=0,N41,IF(C42>1,M42)) -> 3012176.4 | G42: =B42-B41 -> 28 | H42: =DATE(YEAR(B42),12,31)-DATE(YEAR(B42),1,1)+1 -> 365 | I42: =IF($L$5=A42,K42,IF($L$5>A42,I41)) -> 2777777.8 | J42: =SUM($I$8:I41) -> 94444445 | K42: =$J$12-J42 -> 5555555.5 | L42: =ROUND(C42*'Общие данные'!$B$84/H42,2)*G42 -> 234398.64 | M42: =D42+E42 -> 3012176.4 | O42: =TEXT(R42,"ддд") -> Пн | P42: =IF(O42=$U$8,2,IF(O42=$V$8,1,0)) -> 0 | Q42: =DAY('Общие данные'!$B$78)+P42 -> 5 | R42: =IF(A42<='Общие данные'!$B$81,DATE(YEAR($B$8),MONTH($B$8)+A41,DAY('Общие данные'!$B$78)),0) -> 47182
A43: =1+A42 -> 36 | B43: =IF(A43<='Общие данные'!$B$81,DATE(YEAR(R43),MONTH(R43),DAY(IF(A43='Общие данные'!$B$81,'Общие данные'!$B$67,IF(A43<'Общие данные'!$B$81,(Q43),IF(A43>'Общие данные'!$B$81,$H$56,0)))))) -> 47211 | C43: =C42-D42 -> 2777777.7 | D43: =IF(C43=0,L43,IF(C43>1,I43)) -> 2777777.7 | E43: =IF(C43=0,N42,IF(C43>1,L43)) -> 121385.01 | F43: =IF(C43=0,N42,IF(C43>1,M43)) -> 2899162.7 | G43: =B43-B42 -> 29 | H43: =DATE(YEAR(B43),12,31)-DATE(YEAR(B43),1,1)+1 -> 365 | I43: =IF($L$5=A43,K43,IF($L$5>A43,I42)) -> 2777777.7 | J43: =SUM($I$8:I42) -> 97222222 | K43: =$J$12-J43 -> 2777777.7 | L43: =ROUND(C43*'Общие данные'!$B$84/H43,2)*G43 -> 121385.01 | M43: =D43+E43 -> 2899162.7 | O43: =TEXT(R43,"ддд") -> Чт | P43: =IF(O43=$U$8,2,IF(O43=$V$8,1,0)) -> 0 | Q43: =DAY('Общие данные'!$B$78)+P43 -> 5 | R43: =IF(A43<='Общие данные'!$B$81,DATE(YEAR($B$8),MONTH($B$8)+A42,DAY('Общие данные'!$B$78)),0) -> 47213
... A55: =1+A54 -> 48 | B55: =IF(A55<='Общие данные'!$B$81,DATE(YEAR(R55),MONTH(R55),DAY(IF(A55='Общие данные'!$B$81,'Общие данные'!$B$67,IF(A55<'Общие данные'!$B$81,(Q55),IF(A55>'Общие данные'!$B$81,$H$56,0)))))) -> FALSE | C55: =C54-D54 -> -4.1909516e-09 | D55: =IF(C55=0,L55,IF(C55>1,I55)) -> FALSE | E55: =IF(C55=0,N54,IF(C55>1,L55)) -> FALSE | F55: =IF(C55=0,N54,IF(C55>1,M55)) -> FALSE | G55: =B55-B54 -> 0 | H55: =DATE(YEAR(B55),12,31)-DATE(YEAR(B55),1,1)+1 -> 366 | I55: =IF($L$5=A55,K55,IF($L$5>A55,I54)) -> FALSE | J55: =SUM($I$8:I54) -> 100000000 | K55: =$J$12-J55 -> 0 | L55: =ROUND(C55*'Общие данные'!$B$84/H55,2)*G55 -> 0 | M55: =D55+E55 -> 0 | O55: =TEXT(R55,"ддд") -> Сб | P55: =IF(O55=$U$8,2,IF(O55=$V$8,1,0)) -> 2 | Q55: =DAY('Общие данные'!$B$78)+P55 -> 7 | R55: =IF(A55<='Общие данные'!$B$81,DATE(YEAR($B$8),MONTH($B$8)+A54,DAY('Общие данные'!$B$78)),0) -> 0
B56: ИТОГО | D56: =SUM(D8:D55) -> 100000000 | E56: =SUM(E8:E55) -> 85231267 | F56: =SUM(F8:F55) -> 1.8523127e+08
A58: *В случае осуществления погашения платежей по кредиту в даты, отличные от указанных в графике погашения, сумма платежа меняется на сумму процентов, которые начисляются на сумму остатка долга по микрозайму в соответствии с п.п. 2.2. настоящего договора.
A60: =#REF! -> #REF! | D60: =#REF! -> #REF!
A62: =#REF! -> #REF! | D62: =#REF! -> #REF!
A63: =#REF! -> #REF! | D63: =#REF! -> #REF!
A64: =#REF! -> #REF! | D64: ="паспорт серии "&'Общие данные'!B16&", "&'Общие данные'!B20&"" -> паспорт серии AD 2849628, IIV 35233 tomonidan 23.03.2023 yilda berilgan
A65: =#REF! -> #REF!
A66: =#REF! -> #REF! | D66: =#REF! -> #REF!
A67: =#REF! -> #REF! | D67: =#REF! -> #REF!
A68: =#REF! -> #REF! | D68: =#REF! -> #REF!
A70: =#REF! -> #REF! | D70: =#REF! -> #REF!
A72: =#REF! -> #REF! | D72: =#REF! -> #REF!
D74: =#REF! -> #REF!

Sheet Данные для послед. Залога
A1: № | B1: - | E1: ФИО | F1: дата | L1: № договора | M1: Сог. Сумма | N1: сог. Сумма (пропис.)
A2: 1 | B2: ha | C2: yoq | D2: ha | E2: TULYAGANOV XODJIAKBAR IRGASHEVICH | F2: 44207 | G2: =MONTH(F2) -> 1 | H2: =IF(G2=$A$26,$A$28,IF(G2=$B$26,$B$28,IF(G2=$C$26,$C$28,IF(G2=$D$26,$D$28,IF(G2=$E$26,$E$28,IF(G2=$F$26,$F$28,IF(G2=$K$26,$K$28,IF(G2=$L$26,$L$28,IF(G2=$M$26,$M$28,IF(G2=$N$26,$N$28,IF(G2=$O$26,$O$28,IF(G2=$P$26,$P$28,0)))))))))))) -> yanvar | I2: =DAY(F2) -> 11 | J2: =YEAR(F2) -> 2021 | K2: =""&I2&" "&H2&" "&J2&" г." -> 11 yanvar 2021 г. | L2: 5 | M2: 15000000 | N2: on besh million | O2: ="- №"&L2&" от "&K2&", заключенного с ООО «Clever Mikrokredit Tashkiloti» и "&E2&", по согласованной залоговой стоимость - "&FIXED(M2)&" ("&N2&") сум." -> - №5 от 11 yanvar 2021 г., заключенного с ООО «Clever Mikrokredit Tashkiloti» и TULYAGANOV XODJIAKBAR IRGASHEVICH, по согласованной залоговой стоимость - 15 000 000,00 (on besh million) сум. | P2: =IF(D2=$B$2,O2,IF(D2=$C$2,$B$1)) -> - №5 от 11 yanvar 2021 г., заключенного с ООО «Clever Mikrokredit Tashkiloti» и TULYAGANOV XODJIAKBAR IRGASHEVICH, по согласованной залоговой стоимость - 15 000 000,00 (on besh million) сум. | W2: =""&P2&" "&P3&" "&P4&" "&P5&" "&P6&" "&P7&" "&P8&" "&P9&" "&P10&" "&P11&" "&P12&" "&P13&" "&P14&" "&P15&" "&P16&" "&P17&" "&P18&" "&P19&" "&P20&" "&P21&"" -> - №5 от 11 yanvar 2021 г., заключенного с ООО «Clever Mikrokredit Tashkiloti» и TULYAGANOV XODJIAKBAR IRGASHEVICH, по согласованной залоговой стоимость - 15 000 000,00 (on besh million) сум. - №386 от 6 noyabr 2019 г., заключенного с ООО «Clever Mikrokredit Tashkiloti» и YUNUSOVA ZALOXAT MIRSULTANOVNA, по согласованной залоговой стоимость - 15 000 000,00 (on besh million) сум. - №33 от 21 yanvar 2021 г., заключенного с ООО «Clever Mikrokredit Tashkiloti» и YUNUSOVA ZALOXAT MIRSULTANOVNA, по согласованной залоговой стоимость - 15 000 000,00 (on besh million) сум. 0 0 0 0 0 0 0 0 0 0 0 0 0 0 0 0 0
A3: 2 | D3: ha | E3: YUNUSOVA ZALOXAT MIRSULTANOVNA | F3: 43775 | G3: =MONTH(F3) -> 11 | H3: =IF(G3=$A$26,$A$28,IF(G3=$B$26,$B$28,IF(G3=$C$26,$C$28,IF(G3=$D$26,$D$28,IF(G3=$E$26,$E$28,IF(G3=$F$26,$F$28,IF(G3=$K$26,$K$28,IF(G3=$L$26,$L$28,IF(G3=$M$26,$M$28,IF(G3=$N$26,$N$28,IF(G3=$O$26,$O$28,IF(G3=$P$26,$P$28,0)))))))))))) -> noyabr | I3: =DAY(F3) -> 6 | J3: =YEAR(F3) -> 2019 | K3: =""&I3&" "&H3&" "&J3&" г." -> 6 noyabr 2019 г. | L3: 386 | M3: 15000000 | N3: on besh million | O3: ="- №"&L3&" от "&K3&", заключенного с ООО «Clever Mikrokredit Tashkiloti» и "&E3&", по согласованной залоговой стоимость - "&FIXED(M3)&" ("&N3&") сум." -> - №386 от 6 noyabr 2019 г., заключенного с ООО «Clever Mikrokredit Tashkiloti» и YUNUSOVA ZALOXAT MIRSULTANOVNA, по согласованной залоговой стоимость - 15 000 000,00 (on besh million) сум. | P3: =IF(D3=$B$2,O3,IF(D3=$C$2,$B$1)) -> - №386 от 6 noyabr 2019 г., заключенного с ООО «Clever Mikrokredit Tashkiloti» и YUNUSOVA ZALOXAT MIRSULTANOVNA, по согласованной залоговой стоимость - 15 000 000,00 (on besh million) сум.
A4: 3 | D4: ha | E4: YUNUSOVA ZALOXAT MIRSULTANOVNA | F4: 44217 | G4: =MONTH(F4) -> 1 | H4: =IF(G4=$A$26,$A$28,IF(G4=$B$26,$B$28,IF(G4=$C$26,$C$28,IF(G4=$D$26,$D$28,IF(G4=$E$26,$E$28,IF(G4=$F$26,$F$28,IF(G4=$K$26,$K$28,IF(G4=$L$26,$L$28,IF(G4=$M$26,$M$28,IF(G4=$N$26,$N$28,IF(G4=$O$26,$O$28,IF(G4=$P$26,$P$28,0)))))))))))) -> yanvar | I4: =DAY(F4) -> 21 | J4: =YEAR(F4) -> 2021 | K4: =""&I4&" "&H4&" "&J4&" г." -> 21 yanvar 2021 г. | L4: 33 | M4: 15000000 | N4: on besh million | O4: ="- №"&L4&" от "&K4&", заключенного с ООО «Clever Mikrokredit Tashkiloti» и "&E4&", по согласованной залоговой стоимость - "&FIXED(M4)&" ("&N4&") сум." -> - №33 от 21 yanvar 2021 г., заключенного с ООО «Clever Mikrokredit Tashkiloti» и YUNUSOVA ZALOXAT MIRSULTANOVNA, по согласованной залоговой стоимость - 15 000 000,00 (on besh million) сум. | P4: =IF(D4=$B$2,O4,IF(D4=$C$2,$B$1)) -> - №33 от 21 yanvar 2021 г., заключенного с ООО «Clever Mikrokredit Tashkiloti» и YUNUSOVA ZALOXAT MIRSULTANOVNA, по согласованной залоговой стоимость - 15 000 000,00 (on besh million) сум.
A5: 4 | D5: ha | G5: =MONTH(F5) -> 1 | H5: =IF(G5=$A$26,$A$28,IF(G5=$B$26,$B$28,IF(G5=$C$26,$C$28,IF(G5=$D$26,$D$28,IF(G5=$E$26,$E$28,IF(G5=$F$26,$F$28,IF(G5=$K$26,$K$28,IF(G5=$L$26,$L$28,IF(G5=$M$26,$M$28,IF(G5=$N$26,$N$28,IF(G5=$O$26,$O$28,IF(G5=$P$26,$P$28,0)))))))))))) -> yanvar | I5: =DAY(F5) -> 0 | J5: =YEAR(F5) -> 1900 | K5: =""&I5&" "&H5&" "&J5&" г." -> 0 yanvar 1900 г. | P5: =IF(D5=$B$2,O5,IF(D5=$C$2,$B$1)) -> 0
A6: 5 | D6: ha | G6: =MONTH(F6) -> 1 | H6: =IF(G6=$A$26,$A$28,IF(G6=$B$26,$B$28,IF(G6=$C$26,$C$28,IF(G6=$D$26,$D$28,IF(G6=$E$26,$E$28,IF(G6=$F$26,$F$28,IF(G6=$K$26,$K$28,IF(G6=$L$26,$L$28,IF(G6=$M$26,$M$28,IF(G6=$N$26,$N$28,IF(G6=$O$26,$O$28,IF(G6=$P$26,$P$28,0)))))))))))) -> yanvar | I6: =DAY(F6) -> 0 | J6: =YEAR(F6) -> 1900 | K6: =""&I6&" "&H6&" "&J6&" г." -> 0 yanvar 1900 г. | P6: =IF(D6=$B$2,O6,IF(D6=$C$2,$B$1)) -> 0
A7: 6 | D7: ha | G7: =MONTH(F7) -> 1 | H7: =IF(G7=$A$26,$A$28,IF(G7=$B$26,$B$28,IF(G7=$C$26,$C$28,IF(G7=$D$26,$D$28,IF(G7=$E$26,$E$28,IF(G7=$F$26,$F$28,IF(G7=$K$26,$K$28,IF(G7=$L$26,$L$28,IF(G7=$M$26,$M$28,IF(G7=$N$26,$N$28,IF(G7=$O$26,$O$28,IF(G7=$P$26,$P$28,0)))))))))))) -> yanvar | I7: =DAY(F7) -> 0 | J7: =YEAR(F7) -> 1900 | K7: =""&I7&" "&H7&" "&J7&" г." -> 0 yanvar 1900 г. | P7: =IF(D7=$B$2,O7,IF(D7=$C$2,$B$1)) -> 0
A8: 7 | D8: ha | G8: =MONTH(F8) -> 1 | H8: =IF(G8=$A$26,$A$28,IF(G8=$B$26,$B$28,IF(G8=$C$26,$C$28,IF(G8=$D$26,$D$28,IF(G8=$E$26,$E$28,IF(G8=$F$26,$F$28,IF(G8=$K$26,$K$28,IF(G8=$L$26,$L$28,IF(G8=$M$26,$M$28,IF(G8=$N$26,$N$28,IF(G8=$O$26,$O$28,IF(G8=$P$26,$P$28,0)))))))))))) -> yanvar | I8: =DAY(F8) -> 0 | J8: =YEAR(F8) -> 1900 | K8: =""&I8&" "&H8&" "&J8&" г." -> 0 yanvar 1900 г. | P8: =IF(D8=$B$2,O8,IF(D8=$C$2,$B$1)) -> 0
A9: 8 | D9: ha | G9: =MONTH(F9) -> 1 | H9: =IF(G9=$A$26,$A$28,IF(G9=$B$26,$B$28,IF(G9=$C$26,$C$28,IF(G9=$D$26,$D$28,IF(G9=$E$26,$E$28,IF(G9=$F$26,$F$28,IF(G9=$K$26,$K$28,IF(G9=$L$26,$L$28,IF(G9=$M$26,$M$28,IF(G9=$N$26,$N$28,IF(G9=$O$26,$O$28,IF(G9=$P$26,$P$28,0)))))))))))) -> yanvar | I9: =DAY(F9) -> 0 | J9: =YEAR(F9) -> 1900 | K9: =""&I9&" "&H9&" "&J9&" г." -> 0 yanvar 1900 г. | P9: =IF(D9=$B$2,O9,IF(D9=$C$2,$B$1)) -> 0
A10: 9 | D10: ha | G10: =MONTH(F10) -> 1 | H10: =IF(G10=$A$26,$A$28,IF(G10=$B$26,$B$28,IF(G10=$C$26,$C$28,IF(G10=$D$26,$D$28,IF(G10=$E$26,$E$28,IF(G10=$F$26,$F$28,IF(G10=$K$26,$K$28,IF(G10=$L$26,$L$28,IF(G10=$M$26,$M$28,IF(G10=$N$26,$N$28,IF(G10=$O$26,$O$28,IF(G10=$P$26,$P$28,0)))))))))))) -> yanvar | I10: =DAY(F10) -> 0 | J10: =YEAR(F10) -> 1900 | K10: =""&I10&" "&H10&" "&J10&" г." -> 0 yanvar 1900 г. | P10: =IF(D10=$B$2,O10,IF(D10=$C$2,$B$1)) -> 0
A11: 10 | D11: ha | G11: =MONTH(F11) -> 1 | H11: =IF(G11=$A$26,$A$28,IF(G11=$B$26,$B$28,IF(G11=$C$26,$C$28,IF(G11=$D$26,$D$28,IF(G11=$E$26,$E$28,IF(G11=$F$26,$F$28,IF(G11=$K$26,$K$28,IF(G11=$L$26,$L$28,IF(G11=$M$26,$M$28,IF(G11=$N$26,$N$28,IF(G11=$O$26,$O$28,IF(G11=$P$26,$P$28,0)))))))))))) -> yanvar | I11: =DAY(F11) -> 0 | J11: =YEAR(F11) -> 1900 | K11: =""&I11&" "&H11&" "&J11&" г." -> 0 yanvar 1900 г. | P11: =IF(D11=$B$2,O11,IF(D11=$C$2,$B$1)) -> 0
A12: 11 | D12: ha | G12: =MONTH(F12) -> 1 | H12: =IF(G12=$A$26,$A$28,IF(G12=$B$26,$B$28,IF(G12=$C$26,$C$28,IF(G12=$D$26,$D$28,IF(G12=$E$26,$E$28,IF(G12=$F$26,$F$28,IF(G12=$K$26,$K$28,IF(G12=$L$26,$L$28,IF(G12=$M$26,$M$28,IF(G12=$N$26,$N$28,IF(G12=$O$26,$O$28,IF(G12=$P$26,$P$28,0)))))))))))) -> yanvar | I12: =DAY(F12) -> 0 | J12: =YEAR(F12) -> 1900 | K12: =""&I12&" "&H12&" "&J12&" г." -> 0 yanvar 1900 г. | P12: =IF(D12=$B$2,O12,IF(D12=$C$2,$B$1)) -> 0
A13: 12 | D13: ha | G13: =MONTH(F13) -> 1 | H13: =IF(G13=$A$26,$A$28,IF(G13=$B$26,$B$28,IF(G13=$C$26,$C$28,IF(G13=$D$26,$D$28,IF(G13=$E$26,$E$28,IF(G13=$F$26,$F$28,IF(G13=$K$26,$K$28,IF(G13=$L$26,$L$28,IF(G13=$M$26,$M$28,IF(G13=$N$26,$N$28,IF(G13=$O$26,$O$28,IF(G13=$P$26,$P$28,0)))))))))))) -> yanvar | I13: =DAY(F13) -> 0 | J13: =YEAR(F13) -> 1900 | K13: =""&I13&" "&H13&" "&J13&" г." -> 0 yanvar 1900 г. | P13: =IF(D13=$B$2,O13,IF(D13=$C$2,$B$1)) -> 0
A14: 13 | D14: ha | G14: =MONTH(F14) -> 1 | H14: =IF(G14=$A$26,$A$28,IF(G14=$B$26,$B$28,IF(G14=$C$26,$C$28,IF(G14=$D$26,$D$28,IF(G14=$E$26,$E$28,IF(G14=$F$26,$F$28,IF(G14=$K$26,$K$28,IF(G14=$L$26,$L$28,IF(G14=$M$26,$M$28,IF(G14=$N$26,$N$28,IF(G14=$O$26,$O$28,IF(G14=$P$26,$P$28,0)))))))))))) -> yanvar | I14: =DAY(F14) -> 0 | J14: =YEAR(F14) -> 1900 | K14: =""&I14&" "&H14&" "&J14&" г." -> 0 yanvar 1900 г. | P14: =IF(D14=$B$2,O14,IF(D14=$C$2,$B$1)) -> 0
A15: 14 | D15: ha | G15: =MONTH(F15) -> 1 | H15: =IF(G15=$A$26,$A$28,IF(G15=$B$26,$B$28,IF(G15=$C$26,$C$28,IF(G15=$D$26,$D$28,IF(G15=$E$26,$E$28,IF(G15=$F$26,$F$28,IF(G15=$K$26,$K$28,IF(G15=$L$26,$L$28,IF(G15=$M$26,$M$28,IF(G15=$N$26,$N$28,IF(G15=$O$26,$O$28,IF(G15=$P$26,$P$28,0)))))))))))) -> yanvar | I15: =DAY(F15) -> 0 | J15: =YEAR(F15) -> 1900 | K15: =""&I15&" "&H15&" "&J15&" г." -> 0 yanvar 1900 г. | P15: =IF(D15=$B$2,O15,IF(D15=$C$2,$B$1)) -> 0
A16: 15 | D16: ha | G16: =MONTH(F16) -> 1 | H16: =IF(G16=$A$26,$A$28,IF(G16=$B$26,$B$28,IF(G16=$C$26,$C$28,IF(G16=$D$26,$D$28,IF(G16=$E$26,$E$28,IF(G16=$F$26,$F$28,IF(G16=$K$26,$K$28,IF(G16=$L$26,$L$28,IF(G16=$M$26,$M$28,IF(G16=$N$26,$N$28,IF(G16=$O$26,$O$28,IF(G16=$P$26,$P$28,0)))))))))))) -> yanvar | I16: =DAY(F16) -> 0 | J16: =YEAR(F16) -> 1900 | K16: =""&I16&" "&H16&" "&J16&" г." -> 0 yanvar 1900 г. | P16: =IF(D16=$B$2,O16,IF(D16=$C$2,$B$1)) -> 0
... A21: 20 | D21: ha | G21: =MONTH(F21) -> 1 | H21: =IF(G21=$A$26,$A$28,IF(G21=$B$26,$B$28,IF(G21=$C$26,$C$28,IF(G21=$D$26,$D$28,IF(G21=$E$26,$E$28,IF(G21=$F$26,$F$28,IF(G21=$K$26,$K$28,IF(G21=$L$26,$L$28,IF(G21=$M$26,$M$28,IF(G21=$N$26,$N$28,IF(G21=$O$26,$O$28,IF(G21=$P$26,$P$28,0)))))))))))) -> yanvar | I21: =DAY(F21) -> 0 | J21: =YEAR(F21) -> 1900 | K21: =""&I21&" "&H21&" "&J21&" г." -> 0 yanvar 1900 г. | P21: =IF(D21=$B$2,O21,IF(D21=$C$2,$B$1)) -> 0
M22: =SUM(M2:M21)+'Общие данные'!B136 -> 185000000 | Q22: ottiz yetti million besh yuz ming
A25: =MONTH(F2) -> 1 | B25: =IF(A25=A26,A28,IF(A25=B26,B28,IF(A25=C26,C28,IF(A25=D26,D28,IF(A25=E26,E28,IF(A25=F26,F28,IF(A25=K26,K28,IF(A25=L26,L28,IF(A25=M26,M28,IF(A25=N26,N28,IF(A25=O26,O28,IF(A25=#REF!,#REF!,)))))))))))) -> yanvar | C25: =DAY(F2) -> 11 | D25: =YEAR(F2) -> 2021
A26: 1 | B26: 2 | C26: 3 | D26: 4 | E26: 5 | F26: 6 | K26: 7 | L26: 8 | M26: 9 | N26: 10 | O26: 11 | P26: 12
A28: yanvar | B28: fevral | C28: mart | D28: aprel | E28: may | F28: iyun | K28: июля | L28: avgust | M28: sentyabr | N28: oktyabr | O28: noyabr | P28: dekabr
A29: yanvar | B29: fevral | C29: mart | D29: aprel | E29: may | F29: iyun | K29: июль | L29: avgust | M29: sentyabr | N29: oktyabr | O29: noyabr | P29: dekabr

Sheet Общие данные
A1: =CONCATENATE(B65," olish uchun ariza") -> Mikroqarz olish uchun ariza | B1: №310-TR
A2: =CONCATENATE(B65," olish uchun ariza sanasi QO’L BILAN KIRITILADI") -> Mikroqarz olish uchun ariza sanasi QO’L BILAN KIRITILADI | B2: 03.04.2026 | D2: =180+B2 -> 46295
A4: Qarz oluvchi bo’yicha ma’lumotlar
A5: Ariza beruvchining FISh (kim? – Ibragimov Rustam Sadikovich) | B5: ANNAZAROV KAXRAMAN SADULLAYEVICH
A6: agar o’zgarishlar bo’lgan bo’lsa oldingi FISh (Sadikov Rustam Sadikovich yoki yo’q) | B6: yo’q | C6: ha | D6: yo’q
A7: Ariza beruvchining FISh (kim? – Ibragimov R.S.) | B7: ANNAZAROV K.S.
A8: FISh (ariza kimdan? – Ibragimov Rustam Sadikovichdan) | B8: =B5 -> ANNAZAROV KAXRAMAN SADULLAYEVICH
A9: FISh (kimdan? – Ibragimov R.S.dan) | B9: =B7 -> ANNAZAROV K.S.
A10: FISh (kimga? – Ibragimov Rustam Sadikovichga) | B10: =B8 -> ANNAZAROV KAXRAMAN SADULLAYEVICH
A11: FISh (kimga? – Ibragimov R.S.ga) | B11: =B9 -> ANNAZAROV K.S.
A12: FISh (kim bilan? – Ibragimov Rustam Sadikovich bilan) | B12: =B10 -> ANNAZAROV KAXRAMAN SADULLAYEVICH
A13: FISh (kim bilan? – Ibragimov R.S. bilan) | B13: =B11 -> ANNAZAROV K.S.
A14: Fuqaroligi (O’zbekiston Respublikasi) | B14: O’zbekiston Respublikasi
A15: Tug’ilgan sanasi (01.10.2011 yil) | B15: 30.01.1973 y
A16: Pasport seriyasi (СА №1234567) | B16: AD 2849628
B17: IIV 35233 | D17: =TEXT(C17,"ДД.ММ.ГГГГ") -> 00.01.1900
B18: 45008 | C18: =TEXT(B18,"ДД.ММ.ГГГГ") -> 23.03.2023
B19: =DATE(YEAR(B18)+10,MONTH(B18),DAY(B18)-1) -> 48660 | C19: =TEXT(B19,"ДД.ММ.ГГГГ") -> 22.03.2033
A20: Kim va qachon berilgan (Toshkent shahri Chilonzor IIB tomonidan 2011 yil __.____) | B20: =""&B17&" tomonidan "&C18&" yilda berilgan" -> IIV 35233 tomonidan 23.03.2023 yilda berilgan | C20: =""&B17&" tomonidan "&C18&" yilda berilgan" -> IIV 35233 tomonidan 23.03.2023 yilda berilgan
A21: Pasportni amal qilish muddati (01.10.2011 yilgacha / yoki muddatsiz) | B21: =""&C19&" y." -> 22.03.2033 y. | C21: =""&C19&" yilgacha" -> 22.03.2033 yilgacha
A22: doimiy ro’yhatdan o’tgan joyi (Toshkent sh., Mirobod tumani, Nukus ko’chasi, 1 uy, 1 honadon) | B22: QORAQALPOG'ISTON RESPUBLIKASI TO'RTKO'L TUMANI YOSHLIK MFY KALTAMINAR KO'CHASI 1B-UY
A23: doimiy ro’yhatdan o’tgan joyi haqiqatdagi turar joyi bilan mos keladi/mos kelmaydi | B23: mos keladi | C23: mos keladi | D23: mos kelmaydi
A24: Ro’yhatdan o’tish joyida yashash asosi | B24: Mulk huquqi | C24: Mulk huquqi | D24: ijara | E24: служебная | F24: другое | G24: -
A25: Telefon raqami kod bilan ((99871) 277 77 77) | B25: 93 770 26 32 KLIENT
A26: Mo’ljal | B26: VISHKI TARAF GRAF METANNI YONIDA
B27: =IF(B23="mos keladi",B22,B28) -> QORAQALPOG'ISTON RESPUBLIKASI TO'RTKO'L TUMANI YOSHLIK MFY KALTAMINAR KO'CHASI 1B-UY
A28: Haqiqatdagi yashash joyi (Toshkent sh., Mirobod tumani, Nukus ko’chasi, 1 uy, 1 honadon) | B28: QORAQALPOG'ISTON RESPUBLIKASI TO'RTKO'L TUMANI YOSHLIK MFY KALTAMINAR KO'CHASI 1B-UY
A29: Haqiqatdagi yashash joyida turish asosi | B29: Mulk huquqi | C29: Mulk huquqi | D29: ijara | E29: xizmat | F29: boshqa | G29: -
A30: Mijozning jinsi | B30: erkak | C30: erkak | D30: ayol
A31: Tug’ilgan joyi (Toshkent) | B31: TO'RTKO'L SHAHRI
A32: Fuqaroligi (O’zbekiston Respublikasi) | B32: O’zbekiston Respublikasi
A33: Telefon raqami kod bilan ((99871) 277 77 77) | B33: =B25 -> 93 770 26 32 KLIENT
B34: =IF(B23="mos keladi",B26,B35) -> VISHKI TARAF GRAF METANNI YONIDA
A35: Mo’ljal
A36: Oilaviy ahvoli
A37: Oila a'zolari soni (jami):
A38: Ma’lumoti
A39: Mutaxassisligi
A40: Ish telefoni raqami kod bilan ((99890) 3270000) | B40: =B33 -> 93 770 26 32 KLIENT
A41: Mobil telefon raqami kod bilan ((99890) 3270000) | B41: 93 369 60 50 AYOLI
A42: Ish telefoni raqami kod bilan ((99890) 3270000) | B42: 94 149 90 95 UYI
A43: Mobil telefon raqami kod bilan ((99890) 3270000)
A44: Asosiy ish joyi | B44: O'Z O'ZINI BAND QILGAN FUQARO | C44: Yakka tartibdagi tadbirkor | D44: O'Z O'ZINI BAND QILGAN FUQARO
B45: =IF(B44=D44,CONCATENATE("MA'LUMOTNOMA ",B47,B46),C44) -> MA'LUMOTNOMA MA'LUMOTNOMA № 00130682640013068264
A46: O'Z O'ZINI BAND QILGAN BO'LSA, MA'LUMOTNOMA KIRITING | B46: 0013068264
B47: =CONCATENATE(C47," ",B46) -> MA'LUMOTNOMA № 0013068264 | C47: MA'LUMOTNOMA №
A48: AGAR O'Z O'ZINI BAND QILGAN FUQARO BO'LSA FAOLIYAT TURINI KIRITING | B48: Сантехника ишлари
A49: Lavozimi | B49: =IF(B44=C44,C44,B48) -> Сантехника ишлари
A50: Tashkilotning haqiqiy manzili (Toshkent sh., Mirobod tumani, Nukus ko’chasi, 1 uy, 1 honadon) | B50: Қорақалпоғистон Респ. Тўрткўл тумани
A51: Mo’ljal
A52: Ish staji, sanasidan (01.10.2011 yildan)
A53: Umumiy mehnat staji (3 yil/ 5 yil)
A54: Ish joyi telefon raqami
A55: Mijozning JSHIRi | B55: 33001733420046
A56: Mijozning unikal kodi | B56: 990000__
A57: QARZ OLUVCHINING ISH JOYI, LAVOZIMI VA O'RTACHA OYLIK DAROMADI
A58: Ish joyi | B58: =IF(B44=C44,C44,CONCATENATE(B44," ",B47)) -> O'Z O'ZINI BAND QILGAN FUQARO MA'LUMOTNOMA № 0013068264
A59: Lavozimi | B59: =B49 -> Сантехника ишлари
A60: O’rtacha oylik daromadi | B60: 15000000
A61: Mijozning boshqa daromadlari | B61: 6000000
A62: Ishning davomiyligi | B62: =B53 -> 0
A63: Ish joyidan ma’lumotnomaning raqami va sanasi
A64: Kredit bo’yicha parametrlar | C64: Mikrokredit | D64: Mikroqarz
A65: Kredit turi | B65: =IF(B75>100000001,"Mikrokredit",IF(B75<100000001,"Mikroqarz",0)) -> Mikroqarz | C65: =DATE(YEAR(B67),MONTH(B67)+B81,DAY(B67)) -> 47211
A66: Kredit shartnomasi raqami | B66: =B1 -> №310-TR | C66: =MONTH(C65) -> 4 | D66: =IF(C66=C68,C70,IF(C66=D68,D70,IF(C66=E68,E70,IF(C66=F68,F70,IF(C66=G68,G70,IF(C66=H68,H70,IF(C66=I68,I70,IF(C66=J68,J70,IF(C66=K68,K70,IF(C66=L68,L70,IF(C66=M68,M70,IF(C66=N68,N70,)))))))))))) -> aprel | E66: =DAY(C65) -> 3 | F66: =YEAR(C65) -> 2029 | G66: =MONTH(C65) -> 4 | H66: =IF(C66=C68,C71,IF(C66=D68,D71,IF(C66=E68,E71,IF(C66=F68,F71,IF(C66=G68,G71,IF(C66=H68,H71,IF(C66=I68,I71,IF(C66=J68,J71,IF(C66=K68,K71,IF(C66=L68,L71,IF(C66=M68,M71,IF(C66=N68,N71,)))))))))))) -> aprel | I66: =YEAR(C65) -> 2029
A67: Kredit shartnomasi sanasi (14.10.2011) | B67: =B2 -> 03.04.2026 | C67: =MONTH(B67) -> 4 | D67: =IF(C67=C68,C70,IF(C67=D68,D70,IF(C67=E68,E70,IF(C67=F68,F70,IF(C67=G68,G70,IF(C67=H68,H70,IF(C67=I68,I70,IF(C67=J68,J70,IF(C67=K68,K70,IF(C67=L68,L70,IF(C67=M68,M70,IF(C67=N68,N70,)))))))))))) -> aprel | E67: =DAY(B67) -> 3 | F67: =YEAR(B67) -> 2026 | G67: =MONTH(B67) -> 4 | H67: =IF(C67=C68,C71,IF(C67=D68,D71,IF(C67=E68,E71,IF(C67=F68,F71,IF(C67=G68,G71,IF(C67=H68,H71,IF(C67=I68,I71,IF(C67=J68,J71,IF(C67=K68,K71,IF(C67=L68,L71,IF(C67=M68,M71,IF(C67=N68,N71,)))))))))))) -> aprel | I67: =YEAR(B67) -> 2026
A68: Kredit shartnomasi sanasi (14.10.2011 y.) | B68: =""&E67&" "&D67&" "&F67&" y." -> 3 aprel 2026 y. | C68: 1 | D68: 2 | E68: 3 | F68: 4 | G68: 5 | H68: 6 | I68: 7 | J68: 8 | K68: 9 | L68: 10 | M68: 11 | N68: 12
B69: =""&E67&" "&H67&" "&F67&" y." -> 3 aprel 2026 y.
B70: =B68 -> 3 aprel 2026 y. | C70: yanvar | D70: fevral | E70: mart | F70: aprel | G70: may | H70: iyun | I70: iyul | J70: avgust | K70: sentabr | L70: oktabr | M70: noyabr | N70: dekabr
B71: =B69 -> 3 aprel 2026 y. | C71: yanvar | D71: fevral | E71: mart | F71: aprel | G71: may | H71: iyun | I71: iyul | J71: avgust | K71: sentabr | L71: oktabr | M71: noyabr | N71: dekabr
A72: Tugash sanasi QO’L BILAN KIRITILADI | B72: =""&E66&" "&D66&" "&F66&" y." -> 3 aprel 2029 y.
B73: =""&E66&" "&H66&" "&F66&" y." -> 3 aprel 2029 y.
A74: Kredit shartnomasi raqami va sanasi | B74: =""&B68&"dan "&B66&"" -> 3 aprel 2026 y.dan №310-TR
A75: =CONCATENATE(B65," miqdori (summasi)") -> Mikroqarz miqdori (summasi) | B75: 100000000 | C75: Uzbek tilida
A76: QO’L BILAN KIRITILADI | B76: =C76 -> Yuz million so'm | C76: =UPPER(LEFT(SUBSTITUTE(SUBSTITUTE(SUBSTITUTE(TRIM(SUBSTITUTE(SUBSTITUTE(SUBSTITUTE(SUBSTITUTE(SUBSTITUTE(SUBSTITUTE(SUBSTITUTE(SUBSTITUTE(SUBSTITUTE(SUBSTITUTE(SUBSTITUTE(SUBSTITUTE(SUBSTITUTE(SUBSTITUTE(SUBSTITUTE(SUBSTITUTE(SUBSTITUTE(SUBSTITUTE(SUBSTITUTE(SUBSTITUTE(SUBSTITUTE(SUBSTITUTE(SUBSTITUTE(SUBSTITUTE(SUBSTITUTE(SUBSTITUTE(SUBSTITUTE(SUBSTITUTE(SUBSTITUTE(SUBSTITUTE(SUBSTITUTE(SUBSTITUTE(SUBSTITUTE(SUBSTITUTE(SUBSTITUTE(SUBSTITUTE(SUBSTITUTE(SUBSTITUTE(SUBSTITUTE(SUBSTITUTE(SUBSTITUTE(SUBSTITUTE(SUBSTITUTE(SUBSTITUTE(SUBSTITUTE(SUBSTITUTE(SUBSTITUTE(SUBSTITUTE(IF(LEN(ROUNDDOWN(B75,0))>6,ROMAN(MID(ROUNDDOWN(B75,0),1,LEN(ROUNDDOWN(B75,0))-6)+0)&" million "&ROMAN(MID(ROUNDDOWN(B75,0),LEN(ROUNDDOWN(B75,0))-5,3)+0)&" ming "&ROMAN(MID(ROUNDDOWN(B75,0),LEN(ROUNDDOWN(B75,0))-2,3)+0)&" so'm",IF(LEN(ROUNDDOWN(B75,0))>3,ROMAN(MID(ROUNDDOWN(B75,0),1,LEN(ROUNDDOWN(B75,0))-3)+0)&" ming "&ROMAN(MID(ROUNDDOWN(B75,0),LEN(ROUNDDOWN(B75,0))-2,3)+0)&" so'm",ROMAN(ROUNDDOWN(B75,0))&" so'm")),"DCCC"," sakkiz yuz"),"DCC"," yetti yuz"),"DC"," olti yuz"),"CD"," to'rt yuz"),"XC"," to'qson"),"CCC"," uch yuz"),"CC"," ikki yuz"),"D"," besh yuz"),"CM"," to'qqiz yuz"),"C"," yuz"),"XL"," qiriq"),"LXXX"," sakson"),"LXX"," yetmish"),"LX"," oltmish"),"L"," ellik"),"XXX"," o'ttiz"),"XX"," yigirma"),"XIX"," o'n tiqqiz"),"XVIII"," o'n sakkiz"),"XVII"," o'n yetti"),"XVI"," o'n olti"),"XV"," o'n besh"),"XIV"," o'n to'rt"),"XIII"," o'n uch"),"XII"," o'n ikki"),"XI"," o'n bir"),"IX"," to'qqiz"),"X"," o'n"),"VIII"," sakkiz"),"VII"," yetti"),"VI"," olti"),"IV"," to'rt"),"V"," besh"),"III"," uch"),"II"," ikki"),"I"," bir"),"bir ming","bir ming"),"ikki ming","ikki ming"),"uch ming","uch ming"),"to'rt ming","to'rt ming"),"bir million","bir million"),"ikki million","ikki million"),"uch million","uch million"),"to'rt million","to'rt million"),"bir so'm","bir so'm"),"ikki so'm","ikki so'm"),"uch so'm","uch so'm"),"to'rt so'm","to'rt so'm")),"ming million","million"),"ming million","million"),"ming million","million"),1))&MID(SUBSTITUTE(SUBSTITUTE(SUBSTITUTE(TRIM(SUBSTITUTE(SUBSTITUTE(SUBSTITUTE(SUBSTITUTE(SUBSTITUTE(SUBSTITUTE(SUBSTITUTE(SUBSTITUTE(SUBSTITUTE(SUBSTITUTE(SUBSTITUTE(SUBSTITUTE(SUBSTITUTE(SUBSTITUTE(SUBSTITUTE(SUBSTITUTE(SUBSTITUTE(SUBSTITUTE(SUBSTITUTE(SUBSTITUTE(SUBSTITUTE(SUBSTITUTE(SUBSTITUTE(SUBSTITUTE(SUBSTITUTE(SUBSTITUTE(SUBSTITUTE(SUBSTITUTE(SUBSTITUTE(SUBSTITUTE(SUBSTITUTE(SUBSTITUTE(SUBSTITUTE(SUBSTITUTE(SUBSTITUTE(SUBSTITUTE(SUBSTITUTE(SUBSTITUTE(SUBSTITUTE(SUBSTITUTE(SUBSTITUTE(SUBSTITUTE(SUBSTITUTE(SUBSTITUTE(SUBSTITUTE(SUBSTITUTE(SUBSTITUTE(SUBSTITUTE(IF(LEN(ROUNDDOWN(B75,0))>6,ROMAN(MID(ROUNDDOWN(B75,0),1,LEN(ROUNDDOWN(B75,0))-6)+0)&" million "&ROMAN(MID(ROUNDDOWN(B75,0),LEN(ROUNDDOWN(B75,0))-5,3)+0)&" "&ROMAN(MID(ROUNDDOWN(B75,0),LEN(ROUNDDOWN(B75,0))-2,3)+0)&" so'm",IF(LEN(ROUNDDOWN(B75,0))>3,ROMAN(MID(ROUNDDOWN(B75,0),1,LEN(ROUNDDOWN(B75,0))-3)+0)&" ming "&ROMAN(MID(ROUNDDOWN(B75,0),LEN(ROUNDDOWN(B75,0))-2,3)+0)&" so'm",ROMAN(ROUNDDOWN(B75,0))&" so'm")),"DCCC"," sakkiz yuz"),"DCC"," yetti yuz"),"DC"," olti yuz"),"CD"," to'rt yuz"),"XC"," to'qson"),"CCC"," uch yuz"),"CC"," ikki yuz"),"D"," besh yuz"),"CM"," to'qqiz yuz"),"C"," yuz"),"XL"," qirq"),"LXXX"," sakson"),"LXX"," yetmish"),"LX"," oltmish"),"L"," ellik"),"XXX"," o'ttiz"),"XX"," yigirma"),"XIX"," o'n to'qqiz"),"XVIII"," o'n sakkiz"),"XVII"," o'n yetti"),"XVI"," o'n olti"),"XV"," o'n besh"),"XIV"," o'n to'rt"),"XIII"," o'n uch"),"XII"," o'n ikki"),"XI"," o'n bir"),"IX"," to'qqiz"),"X"," o'n"),"VIII"," sakkiz"),"VII"," yetti"),"VI"," olti"),"IV"," to'rt"),"V"," besh"),"III"," uch"),"II"," ikki"),"I"," bir"),"bir ming","bir ming"),"ikki ming","ikki ming"),"uch ming","uch ming"),"to'rt ming","to'rt ming"),"bir million","bir million"),"ikki million","ikki million"),"uch million","uch million"),"to'rt million","to'rt million"),"bir so'm","bir so'm"),"ikki so'm","ikki so'm"),"uch so'm","uch so'm"),"to'rt so'm","to'rt so'm")),"ming million","million"),"ming million","million"),"ming million","million"),2,200)&"" -> Yuz million so'm
A77: Grafik turi | B77: differensial | C77: differensial | D77: annuitet
A78: =CONCATENATE(B65,"ni to'lash sanasi (14.10.2011)") -> Mikroqarzni to'lash sanasi (14.10.2011) | B78: 5 | C78: =DATE(YEAR(B67),MONTH(B67)+1,DAY(B78)) -> 46147 | D78: Пн | E78: Вт | F78: Ср | G78: Чт | H78: Пт | I78: Сб | J78: Вс
A79: =CONCATENATE(B65,"ni to'lash sanasi (14.10.2011 y.) QO’L BILAN KIRITILADI") -> Mikroqarzni to'lash sanasi (14.10.2011 y.) QO’L BILAN KIRITILADI | B79: =DATE(YEAR(B67),MONTH(B67)+1,DAY(B78+C80)) -> 46147 | C79: =TEXT(C78,"ддд") -> Вт | D79: Пн | E79: Вт | F79: Ср | G79: Чт | H79: Пт | I79: Сб | J79: Вс
A80: Mikroqarzni to'lash sanasi (14.10.2011 y.) QO’L BILAN KIRITILADI | B80: =B79 -> 46147 | C80: =IF(C79=I79,2,IF(C79=J79,1,0)) -> 0
A81: =CONCATENATE(B65," muddati") -> Mikroqarz muddati | B81: 36 | C81: 6 | D81: 12 | E81: 18 | F81: 24 | G81: 16
A82: =CONCATENATE(B65," muddati QO’L BILAN KIRITILADI") -> Mikroqarz muddati QO’L BILAN KIRITILADI | B82: Yigirma to'rt
A83: Imtiyozli davr | B83: 0 | BJ83: 1 | BK83: 0
A84: =CONCATENATE(B65," stavkasi") -> Mikroqarz stavkasi | B84: 0.55
A85: =CONCATENATE(B65," stavkasi") -> Mikroqarz stavkasi | B85: 55
A86: =CONCATENATE(B65," stavkasi (so’z bilan)") -> Mikroqarz stavkasi (so’z bilan) | B86: =UPPER(LEFT(SUBSTITUTE(SUBSTITUTE(SUBSTITUTE(TRIM(SUBSTITUTE(SUBSTITUTE(SUBSTITUTE(SUBSTITUTE(SUBSTITUTE(SUBSTITUTE(SUBSTITUTE(SUBSTITUTE(SUBSTITUTE(SUBSTITUTE(SUBSTITUTE(SUBSTITUTE(SUBSTITUTE(SUBSTITUTE(SUBSTITUTE(SUBSTITUTE(SUBSTITUTE(SUBSTITUTE(SUBSTITUTE(SUBSTITUTE(SUBSTITUTE(SUBSTITUTE(SUBSTITUTE(SUBSTITUTE(SUBSTITUTE(SUBSTITUTE(SUBSTITUTE(SUBSTITUTE(SUBSTITUTE(SUBSTITUTE(SUBSTITUTE(SUBSTITUTE(SUBSTITUTE(SUBSTITUTE(SUBSTITUTE(SUBSTITUTE(SUBSTITUTE(SUBSTITUTE(SUBSTITUTE(SUBSTITUTE(SUBSTITUTE(SUBSTITUTE(SUBSTITUTE(SUBSTITUTE(SUBSTITUTE(SUBSTITUTE(SUBSTITUTE(SUBSTITUTE(IF(LEN(ROUNDDOWN(B85,0))>6,ROMAN(MID(ROUNDDOWN(B85,0),1,LEN(ROUNDDOWN(B85,0))-6)+0)&" million "&ROMAN(MID(ROUNDDOWN(B85,0),LEN(ROUNDDOWN(B85,0))-5,3)+0)&" ming "&ROMAN(MID(ROUNDDOWN(B85,0),LEN(ROUNDDOWN(B85,0))-2,3)+0)&"",IF(LEN(ROUNDDOWN(B85,0))>3,ROMAN(MID(ROUNDDOWN(B85,0),1,LEN(ROUNDDOWN(B85,0))-3)+0)&" ming "&ROMAN(MID(ROUNDDOWN(B85,0),LEN(ROUNDDOWN(B85,0))-2,3)+0)&"",ROMAN(ROUNDDOWN(B85,0))&"")),"DCCC"," sakkiz yuz"),"DCC"," yetti yuz"),"DC"," olti yuz"),"CD"," to'rt yuz"),"XC"," to'qson"),"CCC"," uch yuz"),"CC"," ikki yuz"),"D"," besh yuz"),"CM"," to'qqiz yuz"),"C"," yuz"),"XL"," qiriq"),"LXXX"," sakson"),"LXX"," yetmish"),"LX"," oltmish"),"L"," ellik"),"XXX"," o'ttiz"),"XX"," yigirma"),"XIX"," o'n tiqqiz"),"XVIII"," o'n sakkiz"),"XVII"," o'n yetti"),"XVI"," o'n olti"),"XV"," o'n besh"),"XIV"," o'n to'rt"),"XIII"," o'n uch"),"XII"," o'n ikki"),"XI"," o'n bir"),"IX"," to'qqiz"),"X"," o'n"),"VIII"," sakkiz"),"VII"," yetti"),"VI"," olti"),"IV"," to'rt"),"V"," besh"),"III"," uch"),"II"," ikki"),"I"," bir"),"bir ming","bir ming"),"ikki ming","ikki ming"),"uch ming","uch ming"),"to'rt ming","to'rt ming"),"bir million","bir million"),"ikki million","ikki million"),"uch million","uch million"),"to'rt million","to'rt million"),"bir","bir"),"ikki","ikki"),"uch","uch"),"to'rt","to'rt")),"ming million","million"),"ming million","million"),"ming million","million"),1))&MID(SUBSTITUTE(SUBSTITUTE(SUBSTITUTE(TRIM(SUBSTITUTE(SUBSTITUTE(SUBSTITUTE(SUBSTITUTE(SUBSTITUTE(SUBSTITUTE(SUBSTITUTE(SUBSTITUTE(SUBSTITUTE(SUBSTITUTE(SUBSTITUTE(SUBSTITUTE(SUBSTITUTE(SUBSTITUTE(SUBSTITUTE(SUBSTITUTE(SUBSTITUTE(SUBSTITUTE(SUBSTITUTE(SUBSTITUTE(SUBSTITUTE(SUBSTITUTE(SUBSTITUTE(SUBSTITUTE(SUBSTITUTE(SUBSTITUTE(SUBSTITUTE(SUBSTITUTE(SUBSTITUTE(SUBSTITUTE(SUBSTITUTE(SUBSTITUTE(SUBSTITUTE(SUBSTITUTE(SUBSTITUTE(SUBSTITUTE(SUBSTITUTE(SUBSTITUTE(SUBSTITUTE(SUBSTITUTE(SUBSTITUTE(SUBSTITUTE(SUBSTITUTE(SUBSTITUTE(SUBSTITUTE(SUBSTITUTE(SUBSTITUTE(SUBSTITUTE(IF(LEN(ROUNDDOWN(B85,0))>6,ROMAN(MID(ROUNDDOWN(B85,0),1,LEN(ROUNDDOWN(B85,0))-6)+0)&" million "&ROMAN(MID(ROUNDDOWN(B85,0),LEN(ROUNDDOWN(B85,0))-5,3)+0)&" "&ROMAN(MID(ROUNDDOWN(B85,0),LEN(ROUNDDOWN(B85,0))-2,3)+0)&"",IF(LEN(ROUNDDOWN(B85,0))>3,ROMAN(MID(ROUNDDOWN(B85,0),1,LEN(ROUNDDOWN(B85,0))-3)+0)&" ming "&ROMAN(MID(ROUNDDOWN(B85,0),LEN(ROUNDDOWN(B85,0))-2,3)+0)&"",ROMAN(ROUNDDOWN(B85,0))&"")),"DCCC"," sakkiz yuz"),"DCC"," yetti yuz"),"DC"," olti yuz"),"CD"," to'rt yuz"),"XC"," to'qson"),"CCC"," uch yuz"),"CC"," ikki yuz"),"D"," besh yuz"),"CM"," to'qqiz yuz"),"C"," yuz"),"XL"," qirq"),"LXXX"," sakson"),"LXX"," yetmish"),"LX"," oltmish"),"L"," ellik"),"XXX"," o'ttiz"),"XX"," yigirma"),"XIX"," o'n to'qqiz"),"XVIII"," o'n sakkiz"),"XVII"," o'n yetti"),"XVI"," o'n olti"),"XV"," o'n besh"),"XIV"," o'n to'rt"),"XIII"," o'n uch"),"XII"," o'n ikki"),"XI"," o'n bir"),"IX"," to'qqiz"),"X"," o'n"),"VIII"," sakkiz"),"VII"," yetti"),"VI"," olti"),"IV"," to'rt"),"V"," besh"),"III"," uch"),"II"," ikki"),"I"," bir"),"bir ming","bir ming"),"ikki ming","ikki ming"),"uch ming","uch ming"),"to'rt ming","to'rt ming"),"bir million","bir million"),"ikki million","ikki million"),"uch million","uch million"),"to'rt million","to'rt million"),"bir","bir"),"ikki","ikki"),"uch","uch"),"to'rt","to'rt")),"ming million","million"),"ming million","million"),"ming million","million"),2,200)&" "&SUBSTITUTE(SUBSTITUTE(SUBSTITUTE(SUBSTITUTE(SUBSTITUTE(SUBSTITUTE(SUBSTITUTE(SUBSTITUTE(RIGHT(TEXT(B85," "),2)&"","1","1"),"2","2"),"3","3"),"4","4"),"11","11"),"12","12"),"13","13"),"14","14") -> Ellik besh | C86: =UPPER(LEFT(SUBSTITUTE(SUBSTITUTE(SUBSTITUTE(TRIM(SUBSTITUTE(SUBSTITUTE(SUBSTITUTE(SUBSTITUTE(SUBSTITUTE(SUBSTITUTE(SUBSTITUTE(SUBSTITUTE(SUBSTITUTE(SUBSTITUTE(SUBSTITUTE(SUBSTITUTE(SUBSTITUTE(SUBSTITUTE(SUBSTITUTE(SUBSTITUTE(SUBSTITUTE(SUBSTITUTE(SUBSTITUTE(SUBSTITUTE(SUBSTITUTE(SUBSTITUTE(SUBSTITUTE(SUBSTITUTE(SUBSTITUTE(SUBSTITUTE(SUBSTITUTE(SUBSTITUTE(SUBSTITUTE(SUBSTITUTE(SUBSTITUTE(SUBSTITUTE(SUBSTITUTE(SUBSTITUTE(SUBSTITUTE(SUBSTITUTE(SUBSTITUTE(SUBSTITUTE(SUBSTITUTE(SUBSTITUTE(SUBSTITUTE(SUBSTITUTE(SUBSTITUTE(SUBSTITUTE(SUBSTITUTE(SUBSTITUTE(SUBSTITUTE(SUBSTITUTE(IF(LEN(ROUNDDOWN(B85,0))>6,ROMAN(MID(ROUNDDOWN(B85,0),1,LEN(ROUNDDOWN(B85,0))-6)+0)&" million "&ROMAN(MID(ROUNDDOWN(B85,0),LEN(ROUNDDOWN(B85,0))-5,3)+0)&" ming "&ROMAN(MID(ROUNDDOWN(B85,0),LEN(ROUNDDOWN(B85,0))-2,3)+0)&"",IF(LEN(ROUNDDOWN(B85,0))>3,ROMAN(MID(ROUNDDOWN(B85,0),1,LEN(ROUNDDOWN(B85,0))-3)+0)&" ming "&ROMAN(MID(ROUNDDOWN(B85,0),LEN(ROUNDDOWN(B85,0))-2,3)+0)&"",ROMAN(ROUNDDOWN(B85,0))&"")),"DCCC"," sakkiz yuz"),"DCC"," yetti yuz"),"DC"," olti yuz"),"CD"," to'rt yuz"),"XC"," to'qson"),"CCC"," uch yuz"),"CC"," ikki yuz"),"D"," besh yuz"),"CM"," to'qqiz yuz"),"C"," yuz"),"XL"," qiriq"),"LXXX"," sakson"),"LXX"," yetmish"),"LX"," oltmish"),"L"," ellik"),"XXX"," o'ttiz"),"XX"," yigirma"),"XIX"," o'n tiqqiz"),"XVIII"," o'n sakkiz"),"XVII"," o'n yetti"),"XVI"," o'n olti"),"XV"," o'n besh"),"XIV"," o'n to'rt"),"XIII"," o'n uch"),"XII"," o'n ikki"),"XI"," o'n bir"),"IX"," to'qqiz"),"X"," o'n"),"VIII"," sakkiz"),"VII"," yetti"),"VI"," olti"),"IV"," to'rt"),"V"," besh"),"III"," uch"),"II"," ikki"),"I"," bir"),"bir ming","bir ming"),"ikki ming","ikki ming"),"uch ming","uch ming"),"to'rt ming","to'rt ming"),"bir million","bir million"),"ikki million","ikki million"),"uch million","uch million"),"to'rt million","to'rt million"),"bir","bir"),"ikki","ikki"),"uch","uch"),"to'rt","to'rt")),"ming million","million"),"ming million","million"),"ming million","million"),1))&MID(SUBSTITUTE(SUBSTITUTE(SUBSTITUTE(TRIM(SUBSTITUTE(SUBSTITUTE(SUBSTITUTE(SUBSTITUTE(SUBSTITUTE(SUBSTITUTE(SUBSTITUTE(SUBSTITUTE(SUBSTITUTE(SUBSTITUTE(SUBSTITUTE(SUBSTITUTE(SUBSTITUTE(SUBSTITUTE(SUBSTITUTE(SUBSTITUTE(SUBSTITUTE(SUBSTITUTE(SUBSTITUTE(SUBSTITUTE(SUBSTITUTE(SUBSTITUTE(SUBSTITUTE(SUBSTITUTE(SUBSTITUTE(SUBSTITUTE(SUBSTITUTE(SUBSTITUTE(SUBSTITUTE(SUBSTITUTE(SUBSTITUTE(SUBSTITUTE(SUBSTITUTE(SUBSTITUTE(SUBSTITUTE(SUBSTITUTE(SUBSTITUTE(SUBSTITUTE(SUBSTITUTE(SUBSTITUTE(SUBSTITUTE(SUBSTITUTE(SUBSTITUTE(SUBSTITUTE(SUBSTITUTE(SUBSTITUTE(SUBSTITUTE(SUBSTITUTE(IF(LEN(ROUNDDOWN(B85,0))>6,ROMAN(MID(ROUNDDOWN(B85,0),1,LEN(ROUNDDOWN(B85,0))-6)+0)&" million "&ROMAN(MID(ROUNDDOWN(B85,0),LEN(ROUNDDOWN(B85,0))-5,3)+0)&" "&ROMAN(MID(ROUNDDOWN(B85,0),LEN(ROUNDDOWN(B85,0))-2,3)+0)&"",IF(LEN(ROUNDDOWN(B85,0))>3,ROMAN(MID(ROUNDDOWN(B85,0),1,LEN(ROUNDDOWN(B85,0))-3)+0)&" ming "&ROMAN(MID(ROUNDDOWN(B85,0),LEN(ROUNDDOWN(B85,0))-2,3)+0)&"",ROMAN(ROUNDDOWN(B85,0))&"")),"DCCC"," sakkiz yuz"),"DCC"," yetti yuz"),"DC"," olti yuz"),"CD"," to'rt yuz"),"XC"," to'qson"),"CCC"," uch yuz"),"CC"," ikki yuz"),"D"," besh yuz"),"CM"," to'qqiz yuz"),"C"," yuz"),"XL"," qirq"),"LXXX"," sakson"),"LXX"," yetmish"),"LX"," oltmish"),"L"," ellik"),"XXX"," o'ttiz"),"XX"," yigirma"),"XIX"," o'n to'qqiz"),"XVIII"," o'n sakkiz"),"XVII"," o'n yetti"),"XVI"," o'n olti"),"XV"," o'n besh"),"XIV"," o'n to'rt"),"XIII"," o'n uch"),"XII"," o'n ikki"),"XI"," o'n bir"),"IX"," to'qqiz"),"X"," o'n"),"VIII"," sakkiz"),"VII"," yetti"),"VI"," olti"),"IV"," to'rt"),"V"," besh"),"III"," uch"),"II"," ikki"),"I"," bir"),"bir ming","bir ming"),"ikki ming","ikki ming"),"uch ming","uch ming"),"to'rt ming","to'rt ming"),"bir million","bir million"),"ikki million","ikki million"),"uch million","uch million"),"to'rt million","to'rt million"),"bir","bir"),"ikki","ikki"),"uch","uch"),"to'rt","to'rt")),"ming million","million"),"ming million","million"),"ming million","million"),2,200)&" "&SUBSTITUTE(SUBSTITUTE(SUBSTITUTE(SUBSTITUTE(SUBSTITUTE(SUBSTITUTE(SUBSTITUTE(SUBSTITUTE(RIGHT(TEXT(B85," "),2)&"","1","1"),"2","2"),"3","3"),"4","4"),"11","11"),"12","12"),"13","13"),"14","14") -> Ellik besh
A87: =CONCATENATE("Muddati o'tgan ",B65," bo’yicha stavka") -> Muddati o'tgan Mikroqarz bo’yicha stavka | B87: 1.55
A88: QO’L BILAN KIRITILADI | B88: 155
A89: =CONCATENATE("Muddati o'tgan ",B65," bo’yicha stavka") -> Muddati o'tgan Mikroqarz bo’yicha stavka | B89: bir yuz ellik besh | C89: bir yuz ellik besh | D89: besh
A90: Oylik to'lov | B90: =IF(B77=C77,LARGE(График!F9:F26,1),ROUND(PMT(B84/12,B81,-B75,0),-3)) -> 7599695.5
A91: GAROV BO’YICHA MA’LUMOTLAR
B92: Birlamchi | C92: Birlamchi | D92: navbatdagi garov
A93: Garovga beruvchi mulkdormi? | B93: Ha | C93: Ha | D93: yo’q
A94: Agar garovga beruvchi qarz oluvchi bo'lmasa, garovga kim qo'yganligini ko'rsating | B94: Garovga beruvchining o’zi | C94: Garovga beruvchining o’zi | D94: Bosh ishonchnoma bo’yicha boshqa shaxs
A95: Bosh ishonchnoma bo’yicha bo’lsa FIShni ko’rsating
A96: Bosh ishonchnoma bo’yicha bo’lsa FIShni ko’rsating qisqacha
A97: ISHONCHNOMA BO’YICHA MA’LUMOTLAR
A98: Notarius manzili (Toshkent shahri, Olmazor tumani)
A99: Kim tomonidan berilgan (Notariusning FISh – Eshkabilov X.B.)
A100: Ishonchnoma reestr raqami
A101: Ishonchnoma berilgan sana
...

Sheet График аннуитет.
E1: Приложение №1
F2: ="к договору микрозайма "&'Общие данные'!B74&"" -> к договору микрозайма 3 aprel 2026 y.dan №310-TR
A4: График погашения
A6: № | B6: Дата погашения | C6: Остаток основного долга | D6: Сумма погашения, сум
D7: основного долга | E7: процентов* | F7: всего*
A8: 1 | B8: ='График дифференц'!B8 -> 46147 | C8: ='Общие данные'!B75 -> 100000000 | D8: =IF(A8<'Общие данные'!$B$81,'График аннуитет.'!F8-'График аннуитет.'!E8,'График аннуитет.'!C8) -> 2777777.8 | E8: =ROUND(C8*'Общие данные'!$B$84/H8,2)*'График аннуитет.'!G8 -> 4821917.8 | F8: ='Общие данные'!B90 -> 7599695.5 | G8: =B8-'Общие данные'!B67 -> 32 | H8: =DATE(YEAR(B8),12,31)-DATE(YEAR(B8),1,1)+1 -> 365
A9: 2 | B9: ='График дифференц'!B9 -> 46178 | C9: =C8-D8 -> 97222222 | D9: =IF(A9<'Общие данные'!$B$81,'График аннуитет.'!F9-'График аннуитет.'!E9,'График аннуитет.'!C9) -> 3058219.1 | E9: =ROUND(C9*'Общие данные'!$B$84/H9,2)*'График аннуитет.'!G9 -> 4541476.4 | F9: =IF(A9<'Общие данные'!$B$81,'График аннуитет.'!F8,'График аннуитет.'!D9+'График аннуитет.'!E9) -> 7599695.5 | G9: =B9-B8 -> 31 | H9: =DATE(YEAR(B9),12,31)-DATE(YEAR(B9),1,1)+1 -> 365
A10: 3 | B10: ='График дифференц'!B10 -> 46209 | C10: =C9-D9 -> 94164003 | D10: =IF(A10<'Общие данные'!$B$81,'График аннуитет.'!F10-'График аннуитет.'!E10,'График аннуитет.'!C10) -> 3201075.8 | E10: =ROUND(C10*'Общие данные'!$B$84/H10,2)*'График аннуитет.'!G10 -> 4398619.8 | F10: =IF(A10<'Общие данные'!$B$81,'График аннуитет.'!F9,'График аннуитет.'!D10+'График аннуитет.'!E10) -> 7599695.5 | G10: =B10-B9 -> 31 | H10: =DATE(YEAR(B10),12,31)-DATE(YEAR(B10),1,1)+1 -> 365
A11: 4 | B11: ='График дифференц'!B11 -> 46239 | C11: =C10-D10 -> 90962927 | D11: =IF(A11<'Общие данные'!$B$81,'График аннуитет.'!F11-'График аннуитет.'!E11,'График аннуитет.'!C11) -> 3487672.9 | E11: =ROUND(C11*'Общие данные'!$B$84/H11,2)*'График аннуитет.'!G11 -> 4112022.6 | F11: =IF(A11<'Общие данные'!$B$81,'График аннуитет.'!F10,'График аннуитет.'!D11+'График аннуитет.'!E11) -> 7599695.5 | G11: =B11-B10 -> 30 | H11: =DATE(YEAR(B11),12,31)-DATE(YEAR(B11),1,1)+1 -> 365
A12: 5 | B12: ='График дифференц'!B12 -> 46272 | C12: =C11-D11 -> 87475254 | D12: =IF(A12<'Общие данные'!$B$81,'График аннуитет.'!F12-'График аннуитет.'!E12,'График аннуитет.'!C12) -> 3249898.5 | E12: =ROUND(C12*'Общие данные'!$B$84/H12,2)*'График аннуитет.'!G12 -> 4349797 | F12: =IF(A12<'Общие данные'!$B$81,'График аннуитет.'!F11,'График аннуитет.'!D12+'График аннуитет.'!E12) -> 7599695.5 | G12: =B12-B11 -> 33 | H12: =DATE(YEAR(B12),12,31)-DATE(YEAR(B12),1,1)+1 -> 365
A13: 6 | B13: ='График дифференц'!B13 -> 46300 | C13: =C12-D12 -> 84225356 | D13: =IF(A13<'Общие данные'!$B$81,'График аннуитет.'!F13-'График аннуитет.'!E13,'График аннуитет.'!C13) -> 4046077.8 | E13: =ROUND(C13*'Общие данные'!$B$84/H13,2)*'График аннуитет.'!G13 -> 3553617.8 | F13: =IF(A13<'Общие данные'!$B$81,'График аннуитет.'!F12,'График аннуитет.'!D13+'График аннуитет.'!E13) -> 7599695.5 | G13: =B13-B12 -> 28 | H13: =DATE(YEAR(B13),12,31)-DATE(YEAR(B13),1,1)+1 -> 365
A14: 7 | B14: ='График дифференц'!B14 -> 46331 | C14: =C13-D13 -> 80179278 | D14: =IF(A14<'Общие данные'!$B$81,'График аннуитет.'!F14-'График аннуитет.'!E14,'График аннуитет.'!C14) -> 3854334.7 | E14: =ROUND(C14*'Общие данные'!$B$84/H14,2)*'График аннуитет.'!G14 -> 3745360.8 | F14: =IF(A14<'Общие данные'!$B$81,'График аннуитет.'!F13,'График аннуитет.'!D14+'График аннуитет.'!E14) -> 7599695.5 | G14: =B14-B13 -> 31 | H14: =DATE(YEAR(B14),12,31)-DATE(YEAR(B14),1,1)+1 -> 365
A15: 8 | B15: ='График дифференц'!B15 -> 46363 | C15: =C14-D14 -> 76324943 | D15: =IF(A15<'Общие данные'!$B$81,'График аннуитет.'!F15-'График аннуитет.'!E15,'График аннуитет.'!C15) -> 3919369.5 | E15: =ROUND(C15*'Общие данные'!$B$84/H15,2)*'График аннуитет.'!G15 -> 3680326.1 | F15: =IF(A15<'Общие данные'!$B$81,'График аннуитет.'!F14,'График аннуитет.'!D15+'График аннуитет.'!E15) -> 7599695.5 | G15: =B15-B14 -> 32 | H15: =DATE(YEAR(B15),12,31)-DATE(YEAR(B15),1,1)+1 -> 365
A16: 9 | B16: ='График дифференц'!B16 -> 46392 | C16: =C15-D15 -> 72405574 | D16: =IF(A16<'Общие данные'!$B$81,'График аннуитет.'!F16-'График аннуитет.'!E16,'График аннуитет.'!C16) -> 4435671.1 | E16: =ROUND(C16*'Общие данные'!$B$84/H16,2)*'График аннуитет.'!G16 -> 3164024.4 | F16: =IF(A16<'Общие данные'!$B$81,'График аннуитет.'!F15,'График аннуитет.'!D16+'График аннуитет.'!E16) -> 7599695.5 | G16: =B16-B15 -> 29 | H16: =DATE(YEAR(B16),12,31)-DATE(YEAR(B16),1,1)+1 -> 365
A17: 10 | B17: ='График дифференц'!B17 -> 46423 | C17: =C16-D16 -> 67969903 | D17: =IF(A17<'Общие данные'!$B$81,'График аннуитет.'!F17-'График аннуитет.'!E17,'График аннуитет.'!C17) -> 4424663.1 | E17: =ROUND(C17*'Общие данные'!$B$84/H17,2)*'График аннуитет.'!G17 -> 3175032.4 | F17: =IF(A17<'Общие данные'!$B$81,'График аннуитет.'!F16,'График аннуитет.'!D17+'График аннуитет.'!E17) -> 7599695.5 | G17: =B17-B16 -> 31 | H17: =DATE(YEAR(B17),12,31)-DATE(YEAR(B17),1,1)+1 -> 365
A18: 11 | B18: ='График дифференц'!B18 -> 46451 | C18: =C17-D17 -> 63545240 | D18: =IF(A18<'Общие данные'!$B$81,'График аннуитет.'!F18-'График аннуитет.'!E18,'График аннуитет.'!C18) -> 4918608.7 | E18: =ROUND(C18*'Общие данные'!$B$84/H18,2)*'График аннуитет.'!G18 -> 2681086.8 | F18: =IF(A18<'Общие данные'!$B$81,'График аннуитет.'!F17,'График аннуитет.'!D18+'График аннуитет.'!E18) -> 7599695.5 | G18: =B18-B17 -> 28 | H18: =DATE(YEAR(B18),12,31)-DATE(YEAR(B18),1,1)+1 -> 365
A19: 12 | B19: ='График дифференц'!B19 -> 46482 | C19: =C18-D18 -> 58626631 | D19: =IF(A19<'Общие данные'!$B$81,'График аннуитет.'!F19-'График аннуитет.'!E19,'График аннуитет.'!C19) -> 4861109 | E19: =ROUND(C19*'Общие данные'!$B$84/H19,2)*'График аннуитет.'!G19 -> 2738586.5 | F19: =IF(A19<'Общие данные'!$B$81,'График аннуитет.'!F18,'График аннуитет.'!D19+'График аннуитет.'!E19) -> 7599695.5 | G19: =B19-B18 -> 31 | H19: =DATE(YEAR(B19),12,31)-DATE(YEAR(B19),1,1)+1 -> 365
A20: 13 | B20: ='График дифференц'!B20 -> 46512 | C20: =C19-D19 -> 53765522 | D20: =IF(A20<'Общие данные'!$B$81,'График аннуитет.'!F20-'График аннуитет.'!E20,'График аннуитет.'!C20) -> 5169199.3 | E20: =ROUND(C20*'Общие данные'!$B$84/H20,2)*'График аннуитет.'!G20 -> 2430496.2 | F20: =IF(A20<'Общие данные'!$B$81,'График аннуитет.'!F19,'График аннуитет.'!D20+'График аннуитет.'!E20) -> 7599695.5 | G20: =B20-B19 -> 30 | H20: =DATE(YEAR(B20),12,31)-DATE(YEAR(B20),1,1)+1 -> 365
... A31: 24 | B31: ='График дифференц'!B31 -> 46848 | C31: =C30-D30 -> -17487315 | D31: =IF(A31<'Общие данные'!$B$81,'График аннуитет.'!F31-'График аннуитет.'!E31,'График аннуитет.'!C31) -> 8388058 | E31: =ROUND(C31*'Общие данные'!$B$84/H31,2)*'График аннуитет.'!G31 -> -788362.5 | F31: =IF(A31<'Общие данные'!$B$81,'График аннуитет.'!F30,'График аннуитет.'!D31+'График аннуитет.'!E31) -> 7599695.5 | G31: =B31-B30 -> 30 | H31: =DATE(YEAR(B31),12,31)-DATE(YEAR(B31),1,1)+1 -> 366
A32: =1+A31 -> 25 | B32: ='График дифференц'!B32 -> 46878 | C32: =C31-D31 -> -25875373 | D32: =IF(A32<'Общие данные'!$B$81,'График аннуитет.'!F32-'График аннуитет.'!E32,'График аннуитет.'!C32) -> 8766208.3 | E32: =ROUND(C32*'Общие данные'!$B$84/H32,2)*'График аннуитет.'!G32 -> -1166512.8 | F32: =IF(A32<'Общие данные'!$B$81,'График аннуитет.'!F31,'График аннуитет.'!D32+'График аннуитет.'!E32) -> 7599695.5 | G32: =B32-B31 -> 30 | H32: =DATE(YEAR(B32),12,31)-DATE(YEAR(B32),1,1)+1 -> 366
A33: =1+A32 -> 26 | B33: ='График дифференц'!B33 -> 46909 | C33: =C32-D32 -> -34641581 | D33: =IF(A33<'Общие данные'!$B$81,'График аннуитет.'!F33-'График аннуитет.'!E33,'График аннуитет.'!C33) -> 9213463.2 | E33: =ROUND(C33*'Общие данные'!$B$84/H33,2)*'График аннуитет.'!G33 -> -1613767.6 | F33: =IF(A33<'Общие данные'!$B$81,'График аннуитет.'!F32,'График аннуитет.'!D33+'График аннуитет.'!E33) -> 7599695.5 | G33: =B33-B32 -> 31 | H33: =DATE(YEAR(B33),12,31)-DATE(YEAR(B33),1,1)+1 -> 366
A34: =1+A33 -> 27 | B34: ='График дифференц'!B34 -> 46939 | C34: =C33-D33 -> -43855044 | D34: =IF(A34<'Общие данные'!$B$81,'График аннуитет.'!F34-'График аннуитет.'!E34,'График аннуитет.'!C34) -> 9576767.2 | E34: =ROUND(C34*'Общие данные'!$B$84/H34,2)*'График аннуитет.'!G34 -> -1977071.7 | F34: =IF(A34<'Общие данные'!$B$81,'График аннуитет.'!F33,'График аннуитет.'!D34+'График аннуитет.'!E34) -> 7599695.5 | G34: =B34-B33 -> 30 | H34: =DATE(YEAR(B34),12,31)-DATE(YEAR(B34),1,1)+1 -> 366
A35: =1+A34 -> 28 | B35: ='График дифференц'!B35 -> 46972 | C35: =C34-D34 -> -53431812 | D35: =IF(A35<'Общие данные'!$B$81,'График аннуитет.'!F35-'График аннуитет.'!E35,'График аннуитет.'!C35) -> 10249388 | E35: =ROUND(C35*'Общие данные'!$B$84/H35,2)*'График аннуитет.'!G35 -> -2649692.4 | F35: =IF(A35<'Общие данные'!$B$81,'График аннуитет.'!F34,'График аннуитет.'!D35+'График аннуитет.'!E35) -> 7599695.5 | G35: =B35-B34 -> 33 | H35: =DATE(YEAR(B35),12,31)-DATE(YEAR(B35),1,1)+1 -> 366
A36: =1+A35 -> 29 | B36: ='График дифференц'!B36 -> 47001 | C36: =C35-D35 -> -63681200 | D36: =IF(A36<'Общие данные'!$B$81,'График аннуитет.'!F36-'График аннуитет.'!E36,'График аннуитет.'!C36) -> 10374873 | E36: =ROUND(C36*'Общие данные'!$B$84/H36,2)*'График аннуитет.'!G36 -> -2775177.9 | F36: =IF(A36<'Общие данные'!$B$81,'График аннуитет.'!F35,'График аннуитет.'!D36+'График аннуитет.'!E36) -> 7599695.5 | G36: =B36-B35 -> 29 | H36: =DATE(YEAR(B36),12,31)-DATE(YEAR(B36),1,1)+1 -> 366
A37: =1+A36 -> 30 | B37: ='График дифференц'!B37 -> 47031 | C37: =C36-D36 -> -74056073 | D37: =IF(A37<'Общие данные'!$B$81,'График аннуитет.'!F37-'График аннуитет.'!E37,'График аннуитет.'!C37) -> 10938289 | E37: =ROUND(C37*'Общие данные'!$B$84/H37,2)*'График аннуитет.'!G37 -> -3338593.5 | F37: =IF(A37<'Общие данные'!$B$81,'График аннуитет.'!F36,'График аннуитет.'!D37+'График аннуитет.'!E37) -> 7599695.5 | G37: =B37-B36 -> 30 | H37: =DATE(YEAR(B37),12,31)-DATE(YEAR(B37),1,1)+1 -> 366
A38: =1+A37 -> 31 | B38: ='График дифференц'!B38 -> 47063 | C38: =C37-D37 -> -84994362 | D38: =IF(A38<'Общие данные'!$B$81,'График аннуитет.'!F38-'График аннуитет.'!E38,'График аннуитет.'!C38) -> 11686856 | E38: =ROUND(C38*'Общие данные'!$B$84/H38,2)*'График аннуитет.'!G38 -> -4087160.6 | F38: =IF(A38<'Общие данные'!$B$81,'График аннуитет.'!F37,'График аннуитет.'!D38+'График аннуитет.'!E38) -> 7599695.5 | G38: =B38-B37 -> 32 | H38: =DATE(YEAR(B38),12,31)-DATE(YEAR(B38),1,1)+1 -> 366
A39: =1+A38 -> 32 | B39: ='График дифференц'!B39 -> 47092 | C39: =C38-D38 -> -96681218 | D39: =IF(A39<'Общие данные'!$B$81,'График аннуитет.'!F39-'График аннуитет.'!E39,'График аннуитет.'!C39) -> 11812989 | E39: =ROUND(C39*'Общие данные'!$B$84/H39,2)*'График аннуитет.'!G39 -> -4213293.4 | F39: =IF(A39<'Общие данные'!$B$81,'График аннуитет.'!F38,'График аннуитет.'!D39+'График аннуитет.'!E39) -> 7599695.5 | G39: =B39-B38 -> 29 | H39: =DATE(YEAR(B39),12,31)-DATE(YEAR(B39),1,1)+1 -> 366
A40: =1+A39 -> 33 | B40: ='График дифференц'!B40 -> 47123 | C40: =C39-D39 -> -1.0849421e+08 | D40: =IF(A40<'Общие данные'!$B$81,'График аннуитет.'!F40-'График аннуитет.'!E40,'График аннуитет.'!C40) -> 12667713 | E40: =ROUND(C40*'Общие данные'!$B$84/H40,2)*'График аннуитет.'!G40 -> -5068017 | F40: =IF(A40<'Общие данные'!$B$81,'График аннуитет.'!F39,'График аннуитет.'!D40+'График аннуитет.'!E40) -> 7599695.5 | G40: =B40-B39 -> 31 | H40: =DATE(YEAR(B40),12,31)-DATE(YEAR(B40),1,1)+1 -> 365
A41: =1+A40 -> 34 | B41: ='График дифференц'!B41 -> 47154 | C41: =C40-D40 -> -1.2116192e+08 | D41: =IF(A41<'Общие данные'!$B$81,'График аннуитет.'!F41-'График аннуитет.'!E41,'График аннуитет.'!C41) -> 13259451 | E41: =ROUND(C41*'Общие данные'!$B$84/H41,2)*'График аннуитет.'!G41 -> -5659755.6 | F41: =IF(A41<'Общие данные'!$B$81,'График аннуитет.'!F40,'График аннуитет.'!D41+'График аннуитет.'!E41) -> 7599695.5 | G41: =B41-B40 -> 31 | H41: =DATE(YEAR(B41),12,31)-DATE(YEAR(B41),1,1)+1 -> 365
A42: =1+A41 -> 35 | B42: ='График дифференц'!B42 -> 47182 | C42: =C41-D41 -> -1.3442137e+08 | D42: =IF(A42<'Общие данные'!$B$81,'График аннуитет.'!F42-'График аннуитет.'!E42,'График аннуитет.'!C42) -> 13271173 | E42: =ROUND(C42*'Общие данные'!$B$84/H42,2)*'График аннуитет.'!G42 -> -5671477 | F42: =IF(A42<'Общие данные'!$B$81,'График аннуитет.'!F41,'График аннуитет.'!D42+'График аннуитет.'!E42) -> 7599695.5 | G42: =B42-B41 -> 28 | H42: =DATE(YEAR(B42),12,31)-DATE(YEAR(B42),1,1)+1 -> 365
A43: =1+A42 -> 36 | B43: ='График дифференц'!B43 -> 47211 | C43: =C42-D42 -> -1.4769254e+08 | D43: =IF(A43<'Общие данные'!$B$81,'График аннуитет.'!F43-'График аннуитет.'!E43,'График аннуитет.'!C43) -> -1.4769254e+08 | E43: =ROUND(C43*'Общие данные'!$B$84/H43,2)*'График аннуитет.'!G43 -> -6453961.9 | F43: =IF(A43<'Общие данные'!$B$81,'График аннуитет.'!F42,'График аннуитет.'!D43+'График аннуитет.'!E43) -> -1.5414651e+08 | G43: =B43-B42 -> 29 | H43: =DATE(YEAR(B43),12,31)-DATE(YEAR(B43),1,1)+1 -> 365
A44: =1+A43 -> 37 | B44: ='График дифференц'!B44 -> FALSE
A45: =1+A44 -> 38 | B45: ='График дифференц'!B45 -> FALSE
A46: =1+A45 -> 39 | B46: ='График дифференц'!B46 -> FALSE
A47: =1+A46 -> 40 | B47: ='График дифференц'!B47 -> FALSE
A48: =1+A47 -> 41 | B48: ='График дифференц'!B48 -> FALSE
A49: =1+A48 -> 42 | B49: ='График дифференц'!B49 -> FALSE
A50: =1+A49 -> 43 | B50: ='График дифференц'!B50 -> FALSE
A51: =1+A50 -> 44 | B51: ='График дифференц'!B51 -> FALSE
A52: =1+A51 -> 45 | B52: ='График дифференц'!B52 -> FALSE
A53: =1+A52 -> 46 | B53: ='График дифференц'!B53 -> FALSE
A54: =1+A53 -> 47 | B54: ='График дифференц'!B54 -> FALSE
A55: =1+A54 -> 48 | B55: ='График дифференц'!B55 -> FALSE
B56: ИТОГО | D56: =SUM(D8:D55) -> 100000000 | E56: =SUM(E8:E55) -> 11842838 | F56: =SUM(F8:F55) -> 1.1184284e+08
A58: *В случае осуществления погашения платежей по кредиту в даты, отличные от указанных в графике погашения, сумма платежа меняется на сумму процентов, которые начисляются на сумму остатка долга по микрозайму в соответствии с п.п. 2.2. настоящего договора.
A60: =#REF! -> #REF! | D60: =#REF! -> #REF!
A62: =#REF! -> #REF! | D62: =#REF! -> #REF!
A63: =#REF! -> #REF! | D63: =#REF! -> #REF!
A64: =#REF! -> #REF! | D64: ="паспорт серии "&'Общие данные'!B16&", "&'Общие данные'!B20&"" -> паспорт серии AD 2849628, IIV 35233 tomonidan 23.03.2023 yilda berilgan
A65: =#REF! -> #REF!
A66: =#REF! -> #REF! | D66: =#REF! -> #REF!
A67: =#REF! -> #REF! | D67: =#REF! -> #REF!
A68: =#REF! -> #REF! | D68: =#REF! -> #REF!
A70: =#REF! -> #REF! | D70: =#REF! -> #REF!
A72: =#REF! -> #REF! | D72: =#REF! -> #REF!

Sheet Анкета Клиента
A1: MIJOZNING ANKETASI
A2: Anketa kredit menejeri tomonidan mijozning javoblarini kiritish orqali to'ldiriladi, kerak bo'lganda, Mijoz tomonidan tanlangan javob variantlarini belgilash orqali amalga oshiriladi
A3: 1. MIJOZ HAQIDA MA'LUMOTLAR:
A4: ='Заключение КК'!A4:F4 -> Mijozning to'liq ismi sharifi: ANNAZAROV KAXRAMAN SADULLAYEVICH
A5: ='Заключение КК'!A5:F5 -> Tug'ilgan sanasi: 30.01.1973 y
A6: ='Заключение КК'!A6:F6 -> Pasport seriyasi AD 2849628 IIV 35233 tomonidan 23.03.2023 yilda berilgan, amal qilish muddati - 22.03.2033 y.
A7: ="Fuqaroligi: "&'Общие данные'!B32&"" -> Fuqaroligi: O’zbekiston Respublikasi
A8: ='Заключение КК'!A7:F7 -> Ro‘yxatdan o‘tgan manzili: QORAQALPOG'ISTON RESPUBLIKASI TO'RTKO'L TUMANI YOSHLIK MFY KALTAMINAR KO'CHASI 1B-UY, mo'ljal: VISHKI TARAF GRAF METANNI YONIDA
A9: =IF('Общие данные'!B23="mos keladi"," ",'Анкета Клиента'!A10:F10)
A10: ="Haqiqatdan yashash joy manzili: "&'Общие данные'!B28&"" -> Haqiqatdan yashash joy manzili: QORAQALPOG'ISTON RESPUBLIKASI TO'RTKO'L TUMANI YOSHLIK MFY KALTAMINAR KO'CHASI 1B-UY
A11: ='Заключение КК'!A8:F8 -> Ish joyi: lavozimi Сантехника ишлариda O'Z O'ZINI BAND QILGAN FUQARO
A12: 2. Mijoz bilan ulanich uchun aloqa ma'lumotlari:
A13: ="Uy telefoni raqami: "&'Общие данные'!B40&"" -> Uy telefoni raqami: 93 770 26 32 KLIENT
A14: ="Uyali telefon raqami: "&'Общие данные'!B41&"" -> Uyali telefon raqami: 93 369 60 50 AYOLI
A15: ="Uyali telefon raqami: "&'Общие данные'!B42&"" -> Uyali telefon raqami: 94 149 90 95 UYI
A16: ="Uyali telefon raqami: "&'Общие данные'!B42&"" -> Uyali telefon raqami: 94 149 90 95 UYI
A17: ="Ish telefoni raqami: "&'Общие данные'!B43&"" -> Ish telefoni raqami:
A18: 3. MIJOZNING ISH JOYI HAQIDA MA'LUMOT:
A19: ="Muassasa nomlanishi:"&'Общие данные'!B58&"" -> Muassasa nomlanishi:O'Z O'ZINI BAND QILGAN FUQARO MA'LUMOTNOMA № 0013068264
A20: ="Ro‘yxatdan o‘tish manzili:"&'Общие данные'!B50&"" -> Ro‘yxatdan o‘tish manzili:Қорақалпоғистон Респ. Тўрткўл тумани
A21: ="Lavozimi: "&'Общие данные'!B59&"" -> Lavozimi: Сантехника ишлари
A22: 4. MIJOZNING OYLIK DAROMADLARI VA XARAJATLARI HAQIDA MA'LUMOT
A23: Daromad manbalari | B23: Mijoz | C23: Turmush o'rtog'i | D23: Boshqa oila a'zolari | E23: Xarajatlar | F23: Мiqdori
A24: ish haqi (asosiy ish) | B24: ='Общие данные'!B60 -> 15000000 | C24: 0 | D24: 0 | E24: uy-joy va kommunal xizmatlar uchun to'lov | F24: 700000
A25: ish haqi (o‘rindoshlik) | B25: 0 | C25: 0 | D25: 0 | E25: oilaviy xarajatlar | F25: 500000
A26: boshqa daromadlar | B26: ='Общие данные'!B61 -> 6000000 | C26: 0 | D26: 0 | E26: boshqa xarajatlar | F26: 600000
A27: JAMI | B27: =B24+B25+B26 -> 21000000 | C27: =SUM(C24:C26) -> 0 | D27: =SUM(D24:D26) -> 0 | F27: =SUM(F24:F26) -> 1800000
A28: ="Men, "&'Общие данные'!B5&", ushbu anketada ko‘rsatilgan barcha ma'lumotlar anketa to'ldirilgan sanada to'g'ri va aniq ekanligini tasdiqlayman." -> Men, ANNAZAROV KAXRAMAN SADULLAYEVICH, ushbu anketada ko‘rsatilgan barcha ma'lumotlar anketa to'ldirilgan sanada to'g'ri va aniq ekanligini tasdiqlayman.
A29: ="Men, "&'Общие данные'!B5&", quyidagilarni tan olaman va roziman::" -> Men, ANNAZAROV KAXRAMAN SADULLAYEVICH, quyidagilarni tan olaman va roziman::
A30: ="1. Ushbu anketada ko‘rsatilgan har qanday ma’lumot "&'Общие данные'!B147&", uning xodimlari va huquqiy vorislari tomonidan istalgan manbaa va ma’lumotlardan foydalangan holda istalgan vaqtda tekshirilishi va qayta tekshirilishi mumkin." -> 1. Ushbu anketada ko‘rsatilgan har qanday ma’lumot «PULLOL BUSINESS MIKROMOLIYA TASHKILOTI» MChJ, uning xodimlari va huquqiy vorislari tomonidan istalgan manbaa va ma’lumotlardan foydalangan holda istalgan vaqtda tekshirilishi va qayta tekshirilishi mumkin.
A31: ="2. Mazkur anketaning "&'Общие данные'!B147&" tomonidan qabul qilinishi menga "&'Общие данные'!B65&" berish majburiyatini yuklamaydi." -> 2. Mazkur anketaning «PULLOL BUSINESS MIKROMOLIYA TASHKILOTI» MChJ tomonidan qabul qilinishi menga Mikroqarz berish majburiyatini yuklamaydi.
A32: Men, _________________________________________________________________ (to'liq ismi sharifi), ushbu anketadagi barcha ma'lumotlar anketa to'ldirilgan sanada to'g'ri ekanligini tasdiqlayman va ushbu anketaning 1- va 2-bandlarini tan olaman va ularga rozilik bildiraman. Mazkur anketaning 4-bo'limida ko'rsatilgan daromadlarim haqidagi ma'lumotlarni qabul qilishingizni va moliyaviy tahlilda foydalanishingizni so’rayman.
A34: Mijozning to'liq ismi sharifi | D34: Sana | E34: Imzo
D35: ='Общие данные'!B2 -> 03.04.2026

Sheet Анкета 2
A2: ANKETA
E3: ='Общие данные'!B68 -> 3 aprel 2026 y.
A5: Mijozning to'liq ismi sharifi | C5: ='Общие данные'!B8 -> ANNAZAROV KAXRAMAN SADULLAYEVICH
A7: Siz ommaviy mansabdor shaxsmisiz? | D7: Ha
D8: Yo'q
A9: Yaqin qarindoshlaringiz orasida ommaviy mansabdor shaxslar bormi? | D9: Ha
D10: Yo'q
A11: Do'stlaringiz yoki yaqinlaringizdan birontasi ommaviy mansabdor shaxsmi? | D11: Ha
D12: Yo'q
A13: Yuqoridagi savollardan biriga «Ha» deb javob bergan bo'lsangiz, javobingizni qisqacha tushuntirib bering:
A18: Siz bank amaliyotlarini amalga oshirishda uchinchi shaxsning manfaatlarini ifodalaysizmi? | D18: Ha
D19: Yo'q
A20: Agar oldingi savolga «HA» deb javob bergan bo'lsangiz, bank operatsiyalarini bajarich uchun ishonchnomangiz bormi? | D20: Ha
D21: Yo'q
A23: Agar oldingi savolga «YO'Q» deb javob bergan bo'lsangiz, javobingizni qisqacha tushuntirib bering:
A28: Ommaviy mansabdor shaxslar — doimiy, vaqtincha yoki maxsus vakolatli organ tomonidan tayinlangan yoki saylangan, tashkiliy-maʼmuriy funktsiyalarni bajaruvchi hamda xorijiy davlatning qonun chiqaruvchi, ijro etuvchi, maʼmuriy yoki sud organida yoxud xalqaro tashkilotda yuridik ahamiyatga molik harakatlarni amalga oshirishga vakolatli shaxslar, shuningdek xorijiy davlatlar korxonalarining yuqori martabali rahbarlari, taniqli siyosatchilar va xorijiy davlatlar siyosiy partiyalarining taniqli a'zolari.
A30: Anketadagi barcha ma'lumotlar to'g'ri, agar o'zgarishlar bo'lsa, men bu haqida xabardor qilish majburiyatini o'z zimmamga olaman.
A33: =C5 -> ANNAZAROV KAXRAMAN SADULLAYEVICH

Sheet Кредитная заявка
C1: =""&'Общие данные'!B147&"ning "&'Общие данные'!A160&"i" -> «PULLOL BUSINESS MIKROMOLIYA TASHKILOTI» MChJning To'rtko'l filiali boshlig’ii
D2: =""&'Общие данные'!B160&"ga" -> Djumanazarov B.A.ga
A4: =""&'Общие данные'!C64&" olish uchun Ariza" -> Mikrokredit olish uchun Ariza
A6: =""&'Общие данные'!B28&".-da yashovchi O‘zbekiston Respublikasi fuqarosi "&'Общие данные'!B8&"dan. " -> QORAQALPOG'ISTON RESPUBLIKASI TO'RTKO'L TUMANI YOSHLIK MFY KALTAMINAR KO'CHASI 1B-UY.-da yashovchi O‘zbekiston Respublikasi fuqarosi ANNAZAROV KAXRAMAN SADULLAYEVICHdan.
A7: ="Tug'ilgan kuni: "&'Общие данные'!B15&"" -> Tug'ilgan kuni: 30.01.1973 y
A8: ="Pasport seriyasi: "&'Общие данные'!B16&" "&'Общие данные'!B20&"" -> Pasport seriyasi: AD 2849628 IIV 35233 tomonidan 23.03.2023 yilda berilgan
A9: ="Asosiy ish joyi : "&'Общие данные'!B58&"" -> Asosiy ish joyi : O'Z O'ZINI BAND QILGAN FUQARO MA'LUMOTNOMA № 0013068264
A10: ="Lavozimi: "&'Общие данные'!B59&"" -> Lavozimi: Сантехника ишлари
A11: ="O’rtacha oylik daromadi: "&FIXED('Анкета Клиента'!B27,2)&" so'm." -> O’rtacha oylik daromadi: 21 000 000,00 so'm.
A12: ="Menga quyidagi shartlarda "&'Общие данные'!B65&" berishingizni so’rayman:" -> Menga quyidagi shartlarda Mikroqarz berishingizni so’rayman:
A13: =""&'Общие данные'!B65&" summasi: "&FIXED('Общие данные'!B75,2)&" ("&'Общие данные'!B76&") so'm." -> Mikroqarz summasi: 100 000 000,00 (Yuz million so'm) so'm.
A14: =""&'Общие данные'!B65&" muddati: "&'Общие данные'!B81&" ("&'Общие данные'!B82&") oy." -> Mikroqarz muddati: 36 (Yigirma to'rt) oy.
A15: =""&'Общие данные'!B65&"dan foydalanganlik uchun foiz stavkasi: yillik "&'Общие данные'!B85&"% ("&'Общие данные'!B86&") foiz" -> Mikroqarzdan foydalanganlik uchun foiz stavkasi: yillik 55% (Ellik besh ) foiz
A16: =""&'Общие данные'!B65&" bo'yicha asosiy qarz va foizlarni to'lash:" -> Mikroqarz bo'yicha asosiy qarz va foizlarni to'lash:
A17: =" - "&'Общие данные'!B65&" shartnomasi bo'yicha har oy differensial to'lovlari amalga oshiriladi" -> - Mikroqarz shartnomasi bo'yicha har oy differensial to'lovlari amalga oshiriladi
A18: =" - "&'Общие данные'!B65&" shartnomasi bo'yicha har oy annuitet to'lovlari amalga oshiriladi" -> - Mikroqarz shartnomasi bo'yicha har oy annuitet to'lovlari amalga oshiriladi
A19: =IF('Общие данные'!B77='Общие данные'!C77,'Кредитная заявка'!A17:D17,IF('Общие данные'!B77='Общие данные'!D77,'Кредитная заявка'!A18:D18)) -> - Mikroqarz shartnomasi bo'yicha har oy differensial to'lovlari amalga oshiriladi
A20: =IF(DAY('Общие данные'!E67)<15," "," Oxirgi yakuniy to'lov "&'Общие данные'!B65&" shartnomasi tuzilgan kundan boshlab oxirgi oyning oxirgi kunida amalga oshiriladi")
A21: =""&'Общие данные'!B65&" ta’minoti::" -> Mikroqarz ta’minoti::
A22: =IF('Общие данные'!B103="Avtotransport",A26,A23) -> Egalik huquqi ANNAZAROV KAXRAMAN SADULLAYEVICHga tegishli bo'lgan umumiy yer maydoni, (m2) - 704, qurilish osti maydoni - 149,81, umumiy foydali maydoni - 213,72 va yashash maydoni - 108,36 Yakka tartibdagi uy-joy, QORAQALPOG'ISTON RESPUBLIKASI TO'RTKO'L TUMANI YOSHLIK MFY KALTAMINAR KO'CHASI 1B-UY
A23: =IF('Общие данные'!B92='Общие данные'!C92,A25,IF('Общие данные'!B92='Общие данные'!D92,A24,0)) -> Egalik huquqi ANNAZAROV KAXRAMAN SADULLAYEVICHga tegishli bo'lgan umumiy yer maydoni, (m2) - 704, qurilish osti maydoni - 149,81, umumiy foydali maydoni - 213,72 va yashash maydoni - 108,36 Yakka tartibdagi uy-joy, QORAQALPOG'ISTON RESPUBLIKASI TO'RTKO'L TUMANI YOSHLIK MFY KALTAMINAR KO'CHASI 1B-UY
A24: =" - Navbatdagi garov (ipoteka) Egalik huquqi asosida "&'Общие данные'!C117&"ga "&'Общие данные'!C126&", umumiy maydoni - "&'Общие данные'!C130&" va qurilish osti maydoni - "&'Общие данные'!C133&", manzili: "&'Общие данные'!C123&"." -> - Navbatdagi garov (ipoteka) Egalik huquqi asosida ANNAZAROV KAXRAMAN SADULLAYEVICHga Yakka tartibdagi uy-joy, umumiy maydoni - 213,72 va qurilish osti maydoni - 149,81, manzili: QORAQALPOG'ISTON RESPUBLIKASI TO'RTKO'L TUMANI YOSHLIK MFY KALTAMINAR KO'CHASI 1B-UY.
A25: =" Egalik huquqi "&'Общие данные'!C117&"ga tegishli bo'lgan "&'Общие данные'!D134&" - "&'Общие данные'!C134&", "&'Общие данные'!D133&" - "&'Общие данные'!C133&", "&'Общие данные'!D130&" - "&'Общие данные'!C130&" va "&'Общие данные'!D131&" - "&'Общие данные'!C131&" "&'Общие данные'!C126&", "&'Общие данные'!C123&" " -> Egalik huquqi ANNAZAROV KAXRAMAN SADULLAYEVICHga tegishli bo'lgan umumiy yer maydoni, (m2) - 704, qurilish osti maydoni - 149,81, umumiy foydali maydoni - 213,72 va yashash maydoni - 108,36 Yakka tartibdagi uy-joy, QORAQALPOG'ISTON RESPUBLIKASI TO'RTKO'L TUMANI YOSHLIK MFY KALTAMINAR KO'CHASI 1B-UY
A26: =IF('Общие данные'!B92='Общие данные'!C92,'Кредитная заявка'!A28:D28,IF('Общие данные'!B92='Общие данные'!D92,'Кредитная заявка'!A27:D27,0)) -> Egalik huquqi ANNAZAROV KAXRAMAN SADULLAYEVICHga tegishli bo'lgan garovga olingan avtomobil markasi , rangi - , ishlab chiqarilgan yili - , davlat raqam belgisi , kuzov turi - , kuzov raqami , dvigatel raqami , shassi raqami -
A27: =" Egalik huquqi "&'Общие данные'!B117&"ga tegishli bo'lgan "&'Общие данные'!B125&", "&'Общие данные'!B133&", davlat raqam belgisi "&'Общие данные'!B126&", "&'Общие данные'!B127&", "&'Общие данные'!B130&" avtotransport vositasi " -> Egalik huquqi ANNAZAROV KAXRAMAN SADULLAYEVICHga tegishli bo'lgan , rangi - , ishlab chiqarilgan yili - , davlat raqam belgisi , kuzov turi - , kuzov raqami , dvigatel raqami , shassi raqami - avtotransport vositasi
A28: =" Egalik huquqi "&'Общие данные'!B117&"ga tegishli bo'lgan garovga olingan avtomobil markasi "&'Общие данные'!B125&", "&'Общие данные'!B133&", davlat raqam belgisi "&'Общие данные'!B126&", "&'Общие данные'!B127&", "&'Общие данные'!B130&"" -> Egalik huquqi ANNAZAROV KAXRAMAN SADULLAYEVICHga tegishli bo'lgan garovga olingan avtomobil markasi , rangi - , ishlab chiqarilgan yili - , davlat raqam belgisi , kuzov turi - , kuzov raqami , dvigatel raqami , shassi raqami -
A30: ="Mazkur ariza bilan "&'Общие данные'!B147&"ga men va soʻralayotgan "&'Общие данные'!B65&" boʻyicha barcha zarur maʼlumotlarni quyida ko’rsatilgan tashkilotlarga taqdim etish va olishga roziligimni bildirib, ushbu amaliyotlarni o’tkazish uchun huquq beraman:" -> Mazkur ariza bilan «PULLOL BUSINESS MIKROMOLIYA TASHKILOTI» MChJga men va soʻralayotgan Mikroqarz boʻyicha barcha zarur maʼlumotlarni quyida ko’rsatilgan tashkilotlarga taqdim etish va olishga roziligimni bildirib, ushbu amaliyotlarni o’tkazish uchun huquq beraman:
A31: □ O‘zbekiston Respublikasi Markaziy banki huzuridagi kredit axborotining davlat reestri;
A32: □ Kredit-axborot tahliliy markazi «O‘zbekiston Respublikasi kredit byurosi» MChJ;
A33: □ Garov reestri taqdim etilgan garov mulki haqida.
A34: ="Ariza berilgan sana: "&TEXT('Общие данные'!B2,"ДД.ММ.ГГГГ")&"y." -> Ariza berilgan sana: 03.04.2026y.
A36: Ariza berilgan kuniga barcha ma'lumotlar ishonchligini tasdiqlab, ushbu arizani imzolayman
A39: ='Общие данные'!B5 -> ANNAZAROV KAXRAMAN SADULLAYEVICH | D39: P________________
D40: (imzo)

Sheet Мажбуриятнома 
A3: MAJBURIYATNOMA
A4: =" Men, fuqaro "&'Общие данные'!B5&" "&'Общие данные'!B149&" bilan "&'Общие данные'!B69&" sanasidagi "&'Общие данные'!B66&"-sonli shartnomaning garov ta'minoti sifatida taqdim etilayotgan "&'Общие данные'!C125&" ko'chmas mulkni qonunga xilof ravishda o‘zlashtirmaslikka, yashirmaslikka, nobud qilmaslikka yoki unga shikast yetkazmaslik majburiyatini olaman." -> Men, fuqaro ANNAZAROV KAXRAMAN SADULLAYEVICH «PULLOL BUSINESS MIKROMOLIYA TASHKILOTI» MChJ bilan 3 aprel 2026 y. sanasidagi №310-TR-sonli shartnomaning garov ta'minoti sifatida taqdim etilayotgan Yakka tartibdagi uy-joy ko'chmas mulkni qonunga xilof ravishda o‘zlashtirmaslikka, yashirmaslikka, nobud qilmaslikka yoki unga shikast yetkazmaslik majburiyatini olaman.
A5: Ushbu majburiyatlarimni bajarmagan taqdirimda O'zbekiston Respublikasi jinoyat kodeksining 233-moddasi talablari asosida javobgarlik tog'risida ogohlantrildim.
A7: ='Общие данные'!B5 -> ANNAZAROV KAXRAMAN SADULLAYEVICH | B7: Imzo_____________
A9: ='Общие данные'!C105 -> 0 | B9: Imzo_____________
A11: ="sana: "&TEXT('Общие данные'!B2,"ДД.ММ.ГГГГ")&" y." -> sana: 03.04.2026 y.

Sheet Заключение КК
A1: =""&'Общие данные'!B147&" mikromoliya tashkilotining Xulosasi" -> «PULLOL BUSINESS MIKROMOLIYA TASHKILOTI» MChJ mikromoliya tashkilotining Xulosasi
A3: MIJOZ HAQIDA MA'LUMOTLAR
A4: ="Mijozning to'liq ismi sharifi: "&'Общие данные'!B5&"" -> Mijozning to'liq ismi sharifi: ANNAZAROV KAXRAMAN SADULLAYEVICH
A5: ="Tug'ilgan sanasi: "&'Общие данные'!B15&"" -> Tug'ilgan sanasi: 30.01.1973 y
A6: ="Pasport seriyasi "&'Общие данные'!B16&" "&'Общие данные'!B20&", amal qilish muddati - "&'Общие данные'!B21&"" -> Pasport seriyasi AD 2849628 IIV 35233 tomonidan 23.03.2023 yilda berilgan, amal qilish muddati - 22.03.2033 y.
A7: ="Ro‘yxatdan o‘tgan manzili: "&'Общие данные'!B28&", mo'ljal: "&'Общие данные'!B26&"" -> Ro‘yxatdan o‘tgan manzili: QORAQALPOG'ISTON RESPUBLIKASI TO'RTKO'L TUMANI YOSHLIK MFY KALTAMINAR KO'CHASI 1B-UY, mo'ljal: VISHKI TARAF GRAF METANNI YONIDA
A8: ="Ish joyi: "&'Общие данные'!B52&" lavozimi "&'Общие данные'!B49&"da "&'Общие данные'!B44&"" -> Ish joyi: lavozimi Сантехника ишлариda O'Z O'ZINI BAND QILGAN FUQARO
A10: ="Mijoz tomonidan so’ralgan "&'Общие данные'!B65&" shartlari:" -> Mijoz tomonidan so’ralgan Mikroqarz shartlari:
A11: ='Кредитная заявка'!A13 -> Mikroqarz summasi: 100 000 000,00 (Yuz million so'm) so'm.
A12: ='Кредитная заявка'!A14:D14 -> Mikroqarz muddati: 36 (Yigirma to'rt) oy.
A13: ='Кредитная заявка'!A15:D15 -> Mikroqarzdan foydalanganlik uchun foiz stavkasi: yillik 55% (Ellik besh ) foiz
A14: ='Кредитная заявка'!A16:D16 -> Mikroqarz bo'yicha asosiy qarz va foizlarni to'lash:
A15: ='Кредитная заявка'!A19:D19 -> - Mikroqarz shartnomasi bo'yicha har oy differensial to'lovlari amalga oshiriladi
A16: ='Кредитная заявка'!A20:D20
A17: ='Кредитная заявка'!A21:D21 -> Mikroqarz ta’minoti::
A18: ='Кредитная заявка'!A22:D22 -> Egalik huquqi ANNAZAROV KAXRAMAN SADULLAYEVICHga tegishli bo'lgan umumiy yer maydoni, (m2) - 704, qurilish osti maydoni - 149,81, umumiy foydali maydoni - 213,72 va yashash maydoni - 108,36 Yakka tartibdagi uy-joy, QORAQALPOG'ISTON RESPUBLIKASI TO'RTKO'L TUMANI YOSHLIK MFY KALTAMINAR KO'CHASI 1B-UY
A19: Mijozning moliyaviy holati
A20: ="Anketaga muvofiq "&'Общие данные'!B9&"ning o‘rtacha oylik daromadi "&FIXED('Анкета Клиента'!B27)&" so‘mni tashkil etdi." -> Anketaga muvofiq ANNAZAROV K.S.ning o‘rtacha oylik daromadi 21 000 000,00 so‘mni tashkil etdi.
A21: ="Mijozning o'rtacha oylik xarajatlari "&FIXED('Анкета Клиента'!F27)&" so'mni tashkil etdi" -> Mijozning o'rtacha oylik xarajatlari 1 800 000,00 so'mni tashkil etdi
A22: =IF('Общие данные'!B77='Общие данные'!C77,'Заключение КК'!A23:F23,'Заключение КК'!A24:F24) -> Mikrokredit shartnomasi bo'yicha birinchi oy uchun to'lov 7 599 695,54 so'mni tashkil etadi.
A23: =""&'Общие данные'!C64&" shartnomasi bo'yicha birinchi oy uchun to'lov "&FIXED('Общие данные'!B90)&" so'mni tashkil etadi." -> Mikrokredit shartnomasi bo'yicha birinchi oy uchun to'lov 7 599 695,54 so'mni tashkil etadi.
A24: =""&'Общие данные'!C64&" bo‘yicha oylik "&'Общие данные'!B77&" to‘lovi miqdori "&FIXED('Общие данные'!B90)&" so‘mni tashkil etadi." -> Mikrokredit bo‘yicha oylik differensial to‘lovi miqdori 7 599 695,54 so‘mni tashkil etadi.
A25: Mijoz quyidagi majburiyatlarga ega: "TOShKENT Sh., AT "XALQBАNKI" BOSh AMALIYOTLAR BOSHQARMASI 2 430 827.00 so'm, Ayni paytda muddati o'tgan qarzdorligi mavjud emas. O‘rtacha oylik to‘lov 2 430 827.00 so‘mni tashkil qiladi.
A26: =""&'Общие данные'!B65&" bo’yicha ta’minot:" -> Mikroqarz bo’yicha ta’minot:
A27: =" - "&'Общие данные'!B117&" ga mulk huquqi asosida tegishli avtotransport vositasi "&'Общие данные'!B125&" , quyidagi tafsilotlarga muvofiq:" -> - ANNAZAROV KAXRAMAN SADULLAYEVICH ga mulk huquqi asosida tegishli avtotransport vositasi , quyidagi tafsilotlarga muvofiq:
A28: =" - "&'Общие данные'!C117&" ga mulk huquqi asosida tegishli ko'chmas mulk shaklida "&'Общие данные'!C126&", manzili: "&'Общие данные'!C123&", quyidagi tafsilotlarga muvofiq:" -> - ANNAZAROV KAXRAMAN SADULLAYEVICH ga mulk huquqi asosida tegishli ko'chmas mulk shaklida Yakka tartibdagi uy-joy, manzili: QORAQALPOG'ISTON RESPUBLIKASI TO'RTKO'L TUMANI YOSHLIK MFY KALTAMINAR KO'CHASI 1B-UY, quyidagi tafsilotlarga muvofiq:
A29: =IF('Общие данные'!B103="Avtotransport",'Заключение КК'!A27:F27,'Заключение КК'!A28:F28) -> - ANNAZAROV KAXRAMAN SADULLAYEVICH ga mulk huquqi asosida tegishli ko'chmas mulk shaklida Yakka tartibdagi uy-joy, manzili: QORAQALPOG'ISTON RESPUBLIKASI TO'RTKO'L TUMANI YOSHLIK MFY KALTAMINAR KO'CHASI 1B-UY, quyidagi tafsilotlarga muvofiq:
A30: Nomi | B30: Umumiy yer maydoni, m² | C30: Qurilish osti maydoni, m² | D30: Yashash maydoni, m² | E30: Umumiy foydali maydoni, m² | F30: Kelishilgan garov qiymati, so'm
A31: ='Общие данные'!C125 -> Yakka tartibdagi uy-joy | B31: ='Общие данные'!C134 -> 704 | C31: ='Общие данные'!C133 -> 149.81 | D31: ='Общие данные'!C131 -> 108.36 | E31: ='Общие данные'!C130 -> 213.72 | F31: =""&FIXED('Общие данные'!B136)&" ("&'Общие данные'!B137&")" -> 140 000 000,00 (yuz qirq million so'm)
A32: ="-* avtotransport vositasining mulkdori: "&'Общие данные'!B117&"" -> -* avtotransport vositasining mulkdori: ANNAZAROV KAXRAMAN SADULLAYEVICH
A33: ="-* texpasport raqami:: "&'Общие данные'!B124&"" -> -* texpasport raqami::
A34: ="-* roʻyxatdan oʻtgan manzili/garaj manzili: "&'Общие данные'!B122&"" -> -* roʻyxatdan oʻtgan manzili/garaj manzili: QORAQALPOG'ISTON RESPUBLIKASI TO'RTKO'L TUMANI YOSHLIK MFY KALTAMINAR KO'CHASI 1B-UY
A35: ="-* davlat raqami: "&'Общие данные'!B126&"" -> -* davlat raqami:
A37: Nomi | C37: Yer uchastkasining foydalanish maydoni, m² | D37: Yashash maydoni, m² | E37: Umumiy maydoni, m² | F37: Kelishilgan garov qiymati, so'm
A38: ='Акт согласования'!A51 -> Yashash xona | C38: ='Акт согласования'!C51 -> 3 | D38: 18.82 | E38: 43.96 | F38: =""&FIXED('Общие данные'!C136,2)&" ("&'Общие данные'!C137&")" -> 140 000 000,00 (yuz qirq million so'm)
A39: ='Акт согласования'!A52 -> 0 | C39: ='Акт согласования'!C52 -> 0 | D39: ='Акт согласования'!D52 -> 0 | E39: ='Акт согласования'!E52 -> 0
A40: ='Акт согласования'!A53 -> Umumiy maydon | C40: 43.96 | D40: 18.82 | E40: 43.96
A41: ='Акт согласования'!A54 -> 0 | C41: ='Акт согласования'!C54 -> 0 | D41: ='Акт согласования'!D54 -> 0 | E41: ='Акт согласования'!E54 -> 0
A42: ='Акт согласования'!A55 -> 0 | C42: ='Акт согласования'!C55 -> 0 | D42: ='Акт согласования'!D55 -> 0 | E42: ='Акт согласования'!E55 -> 0
A43: ='Акт согласования'!A56 -> 0 | C43: ='Акт согласования'!C56 -> 0 | D43: ='Акт согласования'!D56 -> 0 | E43: ='Акт согласования'!E56 -> 0
A44: ='Акт согласования'!A57 -> 0 | C44: ='Акт согласования'!C57 -> 0 | D44: ='Акт согласования'!D57 -> 0 | E44: ='Акт согласования'!E57 -> 0
A45: ='Акт согласования'!A58 -> 0 | C45: ='Акт согласования'!C58 -> 0 | D45: ='Акт согласования'!D58 -> 0 | E45: ='Акт согласования'!E58 -> 0
A46: ='Акт согласования'!A59 -> 0 | C46: ='Акт согласования'!C59 -> 0 | D46: ='Акт согласования'!D59 -> 0 | E46: ='Акт согласования'!E59 -> 0
A47: ='Акт согласования'!A60 -> 0 | C47: ='Акт согласования'!C60 -> 0 | D47: ='Акт согласования'!D60 -> 0 | E47: ='Акт согласования'!E60 -> 0
A48: ='Акт согласования'!A61 -> 0 | C48: ='Акт согласования'!C61 -> 0 | D48: ='Акт согласования'!D61 -> 0 | E48: ='Акт согласования'!E61 -> 0
A49: ='Акт согласования'!A62 -> JAMI | C49: =C40 -> 43.96 | D49: =D38 -> 18.82 | E49: =E40 -> 43.96 | F49: ='Акт согласования'!F62 -> 140 000 000,00
A50: ="-* ko'chmas mulk egasi: "&'Общие данные'!C117&"" -> -* ko'chmas mulk egasi: ANNAZAROV KAXRAMAN SADULLAYEVICH
A51: ="-* reestr raqami: "&'Общие данные'!C124&"" -> -* reestr raqami: №1735233/Y-26004624
A52: ="-* kadastr raqami: "&'Общие данные'!C127&"" -> -* kadastr raqami: 01.04.2026 y. №23:08:40:01:04:0357
A53: ="-* manzili: "&'Общие данные'!C123&"" -> -* manzili: QORAQALPOG'ISTON RESPUBLIKASI TO'RTKO'L TUMANI YOSHLIK MFY KALTAMINAR KO'CHASI 1B-UY
A55: =""&'Общие данные'!B147&" mikromoliya tashkilotining Xulosasi" -> «PULLOL BUSINESS MIKROMOLIYA TASHKILOTI» MChJ mikromoliya tashkilotining Xulosasi
A56: =""&'Общие данные'!B147&" kredit qo‘mitasining xulosasiga quyidagi shartlarda "&'Общие данные'!B10&"ga "&'Общие данные'!B65&" berish masalasi kiritiladi:" -> «PULLOL BUSINESS MIKROMOLIYA TASHKILOTI» MChJ kredit qo‘mitasining xulosasiga quyidagi shartlarda ANNAZAROV KAXRAMAN SADULLAYEVICHga Mikroqarz berish masalasi kiritiladi:
A57: =A11 -> Mikroqarz summasi: 100 000 000,00 (Yuz million so'm) so'm.
A58: =A12 -> Mikroqarz muddati: 36 (Yigirma to'rt) oy.
A59: =A13 -> Mikroqarzdan foydalanganlik uchun foiz stavkasi: yillik 55% (Ellik besh ) foiz
A60: =A14 -> Mikroqarz bo'yicha asosiy qarz va foizlarni to'lash:
A61: =A15 -> - Mikroqarz shartnomasi bo'yicha har oy differensial to'lovlari amalga oshiriladi
A62: =A16
A63: =A17 -> Mikroqarz ta’minoti::
A64: =A18 -> Egalik huquqi ANNAZAROV KAXRAMAN SADULLAYEVICHga tegishli bo'lgan umumiy yer maydoni, (m2) - 704, qurilish osti maydoni - 149,81, umumiy foydali maydoni - 213,72 va yashash maydoni - 108,36 Yakka tartibdagi uy-joy, QORAQALPOG'ISTON RESPUBLIKASI TO'RTKO'L TUMANI YOSHLIK MFY KALTAMINAR KO'CHASI 1B-UY
A66: =""&'Общие данные'!B147&" mikromoliya tashkilotining xulosasi "&TEXT('Общие данные'!B2,"ДД.ММ.ГГГГ")&" y. tayyorlangan" -> «PULLOL BUSINESS MIKROMOLIYA TASHKILOTI» MChJ mikromoliya tashkilotining xulosasi 03.04.2026 y. tayyorlangan
A69: ='Общие данные'!A160 -> To'rtko'l filiali boshlig’i | F69: ='Общие данные'!B160 -> Djumanazarov B.A.
A71: =""&'Общие данные'!B147&" mikromoliya tashkilotining Kredit qo‘mitasi a’zolari "&'Общие данные'!B147&" mikromoliya tashkilotining xulosasi va Mijoz tomonidan taqdim etilgan ma’lumotlar bilan tanishdilar:" -> «PULLOL BUSINESS MIKROMOLIYA TASHKILOTI» MChJ mikromoliya tashkilotining Kredit qo‘mitasi a’zolari «PULLOL BUSINESS MIKROMOLIYA TASHKILOTI» MChJ mikromoliya tashkilotining xulosasi va Mijoz tomonidan taqdim etilgan ma’lumotlar bilan tanishdilar:
A73: ='Общие данные'!B150 -> Obidov A. Sh.
A75: ='Общие данные'!B160 -> Djumanazarov B.A.
A77: ='Общие данные'!B159 -> Akramov R.N.
A79: ='Общие данные'!B161 -> Eshbekov S.O.

Sheet договор
A1: =""&'Общие данные'!B65&" shartnoma "&'Общие данные'!B66&"" -> Mikroqarz shartnoma №310-TR
A3: ="Toshkent shahri "&'Общие данные'!B70&"" -> Toshkent shahri 3 aprel 2026 y.
A5: =""&'Общие данные'!B147&", bundan buyon «Mikromoliya tashkiloti» deb nomlanuvchi, ishonchnoma asosida xarakat qiluvchi "&'Общие данные'!A160&" "&'Общие данные'!B160&" bir tomondan va o‘z manfaati yo‘lida hamda o‘z nomidan harakat qiluvchi O‘zbekiston Respublikasi fuqarosi "&'Общие данные'!B5&" (pasport raqami "&'Общие данные'!B16&", "&'Общие данные'!C20&" ), bundan buyon «Qarz oluvchi» deb nomlanuvchi, boshqa tomondan, birgalikda “Tomonlar” yoki alohida “Tomon” deb nomlanuvchilar, Qarz oluvchi tomonidan "&TEXT('Общие данные'!B2,"ДД.ММ.ГГГГ")&" yil,"&'Общие данные'!B65&" olish uchun ariza berilganligini hisobga olib, ushbu "&'Общие данные'!B65&" shartnomasini (bundan keyin – «Shartnoma») quyidagilar haqida tuzdilar:" -> «PULLOL BUSINESS MIKROMOLIYA TASHKILOTI» MChJ, bundan buyon «Mikromoliya tashkiloti» deb nomlanuvchi, ishonchnoma asosida xarakat qiluvchi To'rtko'l filiali boshlig’i Djumanazarov B.A. bir tomondan va o‘z manfaati yo‘lida hamda o‘z nomidan harakat qiluvchi O‘zbekiston Respublikasi fuqarosi ANNAZAROV KAXRAMAN SADULLAYEVICH (pasport raqami AD 2849628, IIV 35233 tomonidan 23.03.2023 yilda berilgan ), bundan buyon «Qarz oluvchi» deb nomlanuvchi, boshqa tomondan, birgalikda “Tomonlar” yoki alohida “Tomon” deb nomlanuvchilar, Qarz oluvchi tomonidan 03.04.2026 yil,Mikroqarz olish uchun ariza berilganligini hisobga olib, ushbu Mikroqarz shartnomasini (bundan keyin – «Shartnoma») quyidagilar haqida tuzdilar:
A7: 1. SHARTNOMA PREDMETI
A8: ="1.1. Mikromoliya tashkiloti Qarz oluvchiga umumiy miqdori "&FIXED('Общие данные'!B75,2)&" ("&'Общие данные'!B76&") bo‘lgan "&'Общие данные'!B65&"ni "&'Общие данные'!B71&" dan "&'Общие данные'!B73&" gacha bo'lgan muddatga naqd pul va/yoki o'tkazmasi shaklida ajratadi." -> 1.1. Mikromoliya tashkiloti Qarz oluvchiga umumiy miqdori 100 000 000,00 (Yuz million so'm) bo‘lgan Mikroqarzni 3 aprel 2026 y. dan 3 aprel 2029 y. gacha bo'lgan muddatga naqd pul va/yoki o'tkazmasi shaklida ajratadi.
A9: ="1.2. Qarz oluvchi to‘lovlilik, muddatlilik va ta’minlanganlik tamoyillariga amal qilgan holda "&'Общие данные'!B65&"dan foydalanish majburiyatini o‘z zimmasiga oladi." -> 1.2. Qarz oluvchi to‘lovlilik, muddatlilik va ta’minlanganlik tamoyillariga amal qilgan holda Mikroqarzdan foydalanish majburiyatini o‘z zimmasiga oladi.
A11: ="2. "&'Общие данные'!D64&" BERISH VA QAYTARISH TARTIBI" -> 2. Mikroqarz BERISH VA QAYTARISH TARTIBI
A12: ="2.1. Ushbu Shartnomaning 1.1.-bandida ko‘rsatilgan summa miqdoridagi "&'Общие данные'!B65&" Mikromoliya tashkiloti kassasidan naqd pul shaklida va/yoki plastik kartaga o‘tkazish yuli bilan beriladi." -> 2.1. Ushbu Shartnomaning 1.1.-bandida ko‘rsatilgan summa miqdoridagi Mikroqarz Mikromoliya tashkiloti kassasidan naqd pul shaklida va/yoki plastik kartaga o‘tkazish yuli bilan beriladi.
A13: ="2.2. "&'Общие данные'!B65&" berish ushbu Shartnoma tuzilgan va Qarz oluvchi tomonidan ushbu shartnomaning 3-bo‘limiga muvofiq garov ta'minoti ta'minlangandan so‘ng 10 kalendar kundan kechiktirmay amalga oshiriladi." -> 2.2. Mikroqarz berish ushbu Shartnoma tuzilgan va Qarz oluvchi tomonidan ushbu shartnomaning 3-bo‘limiga muvofiq garov ta'minoti ta'minlangandan so‘ng 10 kalendar kundan kechiktirmay amalga oshiriladi.
A14: ="2.3. "&'Общие данные'!B65&" Qarz oluvchi tomonidan ushbu Shartnomaning ajralmas qismi hisoblanadigan 1-ilovasida ko‘rsatilgan to‘lov jadvalida (bundan keyin - To‘lov jadvali) belgilangan miqdor, tartib va muddatlarda qaytariladi." -> 2.3. Mikroqarz Qarz oluvchi tomonidan ushbu Shartnomaning ajralmas qismi hisoblanadigan 1-ilovasida ko‘rsatilgan to‘lov jadvalida (bundan keyin - To‘lov jadvali) belgilangan miqdor, tartib va muddatlarda qaytariladi.
A15: ="2.4. Mikromoliya tashkiloti, "&'Общие данные'!B65&" berilgan vaqtdan boshlab, "&'Общие данные'!B65&" miqdorining qoldiq summasiga "&'Общие данные'!B85&"% ("&'Общие данные'!C86&") foiz yillik va yiliga 365/366 kunlik hisobidan foizlar hisoblaydi. To'lov jadvaliga muvofiq asosiy qarz bo'yicha navbatdagi to'lov buzilgan hollarda, "&"foiz stavkasi oshiriladi va Mikromoliya tashkiloti "&'Общие данные'!B65&"ning muddati o'tgan asosiy qarz summasiga yillik "&'Общие данные'!B88&"% ("&'Общие данные'!B89&") foiz miqdorida foizlar hisoblaydi.__________" -> 2.4. Mikromoliya tashkiloti, Mikroqarz berilgan vaqtdan boshlab, Mikroqarz miqdorining qoldiq summasiga 55% (Ellik besh ) foiz yillik va yiliga 365/366 kunlik hisobidan foizlar hisoblaydi. To'lov jadvaliga muvofiq asosiy qarz bo'yicha navbatdagi to'lov buzilgan hollarda, foiz stavkasi oshiriladi va Mikromoliya tashkiloti Mikroqarzning muddati o'tgan asosiy qarz summasiga yillik 155% (bir yuz ellik besh) foiz miqdorida foizlar hisoblaydi.__________
A16: 2.4.1 Qarz oluvchining xisob raqamlaridan shartnomaning 4.1.2 bandida ko‘rsatilgan tartibda yechib olingan pul mablag‘lari yechib olinganidan so‘ng mijoz tomonidan kredit qarzdorligini so‘ndirish uchun bank kassalari orqali to‘langan pul mablag‘lari yoki mijoz tomonidan kredit qarzdorligini so‘ndirish uchun bank kassalari orqali to‘langandan so‘ng qarz oluvchining xisob raqamlaridan shartnomaning 4.1.2 bandida ko‘rsatilgan tartibda yechib olingan pul mablag‘larining bir oylik kredit to‘lovini so‘ndirishga yo‘naltirilgan miqdoridan ortiqcha qismi qarz oluvchining to‘lov amalga oshirilgan kundan boshlab 3 bank ish kuni ichida yo‘llagan arizasiga asosan qarz oluvchiga qaytarilishi mumkun. 2.5. Foizlar To‘lov jadvaliga muvofiq asosiy qarzni qaytarish uchun belgilangan sanada to‘lanadi. 2.5.1 Qarz oluvchi tomonidan shartnomaning 2.4 bandida ko‘rsatilgan muddatda ortiqcha to‘langan pul mablag‘larini qaytarish to‘g‘risida ariza berilmagan taqdirda to‘langan ortiqcha pul mablag‘lari mijozning asosiy qarzdorligini so‘ndirishga yo‘naltiriladi.
A17: =CONCATENATE(C17,H17,I17) -> 2.6 Qarz oluvchi tomonidan to‘lov jadvalida ko‘rsatilgan muddatdan oldin xamda to‘lov jadvalida ko‘rsatilgan oylik kredit qarzdorligini so‘ndirish miqdoridan ko‘p miqdorda to‘lovni amalga oshirib, to‘langan pul mablag‘larini asosiy kredit qarzdorligini so‘ndirishga yo‘naltirilishini so‘ralganda qarz oluvchining kredit qarzdorligini so‘ndirish uchun to‘lagan pul mablag‘laridan kredit qarzdorligi to‘langan oy uchun to‘lov jadvali bo‘yicha so‘ndirilishi lozim bo‘lgan foiz qarzdorligi summasi, to‘lov jadvalida foiz qarzdorligi so‘ndirilishi ko‘rsatilgan muddatga qadar tashkilotning xisob raqamida saqlanib to‘lov jadvalida ko‘rsatilgan sanada oylik foiz qarzdorligini so‘ndirishga yo‘naltiriladi. 2.6.1. Qarz oluvchi tomonidan olingan Mikroqarzni va undan foydalanganlik uchun foizlarni qaytarish bo‘yicha muddati o‘tgan qarzdorlik hosil bo‘lganda Qarz oluvchi tomonidan ko‘rsatilgan qarzdorlikni to‘lash hisobiga to‘lanadigan summalar quyidagi tartibda hisobga olinadi: | C17: 2.6 Qarz oluvchi tomonidan to‘lov jadvalida ko‘rsatilgan muddatdan oldin xamda to‘lov jadvalida ko‘rsatilgan oylik kredit qarzdorligini so‘ndirish miqdoridan ko‘p miqdorda to‘lovni amalga oshirib, to‘langan pul mablag‘larini asosiy kredit qarzdorligini so‘ndirishga yo‘naltirilishini so‘ralganda qarz oluvchining kredit qarzdorligini so‘ndirish uchun to‘lagan pul mablag‘laridan kredit qarzdorligi to‘langan oy uchun to‘lov jadvali bo‘yicha so‘ndirilishi lozim bo‘lgan foiz qarzdorligi summasi, to‘lov jadvalida foiz qarzdorligi so‘ndirilishi ko‘rsatilgan muddatga qadar tashkilotning xisob raqamida saqlanib to‘lov jadvalida ko‘rsatilgan sanada oylik foiz qarzdorligini so‘ndirishga yo‘naltiriladi. 2.6.1. Qarz oluvchi tomonidan olingan | H17: ='Общие данные'!B65 -> Mikroqarz | I17: ni va undan foydalanganlik uchun foizlarni qaytarish bo‘yicha muddati o‘tgan qarzdorlik hosil bo‘lganda Qarz oluvchi tomonidan ko‘rsatilgan qarzdorlikni to‘lash hisobiga to‘lanadigan summalar quyidagi tartibda hisobga olinadi:
A18: - jarima sanksiyalarni to‘lash; - to‘lov muddati o‘tgan foizlarni to‘lash; - to‘lov muddati o‘tgan asosiy qarzni to‘lash; - muddatli qarz bo‘yicha hisoblangan foizlarni to‘lash; - muddatli asosiy qarzni to‘lash; - Mikromoliya tashkilotning boshqa zararlarini qoplash.
A19: ="2.7. Qarz oluvchi Mikromoliya tashkilotining "&'Общие данные'!B65&" bo‘yicha asosiy summasi, hisoblangan foizlarni, penya va boshqa moliyaviy talablarini ham naqd pul shaklida, ham naqdsiz shaklda qaytarib beradi." -> 2.7. Qarz oluvchi Mikromoliya tashkilotining Mikroqarz bo‘yicha asosiy summasi, hisoblangan foizlarni, penya va boshqa moliyaviy talablarini ham naqd pul shaklida, ham naqdsiz shaklda qaytarib beradi.
A20: ="2.8. Qarz oluvchi "&'Общие данные'!B65&" miqdorini muddatidan oldin qaytarish, shuningdek, bu haqida Mikromoliya tashkilotini albatta ogohlantirgan holda ulardan aniq foydalangan muddat uchun hisoblangan foizlarni to‘lash huquqiga ega." -> 2.8. Qarz oluvchi Mikroqarz miqdorini muddatidan oldin qaytarish, shuningdek, bu haqida Mikromoliya tashkilotini albatta ogohlantirgan holda ulardan aniq foydalangan muddat uchun hisoblangan foizlarni to‘lash huquqiga ega.
A21: =CONCATENATE(C21,H21,I21) -> 2.9. Qarz oluvchi jismoniy shaxslarning kreditlar (Mikroqarzlar) bo‘yicha qarz yukini hisoblash tartibi, qarz yukining ruxsat etilgan miqdori, shuningdek qarz yuki o‘sishini cheklash to‘g‘risidagi Nizomga muvofiq (O’zbekiston Respublikasi Adliya vazirligi tomonidan 19.12.2019 y. 3205-son bilan ro‘yxatga olingan Markaziy bank Boshqaruvining 28.09.2019 y. 24/5-son qarori bilan tasdiqlangan), qarz yuki ko‘rsatkichi har bir qarz oluvchiga qarz beruvchi tomonidan Mikroqarz ajratishda uning summasi va qarz oluvchining amaldagi kredit (Mikroqarz) shartnomalari bo‘yicha asosiy qarz qoldig‘i yig‘indisi bazaviy hisoblash miqdorining 50 baravaridan oshganda hisoblanadi. | C21: ="2.9. Qarz oluvchi jismoniy shaxslarning kreditlar ("&'Общие данные'!B65&"lar) bo‘yicha qarz yukini hisoblash tartibi, qarz yukining ruxsat etilgan miqdori, shuningdek qarz yuki o‘sishini cheklash to‘g‘risidagi Nizomga muvofiq (O’zbekiston Respublikasi Adliya vazirligi tomonidan 19.12.2019 y. 3205-son bilan ro‘yxatga " -> 2.9. Qarz oluvchi jismoniy shaxslarning kreditlar (Mikroqarzlar) bo‘yicha qarz yukini hisoblash tartibi, qarz yukining ruxsat etilgan miqdori, shuningdek qarz yuki o‘sishini cheklash to‘g‘risidagi Nizomga muvofiq (O’zbekiston Respublikasi Adliya vazirligi tomonidan 19.12.2019 y. 3205-son bilan ro‘yxatga | H21: ="olingan Markaziy bank Boshqaruvining 28.09.2019 y. 24/5-son qarori bilan tasdiqlangan), qarz yuki ko‘rsatkichi har bir qarz oluvchiga qarz beruvchi tomonidan "&'Общие данные'!B65&" ajratishda uning summasi va " -> olingan Markaziy bank Boshqaruvining 28.09.2019 y. 24/5-son qarori bilan tasdiqlangan), qarz yuki ko‘rsatkichi har bir qarz oluvchiga qarz beruvchi tomonidan Mikroqarz ajratishda uning summasi va | I21: ="qarz oluvchining amaldagi kredit ("&'Общие данные'!B65&") shartnomalari bo‘yicha asosiy qarz qoldig‘i yig‘indisi bazaviy hisoblash miqdorining 50 baravaridan oshganda hisoblanadi." -> qarz oluvchining amaldagi kredit (Mikroqarz) shartnomalari bo‘yicha asosiy qarz qoldig‘i yig‘indisi bazaviy hisoblash miqdorining 50 baravaridan oshganda hisoblanadi.
A22: ="3. "&'Общие данные'!D64&" TA'MINOTI BO‘YICHA " -> 3. Mikroqarz TA'MINOTI BO‘YICHA
A23: ="3.1. Ushbu Shartnoma bo‘yicha taqdim etilgan "&'Общие данные'!B65&" quyidagi garov bilan ta'minlanadi:" -> 3.1. Ushbu Shartnoma bo‘yicha taqdim etilgan Mikroqarz quyidagi garov bilan ta'minlanadi:
A24: =IF('Общие данные'!B103='Общие данные'!C103,договор!A28,IF('Общие данные'!B103='Общие данные'!D103,договор!A25,0)) -> 3.1.1. Mikromoliya tashkiloti va Qarz oluvchi tomonidan 2026 yil 3 aprelda imzolangan 1-sonli Garov predmeti qiymatini tasdiqlash dalolatnomasiga muvofiq QORAQALPOG'ISTON RESPUBLIKASI TO'RTKO'L TUMANI YOSHLIK MFY KALTAMINAR KO'CHASI 1B-UY manzilida joylashgan, umumiy yer maydoni - 704, qurilish osti maydoni- 149,81, umumiy foydali maydoni - 213,72 yashash maydoni - 108,36 bo'lgan, Yakka tartibdagi turarjoy - ko'rinishidagi ko'chmas mulk (bundan keyin “Garov predmeti”), egalik huquqiga ko'ra ANNAZAROV KAXRAMAN SADULLAYEVICHga tegishli va kelishilgan garov qiymati 2026 yil 3 aprelda imzolangan 1-sonli Garov predmeti qiymatini tasdiqlash dalolatnomasiga muvofiq 140 000 000,00 (yuz qirq million so'm) so'mni tashkil qiladi. Garovning aniq shartlari tegishli tarzda notarial tasdiqlangan garov shartnomasi bilan belgilangan.
A25: =IF('Общие данные'!B92='Общие данные'!C92,договор!A27,IF('Общие данные'!B92='Общие данные'!D92,договор!A26,0)) -> 3.1.1. Mikromoliya tashkiloti va Qarz oluvchi tomonidan 2026 yil 3 aprelda imzolangan 1-sonli Garov predmeti qiymatini tasdiqlash dalolatnomasiga muvofiq QORAQALPOG'ISTON RESPUBLIKASI TO'RTKO'L TUMANI YOSHLIK MFY KALTAMINAR KO'CHASI 1B-UY manzilida joylashgan, umumiy yer maydoni - 704, qurilish osti maydoni- 149,81, umumiy foydali maydoni - 213,72 yashash maydoni - 108,36 bo'lgan, Yakka tartibdagi turarjoy - ko'rinishidagi ko'chmas mulk (bundan keyin “Garov predmeti”), egalik huquqiga ko'ra ANNAZAROV KAXRAMAN SADULLAYEVICHga tegishli va kelishilgan garov qiymati 2026 yil 3 aprelda imzolangan 1-sonli Garov predmeti qiymatini tasdiqlash dalolatnomasiga muvofiq 140 000 000,00 (yuz qirq million so'm) so'mni tashkil qiladi. Garovning aniq shartlari tegishli tarzda notarial tasdiqlangan garov shartnomasi bilan belgilangan.
A26: ="3.1.1. "&'Общие данные'!N126&" tomonidan "&'Общие данные'!B143&" yil "&'Общие данные'!B145&" "&'Общие данные'!B144&"da imzolangan 1-sonli navbatdagi garov predmeti qiymatini tasdiqlash dalolatnomasiga muvofiq "&'Общие данные'!C123&" manzilida joylashgan, "&'Общие данные'!E126&" bo'lgan, "&'Общие данные'!E125&" ko'rinishidagi ko'chmas mulk (bundan keyin “navbatdagi garov predmeti”), egalik huquqiga ko'ra "&'Общие данные'!C117&"ga tegishli va kelishilgan garov qiymati "&'Общие данные'!B143&" yil "&'Общие данные'!B145&" "&'Общие данные'!B144&"da imzolangan 1-sonli Garov predmeti qiymatini tasdiqlash dalolatnomasiga muvofiq "&FIXED('Общие данные'!B136,2)&" ("&'Общие данные'!B138&") so'mni tashkil qiladi. Garovning aniq shartlari tegishli tarzda notarial tasdiqlangan garov shartnomasi bilan belgilangan." -> 3.1.1. Mikromoliya tashkiloti va Qarz oluvchi tomonidan 2026 yil 3 aprelda imzolangan 1-sonli navbatdagi garov predmeti qiymatini tasdiqlash dalolatnomasiga muvofiq QORAQALPOG'ISTON RESPUBLIKASI TO'RTKO'L TUMANI YOSHLIK MFY KALTAMINAR KO'CHASI 1B-UY manzilida joylashgan, umumiy yer maydoni - 704, qurilish osti maydoni- 149,81, umumiy foydali maydoni - 213,72 yashash maydoni - 108,36 bo'lgan, Yakka tartibdagi turarjoy - ko'rinishidagi ko'chmas mulk (bundan keyin “navbatdagi garov predmeti”), egalik huquqiga ko'ra ANNAZAROV KAXRAMAN SADULLAYEVICHga tegishli va kelishilgan garov qiymati 2026 yil 3 aprelda imzolangan 1-sonli Garov predmeti qiymatini tasdiqlash dalolatnomasiga muvofiq 140 000 000,00 (yuz qirq million so'm) so'mni tashkil qiladi. Garovning aniq shartlari tegishli tarzda notarial tasdiqlangan garov shartnomasi bilan belgilangan.
A27: ="3.1.1. "&'Общие данные'!N126&" tomonidan "&'Общие данные'!B143&" yil "&'Общие данные'!B145&" "&'Общие данные'!B144&"da imzolangan 1-sonli Garov predmeti qiymatini tasdiqlash dalolatnomasiga muvofiq "&'Общие данные'!C123&" manzilida joylashgan, "&'Общие данные'!E126&" bo'lgan, "&'Общие данные'!E125&" ko'rinishidagi ko'chmas mulk (bundan keyin “Garov predmeti”), egalik huquqiga ko'ra "&'Общие данные'!C117&"ga tegishli va kelishilgan garov qiymati "&'Общие данные'!B143&" yil "&'Общие данные'!B145&" "&'Общие данные'!B144&"da imzolangan 1-sonli Garov predmeti qiymatini tasdiqlash dalolatnomasiga muvofiq "&FIXED('Общие данные'!B136,2)&" ("&'Общие данные'!B138&") so'mni tashkil qiladi. Garovning aniq shartlari tegishli tarzda notarial tasdiqlangan garov shartnomasi bilan belgilangan." -> 3.1.1. Mikromoliya tashkiloti va Qarz oluvchi tomonidan 2026 yil 3 aprelda imzolangan 1-sonli Garov predmeti qiymatini tasdiqlash dalolatnomasiga muvofiq QORAQALPOG'ISTON RESPUBLIKASI TO'RTKO'L TUMANI YOSHLIK MFY KALTAMINAR KO'CHASI 1B-UY manzilida joylashgan, umumiy yer maydoni - 704, qurilish osti maydoni- 149,81, umumiy foydali maydoni - 213,72 yashash maydoni - 108,36 bo'lgan, Yakka tartibdagi turarjoy - ko'rinishidagi ko'chmas mulk (bundan keyin “Garov predmeti”), egalik huquqiga ko'ra ANNAZAROV KAXRAMAN SADULLAYEVICHga tegishli va kelishilgan garov qiymati 2026 yil 3 aprelda imzolangan 1-sonli Garov predmeti qiymatini tasdiqlash dalolatnomasiga muvofiq 140 000 000,00 (yuz qirq million so'm) so'mni tashkil qiladi. Garovning aniq shartlari tegishli tarzda notarial tasdiqlangan garov shartnomasi bilan belgilangan.
A28: =IF('Общие данные'!B92='Общие данные'!C92,A29,IF('Общие данные'!B92='Общие данные'!D92,A30,0)) -> 3.1.1. Mikromoliya tashkiloti va Qarz oluvchi tomonidan 2026 yil 3 aprelda imzolangan 1-sonli garov predmeti qiymatini tasdiqlash dalolatnomasiga muvofiq rangli, ishlab chiqarilgan yili – yil, dvigatel raqami , shassi - , kuzov turi - , kuzov raqami №, davlat raqam belgisi bo'lgan rusumli avtomashinasi (bundan keyin “Garov predmeti”), egalik huquqiga ega ANNAZAROV KAXRAMAN SADULLAYEVICHga tegishli va kelishilgan garov qiymati 2026 yil 3 aprelda imzolangan 1-sonli Garov predmeti qiymatini tasdiqlash dalolatnomasiga muvifiq 140 000 000,00 (yuz qirq million so'm) so'mni tashkil qiladi. Garov garovining aniq shartlari tegishli notarial rasmiylashtirilgan garov shartnomasi bilan belgilanadi.
A29: ="3.1.1. "&'Общие данные'!N126&" tomonidan "&'Общие данные'!B143&" yil "&'Общие данные'!B145&" "&'Общие данные'!B144&"da imzolangan 1-sonli garov predmeti qiymatini tasdiqlash dalolatnomasiga muvofiq "&'Общие данные'!B134&" rangli, ishlab chiqarilgan yili – "&'Общие данные'!B135&" yil, dvigatel raqami "&'Общие данные'!B131&", shassi - "&'Общие данные'!B132&", kuzov turi - "&'Общие данные'!B128&", kuzov raqami №"&'Общие данные'!B129&", davlat raqam belgisi "&'Общие данные'!B126&" bo'lgan "&'Общие данные'!B125&" rusumli avtomashinasi (bundan keyin “Garov predmeti”), egalik huquqiga ega "&'Общие данные'!B117&"ga tegishli va kelishilgan garov qiymati "&'Общие данные'!B143&" yil "&'Общие данные'!B145&" "&'Общие данные'!B144&"da imzolangan 1-sonli Garov predmeti qiymatini tasdiqlash dalolatnomasiga muvifiq "&FIXED('Общие данные'!B136,2)&" ("&'Общие данные'!B138&") so'mni tashkil qiladi. Garov garovining aniq shartlari tegishli notarial rasmiylashtirilgan garov shartnomasi bilan belgilanadi." -> 3.1.1. Mikromoliya tashkiloti va Qarz oluvchi tomonidan 2026 yil 3 aprelda imzolangan 1-sonli garov predmeti qiymatini tasdiqlash dalolatnomasiga muvofiq rangli, ishlab chiqarilgan yili – yil, dvigatel raqami , shassi - , kuzov turi - , kuzov raqami №, davlat raqam belgisi bo'lgan rusumli avtomashinasi (bundan keyin “Garov predmeti”), egalik huquqiga ega ANNAZAROV KAXRAMAN SADULLAYEVICHga tegishli va kelishilgan garov qiymati 2026 yil 3 aprelda imzolangan 1-sonli Garov predmeti qiymatini tasdiqlash dalolatnomasiga muvifiq 140 000 000,00 (yuz qirq million so'm) so'mni tashkil qiladi. Garov garovining aniq shartlari tegishli notarial rasmiylashtirilgan garov shartnomasi bilan belgilanadi.
A30: ="3.1.1. "&'Общие данные'!N126&" tomonidan "&'Общие данные'!B143&" yil "&'Общие данные'!B145&" "&'Общие данные'!B144&"da imzolangan 1-sonli navbatdagi garov predmeti qiymatini tasdiqlash dalolatnomasiga muvofiq "&'Общие данные'!B134&" rangli, ishlab chiqarilgan yili – "&'Общие данные'!B135&" yil, dvigatel raqami "&'Общие данные'!B131&", shassi - "&'Общие данные'!B132&", kuzov turi - "&'Общие данные'!B128&", kuzov raqami №"&'Общие данные'!B129&", davlat raqam belgisi "&'Общие данные'!B126&" bo'lgan "&'Общие данные'!B125&" rusumli avtomashinasi (bundan keyin “navbatdagi garov predmeti”), egalik huquqiga ega "&'Общие данные'!B117&"ga tegishli va kelishilgan garov qiymati "&'Общие данные'!B143&" yil "&'Общие данные'!B145&" "&'Общие данные'!B144&"da imzolangan 1-sonli Garov predmeti qiymatini tasdiqlash dalolatnomasiga muvifiq "&FIXED('Общие данные'!B136,2)&" ("&'Общие данные'!B138&") so'mni tashkil qiladi. Garov garovining aniq shartlari tegishli notarial rasmiylashtirilgan garov shartnomasi bilan belgilanadi." -> 3.1.1. Mikromoliya tashkiloti va Qarz oluvchi tomonidan 2026 yil 3 aprelda imzolangan 1-sonli navbatdagi garov predmeti qiymatini tasdiqlash dalolatnomasiga muvofiq rangli, ishlab chiqarilgan yili – yil, dvigatel raqami , shassi - , kuzov turi - , kuzov raqami №, davlat raqam belgisi bo'lgan rusumli avtomashinasi (bundan keyin “navbatdagi garov predmeti”), egalik huquqiga ega ANNAZAROV KAXRAMAN SADULLAYEVICHga tegishli va kelishilgan garov qiymati 2026 yil 3 aprelda imzolangan 1-sonli Garov predmeti qiymatini tasdiqlash dalolatnomasiga muvifiq 140 000 000,00 (yuz qirq million so'm) so'mni tashkil qiladi. Garov garovining aniq shartlari tegishli notarial rasmiylashtirilgan garov shartnomasi bilan belgilanadi.
A31: =CONCATENATE(A32,B32) -> 3.2. Qonun hujjatlariga muvofiq rasmiylashtirilgan, “Garov predmeti” hisoblangan notarial tasdiqlangan garov shartnomasi, shu jumladan “Garov predmeti”ga taʼqiq quyilganligi tasdiqlovchi xujjat Qarz oluvchi tomonidan ushbu shartnoma tuzilgandan so‘ng 10 bank kuni mobaynida Mikromoliya tashkilotiga taqdim etilishi lozim. Garov shartnomasi belgilangan muddatda taqdim etilmagan hollarda, Mikromoliya tashkiloti Qarz oluvchining manziliga yozma bildirishnoma yuborish orqali Mikroqarz berishni rad etish va / yoki ushbu shartnomani bir tomonlama bekor qilish huquqiga egadir. Bunda ushbu shartnoma Qarz oluvchi tomonidan talabnoma olingan vaqtda yoki talabnoma pochta xizmati orqali yuborilgandan keyin uchinchi kuni bekor qilingan hisoblanadi.
A32: 3.2. Qonun hujjatlariga muvofiq rasmiylashtirilgan, “Garov predmeti” hisoblangan notarial tasdiqlangan garov shartnomasi, shu jumladan “Garov predmeti”ga taʼqiq quyilganligi tasdiqlovchi xujjat Qarz oluvchi tomonidan ushbu shartnoma tuzilgandan so‘ng 10 bank kuni mobaynida | B32: =CONCATENATE(A33,B33) -> Mikromoliya tashkilotiga taqdim etilishi lozim. Garov shartnomasi belgilangan muddatda taqdim etilmagan hollarda, Mikromoliya tashkiloti Qarz oluvchining manziliga yozma bildirishnoma yuborish orqali Mikroqarz berishni rad etish va / yoki ushbu shartnomani bir tomonlama bekor qilish huquqiga egadir. Bunda ushbu shartnoma Qarz oluvchi tomonidan talabnoma olingan vaqtda yoki talabnoma pochta xizmati orqali yuborilgandan keyin uchinchi kuni bekor qilingan hisoblanadi.
A33: =" Mikromoliya tashkilotiga taqdim etilishi lozim. Garov shartnomasi belgilangan muddatda taqdim etilmagan hollarda, Mikromoliya tashkiloti Qarz oluvchining manziliga yozma bildirishnoma yuborish orqali "&'Общие данные'!B65&"" -> Mikromoliya tashkilotiga taqdim etilishi lozim. Garov shartnomasi belgilangan muddatda taqdim etilmagan hollarda, Mikromoliya tashkiloti Qarz oluvchining manziliga yozma bildirishnoma yuborish orqali Mikroqarz | B33: berishni rad etish va / yoki ushbu shartnomani bir tomonlama bekor qilish huquqiga egadir. Bunda ushbu shartnoma Qarz oluvchi tomonidan talabnoma olingan vaqtda yoki talabnoma pochta xizmati orqali yuborilgandan keyin uchinchi kuni bekor qilingan hisoblanadi.
A34: 3.3. Asosiy qarzni, foizlar yoki ushbu shartnoma bo‘yicha belgilangan muddatdan kechiktirilganligi bo‘yicha penyalarni qaytarish muddati kechiktirilishi yuzaga kelganda va/yoki ushbu shartnoma bo‘yicha boshqa majburiyatlar buzilishi holatlarida Mikromoliya tashkiloti O‘zbekiston Respublikasining amaldagi qonunchiligiga muvofiq qarzni undirish uchun qaytarib olinmaydigan va muqarrar tartibda unidirishni garov ob'ektiga qaratish huquqiga ega bo‘ladi.
A35: 3.4. O‘zbekiston Respublikasi "Garov to‘g‘risida" gi Qonunining 27-moddasiga muvofiq Garov predmeti sug‘urtalanmaydi. Lekin Mikromoliya tashkiloti Qarz oluvchidan Mikromoliya tashkiloti foydasiga Garov obʼektini ushbu Shartnomaning to‘liq amal qilish muddatiga har turli xavflardan sug‘urta qilishni talab qilish huquqiga ega. Bunda, sug‘urta xavflari ro‘yxati, shuningdek, sug‘urta kompaniyasi Mikromoliya tashkilotining xohishiga ko‘ra belgilanadi. Sug‘urta hodisasi yuz berganda Foyda oluvchi Mikromoliya tashkiloti bo‘lishi kerak.
A37: 4. MIKROMOLIYA TASHKILOTINING HUQUQ VA MAJBURIYATLARI
A38: 4.1. Mikromoliya tashkiloti quyidagi huquqlarga ega:
A39: =CONCATENATE(C39,H39) -> 4.1.1. Ushbu Shartnomada ko‘rsatilgan asoslar bo‘yicha Qarz oluvchiga Shartnomada ko‘zda tutilgan Mikroqarz summasini berilishini to‘liq yoki qisman rad etish. 4.1.2 “Mikromoliya Tashkiloti” qarz oluvchining nomidagi barcha plastik kartalaridan, xozirgi kunda mavjud va bundan so‘ng ochiladigan barcha xisob raqamlaridan (talab qilib olguncha, depozit jamg‘arib boriladigan plastik va boshqa istalgan xisob raqamlaridan) kredit to‘lovini kredit qaytarish jadvaliga asosan oyning kredit qarzdorligi qaytarilishi ko‘rsatilgan kuni akseptsiz tarzda yechib olish xuquqiga ega.____________ | C39: ="4.1.1. Ushbu Shartnomada ko‘rsatilgan asoslar bo‘yicha Qarz oluvchiga Shartnomada ko‘zda tutilgan "&'Общие данные'!B65&"" -> 4.1.1. Ushbu Shartnomada ko‘rsatilgan asoslar bo‘yicha Qarz oluvchiga Shartnomada ko‘zda tutilgan Mikroqarz | H39: summasini berilishini to‘liq yoki qisman rad etish. 4.1.2 “Mikromoliya Tashkiloti” qarz oluvchining nomidagi barcha plastik kartalaridan, xozirgi kunda mavjud va bundan so‘ng ochiladigan barcha xisob raqamlaridan (talab qilib olguncha, depozit jamg‘arib boriladigan plastik va boshqa istalgan xisob raqamlaridan) kredit to‘lovini kredit qaytarish jadvaliga asosan oyning kredit qarzdorligi qaytarilishi ko‘rsatilgan kuni akseptsiz tarzda yechib olish xuquqiga ega.____________
A40: ="4.1.2.1. "&'Общие данные'!C64&" bo‘yicha qolgan barcha qarzdorlik, foiz to‘lovlarining muddatidan oldin qaytarilishini talab qilish, shuningdek, quyidagi holatlardan biri yuzaga kelganda undirishni garov ta'minotiga qaratish:" -> 4.1.2.1. Mikrokredit bo‘yicha qolgan barcha qarzdorlik, foiz to‘lovlarining muddatidan oldin qaytarilishini talab qilish, shuningdek, quyidagi holatlardan biri yuzaga kelganda undirishni garov ta'minotiga qaratish:
A41: a) ta'minotisiz qarzdorlik yuzaga kelganda;
A42: ="b) "&'Общие данные'!B65&" summasiga hisoblanadigan asosiy qarz bo‘yicha muddati o‘tgan qarzdorlik va/yoki foizlarning yuzaga kelishi;" -> b) Mikroqarz summasiga hisoblanadigan asosiy qarz bo‘yicha muddati o‘tgan qarzdorlik va/yoki foizlarning yuzaga kelishi;
A43: с) Qarz oluvchini qonun hujjatlarida belgilangan tartibda to‘lov qobiliyatiga ega emas, muomalaga layoqatli emas yoki muomalaga layoqati cheklangan deb e'lon qilish;
A44: d) Mikromoliya tashkilotiga ushbu Shartnomaning 3.1.-bandida ko‘zda tutilgan hisobotlar, axborotlar va boshqa ma'lumotlarni o‘z vaqtida taqdim etmaslik, shuningdek, moliya-xo‘jalik faoliyat va daromad to‘g‘risidagi hisobotning ishonchsizligi holatlari aniqlanganda;
A45: e) Qarz oluvchi tomonidan ushbu shartnoma shartlariga amal qilmaslik;
A46: ="f) Qarz oluvchi "&'Общие данные'!B65&" summasini olish uchun Mikromoliya tashkilotiga "&'Общие данные'!B65&" taqdim etilishi to‘g‘risida ijobiy qaror qabul qilinishi uchun muhim hisoblangan masalalar bo‘yicha yolg‘on yoki to‘liq bo‘lmagan ma'lumotlarni taqdim etganligi aniqlanganda." -> f) Qarz oluvchi Mikroqarz summasini olish uchun Mikromoliya tashkilotiga Mikroqarz taqdim etilishi to‘g‘risida ijobiy qaror qabul qilinishi uchun muhim hisoblangan masalalar bo‘yicha yolg‘on yoki to‘liq bo‘lmagan ma'lumotlarni taqdim etganligi aniqlanganda.
A47: 4.1.3. Ushbu shartnomaning amal qilish jarayonida Qarz oluvchining moliyaviy holatini tekshirish va Qarz oluvchi tomonidan o‘z zimmasiga olgan majburiyatlarning bajarilishini nazorat qilish.
A48: 4.1.4. Qarz oluvchi tomonidan yoki ushbu Shartnoma bo‘yicha uchinchi shaxs tomonidan ta'minot sifatida garovga qo‘yilgan mol-mulkning tegishli holatdaligi va ulardan foydalanish bo‘yicha tekshiruvlar o‘tkazish.
A49: 4.1.5. Garovga qo‘yuvchi tomonidan garovga qo‘yilgan mol-mulk buzilgan yoki belgilangan maqsadda foydalanish uchun yaroqsiz holga kelganda, bu esa Mikromoliya tashkilotining ushbu Shartnoma bo‘yicha moliyaviy talablarini qondirishga qodir bo‘lgan bozor qiymatiga ma'lum darajada ta'sir ko‘rsatganda, yoki uchinchi shaxsning (kafil) moliyaviy holatining yomonlashuvi sababli ushbu Shartnomadan kelib chiqqan majburiyatlar bo‘yicha javob berish qobiliyatiga ega bo‘lmay qolgan holatlarda Qarz oluvchidan ta'minotning qo‘shimcha turini taqdim etish yoki almashtirishni talab qilish.
A50: 4.1.6. Qonun hujjatlariga muvofiq, Qarz oluvchi tomonidan ushbu Shartnoma bo‘yicha asosiy qarz, foizlar, penya va boshqa pul majburiyatlarini o‘z vaqtida to‘lamaslik holatlarida Qarz oluvchining bank hisobvaraqlaridagi pul mablag‘larini akseptsiz tartibda yechib olish to‘g‘risida to‘lov talabnomasini berish va bunga Qarz oluvchi qaytarib olinmaydigan va so‘zsiz rozilik bildiradi.
A51: ="4.1.7. Qarz oluvchini oldindan ogohlantirmasdan "&'Общие данные'!B65&"ni qaytarish uchun haqiqatdan ham garov ta'minoti mavjudligini tekshirishni amalga oshirish." -> 4.1.7. Qarz oluvchini oldindan ogohlantirmasdan Mikroqarzni qaytarish uchun haqiqatdan ham garov ta'minoti mavjudligini tekshirishni amalga oshirish.
A52: 4.1.8. Ushbu shartnoma doirasida o‘z majburiyatlarini bajarish uchun uchinchi shaxslarga barcha zarur ma'lumotlarni yetkazish.
A53: 4.1.9. Istalgan vaqtda Qarz oluvchining avvaldan roziligini olmasdan turib ushbu Shartnoma bo‘yicha uchinchi tomonga da'vo qilish huquqini berish yoki uning foydasiga voz kechish.
A54: =CONCATENATE(C54,H54) -> 4.1.10. Qarz oluvchi taqdim etilgan Mikroqarzdan Shartnoma tuzilgan kundan boshlab 1 (bir) oy davomida foydalanmagan holatlarda, bu haqda Qarz oluvchini yozma ravishda xabardor qilib, Shartnoma bir tomonlama bekor qilish. Yozma xabarni jo‘natish sanasi uni taqdim etish yoki pochta orqali jo‘natish sanasi hisoblanadi. | C54: ="4.1.10. Qarz oluvchi taqdim etilgan "&'Общие данные'!B65&"dan Shartnoma tuzilgan kundan boshlab 1 (bir) oy davomida foydalanmagan" -> 4.1.10. Qarz oluvchi taqdim etilgan Mikroqarzdan Shartnoma tuzilgan kundan boshlab 1 (bir) oy davomida foydalanmagan | H54: holatlarda, bu haqda Qarz oluvchini yozma ravishda xabardor qilib, Shartnoma bir tomonlama bekor qilish. Yozma xabarni jo‘natish sanasi uni taqdim etish yoki pochta orqali jo‘natish sanasi hisoblanadi.
A55: ="4.1.11. Oldingi "&'Общие данные'!B65&" to‘liq to‘lanmagunga qadar yangi "&'Общие данные'!B65&" berishni rad etish." -> 4.1.11. Oldingi Mikroqarz to‘liq to‘lanmagunga qadar yangi Mikroqarz berishni rad etish.
A57: 5. QARZ OLUVCHINING HUQUQ VA MAJBURIYATLARI
A58: 5.1. Qarz oluvchi quyidagi huquqlarga ega:
A59: ="5.1.1. Ushbu shartnomada nazarda tutilgan shartlar bo‘yicha "&'Общие данные'!B65&" olish, shuningdek, Mikromoliya tashkiloti tomonidan ko‘rsatiladigan pullik xizmatlardan foydalanish." -> 5.1.1. Ushbu shartnomada nazarda tutilgan shartlar bo‘yicha Mikroqarz olish, shuningdek, Mikromoliya tashkiloti tomonidan ko‘rsatiladigan pullik xizmatlardan foydalanish.
A60: ="5.1.2. Shartnoma tuzilgan kundan boshlab 2 (ikki) hafta mobaynida Mikromoliya tashkilotiga bu haqda yozma xabarnoma yo‘llash orqali "&'Общие данные'!B65&"ning foydalanilmagan summasidan voz kechish." -> 5.1.2. Shartnoma tuzilgan kundan boshlab 2 (ikki) hafta mobaynida Mikromoliya tashkilotiga bu haqda yozma xabarnoma yo‘llash orqali Mikroqarzning foydalanilmagan summasidan voz kechish.
A61: ="5.1.3. "&'Общие данные'!C64&" xizmatlari ko‘rsatish qoidalari bilan tanishish." -> 5.1.3. Mikrokredit xizmatlari ko‘rsatish qoidalari bilan tanishish.
A62: ="5.1.4. O‘z huquq va majburiyatlari, shu jumladan "&'Общие данные'!B65&" xizmatlari ko‘rsatish bilan bog‘liq barcha xarajatlar haqida aniq va to‘liq ma'lumot olish." -> 5.1.4. O‘z huquq va majburiyatlari, shu jumladan Mikroqarz xizmatlari ko‘rsatish bilan bog‘liq barcha xarajatlar haqida aniq va to‘liq ma'lumot olish.
A63: 5.1.5. Shartnoma bo‘yicha Mikromoliya tashkilotining majburiyatlarini bajarmaslik yoki tegishli darajada bajarmaslik natijasida yuzaga kelgan zararlarni qoplashni talab qilish.
A64: 5.2. Qarz oluvchining majburiyatlari:
A65: ="5.2.1. Mikromoliya tashkilotining birinchi talabi bilan zarur hujjatlar, shuningdek "&'Общие данные'!B65&"dan foydalanishning butun davri davomida uning moliyaviy holati va to‘lash qobiliyatiga tegishli bo‘lgan ma'lumotlarni taqdim etish." -> 5.2.1. Mikromoliya tashkilotining birinchi talabi bilan zarur hujjatlar, shuningdek Mikroqarzdan foydalanishning butun davri davomida uning moliyaviy holati va to‘lash qobiliyatiga tegishli bo‘lgan ma'lumotlarni taqdim etish.
A66: 5.2.2. Ushbu shartnomada nazarda tutilgan hollarda garov ta'minotini almashtirish yoki qo‘shimcha ta'minot turini taqdim etish bo‘yicha Mikromoliya tashkiloti talablarini bajarish.
A67: ="5.2.3. To‘lov jadvaliga muvofiq "&'Общие данные'!B65&", shuningdek hisoblangan foizlar to‘lovlarini amalga oshirish." -> 5.2.3. To‘lov jadvaliga muvofiq Mikroqarz, shuningdek hisoblangan foizlar to‘lovlarini amalga oshirish.
A68: =CONCATENATE(C68,H68) -> 5.2.4. Mikromoliya tashkiloti vakillariga o‘zlarining moliyaviy holati, yashash joyini tekshirishga, Mikromoliya tashkiloti foydasiga garovga qo‘yilgan mol-mulk saqlanishini tekshirishga ruxsat berish, shuningdek Qarz oluvchi ob'ektlaridan istalganiga tashrif buyurish va har qanday bino, inshoot, mol-mulk, asbob-uskunalar, tovarlar va xizmatlar, shuningdek ularning Mikroqarz mablag‘lari hisobiga moliyalashtirilgan hujjatlarni ko‘zdan kechirish va Mikromoliya tashkiloti tomonidan ushbu huquqni amalga oshirishga to‘sqinlik qilmaslik majburiyatini oladi. | C68: 5.2.4. Mikromoliya tashkiloti vakillariga o‘zlarining moliyaviy holati, yashash joyini tekshirishga, Mikromoliya tashkiloti foydasiga garovga qo‘yilgan mol-mulk saqlanishini tekshirishga ruxsat berish, shuningdek Qarz oluvchi ob'ektlaridan istalganiga tashrif buyurish va har qanday bino, inshoot, mol-mulk, asbob-uskunalar, tovarlar va xizmatlar, shuningdek ularning | H68: =" "&'Общие данные'!B65&" mablag‘lari hisobiga moliyalashtirilgan hujjatlarni ko‘zdan kechirish va Mikromoliya tashkiloti tomonidan ushbu huquqni amalga oshirishga to‘sqinlik qilmaslik majburiyatini oladi." -> Mikroqarz mablag‘lari hisobiga moliyalashtirilgan hujjatlarni ko‘zdan kechirish va Mikromoliya tashkiloti tomonidan ushbu huquqni amalga oshirishga to‘sqinlik qilmaslik majburiyatini oladi.
A69: 5.2.5. Qarz oluvchining moliyaviy ahvoli yomonlashuvi va ushbu shartnoma bo‘yicha Qarz oluvchining Mikromoliya tashkiloti oldidagi majburiyatlarining bajarilmasligi va/yoki tegishli darajada bajarilmaslik xavfi yuzaga kelishiga olib keluvchi hech qanday majburiyat va choralarni o‘z zimmasiga olmaslik;
A70: ="5.2.6. Quyidagi holatlarda Mikromoliya tashkilotning birinchi talabi bilan "&'Общие данные'!B65&" qaytarilishi bo‘yicha qo‘shimcha garov ta'minotini taqdim etish: " -> 5.2.6. Quyidagi holatlarda Mikromoliya tashkilotning birinchi talabi bilan Mikroqarz qaytarilishi bo‘yicha qo‘shimcha garov ta'minotini taqdim etish:
A71: - Qarz oluvchining moliyaviy holatining yomonlashuvi; - Garov ob'ekti va/yoki uning bir qismining yo‘q qilinishi, qiymatining pasayishi, qisman yoki to‘liq yo‘qotilishi; - qarz qaytarilmaslik xavfini ko‘paytiruvchi boshqa omillarning paydo bo‘lishi;
A72: ="5.2.7. Sud qarori asosida Qarz oluvchi – jismoniy shaxsning muomalaga layoqatsizligi yoki muomalaga layoqati cheklangan yoxud to‘lash qobiliyatiga ega emasligi (bankrotligi) tan olinganda, uning vasiysi yoki homiysi "&'Общие данные'!B65&"ning asosiy summa bo‘yicha qarzdorlikni "&'Общие данные'!B65&"dan aniq foydalanish muddati uchun foizlar bilan kechiktirmasdan to‘liq to‘lashi shart." -> 5.2.7. Sud qarori asosida Qarz oluvchi – jismoniy shaxsning muomalaga layoqatsizligi yoki muomalaga layoqati cheklangan yoxud to‘lash qobiliyatiga ega emasligi (bankrotligi) tan olinganda, uning vasiysi yoki homiysi Mikroqarzning asosiy summa bo‘yicha qarzdorlikni Mikroqarzdan aniq foydalanish muddati uchun foizlar bilan kechiktirmasdan to‘liq to‘lashi shart.
A73: ="5.2.8. Mikromoliya tashkilotining "&'Общие данные'!B65&" umumiy summasi va hisoblangan foizlarni muddatidan oldin qaytarish to‘g‘risidagi talabini kechiktirmasdan bajarish." -> 5.2.8. Mikromoliya tashkilotining Mikroqarz umumiy summasi va hisoblangan foizlarni muddatidan oldin qaytarish to‘g‘risidagi talabini kechiktirmasdan bajarish. | H73: "&'Общие данные'!B59&"
A74: =CONCATENATE(C74,H74) -> 5.2.9. Mikromoliya tashkilotining talabi bo‘yicha Mikromoliya tashkiloti ko‘rgan, shu jumladan Mikroqarz bo‘yicha (asosiy qarz, foizlar va boshqalar) qarzdorlikni majburiy va/yoki muddatidan oldin qaytarish bo‘yicha qabul qilingan choralar bilan bog‘liq bo‘lgan barcha xarajatlari va zararlarni qoplash, shuningdek ushbu shartnoma doirasida unidruvni taqdim etilgan garov ta'minotiga qaratish. | C74: ="5.2.9. Mikromoliya tashkilotining talabi bo‘yicha Mikromoliya tashkiloti ko‘rgan, shu jumladan "&'Общие данные'!B65&" bo‘yicha (asosiy qarz, foizlar va boshqalar)" -> 5.2.9. Mikromoliya tashkilotining talabi bo‘yicha Mikromoliya tashkiloti ko‘rgan, shu jumladan Mikroqarz bo‘yicha (asosiy qarz, foizlar va boshqalar) | H74: qarzdorlikni majburiy va/yoki muddatidan oldin qaytarish bo‘yicha qabul qilingan choralar bilan bog‘liq bo‘lgan barcha xarajatlari va zararlarni qoplash, shuningdek ushbu shartnoma doirasida unidruvni taqdim etilgan garov ta'minotiga qaratish.
A76: 6. TOMONLARNING JAVOBGARLIGI
A77: =CONCATENATE(C77,H77) -> 6.1. Mikromoliya tashkiloti tomonidan Qarz oluvchiga pul mablag‘larini ajratib berish bo‘yicha o‘z zimmasiga olgan majburiyatlarning Shartnomaning 1.1.-bandida keltirilgan summa va muddatlarda bajarilmaslik yoki tegishli tarzda bajarilmaslik holatlarida Mikromoliya tashkiloti muddatidan o‘tgan har bir kalendar kun uchun kechiktirilgan to‘lov summasining 0,1% miqdorida, biroq ushbu Shartnomaning 1.1.-bandida ko‘rsatilgan Mikroqarz miqdori umumiy summasining 50% dan ko‘p bo‘lmagan miqdorda penya ko‘rinishidagi neustoyka to‘lash majburiyatini o‘z zimmasiga oladi. | C77: 6.1. Mikromoliya tashkiloti tomonidan Qarz oluvchiga pul mablag‘larini ajratib berish bo‘yicha o‘z zimmasiga olgan majburiyatlarning Shartnomaning 1.1.-bandida keltirilgan summa va muddatlarda bajarilmaslik yoki tegishli tarzda bajarilmaslik holatlarida Mikromoliya tashkiloti muddatidan o‘tgan har bir kalendar kun uchun kechiktirilgan to‘lov summasining 0,1% miqdorida, biroq ushbu Shartnomaning 1.1.-bandida ko‘rsatilgan | H77: =""&'Общие данные'!B65&" miqdori umumiy summasining 50% dan ko‘p bo‘lmagan miqdorda penya ko‘rinishidagi neustoyka to‘lash majburiyatini o‘z zimmasiga oladi." -> Mikroqarz miqdori umumiy summasining 50% dan ko‘p bo‘lmagan miqdorda penya ko‘rinishidagi neustoyka to‘lash majburiyatini o‘z zimmasiga oladi.
A78: 6.2. Jarima sanksiyalarni to‘lash Tomonlarni ushbu Shartnomada ko‘zda tutilgan zimmalaridagi majburiyatlarini bajarishdan ozod qilmaydi.
A79: 6.3. Tomonlarning ushbu Shartnomada nazarda tutilmagan javobgarligi O‘zbekiston Respublikasining amaldagi qonunchiligiga muvofiq belgilanadi.
A80: 6.4. Tomonlar O‘zbekiston Respublikasi Fuqarolik kodeksining 325-moddasiga muvofiq aybdor tomondan yetkazilgan zararni neustoykadan tashqari to‘la hajmda undirish huquqiga egadirlar.
A82: 7. FORS-MAJOR
A83: 7.1. Agar Tomonlar ular zimmasidagi majburiyatlarni tegishli darajada bajarishi yengib bo‘lmas kuch (fors-major) oqibatida mumkin bo‘lmay qolgan bo‘lsa, ya'ni aniq vaqt davri davomida aniq sharoitlarda favqulodda va oldini olib bo‘lmaydigan holatlar ekanligini isbotlay olmasalar, Shartnoma bo‘yicha o‘z majburiyatlarini bajarmagan yoki tegishli darajada bajarmagan Tomon uning shartlarini bajarishda javobgar hisoblanadi. Ushbu Shartnoma Tomonlari yengilmas kuch holatlariga quyidagilarni kiritadi: tabiiy ofat (zilzila, suv toshqini, chaqmoq chaqishi, vulqon otilishi, sel kelishi, ko‘chki, sunami va hokazo), Shartnoma bo‘yicha majburiyatlar bajarilish joyida temperatura – harorat, shamol kuchi va yog‘ingarchilik darajasining inson hayotiy faoliyati normasidan ortiq bo‘lishi; hokimiyat va boshqaruv organlari moratoriysi; qonuniy belgilangan tartibda tashkil etilgan ish tashlashlar va majburiyatlarning tegishli darajada bajarilishi uchun Shartnoma Tomonlari tarafidan yengib bo‘lmas kuch sifatida belgilangan boshqa holatlar.
A84: 7.2. Fors-major holati ta'sirida qolgan Tomon, bunday holatlar yuzaga kelgan kundan boshlab 7 (etti) kalendar kundan kechiktirmasdan boshqa Tomonni xabardor qilishi shart.
A85: 7.3. Fors-major holati boshlanganligi to‘g‘risida xabar qilmaslik yoki o‘z vaqtida xabar bermaslik fors-major holati boshlanganda Shartnoma bo‘yicha o‘z majburiyatlarini bajarish imkoniyatiga vaj qilib keltirish huquqiga ega emas.
A86: 7.4. Fors-major holati boshlanganligini vaj qilib ko‘rsatish huquqidan mahrum etilgan Tomon amaldagi qonun hujjatlariga muvofiq javobgar bo‘ladi.
A88: 8. NIZOLARNI HAL QILISH TARTIBI
A89: 8.1. Ushbu Shartnomadan kelib chiqadigan tomonlar o‘rtasidagi barcha nizolar va undan kelib chiqadigan majburiyatlar, shu jumladan shartnoma bajarilmasligi oqibatida yuzaga kelgan bajarilishi, o‘zgartirilishi, bekor qilinishi, tugatilishi Mikromoliya tashkilot joylashgan yerdagi taalluqli sudda yoki «CONSILIO» Mas'uliyati cheklangan jamiyat qoshidagi Hakamlik sudida, O‘zbekiston Respublikasining amaldagi qonun hujjatlari va uning reglamentiga muvofiq Hakamlik sudi raisi tomonidan tayinlangan, yakka tartibdagi hakamlik sudyasi tomonidan, sud ishlarini sud majlisi bayonnomasi tuzmasdan ko‘rib chiqilishi kerak bo‘ladi. U yoki bu sudga murojaat qilish huquqi da'vogarda qoladi.
A90: Qarzni undirish va garovdagi mol-mulkiga qaratish ham sud tartibida, ham suddan tashqari tartibda, shu jumladan notariusning ijro yozuvini olish yo‘li bilan amalga oshirilishi mumkin.
A91: ="8.2. Mikromoliya tashkiloti sud organlariga murojaat qilganidan keyin Qarz oluvchi tomonidan "&'Общие данные'!B65&" bo‘yicha muddati o‘tgan qarzdorlikning to‘lanishi Mikromoliya tashkilotning "&'Общие данные'!B65&" bo‘yicha qarzdorlikni muddatidan avval undirish, shu jumladan undiruvni garovdagi mol-mulkka qaratish yo‘li bilan undirish huquqidan mahrum qilmaydi." -> 8.2. Mikromoliya tashkiloti sud organlariga murojaat qilganidan keyin Qarz oluvchi tomonidan Mikroqarz bo‘yicha muddati o‘tgan qarzdorlikning to‘lanishi Mikromoliya tashkilotning Mikroqarz bo‘yicha qarzdorlikni muddatidan avval undirish, shu jumladan undiruvni garovdagi mol-mulkka qaratish yo‘li bilan undirish huquqidan mahrum qilmaydi.
A93: 9. SHARTNOMA SHARTLARI VA AMAL QILISH MUDDATI
A94: 9.1. Ushbu Shartnoma Tomonlar tarafidan imzolangandan keyin kuchga kiradi.
A95: ="9.2. Shartnomaning amal qilish muddati Qarz oluvchi "&'Общие данные'!B65&"ni to‘liq qaytargan, hisoblangan foizlar, penya va boshqa pul majburiyatlarini to‘lagan kunda yakunlanadi." -> 9.2. Shartnomaning amal qilish muddati Qarz oluvchi Mikroqarzni to‘liq qaytargan, hisoblangan foizlar, penya va boshqa pul majburiyatlarini to‘lagan kunda yakunlanadi.
A96: 9.3. Ushbu Shartnomaga kiritiladigan barcha o‘zgartirish va qo‘shimchalar, ushbu Shartnomada kelishilgan holatlardan tashqari, ikkala Tomon tarafidan qo‘shimcha bitimni yozma shaklda imzolagan holda amalga oshiriladi.
A98: 10. SHAXSIY MA'LUMOTLARNI QAYTA ISHLASH
A99: 10.1. Ushbu shartnomani tuzish bilan, Qarz oluvchi Mikromoliya tashkilotiga uning shaxsiy ma'lumotlari, shu jumladan, familiyasi, ismi, otasining ismi, pasport ma'lumotlari (shu jumladan, pasport raqami, berilgan vaqti va sanasi, ro‘yxatdan o‘tgan manzili va boshqalar); aloqaga chiqish uchun ma'lumotlar (shu jumladan, telefon raqami, e-mail, pochta manzili va boshqalar); STIR, ushbu shartnoma maqsadiga tegishli bo‘lgan boshqa ma'lumotlarni har qanday maqsadda ishlov berishga rozilik beradi.
A100: 10.2. Rozilik, shu jumladan shahsiy ma'lumotlar bilan quyidagi harakatlarni amalga oshirishga beriladi: yig‘ish, tizimlashtirish, to‘plash, saqlash, aniqlashtirish (yangilash, o‘zgartirish), foydalanish; O‘zbekiston Respublikasi qonun hujjatlarida nazarda tutilgan hollar va darajada tarqatish, shu jumladan davlat organlari va boshqa tashkilotlarga taqdim etish, shaxsiy ma'lumotlarning egasizlantirish, blokirovka va yo‘q qilish.
A101: 10.3. Qarz oluvchi, shuningdek, Mikromoliya tashkiloti shartnoma doirasida olingan ma'lumotlarni kredit byurosi va garov reestri, skoring kompaniyasi, uyali aloqa operatori, sug‘urta kompaniyasi, reklama ishlab chiqaruvchilari va tarqatuvchilari, shuningdek Mikromoliya tashkilotining boshqa hamkorlariga taqdim etishga roziligini bildiradi.
A103: 11. BOSHQA SHARTLAR
A104: 11.1. Ushbu shartnoma kuchga kirganidan keyin, o‘zaro munosabatlarga aloqador barcha yozishmalar yoki kelishuvlar, o‘z kuchini yo‘qotadi.
A105: 11.2. Ushbu shartnomani bajarish, o‘zgartirish va bekor qilish bilan bog‘liq barcha yozishma va xabarnomalar Tomonlarning ushbu shartnomaning yakuniy qismida ko‘rsatilgan pochta manzillariga yuboriladi.
A106: 11.3. Ushbu shartnomani bajarish uchun zarur bo‘lgan ismi (nomlanishi), ro‘yxatdan o‘tgan joyi, haqiqiy yashash joyi, manzili (joylashgan yeri), bank rekvizitlari va boshqa ma'lumotlar o‘zgargan holatlarda, Tomonlarning har biri bunday o‘zgarishlar amalga oshgan kundan boshlab 5 (besh) kalendar kun ichida boshqa Tomonni bunday o‘zgarishlar haqida yozma ravishda xabardor qilishi shart.
A107: 11.4. Ushbu bitimni amalga oshirish bilan, Qarz oluvchi kelishuvning muhimligi va uni tuzishning yuridik oqibatlarini to‘liq tushunib yetishi, shu sababli Shartnomani tuzish yanglishishlar, aldov, zo‘ravonlik, tahdidlar, yomon niyatli bitim yoki murakkab holatlar (tutqinlik) ta'sirida emasligini tasdiqlaydi.
A108: 11.5. Ushbu shartnomada ko‘zda tutilmagan holatlarda Tomonlar O‘zbekiston Respublikasining amaldagi qonunchiligiga amal qiladilar.
A109: 11.6. Qarz oluvchi Mikromoliya tashkilotining oldindan yozma roziligini olmasdan turib o‘z majburiyatlari yoki huquqlarini uchinchi shaxslarga o‘tkaza olmaydi.
... A113: 12. TOMONLARNING YURIDIK MANZILLARI VA REKVIZITLARI:
A115: «Mikromoliya tashkiloti» | B115: «Qarz oluvchi»
A117: ='Общие данные'!B148 -> «PULLOL BUSINESS MIKROMOLIYA TASHKILOTI» MChJ | B117: ='Общие данные'!B5 -> ANNAZAROV KAXRAMAN SADULLAYEVICH
...

Sheet График
F3: =""&'Общие данные'!B74&" "&'Общие данные'!B65&" shartnomasiga 1 sonli ilova" -> 3 aprel 2026 y.dan №310-TR Mikroqarz shartnomasiga 1 sonli ilova
A5: To'lov jadvali
A7: № | B7: To'lov muddati | C7: Asosiy qarz qoldig'i | D7: To'lov miqdori, so'm
D8: asosiy qarz | E8: foizlar | F8: jami*
A9: 1 | B9: ='График дифференц'!B8 -> 46147 | C9: =IF('Общие данные'!$B$77='Общие данные'!$C$77,'График дифференц'!C8,IF('Общие данные'!$B$77='Общие данные'!$D$77,'График аннуитет.'!C8)) -> 100000000 | D9: =IF('Общие данные'!$B$77='Общие данные'!$C$77,'График дифференц'!D8,IF('Общие данные'!$B$77='Общие данные'!$D$77,'График аннуитет.'!D8)) -> 2777777.8 | E9: =IF('Общие данные'!$B$77='Общие данные'!$C$77,'График дифференц'!E8,IF('Общие данные'!$B$77='Общие данные'!$D$77,'График аннуитет.'!E8)) -> 4821917.8 | F9: =IF('Общие данные'!$B$77='Общие данные'!$C$77,'График дифференц'!F8,IF('Общие данные'!$B$77='Общие данные'!$D$77,'График аннуитет.'!F8)) -> 7599695.5
A10: 2 | B10: ='График дифференц'!B9 -> 46178 | C10: =IF('Общие данные'!$B$77='Общие данные'!$C$77,'График дифференц'!C9,IF('Общие данные'!$B$77='Общие данные'!$D$77,'График аннуитет.'!C9)) -> 97222222 | D10: =IF('Общие данные'!$B$77='Общие данные'!$C$77,'График дифференц'!D9,IF('Общие данные'!$B$77='Общие данные'!$D$77,'График аннуитет.'!D9)) -> 2777777.8 | E10: =IF('Общие данные'!$B$77='Общие данные'!$C$77,'График дифференц'!E9,IF('Общие данные'!$B$77='Общие данные'!$D$77,'График аннуитет.'!E9)) -> 4541476.4 | F10: =IF('Общие данные'!$B$77='Общие данные'!$C$77,'График дифференц'!F9,IF('Общие данные'!$B$77='Общие данные'!$D$77,'График аннуитет.'!F9)) -> 7319254.2
A11: 3 | B11: ='График дифференц'!B10 -> 46209 | C11: =IF('Общие данные'!$B$77='Общие данные'!$C$77,'График дифференц'!C10,IF('Общие данные'!$B$77='Общие данные'!$D$77,'График аннуитет.'!C10)) -> 94444444 | D11: =IF('Общие данные'!$B$77='Общие данные'!$C$77,'График дифференц'!D10,IF('Общие данные'!$B$77='Общие данные'!$D$77,'График аннуитет.'!D10)) -> 2777777.8 | E11: =IF('Общие данные'!$B$77='Общие данные'!$C$77,'График дифференц'!E10,IF('Общие данные'!$B$77='Общие данные'!$D$77,'График аннуитет.'!E10)) -> 4411720 | F11: =IF('Общие данные'!$B$77='Общие данные'!$C$77,'График дифференц'!F10,IF('Общие данные'!$B$77='Общие данные'!$D$77,'График аннуитет.'!F10)) -> 7189497.8
A12: 4 | B12: ='График дифференц'!B11 -> 46239 | C12: =IF('Общие данные'!$B$77='Общие данные'!$C$77,'График дифференц'!C11,IF('Общие данные'!$B$77='Общие данные'!$D$77,'График аннуитет.'!C11)) -> 91666667 | D12: =IF('Общие данные'!$B$77='Общие данные'!$C$77,'График дифференц'!D11,IF('Общие данные'!$B$77='Общие данные'!$D$77,'График аннуитет.'!D11)) -> 2777777.8 | E12: =IF('Общие данные'!$B$77='Общие данные'!$C$77,'График дифференц'!E11,IF('Общие данные'!$B$77='Общие данные'!$D$77,'График аннуитет.'!E11)) -> 4143835.5 | F12: =IF('Общие данные'!$B$77='Общие данные'!$C$77,'График дифференц'!F11,IF('Общие данные'!$B$77='Общие данные'!$D$77,'График аннуитет.'!F11)) -> 6921613.3 | H12: GRAFIKTA BO'SH JOY BO'LSA SKRIT' QILIB TASHLANG!!!
A13: 5 | B13: ='График дифференц'!B12 -> 46272 | C13: =IF('Общие данные'!$B$77='Общие данные'!$C$77,'График дифференц'!C12,IF('Общие данные'!$B$77='Общие данные'!$D$77,'График аннуитет.'!C12)) -> 88888889 | D13: =IF('Общие данные'!$B$77='Общие данные'!$C$77,'График дифференц'!D12,IF('Общие данные'!$B$77='Общие данные'!$D$77,'График аннуитет.'!D12)) -> 2777777.8 | E13: =IF('Общие данные'!$B$77='Общие данные'!$C$77,'График дифференц'!E12,IF('Общие данные'!$B$77='Общие данные'!$D$77,'График аннуитет.'!E12)) -> 4420091.3 | F13: =IF('Общие данные'!$B$77='Общие данные'!$C$77,'График дифференц'!F12,IF('Общие данные'!$B$77='Общие данные'!$D$77,'График аннуитет.'!F12)) -> 7197869.1
A14: 6 | B14: ='График дифференц'!B13 -> 46300 | C14: =IF('Общие данные'!$B$77='Общие данные'!$C$77,'График дифференц'!C13,IF('Общие данные'!$B$77='Общие данные'!$D$77,'График аннуитет.'!C13)) -> 86111111 | D14: =IF('Общие данные'!$B$77='Общие данные'!$C$77,'График дифференц'!D13,IF('Общие данные'!$B$77='Общие данные'!$D$77,'График аннуитет.'!D13)) -> 2777777.8 | E14: =IF('Общие данные'!$B$77='Общие данные'!$C$77,'График дифференц'!E13,IF('Общие данные'!$B$77='Общие данные'!$D$77,'График аннуитет.'!E13)) -> 3633181.2 | F14: =IF('Общие данные'!$B$77='Общие данные'!$C$77,'График дифференц'!F13,IF('Общие данные'!$B$77='Общие данные'!$D$77,'График аннуитет.'!F13)) -> 6410958.9
A15: 7 | B15: ='График дифференц'!B14 -> 46331 | C15: =IF('Общие данные'!$B$77='Общие данные'!$C$77,'График дифференц'!C14,IF('Общие данные'!$B$77='Общие данные'!$D$77,'График аннуитет.'!C14)) -> 83333333 | D15: =IF('Общие данные'!$B$77='Общие данные'!$C$77,'График дифференц'!D14,IF('Общие данные'!$B$77='Общие данные'!$D$77,'График аннуитет.'!D14)) -> 2777777.8 | E15: =IF('Общие данные'!$B$77='Общие данные'!$C$77,'График дифференц'!E14,IF('Общие данные'!$B$77='Общие данные'!$D$77,'График аннуитет.'!E14)) -> 3892694.2 | F15: =IF('Общие данные'!$B$77='Общие данные'!$C$77,'График дифференц'!F14,IF('Общие данные'!$B$77='Общие данные'!$D$77,'График аннуитет.'!F14)) -> 6670472
A16: 8 | B16: ='График дифференц'!B15 -> 46363 | C16: =IF('Общие данные'!$B$77='Общие данные'!$C$77,'График дифференц'!C15,IF('Общие данные'!$B$77='Общие данные'!$D$77,'График аннуитет.'!C15)) -> 80555556 | D16: =IF('Общие данные'!$B$77='Общие данные'!$C$77,'График дифференц'!D15,IF('Общие данные'!$B$77='Общие данные'!$D$77,'График аннуитет.'!D15)) -> 2777777.8 | E16: =IF('Общие данные'!$B$77='Общие данные'!$C$77,'График дифференц'!E15,IF('Общие данные'!$B$77='Общие данные'!$D$77,'График аннуитет.'!E15)) -> 3884322.6 | F16: =IF('Общие данные'!$B$77='Общие данные'!$C$77,'График дифференц'!F15,IF('Общие данные'!$B$77='Общие данные'!$D$77,'График аннуитет.'!F15)) -> 6662100.3
A17: 9 | B17: ='График дифференц'!B16 -> 46392 | C17: =IF('Общие данные'!$B$77='Общие данные'!$C$77,'График дифференц'!C16,IF('Общие данные'!$B$77='Общие данные'!$D$77,'График аннуитет.'!C16)) -> 77777778 | D17: =IF('Общие данные'!$B$77='Общие данные'!$C$77,'График дифференц'!D16,IF('Общие данные'!$B$77='Общие данные'!$D$77,'График аннуитет.'!D16)) -> 2777777.8 | E17: =IF('Общие данные'!$B$77='Общие данные'!$C$77,'График дифференц'!E16,IF('Общие данные'!$B$77='Общие данные'!$D$77,'График аннуитет.'!E16)) -> 3398782.3 | F17: =IF('Общие данные'!$B$77='Общие данные'!$C$77,'График дифференц'!F16,IF('Общие данные'!$B$77='Общие данные'!$D$77,'График аннуитет.'!F16)) -> 6176560.1
A18: 10 | B18: ='График дифференц'!B17 -> 46423 | C18: =IF('Общие данные'!$B$77='Общие данные'!$C$77,'График дифференц'!C17,IF('Общие данные'!$B$77='Общие данные'!$D$77,'График аннуитет.'!C17)) -> 75000000 | D18: =IF('Общие данные'!$B$77='Общие данные'!$C$77,'График дифференц'!D17,IF('Общие данные'!$B$77='Общие данные'!$D$77,'График аннуитет.'!D17)) -> 2777777.8 | E18: =IF('Общие данные'!$B$77='Общие данные'!$C$77,'График дифференц'!E17,IF('Общие данные'!$B$77='Общие данные'!$D$77,'График аннуитет.'!E17)) -> 3503424.7 | F18: =IF('Общие данные'!$B$77='Общие данные'!$C$77,'График дифференц'!F17,IF('Общие данные'!$B$77='Общие данные'!$D$77,'График аннуитет.'!F17)) -> 6281202.5
A19: 11 | B19: ='График дифференц'!B18 -> 46451 | C19: =IF('Общие данные'!$B$77='Общие данные'!$C$77,'График дифференц'!C18,IF('Общие данные'!$B$77='Общие данные'!$D$77,'График аннуитет.'!C18)) -> 72222222 | D19: =IF('Общие данные'!$B$77='Общие данные'!$C$77,'График дифференц'!D18,IF('Общие данные'!$B$77='Общие данные'!$D$77,'График аннуитет.'!D18)) -> 2777777.8 | E19: =IF('Общие данные'!$B$77='Общие данные'!$C$77,'График дифференц'!E18,IF('Общие данные'!$B$77='Общие данные'!$D$77,'График аннуитет.'!E18)) -> 3047184.3 | F19: =IF('Общие данные'!$B$77='Общие данные'!$C$77,'График дифференц'!F18,IF('Общие данные'!$B$77='Общие данные'!$D$77,'График аннуитет.'!F18)) -> 5824962.1
A20: 12 | B20: ='График дифференц'!B19 -> 46482 | C20: =IF('Общие данные'!$B$77='Общие данные'!$C$77,'График дифференц'!C19,IF('Общие данные'!$B$77='Общие данные'!$D$77,'График аннуитет.'!C19)) -> 69444444 | D20: =IF('Общие данные'!$B$77='Общие данные'!$C$77,'График дифференц'!D19,IF('Общие данные'!$B$77='Общие данные'!$D$77,'График аннуитет.'!D19)) -> 2777777.8 | E20: =IF('Общие данные'!$B$77='Общие данные'!$C$77,'График дифференц'!E19,IF('Общие данные'!$B$77='Общие данные'!$D$77,'График аннуитет.'!E19)) -> 3243911.6 | F20: =IF('Общие данные'!$B$77='Общие данные'!$C$77,'График дифференц'!F19,IF('Общие данные'!$B$77='Общие данные'!$D$77,'График аннуитет.'!F19)) -> 6021689.4
A21: 13 | B21: ='График дифференц'!B20 -> 46512 | C21: =IF('Общие данные'!$B$77='Общие данные'!$C$77,'График дифференц'!C20,IF('Общие данные'!$B$77='Общие данные'!$D$77,'График аннуитет.'!C20)) -> 66666667 | D21: =IF('Общие данные'!$B$77='Общие данные'!$C$77,'График дифференц'!D20,IF('Общие данные'!$B$77='Общие данные'!$D$77,'График аннуитет.'!D20)) -> 2777777.8 | E21: =IF('Общие данные'!$B$77='Общие данные'!$C$77,'График дифференц'!E20,IF('Общие данные'!$B$77='Общие данные'!$D$77,'График аннуитет.'!E20)) -> 3013698.6 | F21: =IF('Общие данные'!$B$77='Общие данные'!$C$77,'График дифференц'!F20,IF('Общие данные'!$B$77='Общие данные'!$D$77,'График аннуитет.'!F20)) -> 5791476.4
A22: 14 | B22: ='График дифференц'!B21 -> 46545 | C22: =IF('Общие данные'!$B$77='Общие данные'!$C$77,'График дифференц'!C21,IF('Общие данные'!$B$77='Общие данные'!$D$77,'График аннуитет.'!C21)) -> 63888889 | D22: =IF('Общие данные'!$B$77='Общие данные'!$C$77,'График дифференц'!D21,IF('Общие данные'!$B$77='Общие данные'!$D$77,'График аннуитет.'!D21)) -> 2777777.8 | E22: =IF('Общие данные'!$B$77='Общие данные'!$C$77,'График дифференц'!E21,IF('Общие данные'!$B$77='Общие данные'!$D$77,'График аннуитет.'!E21)) -> 3176940.7 | F22: =IF('Общие данные'!$B$77='Общие данные'!$C$77,'График дифференц'!F21,IF('Общие данные'!$B$77='Общие данные'!$D$77,'График аннуитет.'!F21)) -> 5954718.5
A23: 15 | B23: ='График дифференц'!B22 -> 46573 | C23: =IF('Общие данные'!$B$77='Общие данные'!$C$77,'График дифференц'!C22,IF('Общие данные'!$B$77='Общие данные'!$D$77,'График аннуитет.'!C22)) -> 61111111 | D23: =IF('Общие данные'!$B$77='Общие данные'!$C$77,'График дифференц'!D22,IF('Общие данные'!$B$77='Общие данные'!$D$77,'График аннуитет.'!D22)) -> 2777777.8 | E23: =IF('Общие данные'!$B$77='Общие данные'!$C$77,'График дифференц'!E22,IF('Общие данные'!$B$77='Общие данные'!$D$77,'График аннуитет.'!E22)) -> 2578386.7 | F23: =IF('Общие данные'!$B$77='Общие данные'!$C$77,'График дифференц'!F22,IF('Общие данные'!$B$77='Общие данные'!$D$77,'График аннуитет.'!F22)) -> 5356164.5
A24: 16 | B24: ='График дифференц'!B23 -> 46604 | C24: =IF('Общие данные'!$B$77='Общие данные'!$C$77,'График дифференц'!C23,IF('Общие данные'!$B$77='Общие данные'!$D$77,'График аннуитет.'!C23)) -> 58333333 | D24: =IF('Общие данные'!$B$77='Общие данные'!$C$77,'График дифференц'!D23,IF('Общие данные'!$B$77='Общие данные'!$D$77,'График аннуитет.'!D23)) -> 2777777.8 | E24: =IF('Общие данные'!$B$77='Общие данные'!$C$77,'График дифференц'!E23,IF('Общие данные'!$B$77='Общие данные'!$D$77,'График аннуитет.'!E23)) -> 2724885.7 | F24: =IF('Общие данные'!$B$77='Общие данные'!$C$77,'График дифференц'!F23,IF('Общие данные'!$B$77='Общие данные'!$D$77,'График аннуитет.'!F23)) -> 5502663.5
... A32: 24 | B32: ='График дифференц'!B31 -> 46848 | C32: =IF('Общие данные'!$B$77='Общие данные'!$C$77,'График дифференц'!C31,IF('Общие данные'!$B$77='Общие данные'!$D$77,'График аннуитет.'!C31)) -> 36111111 | D32: =IF('Общие данные'!$B$77='Общие данные'!$C$77,'График дифференц'!D31,IF('Общие данные'!$B$77='Общие данные'!$D$77,'График аннуитет.'!D31)) -> 2777777.8 | E32: =IF('Общие данные'!$B$77='Общие данные'!$C$77,'График дифференц'!E31,IF('Общие данные'!$B$77='Общие данные'!$D$77,'График аннуитет.'!E31)) -> 1627959.9 | F32: =IF('Общие данные'!$B$77='Общие данные'!$C$77,'График дифференц'!F31,IF('Общие данные'!$B$77='Общие данные'!$D$77,'График аннуитет.'!F31)) -> 4405737.7
A33: =1+A32 -> 25 | B33: ='График дифференц'!B32 -> 46878 | C33: =IF('Общие данные'!$B$77='Общие данные'!$C$77,'График дифференц'!C32,IF('Общие данные'!$B$77='Общие данные'!$D$77,'График аннуитет.'!C32)) -> 33333333 | D33: =IF('Общие данные'!$B$77='Общие данные'!$C$77,'График дифференц'!D32,IF('Общие данные'!$B$77='Общие данные'!$D$77,'График аннуитет.'!D32)) -> 2777777.8 | E33: =IF('Общие данные'!$B$77='Общие данные'!$C$77,'График дифференц'!E32,IF('Общие данные'!$B$77='Общие данные'!$D$77,'График аннуитет.'!E32)) -> 1502732.1 | F33: =IF('Общие данные'!$B$77='Общие данные'!$C$77,'График дифференц'!F32,IF('Общие данные'!$B$77='Общие данные'!$D$77,'График аннуитет.'!F32)) -> 4280509.9
A34: =1+A33 -> 26 | B34: ='График дифференц'!B33 -> 46909 | C34: =IF('Общие данные'!$B$77='Общие данные'!$C$77,'График дифференц'!C33,IF('Общие данные'!$B$77='Общие данные'!$D$77,'График аннуитет.'!C33)) -> 30555555 | D34: =IF('Общие данные'!$B$77='Общие данные'!$C$77,'График дифференц'!D33,IF('Общие данные'!$B$77='Общие данные'!$D$77,'График аннуитет.'!D33)) -> 2777777.8 | E34: =IF('Общие данные'!$B$77='Общие данные'!$C$77,'График дифференц'!E33,IF('Общие данные'!$B$77='Общие данные'!$D$77,'График аннуитет.'!E33)) -> 1423421.4 | F34: =IF('Общие данные'!$B$77='Общие данные'!$C$77,'График дифференц'!F33,IF('Общие данные'!$B$77='Общие данные'!$D$77,'График аннуитет.'!F33)) -> 4201199.2
A35: =1+A34 -> 27 | B35: ='График дифференц'!B34 -> 46939 | C35: =IF('Общие данные'!$B$77='Общие данные'!$C$77,'График дифференц'!C34,IF('Общие данные'!$B$77='Общие данные'!$D$77,'График аннуитет.'!C34)) -> 27777778 | D35: =IF('Общие данные'!$B$77='Общие данные'!$C$77,'График дифференц'!D34,IF('Общие данные'!$B$77='Общие данные'!$D$77,'График аннуитет.'!D34)) -> 2777777.8 | E35: =IF('Общие данные'!$B$77='Общие данные'!$C$77,'График дифференц'!E34,IF('Общие данные'!$B$77='Общие данные'!$D$77,'График аннуитет.'!E34)) -> 1252276.8 | F35: =IF('Общие данные'!$B$77='Общие данные'!$C$77,'График дифференц'!F34,IF('Общие данные'!$B$77='Общие данные'!$D$77,'График аннуитет.'!F34)) -> 4030054.6
A36: =1+A35 -> 28 | B36: ='График дифференц'!B35 -> 46972 | C36: =IF('Общие данные'!$B$77='Общие данные'!$C$77,'График дифференц'!C35,IF('Общие данные'!$B$77='Общие данные'!$D$77,'График аннуитет.'!C35)) -> 25000000 | D36: =IF('Общие данные'!$B$77='Общие данные'!$C$77,'График дифференц'!D35,IF('Общие данные'!$B$77='Общие данные'!$D$77,'График аннуитет.'!D35)) -> 2777777.8 | E36: =IF('Общие данные'!$B$77='Общие данные'!$C$77,'График дифференц'!E35,IF('Общие данные'!$B$77='Общие данные'!$D$77,'График аннуитет.'!E35)) -> 1239754.2 | F36: =IF('Общие данные'!$B$77='Общие данные'!$C$77,'График дифференц'!F35,IF('Общие данные'!$B$77='Общие данные'!$D$77,'График аннуитет.'!F35)) -> 4017532
A37: =1+A36 -> 29 | B37: ='График дифференц'!B36 -> 47001 | C37: =IF('Общие данные'!$B$77='Общие данные'!$C$77,'График дифференц'!C36,IF('Общие данные'!$B$77='Общие данные'!$D$77,'График аннуитет.'!C36)) -> 22222222 | D37: =IF('Общие данные'!$B$77='Общие данные'!$C$77,'График дифференц'!D36,IF('Общие данные'!$B$77='Общие данные'!$D$77,'График аннуитет.'!D36)) -> 2777777.8 | E37: =IF('Общие данные'!$B$77='Общие данные'!$C$77,'График дифференц'!E36,IF('Общие данные'!$B$77='Общие данные'!$D$77,'График аннуитет.'!E36)) -> 968427.45 | F37: =IF('Общие данные'!$B$77='Общие данные'!$C$77,'График дифференц'!F36,IF('Общие данные'!$B$77='Общие данные'!$D$77,'График аннуитет.'!F36)) -> 3746205.2
A38: =1+A37 -> 30 | B38: ='График дифференц'!B37 -> 47031 | C38: =IF('Общие данные'!$B$77='Общие данные'!$C$77,'График дифференц'!C37,IF('Общие данные'!$B$77='Общие данные'!$D$77,'График аннуитет.'!C37)) -> 19444444 | D38: =IF('Общие данные'!$B$77='Общие данные'!$C$77,'График дифференц'!D37,IF('Общие данные'!$B$77='Общие данные'!$D$77,'График аннуитет.'!D37)) -> 2777777.8 | E38: =IF('Общие данные'!$B$77='Общие данные'!$C$77,'График дифференц'!E37,IF('Общие данные'!$B$77='Общие данные'!$D$77,'График аннуитет.'!E37)) -> 876593.7 | F38: =IF('Общие данные'!$B$77='Общие данные'!$C$77,'График дифференц'!F37,IF('Общие данные'!$B$77='Общие данные'!$D$77,'График аннуитет.'!F37)) -> 3654371.5
A39: =1+A38 -> 31 | B39: ='График дифференц'!B38 -> 47063 | C39: =IF('Общие данные'!$B$77='Общие данные'!$C$77,'График дифференц'!C38,IF('Общие данные'!$B$77='Общие данные'!$D$77,'График аннуитет.'!C38)) -> 16666667 | D39: =IF('Общие данные'!$B$77='Общие данные'!$C$77,'График дифференц'!D38,IF('Общие данные'!$B$77='Общие данные'!$D$77,'График аннуитет.'!D38)) -> 2777777.8 | E39: =IF('Общие данные'!$B$77='Общие данные'!$C$77,'График дифференц'!E38,IF('Общие данные'!$B$77='Общие данные'!$D$77,'График аннуитет.'!E38)) -> 801457.28 | F39: =IF('Общие данные'!$B$77='Общие данные'!$C$77,'График дифференц'!F38,IF('Общие данные'!$B$77='Общие данные'!$D$77,'График аннуитет.'!F38)) -> 3579235.1
A40: =1+A39 -> 32 | B40: ='График дифференц'!B39 -> 47092 | C40: =IF('Общие данные'!$B$77='Общие данные'!$C$77,'График дифференц'!C39,IF('Общие данные'!$B$77='Общие данные'!$D$77,'График аннуитет.'!C39)) -> 13888889 | D40: =IF('Общие данные'!$B$77='Общие данные'!$C$77,'График дифференц'!D39,IF('Общие данные'!$B$77='Общие данные'!$D$77,'График аннуитет.'!D39)) -> 2777777.8 | E40: =IF('Общие данные'!$B$77='Общие данные'!$C$77,'График дифференц'!E39,IF('Общие данные'!$B$77='Общие данные'!$D$77,'График аннуитет.'!E39)) -> 605267.12 | F40: =IF('Общие данные'!$B$77='Общие данные'!$C$77,'График дифференц'!F39,IF('Общие данные'!$B$77='Общие данные'!$D$77,'График аннуитет.'!F39)) -> 3383044.9
A41: =1+A40 -> 33 | B41: ='График дифференц'!B40 -> 47123 | C41: =IF('Общие данные'!$B$77='Общие данные'!$C$77,'График дифференц'!C40,IF('Общие данные'!$B$77='Общие данные'!$D$77,'График аннуитет.'!C40)) -> 11111111 | D41: =IF('Общие данные'!$B$77='Общие данные'!$C$77,'График дифференц'!D40,IF('Общие данные'!$B$77='Общие данные'!$D$77,'График аннуитет.'!D40)) -> 2777777.8 | E41: =IF('Общие данные'!$B$77='Общие данные'!$C$77,'График дифференц'!E40,IF('Общие данные'!$B$77='Общие данные'!$D$77,'График аннуитет.'!E40)) -> 519025.87 | F41: =IF('Общие данные'!$B$77='Общие данные'!$C$77,'График дифференц'!F40,IF('Общие данные'!$B$77='Общие данные'!$D$77,'График аннуитет.'!F40)) -> 3296803.6
A42: =1+A41 -> 34 | B42: ='График дифференц'!B41 -> 47154 | C42: =IF('Общие данные'!$B$77='Общие данные'!$C$77,'График дифференц'!C41,IF('Общие данные'!$B$77='Общие данные'!$D$77,'График аннуитет.'!C41)) -> 8333333.3 | D42: =IF('Общие данные'!$B$77='Общие данные'!$C$77,'График дифференц'!D41,IF('Общие данные'!$B$77='Общие данные'!$D$77,'График аннуитет.'!D41)) -> 2777777.8 | E42: =IF('Общие данные'!$B$77='Общие данные'!$C$77,'График дифференц'!E41,IF('Общие данные'!$B$77='Общие данные'!$D$77,'График аннуитет.'!E41)) -> 389269.48 | F42: =IF('Общие данные'!$B$77='Общие данные'!$C$77,'График дифференц'!F41,IF('Общие данные'!$B$77='Общие данные'!$D$77,'График аннуитет.'!F41)) -> 3167047.3
A43: =1+A42 -> 35 | B43: ='График дифференц'!B42 -> 47182 | C43: =IF('Общие данные'!$B$77='Общие данные'!$C$77,'График дифференц'!C42,IF('Общие данные'!$B$77='Общие данные'!$D$77,'График аннуитет.'!C42)) -> 5555555.5 | D43: =IF('Общие данные'!$B$77='Общие данные'!$C$77,'График дифференц'!D42,IF('Общие данные'!$B$77='Общие данные'!$D$77,'График аннуитет.'!D42)) -> 2777777.8 | E43: =IF('Общие данные'!$B$77='Общие данные'!$C$77,'График дифференц'!E42,IF('Общие данные'!$B$77='Общие данные'!$D$77,'График аннуитет.'!E42)) -> 234398.64 | F43: =IF('Общие данные'!$B$77='Общие данные'!$C$77,'График дифференц'!F42,IF('Общие данные'!$B$77='Общие данные'!$D$77,'График аннуитет.'!F42)) -> 3012176.4
A44: =1+A43 -> 36 | B44: ='График дифференц'!B43 -> 47211 | C44: =IF('Общие данные'!$B$77='Общие данные'!$C$77,'График дифференц'!C43,IF('Общие данные'!$B$77='Общие данные'!$D$77,'График аннуитет.'!C43)) -> 2777777.7 | D44: =IF('Общие данные'!$B$77='Общие данные'!$C$77,'График дифференц'!D43,IF('Общие данные'!$B$77='Общие данные'!$D$77,'График аннуитет.'!D43)) -> 2777777.7 | E44: =IF('Общие данные'!$B$77='Общие данные'!$C$77,'График дифференц'!E43,IF('Общие данные'!$B$77='Общие данные'!$D$77,'График аннуитет.'!E43)) -> 121385.01 | F44: =IF('Общие данные'!$B$77='Общие данные'!$C$77,'График дифференц'!F43,IF('Общие данные'!$B$77='Общие данные'!$D$77,'График аннуитет.'!F43)) -> 2899162.7
A45: =1+A44 -> 37 | B45: ='График дифференц'!B44 -> FALSE | C45: =IF('Общие данные'!$B$77='Общие данные'!$C$77,'График дифференц'!C44,IF('Общие данные'!$B$77='Общие данные'!$D$77,'График аннуитет.'!C44)) -> -4.1909516e-09 | D45: =IF('Общие данные'!$B$77='Общие данные'!$C$77,'График дифференц'!D44,IF('Общие данные'!$B$77='Общие данные'!$D$77,'График аннуитет.'!D44)) -> FALSE | E45: =IF('Общие данные'!$B$77='Общие данные'!$C$77,'График дифференц'!E44,IF('Общие данные'!$B$77='Общие данные'!$D$77,'График аннуитет.'!E44)) -> FALSE | F45: =IF('Общие данные'!$B$77='Общие данные'!$C$77,'График дифференц'!F44,IF('Общие данные'!$B$77='Общие данные'!$D$77,'График аннуитет.'!F44)) -> FALSE
A46: =1+A45 -> 38 | B46: ='График дифференц'!B45 -> FALSE | C46: =IF('Общие данные'!$B$77='Общие данные'!$C$77,'График дифференц'!C45,IF('Общие данные'!$B$77='Общие данные'!$D$77,'График аннуитет.'!C57)) -> -4.1909516e-09 | D46: =IF('Общие данные'!$B$77='Общие данные'!$C$77,'График дифференц'!D45,IF('Общие данные'!$B$77='Общие данные'!$D$77,'График аннуитет.'!D45)) -> FALSE | E46: =IF('Общие данные'!$B$77='Общие данные'!$C$77,'График дифференц'!E45,IF('Общие данные'!$B$77='Общие данные'!$D$77,'График аннуитет.'!E45)) -> FALSE | F46: =IF('Общие данные'!$B$77='Общие данные'!$C$77,'График дифференц'!F45,IF('Общие данные'!$B$77='Общие данные'!$D$77,'График аннуитет.'!F57)) -> FALSE
A47: =1+A46 -> 39 | B47: ='График дифференц'!B46 -> FALSE | C47: =IF('Общие данные'!$B$77='Общие данные'!$C$77,'График дифференц'!C46,IF('Общие данные'!$B$77='Общие данные'!$D$77,'График аннуитет.'!C58)) -> -4.1909516e-09 | D47: =IF('Общие данные'!$B$77='Общие данные'!$C$77,'График дифференц'!D46,IF('Общие данные'!$B$77='Общие данные'!$D$77,'График аннуитет.'!D46)) -> FALSE | E47: =IF('Общие данные'!$B$77='Общие данные'!$C$77,'График дифференц'!E46,IF('Общие данные'!$B$77='Общие данные'!$D$77,'График аннуитет.'!E46)) -> FALSE | F47: =IF('Общие данные'!$B$77='Общие данные'!$C$77,'График дифференц'!F46,IF('Общие данные'!$B$77='Общие данные'!$D$77,'График аннуитет.'!F58)) -> FALSE
A48: =1+A47 -> 40 | B48: ='График дифференц'!B47 -> FALSE | C48: =IF('Общие данные'!$B$77='Общие данные'!$C$77,'График дифференц'!C47,IF('Общие данные'!$B$77='Общие данные'!$D$77,'График аннуитет.'!C59)) -> -4.1909516e-09 | D48: =IF('Общие данные'!$B$77='Общие данные'!$C$77,'График дифференц'!D47,IF('Общие данные'!$B$77='Общие данные'!$D$77,'График аннуитет.'!D47)) -> FALSE | E48: =IF('Общие данные'!$B$77='Общие данные'!$C$77,'График дифференц'!E47,IF('Общие данные'!$B$77='Общие данные'!$D$77,'График аннуитет.'!E47)) -> FALSE | F48: =IF('Общие данные'!$B$77='Общие данные'!$C$77,'График дифференц'!F47,IF('Общие данные'!$B$77='Общие данные'!$D$77,'График аннуитет.'!F59)) -> FALSE
A49: =1+A48 -> 41 | B49: ='График дифференц'!B48 -> FALSE | C49: =IF('Общие данные'!$B$77='Общие данные'!$C$77,'График дифференц'!C48,IF('Общие данные'!$B$77='Общие данные'!$D$77,'График аннуитет.'!C60)) -> -4.1909516e-09 | D49: =IF('Общие данные'!$B$77='Общие данные'!$C$77,'График дифференц'!D48,IF('Общие данные'!$B$77='Общие данные'!$D$77,'График аннуитет.'!D48)) -> FALSE | E49: =IF('Общие данные'!$B$77='Общие данные'!$C$77,'График дифференц'!E48,IF('Общие данные'!$B$77='Общие данные'!$D$77,'График аннуитет.'!E48)) -> FALSE | F49: =IF('Общие данные'!$B$77='Общие данные'!$C$77,'График дифференц'!F48,IF('Общие данные'!$B$77='Общие данные'!$D$77,'График аннуитет.'!F60)) -> FALSE
A50: =1+A49 -> 42 | B50: ='График дифференц'!B49 -> FALSE | C50: =IF('Общие данные'!$B$77='Общие данные'!$C$77,'График дифференц'!C49,IF('Общие данные'!$B$77='Общие данные'!$D$77,'График аннуитет.'!C61)) -> -4.1909516e-09 | D50: =IF('Общие данные'!$B$77='Общие данные'!$C$77,'График дифференц'!D49,IF('Общие данные'!$B$77='Общие данные'!$D$77,'График аннуитет.'!D49)) -> FALSE | E50: =IF('Общие данные'!$B$77='Общие данные'!$C$77,'График дифференц'!E49,IF('Общие данные'!$B$77='Общие данные'!$D$77,'График аннуитет.'!E49)) -> FALSE | F50: =IF('Общие данные'!$B$77='Общие данные'!$C$77,'График дифференц'!F49,IF('Общие данные'!$B$77='Общие данные'!$D$77,'График аннуитет.'!F61)) -> FALSE
A51: =1+A50 -> 43 | B51: ='График дифференц'!B50 -> FALSE | C51: =IF('Общие данные'!$B$77='Общие данные'!$C$77,'График дифференц'!C50,IF('Общие данные'!$B$77='Общие данные'!$D$77,'График аннуитет.'!C62)) -> -4.1909516e-09 | D51: =IF('Общие данные'!$B$77='Общие данные'!$C$77,'График дифференц'!D50,IF('Общие данные'!$B$77='Общие данные'!$D$77,'График аннуитет.'!D50)) -> FALSE | E51: =IF('Общие данные'!$B$77='Общие данные'!$C$77,'График дифференц'!E50,IF('Общие данные'!$B$77='Общие данные'!$D$77,'График аннуитет.'!E50)) -> FALSE | F51: =IF('Общие данные'!$B$77='Общие данные'!$C$77,'График дифференц'!F50,IF('Общие данные'!$B$77='Общие данные'!$D$77,'График аннуитет.'!F62)) -> FALSE
A52: =1+A51 -> 44 | B52: ='График дифференц'!B51 -> FALSE | C52: =IF('Общие данные'!$B$77='Общие данные'!$C$77,'График дифференц'!C51,IF('Общие данные'!$B$77='Общие данные'!$D$77,'График аннуитет.'!C63)) -> -4.1909516e-09 | D52: =IF('Общие данные'!$B$77='Общие данные'!$C$77,'График дифференц'!D51,IF('Общие данные'!$B$77='Общие данные'!$D$77,'График аннуитет.'!D51)) -> FALSE | E52: =IF('Общие данные'!$B$77='Общие данные'!$C$77,'График дифференц'!E51,IF('Общие данные'!$B$77='Общие данные'!$D$77,'График аннуитет.'!E51)) -> FALSE | F52: =IF('Общие данные'!$B$77='Общие данные'!$C$77,'График дифференц'!F51,IF('Общие данные'!$B$77='Общие данные'!$D$77,'График аннуитет.'!F63)) -> FALSE
A53: =1+A52 -> 45 | B53: ='График дифференц'!B52 -> FALSE | C53: =IF('Общие данные'!$B$77='Общие данные'!$C$77,'График дифференц'!C52,IF('Общие данные'!$B$77='Общие данные'!$D$77,'График аннуитет.'!C64)) -> -4.1909516e-09 | D53: =IF('Общие данные'!$B$77='Общие данные'!$C$77,'График дифференц'!D52,IF('Общие данные'!$B$77='Общие данные'!$D$77,'График аннуитет.'!D52)) -> FALSE | E53: =IF('Общие данные'!$B$77='Общие данные'!$C$77,'График дифференц'!E52,IF('Общие данные'!$B$77='Общие данные'!$D$77,'График аннуитет.'!E52)) -> FALSE | F53: =IF('Общие данные'!$B$77='Общие данные'!$C$77,'График дифференц'!F52,IF('Общие данные'!$B$77='Общие данные'!$D$77,'График аннуитет.'!F64)) -> FALSE
A54: =1+A53 -> 46 | B54: ='График дифференц'!B53 -> FALSE | C54: =IF('Общие данные'!$B$77='Общие данные'!$C$77,'График дифференц'!C53,IF('Общие данные'!$B$77='Общие данные'!$D$77,'График аннуитет.'!C65)) -> -4.1909516e-09 | D54: =IF('Общие данные'!$B$77='Общие данные'!$C$77,'График дифференц'!D53,IF('Общие данные'!$B$77='Общие данные'!$D$77,'График аннуитет.'!D53)) -> FALSE | E54: =IF('Общие данные'!$B$77='Общие данные'!$C$77,'График дифференц'!E53,IF('Общие данные'!$B$77='Общие данные'!$D$77,'График аннуитет.'!E53)) -> FALSE | F54: =IF('Общие данные'!$B$77='Общие данные'!$C$77,'График дифференц'!F53,IF('Общие данные'!$B$77='Общие данные'!$D$77,'График аннуитет.'!F65)) -> FALSE
A55: =1+A54 -> 47 | B55: ='График дифференц'!B54 -> FALSE | C55: =IF('Общие данные'!$B$77='Общие данные'!$C$77,'График дифференц'!C54,IF('Общие данные'!$B$77='Общие данные'!$D$77,'График аннуитет.'!C66)) -> -4.1909516e-09 | D55: =IF('Общие данные'!$B$77='Общие данные'!$C$77,'График дифференц'!D54,IF('Общие данные'!$B$77='Общие данные'!$D$77,'График аннуитет.'!D54)) -> FALSE | E55: =IF('Общие данные'!$B$77='Общие данные'!$C$77,'График дифференц'!E54,IF('Общие данные'!$B$77='Общие данные'!$D$77,'График аннуитет.'!E54)) -> FALSE | F55: =IF('Общие данные'!$B$77='Общие данные'!$C$77,'График дифференц'!F54,IF('Общие данные'!$B$77='Общие данные'!$D$77,'График аннуитет.'!F66)) -> FALSE
A56: =1+A55 -> 48 | B56: ='График дифференц'!B55 -> FALSE | C56: =IF('Общие данные'!$B$77='Общие данные'!$C$77,'График дифференц'!C55,IF('Общие данные'!$B$77='Общие данные'!$D$77,'График аннуитет.'!C67)) -> -4.1909516e-09 | D56: =IF('Общие данные'!$B$77='Общие данные'!$C$77,'График дифференц'!D55,IF('Общие данные'!$B$77='Общие данные'!$D$77,'График аннуитет.'!D55)) -> FALSE | E56: =IF('Общие данные'!$B$77='Общие данные'!$C$77,'График дифференц'!E55,IF('Общие данные'!$B$77='Общие данные'!$D$77,'График аннуитет.'!E55)) -> FALSE | F56: =IF('Общие данные'!$B$77='Общие данные'!$C$77,'График дифференц'!F55,IF('Общие данные'!$B$77='Общие данные'!$D$77,'График аннуитет.'!F67)) -> FALSE
B57: JAMI | D57: =IF('Общие данные'!$B$77='Общие данные'!$C$77,'График дифференц'!D56,IF('Общие данные'!$B$77='Общие данные'!$D$77,'График аннуитет.'!D56)) -> 100000000 | E57: =IF('Общие данные'!$B$77='Общие данные'!$C$77,'График дифференц'!E56,IF('Общие данные'!$B$77='Общие данные'!$D$77,'График аннуитет.'!E56)) -> 85231267 | F57: =SUM(F9:F56) -> 1.8523127e+08
A59: ="*"&'Общие данные'!C64&" bo‘yicha to‘lovlar to‘lov jadvalida ko‘rsatilmagan sanalarda to‘langan taqdirda, to‘lov summasi mikroqarz shartnomasining 2.4.-bandiga muvofiq "&'Общие данные'!B65&" qoldig‘iga hisoblangan foizlar summasiga o‘zgartiriladi." -> *Mikrokredit bo‘yicha to‘lovlar to‘lov jadvalida ko‘rsatilmagan sanalarda to‘langan taqdirda, to‘lov summasi mikroqarz shartnomasining 2.4.-bandiga muvofiq Mikroqarz qoldig‘iga hisoblangan foizlar summasiga o‘zgartiriladi.
A61: «Mikromoliya tashkiloti » | D61: «Qarz oluvchi»
A63: =договор!A117 -> «PULLOL BUSINESS MIKROMOLIYA TASHKILOTI» MChJ | D63: =договор!B117 -> ANNAZAROV KAXRAMAN SADULLAYEVICH
A64: =договор!A119 -> Manzil: Toshkent shahri, Yakkasaroy tumani, Rakat ko'chasi, 10-uy, 18 xonadon | D64: =договор!B119 -> Manzil: QORAQALPOG'ISTON RESPUBLIKASI TO'RTKO'L TUMANI YOSHLIK MFY KALTAMINAR KO'CHASI 1B-UY
A65: =договор!A120 -> h/r: № 20208000405643889001 | D65: =договор!B121 -> pasport seriyasi: AD 2849628, IIV 35233 tomonidan 23.03.2023 yilda berilgan
A66: =договор!A121 -> MFO: №01088 в ATB “Kapitalbank” Markaziy amaliyotlar bo'limi
A67: =договор!A122 -> STIR: 310430149 | D67: =договор!B122 -> Tel: 93 770 26 32 KLIENT
A68: =договор!A123 -> Tel: (97) 714 14 14 | D68: =договор!B123 -> 93 369 60 50 AYOLI
A69: =договор!A124 -> (71) 555 10 02 17 | D69: =договор!B124 -> 94 149 90 95 UYI
D70: =IF(договор!B125=0,"",договор!B125)
A71: =договор!A126 -> To'rtko'l filiali boshlig’i | D71: =договор!B126 -> ANNAZAROV K.S. __________________
A73: =договор!A129 -> Djumanazarov B.A. ________________

Sheet заявление залогодателя
B6: ='Общие данные'!B148 -> «PULLOL BUSINESS MIKROMOLIYA TASHKILOTI» MChJ
B7: =""&'Общие данные'!A160&"i "&'Общие данные'!B160&"ga" -> To'rtko'l filiali boshlig’ii Djumanazarov B.A.ga
B8: =""&'Общие данные'!C105&"dan" -> dan
B9: ='Общие данные'!B111 -> ANNAZAROV KAXRAMAN SADULLAYEVICH
B10: ='Общие данные'!C111 -> ANNAZAROV KAXRAMAN SADULLAYEVICH
B11: dan
A13: =IF('Общие данные'!B103="Avtotransport",A14,A15) -> ANNAZAROV KAXRAMAN SADULLAYEVICH tomonidan so’ralayotgan 36 (Yigirma to'rt) oy muddatga, 100 000 000 (Yuz million so'm) miqdoridagi Mikroqarzning ta’minoti sifatida menga mulk huquqi asosida tegishli bo’lgan Yakka tartibdagi uy-joy, umumiy maydoni 213,72 va yashash maydoni 149,81 QORAQALPOG'ISTON RESPUBLIKASI TO'RTKO'L TUMANI YOSHLIK MFY KALTAMINAR KO'CHASI 1B-UY manzilda joylashgan ko'chmas mulkni qabul qilishingizni so’rayman:
A14: =""&'Общие данные'!B12&" tomonidan so’ralayotgan "&'Общие данные'!B81&" ("&'Общие данные'!B82&") oy muddatga, "&FIXED('Общие данные'!B75,0)&" ("&'Общие данные'!B76&") miqdoridagi "&'Общие данные'!B65&"ning ta’minoti sifatida menga mulk huquqi asosida tegishli bo’lgan "&'Общие данные'!B125&", "&'Общие данные'!B127&", "&'Общие данные'!B130&", "&'Общие данные'!B133&", avtotransport vositasini qabul qilishingizni so’rayman:" -> ANNAZAROV KAXRAMAN SADULLAYEVICH tomonidan so’ralayotgan 36 (Yigirma to'rt) oy muddatga, 100 000 000 (Yuz million so'm) miqdoridagi Mikroqarzning ta’minoti sifatida menga mulk huquqi asosida tegishli bo’lgan , kuzov turi - , kuzov raqami , dvigatel raqami , shassi raqami - , rangi - , ishlab chiqarilgan yili - , avtotransport vositasini qabul qilishingizni so’rayman:
A15: =""&'Общие данные'!B12&" tomonidan so’ralayotgan "&'Общие данные'!B81&" ("&'Общие данные'!B82&") oy muddatga, "&FIXED('Общие данные'!B75,0)&" ("&'Общие данные'!B76&") miqdoridagi "&'Общие данные'!B65&"ning ta’minoti sifatida menga mulk huquqi asosida tegishli bo’lgan "&'Общие данные'!C126&", umumiy maydoni "&'Общие данные'!C130&" va yashash maydoni "&'Общие данные'!C133&" "&'Общие данные'!C123&" manzilda joylashgan ko'chmas mulkni qabul qilishingizni so’rayman:" -> ANNAZAROV KAXRAMAN SADULLAYEVICH tomonidan so’ralayotgan 36 (Yigirma to'rt) oy muddatga, 100 000 000 (Yuz million so'm) miqdoridagi Mikroqarzning ta’minoti sifatida menga mulk huquqi asosida tegishli bo’lgan Yakka tartibdagi uy-joy, umumiy maydoni 213,72 va yashash maydoni 149,81 QORAQALPOG'ISTON RESPUBLIKASI TO'RTKO'L TUMANI YOSHLIK MFY KALTAMINAR KO'CHASI 1B-UY manzilda joylashgan ko'chmas mulkni qabul qilishingizni so’rayman:
B18: Sana:
A19: ='Общие данные'!C106 -> 0 | B19: ='Общие данные'!B2 -> 03.04.2026
A20: =IF('Общие данные'!B93="yo’q",CONCATENATE(A24," ",A28,A22),"")
A22: =" xususiy faoliyat ko'rsatuvchi notarius tomonidan "&'Общие данные'!B98&" "&'Общие данные'!B99&" berilgan ishonchnomaga asosan " -> xususiy faoliyat ko'rsatuvchi notarius tomonidan berilgan ishonchnomaga asosan
A24: ="№"&'Общие данные'!B100& "" -> №
A25: ='Общие данные'!B102 -> 00.01.1900
A26: =TEXT(A25,"ДД.ММ.ГГГГ") -> 00.01.1900
A27: . sanasidan
A28: =CONCATENATE(A26,A27) -> 00.01.1900. sanasidan

Sheet Акт согласования
A2: ="GAROV PREDMETI QIYMATINI KELISHISH №"&'Общие данные'!B141&" SONLI DALOLATNOMASI " -> GAROV PREDMETI QIYMATINI KELISHISH №1 SONLI DALOLATNOMASI
A4: Toshkent shahri | F4: ='Общие данные'!B142 -> 3 aprel 2026 y.
A6: =IF('Общие данные'!B103="ko'chmas mulk",'Акт согласования'!A10:F10,'Акт согласования'!A10:F10) -> «PULLOL BUSINESS MIKROMOLIYA TASHKILOTI» MChJning (1-tomon) vakili bo‘lgan To'rtko'l filiali boshlig’i Djumanazarov B.A., O‘zbekiston Respublikasi fuqarosi va garovga beruvchi ANNAZAROV KAXRAMAN SADULLAYEVICH (2-tomon) o’rtalarida, 3 aprel 2026 y.dan №310-TR-sonli Mikrokredit shartnomasiga muvofiq 1-tomon 2-tomonga berilgan Mikroqarz bo‘yicha ta’minot sifatida taqdim etilgan, 2-tomonga mulk huquqi asosida tegishli bo‘lgan mulkning garov qiymatini kelishish muzokaralari o’tkazildi.
A7: =IF('Общие данные'!B93="ha",'Акт согласования'!A9:F9,'Акт согласования'!A8:F8) -> «PULLOL BUSINESS MIKROMOLIYA TASHKILOTI» MChJning (1-tomon) vakili bo‘lgan To'rtko'l filiali boshlig’i Djumanazarov B.A., va O‘zbekiston Respublikasi fuqarosi ANNAZAROV KAXRAMAN SADULLAYEVICH (2-tomon) va garov egasi ANNAZAROV KAXRAMAN SADULLAYEVICH (3-tomon) 3 aprel 2026 y.dan №310-TR Mikrokredit shartnomasiga muvofiq 1-tomon 2-tomonga berilgan Mikroqarz bo‘yicha ta’minot sifatida taqdim etilgan, 2-tomonga mulk huquqi asosida tegishli bo‘lgan mulkning garov qiymatini kelishish muzokaralari o’tkazildi.
A8: =""&'Общие данные'!B147&"ning (1-tomon) vakili bo‘lgan "&'Общие данные'!A160&" "&'Общие данные'!B160&", va O‘zbekiston Respublikasi fuqarosi "&'Общие данные'!B5&" (2-tomon) va garov egasi "&'Общие данные'!C117&" (3-tomon) "&'Общие данные'!B74&" "&'Общие данные'!C64&" shartnomasiga muvofiq 1-tomon 2-tomonga berilgan "&'Общие данные'!B65&" bo‘yicha ta’minot sifatida taqdim etilgan, 2-tomonga mulk huquqi asosida tegishli bo‘lgan mulkning garov qiymatini kelishish muzokaralari o’tkazildi. " -> «PULLOL BUSINESS MIKROMOLIYA TASHKILOTI» MChJning (1-tomon) vakili bo‘lgan To'rtko'l filiali boshlig’i Djumanazarov B.A., va O‘zbekiston Respublikasi fuqarosi ANNAZAROV KAXRAMAN SADULLAYEVICH (2-tomon) va garov egasi ANNAZAROV KAXRAMAN SADULLAYEVICH (3-tomon) 3 aprel 2026 y.dan №310-TR Mikrokredit shartnomasiga muvofiq 1-tomon 2-tomonga berilgan Mikroqarz bo‘yicha ta’minot sifatida taqdim etilgan, 2-tomonga mulk huquqi asosida tegishli bo‘lgan mulkning garov qiymatini kelishish muzokaralari o’tkazildi.
A9: =""&'Общие данные'!B147&"ning (1-tomon) vakili bo‘lgan "&'Общие данные'!A160&" "&'Общие данные'!B160&", va O‘zbekiston Respublikasi fuqarosi "&'Общие данные'!B5&" (2-tomon) va garov egasi "&'Общие данные'!C117&" (3-tomon) "&'Общие данные'!B74&" "&'Общие данные'!C64&" shartnomasiga muvofiq 1-tomon 2-tomonga berilgan "&'Общие данные'!B65&" bo‘yicha ta’minot sifatida taqdim etilgan, 2-tomonga mulk huquqi asosida tegishli bo‘lgan mulkning garov qiymatini kelishish muzokaralari o’tkazildi. " -> «PULLOL BUSINESS MIKROMOLIYA TASHKILOTI» MChJning (1-tomon) vakili bo‘lgan To'rtko'l filiali boshlig’i Djumanazarov B.A., va O‘zbekiston Respublikasi fuqarosi ANNAZAROV KAXRAMAN SADULLAYEVICH (2-tomon) va garov egasi ANNAZAROV KAXRAMAN SADULLAYEVICH (3-tomon) 3 aprel 2026 y.dan №310-TR Mikrokredit shartnomasiga muvofiq 1-tomon 2-tomonga berilgan Mikroqarz bo‘yicha ta’minot sifatida taqdim etilgan, 2-tomonga mulk huquqi asosida tegishli bo‘lgan mulkning garov qiymatini kelishish muzokaralari o’tkazildi.
A10: =IF('Общие данные'!B93="ha",'Акт согласования'!A12:F12,'Акт согласования'!A11:F11) -> «PULLOL BUSINESS MIKROMOLIYA TASHKILOTI» MChJning (1-tomon) vakili bo‘lgan To'rtko'l filiali boshlig’i Djumanazarov B.A., O‘zbekiston Respublikasi fuqarosi va garovga beruvchi ANNAZAROV KAXRAMAN SADULLAYEVICH (2-tomon) o’rtalarida, 3 aprel 2026 y.dan №310-TR-sonli Mikrokredit shartnomasiga muvofiq 1-tomon 2-tomonga berilgan Mikroqarz bo‘yicha ta’minot sifatida taqdim etilgan, 2-tomonga mulk huquqi asosida tegishli bo‘lgan mulkning garov qiymatini kelishish muzokaralari o’tkazildi.
A11: =""&'Общие данные'!B147&"ning (1-tomon) vakili bo‘lgan "&'Общие данные'!A160&" "&'Общие данные'!B150&", O‘zbekiston Respublikasi fuqarosi "&'Общие данные'!B5&" (2-tomon) va garovga beruvchi O‘zbekiston Respublikasi fuqarosi "&'Общие данные'!B117&" (3-tomon) o’rtalarida, "&'Общие данные'!B74&"-sonli "&'Общие данные'!C64&" shartnomasiga muvofiq 1-tomon 2-tomonga berilgan "&'Общие данные'!B65&" bo‘yicha ta’minot sifatida taqdim etilgan, 3-tomonga mulk huquqi asosida tegishli bo‘lgan mulkning garov qiymatini kelishish muzokaralari o’tkazildi." -> «PULLOL BUSINESS MIKROMOLIYA TASHKILOTI» MChJning (1-tomon) vakili bo‘lgan To'rtko'l filiali boshlig’i Obidov A. Sh., O‘zbekiston Respublikasi fuqarosi ANNAZAROV KAXRAMAN SADULLAYEVICH (2-tomon) va garovga beruvchi O‘zbekiston Respublikasi fuqarosi ANNAZAROV KAXRAMAN SADULLAYEVICH (3-tomon) o’rtalarida, 3 aprel 2026 y.dan №310-TR-sonli Mikrokredit shartnomasiga muvofiq 1-tomon 2-tomonga berilgan Mikroqarz bo‘yicha ta’minot sifatida taqdim etilgan, 3-tomonga mulk huquqi asosida tegishli bo‘lgan mulkning garov qiymatini kelishish muzokaralari o’tkazildi.
A12: =""&'Общие данные'!B147&"ning (1-tomon) vakili bo‘lgan "&'Общие данные'!A160&" "&'Общие данные'!B160&", O‘zbekiston Respublikasi fuqarosi va garovga beruvchi "&'Общие данные'!B5&" (2-tomon) o’rtalarida, "&'Общие данные'!B74&"-sonli "&'Общие данные'!C64&" shartnomasiga muvofiq 1-tomon 2-tomonga berilgan "&'Общие данные'!B65&" bo‘yicha ta’minot sifatida taqdim etilgan, 2-tomonga mulk huquqi asosida tegishli bo‘lgan mulkning garov qiymatini kelishish muzokaralari o’tkazildi." -> «PULLOL BUSINESS MIKROMOLIYA TASHKILOTI» MChJning (1-tomon) vakili bo‘lgan To'rtko'l filiali boshlig’i Djumanazarov B.A., O‘zbekiston Respublikasi fuqarosi va garovga beruvchi ANNAZAROV KAXRAMAN SADULLAYEVICH (2-tomon) o’rtalarida, 3 aprel 2026 y.dan №310-TR-sonli Mikrokredit shartnomasiga muvofiq 1-tomon 2-tomonga berilgan Mikroqarz bo‘yicha ta’minot sifatida taqdim etilgan, 2-tomonga mulk huquqi asosida tegishli bo‘lgan mulkning garov qiymatini kelishish muzokaralari o’tkazildi.
A13: ="Garov predmeti sifatida "&'Общие данные'!B125&", 3-tomonga egalik huquqi tegishli bo'lgan, quyidagi tafsilotlarga ega avtotransport vositasi taqdim etiladi:" -> Garov predmeti sifatida , 3-tomonga egalik huquqi tegishli bo'lgan, quyidagi tafsilotlarga ega avtotransport vositasi taqdim etiladi:
A14: ="Garov predmeti sifatida "&'Общие данные'!B125&", 2-tomonga egalik huquqi tegishli bo'lgan, quyidagi tafsilotlarga ega avtotransport vositasi taqdim etiladi:" -> Garov predmeti sifatida , 2-tomonga egalik huquqi tegishli bo'lgan, quyidagi tafsilotlarga ega avtotransport vositasi taqdim etiladi:
A15: =IF('Общие данные'!B93="ha",'Акт согласования'!A14:F14,'Акт согласования'!A13:F13) -> Garov predmeti sifatida , 2-tomonga egalik huquqi tegishli bo'lgan, quyidagi tafsilotlarga ega avtotransport vositasi taqdim etiladi:
A16: ="Garov predmeti sifatida "&'Общие данные'!C126&", 2-tomonga egalik huquqi tegishli bo'lgan, quyidagi tafsilotlarga ega ko'chmas mulk taqdim etiladi:" -> Garov predmeti sifatida Yakka tartibdagi uy-joy, 2-tomonga egalik huquqi tegishli bo'lgan, quyidagi tafsilotlarga ega ko'chmas mulk taqdim etiladi:
A17: ="Garov predmeti sifatida "&'Общие данные'!C126&", 3-tomonga egalik huquqi tegishli bo'lgan, quyidagi tafsilotlarga ega ko'chmas mulk taqdim etiladi:" -> Garov predmeti sifatida Yakka tartibdagi uy-joy, 3-tomonga egalik huquqi tegishli bo'lgan, quyidagi tafsilotlarga ega ko'chmas mulk taqdim etiladi:
A18: =IF('Общие данные'!B93="ha",'Акт согласования'!A16:F16,'Акт согласования'!A17:F17) -> Garov predmeti sifatida Yakka tartibdagi uy-joy, 2-tomonga egalik huquqi tegishli bo'lgan, quyidagi tafsilotlarga ega ko'chmas mulk taqdim etiladi:
A19: =IF('Общие данные'!B103="Avtotransport",'Акт согласования'!A15:F15,'Акт согласования'!A18:F18) -> Garov predmeti sifatida Yakka tartibdagi uy-joy, 2-tomonga egalik huquqi tegishli bo'lgan, quyidagi tafsilotlarga ega ko'chmas mulk taqdim etiladi:
A20: Nomi | B20: Umumiy yer maydoni, (m2) | D20: Qurilish osti maydoni, (m2) | E20: Umumiy foydali maydoni, (m2) | F20: Yashash maydoni, (m2)
A21: ='Общие данные'!C125 -> Yakka tartibdagi uy-joy | B21: ='Общие данные'!C134 -> 704 | D21: ='Общие данные'!C133 -> 149.81 | E21: ='Общие данные'!C130 -> 213.72 | F21: ='Общие данные'!C131 -> 108.36
A22: ="-* avtotransport egasi: "&'Общие данные'!B117&"" -> -* avtotransport egasi: ANNAZAROV KAXRAMAN SADULLAYEVICH
A23: ="-* texnik pasport: "&'Общие данные'!B124&"" -> -* texnik pasport:
A24: ="-* roʻyxatdan oʻtgan manzili/garaj manzili: "&'Общие данные'!B122&"" -> -* roʻyxatdan oʻtgan manzili/garaj manzili: QORAQALPOG'ISTON RESPUBLIKASI TO'RTKO'L TUMANI YOSHLIK MFY KALTAMINAR KO'CHASI 1B-UY
A25: ="-* davlat raqami: "&'Общие данные'!B126&"" -> -* davlat raqami:
A27: Nomi | D27: Umumiy foydali maydoni | E27: Yashash maydoni | F27: Umumiy maydoni
A28: Yashash xona | D28: 3 | E28: 18.82
A29: Umumiy maydon | D29: 43.96 | E29: 18.82 | F29: 43.96
E30: 0 | F30: =D30+E30 -> 0
E31: 0 | F31: =D31+E31 -> 0
E32: 0 | F32: =D32+E32 -> 0
E33: 0 | F33: =D33+E33 -> 0
F34: =D34+E34 -> 0
E35: 0 | F35: =D35+E35 -> 0
F36: =D36+E36 -> 0
F37: =D37+E37 -> 0
A38: JAMI | D38: =D29 -> 43.96 | E38: =E28 -> 18.82 | F38: =F29 -> 43.96
A39: ="-* ko'chmas mulk egasi: "&'Общие данные'!C117&"" -> -* ko'chmas mulk egasi: ANNAZAROV KAXRAMAN SADULLAYEVICH
A40: ="-* reestr raqami: "&'Общие данные'!C124&"" -> -* reestr raqami: №1735233/Y-26004624
A41: ="-* kadastr raqami: "&'Общие данные'!C127&"" -> -* kadastr raqami: 01.04.2026 y. №23:08:40:01:04:0357
A42: ="-* manzil: "&'Общие данные'!C123&"" -> -* manzil: QORAQALPOG'ISTON RESPUBLIKASI TO'RTKO'L TUMANI YOSHLIK MFY KALTAMINAR KO'CHASI 1B-UY
