Workbook
Name mos: '[1]Общие данные'!$C$23:$D$23
Name mos: '[2]Общие данные'!$C$23:$D$23
Name mulk: '[1]Общие данные'!$C$24:$W$24
Name mulk: '[2]Общие данные'!$C$24:$W$24

Sheet protokol
A1: =""&umumiy_malumot!B158&" mikromoliya tashkiloti Kredit qo‘mitasining yig‘ilishi" -> «PULLOL BUSINESS MIKROMOLIYA TASHKILOTI» MChJ mikromoliya tashkiloti Kredit qo‘mitasining yig‘ilishi
A2: =""&I7&" protokolidan ko'chirma" -> № 110 protokolidan ko'chirma
A3: Toshkent shahri | F3: =umumiy_malumot!B68 -> 16 fevral 2026 y.
B4: KUN TARTIBI:
A5: =" "&I8&"."&umumiy_malumot!B5&" ga "&umumiy_malumot!B65&" berish masalasini ko‘rib chiqish to‘g‘risida." -> 1.NORINBOYEVA SOXIBA IZZATILLAYEVNA ga mikrokredit berish masalasini ko‘rib chiqish to‘g‘risida.
A7: =" "&I9&" masala yuzasidan: "&umumiy_malumot!B158&" mikromoliya tashkiloti kredit bo‘yicha menejeri "&umumiy_malumot!B5&"ga "&FIXED(umumiy_malumot!B76)&" ("&umumiy_malumot!B77&") so‘m miqdorida, muddati "&umumiy_malumot!B82&" ("&umumiy_malumot!B83&") oyga va yillik "&umumiy_malumot!B86&" %("&umumiy_malumot!B87&") foiz miqdorida "&umumiy_malumot!B65&" berich bo‘yicha "&umumiy_malumot!B5&"ning kredit arizasi va "&umumiy_malumot!B158&"ning xulosasi bilan ishtirokchilarni tanishtirdi." -> Birinchi masala yuzasidan: «PULLOL BUSINESS MIKROMOLIYA TASHKILOTI» MChJ mikromoliya tashkiloti kredit bo‘yicha menejeri NORINBOYEVA SOXIBA IZZATILLAYEVNAga 175 000 000,00 (yuz yetmish besh million so'm) so‘m miqdorida, muddati 36 (O'ttiz olti ) oyga va yillik 55 %(Ellik besh ) foiz miqdorida mikrokredit berich bo‘yicha NORINBOYEVA SOXIBA IZZATILLAYEVNAning kredit arizasi va «PULLOL BUSINESS MIKROMOLIYA TASHKILOTI» MChJning xulosasi bilan ishtirokchilarni tanishtirdi. | H7: Protokol raqami | I7: =umumiy_malumot!B1 -> № 110
H8: Savol raqami | I8: 1 | J8: 1 | K8: 2 | L8: 3 | M8: 4 | N8: 5 | O8: 6 | P8: 7 | Q8: 8 | R8: 9 | S8: 10 | T8: 11 | U8: 12 | V8: 13 | W8: 14 | X8: 15 | Y8: 16 | Z8: 17 | AA8: 18 | AB8: 19 | AC8: 20 | AD8: 21 | AE8: 22 | AF8: 23 | AG8: 24 | AH8: 25
H9: Savol raqami qol bilan | I9: =IF(I8=J8,J9,IF(I8=K8,K9,IF(I8=L8,L9,IF(I8=M8,M9,IF(I8=N8,N9,IF(I8=O8,O9,IF(I8=P8,P9,IF(I8=Q8,Q9,IF(I8=R8,R9,IF(I8=S8,S9,IF(I8=T8,T9,IF(I8=U8,U9,IF(I8=V8,V9,IF(I8=W8,W9,IF(I8=X8,X9,IF(I8=Y8,Y9,IF(I8=Z8,Z9,IF(I8=AA8,AA9,IF(I8=AB8,AB9,IF(I8=AC8,AC9,IF(I8=AD8,AD9,IF(I8=AE8,AE9,IF(I8=AF8,AF9,IF(I8=AG8,AG9,IF(I8=AH8,AH9))))))))))))))))))))))))) -> Birinchi | J9: Birinchi | K9: Ikkinchi | L9: Uchinchi | M9: To'rtinchi | N9: Beshinchi | O9: O'ltinchi | P9: Yettinchi | Q9: Sakkizinchi | R9: Tuqqizinchi | S9: O'ninchi | T9: O'n birinchi | U9: O'n ikkinchi | V9: O'n uchinchi | W9: O'n to'rtinchi | X9: O'n beshinchi | Y9: O'n oltinchi | Z9: O'n yettinchi | AA9: O'n sakkizinchi | AB9: O'n tuqqizinchi | AC9: Yigirmanchi | AD9: Yigirma birinchi | AE9: Yigizma ikkinchi | AF9: Yigirma uchinchi | AG9: Yigirma to'rtinchi | AH9: Yigirma beshinchi
A11: =""&umumiy_malumot!C64&" ta’minoti:" -> Mikrokredit ta’minoti:
A13: =xulosa!A18:E18 -> 1. Egalik huquqi NORINBAYEVA SAPURA MAMADALIYEVNAga tegishli bo'lgan umumiy yer maydoni - 700,qurilish osti maydoni-340.11, umumiy foydali maydoni-114.59, yashash maydoni - 163.19 Yakka tartibdagi uy-joy, TOSHKENT VILOYATI CHINOZ TUMANI ALISHER NAVOIY MFY SOBIR RAHIMOV KO'CHASI 36 UY
A14: ="2. «"&umumiy_malumot!B154&"» АJ sug‘urta kompaniyasi tomonidan Mikroqarz to'lamaslik xavfini "&FIXED(umumiy_malumot!B155,2)&"("&umumiy_malumot!B156&") so ' m miqdoriga sug’urta qilish" -> 2. «АО СК "IMPEX INSURANCE"» АJ sug‘urta kompaniyasi tomonidan Mikroqarz to'lamaslik xavfini 35 000 000,00(o'ttiz besh million so'm) so ' m miqdoriga sug’urta qilish
D15: masala yuzasidan berilgan ma’lumotlarni muhokama qilib, Kredit qo‘mitasi a’zolariga taqdim etilgan zarur hujjatlarni o‘rganib, majlisda ishtirok etgan Kredit qo‘mitasi a’zolarining taklif va mulohazalarini inobatga olgan holda | E15: =""&umumiy_malumot!B158&" kredit qo‘mitasi" -> «PULLOL BUSINESS MIKROMOLIYA TASHKILOTI» MChJ kredit qo‘mitasi | F15: =CONCATENATE(D15,E15) -> masala yuzasidan berilgan ma’lumotlarni muhokama qilib, Kredit qo‘mitasi a’zolariga taqdim etilgan zarur hujjatlarni o‘rganib, majlisda ishtirok etgan Kredit qo‘mitasi a’zolarining taklif va mulohazalarini inobatga olgan holda «PULLOL BUSINESS MIKROMOLIYA TASHKILOTI» MChJ kredit qo‘mitasi
A16: =CONCATENATE(I9,F15) -> Birinchi masala yuzasidan berilgan ma’lumotlarni muhokama qilib, Kredit qo‘mitasi a’zolariga taqdim etilgan zarur hujjatlarni o‘rganib, majlisda ishtirok etgan Kredit qo‘mitasi a’zolarining taklif va mulohazalarini inobatga olgan holda «PULLOL BUSINESS MIKROMOLIYA TASHKILOTI» MChJ kredit qo‘mitasi
A17: QAROR QILADI:
A18: =" "&umumiy_malumot!B5&"ga quyidagi shartlarda "&umumiy_malumot!B65&" berish masalasi ma’qullansin:" -> NORINBOYEVA SOXIBA IZZATILLAYEVNAga quyidagi shartlarda mikrokredit berish masalasi ma’qullansin:
A19: ="1. "&umumiy_malumot!C64&" summasi: "&FIXED(umumiy_malumot!B76)&" ("&umumiy_malumot!B77&") so'm." -> 1. Mikrokredit summasi: 175 000 000,00 (yuz yetmish besh million so'm) so'm.
A20: ="2. "&umumiy_malumot!C64&" muddati: "&umumiy_malumot!B82&" ("&umumiy_malumot!B83&") oy " -> 2. Mikrokredit muddati: 36 (O'ttiz olti ) oy
A21: ="3. "&umumiy_malumot!C64&"dan foydalanganlik uchun foiz stavkasi:yillik "&umumiy_malumot!B86&"% ("&umumiy_malumot!B87&") foiz." -> 3. Mikrokreditdan foydalanganlik uchun foiz stavkasi:yillik 55% (Ellik besh ) foiz.
A22: ="4. "&umumiy_malumot!C64&" bo‘yicha asosiy qarz va foizlarni to‘lash:" -> 4. Mikrokredit bo‘yicha asosiy qarz va foizlarni to‘lash:
A23: =kredit_ariza!A19:D19 -> - mikrokredit shartnomasi bo'yicha har oy differensial to'lovlari amalga oshiriladi
A24: ="5. "&umumiy_malumot!C64&" bo‘yicha ta'minot:" -> 5. Mikrokredit bo‘yicha ta'minot:
A25: ="1. garov "&xulosa!A29:E29&"" -> 1. garov - NORINBAYEVA SAPURA MAMADALIYEVNA ga mulk huquqi asosida tegishli ko'chmas mulk shaklida Yakka tartibdagi uy-joy, manzili: TOSHKENT VILOYATI CHINOZ TUMANI ALISHER NAVOIY MFY SOBIR RAHIMOV KO'CHASI 36 UY, quyidagi tafsilotlarga muvofiq:
A26: =dalolatnoma!A29 -> Nomi | B26: =dalolatnoma!B29 -> Umumiy yer maydoni, (m2) | C26: =dalolatnoma!C29 -> Qurilish osti maydoni, (m2) | D26: =dalolatnoma!D29 -> Umumiy foydali maydoni, (m2) | E26: =dalolatnoma!E29 -> Yashash maydoni, (m2) | F26: =dalolatnoma!F29 -> Kelishilgan garov qiymati, so'm
A27: =dalolatnoma!A30 -> Yakka tartibdagi uy-joy | B27: =dalolatnoma!B30 -> 700 | C27: =dalolatnoma!C30 -> 340.11 | D27: =dalolatnoma!D30 -> 163.19 | E27: =dalolatnoma!E30 -> 114.59 | F27: =dalolatnoma!F30 -> 210 000 000,00 (ikki yuz o'n million so'm)
A28: =dalolatnoma!A22:F22 -> -* ko'chmas mulk egasi: NORINBAYEVA SAPURA MAMADALIYEVNA
A29: =dalolatnoma!A23:F23 -> -* reest raqami: №1727256/Y-25006342
A30: =dalolatnoma!A24:F24 -> -* kadastr raqami: 13.08.2025 y. №11:13:42:02:01:1840
A31: =dalolatnoma!A25:F25 -> -* manzili: TOSHKENT VILOYATI CHINOZ TUMANI ALISHER NAVOIY MFY SOBIR RAHIMOV KO'CHASI 36 UY
A33: ="6. «"&umumiy_malumot!B154&"» АJ sug‘urta kompaniyasi tomonidan "&umumiy_malumot!C64&" to'lamaslik xavfini "&FIXED(umumiy_malumot!B155,2)&"("&umumiy_malumot!B156&") so ' m miqdoriga sug’urta qilish" -> 6. «АО СК "IMPEX INSURANCE"» АJ sug‘urta kompaniyasi tomonidan Mikrokredit to'lamaslik xavfini 35 000 000,00(o'ttiz besh million so'm) so ' m miqdoriga sug’urta qilish
A34: ="7. Boshqa shartlar – "&IF(umumiy_malumot!B110=umumiy_malumot!B111,"avtotransport vositasi",IF(umumiy_malumot!B110=umumiy_malumot!C111,"ko'chmas mulk",0))&" shaklida garov ta'minlangandan keyin "&umumiy_malumot!B65&" berish." -> 7. Boshqa shartlar – ko'chmas mulk shaklida garov ta'minlangandan keyin mikrokredit berish.
A36: Qaror bir ovozdan qabul qilindi.
A41: =umumiy_malumot!B158&" direktori" -> «PULLOL BUSINESS MIKROMOLIYA TASHKILOTI» MChJ direktori | E41: A.Obidov
A45: =umumiy_malumot!A170 -> Kreditlash bo’limi boshlig’i | E45: =umumiy_malumot!B170 -> Akramov R.N.
A48: =umumiy_malumot!A171 -> Monitoring bo’limi boshlig’i | E48: =umumiy_malumot!B171 -> Omanlikov O.O.
A49: =umumiy_malumot!A172 -> Kredit bo'limi menejeri | E49: =umumiy_malumot!B172 -> Eshbekov S. O.

Sheet umumiy_malumot
A1: =CONCATENATE(B65," olish uchun ariza") -> mikrokredit olish uchun ariza | B1: № 110
A2: =CONCATENATE(B65," olish uchun ariza sanasi QO’L BILAN KIRITILADI") -> mikrokredit olish uchun ariza sanasi QO’L BILAN KIRITILADI | B2: 16.02.2026 | D2: =180+B2 -> 46249
A4: Qarz oluvchi bo’yicha ma’lumotlar
A5: Ariza beruvchining FISh (kim? – Ibragimov Rustam Sadikovich) | B5: NORINBOYEVA SOXIBA IZZATILLAYEVNA
A6: agar o’zgarishlar bo’lgan bo’lsa oldingi FISh (Sadikov Rustam Sadikovich yoki yo’q) | B6: yoq | C6: ha | D6: yo’q
A7: Ariza beruvchining FISh (kim? – Ibragimov R.S.) | B7: NORINBOYEVA S.I.
A8: FISh (ariza kimdan? – Ibragimov Rustam Sadikovichdan) | B8: =B5 -> NORINBOYEVA SOXIBA IZZATILLAYEVNA
A9: FISh (kimdan? – Ibragimov R.S.dan) | B9: =B7 -> NORINBOYEVA S.I.
A10: FISh (kimga? – Ibragimov Rustam Sadikovichga) | B10: =B8 -> NORINBOYEVA SOXIBA IZZATILLAYEVNA
A11: FISh (kimga? – Ibragimov R.S.ga) | B11: =B9 -> NORINBOYEVA S.I.
A12: FISh (kim bilan? – Ibragimov Rustam Sadikovich bilan) | B12: =B10 -> NORINBOYEVA SOXIBA IZZATILLAYEVNA
A13: FISh (kim bilan? – Ibragimov R.S. bilan) | B13: =B11 -> NORINBOYEVA S.I.
A14: Fuqaroligi (O’zbekiston Respublikasi) | B14: O’zbekiston Respublikasi
A15: Tug’ilgan sanasi (01.10.2011 yil) | B15: 19.10.1985 yil
A16: Pasport seriyasi (СА №1234567) | B16: AE 5547691
B17: IIV 27256 | D17: =TEXT(C17,"ДД.ММ.ГГГГ") -> 00.01.1900
B18: 46013 | C18: =TEXT(B18,"ДД.ММ.ГГГГ") -> 22.12.2025
B19: =DATE(YEAR(B18)+10,MONTH(B18),DAY(B18)-1) -> 49664 | C19: =TEXT(B19,"ДД.ММ.ГГГГ") -> 21.12.2035
A20: Kim va qachon berilgan (Toshkent shahri Chilonzor IIB tomonidan 2011 yil __.____) | B20: =""&B17&" tomonidan "&C18&" yilda berilgan" -> IIV 27256 tomonidan 22.12.2025 yilda berilgan | C20: =""&B17&" tomonidan "&C18&" yilda berilgan" -> IIV 27256 tomonidan 22.12.2025 yilda berilgan
A21: Pasportni amal qilish muddati (01.10.2011 yilgacha / yoki muddatsiz) | B21: =""&C19&" y." -> 21.12.2035 y. | C21: =""&C19&" yilgacha" -> 21.12.2035 yilgacha
A22: doimiy ro’yhatdan o’tgan joyi (Toshkent sh., Mirobod tumani, Nukus ko’chasi, 1 uy, 1 honadon) | B22: TOSHKENT VILOYATI CHINOZ TUMANI ALISHER NAVOIY MFY SOBIR RAHIMOV KO'CHASI 36 UY | C22: =TEXT(B19,"ДД.ММ.ГГГГ") -> 21.12.2035
A23: doimiy ro’yhatdan o’tgan joyi haqiqatdagi turar joyi bilan mos keladi/mos kelmaydi | B23: mos keladi | C23: mos keladi | D23: mos kelmaydi
A24: Ro’yhatdan o’tish joyida yashash asosi | B24: Mulk huquqi | C24: Mulk huquqi | D24: ijara | E24: служебная | F24: другое | G24: -
A25: Telefon raqami kod bilan ((99871) 277 77 77) | B25: 33 730 30 31 MIJOZ
A26: Mo’ljal | B26: 1 MAKTAB BALNITSA CHINOZ
B27: =IF(B23="mos keladi",B22,B28) -> TOSHKENT VILOYATI CHINOZ TUMANI ALISHER NAVOIY MFY SOBIR RAHIMOV KO'CHASI 36 UY
A28: Haqiqatdagi yashash joyi (Toshkent sh., Mirobod tumani, Nukus ko’chasi, 1 uy, 1 honadon) | B28: TOSHKENT VILOYATI CHINOZ TUMANI ALISHER NAVOIY MFY SOBIR RAHIMOV KO'CHASI 36 UY
A29: Haqiqatdagi yashash joyida turish asosi | B29: Mulk huquqi | C29: Mulk huquqi | D29: ijara | E29: xizmat | F29: boshqa | G29: -
A30: Mijozning jinsi | B30: ayol | C30: erkak | D30: ayol
A31: Tug’ilgan joyi (Toshkent) | B31: CHINOZ TUMANI
A32: Fuqaroligi (O’zbekiston Respublikasi) | B32: O’zbekiston Respublikasi
A33: Telefon raqami kod bilan ((99871) 277 77 77) | B33: =B25 -> 33 730 30 31 MIJOZ
B34: =IF(B23="mos keladi",B26,B35) -> 1 MAKTAB BALNITSA CHINOZ
A35: Mo’ljal
A36: Oilaviy ahvoli
A37: Oila a'zolari soni (jami):
A38: Ma’lumoti
A39: Mutaxassisligi
A40: Ish telefoni raqami kod bilan ((99890) 3270000) | B40: =B25 -> 33 730 30 31 MIJOZ
A41: Mobil telefon raqami kod bilan ((99890) 3270000) | B41: 99 407 50 08 UY EGASI
A42: Ish telefoni raqami kod bilan ((99890) 3270000) | B42: 94 659 57 51 ADASI
A43: Mobil telefon raqami kod bilan ((99890) 3270000)
A44: Asosiy ish joyi | B44: O'Z O'ZINI BAND QILGAN FUQARO | C44: Yakka tartibdagi tadbirkor | D44: O'Z O'ZINI BAND QILGAN FUQARO
B45: =IF(B44=D44,CONCATENATE("MA'LUMOTNOMA ",B47,B46),C44) -> MA'LUMOTNOMA №0012660051
A46: O'Z O'ZINI BAND QILGAN BO'LSA, MA'LUMOTNOMA KIRITING | B46: №0012660051
C47: №
A48: AGAR O'Z O'ZINI BAND QILGAN FUQARO BO'LSA FAOLIYAT TURINI KIRITING | B48: BOLALAR O'YINCHOGINI ISHLAB CHIQARISH (UY SHAROITIDA)
A49: Lavozimi | B49: =IF(B44=C44,C44,B48) -> BOLALAR O'YINCHOGINI ISHLAB CHIQARISH (UY SHAROITIDA)
A50: Tashkilotning haqiqiy manzili (Toshkent sh., Mirobod tumani, Nukus ko’chasi, 1 uy, 1 honadon)
A51: Mo’ljal
A52: Ish staji, sanasidan (01.10.2011 yildan)
A53: Umumiy mehnat staji (3 yil/ 5 yil)
A54: Ish joyi telefon raqami
A55: Mijozning STIRi
A56: Mijozning unikal kodi | B56: 990000__
A57: QARZ OLUVCHINING ISH JOYI, LAVOZIMI VA O'RTACHA OYLIK DAROMADI
A58: Ish joyi | B58: =IF(B44=C44,C44,CONCATENATE(B44," ",B47)) -> O'Z O'ZINI BAND QILGAN FUQARO
A59: Lavozimi | B59: =B49 -> BOLALAR O'YINCHOGINI ISHLAB CHIQARISH (UY SHAROITIDA)
A60: O’rtacha oylik daromadi | B60: 20000000 | C60: =C63/B76 -> 0.45640791
A61: Mijozning boshqa daromadlari | B61: 10000000 | C61: Процент годовой
A62: Ishning davomiyligi | B62: =B53 -> 0
A63: Ish joyidan ma’lumotnomaning raqami va sanasi | C63: =SUM(grafik!E9:E20) -> 79871385
A64: Kredit bo’yicha parametrlar | C64: =PROPER(B65) -> Mikrokredit | D64: =UPPER(B65) -> MIKROKREDIT
A65: Kredit turi | B65: =IF(B76>100000001,"mikrokredit",IF(B76<100000001,"mikroqarz",0)) -> mikrokredit | C65: =DATE(YEAR(B67),MONTH(B67)+B82,DAY(B67)) -> 47165
A66: Kredit shartnomasi raqami | B66: =B1 -> № 110 | C66: =MONTH(C65) -> 2 | D66: =IF(C66=C68,C70,IF(C66=D68,D70,IF(C66=E68,E70,IF(C66=F68,F70,IF(C66=G68,G70,IF(C66=H68,H70,IF(C66=I68,I70,IF(C66=J68,J70,IF(C66=K68,K70,IF(C66=L68,L70,IF(C66=M68,M70,IF(C66=N68,N70,)))))))))))) -> fevral | E66: =DAY(C65) -> 16 | F66: =YEAR(C65) -> 2029 | G66: =MONTH(C65) -> 2 | H66: =IF(C66=C68,C71,IF(C66=D68,D71,IF(C66=E68,E71,IF(C66=F68,F71,IF(C66=G68,G71,IF(C66=H68,H71,IF(C66=I68,I71,IF(C66=J68,J71,IF(C66=K68,K71,IF(C66=L68,L71,IF(C66=M68,M71,IF(C66=N68,N71,)))))))))))) -> fevral | I66: =YEAR(C65) -> 2029
A67: Kredit shartnomasi sanasi (14.10.2011) | B67: =B2 -> 16.02.2026 | C67: =MONTH(B67) -> 2 | D67: =IF(C67=C68,C70,IF(C67=D68,D70,IF(C67=E68,E70,IF(C67=F68,F70,IF(C67=G68,G70,IF(C67=H68,H70,IF(C67=I68,I70,IF(C67=J68,J70,IF(C67=K68,K70,IF(C67=L68,L70,IF(C67=M68,M70,IF(C67=N68,N70,)))))))))))) -> fevral | E67: =DAY(B67) -> 16 | F67: =YEAR(B67) -> 2026 | G67: =MONTH(B67) -> 2 | H67: =IF(C67=C68,C71,IF(C67=D68,D71,IF(C67=E68,E71,IF(C67=F68,F71,IF(C67=G68,G71,IF(C67=H68,H71,IF(C67=I68,I71,IF(C67=J68,J71,IF(C67=K68,K71,IF(C67=L68,L71,IF(C67=M68,M71,IF(C67=N68,N71,)))))))))))) -> fevral | I67: =YEAR(B67) -> 2026
A68: Kredit shartnomasi sanasi (14.10.2011 y.) | B68: =""&E67&" "&D67&" "&F67&" y." -> 16 fevral 2026 y. | C68: 1 | D68: 2 | E68: 3 | F68: 4 | G68: 5 | H68: 6 | I68: 7 | J68: 8 | K68: 9 | L68: 10 | M68: 11 | N68: 12
B69: =""&E67&" "&H67&" "&F67&" y." -> 16 fevral 2026 y.
B70: =B68 -> 16 fevral 2026 y. | C70: yanvar | D70: fevral | E70: mart | F70: aprel | G70: may | H70: iyun | I70: iyul | J70: avgust | K70: sentabr | L70: oktabr | M70: noyabr | N70: dekabr
B71: =B69 -> 16 fevral 2026 y. | C71: yanvar | D71: fevral | E71: mart | F71: aprel | G71: may | H71: iyun | I71: iyul | J71: avgust | K71: sentabr | L71: oktabr | M71: noyabr | N71: dekabr
A72: Tugash sanasi QO’L BILAN KIRITILADI | B72: =""&E66&" "&D66&" "&F66&" y." -> 16 fevral 2029 y.
B73: =""&E66&" "&H66&" "&F66&" y." -> 16 fevral 2029 y.
A74: Kredit shartnomasi raqami va sanasi | B74: =""&B68&"dan "&B66&"" -> 16 fevral 2026 y.dan № 110
A75: =CONCATENATE(B65," miqdori (summasi)") -> mikrokredit miqdori (summasi) | B75: 150000000 | C75: =+B76*1.4 -> 2.45e+08 | D75: =""&SUBSTITUTE(SUBSTITUTE(SUBSTITUTE(TRIM(SUBSTITUTE(SUBSTITUTE(SUBSTITUTE(SUBSTITUTE(SUBSTITUTE(SUBSTITUTE(SUBSTITUTE(SUBSTITUTE(SUBSTITUTE(SUBSTITUTE(SUBSTITUTE(SUBSTITUTE(SUBSTITUTE(SUBSTITUTE(SUBSTITUTE(SUBSTITUTE(SUBSTITUTE(SUBSTITUTE(SUBSTITUTE(SUBSTITUTE(SUBSTITUTE(SUBSTITUTE(SUBSTITUTE(SUBSTITUTE(SUBSTITUTE(SUBSTITUTE(SUBSTITUTE(SUBSTITUTE(SUBSTITUTE(SUBSTITUTE(SUBSTITUTE(SUBSTITUTE(SUBSTITUTE(SUBSTITUTE(SUBSTITUTE(SUBSTITUTE(SUBSTITUTE(SUBSTITUTE(SUBSTITUTE(SUBSTITUTE(SUBSTITUTE(SUBSTITUTE(SUBSTITUTE(SUBSTITUTE(IF(LEN(INT(C75))>6,ROMAN(MID(INT(C75),1,LEN(INT(C75))-6)+0)&" million "&ROMAN(MID(INT(C75),LEN(INT(C75))-5,3)+0)&" ming "&ROMAN(MID(INT(C75),LEN(INT(C75))-2,3)+0),IF(LEN(INT(C75))>3,ROMAN(MID(INT(C75),1,LEN(INT(C75))-3)+0)&" ming "&ROMAN(MID(INT(C75),LEN(INT(C75))-2,3)+0),ROMAN(INT(C75)))),"DCCC"," sakkiz yuz"),"DCC"," yetti yuz"),"DC"," olti yuz"),"CD"," to'rt yuz"),"XC"," to'qson"),"CCC"," uch yuz"),"CC"," ikki yuz"),"D"," besh yuz"),"CM"," to'qqiz yuz"),"C"," yuz"),"XL"," qirq"),"LXXX"," sakson"),"LXX"," yetmish"),"LX"," oltmish"),"L"," ellik"),"XXX"," o'ttiz"),"XX"," yigirma"),"XIX"," o'n toqqiz"),"XVIII"," o'n sakkiz"),"XVII"," o'n yetti"),"XVI"," o'n olti"),"XV"," o'n besh"),"XIV"," o'n to'rt"),"XIII"," o'n uch"),"XII"," o'n ikki"),"XI"," o'n bir"),"IX"," to'qqiz"),"X"," o'n"),"VIII"," sakkiz"),"VII"," yetti"),"VI"," olti"),"IV"," to'rt"),"V"," besh"),"III"," uch"),"II"," ikki"),"I"," bir"),"bir ming","bir ming"),"ikki ming","ikki ming"),"uch ming","uch ming"),"to'rt ming","to'rt ming"),"bir million","bir million"),"ikki million","ikki million"),"uch million","uch million"),"to'rt million","to'rt million")),"million ming","million"),"million ming","million"),"million ming","million")&" so'm" -> ikki yuz qirq besh million so'm
A76: =CONCATENATE(B65," miqdori (summasi)") -> mikrokredit miqdori (summasi) | B76: =B75+B153 -> 175000000 | C76: Uzbek tilida
A77: QO’L BILAN KIRITILADI | B77: =""&SUBSTITUTE(SUBSTITUTE(SUBSTITUTE(TRIM(SUBSTITUTE(SUBSTITUTE(SUBSTITUTE(SUBSTITUTE(SUBSTITUTE(SUBSTITUTE(SUBSTITUTE(SUBSTITUTE(SUBSTITUTE(SUBSTITUTE(SUBSTITUTE(SUBSTITUTE(SUBSTITUTE(SUBSTITUTE(SUBSTITUTE(SUBSTITUTE(SUBSTITUTE(SUBSTITUTE(SUBSTITUTE(SUBSTITUTE(SUBSTITUTE(SUBSTITUTE(SUBSTITUTE(SUBSTITUTE(SUBSTITUTE(SUBSTITUTE(SUBSTITUTE(SUBSTITUTE(SUBSTITUTE(SUBSTITUTE(SUBSTITUTE(SUBSTITUTE(SUBSTITUTE(SUBSTITUTE(SUBSTITUTE(SUBSTITUTE(SUBSTITUTE(SUBSTITUTE(SUBSTITUTE(SUBSTITUTE(SUBSTITUTE(SUBSTITUTE(SUBSTITUTE(SUBSTITUTE(IF(LEN(INT(B76))>6,ROMAN(MID(INT(B76),1,LEN(INT(B76))-6)+0)&" million "&ROMAN(MID(INT(B76),LEN(INT(B76))-5,3)+0)&" ming "&ROMAN(MID(INT(B76),LEN(INT(B76))-2,3)+0),IF(LEN(INT(B76))>3,ROMAN(MID(INT(B76),1,LEN(INT(B76))-3)+0)&" ming "&ROMAN(MID(INT(B76),LEN(INT(B76))-2,3)+0),ROMAN(INT(B76)))),"DCCC"," sakkiz yuz"),"DCC"," yetti yuz"),"DC"," olti yuz"),"CD"," to'rt yuz"),"XC"," to'qson"),"CCC"," uch yuz"),"CC"," ikki yuz"),"D"," besh yuz"),"CM"," to'qqiz yuz"),"C"," yuz"),"XL"," qirq"),"LXXX"," sakson"),"LXX"," yetmish"),"LX"," oltmish"),"L"," ellik"),"XXX"," o'ttiz"),"XX"," yigirma"),"XIX"," o'n toqqiz"),"XVIII"," o'n sakkiz"),"XVII"," o'n yetti"),"XVI"," o'n olti"),"XV"," o'n besh"),"XIV"," o'n to'rt"),"XIII"," o'n uch"),"XII"," o'n ikki"),"XI"," o'n bir"),"IX"," to'qqiz"),"X"," o'n"),"VIII"," sakkiz"),"VII"," yetti"),"VI"," olti"),"IV"," to'rt"),"V"," besh"),"III"," uch"),"II"," ikki"),"I"," bir"),"bir ming","bir ming"),"ikki ming","ikki ming"),"uch ming","uch ming"),"to'rt ming","to'rt ming"),"bir million","bir million"),"ikki million","ikki million"),"uch million","uch million"),"to'rt million","to'rt million")),"million ming","million"),"million ming","million"),"million ming","million")&" so'm" -> yuz yetmish besh million so'm | C77: =UPPER(LEFT(SUBSTITUTE(SUBSTITUTE(SUBSTITUTE(TRIM(SUBSTITUTE(SUBSTITUTE(SUBSTITUTE(SUBSTITUTE(SUBSTITUTE(SUBSTITUTE(SUBSTITUTE(SUBSTITUTE(SUBSTITUTE(SUBSTITUTE(SUBSTITUTE(SUBSTITUTE(SUBSTITUTE(SUBSTITUTE(SUBSTITUTE(SUBSTITUTE(SUBSTITUTE(SUBSTITUTE(SUBSTITUTE(SUBSTITUTE(SUBSTITUTE(SUBSTITUTE(SUBSTITUTE(SUBSTITUTE(SUBSTITUTE(SUBSTITUTE(SUBSTITUTE(SUBSTITUTE(SUBSTITUTE(SUBSTITUTE(SUBSTITUTE(SUBSTITUTE(SUBSTITUTE(SUBSTITUTE(SUBSTITUTE(SUBSTITUTE(SUBSTITUTE(SUBSTITUTE(SUBSTITUTE(SUBSTITUTE(SUBSTITUTE(SUBSTITUTE(SUBSTITUTE(SUBSTITUTE(SUBSTITUTE(SUBSTITUTE(SUBSTITUTE(SUBSTITUTE(IF(LEN(ROUNDDOWN(B76,0))>6,ROMAN(MID(ROUNDDOWN(B76,0),1,LEN(ROUNDDOWN(B76,0))-6)+0)&" million "&ROMAN(MID(ROUNDDOWN(B76,0),LEN(ROUNDDOWN(B76,0))-5,3)+0)&" ming "&ROMAN(MID(ROUNDDOWN(B76,0),LEN(ROUNDDOWN(B76,0))-2,3)+0)&" so'm",IF(LEN(ROUNDDOWN(B76,0))>3,ROMAN(MID(ROUNDDOWN(B76,0),1,LEN(ROUNDDOWN(B76,0))-3)+0)&" ming "&ROMAN(MID(ROUNDDOWN(B76,0),LEN(ROUNDDOWN(B76,0))-2,3)+0)&" so'm",ROMAN(ROUNDDOWN(B76,0))&" so'm")),"DCCC"," sakkiz yuz"),"DCC"," yetti yuz"),"DC"," olti yuz"),"CD"," to'rt yuz"),"XC"," to'qson"),"CCC"," uch yuz"),"CC"," ikki yuz"),"D"," besh yuz"),"CM"," to'qqiz yuz"),"C"," yuz"),"XL"," qiriq"),"LXXX"," sakson"),"LXX"," yetmish"),"LX"," oltmish"),"L"," ellik"),"XXX"," o'ttiz"),"XX"," yigirma"),"XIX"," o'n tiqqiz"),"XVIII"," o'n sakkiz"),"XVII"," o'n yetti"),"XVI"," o'n olti"),"XV"," o'n besh"),"XIV"," o'n to'rt"),"XIII"," o'n uch"),"XII"," o'n ikki"),"XI"," o'n bir"),"IX"," to'qqiz"),"X"," o'n"),"VIII"," sakkiz"),"VII"," yetti"),"VI"," olti"),"IV"," to'rt"),"V"," besh"),"III"," uch"),"II"," ikki"),"I"," bir"),"bir ming","bir ming"),"ikki ming","ikki ming"),"uch ming","uch ming"),"to'rt ming","to'rt ming"),"bir million","bir million"),"ikki million","ikki million"),"uch million","uch million"),"to'rt million","to'rt million"),"bir so'm","bir so'm"),"ikki so'm","ikki so'm"),"uch so'm","uch so'm"),"to'rt so'm","to'rt so'm")),"ming million","million"),"ming million","million"),"ming million","million"),1))&MID(SUBSTITUTE(SUBSTITUTE(SUBSTITUTE(TRIM(SUBSTITUTE(SUBSTITUTE(SUBSTITUTE(SUBSTITUTE(SUBSTITUTE(SUBSTITUTE(SUBSTITUTE(SUBSTITUTE(SUBSTITUTE(SUBSTITUTE(SUBSTITUTE(SUBSTITUTE(SUBSTITUTE(SUBSTITUTE(SUBSTITUTE(SUBSTITUTE(SUBSTITUTE(SUBSTITUTE(SUBSTITUTE(SUBSTITUTE(SUBSTITUTE(SUBSTITUTE(SUBSTITUTE(SUBSTITUTE(SUBSTITUTE(SUBSTITUTE(SUBSTITUTE(SUBSTITUTE(SUBSTITUTE(SUBSTITUTE(SUBSTITUTE(SUBSTITUTE(SUBSTITUTE(SUBSTITUTE(SUBSTITUTE(SUBSTITUTE(SUBSTITUTE(SUBSTITUTE(SUBSTITUTE(SUBSTITUTE(SUBSTITUTE(SUBSTITUTE(SUBSTITUTE(SUBSTITUTE(SUBSTITUTE(SUBSTITUTE(SUBSTITUTE(SUBSTITUTE(IF(LEN(ROUNDDOWN(B76,0))>6,ROMAN(MID(ROUNDDOWN(B76,0),1,LEN(ROUNDDOWN(B76,0))-6)+0)&" million "&ROMAN(MID(ROUNDDOWN(B76,0),LEN(ROUNDDOWN(B76,0))-5,3)+0)&" "&ROMAN(MID(ROUNDDOWN(B76,0),LEN(ROUNDDOWN(B76,0))-2,3)+0)&" so'm",IF(LEN(ROUNDDOWN(B76,0))>3,ROMAN(MID(ROUNDDOWN(B76,0),1,LEN(ROUNDDOWN(B76,0))-3)+0)&" ming "&ROMAN(MID(ROUNDDOWN(B76,0),LEN(ROUNDDOWN(B76,0))-2,3)+0)&" so'm",ROMAN(ROUNDDOWN(B76,0))&" so'm")),"DCCC"," sakkiz yuz"),"DCC"," yetti yuz"),"DC"," olti yuz"),"CD"," to'rt yuz"),"XC"," to'qson"),"CCC"," uch yuz"),"CC"," ikki yuz"),"D"," besh yuz"),"CM"," to'qqiz yuz"),"C"," yuz"),"XL"," qirq"),"LXXX"," sakson"),"LXX"," yetmish"),"LX"," oltmish"),"L"," ellik"),"XXX"," o'ttiz"),"XX"," yigirma"),"XIX"," o'n to'qqiz"),"XVIII"," o'n sakkiz"),"XVII"," o'n yetti"),"XVI"," o'n olti"),"XV"," o'n besh"),"XIV"," o'n to'rt"),"XIII"," o'n uch"),"XII"," o'n ikki"),"XI"," o'n bir"),"IX"," to'qqiz"),"X"," o'n"),"VIII"," sakkiz"),"VII"," yetti"),"VI"," olti"),"IV"," to'rt"),"V"," besh"),"III"," uch"),"II"," ikki"),"I"," bir"),"bir ming","bir ming"),"ikki ming","ikki ming"),"uch ming","uch ming"),"to'rt ming","to'rt ming"),"bir million","bir million"),"ikki million","ikki million"),"uch million","uch million"),"to'rt million","to'rt million"),"bir so'm","bir so'm"),"ikki so'm","ikki so'm"),"uch so'm","uch so'm"),"to'rt so'm","to'rt so'm")),"ming million","million"),"ming million","million"),"ming million","million"),2,200)&"" -> Yuz yetmish besh million so'm
A78: Grafik turi | B78: differensial | C78: differensial | D78: annuitet
A79: =CONCATENATE(B65,"ni to'lash sanasi (14.10.2011)") -> mikrokreditni to'lash sanasi (14.10.2011) | B79: 10 | C79: =DATE(YEAR(B67),MONTH(B67)+1,DAY(B79)) -> 46091 | D79: Пн | E79: Вт | F79: Ср | G79: Чт | H79: Пт | I79: Сб | J79: Вс
A80: =CONCATENATE(B65,"ni to'lash sanasi (14.10.2011 y.) QO’L BILAN KIRITILADI") -> mikrokreditni to'lash sanasi (14.10.2011 y.) QO’L BILAN KIRITILADI | B80: =DATE(YEAR(B67),MONTH(B67)+1,DAY(B79+C81)) -> 46091 | C80: =TEXT(C79,"ддд") -> Вт | D80: Пн | E80: Вт | F80: Ср | G80: Чт | H80: Пт | I80: Сб | J80: Вс
A81: Mikroqarzni to'lash sanasi (14.10.2011 y.) QO’L BILAN KIRITILADI | B81: =B80 -> 46091 | C81: =IF(C80=I80,2,IF(C80=J80,1,0)) -> 0
A82: =CONCATENATE(B65," muddati") -> mikrokredit muddati | B82: 36 | C82: 6 | D82: 12 | E82: 18 | F82: 24 | G82: 36
A83: =CONCATENATE(B65," muddati QO’L BILAN KIRITILADI") -> mikrokredit muddati QO’L BILAN KIRITILADI | B83: =UPPER(LEFT(SUBSTITUTE(SUBSTITUTE(SUBSTITUTE(TRIM(SUBSTITUTE(SUBSTITUTE(SUBSTITUTE(SUBSTITUTE(SUBSTITUTE(SUBSTITUTE(SUBSTITUTE(SUBSTITUTE(SUBSTITUTE(SUBSTITUTE(SUBSTITUTE(SUBSTITUTE(SUBSTITUTE(SUBSTITUTE(SUBSTITUTE(SUBSTITUTE(SUBSTITUTE(SUBSTITUTE(SUBSTITUTE(SUBSTITUTE(SUBSTITUTE(SUBSTITUTE(SUBSTITUTE(SUBSTITUTE(SUBSTITUTE(SUBSTITUTE(SUBSTITUTE(SUBSTITUTE(SUBSTITUTE(SUBSTITUTE(SUBSTITUTE(SUBSTITUTE(SUBSTITUTE(SUBSTITUTE(SUBSTITUTE(SUBSTITUTE(SUBSTITUTE(SUBSTITUTE(SUBSTITUTE(SUBSTITUTE(SUBSTITUTE(SUBSTITUTE(SUBSTITUTE(SUBSTITUTE(SUBSTITUTE(SUBSTITUTE(SUBSTITUTE(SUBSTITUTE(IF(LEN(ROUNDDOWN(B82,0))>6,ROMAN(MID(ROUNDDOWN(B82,0),1,LEN(ROUNDDOWN(B82,0))-6)+0)&" million "&ROMAN(MID(ROUNDDOWN(B82,0),LEN(ROUNDDOWN(B82,0))-5,3)+0)&" ming "&ROMAN(MID(ROUNDDOWN(B82,0),LEN(ROUNDDOWN(B82,0))-2,3)+0)&"",IF(LEN(ROUNDDOWN(B82,0))>3,ROMAN(MID(ROUNDDOWN(B82,0),1,LEN(ROUNDDOWN(B82,0))-3)+0)&" ming "&ROMAN(MID(ROUNDDOWN(B82,0),LEN(ROUNDDOWN(B82,0))-2,3)+0)&"",ROMAN(ROUNDDOWN(B82,0))&"")),"DCCC"," sakkiz yuz"),"DCC"," yetti yuz"),"DC"," olti yuz"),"CD"," to'rt yuz"),"XC"," to'qson"),"CCC"," uch yuz"),"CC"," ikki yuz"),"D"," besh yuz"),"CM"," to'qqiz yuz"),"C"," yuz"),"XL"," qiriq"),"LXXX"," sakson"),"LXX"," yetmish"),"LX"," oltmish"),"L"," ellik"),"XXX"," o'ttiz"),"XX"," yigirma"),"XIX"," o'n tiqqiz"),"XVIII"," o'n sakkiz"),"XVII"," o'n yetti"),"XVI"," o'n olti"),"XV"," o'n besh"),"XIV"," o'n to'rt"),"XIII"," o'n uch"),"XII"," o'n ikki"),"XI"," o'n bir"),"IX"," to'qqiz"),"X"," o'n"),"VIII"," sakkiz"),"VII"," yetti"),"VI"," olti"),"IV"," to'rt"),"V"," besh"),"III"," uch"),"II"," ikki"),"I"," bir"),"bir ming","bir ming"),"ikki ming","ikki ming"),"uch ming","uch ming"),"to'rt ming","to'rt ming"),"bir million","bir million"),"ikki million","ikki million"),"uch million","uch million"),"to'rt million","to'rt million"),"bir","bir"),"ikki","ikki"),"uch","uch"),"to'rt","to'rt")),"ming million","million"),"ming million","million"),"ming million","million"),1))&MID(SUBSTITUTE(SUBSTITUTE(SUBSTITUTE(TRIM(SUBSTITUTE(SUBSTITUTE(SUBSTITUTE(SUBSTITUTE(SUBSTITUTE(SUBSTITUTE(SUBSTITUTE(SUBSTITUTE(SUBSTITUTE(SUBSTITUTE(SUBSTITUTE(SUBSTITUTE(SUBSTITUTE(SUBSTITUTE(SUBSTITUTE(SUBSTITUTE(SUBSTITUTE(SUBSTITUTE(SUBSTITUTE(SUBSTITUTE(SUBSTITUTE(SUBSTITUTE(SUBSTITUTE(SUBSTITUTE(SUBSTITUTE(SUBSTITUTE(SUBSTITUTE(SUBSTITUTE(SUBSTITUTE(SUBSTITUTE(SUBSTITUTE(SUBSTITUTE(SUBSTITUTE(SUBSTITUTE(SUBSTITUTE(SUBSTITUTE(SUBSTITUTE(SUBSTITUTE(SUBSTITUTE(SUBSTITUTE(SUBSTITUTE(SUBSTITUTE(SUBSTITUTE(SUBSTITUTE(SUBSTITUTE(SUBSTITUTE(SUBSTITUTE(SUBSTITUTE(IF(LEN(ROUNDDOWN(B82,0))>6,ROMAN(MID(ROUNDDOWN(B82,0),1,LEN(ROUNDDOWN(B82,0))-6)+0)&" million "&ROMAN(MID(ROUNDDOWN(B82,0),LEN(ROUNDDOWN(B82,0))-5,3)+0)&" "&ROMAN(MID(ROUNDDOWN(B82,0),LEN(ROUNDDOWN(B82,0))-2,3)+0)&"",IF(LEN(ROUNDDOWN(B82,0))>3,ROMAN(MID(ROUNDDOWN(B82,0),1,LEN(ROUNDDOWN(B82,0))-3)+0)&" ming "&ROMAN(MID(ROUNDDOWN(B82,0),LEN(ROUNDDOWN(B82,0))-2,3)+0)&"",ROMAN(ROUNDDOWN(B82,0))&"")),"DCCC"," sakkiz yuz"),"DCC"," yetti yuz"),"DC"," olti yuz"),"CD"," to'rt yuz"),"XC"," to'qson"),"CCC"," uch yuz"),"CC"," ikki yuz"),"D"," besh yuz"),"CM"," to'qqiz yuz"),"C"," yuz"),"XL"," qirq"),"LXXX"," sakson"),"LXX"," yetmish"),"LX"," oltmish"),"L"," ellik"),"XXX"," o'ttiz"),"XX"," yigirma"),"XIX"," o'n to'qqiz"),"XVIII"," o'n sakkiz"),"XVII"," o'n yetti"),"XVI"," o'n olti"),"XV"," o'n besh"),"XIV"," o'n to'rt"),"XIII"," o'n uch"),"XII"," o'n ikki"),"XI"," o'n bir"),"IX"," to'qqiz"),"X"," o'n"),"VIII"," sakkiz"),"VII"," yetti"),"VI"," olti"),"IV"," to'rt"),"V"," besh"),"III"," uch"),"II"," ikki"),"I"," bir"),"bir ming","bir ming"),"ikki ming","ikki ming"),"uch ming","uch ming"),"to'rt ming","to'rt ming"),"bir million","bir million"),"ikki million","ikki million"),"uch million","uch million"),"to'rt million","to'rt million"),"bir","bir"),"ikki","ikki"),"uch","uch"),"to'rt","to'rt")),"ming million","million"),"ming million","million"),"ming million","million"),2,200)&" "&SUBSTITUTE(SUBSTITUTE(SUBSTITUTE(SUBSTITUTE(SUBSTITUTE(SUBSTITUTE(SUBSTITUTE(SUBSTITUTE(RIGHT(TEXT(B82," "),2)&"","1","1"),"2","2"),"3","3"),"4","4"),"11","11"),"12","12"),"13","13"),"14","14") -> O'ttiz olti
A84: Imtiyozli davr | B84: 0 | BJ84: 1 | BK84: 0
A85: =CONCATENATE(B65," stavkasi") -> mikrokredit stavkasi | B85: 0.55
A86: =CONCATENATE(B65," stavkasi") -> mikrokredit stavkasi | B86: 55
A87: =CONCATENATE(B65," stavkasi (so’z bilan)") -> mikrokredit stavkasi (so’z bilan) | B87: =UPPER(LEFT(SUBSTITUTE(SUBSTITUTE(SUBSTITUTE(TRIM(SUBSTITUTE(SUBSTITUTE(SUBSTITUTE(SUBSTITUTE(SUBSTITUTE(SUBSTITUTE(SUBSTITUTE(SUBSTITUTE(SUBSTITUTE(SUBSTITUTE(SUBSTITUTE(SUBSTITUTE(SUBSTITUTE(SUBSTITUTE(SUBSTITUTE(SUBSTITUTE(SUBSTITUTE(SUBSTITUTE(SUBSTITUTE(SUBSTITUTE(SUBSTITUTE(SUBSTITUTE(SUBSTITUTE(SUBSTITUTE(SUBSTITUTE(SUBSTITUTE(SUBSTITUTE(SUBSTITUTE(SUBSTITUTE(SUBSTITUTE(SUBSTITUTE(SUBSTITUTE(SUBSTITUTE(SUBSTITUTE(SUBSTITUTE(SUBSTITUTE(SUBSTITUTE(SUBSTITUTE(SUBSTITUTE(SUBSTITUTE(SUBSTITUTE(SUBSTITUTE(SUBSTITUTE(SUBSTITUTE(SUBSTITUTE(SUBSTITUTE(SUBSTITUTE(SUBSTITUTE(IF(LEN(ROUNDDOWN(B86,0))>6,ROMAN(MID(ROUNDDOWN(B86,0),1,LEN(ROUNDDOWN(B86,0))-6)+0)&" million "&ROMAN(MID(ROUNDDOWN(B86,0),LEN(ROUNDDOWN(B86,0))-5,3)+0)&" ming "&ROMAN(MID(ROUNDDOWN(B86,0),LEN(ROUNDDOWN(B86,0))-2,3)+0)&"",IF(LEN(ROUNDDOWN(B86,0))>3,ROMAN(MID(ROUNDDOWN(B86,0),1,LEN(ROUNDDOWN(B86,0))-3)+0)&" ming "&ROMAN(MID(ROUNDDOWN(B86,0),LEN(ROUNDDOWN(B86,0))-2,3)+0)&"",ROMAN(ROUNDDOWN(B86,0))&"")),"DCCC"," sakkiz yuz"),"DCC"," yetti yuz"),"DC"," olti yuz"),"CD"," to'rt yuz"),"XC"," to'qson"),"CCC"," uch yuz"),"CC"," ikki yuz"),"D"," besh yuz"),"CM"," to'qqiz yuz"),"C"," yuz"),"XL"," qiriq"),"LXXX"," sakson"),"LXX"," yetmish"),"LX"," oltmish"),"L"," ellik"),"XXX"," o'ttiz"),"XX"," yigirma"),"XIX"," o'n tiqqiz"),"XVIII"," o'n sakkiz"),"XVII"," o'n yetti"),"XVI"," o'n olti"),"XV"," o'n besh"),"XIV"," o'n to'rt"),"XIII"," o'n uch"),"XII"," o'n ikki"),"XI"," o'n bir"),"IX"," to'qqiz"),"X"," o'n"),"VIII"," sakkiz"),"VII"," yetti"),"VI"," olti"),"IV"," to'rt"),"V"," besh"),"III"," uch"),"II"," ikki"),"I"," bir"),"bir ming","bir ming"),"ikki ming","ikki ming"),"uch ming","uch ming"),"to'rt ming","to'rt ming"),"bir million","bir million"),"ikki million","ikki million"),"uch million","uch million"),"to'rt million","to'rt million"),"bir","bir"),"ikki","ikki"),"uch","uch"),"to'rt","to'rt")),"ming million","million"),"ming million","million"),"ming million","million"),1))&MID(SUBSTITUTE(SUBSTITUTE(SUBSTITUTE(TRIM(SUBSTITUTE(SUBSTITUTE(SUBSTITUTE(SUBSTITUTE(SUBSTITUTE(SUBSTITUTE(SUBSTITUTE(SUBSTITUTE(SUBSTITUTE(SUBSTITUTE(SUBSTITUTE(SUBSTITUTE(SUBSTITUTE(SUBSTITUTE(SUBSTITUTE(SUBSTITUTE(SUBSTITUTE(SUBSTITUTE(SUBSTITUTE(SUBSTITUTE(SUBSTITUTE(SUBSTITUTE(SUBSTITUTE(SUBSTITUTE(SUBSTITUTE(SUBSTITUTE(SUBSTITUTE(SUBSTITUTE(SUBSTITUTE(SUBSTITUTE(SUBSTITUTE(SUBSTITUTE(SUBSTITUTE(SUBSTITUTE(SUBSTITUTE(SUBSTITUTE(SUBSTITUTE(SUBSTITUTE(SUBSTITUTE(SUBSTITUTE(SUBSTITUTE(SUBSTITUTE(SUBSTITUTE(SUBSTITUTE(SUBSTITUTE(SUBSTITUTE(SUBSTITUTE(SUBSTITUTE(IF(LEN(ROUNDDOWN(B86,0))>6,ROMAN(MID(ROUNDDOWN(B86,0),1,LEN(ROUNDDOWN(B86,0))-6)+0)&" million "&ROMAN(MID(ROUNDDOWN(B86,0),LEN(ROUNDDOWN(B86,0))-5,3)+0)&" "&ROMAN(MID(ROUNDDOWN(B86,0),LEN(ROUNDDOWN(B86,0))-2,3)+0)&"",IF(LEN(ROUNDDOWN(B86,0))>3,ROMAN(MID(ROUNDDOWN(B86,0),1,LEN(ROUNDDOWN(B86,0))-3)+0)&" ming "&ROMAN(MID(ROUNDDOWN(B86,0),LEN(ROUNDDOWN(B86,0))-2,3)+0)&"",ROMAN(ROUNDDOWN(B86,0))&"")),"DCCC"," sakkiz yuz"),"DCC"," yetti yuz"),"DC"," olti yuz"),"CD"," to'rt yuz"),"XC"," to'qson"),"CCC"," uch yuz"),"CC"," ikki yuz"),"D"," besh yuz"),"CM"," to'qqiz yuz"),"C"," yuz"),"XL"," qirq"),"LXXX"," sakson"),"LXX"," yetmish"),"LX"," oltmish"),"L"," ellik"),"XXX"," o'ttiz"),"XX"," yigirma"),"XIX"," o'n to'qqiz"),"XVIII"," o'n sakkiz"),"XVII"," o'n yetti"),"XVI"," o'n olti"),"XV"," o'n besh"),"XIV"," o'n to'rt"),"XIII"," o'n uch"),"XII"," o'n ikki"),"XI"," o'n bir"),"IX"," to'qqiz"),"X"," o'n"),"VIII"," sakkiz"),"VII"," yetti"),"VI"," olti"),"IV"," to'rt"),"V"," besh"),"III"," uch"),"II"," ikki"),"I"," bir"),"bir ming","bir ming"),"ikki ming","ikki ming"),"uch ming","uch ming"),"to'rt ming","to'rt ming"),"bir million","bir million"),"ikki million","ikki million"),"uch million","uch million"),"to'rt million","to'rt million"),"bir","bir"),"ikki","ikki"),"uch","uch"),"to'rt","to'rt")),"ming million","million"),"ming million","million"),"ming million","million"),2,200)&" "&SUBSTITUTE(SUBSTITUTE(SUBSTITUTE(SUBSTITUTE(SUBSTITUTE(SUBSTITUTE(SUBSTITUTE(SUBSTITUTE(RIGHT(TEXT(B86," "),2)&"","1","1"),"2","2"),"3","3"),"4","4"),"11","11"),"12","12"),"13","13"),"14","14") -> Ellik besh | C87: =UPPER(LEFT(SUBSTITUTE(SUBSTITUTE(SUBSTITUTE(TRIM(SUBSTITUTE(SUBSTITUTE(SUBSTITUTE(SUBSTITUTE(SUBSTITUTE(SUBSTITUTE(SUBSTITUTE(SUBSTITUTE(SUBSTITUTE(SUBSTITUTE(SUBSTITUTE(SUBSTITUTE(SUBSTITUTE(SUBSTITUTE(SUBSTITUTE(SUBSTITUTE(SUBSTITUTE(SUBSTITUTE(SUBSTITUTE(SUBSTITUTE(SUBSTITUTE(SUBSTITUTE(SUBSTITUTE(SUBSTITUTE(SUBSTITUTE(SUBSTITUTE(SUBSTITUTE(SUBSTITUTE(SUBSTITUTE(SUBSTITUTE(SUBSTITUTE(SUBSTITUTE(SUBSTITUTE(SUBSTITUTE(SUBSTITUTE(SUBSTITUTE(SUBSTITUTE(SUBSTITUTE(SUBSTITUTE(SUBSTITUTE(SUBSTITUTE(SUBSTITUTE(SUBSTITUTE(SUBSTITUTE(SUBSTITUTE(SUBSTITUTE(SUBSTITUTE(SUBSTITUTE(IF(LEN(ROUNDDOWN(B86,0))>6,ROMAN(MID(ROUNDDOWN(B86,0),1,LEN(ROUNDDOWN(B86,0))-6)+0)&" million "&ROMAN(MID(ROUNDDOWN(B86,0),LEN(ROUNDDOWN(B86,0))-5,3)+0)&" ming "&ROMAN(MID(ROUNDDOWN(B86,0),LEN(ROUNDDOWN(B86,0))-2,3)+0)&"",IF(LEN(ROUNDDOWN(B86,0))>3,ROMAN(MID(ROUNDDOWN(B86,0),1,LEN(ROUNDDOWN(B86,0))-3)+0)&" ming "&ROMAN(MID(ROUNDDOWN(B86,0),LEN(ROUNDDOWN(B86,0))-2,3)+0)&"",ROMAN(ROUNDDOWN(B86,0))&"")),"DCCC"," sakkiz yuz"),"DCC"," yetti yuz"),"DC"," olti yuz"),"CD"," to'rt yuz"),"XC"," to'qson"),"CCC"," uch yuz"),"CC"," ikki yuz"),"D"," besh yuz"),"CM"," to'qqiz yuz"),"C"," yuz"),"XL"," qiriq"),"LXXX"," sakson"),"LXX"," yetmish"),"LX"," oltmish"),"L"," ellik"),"XXX"," o'ttiz"),"XX"," yigirma"),"XIX"," o'n tiqqiz"),"XVIII"," o'n sakkiz"),"XVII"," o'n yetti"),"XVI"," o'n olti"),"XV"," o'n besh"),"XIV"," o'n to'rt"),"XIII"," o'n uch"),"XII"," o'n ikki"),"XI"," o'n bir"),"IX"," to'qqiz"),"X"," o'n"),"VIII"," sakkiz"),"VII"," yetti"),"VI"," olti"),"IV"," to'rt"),"V"," besh"),"III"," uch"),"II"," ikki"),"I"," bir"),"bir ming","bir ming"),"ikki ming","ikki ming"),"uch ming","uch ming"),"to'rt ming","to'rt ming"),"bir million","bir million"),"ikki million","ikki million"),"uch million","uch million"),"to'rt million","to'rt million"),"bir","bir"),"ikki","ikki"),"uch","uch"),"to'rt","to'rt")),"ming million","million"),"ming million","million"),"ming million","million"),1))&MID(SUBSTITUTE(SUBSTITUTE(SUBSTITUTE(TRIM(SUBSTITUTE(SUBSTITUTE(SUBSTITUTE(SUBSTITUTE(SUBSTITUTE(SUBSTITUTE(SUBSTITUTE(SUBSTITUTE(SUBSTITUTE(SUBSTITUTE(SUBSTITUTE(SUBSTITUTE(SUBSTITUTE(SUBSTITUTE(SUBSTITUTE(SUBSTITUTE(SUBSTITUTE(SUBSTITUTE(SUBSTITUTE(SUBSTITUTE(SUBSTITUTE(SUBSTITUTE(SUBSTITUTE(SUBSTITUTE(SUBSTITUTE(SUBSTITUTE(SUBSTITUTE(SUBSTITUTE(SUBSTITUTE(SUBSTITUTE(SUBSTITUTE(SUBSTITUTE(SUBSTITUTE(SUBSTITUTE(SUBSTITUTE(SUBSTITUTE(SUBSTITUTE(SUBSTITUTE(SUBSTITUTE(SUBSTITUTE(SUBSTITUTE(SUBSTITUTE(SUBSTITUTE(SUBSTITUTE(SUBSTITUTE(SUBSTITUTE(SUBSTITUTE(SUBSTITUTE(IF(LEN(ROUNDDOWN(B86,0))>6,ROMAN(MID(ROUNDDOWN(B86,0),1,LEN(ROUNDDOWN(B86,0))-6)+0)&" million "&ROMAN(MID(ROUNDDOWN(B86,0),LEN(ROUNDDOWN(B86,0))-5,3)+0)&" "&ROMAN(MID(ROUNDDOWN(B86,0),LEN(ROUNDDOWN(B86,0))-2,3)+0)&"",IF(LEN(ROUNDDOWN(B86,0))>3,ROMAN(MID(ROUNDDOWN(B86,0),1,LEN(ROUNDDOWN(B86,0))-3)+0)&" ming "&ROMAN(MID(ROUNDDOWN(B86,0),LEN(ROUNDDOWN(B86,0))-2,3)+0)&"",ROMAN(ROUNDDOWN(B86,0))&"")),"DCCC"," sakkiz yuz"),"DCC"," yetti yuz"),"DC"," olti yuz"),"CD"," to'rt yuz"),"XC"," to'qson"),"CCC"," uch yuz"),"CC"," ikki yuz"),"D"," besh yuz"),"CM"," to'qqiz yuz"),"C"," yuz"),"XL"," qirq"),"LXXX"," sakson"),"LXX"," yetmish"),"LX"," oltmish"),"L"," ellik"),"XXX"," o'ttiz"),"XX"," yigirma"),"XIX"," o'n to'qqiz"),"XVIII"," o'n sakkiz"),"XVII"," o'n yetti"),"XVI"," o'n olti"),"XV"," o'n besh"),"XIV"," o'n to'rt"),"XIII"," o'n uch"),"XII"," o'n ikki"),"XI"," o'n bir"),"IX"," to'qqiz"),"X"," o'n"),"VIII"," sakkiz"),"VII"," yetti"),"VI"," olti"),"IV"," to'rt"),"V"," besh"),"III"," uch"),"II"," ikki"),"I"," bir"),"bir ming","bir ming"),"ikki ming","ikki ming"),"uch ming","uch ming"),"to'rt ming","to'rt ming"),"bir million","bir million"),"ikki million","ikki million"),"uch million","uch million"),"to'rt million","to'rt million"),"bir","bir"),"ikki","ikki"),"uch","uch"),"to'rt","to'rt")),"ming million","million"),"ming million","million"),"ming million","million"),2,200)&" "&SUBSTITUTE(SUBSTITUTE(SUBSTITUTE(SUBSTITUTE(SUBSTITUTE(SUBSTITUTE(SUBSTITUTE(SUBSTITUTE(RIGHT(TEXT(B86," "),2)&"","1","1"),"2","2"),"3","3"),"4","4"),"11","11"),"12","12"),"13","13"),"14","14") -> Ellik besh
A88: =CONCATENATE("Muddati o'tgan ",B65," bo’yicha stavka") -> Muddati o'tgan mikrokredit bo’yicha stavka | B88: 1.55
A89: QO’L BILAN KIRITILADI | B89: 155
A90: =CONCATENATE("Muddati o'tgan ",B65," bo’yicha stavka") -> Muddati o'tgan mikrokredit bo’yicha stavka | B90: bir yuz ellik besh | C90: bir yuz ellik besh
A91: Oylik to'lov | B91: =IF(B78=C78,LARGE(grafik!F9:F26,1),ROUND(PMT(B85/12,B82,-B76,0),-3)) -> 12808695
A92: Mijoz plastik kartasi parametrlari
A93: Bank nomi:
A94: H/r:
A95: MFO:
A96: STIR:
A97: Karta raqami:
A98: GAROV BO’YICHA MA’LUMOTLAR
B99: Birlamchi | C99: Birlamchi | D99: navbatdagi garov
A100: Garovga beruvchi mulkdormi? | B100: yo’q | C100: Ha | D100: yo’q
A101: Agar garovga beruvchi qarz oluvchi bo'lmasa, garovga kim qo'yganligini ko'rsating | B101: Garovga beruvchining o’zi | C101: Garovga beruvchining o’zi | D101: Bosh ishonchnoma bo’yicha boshqa shaxs
...

Sheet mijoz_anketasi
A1: MIJOZNING ANKETASI
A2: Anketa kredit menejeri tomonidan mijozning javoblarini kiritish orqali to'ldiriladi, kerak bo'lganda, Mijoz tomonidan tanlangan javob variantlarini belgilash orqali amalga oshiriladi
A3: 1. MIJOZ HAQIDA MA'LUMOTLAR:
A4: =xulosa!A4:E4 -> Mijozning to'liq ismi sharifi: NORINBOYEVA SOXIBA IZZATILLAYEVNA
A5: =xulosa!A5:E5 -> Tug'ilgan sanasi: 19.10.1985 yil
A6: =xulosa!A6:E6 -> Pasport seriyasi AE 5547691 IIV 27256 tomonidan 22.12.2025 yilda berilgan, amal qilish muddati - 21.12.2035 y.
A7: ="Fuqaroligi: "&umumiy_malumot!B32&"" -> Fuqaroligi: O’zbekiston Respublikasi
A8: =xulosa!A7:E7 -> Ro‘yxatdan o‘tgan manzili: TOSHKENT VILOYATI CHINOZ TUMANI ALISHER NAVOIY MFY SOBIR RAHIMOV KO'CHASI 36 UY, mo'ljal: 1 MAKTAB BALNITSA CHINOZ
A9: =IF(umumiy_malumot!B23="mos keladi"," ",mijoz_anketasi!A10:F10)
A10: ="Haqiqatdan yashash joy manzili: "&umumiy_malumot!B28&"" -> Haqiqatdan yashash joy manzili: TOSHKENT VILOYATI CHINOZ TUMANI ALISHER NAVOIY MFY SOBIR RAHIMOV KO'CHASI 36 UY
A11: =xulosa!A8:E8 -> Ish joyi: lavozimi BOLALAR O'YINCHOGINI ISHLAB CHIQARISH (UY SHAROITIDA)da O'Z O'ZINI BAND QILGAN FUQARO
A12: 2. Mijoz bilan ulanich uchun aloqa ma'lumotlari:
A13: ="Uy telefoni raqami: "&umumiy_malumot!B40&"" -> Uy telefoni raqami: 33 730 30 31 MIJOZ
A14: ="Uyali telefon raqami: "&umumiy_malumot!B41&"" -> Uyali telefon raqami: 99 407 50 08 UY EGASI
A15: ="Uyali telefon raqami: "&umumiy_malumot!B42&"" -> Uyali telefon raqami: 94 659 57 51 ADASI
A16: ="Uyali telefon raqami: "&umumiy_malumot!B42&"" -> Uyali telefon raqami: 94 659 57 51 ADASI
A17: ="Ish telefoni raqami: "&umumiy_malumot!B43&"" -> Ish telefoni raqami:
A18: 3. MIJOZNING ISH JOYI HAQIDA MA'LUMOT:
A19: ="Muassasa nomlanishi:"&umumiy_malumot!B58&"" -> Muassasa nomlanishi:O'Z O'ZINI BAND QILGAN FUQARO
A20: ="Ro‘yxatdan o‘tish manzili:"&umumiy_malumot!B46&"" -> Ro‘yxatdan o‘tish manzili:№0012660051
A21: ="Lavozimi: "&umumiy_malumot!B59&"" -> Lavozimi: BOLALAR O'YINCHOGINI ISHLAB CHIQARISH (UY SHAROITIDA)
A22: 4. MIJOZNING OYLIK DAROMADLARI VA XARAJATLARI HAQIDA MA'LUMOT
A23: Daromad manbalari | B23: Mijoz | C23: Turmush o'rtog'i | D23: Boshqa oila a'zolari | E23: Xarajatlar | F23: Мiqdori
A24: ish haqi (asosiy ish) | B24: =umumiy_malumot!B60 -> 20000000 | C24: 0 | D24: 0 | E24: uy-joy va kommunal xizmatlar uchun to'lov | F24: 700000
A25: ish haqi (o‘rindoshlik) | B25: 0 | C25: 0 | D25: 0 | E25: oilaviy xarajatlar | F25: 500000
A26: boshqa daromadlar | B26: =umumiy_malumot!B61 -> 10000000 | C26: 0 | D26: 0 | E26: boshqa xarajatlar | F26: 600000
A27: JAMI | B27: =B24+B25+B26 -> 30000000 | C27: =SUM(C24:C26) -> 0 | D27: =SUM(D24:D26) -> 0 | F27: =SUM(F24:F26) -> 1800000
A28: ="Men, "&umumiy_malumot!B5&", ushbu anketada ko‘rsatilgan barcha ma'lumotlar anketa to'ldirilgan sanada to'g'ri va aniq ekanligini tasdiqlayman." -> Men, NORINBOYEVA SOXIBA IZZATILLAYEVNA, ushbu anketada ko‘rsatilgan barcha ma'lumotlar anketa to'ldirilgan sanada to'g'ri va aniq ekanligini tasdiqlayman.
A29: ="Men, "&umumiy_malumot!B5&", quyidagilarni tan olaman va roziman::" -> Men, NORINBOYEVA SOXIBA IZZATILLAYEVNA, quyidagilarni tan olaman va roziman::
A30: ="1. Ushbu anketada ko‘rsatilgan har qanday ma’lumot "&umumiy_malumot!B158&", uning xodimlari va huquqiy vorislari tomonidan istalgan manbaa va ma’lumotlardan foydalangan holda istalgan vaqtda tekshirilishi va qayta tekshirilishi mumkin." -> 1. Ushbu anketada ko‘rsatilgan har qanday ma’lumot «PULLOL BUSINESS MIKROMOLIYA TASHKILOTI» MChJ, uning xodimlari va huquqiy vorislari tomonidan istalgan manbaa va ma’lumotlardan foydalangan holda istalgan vaqtda tekshirilishi va qayta tekshirilishi mumkin.
A31: ="2. Mazkur anketaning "&umumiy_malumot!B158&" tomonidan qabul qilinishi "&umumiy_malumot!B158&" tomonidan menga "&umumiy_malumot!B65&" berish majburiyatini yuklamaydi." -> 2. Mazkur anketaning «PULLOL BUSINESS MIKROMOLIYA TASHKILOTI» MChJ tomonidan qabul qilinishi «PULLOL BUSINESS MIKROMOLIYA TASHKILOTI» MChJ tomonidan menga mikrokredit berish majburiyatini yuklamaydi.
A32: Men, _________________________________________________________________ (to'liq ismi sharifi), ushbu anketadagi barcha ma'lumotlar anketa to'ldirilgan sanada to'g'ri ekanligini tasdiqlayman va ushbu anketaning 1- va 2-bandlarini tan olaman va ularga rozilik bildiraman. Mazkur anketaning 4-bo'limida ko'rsatilgan daromadlarim haqidagi ma'lumotlarni qabul qilishingizni va moliyaviy tahlilda foydalanishingizni so’rayman.
A34: Mijozning to'liq ismi sharifi | D34: Sana | E34: Imzo
D35: =umumiy_malumot!B2 -> 16.02.2026

Sheet anketa
A2: ANKETA
E3: =umumiy_malumot!B68 -> 16 fevral 2026 y.
A5: Mijozning to'liq ismi sharifi | C5: =umumiy_malumot!B8 -> NORINBOYEVA SOXIBA IZZATILLAYEVNA
A7: Siz ommaviy mansabdor shaxsmisiz? | D7: Ha
D8: Yo'q
A9: Yaqin qarindoshlaringiz orasida ommaviy mansabdor shaxslar bormi? | D9: Ha
D10: Yo'q
A11: Do'stlaringiz yoki yaqinlaringizdan birontasi ommaviy mansabdor shaxsmi? | D11: Ha
D12: Yo'q
A13: Yuqoridagi savollardan biriga «Ha» deb javob bergan bo'lsangiz, javobingizni qisqacha tushuntirib bering:
A18: Siz bank amaliyotlarini amalga oshirishda uchinchi shaxsning manfaatlarini ifodalaysizmi? | D18: Ha
D19: Yo'q
A20: Agar oldingi savolga «HA» deb javob bergan bo'lsangiz, bank operatsiyalarini bajarich uchun ishonchnomangiz bormi? | D20: Ha
D21: Yo'q
A23: Agar oldingi savolga «YO'Q» deb javob bergan bo'lsangiz, javobingizni qisqacha tushuntirib bering:
A28: Ommaviy mansabdor shaxslar — doimiy, vaqtincha yoki maxsus vakolatli organ tomonidan tayinlangan yoki saylangan, tashkiliy-maʼmuriy funktsiyalarni bajaruvchi hamda xorijiy davlatning qonun chiqaruvchi, ijro etuvchi, maʼmuriy yoki sud organida yoxud xalqaro tashkilotda yuridik ahamiyatga molik harakatlarni amalga oshirishga vakolatli shaxslar, shuningdek xorijiy davlatlar korxonalarining yuqori martabali rahbarlari, taniqli siyosatchilar va xorijiy davlatlar siyosiy partiyalarining taniqli a'zolari.
A30: Anketadagi barcha ma'lumotlar to'g'ri, agar o'zgarishlar bo'lsa, men bu haqida xabardor qilish majburiyatini o'z zimmamga olaman.
A33: =C5 -> NORINBOYEVA SOXIBA IZZATILLAYEVNA

Sheet kredit_ariza
C1: =""&umumiy_malumot!B158&"ning "&umumiy_malumot!A161&"" -> «PULLOL BUSINESS MIKROMOLIYA TASHKILOTI» MChJning Direktor
D2: =""&umumiy_malumot!B161&"ga" -> Obidov A.Sh.ga
A4: =""&umumiy_malumot!C64&" olish uchun Ariza" -> Mikrokredit olish uchun Ariza
A6: =""&umumiy_malumot!B28&".-da yashovchi O‘zbekiston Respublikasi fuqarosi "&umumiy_malumot!B8&"dan. " -> TOSHKENT VILOYATI CHINOZ TUMANI ALISHER NAVOIY MFY SOBIR RAHIMOV KO'CHASI 36 UY.-da yashovchi O‘zbekiston Respublikasi fuqarosi NORINBOYEVA SOXIBA IZZATILLAYEVNAdan.
A7: ="Tug'ilgan kuni: "&umumiy_malumot!B15&"" -> Tug'ilgan kuni: 19.10.1985 yil
A8: ="Pasport seriyasi: "&umumiy_malumot!B16&" "&umumiy_malumot!B20&"" -> Pasport seriyasi: AE 5547691 IIV 27256 tomonidan 22.12.2025 yilda berilgan
A9: ="Asosiy ish joyi : "&umumiy_malumot!B58&"" -> Asosiy ish joyi : O'Z O'ZINI BAND QILGAN FUQARO
A10: ="Lavozimi: "&umumiy_malumot!B59&"" -> Lavozimi: BOLALAR O'YINCHOGINI ISHLAB CHIQARISH (UY SHAROITIDA)
A11: ="O’rtacha oylik daromadi: "&FIXED(mijoz_anketasi!B27,2)&" so'm." -> O’rtacha oylik daromadi: 30 000 000,00 so'm.
A12: ="Menga quyidagi shartlarda "&umumiy_malumot!B65&" berishingizni so’rayman:" -> Menga quyidagi shartlarda mikrokredit berishingizni so’rayman:
A13: =""&umumiy_malumot!C64&" summasi: "&FIXED(umumiy_malumot!B76,2)&" ("&umumiy_malumot!B77&") so'm." -> Mikrokredit summasi: 175 000 000,00 (yuz yetmish besh million so'm) so'm.
A14: =""&umumiy_malumot!C64&" muddati: "&umumiy_malumot!B82&" ("&umumiy_malumot!B83&") oy." -> Mikrokredit muddati: 36 (O'ttiz olti ) oy.
A15: =""&umumiy_malumot!C64&"dan foydalanganlik uchun foiz stavkasi: yillik "&umumiy_malumot!B86&"% ("&umumiy_malumot!B87&") foiz" -> Mikrokreditdan foydalanganlik uchun foiz stavkasi: yillik 55% (Ellik besh ) foiz
A16: =""&umumiy_malumot!C64&" bo'yicha asosiy qarz va foizlarni to'lash:" -> Mikrokredit bo'yicha asosiy qarz va foizlarni to'lash:
A17: =" - "&umumiy_malumot!B65&" shartnomasi bo'yicha har oy differensial to'lovlari amalga oshiriladi" -> - mikrokredit shartnomasi bo'yicha har oy differensial to'lovlari amalga oshiriladi
A18: =" - "&umumiy_malumot!B65&" shartnomasi bo'yicha har oy annuitet to'lovlari amalga oshiriladi" -> - mikrokredit shartnomasi bo'yicha har oy annuitet to'lovlari amalga oshiriladi
A19: =IF(umumiy_malumot!B78=umumiy_malumot!C78,kredit_ariza!A17:D17,IF(umumiy_malumot!B78=umumiy_malumot!D78,kredit_ariza!A18:D18)) -> - mikrokredit shartnomasi bo'yicha har oy differensial to'lovlari amalga oshiriladi
A20: =IF(DAY(umumiy_malumot!E67)<15," "," Oxirgi yakuniy to'lov "&umumiy_malumot!B65&" shartnomasi tuzilgan kundan boshlab oxirgi oyning oxirgi kunida amalga oshiriladi") -> Oxirgi yakuniy to'lov mikrokredit shartnomasi tuzilgan kundan boshlab oxirgi oyning oxirgi kunida amalga oshiriladi
A21: =""&umumiy_malumot!C64&" ta’minoti::" -> Mikrokredit ta’minoti::
A22: ="1. "&IF(umumiy_malumot!B110="Avtotransport",A26,A23)&"" -> 1. Egalik huquqi NORINBAYEVA SAPURA MAMADALIYEVNAga tegishli bo'lgan umumiy yer maydoni - 700,qurilish osti maydoni-340.11, umumiy foydali maydoni-114.59, yashash maydoni - 163.19 Yakka tartibdagi uy-joy, TOSHKENT VILOYATI CHINOZ TUMANI ALISHER NAVOIY MFY SOBIR RAHIMOV KO'CHASI 36 UY
A23: =IF(umumiy_malumot!B99=umumiy_malumot!C99,A25,IF(umumiy_malumot!B99=umumiy_malumot!D99,A24,0)) -> Egalik huquqi NORINBAYEVA SAPURA MAMADALIYEVNAga tegishli bo'lgan umumiy yer maydoni - 700,qurilish osti maydoni-340.11, umumiy foydali maydoni-114.59, yashash maydoni - 163.19 Yakka tartibdagi uy-joy, TOSHKENT VILOYATI CHINOZ TUMANI ALISHER NAVOIY MFY SOBIR RAHIMOV KO'CHASI 36 UY
A24: =" - Navbatdagi garov (ipoteka) Egalik huquqi asosida "&umumiy_malumot!C124&"ga "&umumiy_malumot!C133&", umumiy maydoni - "&umumiy_malumot!C137&" va yashash maydoni - "&umumiy_malumot!C140&", manzili: "&umumiy_malumot!C130&"." -> - Navbatdagi garov (ipoteka) Egalik huquqi asosida NORINBAYEVA SAPURA MAMADALIYEVNAga Yakka tartibdagi uy-joy, umumiy maydoni - 163.19 va yashash maydoni - 700, manzili: TOSHKENT VILOYATI CHINOZ TUMANI ALISHER NAVOIY MFY SOBIR RAHIMOV KO'CHASI 36 UY.
A25: =" Egalik huquqi "&umumiy_malumot!C124&"ga tegishli bo'lgan umumiy yer maydoni - "&umumiy_malumot!C140&",qurilish osti maydoni-"&umumiy_malumot!C139&", umumiy foydali maydoni-"&umumiy_malumot!C138&", yashash maydoni - "&umumiy_malumot!C137&" "&umumiy_malumot!C133&", "&umumiy_malumot!C130&" " -> Egalik huquqi NORINBAYEVA SAPURA MAMADALIYEVNAga tegishli bo'lgan umumiy yer maydoni - 700,qurilish osti maydoni-340.11, umumiy foydali maydoni-114.59, yashash maydoni - 163.19 Yakka tartibdagi uy-joy, TOSHKENT VILOYATI CHINOZ TUMANI ALISHER NAVOIY MFY SOBIR RAHIMOV KO'CHASI 36 UY | G25: =" umumiy yer maydoni - "&C140&", qurilish osti maydoni- "&C139&", umumiy foydali maydoni - "&C137&" yashash maydoni - "&C138&"" -> umumiy yer maydoni - , qurilish osti maydoni- , umumiy foydali maydoni - yashash maydoni -
A26: =IF(umumiy_malumot!B99=umumiy_malumot!C99,kredit_ariza!A28:D28,IF(umumiy_malumot!B99=umumiy_malumot!D99,kredit_ariza!A27:D27,0)) -> Egalik huquqi NORINBAYEVA SAPURA MAMADALIYEVNAga tegishli bo'lgan garovga olingan avtomobil markasi CHEVROLET COBALT, rangi - OQ SUMMIT WHITE, ishlab chiqarilgan yili - 2024, davlat raqam belgisi 01Z067RC, kuzov turi - YENGIL SEDAN, kuzov raqami XWBJA69VERA108471, dvigatel raqami B15D213241352MTAX0118, shassi raqami - RAQAMSIZ
A27: =" Egalik huquqi "&umumiy_malumot!B124&"ga tegishli bo'lgan "&umumiy_malumot!B132&", "&umumiy_malumot!B140&", davlat raqam belgisi "&umumiy_malumot!B133&", "&umumiy_malumot!B134&", "&umumiy_malumot!B137&" avtotransport vositasi " -> Egalik huquqi NORINBAYEVA SAPURA MAMADALIYEVNAga tegishli bo'lgan CHEVROLET COBALT, rangi - OQ SUMMIT WHITE, ishlab chiqarilgan yili - 2024, davlat raqam belgisi 01Z067RC, kuzov turi - YENGIL SEDAN, kuzov raqami XWBJA69VERA108471, dvigatel raqami B15D213241352MTAX0118, shassi raqami - RAQAMSIZ avtotransport vositasi
A28: =" Egalik huquqi "&umumiy_malumot!B124&"ga tegishli bo'lgan garovga olingan avtomobil markasi "&umumiy_malumot!B132&", "&umumiy_malumot!B140&", davlat raqam belgisi "&umumiy_malumot!B133&", "&umumiy_malumot!B134&", "&umumiy_malumot!B137&"" -> Egalik huquqi NORINBAYEVA SAPURA MAMADALIYEVNAga tegishli bo'lgan garovga olingan avtomobil markasi CHEVROLET COBALT, rangi - OQ SUMMIT WHITE, ishlab chiqarilgan yili - 2024, davlat raqam belgisi 01Z067RC, kuzov turi - YENGIL SEDAN, kuzov raqami XWBJA69VERA108471, dvigatel raqami B15D213241352MTAX0118, shassi raqami - RAQAMSIZ
A29: ="2. «"&umumiy_malumot!B154&"» АJ sug‘urta kompaniyasi tomonidan "&umumiy_malumot!C64&" to'lamaslik xavfini "&FIXED(umumiy_malumot!B155,2)&"("&umumiy_malumot!B156&") so ' m miqdoriga sug’urta qilish" -> 2. «АО СК "IMPEX INSURANCE"» АJ sug‘urta kompaniyasi tomonidan Mikrokredit to'lamaslik xavfini 35 000 000,00(o'ttiz besh million so'm) so ' m miqdoriga sug’urta qilish
A31: ="Mazkur ariza bilan "&umumiy_malumot!B158&"ga men va soʻralayotgan "&umumiy_malumot!B65&" boʻyicha barcha zarur maʼlumotlarni quyida ko’rsatilgan tashkilotlarga taqdim etish va olishga roziligimni bildirib, ushbu amaliyotlarni o’tkazish uchun huquq beraman:" -> Mazkur ariza bilan «PULLOL BUSINESS MIKROMOLIYA TASHKILOTI» MChJga men va soʻralayotgan mikrokredit boʻyicha barcha zarur maʼlumotlarni quyida ko’rsatilgan tashkilotlarga taqdim etish va olishga roziligimni bildirib, ushbu amaliyotlarni o’tkazish uchun huquq beraman:
A32: □ O‘zbekiston Respublikasi Markaziy banki huzuridagi kredit axborotining davlat reestri;
A33: □ Kredit-axborot tahliliy markazi «O‘zbekiston Respublikasi kredit byurosi» MChJ;
A34: □ Garov reestri taqdim etilgan garov mulki haqida.
A35: ="Ariza berilgan sana: "&TEXT(umumiy_malumot!B2,"ДД.ММ.ГГГГ")&"y." -> Ariza berilgan sana: 16.02.2026y.
A37: Ariza berilgan kuniga barcha ma'lumotlar ishonchligini tasdiqlab, ushbu arizani imzolayman
A40: =umumiy_malumot!B5 -> NORINBOYEVA SOXIBA IZZATILLAYEVNA | D40: ________________
D41: (imzo)
A43: =umumiy_malumot!A161 -> Direktor | D43: =umumiy_malumot!B161 -> Obidov A.Sh.

Sheet majburiyatnoma
A3: MAJBURIYATNOMA
A4: =" Men, fuqaro "&umumiy_malumot!B5&" "&umumiy_malumot!B160&" bilan "&umumiy_malumot!B69&" sanasidagi "&umumiy_malumot!B66&"-sonli shartnomaning garov ta'minoti sifatida taqdim etilayotgan mulk "&umumiy_malumot!B132&" rusumli avtotransport vositasini qonunga xilof ravishda o‘zlashtirmaslikka, yashirmaslikka, nobud qilmaslikka yoki unga shikast yetkazmaslik majburiyatini olaman." -> Men, fuqaro NORINBOYEVA SOXIBA IZZATILLAYEVNA «PULLOL BUSINESS MIKROMOLIYA TASHKILOTI» MChJ bilan 16 fevral 2026 y. sanasidagi № 110-sonli shartnomaning garov ta'minoti sifatida taqdim etilayotgan mulk CHEVROLET COBALT rusumli avtotransport vositasini qonunga xilof ravishda o‘zlashtirmaslikka, yashirmaslikka, nobud qilmaslikka yoki unga shikast yetkazmaslik majburiyatini olaman.
A5: Ushbu majburiyatlarimni bajarmagan taqdirimda O'zbekiston Respublikasi jinoyat kodeksining 233-moddasi talablari asosida javobgarlik tog'risida ogohlantrildim.
A7: =umumiy_malumot!B5 -> NORINBOYEVA SOXIBA IZZATILLAYEVNA | B7: Imzo_____________
A9: =umumiy_malumot!B5 -> NORINBOYEVA SOXIBA IZZATILLAYEVNA | B9: Imzo_____________
A11: ="sana: "&TEXT(umumiy_malumot!B2,"ДД.ММ.ГГГГ")&" y." -> sana: 16.02.2026 y.

Sheet xulosa
A1: =""&umumiy_malumot!B158&" mikromoliya tashkilotining Xulosasi" -> «PULLOL BUSINESS MIKROMOLIYA TASHKILOTI» MChJ mikromoliya tashkilotining Xulosasi
A3: MIJOZ HAQIDA MA'LUMOTLAR
A4: ="Mijozning to'liq ismi sharifi: "&umumiy_malumot!B5&"" -> Mijozning to'liq ismi sharifi: NORINBOYEVA SOXIBA IZZATILLAYEVNA
A5: ="Tug'ilgan sanasi: "&umumiy_malumot!B15&"" -> Tug'ilgan sanasi: 19.10.1985 yil
A6: ="Pasport seriyasi "&umumiy_malumot!B16&" "&umumiy_malumot!B20&", amal qilish muddati - "&umumiy_malumot!B21&"" -> Pasport seriyasi AE 5547691 IIV 27256 tomonidan 22.12.2025 yilda berilgan, amal qilish muddati - 21.12.2035 y.
A7: ="Ro‘yxatdan o‘tgan manzili: "&umumiy_malumot!B22&", mo'ljal: "&umumiy_malumot!B26&"" -> Ro‘yxatdan o‘tgan manzili: TOSHKENT VILOYATI CHINOZ TUMANI ALISHER NAVOIY MFY SOBIR RAHIMOV KO'CHASI 36 UY, mo'ljal: 1 MAKTAB BALNITSA CHINOZ
A8: ="Ish joyi: "&umumiy_malumot!B52&" lavozimi "&umumiy_malumot!B49&"da "&umumiy_malumot!B44&"" -> Ish joyi: lavozimi BOLALAR O'YINCHOGINI ISHLAB CHIQARISH (UY SHAROITIDA)da O'Z O'ZINI BAND QILGAN FUQARO
A10: ="Mijoz tomonidan so’ralgan "&umumiy_malumot!B65&" shartlari:" -> Mijoz tomonidan so’ralgan mikrokredit shartlari:
A11: =kredit_ariza!A13:D13 -> Mikrokredit summasi: 175 000 000,00 (yuz yetmish besh million so'm) so'm.
A12: =kredit_ariza!A14:D14 -> Mikrokredit muddati: 36 (O'ttiz olti ) oy.
A13: =kredit_ariza!A15:D15 -> Mikrokreditdan foydalanganlik uchun foiz stavkasi: yillik 55% (Ellik besh ) foiz
A14: =kredit_ariza!A16:D16 -> Mikrokredit bo'yicha asosiy qarz va foizlarni to'lash:
A15: =kredit_ariza!A19:D19 -> - mikrokredit shartnomasi bo'yicha har oy differensial to'lovlari amalga oshiriladi
A16: =kredit_ariza!A20:D20 -> Oxirgi yakuniy to'lov mikrokredit shartnomasi tuzilgan kundan boshlab oxirgi oyning oxirgi kunida amalga oshiriladi
A17: =kredit_ariza!A21:D21 -> Mikrokredit ta’minoti::
A18: =kredit_ariza!A22:D22 -> 1. Egalik huquqi NORINBAYEVA SAPURA MAMADALIYEVNAga tegishli bo'lgan umumiy yer maydoni - 700,qurilish osti maydoni-340.11, umumiy foydali maydoni-114.59, yashash maydoni - 163.19 Yakka tartibdagi uy-joy, TOSHKENT VILOYATI CHINOZ TUMANI ALISHER NAVOIY MFY SOBIR RAHIMOV KO'CHASI 36 UY
A19: Mijozning moliyaviy holati
A20: ="Anketaga muvofiq "&umumiy_malumot!B9&"ning o‘rtacha oylik daromadi "&FIXED(mijoz_anketasi!B27)&" so‘mni tashkil etdi." -> Anketaga muvofiq NORINBOYEVA S.I.ning o‘rtacha oylik daromadi 30 000 000,00 so‘mni tashkil etdi.
A21: ="Mijozning o'rtacha oylik xarajatlari "&FIXED(mijoz_anketasi!F27)&" so'mni tashkil etdi" -> Mijozning o'rtacha oylik xarajatlari 1 800 000,00 so'mni tashkil etdi
A22: =IF(umumiy_malumot!B78=umumiy_malumot!C78,xulosa!A23:E23,xulosa!A24:E24) -> Mikrokredit shartnomasi bo'yicha birinchi oy uchun to'lov 12 808 694,88 so'mni tashkil etadi.
A23: =""&umumiy_malumot!C64&" shartnomasi bo'yicha birinchi oy uchun to'lov "&FIXED(umumiy_malumot!B91)&" so'mni tashkil etadi." -> Mikrokredit shartnomasi bo'yicha birinchi oy uchun to'lov 12 808 694,88 so'mni tashkil etadi.
A24: =""&umumiy_malumot!C64&" bo‘yicha oylik "&umumiy_malumot!B78&" to‘lovi miqdori "&FIXED(umumiy_malumot!B91)&" so‘mni tashkil etadi." -> Mikrokredit bo‘yicha oylik differensial to‘lovi miqdori 12 808 694,88 so‘mni tashkil etadi.
A25: Mijoz quyidagi majburiyatlarga ega: "TOShKENT Sh., "ANOR BANK" АKTSIYADORLIK JАMIYATI 106 139 813.00 so'm, Ayni paytda muddati o'tgan qarzdorligi mavjud emas. O‘rtacha oylik to‘lov 5 353 870.46 so‘mni tashkil qiladi
A26: =""&umumiy_malumot!C64&" bo’yicha ta’minot:" -> Mikrokredit bo’yicha ta’minot:
A27: =" - "&umumiy_malumot!B124&" ga mulk huquqi asosida tegishli avtotransport vositasi "&umumiy_malumot!B132&" , quyidagi tafsilotlarga muvofiq:" -> - NORINBAYEVA SAPURA MAMADALIYEVNA ga mulk huquqi asosida tegishli avtotransport vositasi CHEVROLET COBALT , quyidagi tafsilotlarga muvofiq:
A28: =" - "&umumiy_malumot!C124&" ga mulk huquqi asosida tegishli ko'chmas mulk shaklida "&umumiy_malumot!C133&", manzili: "&umumiy_malumot!C130&", quyidagi tafsilotlarga muvofiq:" -> - NORINBAYEVA SAPURA MAMADALIYEVNA ga mulk huquqi asosida tegishli ko'chmas mulk shaklida Yakka tartibdagi uy-joy, manzili: TOSHKENT VILOYATI CHINOZ TUMANI ALISHER NAVOIY MFY SOBIR RAHIMOV KO'CHASI 36 UY, quyidagi tafsilotlarga muvofiq:
A29: =IF(umumiy_malumot!B110="Avtotransport",xulosa!A27:E27,xulosa!A28:E28) -> - NORINBAYEVA SAPURA MAMADALIYEVNA ga mulk huquqi asosida tegishli ko'chmas mulk shaklida Yakka tartibdagi uy-joy, manzili: TOSHKENT VILOYATI CHINOZ TUMANI ALISHER NAVOIY MFY SOBIR RAHIMOV KO'CHASI 36 UY, quyidagi tafsilotlarga muvofiq:
A30: =dalolatnoma!A29 -> Nomi | B30: =dalolatnoma!C29 -> Qurilish osti maydoni, (m2) | C30: =dalolatnoma!D29 -> Umumiy foydali maydoni, (m2) | D30: =dalolatnoma!E29 -> Yashash maydoni, (m2) | E30: =dalolatnoma!F29 -> Kelishilgan garov qiymati, so'm
A31: =dalolatnoma!A30 -> Yakka tartibdagi uy-joy | B31: =dalolatnoma!C30 -> 340.11 | C31: =dalolatnoma!D30 -> 163.19 | D31: =dalolatnoma!E30 -> 114.59 | E31: =dalolatnoma!F30 -> 210 000 000,00 (ikki yuz o'n million so'm)
A32: =dalolatnoma!A22 -> -* ko'chmas mulk egasi: NORINBAYEVA SAPURA MAMADALIYEVNA
A33: =dalolatnoma!A23 -> -* reest raqami: №1727256/Y-25006342
A34: =dalolatnoma!A24 -> -* kadastr raqami: 13.08.2025 y. №11:13:42:02:01:1840
A35: =dalolatnoma!A25 -> -* manzili: TOSHKENT VILOYATI CHINOZ TUMANI ALISHER NAVOIY MFY SOBIR RAHIMOV KO'CHASI 36 UY
A36: =""&umumiy_malumot!B158&" mikromoliya tashkilotining Xulosasi" -> «PULLOL BUSINESS MIKROMOLIYA TASHKILOTI» MChJ mikromoliya tashkilotining Xulosasi
A37: =""&umumiy_malumot!B158&" kredit qo‘mitasining xulosasiga quyidagi shartlarda "&umumiy_malumot!B10&"ga "&umumiy_malumot!B65&" berish masalasi kiritiladi:" -> «PULLOL BUSINESS MIKROMOLIYA TASHKILOTI» MChJ kredit qo‘mitasining xulosasiga quyidagi shartlarda NORINBOYEVA SOXIBA IZZATILLAYEVNAga mikrokredit berish masalasi kiritiladi:
A38: =A11 -> Mikrokredit summasi: 175 000 000,00 (yuz yetmish besh million so'm) so'm.
A39: =A12 -> Mikrokredit muddati: 36 (O'ttiz olti ) oy.
A40: =A13 -> Mikrokreditdan foydalanganlik uchun foiz stavkasi: yillik 55% (Ellik besh ) foiz
A41: =A14 -> Mikrokredit bo'yicha asosiy qarz va foizlarni to'lash:
A42: =A15 -> - mikrokredit shartnomasi bo'yicha har oy differensial to'lovlari amalga oshiriladi
A43: =A16 -> Oxirgi yakuniy to'lov mikrokredit shartnomasi tuzilgan kundan boshlab oxirgi oyning oxirgi kunida amalga oshiriladi
A44: =A17 -> Mikrokredit ta’minoti::
A45: =A18 -> 1. Egalik huquqi NORINBAYEVA SAPURA MAMADALIYEVNAga tegishli bo'lgan umumiy yer maydoni - 700,qurilish osti maydoni-340.11, umumiy foydali maydoni-114.59, yashash maydoni - 163.19 Yakka tartibdagi uy-joy, TOSHKENT VILOYATI CHINOZ TUMANI ALISHER NAVOIY MFY SOBIR RAHIMOV KO'CHASI 36 UY
A47: =""&umumiy_malumot!B158&" mikromoliya tashkilotining xulosasi "&TEXT(umumiy_malumot!B2,"ДД.ММ.ГГГГ")&" y. tayyorlangan" -> «PULLOL BUSINESS MIKROMOLIYA TASHKILOTI» MChJ mikromoliya tashkilotining xulosasi 16.02.2026 y. tayyorlangan
A52: =""&umumiy_malumot!B158&" mikromoliya tashkilotining Kredit qo‘mitasi a’zolari "&umumiy_malumot!B158&" mikromoliya tashkilotining xulosasi va Mijoz tomonidan taqdim etilgan ma’lumotlar bilan tanishdilar:" -> «PULLOL BUSINESS MIKROMOLIYA TASHKILOTI» MChJ mikromoliya tashkilotining Kredit qo‘mitasi a’zolari «PULLOL BUSINESS MIKROMOLIYA TASHKILOTI» MChJ mikromoliya tashkilotining xulosasi va Mijoz tomonidan taqdim etilgan ma’lumotlar bilan tanishdilar:
A53: Imzolaganlar ro'yxati:
A55: =umumiy_malumot!A172 -> Kredit bo'limi menejeri | D55: =umumiy_malumot!B172 -> Eshbekov S. O.
A59: =umumiy_malumot!A170 -> Kreditlash bo’limi boshlig’i | D59: =umumiy_malumot!B170 -> Akramov R.N.
A63: =umumiy_malumot!A171 -> Monitoring bo’limi boshlig’i | D63: =umumiy_malumot!B171 -> Omanlikov O.O.
A67: direktor | D67: A.Obidov

Sheet shartnoma
A1: =""&umumiy_malumot!C64&" shartnoma "&umumiy_malumot!B66&"" -> Mikrokredit shartnoma № 110
A3: ="Toshkent shahri "&umumiy_malumot!B70&"" -> Toshkent shahri 16 fevral 2026 y.
A5: =""&umumiy_malumot!B158&", bundan buyon «Mikromoliya tashkiloti» deb nomlanuvchi, Ustav va 14.08.2023 yildagi 27-13/968-sonli Litsenziya asosida faoliyat yurituvchi "&umumiy_malumot!A161&" "&umumiy_malumot!B161&" bir tomondan va o‘z manfaati yo‘lida hamda o‘z nomidan harakat qiluvchi O‘zbekiston Respublikasi fuqarosi "&umumiy_malumot!B5&" (pasport raqami "&umumiy_malumot!B16&", "&umumiy_malumot!C20&" ), bundan buyon «Qarz oluvchi» deb nomlanuvchi, boshqa tomondan, birgalikda “Tomonlar” yoki alohida “Tomon” deb nomlanuvchilar, Qarz oluvchi tomonidan "&TEXT(umumiy_malumot!B2,"ДД.ММ.ГГГГ")&" yil,"&umumiy_malumot!B65&" olish uchun ariza berilganligini hisobga olib, ushbu "&umumiy_malumot!C64&" shartnomasini (bundan keyin – «Shartnoma») quyidagilar haqida tuzdilar:" -> «PULLOL BUSINESS MIKROMOLIYA TASHKILOTI» MChJ, bundan buyon «Mikromoliya tashkiloti» deb nomlanuvchi, Ustav va 14.08.2023 yildagi 27-13/968-sonli Litsenziya asosida faoliyat yurituvchi Direktor Obidov A.Sh. bir tomondan va o‘z manfaati yo‘lida hamda o‘z nomidan harakat qiluvchi O‘zbekiston Respublikasi fuqarosi NORINBOYEVA SOXIBA IZZATILLAYEVNA (pasport raqami AE 5547691, IIV 27256 tomonidan 22.12.2025 yilda berilgan ), bundan buyon «Qarz oluvchi» deb nomlanuvchi, boshqa tomondan, birgalikda “Tomonlar” yoki alohida “Tomon” deb nomlanuvchilar, Qarz oluvchi tomonidan 16.02.2026 yil,mikrokredit olish uchun ariza berilganligini hisobga olib, ushbu Mikrokredit shartnomasini (bundan keyin – «Shartnoma») quyidagilar haqida tuzdilar:
A7: 1. SHARTNOMA PREDMETI
A8: ="1.1. Mikromoliya tashkiloti Qarz oluvchiga umumiy miqdori "&FIXED(umumiy_malumot!B76,2)&" ("&umumiy_malumot!C77&") bo‘lgan "&umumiy_malumot!B65&"ni "&umumiy_malumot!B71&" dan "&umumiy_malumot!B73&" gacha bo'lgan muddatga naqd pul va/yoki o'tkazmasi shaklida ajratadi." -> 1.1. Mikromoliya tashkiloti Qarz oluvchiga umumiy miqdori 175 000 000,00 (Yuz yetmish besh million so'm) bo‘lgan mikrokreditni 16 fevral 2026 y. dan 16 fevral 2029 y. gacha bo'lgan muddatga naqd pul va/yoki o'tkazmasi shaklida ajratadi.
A9: ="1.2. Qarz oluvchi to‘lovlilik, muddatlilik va ta’minlanganlik tamoyillariga amal qilgan holda "&umumiy_malumot!B65&"dan foydalanish majburiyatini o‘z zimmasiga oladi." -> 1.2. Qarz oluvchi to‘lovlilik, muddatlilik va ta’minlanganlik tamoyillariga amal qilgan holda mikrokreditdan foydalanish majburiyatini o‘z zimmasiga oladi.
A11: ="2. "&umumiy_malumot!D64&" BERISH VA QAYTARISH TARTIBI" -> 2. MIKROKREDIT BERISH VA QAYTARISH TARTIBI
A12: ="2.1. Ushbu Shartnomaning 1.1.-bandida ko‘rsatilgan summa miqdoridagi "&umumiy_malumot!B65&" Mikromoliya tashkiloti kassasidan naqd pul shaklida va/yoki plastik kartaga o‘tkazish yuli bilan beriladi." -> 2.1. Ushbu Shartnomaning 1.1.-bandida ko‘rsatilgan summa miqdoridagi mikrokredit Mikromoliya tashkiloti kassasidan naqd pul shaklida va/yoki plastik kartaga o‘tkazish yuli bilan beriladi.
A13: ="2.2. "&umumiy_malumot!C64&" berish ushbu Shartnoma tuzilgan va Qarz oluvchi tomonidan ushbu shartnomaning 3-bo‘limiga muvofiq garov ta'minoti ta'minlangandan so‘ng 10 kalendar kundan kechiktirmay amalga oshiriladi." -> 2.2. Mikrokredit berish ushbu Shartnoma tuzilgan va Qarz oluvchi tomonidan ushbu shartnomaning 3-bo‘limiga muvofiq garov ta'minoti ta'minlangandan so‘ng 10 kalendar kundan kechiktirmay amalga oshiriladi.
A14: ="2.3. "&umumiy_malumot!C64&" Qarz oluvchi tomonidan ushbu Shartnomaning ajralmas qismi hisoblanadigan 1-ilovasida ko‘rsatilgan to‘lov jadvalida (bundan keyin - To‘lov jadvali) belgilangan miqdor, tartib va muddatlarda qaytariladi." -> 2.3. Mikrokredit Qarz oluvchi tomonidan ushbu Shartnomaning ajralmas qismi hisoblanadigan 1-ilovasida ko‘rsatilgan to‘lov jadvalida (bundan keyin - To‘lov jadvali) belgilangan miqdor, tartib va muddatlarda qaytariladi.
A15: ="2.4. Mikromoliya tashkiloti, "&umumiy_malumot!B65&" berilgan vaqtdan boshlab, "&umumiy_malumot!B65&" miqdorining qoldiq summasiga "&umumiy_malumot!B86&"% ("&umumiy_malumot!C87&") foiz yillik va yiliga 365/366 kunlik hisobidan foizlar hisoblaydi. To'lov jadvaliga muvofiq asosiy qarz bo'yicha navbatdagi to'lov buzilgan hollarda, "&"foiz stavkasi oshiriladi va Mikromoliya tashkiloti "&umumiy_malumot!B65&"ning muddati o'tgan asosiy qarz summasiga yillik "&umumiy_malumot!B89&"% ("&umumiy_malumot!B90&") foiz miqdorida foizlar hisoblaydi." -> 2.4. Mikromoliya tashkiloti, mikrokredit berilgan vaqtdan boshlab, mikrokredit miqdorining qoldiq summasiga 55% (Ellik besh ) foiz yillik va yiliga 365/366 kunlik hisobidan foizlar hisoblaydi. To'lov jadvaliga muvofiq asosiy qarz bo'yicha navbatdagi to'lov buzilgan hollarda, foiz stavkasi oshiriladi va Mikromoliya tashkiloti mikrokreditning muddati o'tgan asosiy qarz summasiga yillik 155% (bir yuz ellik besh) foiz miqdorida foizlar hisoblaydi.
A16: 2.4.1 Qarz oluvchining xisob raqamlaridan shartnomaning 4.1.2 bandida ko‘rsatilgan tartibda yechib olingan pul mablag‘lari yechib olinganidan so‘ng mijoz tomonidan kredit qarzdorligini so‘ndirish uchun bank kassalari orqali to‘langan pul mablag‘lari yoki mijoz tomonidan kredit qarzdorligini so‘ndirish uchun bank kassalari orqali to‘langandan so‘ng qarz oluvchining xisob raqamlaridan shartnomaning 4.1.2 bandida ko‘rsatilgan tartibda yechib olingan pul mablag‘larining bir oylik kredit to‘lovini so‘ndirishga yo‘naltirilgan miqdoridan ortiqcha qismi qarz oluvchining to‘lov amalga oshirilgan kundan boshlab 3 bank ish kuni ichida yo‘llagan arizasiga asosan qarz oluvchiga qaytarilishi mumkun. 2.5. Foizlar To‘lov jadvaliga muvofiq asosiy qarzni qaytarish uchun belgilangan sanada to‘lanadi. 2.5.1 Qarz oluvchi tomonidan shartnomaning 2.4 bandida ko‘rsatilgan muddatda ortiqcha to‘langan pul mablag‘larini qaytarish to‘g‘risida ariza berilmagan taqdirda to‘langan ortiqcha pul mablag‘lari mijozning asosiy qarzdorligini so‘ndirishga yo‘naltiriladi.
A17: =CONCATENATE(C17,H17,I17) -> 2.6 Qarz oluvchi tomonidan to‘lov jadvalida ko‘rsatilgan muddatdan oldin xamda to‘lov jadvalida ko‘rsatilgan oylik kredit qarzdorligini so‘ndirish miqdoridan ko‘p miqdorda to‘lovni amalga oshirib, to‘langan pul mablag‘larini asosiy kredit qarzdorligini so‘ndirishga yo‘naltirilishini so‘ralganda qarz oluvchining kredit qarzdorligini so‘ndirish uchun to‘lagan pul mablag‘laridan kredit qarzdorligi to‘langan oy uchun to‘lov jadvali bo‘yicha so‘ndirilishi lozim bo‘lgan foiz qarzdorligi summasi, to‘lov jadvalida foiz qarzdorligi so‘ndirilishi ko‘rsatilgan muddatga qadar tashkilotning xisob raqamida saqlanib to‘lov jadvalida ko‘rsatilgan sanada oylik foiz qarzdorligini so‘ndirishga yo‘naltiriladi. 2.6.1. Qarz oluvchi tomonidan olingan mikrokreditni va undan foydalanganlik uchun foizlarni qaytarish bo‘yicha muddati o‘tgan qarzdorlik hosil bo‘lganda Qarz oluvchi tomonidan ko‘rsatilgan qarzdorlikni to‘lash hisobiga to‘lanadigan summalar quyidagi tartibda hisobga olinadi: | C17: 2.6 Qarz oluvchi tomonidan to‘lov jadvalida ko‘rsatilgan muddatdan oldin xamda to‘lov jadvalida ko‘rsatilgan oylik kredit qarzdorligini so‘ndirish miqdoridan ko‘p miqdorda to‘lovni amalga oshirib, to‘langan pul mablag‘larini asosiy kredit qarzdorligini so‘ndirishga yo‘naltirilishini so‘ralganda qarz oluvchining kredit qarzdorligini so‘ndirish uchun to‘lagan pul mablag‘laridan kredit qarzdorligi to‘langan oy uchun to‘lov jadvali bo‘yicha so‘ndirilishi lozim bo‘lgan foiz qarzdorligi summasi, to‘lov jadvalida foiz qarzdorligi so‘ndirilishi ko‘rsatilgan muddatga qadar tashkilotning xisob raqamida saqlanib to‘lov jadvalida ko‘rsatilgan sanada oylik foiz qarzdorligini so‘ndirishga yo‘naltiriladi. 2.6.1. Qarz oluvchi tomonidan olingan | H17: =umumiy_malumot!B65 -> mikrokredit | I17: ni va undan foydalanganlik uchun foizlarni qaytarish bo‘yicha muddati o‘tgan qarzdorlik hosil bo‘lganda Qarz oluvchi tomonidan ko‘rsatilgan qarzdorlikni to‘lash hisobiga to‘lanadigan summalar quyidagi tartibda hisobga olinadi:
A18: - jarima sanksiyalarni to‘lash; - to‘lov muddati o‘tgan foizlarni to‘lash; - to‘lov muddati o‘tgan asosiy qarzni to‘lash; - muddatli qarz bo‘yicha hisoblangan foizlarni to‘lash; - muddatli asosiy qarzni to‘lash; - Mikromoliya tashkilotning boshqa zararlarini qoplash.
A19: ="2.7. Qarz oluvchi Mikromoliya tashkilotining "&umumiy_malumot!B65&" bo‘yicha asosiy summasi, hisoblangan foizlarni, penya va boshqa moliyaviy talablarini ham naqd pul shaklida, ham naqdsiz shaklda qaytarib beradi." -> 2.7. Qarz oluvchi Mikromoliya tashkilotining mikrokredit bo‘yicha asosiy summasi, hisoblangan foizlarni, penya va boshqa moliyaviy talablarini ham naqd pul shaklida, ham naqdsiz shaklda qaytarib beradi.
A20: ="2.8. Qarz oluvchi "&umumiy_malumot!B65&" miqdorini muddatidan oldin qaytarish, shuningdek, bu haqida Mikromoliya tashkilotini albatta ogohlantirgan holda ulardan aniq foydalangan muddat uchun hisoblangan foizlarni to‘lash huquqiga ega." -> 2.8. Qarz oluvchi mikrokredit miqdorini muddatidan oldin qaytarish, shuningdek, bu haqida Mikromoliya tashkilotini albatta ogohlantirgan holda ulardan aniq foydalangan muddat uchun hisoblangan foizlarni to‘lash huquqiga ega.
A21: =CONCATENATE(C21,H21,I21) -> 2.9. Qarz oluvchi jismoniy shaxslarning kreditlar (mikrokreditlar) bo‘yicha qarz yukini hisoblash tartibi, qarz yukining ruxsat etilgan miqdori, shuningdek qarz yuki o‘sishini cheklash to‘g‘risidagi Nizomga muvofiq (O’zbekiston Respublikasi Adliya vazirligi tomonidan 19.12.2019 y. 3205-son bilan ro‘yxatga olingan Markaziy bank Boshqaruvining 28.09.2019 y. 24/5-son qarori bilan tasdiqlangan), qarz yuki ko‘rsatkichi har bir qarz oluvchiga qarz beruvchi tomonidan mikrokredit ajratishda uning summasi va qarz oluvchining amaldagi kredit (mikrokredit) shartnomalari bo‘yicha asosiy qarz qoldig‘i yig‘indisi bazaviy hisoblash miqdorining 50 baravaridan oshganda hisoblanadi. | C21: ="2.9. Qarz oluvchi jismoniy shaxslarning kreditlar ("&umumiy_malumot!B65&"lar) bo‘yicha qarz yukini hisoblash tartibi, qarz yukining ruxsat etilgan miqdori, shuningdek qarz yuki o‘sishini cheklash to‘g‘risidagi Nizomga muvofiq (O’zbekiston Respublikasi Adliya vazirligi tomonidan 19.12.2019 y. 3205-son bilan ro‘yxatga " -> 2.9. Qarz oluvchi jismoniy shaxslarning kreditlar (mikrokreditlar) bo‘yicha qarz yukini hisoblash tartibi, qarz yukining ruxsat etilgan miqdori, shuningdek qarz yuki o‘sishini cheklash to‘g‘risidagi Nizomga muvofiq (O’zbekiston Respublikasi Adliya vazirligi tomonidan 19.12.2019 y. 3205-son bilan ro‘yxatga | H21: ="olingan Markaziy bank Boshqaruvining 28.09.2019 y. 24/5-son qarori bilan tasdiqlangan), qarz yuki ko‘rsatkichi har bir qarz oluvchiga qarz beruvchi tomonidan "&umumiy_malumot!B65&" ajratishda uning summasi va " -> olingan Markaziy bank Boshqaruvining 28.09.2019 y. 24/5-son qarori bilan tasdiqlangan), qarz yuki ko‘rsatkichi har bir qarz oluvchiga qarz beruvchi tomonidan mikrokredit ajratishda uning summasi va | I21: ="qarz oluvchining amaldagi kredit ("&umumiy_malumot!B65&") shartnomalari bo‘yicha asosiy qarz qoldig‘i yig‘indisi bazaviy hisoblash miqdorining 50 baravaridan oshganda hisoblanadi." -> qarz oluvchining amaldagi kredit (mikrokredit) shartnomalari bo‘yicha asosiy qarz qoldig‘i yig‘indisi bazaviy hisoblash miqdorining 50 baravaridan oshganda hisoblanadi.
A22: ="3. "&umumiy_malumot!D64&" TA'MINOTI BO‘YICHA " -> 3. MIKROKREDIT TA'MINOTI BO‘YICHA
A23: ="3.1. Ushbu Shartnoma bo‘yicha taqdim etilgan "&umumiy_malumot!C64&" quyidagi "&umumiy_malumot!C64&" summasiga nisbatan 140% dan kam bo'lmagan, yani birgalikdagi jami qiymati "&FIXED(umumiy_malumot!C75,2)&" ("&umumiy_malumot!D75&") so'm miqdorida bo'lgan garov va "&umumiy_malumot!C64&" to'lamaslik xavfini sug'urta polisi bilan ta'minlanadi:" -> 3.1. Ushbu Shartnoma bo‘yicha taqdim etilgan Mikrokredit quyidagi Mikrokredit summasiga nisbatan 140% dan kam bo'lmagan, yani birgalikdagi jami qiymati 245 000 000,00 (ikki yuz qirq besh million so'm) so'm miqdorida bo'lgan garov va Mikrokredit to'lamaslik xavfini sug'urta polisi bilan ta'minlanadi:
A24: =IF(umumiy_malumot!B110=umumiy_malumot!C110,shartnoma!A28,IF(umumiy_malumot!B110=umumiy_malumot!D110,shartnoma!A25,0)) -> 3.1.1. Mikromoliya tashkiloti, Qarz oluvchi va NORINBAYEVA SAPURA MAMADALIYEVNA tomonidan 2026 yil 16 fevralda imzolangan 1-sonli Garov predmeti qiymatini tasdiqlash dalolatnomasiga muvofiq TOSHKENT VILOYATI CHINOZ TUMANI ALISHER NAVOIY MFY SOBIR RAHIMOV KO'CHASI 36 UY manzilida joylashgan, umumiy yer maydoni - 700, qurilish osti maydoni- 340.11, umumiy foydali maydoni - 163.19 yashash maydoni - 114.59 bo'lgan, Ko'p qavatli uydagi - xonali xonadon ko'rinishidagi ko'chmas mulk (bundan keyin “Garov predmeti”), egalik huquqiga ko'ra NORINBAYEVA SAPURA MAMADALIYEVNAga tegishli va kelishilgan garov qiymati 2026 yil 16 fevralda imzolangan 1-sonli Garov predmeti qiymatini tasdiqlash dalolatnomasiga muvofiq 210 000 000,00 (ikki yuz o'n million so'm) so'mni tashkil qiladi. Garovning aniq shartlari tegishli tarzda notarial tasdiqlangan garov shartnomasi bilan belgilangan.
A25: =IF(umumiy_malumot!B99=umumiy_malumot!C99,shartnoma!A27,IF(umumiy_malumot!B99=umumiy_malumot!D99,shartnoma!A26,0)) -> 3.1.1. Mikromoliya tashkiloti, Qarz oluvchi va NORINBAYEVA SAPURA MAMADALIYEVNA tomonidan 2026 yil 16 fevralda imzolangan 1-sonli Garov predmeti qiymatini tasdiqlash dalolatnomasiga muvofiq TOSHKENT VILOYATI CHINOZ TUMANI ALISHER NAVOIY MFY SOBIR RAHIMOV KO'CHASI 36 UY manzilida joylashgan, umumiy yer maydoni - 700, qurilish osti maydoni- 340.11, umumiy foydali maydoni - 163.19 yashash maydoni - 114.59 bo'lgan, Ko'p qavatli uydagi - xonali xonadon ko'rinishidagi ko'chmas mulk (bundan keyin “Garov predmeti”), egalik huquqiga ko'ra NORINBAYEVA SAPURA MAMADALIYEVNAga tegishli va kelishilgan garov qiymati 2026 yil 16 fevralda imzolangan 1-sonli Garov predmeti qiymatini tasdiqlash dalolatnomasiga muvofiq 210 000 000,00 (ikki yuz o'n million so'm) so'mni tashkil qiladi. Garovning aniq shartlari tegishli tarzda notarial tasdiqlangan garov shartnomasi bilan belgilangan.
A26: ="3.1.1. "&umumiy_malumot!N133&" tomonidan "&umumiy_malumot!B150&" yil "&umumiy_malumot!B152&" "&umumiy_malumot!B151&"da imzolangan 1-sonli navbatdagi garov predmeti qiymatini tasdiqlash dalolatnomasiga muvofiq "&umumiy_malumot!C130&" manzilida joylashgan, "&umumiy_malumot!E133&" bo'lgan, "&umumiy_malumot!E132&" ko'rinishidagi ko'chmas mulk (bundan keyin “navbatdagi garov predmeti”), egalik huquqiga ko'ra "&umumiy_malumot!C124&"ga tegishli va kelishilgan garov qiymati "&umumiy_malumot!B150&" yil "&umumiy_malumot!B152&" "&umumiy_malumot!B151&"da imzolangan 1-sonli Garov predmeti qiymatini tasdiqlash dalolatnomasiga muvofiq "&FIXED(umumiy_malumot!B143,2)&" ("&umumiy_malumot!B145&") so'mni tashkil qiladi. Garovning aniq shartlari tegishli tarzda notarial tasdiqlangan garov shartnomasi bilan belgilangan." -> 3.1.1. Mikromoliya tashkiloti, Qarz oluvchi va NORINBAYEVA SAPURA MAMADALIYEVNA tomonidan 2026 yil 16 fevralda imzolangan 1-sonli navbatdagi garov predmeti qiymatini tasdiqlash dalolatnomasiga muvofiq TOSHKENT VILOYATI CHINOZ TUMANI ALISHER NAVOIY MFY SOBIR RAHIMOV KO'CHASI 36 UY manzilida joylashgan, umumiy yer maydoni - 700, qurilish osti maydoni- 340.11, umumiy foydali maydoni - 163.19 yashash maydoni - 114.59 bo'lgan, Ko'p qavatli uydagi - xonali xonadon ko'rinishidagi ko'chmas mulk (bundan keyin “navbatdagi garov predmeti”), egalik huquqiga ko'ra NORINBAYEVA SAPURA MAMADALIYEVNAga tegishli va kelishilgan garov qiymati 2026 yil 16 fevralda imzolangan 1-sonli Garov predmeti qiymatini tasdiqlash dalolatnomasiga muvofiq 210 000 000,00 (ikki yuz o'n million so'm) so'mni tashkil qiladi. Garovning aniq shartlari tegishli tarzda notarial tasdiqlangan garov shartnomasi bilan belgilangan.
A27: ="3.1.1. "&umumiy_malumot!N133&" tomonidan "&umumiy_malumot!B150&" yil "&umumiy_malumot!B152&" "&umumiy_malumot!B151&"da imzolangan 1-sonli Garov predmeti qiymatini tasdiqlash dalolatnomasiga muvofiq "&umumiy_malumot!C130&" manzilida joylashgan, "&umumiy_malumot!E133&" bo'lgan, "&umumiy_malumot!E132&" ko'rinishidagi ko'chmas mulk (bundan keyin “Garov predmeti”), egalik huquqiga ko'ra "&umumiy_malumot!C124&"ga tegishli va kelishilgan garov qiymati "&umumiy_malumot!B150&" yil "&umumiy_malumot!B152&" "&umumiy_malumot!B151&"da imzolangan 1-sonli Garov predmeti qiymatini tasdiqlash dalolatnomasiga muvofiq "&FIXED(umumiy_malumot!B143,2)&" ("&umumiy_malumot!B145&") so'mni tashkil qiladi. Garovning aniq shartlari tegishli tarzda notarial tasdiqlangan garov shartnomasi bilan belgilangan." -> 3.1.1. Mikromoliya tashkiloti, Qarz oluvchi va NORINBAYEVA SAPURA MAMADALIYEVNA tomonidan 2026 yil 16 fevralda imzolangan 1-sonli Garov predmeti qiymatini tasdiqlash dalolatnomasiga muvofiq TOSHKENT VILOYATI CHINOZ TUMANI ALISHER NAVOIY MFY SOBIR RAHIMOV KO'CHASI 36 UY manzilida joylashgan, umumiy yer maydoni - 700, qurilish osti maydoni- 340.11, umumiy foydali maydoni - 163.19 yashash maydoni - 114.59 bo'lgan, Ko'p qavatli uydagi - xonali xonadon ko'rinishidagi ko'chmas mulk (bundan keyin “Garov predmeti”), egalik huquqiga ko'ra NORINBAYEVA SAPURA MAMADALIYEVNAga tegishli va kelishilgan garov qiymati 2026 yil 16 fevralda imzolangan 1-sonli Garov predmeti qiymatini tasdiqlash dalolatnomasiga muvofiq 210 000 000,00 (ikki yuz o'n million so'm) so'mni tashkil qiladi. Garovning aniq shartlari tegishli tarzda notarial tasdiqlangan garov shartnomasi bilan belgilangan.
A28: =IF(umumiy_malumot!B99=umumiy_malumot!C99,A29,IF(umumiy_malumot!B99=umumiy_malumot!D99,A30,0)) -> 3.1.1. Mikromoliya tashkiloti, Qarz oluvchi va NORINBAYEVA SAPURA MAMADALIYEVNA tomonidan 2026 yil 16 fevralda imzolangan 1-sonli garov predmeti qiymatini tasdiqlash dalolatnomasiga muvofiq OQ SUMMIT WHITE rangli, ishlab chiqarilgan yili – 2024 yil, dvigatel raqami B15D213241352MTAX0118, shassi - RAQAMSIZ, kuzov turi - YENGIL SEDAN, kuzov raqami №XWBJA69VERA108471, davlat raqam belgisi 01Z067RC bo'lgan CHEVROLET COBALT rusumli avtomashinasi (bundan keyin “Garov predmeti”), egalik huquqiga ega NORINBAYEVA SAPURA MAMADALIYEVNAga tegishli va kelishilgan garov qiymati 2026 yil 16 fevralda imzolangan 1-sonli Garov predmeti qiymatini tasdiqlash dalolatnomasiga muvifiq 210 000 000,00 (ikki yuz o'n million so'm) so'mni tashkil qiladi. Garov garovining aniq shartlari tegishli notarial rasmiylashtirilgan garov shartnomasi bilan belgilanadi.
A29: ="3.1.1. "&umumiy_malumot!N133&" tomonidan "&umumiy_malumot!B150&" yil "&umumiy_malumot!B152&" "&umumiy_malumot!B151&"da imzolangan 1-sonli garov predmeti qiymatini tasdiqlash dalolatnomasiga muvofiq "&umumiy_malumot!B141&" rangli, ishlab chiqarilgan yili – "&umumiy_malumot!B142&" yil, dvigatel raqami "&umumiy_malumot!B138&", shassi - "&umumiy_malumot!B139&", kuzov turi - "&umumiy_malumot!B135&", kuzov raqami №"&umumiy_malumot!B136&", davlat raqam belgisi "&umumiy_malumot!B133&" bo'lgan "&umumiy_malumot!B132&" rusumli avtomashinasi (bundan keyin “Garov predmeti”), egalik huquqiga ega "&umumiy_malumot!B124&"ga tegishli va kelishilgan garov qiymati "&umumiy_malumot!B150&" yil "&umumiy_malumot!B152&" "&umumiy_malumot!B151&"da imzolangan 1-sonli Garov predmeti qiymatini tasdiqlash dalolatnomasiga muvifiq "&FIXED(umumiy_malumot!B143,2)&" ("&umumiy_malumot!B145&") so'mni tashkil qiladi. Garov garovining aniq shartlari tegishli notarial rasmiylashtirilgan garov shartnomasi bilan belgilanadi." -> 3.1.1. Mikromoliya tashkiloti, Qarz oluvchi va NORINBAYEVA SAPURA MAMADALIYEVNA tomonidan 2026 yil 16 fevralda imzolangan 1-sonli garov predmeti qiymatini tasdiqlash dalolatnomasiga muvofiq OQ SUMMIT WHITE rangli, ishlab chiqarilgan yili – 2024 yil, dvigatel raqami B15D213241352MTAX0118, shassi - RAQAMSIZ, kuzov turi - YENGIL SEDAN, kuzov raqami №XWBJA69VERA108471, davlat raqam belgisi 01Z067RC bo'lgan CHEVROLET COBALT rusumli avtomashinasi (bundan keyin “Garov predmeti”), egalik huquqiga ega NORINBAYEVA SAPURA MAMADALIYEVNAga tegishli va kelishilgan garov qiymati 2026 yil 16 fevralda imzolangan 1-sonli Garov predmeti qiymatini tasdiqlash dalolatnomasiga muvifiq 210 000 000,00 (ikki yuz o'n million so'm) so'mni tashkil qiladi. Garov garovining aniq shartlari tegishli notarial rasmiylashtirilgan garov shartnomasi bilan belgilanadi.
A30: ="3.1.1. "&umumiy_malumot!N133&" tomonidan "&umumiy_malumot!B150&" yil "&umumiy_malumot!B152&" "&umumiy_malumot!B151&"da imzolangan 1-sonli navbatdagi garov predmeti qiymatini tasdiqlash dalolatnomasiga muvofiq "&umumiy_malumot!B141&" rangli, ishlab chiqarilgan yili – "&umumiy_malumot!B142&" yil, dvigatel raqami "&umumiy_malumot!B138&", shassi - "&umumiy_malumot!B139&", kuzov turi - "&umumiy_malumot!B135&", kuzov raqami №"&umumiy_malumot!B136&", davlat raqam belgisi "&umumiy_malumot!B133&" bo'lgan "&umumiy_malumot!B132&" rusumli avtomashinasi (bundan keyin “navbatdagi garov predmeti”), egalik huquqiga ega "&umumiy_malumot!B124&"ga tegishli va kelishilgan garov qiymati "&umumiy_malumot!B150&" yil "&umumiy_malumot!B152&" "&umumiy_malumot!B151&"da imzolangan 1-sonli Garov predmeti qiymatini tasdiqlash dalolatnomasiga muvifiq "&FIXED(umumiy_malumot!B143,2)&" ("&umumiy_malumot!B145&") so'mni tashkil qiladi. Garov garovining aniq shartlari tegishli notarial rasmiylashtirilgan garov shartnomasi bilan belgilanadi." -> 3.1.1. Mikromoliya tashkiloti, Qarz oluvchi va NORINBAYEVA SAPURA MAMADALIYEVNA tomonidan 2026 yil 16 fevralda imzolangan 1-sonli navbatdagi garov predmeti qiymatini tasdiqlash dalolatnomasiga muvofiq OQ SUMMIT WHITE rangli, ishlab chiqarilgan yili – 2024 yil, dvigatel raqami B15D213241352MTAX0118, shassi - RAQAMSIZ, kuzov turi - YENGIL SEDAN, kuzov raqami №XWBJA69VERA108471, davlat raqam belgisi 01Z067RC bo'lgan CHEVROLET COBALT rusumli avtomashinasi (bundan keyin “navbatdagi garov predmeti”), egalik huquqiga ega NORINBAYEVA SAPURA MAMADALIYEVNAga tegishli va kelishilgan garov qiymati 2026 yil 16 fevralda imzolangan 1-sonli Garov predmeti qiymatini tasdiqlash dalolatnomasiga muvifiq 210 000 000,00 (ikki yuz o'n million so'm) so'mni tashkil qiladi. Garov garovining aniq shartlari tegishli notarial rasmiylashtirilgan garov shartnomasi bilan belgilanadi.
A31: =CONCATENATE(C31,D31) -> 3.1.2. «АО СК "IMPEX INSURANCE"» АJ sug‘urta kompaniyasi (keyingi o'rinlarda-Sug‘urtalovchi) tomonidan Mikrokredit to'lamaslik xavfini Mikrokredit summasiga nisbatan 140% dan hisoblab 35 000 000,00(o'ttiz besh million so'm) so ' m miqdoriga sug’urta qilish. Ushbu shartnoma bo‘yicha Mikrokredit berilgunga qadar Mikromoliya tashkiloti Sug‘urtalovchi 35 000 000,00(o'ttiz besh million so'm) so ' m miqdoridagi Mikrokreditni to‘lamaslik xavfini sug‘urta qilish shartnomasini tuzadi va Sug‘urtalovchi nomiga sug‘urta mukofotini to‘laydi, Qarz oluvchi esa Mikromoliya tashkiloti tomonidan sug‘urta mukofotini to‘langan kuni Mikromoliya tashkiloti tomonidan to‘langan sug‘urta mukofotini Mikromoliya tashkilotiga to‘laydi." | C31: ="3.1.2. «"&umumiy_malumot!B154&"» АJ sug‘urta kompaniyasi (keyingi o'rinlarda-Sug‘urtalovchi) tomonidan "&umumiy_malumot!C64&" to'lamaslik xavfini "&umumiy_malumot!C64&" summasiga nisbatan 140% dan hisoblab "&FIXED(umumiy_malumot!B155,2)&"("&umumiy_malumot!B156&") so ' m miqdoriga sug’urta qilish." -> 3.1.2. «АО СК "IMPEX INSURANCE"» АJ sug‘urta kompaniyasi (keyingi o'rinlarda-Sug‘urtalovchi) tomonidan Mikrokredit to'lamaslik xavfini Mikrokredit summasiga nisbatan 140% dan hisoblab 35 000 000,00(o'ttiz besh million so'm) so ' m miqdoriga sug’urta qilish. | D31: =CONCATENATE(E31,F31) -> Ushbu shartnoma bo‘yicha Mikrokredit berilgunga qadar Mikromoliya tashkiloti Sug‘urtalovchi 35 000 000,00(o'ttiz besh million so'm) so ' m miqdoridagi Mikrokreditni to‘lamaslik xavfini sug‘urta qilish shartnomasini tuzadi va Sug‘urtalovchi nomiga sug‘urta mukofotini to‘laydi, Qarz oluvchi esa Mikromoliya tashkiloti tomonidan sug‘urta mukofotini to‘langan kuni Mikromoliya tashkiloti tomonidan to‘langan sug‘urta mukofotini Mikromoliya tashkilotiga to‘laydi." | E31: =" Ushbu shartnoma bo‘yicha "&umumiy_malumot!C64&" berilgunga qadar Mikromoliya tashkiloti Sug‘urtalovchi "&FIXED(umumiy_malumot!B155,2)&"("&umumiy_malumot!B156&") so ' m miqdoridagi "&umumiy_malumot!C64&"" -> Ushbu shartnoma bo‘yicha Mikrokredit berilgunga qadar Mikromoliya tashkiloti Sug‘urtalovchi 35 000 000,00(o'ttiz besh million so'm) so ' m miqdoridagi Mikrokredit | F31: ni to‘lamaslik xavfini sug‘urta qilish shartnomasini tuzadi va Sug‘urtalovchi nomiga sug‘urta mukofotini to‘laydi, Qarz oluvchi esa Mikromoliya tashkiloti tomonidan sug‘urta mukofotini to‘langan kuni Mikromoliya tashkiloti tomonidan to‘langan sug‘urta mukofotini Mikromoliya tashkilotiga to‘laydi."
A32: =CONCATENATE(A33,B33) -> 3.2. Qonun hujjatlariga muvofiq rasmiylashtirilgan, “Garov predmeti” hisoblangan notarial tasdiqlangan garov shartnomasi, shu jumladan “Garov predmeti”ga taʼqiq quyilganligi tasdiqlovchi xujjat Qarz oluvchi tomonidan ushbu shartnoma tuzilgandan so‘ng 10 bank kuni mobaynida Mikromoliya tashkilotiga taqdim etilishi lozim. Garov shartnomasi belgilangan muddatda taqdim etilmagan hollarda, Mikromoliya tashkiloti Qarz oluvchining manziliga yozma bildirishnoma yuborish orqali mikrokredit berishni rad etish va / yoki ushbu shartnomani bir tomonlama bekor qilish huquqiga egadir. Bunda ushbu shartnoma Qarz oluvchi tomonidan talabnoma olingan vaqtda yoki talabnoma pochta xizmati orqali yuborilgandan keyin uchinchi kuni bekor qilingan hisoblanadi.
A33: 3.2. Qonun hujjatlariga muvofiq rasmiylashtirilgan, “Garov predmeti” hisoblangan notarial tasdiqlangan garov shartnomasi, shu jumladan “Garov predmeti”ga taʼqiq quyilganligi tasdiqlovchi xujjat Qarz oluvchi tomonidan ushbu shartnoma tuzilgandan so‘ng 10 bank kuni mobaynida | B33: =CONCATENATE(A34,B34) -> Mikromoliya tashkilotiga taqdim etilishi lozim. Garov shartnomasi belgilangan muddatda taqdim etilmagan hollarda, Mikromoliya tashkiloti Qarz oluvchining manziliga yozma bildirishnoma yuborish orqali mikrokredit berishni rad etish va / yoki ushbu shartnomani bir tomonlama bekor qilish huquqiga egadir. Bunda ushbu shartnoma Qarz oluvchi tomonidan talabnoma olingan vaqtda yoki talabnoma pochta xizmati orqali yuborilgandan keyin uchinchi kuni bekor qilingan hisoblanadi.
A34: =" Mikromoliya tashkilotiga taqdim etilishi lozim. Garov shartnomasi belgilangan muddatda taqdim etilmagan hollarda, Mikromoliya tashkiloti Qarz oluvchining manziliga yozma bildirishnoma yuborish orqali "&umumiy_malumot!B65&"" -> Mikromoliya tashkilotiga taqdim etilishi lozim. Garov shartnomasi belgilangan muddatda taqdim etilmagan hollarda, Mikromoliya tashkiloti Qarz oluvchining manziliga yozma bildirishnoma yuborish orqali mikrokredit | B34: berishni rad etish va / yoki ushbu shartnomani bir tomonlama bekor qilish huquqiga egadir. Bunda ushbu shartnoma Qarz oluvchi tomonidan talabnoma olingan vaqtda yoki talabnoma pochta xizmati orqali yuborilgandan keyin uchinchi kuni bekor qilingan hisoblanadi.
A35: 3.3. Asosiy qarzni, foizlar yoki ushbu shartnoma bo‘yicha belgilangan muddatdan kechiktirilganligi bo‘yicha penyalarni qaytarish muddati kechiktirilishi yuzaga kelganda va/yoki ushbu shartnoma bo‘yicha boshqa majburiyatlar buzilishi holatlarida Mikromoliya tashkiloti O‘zbekiston Respublikasining amaldagi qonunchiligiga muvofiq qarzni undirish uchun qaytarib olinmaydigan va muqarrar tartibda unidirishni garov ob'ektiga qaratish huquqiga ega bo‘ladi.
A36: 3.4. O‘zbekiston Respublikasi "Garov to‘g‘risida" gi Qonunining 27-moddasiga muvofiq Garov predmeti sug‘urtalanmaydi. Lekin Mikromoliya tashkiloti Qarz oluvchidan Mikromoliya tashkiloti foydasiga Garov obʼektini ushbu Shartnomaning to‘liq amal qilish muddatiga har turli xavflardan sug‘urta qilishni talab qilish huquqiga ega. Bunda, sug‘urta xavflari ro‘yxati, shuningdek, sug‘urta kompaniyasi Mikromoliya tashkilotining xohishiga ko‘ra belgilanadi. Sug‘urta hodisasi yuz berganda Foyda oluvchi Mikromoliya tashkiloti bo‘lishi kerak.
A37: 3.5. Undiruvni Garov narsasiga (predmetlariga) va/yoki uning (ularning) bir qismiga (qismlariga) qaratishda va/yoki Qarz oluvchining Kafildan qarzini undirishda Mikromoliya tashkiloti undiruvning birinchi navbatdagi obyektini o‘z xohishiga ko‘ra bir tomonlama tanlash yoki bir vaqtning o‘zida undiruvni Garov narsasiga (predmetlariga) qaratish va Kafilga talab qo‘yish huquqini o‘zida saqlab qoladi. Undiruvni garov narsasining bir obyektiga va/yoki uning (ularning) bir qismiga qaratish va/yoki Mikroqarzni Kafildan undirish Mikromoliya tashkilotini undiruvni garov narsasining boshqa obyektiga (obyektlariga) va/yoki uning (ularning) bir qismiga qaratish va/yoki Mikroqarzni Kafildan undirishda cheklamaydi. Qarz oluvchining Mikroqarzni Sug‘urtalovchidan undirish tartibi tegishli sug‘urta shartnomasida belgilanadi.
A39: 4. MIKROMOLIYA TASHKILOTINING HUQUQ VA MAJBURIYATLARI
A40: 4.1. Mikromoliya tashkiloti quyidagi huquqlarga ega:
A41: =CONCATENATE(C41,H41) -> 4.1.1. Ushbu Shartnomada ko‘rsatilgan asoslar bo‘yicha Qarz oluvchiga Shartnomada ko‘zda tutilgan mikrokredit summasini berilishini to‘liq yoki qisman rad etish. 4.1.2 “Mikromoliya Tashkiloti” qarz oluvchining nomidagi barcha plastik kartalaridan, xozirgi kunda mavjud va bundan so‘ng ochiladigan barcha xisob raqamlaridan (talab qilib olguncha, depozit jamg‘arib boriladigan plastik va boshqa istalgan xisob raqamlaridan) kredit to‘lovini kredit qaytarish jadvaliga asosan oyning kredit qarzdorligi qaytarilishi ko‘rsatilgan kuni akseptsiz tarzda yechib olish xuquqiga ega.Usbu bandda belgilangan harakatlarni amalga oshirish uchun bo‘lgan barcha xarajatlar Qarz oluvchi xisobidan qoplanadi. | C41: ="4.1.1. Ushbu Shartnomada ko‘rsatilgan asoslar bo‘yicha Qarz oluvchiga Shartnomada ko‘zda tutilgan "&umumiy_malumot!B65&"" -> 4.1.1. Ushbu Shartnomada ko‘rsatilgan asoslar bo‘yicha Qarz oluvchiga Shartnomada ko‘zda tutilgan mikrokredit | H41: summasini berilishini to‘liq yoki qisman rad etish. 4.1.2 “Mikromoliya Tashkiloti” qarz oluvchining nomidagi barcha plastik kartalaridan, xozirgi kunda mavjud va bundan so‘ng ochiladigan barcha xisob raqamlaridan (talab qilib olguncha, depozit jamg‘arib boriladigan plastik va boshqa istalgan xisob raqamlaridan) kredit to‘lovini kredit qaytarish jadvaliga asosan oyning kredit qarzdorligi qaytarilishi ko‘rsatilgan kuni akseptsiz tarzda yechib olish xuquqiga ega.Usbu bandda belgilangan harakatlarni amalga oshirish uchun bo‘lgan barcha xarajatlar Qarz oluvchi xisobidan qoplanadi.
A42: ="4.1.2.1. "&umumiy_malumot!C64&" bo‘yicha qolgan barcha qarzdorlik, foiz to‘lovlarining muddatidan oldin qaytarilishini talab qilish, shuningdek, quyidagi holatlardan biri yuzaga kelganda undirishni garov ta'minotiga qaratish:" -> 4.1.2.1. Mikrokredit bo‘yicha qolgan barcha qarzdorlik, foiz to‘lovlarining muddatidan oldin qaytarilishini talab qilish, shuningdek, quyidagi holatlardan biri yuzaga kelganda undirishni garov ta'minotiga qaratish:
A43: a) ta'minotisiz qarzdorlik yuzaga kelganda;
A44: ="b) "&umumiy_malumot!B65&" summasiga hisoblanadigan asosiy qarz bo‘yicha muddati o‘tgan qarzdorlik va/yoki foizlarning yuzaga kelishi;" -> b) mikrokredit summasiga hisoblanadigan asosiy qarz bo‘yicha muddati o‘tgan qarzdorlik va/yoki foizlarning yuzaga kelishi;
A45: с) Qarz oluvchini qonun hujjatlarida belgilangan tartibda to‘lov qobiliyatiga ega emas, muomalaga layoqatli emas yoki muomalaga layoqati cheklangan deb e'lon qilish;
A46: d) Mikromoliya tashkilotiga ushbu Shartnomaning 3.1.-bandida ko‘zda tutilgan hisobotlar, axborotlar va boshqa ma'lumotlarni o‘z vaqtida taqdim etmaslik, shuningdek, moliya-xo‘jalik faoliyat va daromad to‘g‘risidagi hisobotning ishonchsizligi holatlari aniqlanganda;
A47: e) Qarz oluvchi tomonidan ushbu shartnoma shartlariga amal qilmaslik;
A48: ="f) Qarz oluvchi "&umumiy_malumot!B65&" summasini olish uchun Mikromoliya tashkilotiga "&umumiy_malumot!B65&" taqdim etilishi to‘g‘risida ijobiy qaror qabul qilinishi uchun muhim hisoblangan masalalar bo‘yicha yolg‘on yoki to‘liq bo‘lmagan ma'lumotlarni taqdim etganligi aniqlanganda." -> f) Qarz oluvchi mikrokredit summasini olish uchun Mikromoliya tashkilotiga mikrokredit taqdim etilishi to‘g‘risida ijobiy qaror qabul qilinishi uchun muhim hisoblangan masalalar bo‘yicha yolg‘on yoki to‘liq bo‘lmagan ma'lumotlarni taqdim etganligi aniqlanganda.
A49: 4.1.3. Ushbu shartnomaning amal qilish jarayonida Qarz oluvchining moliyaviy holatini tekshirish va Qarz oluvchi tomonidan o‘z zimmasiga olgan majburiyatlarning bajarilishini nazorat qilish.
A50: 4.1.4. Qarz oluvchi tomonidan yoki ushbu Shartnoma bo‘yicha uchinchi shaxs tomonidan ta'minot sifatida garovga qo‘yilgan mol-mulkning tegishli holatdaligi va ulardan foydalanish bo‘yicha tekshiruvlar o‘tkazish.
A51: 4.1.5. Garovga qo‘yuvchi tomonidan garovga qo‘yilgan mol-mulk buzilgan yoki belgilangan maqsadda foydalanish uchun yaroqsiz holga kelganda, bu esa Mikromoliya tashkilotining ushbu Shartnoma bo‘yicha moliyaviy talablarini qondirishga qodir bo‘lgan bozor qiymatiga ma'lum darajada ta'sir ko‘rsatganda, yoki uchinchi shaxsning (kafil) moliyaviy holatining yomonlashuvi sababli ushbu Shartnomadan kelib chiqqan majburiyatlar bo‘yicha javob berish qobiliyatiga ega bo‘lmay qolgan holatlarda Qarz oluvchidan ta'minotning qo‘shimcha turini taqdim etish yoki almashtirishni talab qilish.
A52: 4.1.6. Qonun hujjatlariga muvofiq, Qarz oluvchi tomonidan ushbu Shartnoma bo‘yicha asosiy qarz, foizlar, penya va boshqa pul majburiyatlarini o‘z vaqtida to‘lamaslik holatlarida Qarz oluvchining bank hisobvaraqlaridagi pul mablag‘larini akseptsiz tartibda yechib olish to‘g‘risida to‘lov talabnomasini berish va bunga Qarz oluvchi qaytarib olinmaydigan va so‘zsiz rozilik bildiradi.
A53: ="4.1.7. Qarz oluvchini oldindan ogohlantirmasdan "&umumiy_malumot!B65&"ni qaytarish uchun haqiqatdan ham garov ta'minoti mavjudligini tekshirishni amalga oshirish." -> 4.1.7. Qarz oluvchini oldindan ogohlantirmasdan mikrokreditni qaytarish uchun haqiqatdan ham garov ta'minoti mavjudligini tekshirishni amalga oshirish.
A54: 4.1.8. Ushbu shartnoma doirasida o‘z majburiyatlarini bajarish uchun uchinchi shaxslarga barcha zarur ma'lumotlarni yetkazish.
A55: 4.1.9. Istalgan vaqtda Qarz oluvchining avvaldan roziligini olmasdan turib ushbu Shartnoma bo‘yicha uchinchi tomonga da'vo qilish huquqini berish yoki uning foydasiga voz kechish.
A56: =CONCATENATE(C56,H56) -> 4.1.10. Qarz oluvchi taqdim etilgan mikrokreditdan Shartnoma tuzilgan kundan boshlab 1 (bir) oy davomida foydalanmagan holatlarda, bu haqda Qarz oluvchini yozma ravishda xabardor qilib, Shartnoma bir tomonlama bekor qilish. Yozma xabarni jo‘natish sanasi uni taqdim etish yoki pochta orqali jo‘natish sanasi hisoblanadi. | C56: ="4.1.10. Qarz oluvchi taqdim etilgan "&umumiy_malumot!B65&"dan Shartnoma tuzilgan kundan boshlab 1 (bir) oy davomida foydalanmagan" -> 4.1.10. Qarz oluvchi taqdim etilgan mikrokreditdan Shartnoma tuzilgan kundan boshlab 1 (bir) oy davomida foydalanmagan | H56: holatlarda, bu haqda Qarz oluvchini yozma ravishda xabardor qilib, Shartnoma bir tomonlama bekor qilish. Yozma xabarni jo‘natish sanasi uni taqdim etish yoki pochta orqali jo‘natish sanasi hisoblanadi.
A57: ="4.1.11. Oldingi "&umumiy_malumot!B65&" to‘liq to‘lanmagunga qadar yangi "&umumiy_malumot!B65&" berishni rad etish." -> 4.1.11. Oldingi mikrokredit to‘liq to‘lanmagunga qadar yangi mikrokredit berishni rad etish.
A59: 5. QARZ OLUVCHINING HUQUQ VA MAJBURIYATLARI
A60: 5.1. Qarz oluvchi quyidagi huquqlarga ega:
A61: ="5.1.1. Ushbu shartnomada nazarda tutilgan shartlar bo‘yicha "&umumiy_malumot!B65&" olish, shuningdek, Mikromoliya tashkiloti tomonidan ko‘rsatiladigan pullik xizmatlardan foydalanish." -> 5.1.1. Ushbu shartnomada nazarda tutilgan shartlar bo‘yicha mikrokredit olish, shuningdek, Mikromoliya tashkiloti tomonidan ko‘rsatiladigan pullik xizmatlardan foydalanish.
A62: ="5.1.2. Shartnoma tuzilgan kundan boshlab 2 (ikki) hafta mobaynida Mikromoliya tashkilotiga bu haqda yozma xabarnoma yo‘llash orqali "&umumiy_malumot!B65&"ning foydalanilmagan summasidan voz kechish." -> 5.1.2. Shartnoma tuzilgan kundan boshlab 2 (ikki) hafta mobaynida Mikromoliya tashkilotiga bu haqda yozma xabarnoma yo‘llash orqali mikrokreditning foydalanilmagan summasidan voz kechish.
A63: ="5.1.3. "&umumiy_malumot!C64&" xizmatlari ko‘rsatish qoidalari bilan tanishish." -> 5.1.3. Mikrokredit xizmatlari ko‘rsatish qoidalari bilan tanishish.
A64: ="5.1.4. O‘z huquq va majburiyatlari, shu jumladan "&umumiy_malumot!B65&" xizmatlari ko‘rsatish bilan bog‘liq barcha xarajatlar haqida aniq va to‘liq ma'lumot olish." -> 5.1.4. O‘z huquq va majburiyatlari, shu jumladan mikrokredit xizmatlari ko‘rsatish bilan bog‘liq barcha xarajatlar haqida aniq va to‘liq ma'lumot olish.
A65: 5.1.5. Shartnoma bo‘yicha Mikromoliya tashkilotining majburiyatlarini bajarmaslik yoki tegishli darajada bajarmaslik natijasida yuzaga kelgan zararlarni qoplashni talab qilish.
A66: 5.2. Qarz oluvchining majburiyatlari:
A67: ="5.2.1. Mikromoliya tashkilotining birinchi talabi bilan zarur hujjatlar, shuningdek "&umumiy_malumot!B65&"dan foydalanishning butun davri davomida uning moliyaviy holati va to‘lash qobiliyatiga tegishli bo‘lgan ma'lumotlarni taqdim etish." -> 5.2.1. Mikromoliya tashkilotining birinchi talabi bilan zarur hujjatlar, shuningdek mikrokreditdan foydalanishning butun davri davomida uning moliyaviy holati va to‘lash qobiliyatiga tegishli bo‘lgan ma'lumotlarni taqdim etish.
A68: 5.2.2. Ushbu shartnomada nazarda tutilgan hollarda garov ta'minotini almashtirish yoki qo‘shimcha ta'minot turini taqdim etish bo‘yicha Mikromoliya tashkiloti talablarini bajarish.
A69: ="5.2.3. To‘lov jadvaliga muvofiq "&umumiy_malumot!B65&", shuningdek hisoblangan foizlar to‘lovlarini amalga oshirish." -> 5.2.3. To‘lov jadvaliga muvofiq mikrokredit, shuningdek hisoblangan foizlar to‘lovlarini amalga oshirish.
A70: =CONCATENATE(C70,H70) -> 5.2.4. Mikromoliya tashkiloti vakillariga o‘zlarining moliyaviy holati, yashash joyini tekshirishga, Mikromoliya tashkiloti foydasiga garovga qo‘yilgan mol-mulk saqlanishini tekshirishga ruxsat berish, shuningdek Qarz oluvchi ob'ektlaridan istalganiga tashrif buyurish va har qanday bino, inshoot, mol-mulk, asbob-uskunalar, tovarlar va xizmatlar, shuningdek ularning mikrokredit mablag‘lari hisobiga moliyalashtirilgan hujjatlarni ko‘zdan kechirish va Mikromoliya tashkiloti tomonidan ushbu huquqni amalga oshirishga to‘sqinlik qilmaslik majburiyatini oladi. | C70: 5.2.4. Mikromoliya tashkiloti vakillariga o‘zlarining moliyaviy holati, yashash joyini tekshirishga, Mikromoliya tashkiloti foydasiga garovga qo‘yilgan mol-mulk saqlanishini tekshirishga ruxsat berish, shuningdek Qarz oluvchi ob'ektlaridan istalganiga tashrif buyurish va har qanday bino, inshoot, mol-mulk, asbob-uskunalar, tovarlar va xizmatlar, shuningdek ularning | H70: =" "&umumiy_malumot!B65&" mablag‘lari hisobiga moliyalashtirilgan hujjatlarni ko‘zdan kechirish va Mikromoliya tashkiloti tomonidan ushbu huquqni amalga oshirishga to‘sqinlik qilmaslik majburiyatini oladi." -> mikrokredit mablag‘lari hisobiga moliyalashtirilgan hujjatlarni ko‘zdan kechirish va Mikromoliya tashkiloti tomonidan ushbu huquqni amalga oshirishga to‘sqinlik qilmaslik majburiyatini oladi.
A71: 5.2.5. Qarz oluvchining moliyaviy ahvoli yomonlashuvi va ushbu shartnoma bo‘yicha Qarz oluvchining Mikromoliya tashkiloti oldidagi majburiyatlarining bajarilmasligi va/yoki tegishli darajada bajarilmaslik xavfi yuzaga kelishiga olib keluvchi hech qanday majburiyat va choralarni o‘z zimmasiga olmaslik;
A72: ="5.2.6. Quyidagi holatlarda Mikromoliya tashkilotning birinchi talabi bilan "&umumiy_malumot!B65&" qaytarilishi bo‘yicha qo‘shimcha garov ta'minotini taqdim etish: " -> 5.2.6. Quyidagi holatlarda Mikromoliya tashkilotning birinchi talabi bilan mikrokredit qaytarilishi bo‘yicha qo‘shimcha garov ta'minotini taqdim etish:
A73: - Qarz oluvchining moliyaviy holatining yomonlashuvi; - Garov ob'ekti va/yoki uning bir qismining yo‘q qilinishi, qiymatining pasayishi, qisman yoki to‘liq yo‘qotilishi; - qarz qaytarilmaslik xavfini ko‘paytiruvchi boshqa omillarning paydo bo‘lishi;
A74: ="5.2.7. Sud qarori asosida Qarz oluvchi – jismoniy shaxsning muomalaga layoqatsizligi yoki muomalaga layoqati cheklangan yoxud to‘lash qobiliyatiga ega emasligi (bankrotligi) tan olinganda, uning vasiysi yoki homiysi "&umumiy_malumot!B65&"ning asosiy summa bo‘yicha qarzdorlikni "&umumiy_malumot!B65&"dan aniq foydalanish muddati uchun foizlar bilan kechiktirmasdan to‘liq to‘lashi shart." -> 5.2.7. Sud qarori asosida Qarz oluvchi – jismoniy shaxsning muomalaga layoqatsizligi yoki muomalaga layoqati cheklangan yoxud to‘lash qobiliyatiga ega emasligi (bankrotligi) tan olinganda, uning vasiysi yoki homiysi mikrokreditning asosiy summa bo‘yicha qarzdorlikni mikrokreditdan aniq foydalanish muddati uchun foizlar bilan kechiktirmasdan to‘liq to‘lashi shart.
A75: ="5.2.8. Mikromoliya tashkilotining "&umumiy_malumot!B65&" umumiy summasi va hisoblangan foizlarni muddatidan oldin qaytarish to‘g‘risidagi talabini kechiktirmasdan bajarish." -> 5.2.8. Mikromoliya tashkilotining mikrokredit umumiy summasi va hisoblangan foizlarni muddatidan oldin qaytarish to‘g‘risidagi talabini kechiktirmasdan bajarish. | H75: "&'Общие данные'!B59&"
A76: =CONCATENATE(C76,H76) -> 5.2.9. Mikromoliya tashkilotining talabi bo‘yicha Mikromoliya tashkiloti ko‘rgan, shu jumladan mikrokredit bo‘yicha (asosiy qarz, foizlar va boshqalar) qarzdorlikni majburiy va/yoki muddatidan oldin qaytarish bo‘yicha qabul qilingan choralar bilan bog‘liq bo‘lgan barcha xarajatlari va zararlarni qoplash, shuningdek ushbu shartnoma doirasida unidruvni taqdim etilgan garov ta'minotiga qaratish. | C76: ="5.2.9. Mikromoliya tashkilotining talabi bo‘yicha Mikromoliya tashkiloti ko‘rgan, shu jumladan "&umumiy_malumot!B65&" bo‘yicha (asosiy qarz, foizlar va boshqalar)" -> 5.2.9. Mikromoliya tashkilotining talabi bo‘yicha Mikromoliya tashkiloti ko‘rgan, shu jumladan mikrokredit bo‘yicha (asosiy qarz, foizlar va boshqalar) | H76: qarzdorlikni majburiy va/yoki muddatidan oldin qaytarish bo‘yicha qabul qilingan choralar bilan bog‘liq bo‘lgan barcha xarajatlari va zararlarni qoplash, shuningdek ushbu shartnoma doirasida unidruvni taqdim etilgan garov ta'minotiga qaratish.
A78: 6. TOMONLARNING JAVOBGARLIGI
A79: =CONCATENATE(C79,H79) -> 6.1. Mikromoliya tashkiloti tomonidan Qarz oluvchiga pul mablag‘larini ajratib berish bo‘yicha o‘z zimmasiga olgan majburiyatlarning Shartnomaning 1.1.-bandida keltirilgan summa va muddatlarda bajarilmaslik yoki tegishli tarzda bajarilmaslik holatlarida Mikromoliya tashkiloti muddatidan o‘tgan har bir kalendar kun uchun kechiktirilgan to‘lov summasining 0,1% miqdorida, biroq ushbu Shartnomaning 1.1.-bandida ko‘rsatilgan mikrokredit miqdori umumiy summasining 50% dan ko‘p bo‘lmagan miqdorda penya ko‘rinishidagi neustoyka to‘lash majburiyatini o‘z zimmasiga oladi. | C79: 6.1. Mikromoliya tashkiloti tomonidan Qarz oluvchiga pul mablag‘larini ajratib berish bo‘yicha o‘z zimmasiga olgan majburiyatlarning Shartnomaning 1.1.-bandida keltirilgan summa va muddatlarda bajarilmaslik yoki tegishli tarzda bajarilmaslik holatlarida Mikromoliya tashkiloti muddatidan o‘tgan har bir kalendar kun uchun kechiktirilgan to‘lov summasining 0,1% miqdorida, biroq ushbu Shartnomaning 1.1.-bandida ko‘rsatilgan | H79: =""&umumiy_malumot!B65&" miqdori umumiy summasining 50% dan ko‘p bo‘lmagan miqdorda penya ko‘rinishidagi neustoyka to‘lash majburiyatini o‘z zimmasiga oladi." -> mikrokredit miqdori umumiy summasining 50% dan ko‘p bo‘lmagan miqdorda penya ko‘rinishidagi neustoyka to‘lash majburiyatini o‘z zimmasiga oladi.
A80: 6.2. Jarima sanksiyalarni to‘lash Tomonlarni ushbu Shartnomada ko‘zda tutilgan zimmalaridagi majburiyatlarini bajarishdan ozod qilmaydi.
A81: 6.3. Tomonlarning ushbu Shartnomada nazarda tutilmagan javobgarligi O‘zbekiston Respublikasining amaldagi qonunchiligiga muvofiq belgilanadi.
A82: 6.4. Tomonlar O‘zbekiston Respublikasi Fuqarolik kodeksining 325-moddasiga muvofiq aybdor tomondan yetkazilgan zararni neustoykadan tashqari to‘la hajmda undirish huquqiga egadirlar.
A84: 7. FORS-MAJOR
A85: 7.1. Agar Tomonlar ular zimmasidagi majburiyatlarni tegishli darajada bajarishi yengib bo‘lmas kuch (fors-major) oqibatida mumkin bo‘lmay qolgan bo‘lsa, ya'ni aniq vaqt davri davomida aniq sharoitlarda favqulodda va oldini olib bo‘lmaydigan holatlar ekanligini isbotlay olmasalar, Shartnoma bo‘yicha o‘z majburiyatlarini bajarmagan yoki tegishli darajada bajarmagan Tomon uning shartlarini bajarishda javobgar hisoblanadi. Ushbu Shartnoma Tomonlari yengilmas kuch holatlariga quyidagilarni kiritadi: tabiiy ofat (zilzila, suv toshqini, chaqmoq chaqishi, vulqon otilishi, sel kelishi, ko‘chki, sunami va hokazo), Shartnoma bo‘yicha majburiyatlar bajarilish joyida temperatura – harorat, shamol kuchi va yog‘ingarchilik darajasining inson hayotiy faoliyati normasidan ortiq bo‘lishi; hokimiyat va boshqaruv organlari moratoriysi; qonuniy belgilangan tartibda tashkil etilgan ish tashlashlar va majburiyatlarning tegishli darajada bajarilishi uchun Shartnoma Tomonlari tarafidan yengib bo‘lmas kuch sifatida belgilangan boshqa holatlar.
A86: 7.2. Fors-major holati ta'sirida qolgan Tomon, bunday holatlar yuzaga kelgan kundan boshlab 7 (etti) kalendar kundan kechiktirmasdan boshqa Tomonni xabardor qilishi shart.
A87: 7.3. Fors-major holati boshlanganligi to‘g‘risida xabar qilmaslik yoki o‘z vaqtida xabar bermaslik fors-major holati boshlanganda Shartnoma bo‘yicha o‘z majburiyatlarini bajarish imkoniyatiga vaj qilib keltirish huquqiga ega emas.
A88: 7.4. Fors-major holati boshlanganligini vaj qilib ko‘rsatish huquqidan mahrum etilgan Tomon amaldagi qonun hujjatlariga muvofiq javobgar bo‘ladi.
A90: 8. NIZOLARNI HAL QILISH TARTIBI
A91: 8.1. Ushbu Shartnomadan kelib chiqadigan tomonlar o‘rtasidagi barcha nizolar va undan kelib chiqadigan majburiyatlar, shu jumladan shartnoma bajarilmasligi oqibatida yuzaga kelgan bajarilishi, o‘zgartirilishi, bekor qilinishi, tugatilishi Mikromoliya tashkilot joylashgan yerdagi taalluqli sudda yoki «CONSILIO» Mas'uliyati cheklangan jamiyat qoshidagi Hakamlik sudida, O‘zbekiston Respublikasining amaldagi qonun hujjatlari va uning reglamentiga muvofiq Hakamlik sudi raisi tomonidan tayinlangan, yakka tartibdagi hakamlik sudyasi tomonidan, sud ishlarini sud majlisi bayonnomasi tuzmasdan ko‘rib chiqilishi kerak bo‘ladi. U yoki bu sudga murojaat qilish huquqi da'vogarda qoladi.
A92: Qarzni undirish va garovdagi mol-mulkiga qaratish ham sud tartibida, ham suddan tashqari tartibda, shu jumladan notariusning ijro yozuvini olish yo‘li bilan amalga oshirilishi mumkin.
A93: ="8.2. Mikromoliya tashkiloti sud organlariga murojaat qilganidan keyin Qarz oluvchi tomonidan "&umumiy_malumot!B65&" bo‘yicha muddati o‘tgan qarzdorlikning to‘lanishi Mikromoliya tashkilotning "&umumiy_malumot!B65&" bo‘yicha qarzdorlikni muddatidan avval undirish, shu jumladan undiruvni garovdagi mol-mulkka qaratish yo‘li bilan undirish huquqidan mahrum qilmaydi." -> 8.2. Mikromoliya tashkiloti sud organlariga murojaat qilganidan keyin Qarz oluvchi tomonidan mikrokredit bo‘yicha muddati o‘tgan qarzdorlikning to‘lanishi Mikromoliya tashkilotning mikrokredit bo‘yicha qarzdorlikni muddatidan avval undirish, shu jumladan undiruvni garovdagi mol-mulkka qaratish yo‘li bilan undirish huquqidan mahrum qilmaydi.
A95: 9. SHARTNOMA SHARTLARI VA AMAL QILISH MUDDATI
A96: 9.1. Ushbu Shartnoma Tomonlar tarafidan imzolangandan keyin kuchga kiradi.
A97: ="9.2. Shartnomaning amal qilish muddati Qarz oluvchi "&umumiy_malumot!B65&"ni to‘liq qaytargan, hisoblangan foizlar, penya va boshqa pul majburiyatlarini to‘lagan kunda yakunlanadi." -> 9.2. Shartnomaning amal qilish muddati Qarz oluvchi mikrokreditni to‘liq qaytargan, hisoblangan foizlar, penya va boshqa pul majburiyatlarini to‘lagan kunda yakunlanadi.
A98: 9.3. Ushbu Shartnomaga kiritiladigan barcha o‘zgartirish va qo‘shimchalar, ushbu Shartnomada kelishilgan holatlardan tashqari, ikkala Tomon tarafidan qo‘shimcha bitimni yozma shaklda imzolagan holda amalga oshiriladi.
A100: 10. SHAXSIY MA'LUMOTLARNI QAYTA ISHLASH
A101: 10.1. Ushbu shartnomani tuzish bilan, Qarz oluvchi Mikromoliya tashkilotiga uning shaxsiy ma'lumotlari, shu jumladan, familiyasi, ismi, otasining ismi, pasport ma'lumotlari (shu jumladan, pasport raqami, berilgan vaqti va sanasi, ro‘yxatdan o‘tgan manzili va boshqalar); aloqaga chiqish uchun ma'lumotlar (shu jumladan, telefon raqami, e-mail, pochta manzili va boshqalar); STIR, ushbu shartnoma maqsadiga tegishli bo‘lgan boshqa ma'lumotlarni har qanday maqsadda ishlov berishga rozilik beradi.
A102: 10.2. Rozilik, shu jumladan shahsiy ma'lumotlar bilan quyidagi harakatlarni amalga oshirishga beriladi: yig‘ish, tizimlashtirish, to‘plash, saqlash, aniqlashtirish (yangilash, o‘zgartirish), foydalanish; O‘zbekiston Respublikasi qonun hujjatlarida nazarda tutilgan hollar va darajada tarqatish, shu jumladan davlat organlari va boshqa tashkilotlarga taqdim etish, shaxsiy ma'lumotlarning egasizlantirish, blokirovka va yo‘q qilish.
A103: 10.3. Qarz oluvchi, shuningdek, Mikromoliya tashkiloti shartnoma doirasida olingan ma'lumotlarni kredit byurosi va garov reestri, skoring kompaniyasi, uyali aloqa operatori, sug‘urta kompaniyasi, reklama ishlab chiqaruvchilari va tarqatuvchilari, shuningdek Mikromoliya tashkilotining boshqa hamkorlariga taqdim etishga roziligini bildiradi.
A105: 11. BOSHQA SHARTLAR
A106: 11.1. Ushbu shartnoma kuchga kirganidan keyin, o‘zaro munosabatlarga aloqador barcha yozishmalar yoki kelishuvlar, o‘z kuchini yo‘qotadi.
A107: 11.2. Ushbu shartnomani bajarish, o‘zgartirish va bekor qilish bilan bog‘liq barcha yozishma va xabarnomalar Tomonlarning ushbu shartnomaning yakuniy qismida ko‘rsatilgan pochta manzillariga yuboriladi.
A108: 11.3. Ushbu shartnomani bajarish uchun zarur bo‘lgan ismi (nomlanishi), ro‘yxatdan o‘tgan joyi, haqiqiy yashash joyi, manzili (joylashgan yeri), bank rekvizitlari va boshqa ma'lumotlar o‘zgargan holatlarda, Tomonlarning har biri bunday o‘zgarishlar amalga oshgan kundan boshlab 5 (besh) kalendar kun ichida boshqa Tomonni bunday o‘zgarishlar haqida yozma ravishda xabardor qilishi shart.
A109: 11.4. Ushbu bitimni amalga oshirish bilan, Qarz oluvchi kelishuvning muhimligi va uni tuzishning yuridik oqibatlarini to‘liq tushunib yetishi, shu sababli Shartnomani tuzish yanglishishlar, aldov, zo‘ravonlik, tahdidlar, yomon niyatli bitim yoki murakkab holatlar (tutqinlik) ta'sirida emasligini tasdiqlaydi.
A110: 11.5. Ushbu shartnomada ko‘zda tutilmagan holatlarda Tomonlar O‘zbekiston Respublikasining amaldagi qonunchiligiga amal qiladilar.
A111: 11.6. Qarz oluvchi Mikromoliya tashkilotining oldindan yozma roziligini olmasdan turib o‘z majburiyatlari yoki huquqlarini uchinchi shaxslarga o‘tkaza olmaydi.
... A113: 12. TOMONLARNING YURIDIK MANZILLARI VA REKVIZITLARI:
...

Sheet grafik
E3: =""&umumiy_malumot!B74&" "&umumiy_malumot!B65&" shartnomasiga 1 sonli ilova" -> 16 fevral 2026 y.dan № 110 mikrokredit shartnomasiga 1 sonli ilova
A5: To'lov jadvali
A7: № | B7: To'lov muddati | C7: Asosiy qarz qoldig'i | D7: To'lov miqdori, so'm
D8: asosiy qarz | E8: foizlar | F8: jami*
A9: 1 | B9: ='График аннуитет.'!B8 -> 46091 | C9: =IF(umumiy_malumot!$B$78=umumiy_malumot!$C$78,'График дифференц'!C8,IF(umumiy_malumot!$B$78=umumiy_malumot!$D$78,'График аннуитет.'!C8)) -> 175000000 | D9: =IF(umumiy_malumot!$B$78=umumiy_malumot!$C$78,'График дифференц'!D8,IF(umumiy_malumot!$B$78=umumiy_malumot!$D$78,'График аннуитет.'!D8)) -> 4861111.1 | E9: =IF(umumiy_malumot!$B$78=umumiy_malumot!$C$78,'График дифференц'!E8,IF(umumiy_malumot!$B$78=umumiy_malumot!$D$78,'График аннуитет.'!E8)) -> 5801369.9 | F9: =IF(umumiy_malumot!$B$78=umumiy_malumot!$C$78,'График дифференц'!F8,IF(umumiy_malumot!$B$78=umumiy_malumot!$D$78,'График аннуитет.'!F8)) -> 10662481
A10: 2 | B10: ='График аннуитет.'!B9 -> 46122 | C10: =IF(umumiy_malumot!$B$78=umumiy_malumot!$C$78,'График дифференц'!C9,IF(umumiy_malumot!$B$78=umumiy_malumot!$D$78,'График аннуитет.'!C9)) -> 1.7013889e+08 | D10: =IF(umumiy_malumot!$B$78=umumiy_malumot!$C$78,'График дифференц'!D9,IF(umumiy_malumot!$B$78=umumiy_malumot!$D$78,'График аннуитет.'!D9)) -> 4861111.1 | E10: =IF(umumiy_malumot!$B$78=umumiy_malumot!$C$78,'График дифференц'!E9,IF(umumiy_malumot!$B$78=umumiy_malumot!$D$78,'График аннуитет.'!E9)) -> 7947583.8 | F10: =IF(umumiy_malumot!$B$78=umumiy_malumot!$C$78,'График дифференц'!F9,IF(umumiy_malumot!$B$78=umumiy_malumot!$D$78,'График аннуитет.'!F9)) -> 12808695
A11: 3 | B11: ='График аннуитет.'!B10 -> 46153 | C11: =IF(umumiy_malumot!$B$78=umumiy_malumot!$C$78,'График дифференц'!C10,IF(umumiy_malumot!$B$78=umumiy_malumot!$D$78,'График аннуитет.'!C10)) -> 1.6527778e+08 | D11: =IF(umumiy_malumot!$B$78=umumiy_malumot!$C$78,'График дифференц'!D10,IF(umumiy_malumot!$B$78=umumiy_malumot!$D$78,'График аннуитет.'!D10)) -> 4861111.1 | E11: =IF(umumiy_malumot!$B$78=umumiy_malumot!$C$78,'График дифференц'!E10,IF(umumiy_malumot!$B$78=umumiy_malumot!$D$78,'График аннуитет.'!E10)) -> 7720510 | F11: =IF(umumiy_malumot!$B$78=umumiy_malumot!$C$78,'График дифференц'!F10,IF(umumiy_malumot!$B$78=umumiy_malumot!$D$78,'График аннуитет.'!F10)) -> 12581621
A12: 4 | B12: ='График аннуитет.'!B11 -> 46183 | C12: =IF(umumiy_malumot!$B$78=umumiy_malumot!$C$78,'График дифференц'!C11,IF(umumiy_malumot!$B$78=umumiy_malumot!$D$78,'График аннуитет.'!C11)) -> 1.6041667e+08 | D12: =IF(umumiy_malumot!$B$78=umumiy_malumot!$C$78,'График дифференц'!D11,IF(umumiy_malumot!$B$78=umumiy_malumot!$D$78,'График аннуитет.'!D11)) -> 4861111.1 | E12: =IF(umumiy_malumot!$B$78=umumiy_malumot!$C$78,'График дифференц'!E11,IF(umumiy_malumot!$B$78=umumiy_malumot!$D$78,'График аннуитет.'!E11)) -> 7251712.2 | F12: =IF(umumiy_malumot!$B$78=umumiy_malumot!$C$78,'График дифференц'!F11,IF(umumiy_malumot!$B$78=umumiy_malumot!$D$78,'График аннуитет.'!F11)) -> 12112823 | H12: GRAFIKTA BO'SH JOY BO'LSA SKRIT' QILIB TASHLANG!!!
A13: 5 | B13: ='График аннуитет.'!B12 -> 46213 | C13: =IF(umumiy_malumot!$B$78=umumiy_malumot!$C$78,'График дифференц'!C12,IF(umumiy_malumot!$B$78=umumiy_malumot!$D$78,'График аннуитет.'!C12)) -> 1.5555556e+08 | D13: =IF(umumiy_malumot!$B$78=umumiy_malumot!$C$78,'График дифференц'!D12,IF(umumiy_malumot!$B$78=umumiy_malumot!$D$78,'График аннуитет.'!D12)) -> 4861111.1 | E13: =IF(umumiy_malumot!$B$78=umumiy_malumot!$C$78,'График дифференц'!E12,IF(umumiy_malumot!$B$78=umumiy_malumot!$D$78,'График аннуитет.'!E12)) -> 7031963.4 | F13: =IF(umumiy_malumot!$B$78=umumiy_malumot!$C$78,'График дифференц'!F12,IF(umumiy_malumot!$B$78=umumiy_malumot!$D$78,'График аннуитет.'!F12)) -> 11893075
A14: 6 | B14: ='График аннуитет.'!B13 -> 46244 | C14: =IF(umumiy_malumot!$B$78=umumiy_malumot!$C$78,'График дифференц'!C13,IF(umumiy_malumot!$B$78=umumiy_malumot!$D$78,'График аннуитет.'!C13)) -> 1.5069444e+08 | D14: =IF(umumiy_malumot!$B$78=umumiy_malumot!$C$78,'График дифференц'!D13,IF(umumiy_malumot!$B$78=umumiy_malumot!$D$78,'График аннуитет.'!D13)) -> 4861111.1 | E14: =IF(umumiy_malumot!$B$78=umumiy_malumot!$C$78,'График дифференц'!E13,IF(umumiy_malumot!$B$78=umumiy_malumot!$D$78,'График аннуитет.'!E13)) -> 7039288.4 | F14: =IF(umumiy_malumot!$B$78=umumiy_malumot!$C$78,'График дифференц'!F13,IF(umumiy_malumot!$B$78=umumiy_malumot!$D$78,'График аннуитет.'!F13)) -> 11900400
A15: 7 | B15: ='График аннуитет.'!B14 -> 46275 | C15: =IF(umumiy_malumot!$B$78=umumiy_malumot!$C$78,'График дифференц'!C14,IF(umumiy_malumot!$B$78=umumiy_malumot!$D$78,'График аннуитет.'!C14)) -> 1.4583333e+08 | D15: =IF(umumiy_malumot!$B$78=umumiy_malumot!$C$78,'График дифференц'!D14,IF(umumiy_malumot!$B$78=umumiy_malumot!$D$78,'График аннуитет.'!D14)) -> 4861111.1 | E15: =IF(umumiy_malumot!$B$78=umumiy_malumot!$C$78,'График дифференц'!E14,IF(umumiy_malumot!$B$78=umumiy_malumot!$D$78,'График аннуитет.'!E14)) -> 6812214.7 | F15: =IF(umumiy_malumot!$B$78=umumiy_malumot!$C$78,'График дифференц'!F14,IF(umumiy_malumot!$B$78=umumiy_malumot!$D$78,'График аннуитет.'!F14)) -> 11673326
A16: 8 | B16: ='График аннуитет.'!B15 -> 46307 | C16: =IF(umumiy_malumot!$B$78=umumiy_malumot!$C$78,'График дифференц'!C15,IF(umumiy_malumot!$B$78=umumiy_malumot!$D$78,'График аннуитет.'!C15)) -> 1.4097222e+08 | D16: =IF(umumiy_malumot!$B$78=umumiy_malumot!$C$78,'График дифференц'!D15,IF(umumiy_malumot!$B$78=umumiy_malumot!$D$78,'График аннуитет.'!D15)) -> 4861111.1 | E16: =IF(umumiy_malumot!$B$78=umumiy_malumot!$C$78,'График дифференц'!E15,IF(umumiy_malumot!$B$78=umumiy_malumot!$D$78,'График аннуитет.'!E15)) -> 6797564.8 | F16: =IF(umumiy_malumot!$B$78=umumiy_malumot!$C$78,'График дифференц'!F15,IF(umumiy_malumot!$B$78=umumiy_malumot!$D$78,'График аннуитет.'!F15)) -> 11658676
A17: 9 | B17: ='График аннуитет.'!B16 -> 46336 | C17: =IF(umumiy_malumot!$B$78=umumiy_malumot!$C$78,'График дифференц'!C16,IF(umumiy_malumot!$B$78=umumiy_malumot!$D$78,'График аннуитет.'!C16)) -> 1.3611111e+08 | D17: =IF(umumiy_malumot!$B$78=umumiy_malumot!$C$78,'График дифференц'!D16,IF(umumiy_malumot!$B$78=umumiy_malumot!$D$78,'График аннуитет.'!D16)) -> 4861111.1 | E17: =IF(umumiy_malumot!$B$78=umumiy_malumot!$C$78,'График дифференц'!E16,IF(umumiy_malumot!$B$78=umumiy_malumot!$D$78,'График аннуитет.'!E16)) -> 5947869 | F17: =IF(umumiy_malumot!$B$78=umumiy_malumot!$C$78,'График дифференц'!F16,IF(umumiy_malumot!$B$78=umumiy_malumot!$D$78,'График аннуитет.'!F16)) -> 10808980
A18: 10 | B18: ='График аннуитет.'!B17 -> 46366 | C18: =IF(umumiy_malumot!$B$78=umumiy_malumot!$C$78,'График дифференц'!C17,IF(umumiy_malumot!$B$78=umumiy_malumot!$D$78,'График аннуитет.'!C17)) -> 1.3125e+08 | D18: =IF(umumiy_malumot!$B$78=umumiy_malumot!$C$78,'График дифференц'!D17,IF(umumiy_malumot!$B$78=umumiy_malumot!$D$78,'График аннуитет.'!D17)) -> 4861111.1 | E18: =IF(umumiy_malumot!$B$78=umumiy_malumot!$C$78,'График дифференц'!E17,IF(umumiy_malumot!$B$78=umumiy_malumot!$D$78,'График аннуитет.'!E17)) -> 5933219.1 | F18: =IF(umumiy_malumot!$B$78=umumiy_malumot!$C$78,'График дифференц'!F17,IF(umumiy_malumot!$B$78=umumiy_malumot!$D$78,'График аннуитет.'!F17)) -> 10794330
A19: 11 | B19: ='График аннуитет.'!B18 -> 46398 | C19: =IF(umumiy_malumot!$B$78=umumiy_malumot!$C$78,'График дифференц'!C18,IF(umumiy_malumot!$B$78=umumiy_malumot!$D$78,'График аннуитет.'!C18)) -> 1.2638889e+08 | D19: =IF(umumiy_malumot!$B$78=umumiy_malumot!$C$78,'График дифференц'!D18,IF(umumiy_malumot!$B$78=umumiy_malumot!$D$78,'График аннуитет.'!D18)) -> 4861111.1 | E19: =IF(umumiy_malumot!$B$78=umumiy_malumot!$C$78,'График дифференц'!E18,IF(umumiy_malumot!$B$78=umumiy_malumot!$D$78,'График аннуитет.'!E18)) -> 6094368.3 | F19: =IF(umumiy_malumot!$B$78=umumiy_malumot!$C$78,'График дифференц'!F18,IF(umumiy_malumot!$B$78=umumiy_malumot!$D$78,'График аннуитет.'!F18)) -> 10955479
A20: 12 | B20: ='График аннуитет.'!B19 -> 46428 | C20: =IF(umumiy_malumot!$B$78=umumiy_malumot!$C$78,'График дифференц'!C19,IF(umumiy_malumot!$B$78=umumiy_malumot!$D$78,'График аннуитет.'!C19)) -> 1.2152778e+08 | D20: =IF(umumiy_malumot!$B$78=umumiy_malumot!$C$78,'График дифференц'!D19,IF(umumiy_malumot!$B$78=umumiy_malumot!$D$78,'График аннуитет.'!D19)) -> 4861111.1 | E20: =IF(umumiy_malumot!$B$78=umumiy_malumot!$C$78,'График дифференц'!E19,IF(umumiy_malumot!$B$78=umumiy_malumot!$D$78,'График аннуитет.'!E19)) -> 5493721.5 | F20: =IF(umumiy_malumot!$B$78=umumiy_malumot!$C$78,'График дифференц'!F19,IF(umumiy_malumot!$B$78=umumiy_malumot!$D$78,'График аннуитет.'!F19)) -> 10354833
A21: 13 | B21: ='График аннуитет.'!B20 -> 46456 | C21: =IF(umumiy_malumot!$B$78=umumiy_malumot!$C$78,'График дифференц'!C20,IF(umumiy_malumot!$B$78=umumiy_malumot!$D$78,'График аннуитет.'!C20)) -> 1.1666667e+08 | D21: =IF(umumiy_malumot!$B$78=umumiy_malumot!$C$78,'График дифференц'!D20,IF(umumiy_malumot!$B$78=umumiy_malumot!$D$78,'График аннуитет.'!D20)) -> 4861111.1 | E21: =IF(umumiy_malumot!$B$78=umumiy_malumot!$C$78,'График дифференц'!E20,IF(umumiy_malumot!$B$78=umumiy_malumot!$D$78,'График аннуитет.'!E20)) -> 4922374.5 | F21: =IF(umumiy_malumot!$B$78=umumiy_malumot!$C$78,'График дифференц'!F20,IF(umumiy_malumot!$B$78=umumiy_malumot!$D$78,'График аннуитет.'!F20)) -> 9783485.6
A22: 14 | B22: ='График аннуитет.'!B21 -> 46489 | C22: =IF(umumiy_malumot!$B$78=umumiy_malumot!$C$78,'График дифференц'!C21,IF(umumiy_malumot!$B$78=umumiy_malumot!$D$78,'График аннуитет.'!C21)) -> 1.1180556e+08 | D22: =IF(umumiy_malumot!$B$78=umumiy_malumot!$C$78,'График дифференц'!D21,IF(umumiy_malumot!$B$78=umumiy_malumot!$D$78,'График аннуитет.'!D21)) -> 4861111.1 | E22: =IF(umumiy_malumot!$B$78=umumiy_malumot!$C$78,'График дифференц'!E21,IF(umumiy_malumot!$B$78=umumiy_malumot!$D$78,'График аннуитет.'!E21)) -> 5559646 | F22: =IF(umumiy_malumot!$B$78=umumiy_malumot!$C$78,'График дифференц'!F21,IF(umumiy_malumot!$B$78=umumiy_malumot!$D$78,'График аннуитет.'!F21)) -> 10420757
A23: 15 | B23: ='График аннуитет.'!B22 -> 46517 | C23: =IF(umumiy_malumot!$B$78=umumiy_malumot!$C$78,'График дифференц'!C22,IF(umumiy_malumot!$B$78=umumiy_malumot!$D$78,'График аннуитет.'!C22)) -> 1.0694444e+08 | D23: =IF(umumiy_malumot!$B$78=umumiy_malumot!$C$78,'График дифференц'!D22,IF(umumiy_malumot!$B$78=umumiy_malumot!$D$78,'График аннуитет.'!D22)) -> 4861111.1 | E23: =IF(umumiy_malumot!$B$78=umumiy_malumot!$C$78,'График дифференц'!E22,IF(umumiy_malumot!$B$78=umumiy_malumot!$D$78,'График аннуитет.'!E22)) -> 4512176.5 | F23: =IF(umumiy_malumot!$B$78=umumiy_malumot!$C$78,'График дифференц'!F22,IF(umumiy_malumot!$B$78=umumiy_malumot!$D$78,'График аннуитет.'!F22)) -> 9373287.6
A24: 16 | B24: ='График аннуитет.'!B23 -> 46548 | C24: =IF(umumiy_malumot!$B$78=umumiy_malumot!$C$78,'График дифференц'!C23,IF(umumiy_malumot!$B$78=umumiy_malumot!$D$78,'График аннуитет.'!C23)) -> 1.0208333e+08 | D24: =IF(umumiy_malumot!$B$78=umumiy_malumot!$C$78,'График дифференц'!D23,IF(umumiy_malumot!$B$78=umumiy_malumot!$D$78,'График аннуитет.'!D23)) -> 4861111.1 | E24: =IF(umumiy_malumot!$B$78=umumiy_malumot!$C$78,'График дифференц'!E23,IF(umumiy_malumot!$B$78=umumiy_malumot!$D$78,'График аннуитет.'!E23)) -> 4768550.2 | F24: =IF(umumiy_malumot!$B$78=umumiy_malumot!$C$78,'График дифференц'!F23,IF(umumiy_malumot!$B$78=umumiy_malumot!$D$78,'График аннуитет.'!F23)) -> 9629661.3
... A26: 18 | B26: ='График аннуитет.'!B25 -> 46609 | C26: =IF(umumiy_malumot!$B$78=umumiy_malumot!$C$78,'График дифференц'!C25,IF(umumiy_malumot!$B$78=umumiy_malumot!$D$78,'График аннуитет.'!C25)) -> 92361111 | D26: =IF(umumiy_malumot!$B$78=umumiy_malumot!$C$78,'График дифференц'!D25,IF(umumiy_malumot!$B$78=umumiy_malumot!$D$78,'График аннуитет.'!D25)) -> 4861111.1 | E26: =IF(umumiy_malumot!$B$78=umumiy_malumot!$C$78,'График дифференц'!E25,IF(umumiy_malumot!$B$78=umumiy_malumot!$D$78,'График аннуитет.'!E25)) -> 4036054.1 | F26: =IF(umumiy_malumot!$B$78=umumiy_malumot!$C$78,'График дифференц'!F25,IF(umumiy_malumot!$B$78=umumiy_malumot!$D$78,'График аннуитет.'!F25)) -> 8897165.2
A27: =1+A26 -> 19 | B27: ='График аннуитет.'!B26 -> 46640 | C27: =IF(umumiy_malumot!$B$78=umumiy_malumot!$C$78,'График дифференц'!C26,IF(umumiy_malumot!$B$78=umumiy_malumot!$D$78,'График аннуитет.'!C26)) -> 87500000 | D27: =IF(umumiy_malumot!$B$78=umumiy_malumot!$C$78,'График дифференц'!D26,IF(umumiy_malumot!$B$78=umumiy_malumot!$D$78,'График аннуитет.'!D26)) -> 4861111.1 | E27: =IF(umumiy_malumot!$B$78=umumiy_malumot!$C$78,'График дифференц'!E26,IF(umumiy_malumot!$B$78=umumiy_malumot!$D$78,'График аннуитет.'!E26)) -> 4087328.9 | F27: =IF(umumiy_malumot!$B$78=umumiy_malumot!$C$78,'График дифференц'!F26,IF(umumiy_malumot!$B$78=umumiy_malumot!$D$78,'График аннуитет.'!F26)) -> 8948440
A28: =1+A27 -> 20 | B28: ='График аннуитет.'!B27 -> 46671 | C28: =IF(umumiy_malumot!$B$78=umumiy_malumot!$C$78,'График дифференц'!C27,IF(umumiy_malumot!$B$78=umumiy_malumot!$D$78,'График аннуитет.'!C27)) -> 82638889 | D28: =IF(umumiy_malumot!$B$78=umumiy_malumot!$C$78,'График дифференц'!D27,IF(umumiy_malumot!$B$78=umumiy_malumot!$D$78,'График аннуитет.'!D27)) -> 4861111.1 | E28: =IF(umumiy_malumot!$B$78=umumiy_malumot!$C$78,'График дифференц'!E27,IF(umumiy_malumot!$B$78=umumiy_malumot!$D$78,'График аннуитет.'!E27)) -> 3860254.9 | F28: =IF(umumiy_malumot!$B$78=umumiy_malumot!$C$78,'График дифференц'!F27,IF(umumiy_malumot!$B$78=umumiy_malumot!$D$78,'График аннуитет.'!F27)) -> 8721366
A29: =1+A28 -> 21 | B29: ='График аннуитет.'!B28 -> 46701 | C29: =IF(umumiy_malumot!$B$78=umumiy_malumot!$C$78,'График дифференц'!C28,IF(umumiy_malumot!$B$78=umumiy_malumot!$D$78,'График аннуитет.'!C28)) -> 77777778 | D29: =IF(umumiy_malumot!$B$78=umumiy_malumot!$C$78,'График дифференц'!D28,IF(umumiy_malumot!$B$78=umumiy_malumot!$D$78,'График аннуитет.'!D28)) -> 4861111.1 | E29: =IF(umumiy_malumot!$B$78=umumiy_malumot!$C$78,'График дифференц'!E28,IF(umumiy_malumot!$B$78=umumiy_malumot!$D$78,'График аннуитет.'!E28)) -> 3515981.7 | F29: =IF(umumiy_malumot!$B$78=umumiy_malumot!$C$78,'График дифференц'!F28,IF(umumiy_malumot!$B$78=umumiy_malumot!$D$78,'График аннуитет.'!F28)) -> 8377092.8
A30: =1+A29 -> 22 | B30: ='График аннуитет.'!B29 -> 46731 | C30: =IF(umumiy_malumot!$B$78=umumiy_malumot!$C$78,'График дифференц'!C29,IF(umumiy_malumot!$B$78=umumiy_malumot!$D$78,'График аннуитет.'!C29)) -> 72916667 | D30: =IF(umumiy_malumot!$B$78=umumiy_malumot!$C$78,'График дифференц'!D29,IF(umumiy_malumot!$B$78=umumiy_malumot!$D$78,'График аннуитет.'!D29)) -> 4861111.1 | E30: =IF(umumiy_malumot!$B$78=umumiy_malumot!$C$78,'График дифференц'!E29,IF(umumiy_malumot!$B$78=umumiy_malumot!$D$78,'График аннуитет.'!E29)) -> 3296232.9 | F30: =IF(umumiy_malumot!$B$78=umumiy_malumot!$C$78,'График дифференц'!F29,IF(umumiy_malumot!$B$78=umumiy_malumot!$D$78,'График аннуитет.'!F29)) -> 8157344
A31: =1+A30 -> 23 | B31: ='График аннуитет.'!B30 -> 46762 | C31: =IF(umumiy_malumot!$B$78=umumiy_malumot!$C$78,'График дифференц'!C30,IF(umumiy_malumot!$B$78=umumiy_malumot!$D$78,'График аннуитет.'!C30)) -> 68055556 | D31: =IF(umumiy_malumot!$B$78=umumiy_malumot!$C$78,'График дифференц'!D30,IF(umumiy_malumot!$B$78=umumiy_malumot!$D$78,'График аннуитет.'!D30)) -> 4861111.1 | E31: =IF(umumiy_malumot!$B$78=umumiy_malumot!$C$78,'График дифференц'!E30,IF(umumiy_malumot!$B$78=umumiy_malumot!$D$78,'График аннуитет.'!E30)) -> 3170347.7 | F31: =IF(umumiy_malumot!$B$78=umumiy_malumot!$C$78,'График дифференц'!F30,IF(umumiy_malumot!$B$78=umumiy_malumot!$D$78,'График аннуитет.'!F30)) -> 8031458.8
A32: =1+A31 -> 24 | B32: ='График аннуитет.'!B31 -> 46793 | C32: =IF(umumiy_malumot!$B$78=umumiy_malumot!$C$78,'График дифференц'!C31,IF(umumiy_malumot!$B$78=umumiy_malumot!$D$78,'График аннуитет.'!C31)) -> 63194444 | D32: =IF(umumiy_malumot!$B$78=umumiy_malumot!$C$78,'График дифференц'!D31,IF(umumiy_malumot!$B$78=umumiy_malumot!$D$78,'График аннуитет.'!D31)) -> 4861111.1 | E32: =IF(umumiy_malumot!$B$78=umumiy_malumot!$C$78,'График дифференц'!E31,IF(umumiy_malumot!$B$78=umumiy_malumot!$D$78,'График аннуитет.'!E31)) -> 2943894.2 | F32: =IF(umumiy_malumot!$B$78=umumiy_malumot!$C$78,'График дифференц'!F31,IF(umumiy_malumot!$B$78=umumiy_malumot!$D$78,'График аннуитет.'!F31)) -> 7805005.3
A33: =1+A32 -> 25 | B33: =IF('График аннуитет.'!B32=FALSE,"",'График аннуитет.'!B32) -> 46822 | C33: =IF(umumiy_malumot!$B$78=umumiy_malumot!$C$78,'График дифференц'!C32,IF(umumiy_malumot!$B$78=umumiy_malumot!$D$78,'График аннуитет.'!C32)) -> 58333333 | D33: =IF(umumiy_malumot!$B$78=umumiy_malumot!$C$78,'График дифференц'!D32,IF(umumiy_malumot!$B$78=umumiy_malumot!$D$78,'График аннуитет.'!D32)) -> 4861111.1 | E33: =IF(umumiy_malumot!$B$78=umumiy_malumot!$C$78,'График дифференц'!E32,IF(umumiy_malumot!$B$78=umumiy_malumot!$D$78,'График аннуитет.'!E32)) -> 2542122 | F33: =IF(umumiy_malumot!$B$78=umumiy_malumot!$C$78,'График дифференц'!F32,IF(umumiy_malumot!$B$78=umumiy_malumot!$D$78,'График аннуитет.'!F32)) -> 7403233.1
A34: =1+A33 -> 26 | B34: =IF('График аннуитет.'!B33=FALSE,"",'График аннуитет.'!B33) -> 46853 | C34: =IF(umumiy_malumot!$B$78=umumiy_malumot!$C$78,'График дифференц'!C33,IF(umumiy_malumot!$B$78=umumiy_malumot!$D$78,'График аннуитет.'!C33)) -> 53472222 | D34: =IF(umumiy_malumot!$B$78=umumiy_malumot!$C$78,'График дифференц'!D33,IF(umumiy_malumot!$B$78=umumiy_malumot!$D$78,'График аннуитет.'!D33)) -> 4861111.1 | E34: =IF(umumiy_malumot!$B$78=umumiy_malumot!$C$78,'График дифференц'!E33,IF(umumiy_malumot!$B$78=umumiy_malumot!$D$78,'График аннуитет.'!E33)) -> 2490987.3 | F34: =IF(umumiy_malumot!$B$78=umumiy_malumot!$C$78,'График дифференц'!F33,IF(umumiy_malumot!$B$78=umumiy_malumot!$D$78,'График аннуитет.'!F33)) -> 7352098.4
A35: =1+A34 -> 27 | B35: =IF('График аннуитет.'!B34=FALSE,"",'График аннуитет.'!B34) -> 46883 | C35: =IF(umumiy_malumot!$B$78=umumiy_malumot!$C$78,'График дифференц'!C34,IF(umumiy_malumot!$B$78=umumiy_malumot!$D$78,'График аннуитет.'!C34)) -> 48611111 | D35: =IF(umumiy_malumot!$B$78=umumiy_malumot!$C$78,'График дифференц'!D34,IF(umumiy_malumot!$B$78=umumiy_malumot!$D$78,'График аннуитет.'!D34)) -> 4861111.1 | E35: =IF(umumiy_malumot!$B$78=umumiy_malumot!$C$78,'График дифференц'!E34,IF(umumiy_malumot!$B$78=umumiy_malumot!$D$78,'График аннуитет.'!E34)) -> 2191484.4 | F35: =IF(umumiy_malumot!$B$78=umumiy_malumot!$C$78,'График дифференц'!F34,IF(umumiy_malumot!$B$78=umumiy_malumot!$D$78,'График аннуитет.'!F34)) -> 7052595.5
A36: =1+A35 -> 28 | B36: =IF('График аннуитет.'!B35=FALSE,"",'График аннуитет.'!B35) -> 46916 | C36: =IF(umumiy_malumot!$B$78=umumiy_malumot!$C$78,'График дифференц'!C35,IF(umumiy_malumot!$B$78=umumiy_malumot!$D$78,'График аннуитет.'!C35)) -> 43750000 | D36: =IF(umumiy_malumot!$B$78=umumiy_malumot!$C$78,'График дифференц'!D35,IF(umumiy_malumot!$B$78=umumiy_malumot!$D$78,'График аннуитет.'!D35)) -> 4861111.1 | E36: =IF(umumiy_malumot!$B$78=umumiy_malumot!$C$78,'График дифференц'!E35,IF(umumiy_malumot!$B$78=umumiy_malumot!$D$78,'График аннуитет.'!E35)) -> 2169569.8 | F36: =IF(umumiy_malumot!$B$78=umumiy_malumot!$C$78,'График дифференц'!F35,IF(umumiy_malumot!$B$78=umumiy_malumot!$D$78,'График аннуитет.'!F35)) -> 7030680.9
A37: =1+A36 -> 29 | B37: =IF('График аннуитет.'!B36=FALSE,"",'График аннуитет.'!B36) -> 46944 | C37: =IF(umumiy_malumot!$B$78=umumiy_malumot!$C$78,'График дифференц'!C36,IF(umumiy_malumot!$B$78=umumiy_malumot!$D$78,'График аннуитет.'!C36)) -> 38888889 | D37: =IF(umumiy_malumot!$B$78=umumiy_malumot!$C$78,'График дифференц'!D36,IF(umumiy_malumot!$B$78=umumiy_malumot!$D$78,'График аннуитет.'!D36)) -> 4861111.1 | E37: =IF(umumiy_malumot!$B$78=umumiy_malumot!$C$78,'График дифференц'!E36,IF(umumiy_malumot!$B$78=umumiy_malumot!$D$78,'График аннуитет.'!E36)) -> 1636308.5 | F37: =IF(umumiy_malumot!$B$78=umumiy_malumot!$C$78,'График дифференц'!F36,IF(umumiy_malumot!$B$78=umumiy_malumot!$D$78,'График аннуитет.'!F36)) -> 6497419.6
A38: =1+A37 -> 30 | B38: =IF('График аннуитет.'!B37=FALSE,"",'График аннуитет.'!B37) -> 46975 | C38: =IF(umumiy_malumot!$B$78=umumiy_malumot!$C$78,'График дифференц'!C37,IF(umumiy_malumot!$B$78=umumiy_malumot!$D$78,'График аннуитет.'!C37)) -> 34027778 | D38: =IF(umumiy_malumot!$B$78=umumiy_malumot!$C$78,'График дифференц'!D37,IF(umumiy_malumot!$B$78=umumiy_malumot!$D$78,'График аннуитет.'!D37)) -> 4861111.1 | E38: =IF(umumiy_malumot!$B$78=umumiy_malumot!$C$78,'График дифференц'!E37,IF(umumiy_malumot!$B$78=umumiy_malumot!$D$78,'График аннуитет.'!E37)) -> 1585173.8 | F38: =IF(umumiy_malumot!$B$78=umumiy_malumot!$C$78,'График дифференц'!F37,IF(umumiy_malumot!$B$78=umumiy_malumot!$D$78,'График аннуитет.'!F37)) -> 6446285
A39: =1+A38 -> 31 | B39: =IF('График аннуитет.'!B38=FALSE,"",'График аннуитет.'!B38) -> 47007 | C39: =IF(umumiy_malumot!$B$78=umumiy_malumot!$C$78,'График дифференц'!C38,IF(umumiy_malumot!$B$78=umumiy_malumot!$D$78,'График аннуитет.'!C38)) -> 29166667 | D39: =IF(umumiy_malumot!$B$78=umumiy_malumot!$C$78,'График дифференц'!D38,IF(umumiy_malumot!$B$78=umumiy_malumot!$D$78,'График аннуитет.'!D38)) -> 4861111.1 | E39: =IF(umumiy_malumot!$B$78=umumiy_malumot!$C$78,'График дифференц'!E38,IF(umumiy_malumot!$B$78=umumiy_malumot!$D$78,'График аннуитет.'!E38)) -> 1402550.1 | F39: =IF(umumiy_malumot!$B$78=umumiy_malumot!$C$78,'График дифференц'!F38,IF(umumiy_malumot!$B$78=umumiy_malumot!$D$78,'График аннуитет.'!F38)) -> 6263661.2
A40: =1+A39 -> 32 | B40: =IF('График аннуитет.'!B39=FALSE,"",'График аннуитет.'!B39) -> 47036 | C40: =IF(umumiy_malumot!$B$78=umumiy_malumot!$C$78,'График дифференц'!C39,IF(umumiy_malumot!$B$78=umumiy_malumot!$D$78,'График аннуитет.'!C39)) -> 24305556 | D40: =IF(umumiy_malumot!$B$78=umumiy_malumot!$C$78,'График дифференц'!D39,IF(umumiy_malumot!$B$78=umumiy_malumot!$D$78,'График аннуитет.'!D39)) -> 4861111.1 | E40: =IF(umumiy_malumot!$B$78=umumiy_malumot!$C$78,'График дифференц'!E39,IF(umumiy_malumot!$B$78=umumiy_malumot!$D$78,'График аннуитет.'!E39)) -> 1059217.5 | F40: =IF(umumiy_malumot!$B$78=umumiy_malumot!$C$78,'График дифференц'!F39,IF(umumiy_malumot!$B$78=umumiy_malumot!$D$78,'График аннуитет.'!F39)) -> 5920328.6
A41: =1+A40 -> 33 | B41: =IF('График аннуитет.'!B40=FALSE,"",'График аннуитет.'!B40) -> 47067 | C41: =IF(umumiy_malumot!$B$78=umumiy_malumot!$C$78,'График дифференц'!C40,IF(umumiy_malumot!$B$78=umumiy_malumot!$D$78,'График аннуитет.'!C40)) -> 19444444 | D41: =IF(umumiy_malumot!$B$78=umumiy_malumot!$C$78,'График дифференц'!D40,IF(umumiy_malumot!$B$78=umumiy_malumot!$D$78,'График аннуитет.'!D40)) -> 4861111.1 | E41: =IF(umumiy_malumot!$B$78=umumiy_malumot!$C$78,'График дифференц'!E40,IF(umumiy_malumot!$B$78=umumiy_malumot!$D$78,'График аннуитет.'!E40)) -> 905813.49 | F41: =IF(umumiy_malumot!$B$78=umumiy_malumot!$C$78,'График дифференц'!F40,IF(umumiy_malumot!$B$78=umumiy_malumot!$D$78,'График аннуитет.'!F40)) -> 5766924.6
A42: =1+A41 -> 34 | B42: =IF('График аннуитет.'!B41=FALSE,"",'График аннуитет.'!B41) -> 47098 | C42: =IF(umumiy_malumot!$B$78=umumiy_malumot!$C$78,'График дифференц'!C41,IF(umumiy_malumot!$B$78=umumiy_malumot!$D$78,'График аннуитет.'!C41)) -> 14583333 | D42: =IF(umumiy_malumot!$B$78=umumiy_malumot!$C$78,'График дифференц'!D41,IF(umumiy_malumot!$B$78=umumiy_malumot!$D$78,'График аннуитет.'!D41)) -> 4861111.1 | E42: =IF(umumiy_malumot!$B$78=umumiy_malumot!$C$78,'График дифференц'!E41,IF(umumiy_malumot!$B$78=umumiy_malumot!$D$78,'График аннуитет.'!E41)) -> 679360.35 | F42: =IF(umumiy_malumot!$B$78=umumiy_malumot!$C$78,'График дифференц'!F41,IF(umumiy_malumot!$B$78=umumiy_malumot!$D$78,'График аннуитет.'!F41)) -> 5540471.5
A43: =1+A42 -> 35 | B43: =IF('График аннуитет.'!B42=FALSE,"",'График аннуитет.'!B42) -> 47128 | C43: =IF(umumiy_malumot!$B$78=umumiy_malumot!$C$78,'График дифференц'!C42,IF(umumiy_malumot!$B$78=umumiy_malumot!$D$78,'График аннуитет.'!C42)) -> 9722222.3 | D43: =IF(umumiy_malumot!$B$78=umumiy_malumot!$C$78,'График дифференц'!D42,IF(umumiy_malumot!$B$78=umumiy_malumot!$D$78,'График аннуитет.'!D42)) -> 4861111.1 | E43: =IF(umumiy_malumot!$B$78=umumiy_malumot!$C$78,'График дифференц'!E42,IF(umumiy_malumot!$B$78=umumiy_malumot!$D$78,'График аннуитет.'!E42)) -> 439497.6 | F43: =IF(umumiy_malumot!$B$78=umumiy_malumot!$C$78,'График дифференц'!F42,IF(umumiy_malumot!$B$78=umumiy_malumot!$D$78,'График аннуитет.'!F42)) -> 5300608.7
A44: =1+A43 -> 36 | B44: =IF('График аннуитет.'!B43=FALSE,"",'График аннуитет.'!B43) -> 47165 | C44: =IF(umumiy_malumot!$B$78=umumiy_malumot!$C$78,'График дифференц'!C43,IF(umumiy_malumot!$B$78=umumiy_malumot!$D$78,'График аннуитет.'!C43)) -> 4861111.1 | D44: =IF(umumiy_malumot!$B$78=umumiy_malumot!$C$78,'График дифференц'!D43,IF(umumiy_malumot!$B$78=umumiy_malumot!$D$78,'График аннуитет.'!D43)) -> 4861111.1 | E44: =IF(umumiy_malumot!$B$78=umumiy_malumot!$C$78,'График дифференц'!E43,IF(umumiy_malumot!$B$78=umumiy_malumot!$D$78,'График аннуитет.'!E43)) -> 271023.52 | F44: =IF(umumiy_malumot!$B$78=umumiy_malumot!$C$78,'График дифференц'!F43,IF(umumiy_malumot!$B$78=umumiy_malumot!$D$78,'График аннуитет.'!F43)) -> 5132134.7
... A56: =1+A55 -> 48 | B56: =IF('График аннуитет.'!B55=FALSE,"",'График аннуитет.'!B55) | C56: =IF(umumiy_malumot!$B$78=umumiy_malumot!$C$78,'График дифференц'!C55,IF(umumiy_malumot!$B$78=umumiy_malumot!$D$78,'График аннуитет.'!C55)) -> 1.3969839e-08 | D56: =IF(umumiy_malumot!$B$78=umumiy_malumot!$C$78,'График дифференц'!D55,IF(umumiy_malumot!$B$78=umumiy_malumot!$D$78,'График аннуитет.'!D55)) -> FALSE | E56: =IF(umumiy_malumot!$B$78=umumiy_malumot!$C$78,'График дифференц'!E55,IF(umumiy_malumot!$B$78=umumiy_malumot!$D$78,'График аннуитет.'!E55)) -> FALSE | F56: =IF(umumiy_malumot!$B$78=umumiy_malumot!$C$78,'График дифференц'!F55,IF(umumiy_malumot!$B$78=umumiy_malumot!$D$78,'График аннуитет.'!F55)) -> FALSE
B57: JAMI | D57: =SUM(D9:D56) -> 175000000 | E57: =SUM(E9:E56) -> 1.4660531e+08 | F57: =SUM(F9:F56) -> 3.2160531e+08
A59: ="*"&umumiy_malumot!C64&" bo‘yicha to‘lovlar to‘lov jadvalida ko‘rsatilmagan sanalarda to‘langan taqdirda, to‘lov summasi mikroqarz shartnomasining 2.2.-bandiga muvofiq "&umumiy_malumot!B65&" qoldig‘iga hisoblangan foizlar summasiga o‘zgartiriladi." -> *Mikrokredit bo‘yicha to‘lovlar to‘lov jadvalida ko‘rsatilmagan sanalarda to‘langan taqdirda, to‘lov summasi mikroqarz shartnomasining 2.2.-bandiga muvofiq mikrokredit qoldig‘iga hisoblangan foizlar summasiga o‘zgartiriladi.
A61: «Mikromoliya tashkiloti » | D61: «Qarz oluvchi»
A63: =shartnoma!A117 -> «PULLOL BUSINESS MIKROMOLIYA TASHKILOTI» MChJ | D63: =shartnoma!B117 -> NORINBOYEVA SOXIBA IZZATILLAYEVNA
A64: =shartnoma!A119 -> Manzil: Toshkent shahri, Yakkasaroy tumani, Rakat ko'chasi, 10 uy, 18 xonadon | D64: =shartnoma!B119 -> Manzil: TOSHKENT VILOYATI CHINOZ TUMANI ALISHER NAVOIY MFY SOBIR RAHIMOV KO'CHASI 36 UY
A65: =shartnoma!A120 -> h/r: №20208000405643889001 | D65: =shartnoma!B121 -> Pasport: AE 5547691, IIV 27256 tomonidan 22.12.2025 yilda berilgan
A66: =shartnoma!A121 -> MFO: №01088 в ATB “Kapitalbank” Markaziy amaliyotlar bo'limi
A67: =shartnoma!A122 -> STIR: 310430149 | D67: =shartnoma!B122 -> Tel: 33 730 30 31 MIJOZ
A68: =shartnoma!A123 -> Tel: 555 100 217 | D68: =shartnoma!B123 -> 99 407 50 08 UY EGASI
A69: =shartnoma!A124 -> Tel: (97) 714 14 17 | D69: =shartnoma!B124 -> 94 659 57 51 ADASI
A70: =shartnoma!A126 -> Tel: (97) 706 96 65 | D70: =IF(shartnoma!B125=0,"",shartnoma!B125)
A71: =umumiy_malumot!A161 -> Direktor | D71: =shartnoma!B128 -> NORINBOYEVA S.I. __________________
A72: =umumiy_malumot!B161 -> Obidov A.Sh.

Sheet garov_ariza
C6: =umumiy_malumot!B158 -> «PULLOL BUSINESS MIKROMOLIYA TASHKILOTI» MChJ
C7: =umumiy_malumot!A161&" "&umumiy_malumot!B161 &"ga" -> Direktor Obidov A.Sh.ga
C8: =umumiy_malumot!B113 & "dan" -> NORINBAYEVA S.M.dan
C9: =[3]malumot!B119 -> FAYZIYEV JAMSHID KURBONOVICH
C10: =[3]malumot!C119 -> 0
C11: dan
B12: ARIZA
A13: =IF(umumiy_malumot!B103="Avtotransport",A14,A15) -> NORINBOYEVA SOXIBA IZZATILLAYEVNA tomonidan so’ralayotgan 36 (O'ttiz olti ) oy muddatga, 175 000 000 (yuz yetmish besh million so'm) miqdoridagi mikrokreditning ta’minoti sifatida menga mulk huquqi asosida tegishli bo’lgan , umumiy yer maydoni-700,qurilish osti maydoni- 340.11 umumiy foydali maydoni- 163.19 va yashash maydoni 114.59 TOSHKENT VILOYATI CHINOZ TUMANI ALISHER NAVOIY MFY SOBIR RAHIMOV KO'CHASI 36 UY manzilda joylashgan ko'chmas mulkni qabul qilishingizni so’rayman:
A14: =""&umumiy_malumot!B12&" tomonidan so’ralayotgan "&umumiy_malumot!B81&" ("&umumiy_malumot!B82&") oy muddatga, "&FIXED(umumiy_malumot!B75,0)&" ("&umumiy_malumot!B76&") miqdoridagi "&umumiy_malumot!B65&"ning ta’minoti sifatida menga mulk huquqi asosida tegishli bo’lgan "&umumiy_malumot!B125&", "&umumiy_malumot!B127&", "&umumiy_malumot!B130&", "&umumiy_malumot!B133&", avtotransport vositasini qabul qilishingizni so’rayman:" -> NORINBOYEVA SOXIBA IZZATILLAYEVNA tomonidan so’ralayotgan 46091 (36) oy muddatga, 150 000 000 (175000000) miqdoridagi mikrokreditning ta’minoti sifatida menga mulk huquqi asosida tegishli bo’lgan NORINBAYEVA S.M., AE 4754225, 7- TRO' VA IOB (YANGIHAYOT), 01Z067RC, avtotransport vositasini qabul qilishingizni so’rayman:
A15: =""&umumiy_malumot!B12&" tomonidan so’ralayotgan "&umumiy_malumot!B82&" ("&umumiy_malumot!B83&") oy muddatga, "&FIXED(umumiy_malumot!B76,0)&" ("&umumiy_malumot!B77&") miqdoridagi "&umumiy_malumot!B65&"ning ta’minoti sifatida menga mulk huquqi asosida tegishli bo’lgan "&umumiy_malumot!C1232&", umumiy yer maydoni-"&umumiy_malumot!C140&",qurilish osti maydoni- "&umumiy_malumot!C139&" umumiy foydali maydoni- "&umumiy_malumot!C137&" va yashash maydoni "&umumiy_malumot!C138&" "&umumiy_malumot!C123&" manzilda joylashgan ko'chmas mulkni qabul qilishingizni so’rayman:" -> NORINBOYEVA SOXIBA IZZATILLAYEVNA tomonidan so’ralayotgan 36 (O'ttiz olti ) oy muddatga, 175 000 000 (yuz yetmish besh million so'm) miqdoridagi mikrokreditning ta’minoti sifatida menga mulk huquqi asosida tegishli bo’lgan , umumiy yer maydoni-700,qurilish osti maydoni- 340.11 umumiy foydali maydoni- 163.19 va yashash maydoni 114.59 TOSHKENT VILOYATI CHINOZ TUMANI ALISHER NAVOIY MFY SOBIR RAHIMOV KO'CHASI 36 UY manzilda joylashgan ko'chmas mulkni qabul qilishingizni so’rayman:
C18: Sana:
A19: =+IF(umumiy_malumot!B100="ha",umumiy_malumot!B7,umumiy_malumot!B113) -> NORINBAYEVA S.M. | C19: =umumiy_malumot!B2 -> 16.02.2026
A20: =IF(umumiy_malumot!B100=umumiy_malumot!D100,CONCATENATE(A28," ",A32,A26),"") -> № 00.01.1900sanasidan xususiy faoliyat ko'rsatuvchi notarius tomonidan berilgan ishonchnomaga asosan
A23: =umumiy_malumot!A161 -> Direktor | C23: =umumiy_malumot!B161 -> Obidov A.Sh.
A26: =" xususiy faoliyat ko'rsatuvchi notarius tomonidan "&umumiy_malumot!B104&" "&umumiy_malumot!B105&" berilgan ishonchnomaga asosan " -> xususiy faoliyat ko'rsatuvchi notarius tomonidan berilgan ishonchnomaga asosan
A28: ="№"&umumiy_malumot!B107& "" -> №
A29: =umumiy_malumot!B108 -> 0
A30: =TEXT(A29,"ДД.ММ.ГГГГ") -> 00.01.1900
A31: sanasidan
A32: =CONCATENATE(A30,A31) -> 00.01.1900sanasidan

Sheet dalolatnoma
A2: ="GAROV PREDMETI QIYMATINI KELISHISH №"&umumiy_malumot!B148&" SONLI DALOLATNOMASI " -> GAROV PREDMETI QIYMATINI KELISHISH №1 SONLI DALOLATNOMASI
A4: Toshkent shahri | F4: =umumiy_malumot!B149 -> 16 fevral 2026 y.
A6: =IF(umumiy_malumot!B110="avtotransport",dalolatnoma!A10:F10,dalolatnoma!A7:F7) -> «PULLOL BUSINESS MIKROMOLIYA TASHKILOTI» MChJning (1-tomon) vakili bo‘lgan Direktor Obidov A.Sh., va O‘zbekiston Respublikasi fuqarosi NORINBOYEVA SOXIBA IZZATILLAYEVNA (2-tomon) va garov egasi NORINBAYEVA SAPURA MAMADALIYEVNA (3-tomon) 16 fevral 2026 y.dan № 110 Mikrokredit shartnomasiga muvofiq 1-tomon 2-tomonga berilgan mikrokredit bo‘yicha ta’minot sifatida taqdim etilgan, 2-tomonga mulk huquqi asosida tegishli bo‘lgan mulkning garov qiymatini kelishish muzokaralari o’tkazildi.
A7: =IF(umumiy_malumot!B100="ha",dalolatnoma!A9:F9,dalolatnoma!A8:F8) -> «PULLOL BUSINESS MIKROMOLIYA TASHKILOTI» MChJning (1-tomon) vakili bo‘lgan Direktor Obidov A.Sh., va O‘zbekiston Respublikasi fuqarosi NORINBOYEVA SOXIBA IZZATILLAYEVNA (2-tomon) va garov egasi NORINBAYEVA SAPURA MAMADALIYEVNA (3-tomon) 16 fevral 2026 y.dan № 110 Mikrokredit shartnomasiga muvofiq 1-tomon 2-tomonga berilgan mikrokredit bo‘yicha ta’minot sifatida taqdim etilgan, 2-tomonga mulk huquqi asosida tegishli bo‘lgan mulkning garov qiymatini kelishish muzokaralari o’tkazildi.
A8: =""&umumiy_malumot!B158&"ning (1-tomon) vakili bo‘lgan "&umumiy_malumot!A161&" "&umumiy_malumot!B161&", va O‘zbekiston Respublikasi fuqarosi "&umumiy_malumot!B5&" (2-tomon) va garov egasi "&umumiy_malumot!C124&" (3-tomon) "&umumiy_malumot!B74&" "&umumiy_malumot!C64&" shartnomasiga muvofiq 1-tomon 2-tomonga berilgan "&umumiy_malumot!B65&" bo‘yicha ta’minot sifatida taqdim etilgan, 2-tomonga mulk huquqi asosida tegishli bo‘lgan mulkning garov qiymatini kelishish muzokaralari o’tkazildi. " -> «PULLOL BUSINESS MIKROMOLIYA TASHKILOTI» MChJning (1-tomon) vakili bo‘lgan Direktor Obidov A.Sh., va O‘zbekiston Respublikasi fuqarosi NORINBOYEVA SOXIBA IZZATILLAYEVNA (2-tomon) va garov egasi NORINBAYEVA SAPURA MAMADALIYEVNA (3-tomon) 16 fevral 2026 y.dan № 110 Mikrokredit shartnomasiga muvofiq 1-tomon 2-tomonga berilgan mikrokredit bo‘yicha ta’minot sifatida taqdim etilgan, 2-tomonga mulk huquqi asosida tegishli bo‘lgan mulkning garov qiymatini kelishish muzokaralari o’tkazildi.
A9: =""&umumiy_malumot!B158&"ning (1-tomon) vakili bo‘lgan "&umumiy_malumot!A161&" "&umumiy_malumot!B161&", va O‘zbekiston Respublikasi fuqarosi "&umumiy_malumot!B5&" (2-tomon) va garov egasi "&umumiy_malumot!C124&" (3-tomon) "&umumiy_malumot!B74&" "&umumiy_malumot!C64&" shartnomasiga muvofiq 1-tomon 2-tomonga berilgan "&umumiy_malumot!B65&" bo‘yicha ta’minot sifatida taqdim etilgan, 2-tomonga mulk huquqi asosida tegishli bo‘lgan mulkning garov qiymatini kelishish muzokaralari o’tkazildi. " -> «PULLOL BUSINESS MIKROMOLIYA TASHKILOTI» MChJning (1-tomon) vakili bo‘lgan Direktor Obidov A.Sh., va O‘zbekiston Respublikasi fuqarosi NORINBOYEVA SOXIBA IZZATILLAYEVNA (2-tomon) va garov egasi NORINBAYEVA SAPURA MAMADALIYEVNA (3-tomon) 16 fevral 2026 y.dan № 110 Mikrokredit shartnomasiga muvofiq 1-tomon 2-tomonga berilgan mikrokredit bo‘yicha ta’minot sifatida taqdim etilgan, 2-tomonga mulk huquqi asosida tegishli bo‘lgan mulkning garov qiymatini kelishish muzokaralari o’tkazildi.
A10: =IF(umumiy_malumot!B100="ha",dalolatnoma!A12:F12,dalolatnoma!A11:F11) -> «PULLOL BUSINESS MIKROMOLIYA TASHKILOTI» MChJning (1-tomon) vakili bo‘lgan Direktor Obidov A.Sh., O‘zbekiston Respublikasi fuqarosi NORINBOYEVA SOXIBA IZZATILLAYEVNA (2-tomon) va garovga beruvchi O‘zbekiston Respublikasi fuqarosi NORINBAYEVA SAPURA MAMADALIYEVNA (3-tomon) o’rtalarida, 16 fevral 2026 y.dan № 110-sonli Mikrokredit shartnomasiga muvofiq 1-tomon 2-tomonga berilgan mikrokredit bo‘yicha ta’minot sifatida taqdim etilgan, 3-tomonga mulk huquqi asosida tegishli bo‘lgan mulkning garov qiymatini kelishish muzokaralari o’tkazildi.
A11: =""&umumiy_malumot!B158&"ning (1-tomon) vakili bo‘lgan "&umumiy_malumot!A161&" "&umumiy_malumot!B161&", O‘zbekiston Respublikasi fuqarosi "&umumiy_malumot!B5&" (2-tomon) va garovga beruvchi O‘zbekiston Respublikasi fuqarosi "&umumiy_malumot!B124&" (3-tomon) o’rtalarida, "&umumiy_malumot!B74&"-sonli "&umumiy_malumot!C64&" shartnomasiga muvofiq 1-tomon 2-tomonga berilgan "&umumiy_malumot!B65&" bo‘yicha ta’minot sifatida taqdim etilgan, 3-tomonga mulk huquqi asosida tegishli bo‘lgan mulkning garov qiymatini kelishish muzokaralari o’tkazildi." -> «PULLOL BUSINESS MIKROMOLIYA TASHKILOTI» MChJning (1-tomon) vakili bo‘lgan Direktor Obidov A.Sh., O‘zbekiston Respublikasi fuqarosi NORINBOYEVA SOXIBA IZZATILLAYEVNA (2-tomon) va garovga beruvchi O‘zbekiston Respublikasi fuqarosi NORINBAYEVA SAPURA MAMADALIYEVNA (3-tomon) o’rtalarida, 16 fevral 2026 y.dan № 110-sonli Mikrokredit shartnomasiga muvofiq 1-tomon 2-tomonga berilgan mikrokredit bo‘yicha ta’minot sifatida taqdim etilgan, 3-tomonga mulk huquqi asosida tegishli bo‘lgan mulkning garov qiymatini kelishish muzokaralari o’tkazildi.
A12: =""&umumiy_malumot!B158&"ning (1-tomon) vakili bo‘lgan "&umumiy_malumot!A161&" "&umumiy_malumot!B161&", O‘zbekiston Respublikasi fuqarosi va garovga beruvchi "&umumiy_malumot!B5&" (2-tomon) o’rtalarida, "&umumiy_malumot!B74&"-sonli "&umumiy_malumot!C64&" shartnomasiga muvofiq 1-tomon 2-tomonga berilgan "&umumiy_malumot!B65&" bo‘yicha ta’minot sifatida taqdim etilgan, 2-tomonga mulk huquqi asosida tegishli bo‘lgan mulkning garov qiymatini kelishish muzokaralari o’tkazildi." -> «PULLOL BUSINESS MIKROMOLIYA TASHKILOTI» MChJning (1-tomon) vakili bo‘lgan Direktor Obidov A.Sh., O‘zbekiston Respublikasi fuqarosi va garovga beruvchi NORINBOYEVA SOXIBA IZZATILLAYEVNA (2-tomon) o’rtalarida, 16 fevral 2026 y.dan № 110-sonli Mikrokredit shartnomasiga muvofiq 1-tomon 2-tomonga berilgan mikrokredit bo‘yicha ta’minot sifatida taqdim etilgan, 2-tomonga mulk huquqi asosida tegishli bo‘lgan mulkning garov qiymatini kelishish muzokaralari o’tkazildi.
A13: ="Garov predmeti sifatida "&umumiy_malumot!B132&", 3-tomonga egalik huquqi tegishli bo'lgan, quyidagi tafsilotlarga ega avtotransport vositasi taqdim etiladi:" -> Garov predmeti sifatida CHEVROLET COBALT, 3-tomonga egalik huquqi tegishli bo'lgan, quyidagi tafsilotlarga ega avtotransport vositasi taqdim etiladi:
A14: ="Garov predmeti sifatida "&umumiy_malumot!B132&", 2-tomonga egalik huquqi tegishli bo'lgan, quyidagi tafsilotlarga ega avtotransport vositasi taqdim etiladi:" -> Garov predmeti sifatida CHEVROLET COBALT, 2-tomonga egalik huquqi tegishli bo'lgan, quyidagi tafsilotlarga ega avtotransport vositasi taqdim etiladi:
A15: =IF(umumiy_malumot!B100="ha",dalolatnoma!A14:F14,dalolatnoma!A13:F13) -> Garov predmeti sifatida CHEVROLET COBALT, 3-tomonga egalik huquqi tegishli bo'lgan, quyidagi tafsilotlarga ega avtotransport vositasi taqdim etiladi:
A16: ="Garov predmeti sifatida "&umumiy_malumot!C133&", 2-tomonga egalik huquqi tegishli bo'lgan, quyidagi tafsilotlarga ega ko'chmas mulk taqdim etiladi:" -> Garov predmeti sifatida Yakka tartibdagi uy-joy, 2-tomonga egalik huquqi tegishli bo'lgan, quyidagi tafsilotlarga ega ko'chmas mulk taqdim etiladi:
A17: ="Garov predmeti sifatida "&umumiy_malumot!C133&", 3-tomonga egalik huquqi tegishli bo'lgan, quyidagi tafsilotlarga ega ko'chmas mulk taqdim etiladi:" -> Garov predmeti sifatida Yakka tartibdagi uy-joy, 3-tomonga egalik huquqi tegishli bo'lgan, quyidagi tafsilotlarga ega ko'chmas mulk taqdim etiladi:
A18: =IF(umumiy_malumot!B100="ha",dalolatnoma!A16:F16,dalolatnoma!A17:F17) -> Garov predmeti sifatida Yakka tartibdagi uy-joy, 3-tomonga egalik huquqi tegishli bo'lgan, quyidagi tafsilotlarga ega ko'chmas mulk taqdim etiladi:
A19: =IF(umumiy_malumot!B110="Avtotransport",dalolatnoma!A15:F15,dalolatnoma!A18:F18) -> Garov predmeti sifatida Yakka tartibdagi uy-joy, 3-tomonga egalik huquqi tegishli bo'lgan, quyidagi tafsilotlarga ega ko'chmas mulk taqdim etiladi:
A20: Nomi | B20: Umumiy yer maydoni, (m2) | D20: Qurilish osti maydoni, (m2) | E20: Umumiy foydali maydoni, (m2) | F20: Yashash maydoni, (m2)
A21: =IF(umumiy_malumot!B110=umumiy_malumot!C110,umumiy_malumot!B132,umumiy_malumot!C132) -> Yakka tartibdagi uy-joy | B21: =umumiy_malumot!C140 -> 700 | D21: =umumiy_malumot!C139 -> 340.11 | E21: =umumiy_malumot!C137 -> 163.19 | F21: =umumiy_malumot!C138 -> 114.59
A22: ="-* "&IF(umumiy_malumot!B110=umumiy_malumot!C110,"avtotransport "&"egasi: "&umumiy_malumot!B124&"","ko'chmas mulk"&" egasi: "&umumiy_malumot!B124&"") -> -* ko'chmas mulk egasi: NORINBAYEVA SAPURA MAMADALIYEVNA
A23: =IF(umumiy_malumot!B110=umumiy_malumot!C110,"-* texnik pasport: "&umumiy_malumot!B131&"","-* reest raqami: "&umumiy_malumot!C131&"") -> -* reest raqami: №1727256/Y-25006342
A24: =IF(umumiy_malumot!B110=umumiy_malumot!C110,"-* roʻyxatdan oʻtgan manzili/garaj manzili: "&umumiy_malumot!B129&"","-* kadastr raqami: "&umumiy_malumot!C134&"") -> -* kadastr raqami: 13.08.2025 y. №11:13:42:02:01:1840
A25: =IF(umumiy_malumot!B110=umumiy_malumot!C110,"-* davlat raqami: "&umumiy_malumot!B133&"","-* manzili: "&umumiy_malumot!C130&"") -> -* manzili: TOSHKENT VILOYATI CHINOZ TUMANI ALISHER NAVOIY MFY SOBIR RAHIMOV KO'CHASI 36 UY
A26: =IF(umumiy_malumot!B100="ha",dalolatnoma!A28:F28,dalolatnoma!A27:F27) -> Tomonlar o’rtasida o’tkazilgan muzokaralar natijalariga ko‘ra, 2-tomon ta’minot sifatida quyidagi tafsilotlarga ega bo’lgan garov predmetini taqdim etadi, 1-tomon esa ushbu garov predmetini 16 fevral 2026 y.dan № 110 mikrokredit shartnomasi bo‘yicha berilgan mikrokredit bo‘yicha 210 000 000,00 (ikki yuz o'n million so'm) so’m bo‘lgan kelishilgan garov qiymatida qabul qiladi::
A27: ="Tomonlar o’rtasida o’tkazilgan muzokaralar natijalariga ko‘ra, 2-tomon ta’minot sifatida quyidagi tafsilotlarga ega bo’lgan garov predmetini taqdim etadi, 1-tomon esa ushbu garov predmetini "&umumiy_malumot!B74&" "&umumiy_malumot!B65&" shartnomasi bo‘yicha berilgan "&umumiy_malumot!B65&" bo‘yicha "&FIXED(umumiy_malumot!B143,2)&" ("&umumiy_malumot!B144&") so’m bo‘lgan kelishilgan garov qiymatida qabul qiladi::" -> Tomonlar o’rtasida o’tkazilgan muzokaralar natijalariga ko‘ra, 2-tomon ta’minot sifatida quyidagi tafsilotlarga ega bo’lgan garov predmetini taqdim etadi, 1-tomon esa ushbu garov predmetini 16 fevral 2026 y.dan № 110 mikrokredit shartnomasi bo‘yicha berilgan mikrokredit bo‘yicha 210 000 000,00 (ikki yuz o'n million so'm) so’m bo‘lgan kelishilgan garov qiymatida qabul qiladi::
A28: ="Tomonlar o’rtasida o’tkazilgan muzokaralar natijalariga ko‘ra, 2-tomon ta’minot sifatida quyidagi tafsilotlarga ega bo’lgan garov predmetini taqdim etadi, 1-tomon esa ushbu garov predmetini "&umumiy_malumot!B74&" "&umumiy_malumot!C64&" shartnomasi bo‘yicha berilgan "&umumiy_malumot!B65&" bo‘yicha "&FIXED(umumiy_malumot!B143,2)&" ("&umumiy_malumot!B144&") so’m bo‘lgan kelishilgan garov qiymatida qabul qiladi::" -> Tomonlar o’rtasida o’tkazilgan muzokaralar natijalariga ko‘ra, 2-tomon ta’minot sifatida quyidagi tafsilotlarga ega bo’lgan garov predmetini taqdim etadi, 1-tomon esa ushbu garov predmetini 16 fevral 2026 y.dan № 110 Mikrokredit shartnomasi bo‘yicha berilgan mikrokredit bo‘yicha 210 000 000,00 (ikki yuz o'n million so'm) so’m bo‘lgan kelishilgan garov qiymatida qabul qiladi::
A29: Nomi | B29: =B20 -> Umumiy yer maydoni, (m2) | C29: =D20 -> Qurilish osti maydoni, (m2) | D29: =E20 -> Umumiy foydali maydoni, (m2) | E29: =F20 -> Yashash maydoni, (m2) | F29: Kelishilgan garov qiymati, so'm
A30: =A21 -> Yakka tartibdagi uy-joy | B30: =B21 -> 700 | C30: =D21 -> 340.11 | D30: =E21 -> 163.19 | E30: =F21 -> 114.59 | F30: =""&FIXED(umumiy_malumot!B143,2)&" ("&umumiy_malumot!B144&")" -> 210 000 000,00 (ikki yuz o'n million so'm)
A32: Наименование | C32: Полезная площадь | D32: Жилая площадь | E32: Общая площадь | F32: Согласованная залоговая стоимость, сум
A33: =#REF! -> #REF! | C33: =#REF! -> #REF! | D33: =#REF! -> #REF! | E33: =#REF! -> #REF! | F33: =""&FIXED(umumiy_malumot!C143,2)&" ("&umumiy_malumot!B144&")" -> 210 000 000,00 (ikki yuz o'n million so'm)
A35: =#REF! -> #REF! | C35: =#REF! -> #REF! | D35: =#REF! -> #REF! | E35: =#REF! -> #REF!
A36: =#REF! -> #REF! | C36: =#REF! -> #REF! | D36: =#REF! -> #REF! | E36: =#REF! -> #REF!
A37: =#REF! -> #REF! | C37: =#REF! -> #REF! | D37: =#REF! -> #REF! | E37: =#REF! -> #REF!
A38: =#REF! -> #REF! | C38: =#REF! -> #REF! | D38: =#REF! -> #REF! | E38: =#REF! -> #REF!
A39: =#REF! -> #REF! | C39: =#REF! -> #REF! | D39: =#REF! -> #REF! | E39: =#REF! -> #REF!
A40: =#REF! -> #REF! | C40: =#REF! -> #REF! | D40: =#REF! -> #REF! | E40: =#REF! -> #REF!
A41: =#REF! -> #REF! | C41: =#REF! -> #REF! | D41: =#REF! -> #REF! | E41: =#REF! -> #REF!
A42: =#REF! -> #REF! | C42: =#REF! -> #REF! | D42: =#REF! -> #REF! | E42: =#REF! -> #REF!
A43: =#REF! -> #REF! | C43: =#REF! -> #REF! | D43: =#REF! -> #REF! | E43: =#REF! -> #REF!
A44: =#REF! -> #REF! | C44: =#REF! -> #REF! | D44: =#REF! -> #REF! | E44: =#REF! -> #REF! | F44: =FIXED(umumiy_malumot!C143,2) -> 210 000 000,00
A46: ="“Birinchi talabga ko‘ra, yuqoridagi avtomobil Mikrokredit shartnomasi bo‘yicha garovga qo‘yilgan edi:: "&'Данные для послед. Залога'!W2&"" -> “Birinchi talabga ko‘ra, yuqoridagi avtomobil Mikrokredit shartnomasi bo‘yicha garovga qo‘yilgan edi:: - №5 от 11 yanvar 2021 г., заключенного с ООО «Clever Mikrokredit Tashkiloti» и TULYAGANOV XODJIAKBAR IRGASHEVICH, по согласованной залоговой стоимость - 15 000 000,00 (on besh million) сум. - №386 от 6 noyabr 2019 г., заключенного с ООО «Clever Mikrokredit Tashkiloti» и YUNUSOVA ZALOXAT MIRSULTANOVNA, по согласованной залоговой стоимость - 15 000 000,00 (on besh million) сум. - №33 от 21 yanvar 2021 г., заключенного с ООО «Clever Mikrokredit Tashkiloti» и YUNUSOVA ZALOXAT MIRSULTANOVNA, по согласованной залоговой стоимость - 15 000 000,00 (on besh million) сум. 0 0 0 0 0 0 0 0 0 0 0 0 0 0 0 0 0
A47: Shu bilan birga, garov predmetining kelishilgan garov qiymati deganda ushbu mulk garov sifatida taqdim etilgan/qabul qilingan qiymati tushuniladi.
A48: ="Shunday qilib, garov predmetining kelishilgan garov qiymati "&FIXED(umumiy_malumot!B143)&" ("&umumiy_malumot!B144&") so‘mni tashkil etadi." -> Shunday qilib, garov predmetining kelishilgan garov qiymati 210 000 000,00 (ikki yuz o'n million so'm) so‘mni tashkil etadi.
E49: =IF(umumiy_malumot!B99=umumiy_malumot!C99,umumiy_malumot!C143,IF(umumiy_malumot!B99=umumiy_malumot!D99,'Данные для послед. Залога'!M22,0)) -> 210000000 | F49: =IF(umumiy_malumot!B99=umumiy_malumot!C99,umumiy_malumot!B144,IF(umumiy_malumot!B99=umumiy_malumot!D99,'Данные для послед. Залога'!Q22,0)) -> ikki yuz o'n million so'm
A50: 1-tomondan:
A51: =umumiy_malumot!B159 -> «PULLOL BUSINESS MIKROMOLIYA TASHKILOTI» MChJ
A52: =""&umumiy_malumot!A161&"" -> Direktor | F52: =umumiy_malumot!B161 -> Obidov A.Sh.
A55: Начальник отдела кредитования
A56: =umumiy_malumot!B159 -> «PULLOL BUSINESS MIKROMOLIYA TASHKILOTI» MChJ | E56: ="_______________ "&umumiy_malumot!B170&"" -> _______________ Akramov R.N.
A58: 2-tomondan:
A59: O'zbekiston Respublikasi fuqarosi | E59: ="_____________ "&umumiy_malumot!B7&"" -> _____________ NORINBOYEVA S.I.
E60: =IF(umumiy_malumot!B100="да","",umumiy_malumot!B125) -> NORINBAYEVA S.M.
A61: =+IF(umumiy_malumot!B100="ha"," ","3-tomondan:") -> 3-tomondan: | G61: =IF(umumiy_malumot!B101=umumiy_malumot!D101,C7,"")
A62: =+IF(umumiy_malumot!B100="ha"," ","O'zbekiston Respublikasi fuqarosi") -> O'zbekiston Respublikasi fuqarosi | E62: ="_______________ "&umumiy_malumot!B113 -> _______________ NORINBAYEVA S.M.
A63: =+IF(umumiy_malumot!B100="ha"," ","O'zbekiston Respublikasi fuqarosi") -> O'zbekiston Respublikasi fuqarosi | E63: =+IF(umumiy_malumot!B100="ha"," ","_______________ "&umumiy_malumot!B113&"") -> _______________ NORINBAYEVA S.M.
C64: =garov_ariza!A20 -> № 00.01.1900sanasidan xususiy faoliyat ko'rsatuvchi notarius tomonidan berilgan ishonchnomaga asosan
A69: O'zbekiston Respublikasi fuqarosi

Sheet buyruq
A2: =""&umumiy_malumot!B158&" direktorining "&umumiy_malumot!B176&"dagi "&umumiy_malumot!B175&"-sonli buyrug‘i" -> «PULLOL BUSINESS MIKROMOLIYA TASHKILOTI» MChJ direktorining 16 fevral 2026 y.dagi № 110-sonli buyrug‘i
A6: ="Men, Obidov Abdullo Shokir o'g'li "&umumiy_malumot!B158&" direktori, jismoniy shaxs "&umumiy_malumot!B10&"ga quyidagi shartlarda "&umumiy_malumot!B65&" berishni buyuraman:" -> Men, Obidov Abdullo Shokir o'g'li «PULLOL BUSINESS MIKROMOLIYA TASHKILOTI» MChJ direktori, jismoniy shaxs NORINBOYEVA SOXIBA IZZATILLAYEVNAga quyidagi shartlarda mikrokredit berishni buyuraman:
A7: =kredit_ariza!A13:D13 -> Mikrokredit summasi: 175 000 000,00 (yuz yetmish besh million so'm) so'm.
A8: =kredit_ariza!A14:D14 -> Mikrokredit muddati: 36 (O'ttiz olti ) oy.
A9: =kredit_ariza!A15:D15 -> Mikrokreditdan foydalanganlik uchun foiz stavkasi: yillik 55% (Ellik besh ) foiz
A10: =kredit_ariza!A16:D16 -> Mikrokredit bo'yicha asosiy qarz va foizlarni to'lash:
A11: =kredit_ariza!A17:D17 -> - mikrokredit shartnomasi bo'yicha har oy differensial to'lovlari amalga oshiriladi
A12: =kredit_ariza!A19:D19 -> - mikrokredit shartnomasi bo'yicha har oy differensial to'lovlari amalga oshiriladi
A13: =IF(umumiy_malumot!B110="Avtotransport",buyruq!A12:F12,buyruq!A11:F11) -> - mikrokredit shartnomasi bo'yicha har oy differensial to'lovlari amalga oshiriladi
A14: =IF(umumiy_malumot!B110=umumiy_malumot!D110,""&umumiy_malumot!C124&"ga tegishli "&umumiy_malumot!C133&" ko'rinishidagi ko'chmas mulkni quyidagi ma'lumotlarga muvofiq garovga qabul qilinsin:",""&umumiy_malumot!B124&"ga tegishli "&umumiy_malumot!B132&" ko'rinishidagi transport vositasini quyidagi ma'lumotlarga muvofiq garovga qabul qilinsin:") -> NORINBAYEVA SAPURA MAMADALIYEVNAga tegishli Yakka tartibdagi uy-joy ko'rinishidagi ko'chmas mulkni quyidagi ma'lumotlarga muvofiq garovga qabul qilinsin:
A15: =""&umumiy_malumot!C124&"ga tegishli "&umumiy_malumot!C133&" ko'rinishidagi ko'chmas mulkni quyidagi ma'lumotlarga muvofiq garovga qabul qilinsin:" -> NORINBAYEVA SAPURA MAMADALIYEVNAga tegishli Yakka tartibdagi uy-joy ko'rinishidagi ko'chmas mulkni quyidagi ma'lumotlarga muvofiq garovga qabul qilinsin:
A16: =""&umumiy_malumot!B124&"ga tegishli "&umumiy_malumot!B132&" ko'rinishidagi transport vositasini quyidagi ma'lumotlarga muvofiq garovga qabul qilinsin:" -> NORINBAYEVA SAPURA MAMADALIYEVNAga tegishli CHEVROLET COBALT ko'rinishidagi transport vositasini quyidagi ma'lumotlarga muvofiq garovga qabul qilinsin:
A17: =dalolatnoma!A29 -> Nomi | B17: =dalolatnoma!B29 -> Umumiy yer maydoni, (m2) | C17: =dalolatnoma!C29 -> Qurilish osti maydoni, (m2) | D17: =dalolatnoma!D29 -> Umumiy foydali maydoni, (m2) | E17: =dalolatnoma!E29 -> Yashash maydoni, (m2) | F17: =dalolatnoma!F29 -> Kelishilgan garov qiymati, so'm
A18: =dalolatnoma!A30 -> Yakka tartibdagi uy-joy | B18: =dalolatnoma!B30 -> 700 | C18: =dalolatnoma!C30 -> 340.11 | D18: =dalolatnoma!D30 -> 163.19 | E18: =dalolatnoma!E30 -> 114.59 | F18: =dalolatnoma!F30 -> 210 000 000,00 (ikki yuz o'n million so'm)
A19: =dalolatnoma!A22:F22 -> -* ko'chmas mulk egasi: NORINBAYEVA SAPURA MAMADALIYEVNA
A20: =dalolatnoma!A23:F23 -> -* reest raqami: №1727256/Y-25006342
A21: =dalolatnoma!A24:F24 -> -* kadastr raqami: 13.08.2025 y. №11:13:42:02:01:1840
A22: =dalolatnoma!A25:F25 -> -* manzili: TOSHKENT VILOYATI CHINOZ TUMANI ALISHER NAVOIY MFY SOBIR RAHIMOV KO'CHASI 36 UY
A23: =" «"&umumiy_malumot!B154&"» АJ sug‘urta kompaniyasi bilan "&umumiy_malumot!C64&" to'lamaslik xavfini "&FIXED(umumiy_malumot!B155,2)&"("&umumiy_malumot!B156&") so'm miqdoriga sug’urta qilish shartnomasi tuzilsin" -> «АО СК "IMPEX INSURANCE"» АJ sug‘urta kompaniyasi bilan Mikrokredit to'lamaslik xavfini 35 000 000,00(o'ttiz besh million so'm) so'm miqdoriga sug’urta qilish shartnomasi tuzilsin
A27: «PULLOL BUSINESS MIKROMOLIYA TASHKILOTI» MChJ direktori | E27: A.Obidov

Sheet График дифференц
E1: Приложение №1
F2: ="к договору микрозайма "&umumiy_malumot!B74&"" -> к договору микрозайма 16 fevral 2026 y.dan № 110
A4: График погашения
L5: =umumiy_malumot!B82 -> 36
A6: № | B6: Дата погашения | C6: Остаток основного долга | D6: Сумма погашения, сум
D7: основного долга | E7: процентов* | F7: всего*
A8: 1 | B8: =umumiy_malumot!B80 -> 46091 | C8: =umumiy_malumot!B76 -> 175000000 | D8: =IF(IF(C8=0,L8,IF(C8>1,I8))="",0,(IF(C8=0,L8,IF(C8>1,I8)))) -> 4861111.1 | E8: =IF(C8=0,N6,IF(C8>1,L8)) -> 5801369.9 | F8: =IF(C8=0,O6,IF(C8>1,M8)) -> 10662481 | G8: =B8-umumiy_malumot!B67 -> 22 | H8: =DATE(YEAR(B8),12,31)-DATE(YEAR(B8),1,1)+1 -> 365 | I8: =IF(umumiy_malumot!B84=0,ROUND(C8/L5,2),"") -> 4861111.1 | L8: =ROUND(C8*umumiy_malumot!$B$85/H8,2)*G8 -> 5801369.9 | M8: =D8+E8 -> 10662481 | O8: =TEXT(B8,"ддд") -> Вт | P8: =IF(O8=$U$8,2,IF(O8=$V$8,1,0)) -> 0 | Q8: =DAY(umumiy_malumot!$B$79)+P8 -> 10 | S8: Чт | T8: Пт | U8: Сб | V8: Вс
A9: 2 | B9: =IF(A9<=umumiy_malumot!$B$82,DATE(YEAR(R9),MONTH(R9),DAY(IF(A9=umumiy_malumot!$B$82,umumiy_malumot!$B$67,IF(A9<umumiy_malumot!$B$82,(Q9),IF(A9>umumiy_malumot!$B$82,$H$56,0)))))) -> 46122 | C9: =C8-D8 -> 1.7013889e+08 | D9: =IF(C9=0,L9,IF(C9>1,I9)) -> 4861111.1 | E9: =IF(C9=0,N8,IF(C9>1,L9)) -> 7947583.8 | F9: =IF(C9=0,N8,IF(C9>1,M9)) -> 12808695 | G9: =B9-B8 -> 31 | H9: =DATE(YEAR(B9),12,31)-DATE(YEAR(B9),1,1)+1 -> 365 | I9: =IF(I8="",ROUND(C8/(L5-1),2),I8) -> 4861111.1 | L9: =ROUND(C9*umumiy_malumot!$B$85/H9,2)*G9 -> 7947583.8 | M9: =D9+E9 -> 12808695 | O9: =TEXT(R9,"ддд") -> Пт | P9: =IF(O9=$U$8,2,IF(O9=$V$8,1,0)) -> 0 | Q9: =DAY(umumiy_malumot!$B$79)+P9 -> 10 | R9: =IF(A9<=umumiy_malumot!$B$82,DATE(YEAR($B$8),MONTH($B$8)+A8,DAY(umumiy_malumot!$B$79)),0) -> 46122
A10: 3 | B10: =IF(A10<=umumiy_malumot!$B$82,DATE(YEAR(R10),MONTH(R10),DAY(IF(A10=umumiy_malumot!$B$82,umumiy_malumot!$B$67,IF(A10<umumiy_malumot!$B$82,(Q10),IF(A10>umumiy_malumot!$B$82,$H$56,0)))))) -> 46153 | C10: =C9-D9 -> 1.6527778e+08 | D10: =IF(C10=0,L10,IF(C10>1,I10)) -> 4861111.1 | E10: =IF(C10=0,N9,IF(C10>1,L10)) -> 7720510 | F10: =IF(C10=0,N9,IF(C10>1,M10)) -> 12581621 | G10: =B10-B9 -> 31 | H10: =DATE(YEAR(B10),12,31)-DATE(YEAR(B10),1,1)+1 -> 365 | I10: =I9 -> 4861111.1 | L10: =ROUND(C10*umumiy_malumot!$B$85/H10,2)*G10 -> 7720510 | M10: =D10+E10 -> 12581621 | O10: =TEXT(R10,"ддд") -> Вс | P10: =IF(O10=$U$8,2,IF(O10=$V$8,1,0)) -> 1 | Q10: =DAY(umumiy_malumot!$B$79)+P10 -> 11 | R10: =IF(A10<=umumiy_malumot!$B$82,DATE(YEAR($B$8),MONTH($B$8)+A9,DAY(umumiy_malumot!$B$79)),0) -> 46152
A11: 4 | B11: =IF(A11<=umumiy_malumot!$B$82,DATE(YEAR(R11),MONTH(R11),DAY(IF(A11=umumiy_malumot!$B$82,umumiy_malumot!$B$67,IF(A11<umumiy_malumot!$B$82,(Q11),IF(A11>umumiy_malumot!$B$82,$H$56,0)))))) -> 46183 | C11: =C10-D10 -> 1.6041667e+08 | D11: =IF(C11=0,L11,IF(C11>1,I11)) -> 4861111.1 | E11: =IF(C11=0,N10,IF(C11>1,L11)) -> 7251712.2 | F11: =IF(C11=0,N10,IF(C11>1,M11)) -> 12112823 | G11: =B11-B10 -> 30 | H11: =DATE(YEAR(B11),12,31)-DATE(YEAR(B11),1,1)+1 -> 365 | I11: =I10 -> 4861111.1 | L11: =ROUND(C11*umumiy_malumot!$B$85/H11,2)*G11 -> 7251712.2 | M11: =D11+E11 -> 12112823 | O11: =TEXT(R11,"ддд") -> Ср | P11: =IF(O11=$U$8,2,IF(O11=$V$8,1,0)) -> 0 | Q11: =DAY(umumiy_malumot!$B$79)+P11 -> 10 | R11: =IF(A11<=umumiy_malumot!$B$82,DATE(YEAR($B$8),MONTH($B$8)+A10,DAY(umumiy_malumot!$B$79)),0) -> 46183
A12: 5 | B12: =IF(A12<=umumiy_malumot!$B$82,DATE(YEAR(R12),MONTH(R12),DAY(IF(A12=umumiy_malumot!$B$82,umumiy_malumot!$B$67,IF(A12<umumiy_malumot!$B$82,(Q12),IF(A12>umumiy_malumot!$B$82,$H$56,0)))))) -> 46213 | C12: =C11-D11 -> 1.5555556e+08 | D12: =IF(C12=0,L12,IF(C12>1,I12)) -> 4861111.1 | E12: =IF(C12=0,N11,IF(C12>1,L12)) -> 7031963.4 | F12: =IF(C12=0,N11,IF(C12>1,M12)) -> 11893075 | G12: =B12-B11 -> 30 | H12: =DATE(YEAR(B12),12,31)-DATE(YEAR(B12),1,1)+1 -> 365 | I12: =I11 -> 4861111.1 | J12: =umumiy_malumot!B76 -> 175000000 | L12: =ROUND(C12*umumiy_malumot!$B$85/H12,2)*G12 -> 7031963.4 | M12: =D12+E12 -> 11893075 | O12: =TEXT(R12,"ддд") -> Пт | P12: =IF(O12=$U$8,2,IF(O12=$V$8,1,0)) -> 0 | Q12: =DAY(umumiy_malumot!$B$79)+P12 -> 10 | R12: =IF(A12<=umumiy_malumot!$B$82,DATE(YEAR($B$8),MONTH($B$8)+A11,DAY(umumiy_malumot!$B$79)),0) -> 46213
A13: 6 | B13: =IF(A13<=umumiy_malumot!$B$82,DATE(YEAR(R13),MONTH(R13),DAY(IF(A13=umumiy_malumot!$B$82,umumiy_malumot!$B$67,IF(A13<umumiy_malumot!$B$82,(Q13),IF(A13>umumiy_malumot!$B$82,$H$56,0)))))) -> 46244 | C13: =C12-D12 -> 1.5069444e+08 | D13: =IF(C13=0,L13,IF(C13>1,I13)) -> 4861111.1 | E13: =IF(C13=0,N12,IF(C13>1,L13)) -> 7039288.4 | F13: =IF(C13=0,N12,IF(C13>1,M13)) -> 11900400 | G13: =B13-B12 -> 31 | H13: =DATE(YEAR(B13),12,31)-DATE(YEAR(B13),1,1)+1 -> 365 | I13: =IF(L5=H1,K13,IF(L5>H1,I12)) -> 4861111.1 | J13: =SUM($I$8:I12) -> 24305556 | K13: =$J$12-J13 -> 1.5069444e+08 | L13: =ROUND(C13*umumiy_malumot!$B$85/H13,2)*G13 -> 7039288.4 | M13: =D13+E13 -> 11900400 | O13: =TEXT(R13,"ддд") -> Пн | P13: =IF(O13=$U$8,2,IF(O13=$V$8,1,0)) -> 0 | Q13: =DAY(umumiy_malumot!$B$79)+P13 -> 10 | R13: =IF(A13<=umumiy_malumot!$B$82,DATE(YEAR($B$8),MONTH($B$8)+A12,DAY(umumiy_malumot!$B$79)),0) -> 46244
A14: 7 | B14: =IF(A14<=umumiy_malumot!$B$82,DATE(YEAR(R14),MONTH(R14),DAY(IF(A14=umumiy_malumot!$B$82,umumiy_malumot!$B$67,IF(A14<umumiy_malumot!$B$82,(Q14),IF(A14>umumiy_malumot!$B$82,$H$56,0)))))) -> 46275 | C14: =C13-D13 -> 1.4583333e+08 | D14: =IF(C14=0,L14,IF(C14>1,I14)) -> 4861111.1 | E14: =IF(C14=0,N13,IF(C14>1,L14)) -> 6812214.7 | F14: =IF(C14=0,N13,IF(C14>1,M14)) -> 11673326 | G14: =B14-B13 -> 31 | H14: =DATE(YEAR(B14),12,31)-DATE(YEAR(B14),1,1)+1 -> 365 | I14: =IF($L$5=A14,K14,IF($L$5>A14,I13)) -> 4861111.1 | J14: =SUM($I$8:I13) -> 29166667 | K14: =$J$12-J14 -> 1.4583333e+08 | L14: =ROUND(C14*umumiy_malumot!$B$85/H14,2)*G14 -> 6812214.7 | M14: =D14+E14 -> 11673326 | O14: =TEXT(R14,"ддд") -> Чт | P14: =IF(O14=$U$8,2,IF(O14=$V$8,1,0)) -> 0 | Q14: =DAY(umumiy_malumot!$B$79)+P14 -> 10 | R14: =IF(A14<=umumiy_malumot!$B$82,DATE(YEAR($B$8),MONTH($B$8)+A13,DAY(umumiy_malumot!$B$79)),0) -> 46275
A15: 8 | B15: =IF(A15<=umumiy_malumot!$B$82,DATE(YEAR(R15),MONTH(R15),DAY(IF(A15=umumiy_malumot!$B$82,umumiy_malumot!$B$67,IF(A15<umumiy_malumot!$B$82,(Q15),IF(A15>umumiy_malumot!$B$82,$H$56,0)))))) -> 46307 | C15: =C14-D14 -> 1.4097222e+08 | D15: =IF(C15=0,L15,IF(C15>1,I15)) -> 4861111.1 | E15: =IF(C15=0,N14,IF(C15>1,L15)) -> 6797564.8 | F15: =IF(C15=0,N14,IF(C15>1,M15)) -> 11658676 | G15: =B15-B14 -> 32 | H15: =DATE(YEAR(B15),12,31)-DATE(YEAR(B15),1,1)+1 -> 365 | I15: =IF($L$5=A15,K15,IF($L$5>A15,I14)) -> 4861111.1 | J15: =SUM($I$8:I14) -> 34027778 | K15: =$J$12-J15 -> 1.4097222e+08 | L15: =ROUND(C15*umumiy_malumot!$B$85/H15,2)*G15 -> 6797564.8 | M15: =D15+E15 -> 11658676 | O15: =TEXT(R15,"ддд") -> Сб | P15: =IF(O15=$U$8,2,IF(O15=$V$8,1,0)) -> 2 | Q15: =DAY(umumiy_malumot!$B$79)+P15 -> 12 | R15: =IF(A15<=umumiy_malumot!$B$82,DATE(YEAR($B$8),MONTH($B$8)+A14,DAY(umumiy_malumot!$B$79)),0) -> 46305
A16: 9 | B16: =IF(A16<=umumiy_malumot!$B$82,DATE(YEAR(R16),MONTH(R16),DAY(IF(A16=umumiy_malumot!$B$82,umumiy_malumot!$B$67,IF(A16<umumiy_malumot!$B$82,(Q16),IF(A16>umumiy_malumot!$B$82,$H$56,0)))))) -> 46336 | C16: =C15-D15 -> 1.3611111e+08 | D16: =IF(C16=0,L16,IF(C16>1,I16)) -> 4861111.1 | E16: =IF(C16=0,N15,IF(C16>1,L16)) -> 5947869 | F16: =IF(C16=0,N15,IF(C16>1,M16)) -> 10808980 | G16: =B16-B15 -> 29 | H16: =DATE(YEAR(B16),12,31)-DATE(YEAR(B16),1,1)+1 -> 365 | I16: =IF($L$5=A16,K16,IF($L$5>A16,I15)) -> 4861111.1 | J16: =SUM($I$8:I15) -> 38888889 | K16: =$J$12-J16 -> 1.3611111e+08 | L16: =ROUND(C16*umumiy_malumot!$B$85/H16,2)*G16 -> 5947869 | M16: =D16+E16 -> 10808980 | O16: =TEXT(R16,"ддд") -> Вт | P16: =IF(O16=$U$8,2,IF(O16=$V$8,1,0)) -> 0 | Q16: =DAY(umumiy_malumot!$B$79)+P16 -> 10 | R16: =IF(A16<=umumiy_malumot!$B$82,DATE(YEAR($B$8),MONTH($B$8)+A15,DAY(umumiy_malumot!$B$79)),0) -> 46336
A17: 10 | B17: =IF(A17<=umumiy_malumot!$B$82,DATE(YEAR(R17),MONTH(R17),DAY(IF(A17=umumiy_malumot!$B$82,umumiy_malumot!$B$67,IF(A17<umumiy_malumot!$B$82,(Q17),IF(A17>umumiy_malumot!$B$82,$H$56,0)))))) -> 46366 | C17: =C16-D16 -> 1.3125e+08 | D17: =IF(C17=0,L17,IF(C17>1,I17)) -> 4861111.1 | E17: =IF(C17=0,N16,IF(C17>1,L17)) -> 5933219.1 | F17: =IF(C17=0,N16,IF(C17>1,M17)) -> 10794330 | G17: =B17-B16 -> 30 | H17: =DATE(YEAR(B17),12,31)-DATE(YEAR(B17),1,1)+1 -> 365 | I17: =IF($L$5=A17,K17,IF($L$5>A17,I16)) -> 4861111.1 | J17: =SUM($I$8:I16) -> 43750000 | K17: =$J$12-J17 -> 1.3125e+08 | L17: =ROUND(C17*umumiy_malumot!$B$85/H17,2)*G17 -> 5933219.1 | M17: =D17+E17 -> 10794330 | O17: =TEXT(R17,"ддд") -> Чт | P17: =IF(O17=$U$8,2,IF(O17=$V$8,1,0)) -> 0 | Q17: =DAY(umumiy_malumot!$B$79)+P17 -> 10 | R17: =IF(A17<=umumiy_malumot!$B$82,DATE(YEAR($B$8),MONTH($B$8)+A16,DAY(umumiy_malumot!$B$79)),0) -> 46366
A18: 11 | B18: =IF(A18<=umumiy_malumot!$B$82,DATE(YEAR(R18),MONTH(R18),DAY(IF(A18=umumiy_malumot!$B$82,umumiy_malumot!$B$67,IF(A18<umumiy_malumot!$B$82,(Q18),IF(A18>umumiy_malumot!$B$82,$H$56,0)))))) -> 46398 | C18: =C17-D17 -> 1.2638889e+08 | D18: =IF(C18=0,L18,IF(C18>1,I18)) -> 4861111.1 | E18: =IF(C18=0,N17,IF(C18>1,L18)) -> 6094368.3 | F18: =IF(C18=0,N17,IF(C18>1,M18)) -> 10955479 | G18: =B18-B17 -> 32 | H18: =DATE(YEAR(B18),12,31)-DATE(YEAR(B18),1,1)+1 -> 365 | I18: =IF($L$5=A18,K18,IF($L$5>A18,I17)) -> 4861111.1 | J18: =SUM($I$8:I17) -> 48611111 | K18: =$J$12-J18 -> 1.2638889e+08 | L18: =ROUND(C18*umumiy_malumot!$B$85/H18,2)*G18 -> 6094368.3 | M18: =D18+E18 -> 10955479 | O18: =TEXT(R18,"ддд") -> Вс | P18: =IF(O18=$U$8,2,IF(O18=$V$8,1,0)) -> 1 | Q18: =DAY(umumiy_malumot!$B$79)+P18 -> 11 | R18: =IF(A18<=umumiy_malumot!$B$82,DATE(YEAR($B$8),MONTH($B$8)+A17,DAY(umumiy_malumot!$B$79)),0) -> 46397
A19: 12 | B19: =IF(A19<=umumiy_malumot!$B$82,DATE(YEAR(R19),MONTH(R19),DAY(IF(A19=umumiy_malumot!$B$82,umumiy_malumot!$B$67,IF(A19<umumiy_malumot!$B$82,(Q19),IF(A19>umumiy_malumot!$B$82,$H$56,0)))))) -> 46428 | C19: =C18-D18 -> 1.2152778e+08 | D19: =IF(C19=0,L19,IF(C19>1,I19)) -> 4861111.1 | E19: =IF(C19=0,N18,IF(C19>1,L19)) -> 5493721.5 | F19: =IF(C19=0,N18,IF(C19>1,M19)) -> 10354833 | G19: =B19-B18 -> 30 | H19: =DATE(YEAR(B19),12,31)-DATE(YEAR(B19),1,1)+1 -> 365 | I19: =IF($L$5=A19,K19,IF($L$5>A19,I18)) -> 4861111.1 | J19: =SUM($I$8:I18) -> 53472222 | K19: =$J$12-J19 -> 1.2152778e+08 | L19: =ROUND(C19*umumiy_malumot!$B$85/H19,2)*G19 -> 5493721.5 | M19: =D19+E19 -> 10354833 | O19: =TEXT(R19,"ддд") -> Ср | P19: =IF(O19=$U$8,2,IF(O19=$V$8,1,0)) -> 0 | Q19: =DAY(umumiy_malumot!$B$79)+P19 -> 10 | R19: =IF(A19<=umumiy_malumot!$B$82,DATE(YEAR($B$8),MONTH($B$8)+A18,DAY(umumiy_malumot!$B$79)),0) -> 46428
A20: 13 | B20: =IF(A20<=umumiy_malumot!$B$82,DATE(YEAR(R20),MONTH(R20),DAY(IF(A20=umumiy_malumot!$B$82,umumiy_malumot!$B$67,IF(A20<umumiy_malumot!$B$82,(Q20),IF(A20>umumiy_malumot!$B$82,$H$56,0)))))) -> 46456 | C20: =C19-D19 -> 1.1666667e+08 | D20: =IF(C20=0,L20,IF(C20>1,I20)) -> 4861111.1 | E20: =IF(C20=0,N19,IF(C20>1,L20)) -> 4922374.5 | F20: =IF(C20=0,N19,IF(C20>1,M20)) -> 9783485.6 | G20: =B20-B19 -> 28 | H20: =DATE(YEAR(B20),12,31)-DATE(YEAR(B20),1,1)+1 -> 365 | I20: =IF($L$5=A20,K20,IF($L$5>A20,I19)) -> 4861111.1 | J20: =SUM($I$8:I19) -> 58333333 | K20: =$J$12-J20 -> 1.1666667e+08 | L20: =ROUND(C20*umumiy_malumot!$B$85/H20,2)*G20 -> 4922374.5 | M20: =D20+E20 -> 9783485.6 | O20: =TEXT(R20,"ддд") -> Ср | P20: =IF(O20=$U$8,2,IF(O20=$V$8,1,0)) -> 0 | Q20: =DAY(umumiy_malumot!$B$79)+P20 -> 10 | R20: =IF(A20<=umumiy_malumot!$B$82,DATE(YEAR($B$8),MONTH($B$8)+A19,DAY(umumiy_malumot!$B$79)),0) -> 46456
A21: 14 | B21: =IF(A21<=umumiy_malumot!$B$82,DATE(YEAR(R21),MONTH(R21),DAY(IF(A21=umumiy_malumot!$B$82,umumiy_malumot!$B$67,IF(A21<umumiy_malumot!$B$82,(Q21),IF(A21>umumiy_malumot!$B$82,$H$56,0)))))) -> 46489 | C21: =C20-D20 -> 1.1180556e+08 | D21: =IF(C21=0,L21,IF(C21>1,I21)) -> 4861111.1 | E21: =IF(C21=0,N20,IF(C21>1,L21)) -> 5559646 | F21: =IF(C21=0,N20,IF(C21>1,M21)) -> 10420757 | G21: =B21-B20 -> 33 | H21: =DATE(YEAR(B21),12,31)-DATE(YEAR(B21),1,1)+1 -> 365 | I21: =IF($L$5=A21,K21,IF($L$5>A21,I20)) -> 4861111.1 | J21: =SUM($I$8:I20) -> 63194444 | K21: =$J$12-J21 -> 1.1180556e+08 | L21: =ROUND(C21*umumiy_malumot!$B$85/H21,2)*G21 -> 5559646 | M21: =D21+E21 -> 10420757 | O21: =TEXT(R21,"ддд") -> Сб | P21: =IF(O21=$U$8,2,IF(O21=$V$8,1,0)) -> 2 | Q21: =DAY(umumiy_malumot!$B$79)+P21 -> 12 | R21: =IF(A21<=umumiy_malumot!$B$82,DATE(YEAR($B$8),MONTH($B$8)+A20,DAY(umumiy_malumot!$B$79)),0) -> 46487
A22: 15 | B22: =IF(A22<=umumiy_malumot!$B$82,DATE(YEAR(R22),MONTH(R22),DAY(IF(A22=umumiy_malumot!$B$82,umumiy_malumot!$B$67,IF(A22<umumiy_malumot!$B$82,(Q22),IF(A22>umumiy_malumot!$B$82,$H$56,0)))))) -> 46517 | C22: =C21-D21 -> 1.0694444e+08 | D22: =IF(C22=0,L22,IF(C22>1,I22)) -> 4861111.1 | E22: =IF(C22=0,N21,IF(C22>1,L22)) -> 4512176.5 | F22: =IF(C22=0,N21,IF(C22>1,M22)) -> 9373287.6 | G22: =B22-B21 -> 28 | H22: =DATE(YEAR(B22),12,31)-DATE(YEAR(B22),1,1)+1 -> 365 | I22: =IF($L$5=A22,K22,IF($L$5>A22,I21)) -> 4861111.1 | J22: =SUM($I$8:I21) -> 68055556 | K22: =$J$12-J22 -> 1.0694444e+08 | L22: =ROUND(C22*umumiy_malumot!$B$85/H22,2)*G22 -> 4512176.5 | M22: =D22+E22 -> 9373287.6 | O22: =TEXT(R22,"ддд") -> Пн | P22: =IF(O22=$U$8,2,IF(O22=$V$8,1,0)) -> 0 | Q22: =DAY(umumiy_malumot!$B$79)+P22 -> 10 | R22: =IF(A22<=umumiy_malumot!$B$82,DATE(YEAR($B$8),MONTH($B$8)+A21,DAY(umumiy_malumot!$B$79)),0) -> 46517
A23: 16 | B23: =IF(A23<=umumiy_malumot!$B$82,DATE(YEAR(R23),MONTH(R23),DAY(IF(A23=umumiy_malumot!$B$82,umumiy_malumot!$B$67,IF(A23<umumiy_malumot!$B$82,(Q23),IF(A23>umumiy_malumot!$B$82,$H$56,0)))))) -> 46548 | C23: =C22-D22 -> 1.0208333e+08 | D23: =IF(C23=0,L23,IF(C23>1,I23)) -> 4861111.1 | E23: =IF(C23=0,N22,IF(C23>1,L23)) -> 4768550.2 | F23: =IF(C23=0,N22,IF(C23>1,M23)) -> 9629661.3 | G23: =B23-B22 -> 31 | H23: =DATE(YEAR(B23),12,31)-DATE(YEAR(B23),1,1)+1 -> 365 | I23: =IF($L$5=A23,K23,IF($L$5>A23,I22)) -> 4861111.1 | J23: =SUM($I$8:I22) -> 72916667 | K23: =$J$12-J23 -> 1.0208333e+08 | L23: =ROUND(C23*umumiy_malumot!$B$85/H23,2)*G23 -> 4768550.2 | M23: =D23+E23 -> 9629661.3 | O23: =TEXT(R23,"ддд") -> Чт | P23: =IF(O23=$U$8,2,IF(O23=$V$8,1,0)) -> 0 | Q23: =DAY(umumiy_malumot!$B$79)+P23 -> 10 | R23: =IF(A23<=umumiy_malumot!$B$82,DATE(YEAR($B$8),MONTH($B$8)+A22,DAY(umumiy_malumot!$B$79)),0) -> 46548
A24: 17 | B24: =IF(A24<=umumiy_malumot!$B$82,DATE(YEAR(R24),MONTH(R24),DAY(IF(A24=umumiy_malumot!$B$82,umumiy_malumot!$B$67,IF(A24<umumiy_malumot!$B$82,(Q24),IF(A24>umumiy_malumot!$B$82,$H$56,0)))))) -> 46580 | C24: =C23-D23 -> 97222222 | D24: =IF(C24=0,L24,IF(C24>1,I24)) -> 4861111.1 | E24: =IF(C24=0,N23,IF(C24>1,L24)) -> 4687975.7 | F24: =IF(C24=0,N23,IF(C24>1,M24)) -> 9549086.8 | G24: =B24-B23 -> 32 | H24: =DATE(YEAR(B24),12,31)-DATE(YEAR(B24),1,1)+1 -> 365 | I24: =IF($L$5=A24,K24,IF($L$5>A24,I23)) -> 4861111.1 | J24: =SUM($I$8:I23) -> 77777778 | K24: =$J$12-J24 -> 97222222 | L24: =ROUND(C24*umumiy_malumot!$B$85/H24,2)*G24 -> 4687975.7 | M24: =D24+E24 -> 9549086.8 | O24: =TEXT(R24,"ддд") -> Сб | P24: =IF(O24=$U$8,2,IF(O24=$V$8,1,0)) -> 2 | Q24: =DAY(umumiy_malumot!$B$79)+P24 -> 12 | R24: =IF(A24<=umumiy_malumot!$B$82,DATE(YEAR($B$8),MONTH($B$8)+A23,DAY(umumiy_malumot!$B$79)),0) -> 46578
A25: 18 | B25: =IF(A25<=umumiy_malumot!$B$82,DATE(YEAR(R25),MONTH(R25),DAY(IF(A25=umumiy_malumot!$B$82,umumiy_malumot!$B$67,IF(A25<umumiy_malumot!$B$82,(Q25),IF(A25>umumiy_malumot!$B$82,$H$56,0)))))) -> 46609 | C25: =C24-D24 -> 92361111 | D25: =IF(C25=0,L25,IF(C25>1,I25)) -> 4861111.1 | E25: =IF(C25=0,N24,IF(C25>1,L25)) -> 4036054.1 | F25: =IF(C25=0,N24,IF(C25>1,M25)) -> 8897165.2 | G25: =B25-B24 -> 29 | H25: =DATE(YEAR(B25),12,31)-DATE(YEAR(B25),1,1)+1 -> 365 | I25: =IF($L$5=A25,K25,IF($L$5>A25,I24)) -> 4861111.1 | J25: =SUM($I$8:I24) -> 82638889 | K25: =$J$12-J25 -> 92361111 | L25: =ROUND(C25*umumiy_malumot!$B$85/H25,2)*G25 -> 4036054.1 | M25: =D25+E25 -> 8897165.2 | O25: =TEXT(R25,"ддд") -> Вт | P25: =IF(O25=$U$8,2,IF(O25=$V$8,1,0)) -> 0 | Q25: =DAY(umumiy_malumot!$B$79)+P25 -> 10 | R25: =IF(A25<=umumiy_malumot!$B$82,DATE(YEAR($B$8),MONTH($B$8)+A24,DAY(umumiy_malumot!$B$79)),0) -> 46609
... A31: 24 | B31: =IF(A31<=umumiy_malumot!$B$82,DATE(YEAR(R31),MONTH(R31),DAY(IF(A31=umumiy_malumot!$B$82,umumiy_malumot!$B$67,IF(A31<umumiy_malumot!$B$82,(Q31),IF(A31>umumiy_malumot!$B$82,$H$56,0)))))) -> 46793 | C31: =C30-D30 -> 63194444 | D31: =IF(C31=0,L31,IF(C31>1,I31)) -> 4861111.1 | E31: =IF(C31=0,N30,IF(C31>1,L31)) -> 2943894.2 | F31: =IF(C31=0,N30,IF(C31>1,M31)) -> 7805005.3 | G31: =B31-B30 -> 31 | H31: =DATE(YEAR(B31),12,31)-DATE(YEAR(B31),1,1)+1 -> 366 | I31: =IF($L$5=A31,K31,IF($L$5>A31,I30)) -> 4861111.1 | J31: =SUM($I$8:I30) -> 1.1180556e+08 | K31: =$J$12-J31 -> 63194444 | L31: =ROUND(C31*umumiy_malumot!$B$85/H31,2)*G31 -> 2943894.2 | M31: =D31+E31 -> 7805005.3 | O31: =TEXT(R31,"ддд") -> Чт | P31: =IF(O31=$U$8,2,IF(O31=$V$8,1,0)) -> 0 | Q31: =DAY(umumiy_malumot!$B$79)+P31 -> 10 | R31: =IF(A31<=umumiy_malumot!$B$82,DATE(YEAR($B$8),MONTH($B$8)+A30,DAY(umumiy_malumot!$B$79)),0) -> 46793
A32: =1+A31 -> 25 | B32: =IF(A32<=umumiy_malumot!$B$82,DATE(YEAR(R32),MONTH(R32),DAY(IF(A32=umumiy_malumot!$B$82,umumiy_malumot!$B$67,IF(A32<umumiy_malumot!$B$82,(Q32),IF(A32>umumiy_malumot!$B$82,$H$56,0)))))) -> 46822 | C32: =C31-D31 -> 58333333 | D32: =IF(C32=0,L32,IF(C32>1,I32)) -> 4861111.1 | E32: =IF(C32=0,N31,IF(C32>1,L32)) -> 2542122 | F32: =IF(C32=0,N31,IF(C32>1,M32)) -> 7403233.1 | G32: =B32-B31 -> 29 | H32: =DATE(YEAR(B32),12,31)-DATE(YEAR(B32),1,1)+1 -> 366 | I32: =IF($L$5=A32,K32,IF($L$5>A32,I31)) -> 4861111.1 | J32: =SUM($I$8:I31) -> 1.1666667e+08 | K32: =$J$12-J32 -> 58333333 | L32: =ROUND(C32*umumiy_malumot!$B$85/H32,2)*G32 -> 2542122 | M32: =D32+E32 -> 7403233.1 | O32: =TEXT(R32,"ддд") -> Пт | P32: =IF(O32=$U$8,2,IF(O32=$V$8,1,0)) -> 0 | Q32: =DAY(umumiy_malumot!$B$79)+P32 -> 10 | R32: =IF(A32<=umumiy_malumot!$B$82,DATE(YEAR($B$8),MONTH($B$8)+A31,DAY(umumiy_malumot!$B$79)),0) -> 46822
A33: =1+A32 -> 26 | B33: =IF(A33<=umumiy_malumot!$B$82,DATE(YEAR(R33),MONTH(R33),DAY(IF(A33=umumiy_malumot!$B$82,umumiy_malumot!$B$67,IF(A33<umumiy_malumot!$B$82,(Q33),IF(A33>umumiy_malumot!$B$82,$H$56,0)))))) -> 46853 | C33: =C32-D32 -> 53472222 | D33: =IF(C33=0,L33,IF(C33>1,I33)) -> 4861111.1 | E33: =IF(C33=0,N32,IF(C33>1,L33)) -> 2490987.3 | F33: =IF(C33=0,N32,IF(C33>1,M33)) -> 7352098.4 | G33: =B33-B32 -> 31 | H33: =DATE(YEAR(B33),12,31)-DATE(YEAR(B33),1,1)+1 -> 366 | I33: =IF($L$5=A33,K33,IF($L$5>A33,I32)) -> 4861111.1 | J33: =SUM($I$8:I32) -> 1.2152778e+08 | K33: =$J$12-J33 -> 53472222 | L33: =ROUND(C33*umumiy_malumot!$B$85/H33,2)*G33 -> 2490987.3 | M33: =D33+E33 -> 7352098.4 | O33: =TEXT(R33,"ддд") -> Пн | P33: =IF(O33=$U$8,2,IF(O33=$V$8,1,0)) -> 0 | Q33: =DAY(umumiy_malumot!$B$79)+P33 -> 10 | R33: =IF(A33<=umumiy_malumot!$B$82,DATE(YEAR($B$8),MONTH($B$8)+A32,DAY(umumiy_malumot!$B$79)),0) -> 46853
A34: =1+A33 -> 27 | B34: =IF(A34<=umumiy_malumot!$B$82,DATE(YEAR(R34),MONTH(R34),DAY(IF(A34=umumiy_malumot!$B$82,umumiy_malumot!$B$67,IF(A34<umumiy_malumot!$B$82,(Q34),IF(A34>umumiy_malumot!$B$82,$H$56,0)))))) -> 46883 | C34: =C33-D33 -> 48611111 | D34: =IF(C34=0,L34,IF(C34>1,I34)) -> 4861111.1 | E34: =IF(C34=0,N33,IF(C34>1,L34)) -> 2191484.4 | F34: =IF(C34=0,N33,IF(C34>1,M34)) -> 7052595.5 | G34: =B34-B33 -> 30 | H34: =DATE(YEAR(B34),12,31)-DATE(YEAR(B34),1,1)+1 -> 366 | I34: =IF($L$5=A34,K34,IF($L$5>A34,I33)) -> 4861111.1 | J34: =SUM($I$8:I33) -> 1.2638889e+08 | K34: =$J$12-J34 -> 48611111 | L34: =ROUND(C34*umumiy_malumot!$B$85/H34,2)*G34 -> 2191484.4 | M34: =D34+E34 -> 7052595.5 | O34: =TEXT(R34,"ддд") -> Ср | P34: =IF(O34=$U$8,2,IF(O34=$V$8,1,0)) -> 0 | Q34: =DAY(umumiy_malumot!$B$79)+P34 -> 10 | R34: =IF(A34<=umumiy_malumot!$B$82,DATE(YEAR($B$8),MONTH($B$8)+A33,DAY(umumiy_malumot!$B$79)),0) -> 46883
A35: =1+A34 -> 28 | B35: =IF(A35<=umumiy_malumot!$B$82,DATE(YEAR(R35),MONTH(R35),DAY(IF(A35=umumiy_malumot!$B$82,umumiy_malumot!$B$67,IF(A35<umumiy_malumot!$B$82,(Q35),IF(A35>umumiy_malumot!$B$82,$H$56,0)))))) -> 46916 | C35: =C34-D34 -> 43750000 | D35: =IF(C35=0,L35,IF(C35>1,I35)) -> 4861111.1 | E35: =IF(C35=0,N34,IF(C35>1,L35)) -> 2169569.8 | F35: =IF(C35=0,N34,IF(C35>1,M35)) -> 7030680.9 | G35: =B35-B34 -> 33 | H35: =DATE(YEAR(B35),12,31)-DATE(YEAR(B35),1,1)+1 -> 366 | I35: =IF($L$5=A35,K35,IF($L$5>A35,I34)) -> 4861111.1 | J35: =SUM($I$8:I34) -> 1.3125e+08 | K35: =$J$12-J35 -> 43750000 | L35: =ROUND(C35*umumiy_malumot!$B$85/H35,2)*G35 -> 2169569.8 | M35: =D35+E35 -> 7030680.9 | O35: =TEXT(R35,"ддд") -> Сб | P35: =IF(O35=$U$8,2,IF(O35=$V$8,1,0)) -> 2 | Q35: =DAY(umumiy_malumot!$B$79)+P35 -> 12 | R35: =IF(A35<=umumiy_malumot!$B$82,DATE(YEAR($B$8),MONTH($B$8)+A34,DAY(umumiy_malumot!$B$79)),0) -> 46914
A36: =1+A35 -> 29 | B36: =IF(A36<=umumiy_malumot!$B$82,DATE(YEAR(R36),MONTH(R36),DAY(IF(A36=umumiy_malumot!$B$82,umumiy_malumot!$B$67,IF(A36<umumiy_malumot!$B$82,(Q36),IF(A36>umumiy_malumot!$B$82,$H$56,0)))))) -> 46944 | C36: =C35-D35 -> 38888889 | D36: =IF(C36=0,L36,IF(C36>1,I36)) -> 4861111.1 | E36: =IF(C36=0,N35,IF(C36>1,L36)) -> 1636308.5 | F36: =IF(C36=0,N35,IF(C36>1,M36)) -> 6497419.6 | G36: =B36-B35 -> 28 | H36: =DATE(YEAR(B36),12,31)-DATE(YEAR(B36),1,1)+1 -> 366 | I36: =IF($L$5=A36,K36,IF($L$5>A36,I35)) -> 4861111.1 | J36: =SUM($I$8:I35) -> 1.3611111e+08 | K36: =$J$12-J36 -> 38888889 | L36: =ROUND(C36*umumiy_malumot!$B$85/H36,2)*G36 -> 1636308.5 | M36: =D36+E36 -> 6497419.6 | O36: =TEXT(R36,"ддд") -> Пн | P36: =IF(O36=$U$8,2,IF(O36=$V$8,1,0)) -> 0 | Q36: =DAY(umumiy_malumot!$B$79)+P36 -> 10 | R36: =IF(A36<=umumiy_malumot!$B$82,DATE(YEAR($B$8),MONTH($B$8)+A35,DAY(umumiy_malumot!$B$79)),0) -> 46944
A37: =1+A36 -> 30 | B37: =IF(A37<=umumiy_malumot!$B$82,DATE(YEAR(R37),MONTH(R37),DAY(IF(A37=umumiy_malumot!$B$82,umumiy_malumot!$B$67,IF(A37<umumiy_malumot!$B$82,(Q37),IF(A37>umumiy_malumot!$B$82,$H$56,0)))))) -> 46975 | C37: =C36-D36 -> 34027778 | D37: =IF(C37=0,L37,IF(C37>1,I37)) -> 4861111.1 | E37: =IF(C37=0,N36,IF(C37>1,L37)) -> 1585173.8 | F37: =IF(C37=0,N36,IF(C37>1,M37)) -> 6446285 | G37: =B37-B36 -> 31 | H37: =DATE(YEAR(B37),12,31)-DATE(YEAR(B37),1,1)+1 -> 366 | I37: =IF($L$5=A37,K37,IF($L$5>A37,I36)) -> 4861111.1 | J37: =SUM($I$8:I36) -> 1.4097222e+08 | K37: =$J$12-J37 -> 34027778 | L37: =ROUND(C37*umumiy_malumot!$B$85/H37,2)*G37 -> 1585173.8 | M37: =D37+E37 -> 6446285 | O37: =TEXT(R37,"ддд") -> Чт | P37: =IF(O37=$U$8,2,IF(O37=$V$8,1,0)) -> 0 | Q37: =DAY(umumiy_malumot!$B$79)+P37 -> 10 | R37: =IF(A37<=umumiy_malumot!$B$82,DATE(YEAR($B$8),MONTH($B$8)+A36,DAY(umumiy_malumot!$B$79)),0) -> 46975
A38: =1+A37 -> 31 | B38: =IF(A38<=umumiy_malumot!$B$82,DATE(YEAR(R38),MONTH(R38),DAY(IF(A38=umumiy_malumot!$B$82,umumiy_malumot!$B$67,IF(A38<umumiy_malumot!$B$82,(Q38),IF(A38>umumiy_malumot!$B$82,$H$56,0)))))) -> 47007 | C38: =C37-D37 -> 29166667 | D38: =IF(C38=0,L38,IF(C38>1,I38)) -> 4861111.1 | E38: =IF(C38=0,N37,IF(C38>1,L38)) -> 1402550.1 | F38: =IF(C38=0,N37,IF(C38>1,M38)) -> 6263661.2 | G38: =B38-B37 -> 32 | H38: =DATE(YEAR(B38),12,31)-DATE(YEAR(B38),1,1)+1 -> 366 | I38: =IF($L$5=A38,K38,IF($L$5>A38,I37)) -> 4861111.1 | J38: =SUM($I$8:I37) -> 1.4583333e+08 | K38: =$J$12-J38 -> 29166667 | L38: =ROUND(C38*umumiy_malumot!$B$85/H38,2)*G38 -> 1402550.1 | M38: =D38+E38 -> 6263661.2 | O38: =TEXT(R38,"ддд") -> Вс | P38: =IF(O38=$U$8,2,IF(O38=$V$8,1,0)) -> 1 | Q38: =DAY(umumiy_malumot!$B$79)+P38 -> 11 | R38: =IF(A38<=umumiy_malumot!$B$82,DATE(YEAR($B$8),MONTH($B$8)+A37,DAY(umumiy_malumot!$B$79)),0) -> 47006
A39: =1+A38 -> 32 | B39: =IF(A39<=umumiy_malumot!$B$82,DATE(YEAR(R39),MONTH(R39),DAY(IF(A39=umumiy_malumot!$B$82,umumiy_malumot!$B$67,IF(A39<umumiy_malumot!$B$82,(Q39),IF(A39>umumiy_malumot!$B$82,$H$56,0)))))) -> 47036 | C39: =C38-D38 -> 24305556 | D39: =IF(C39=0,L39,IF(C39>1,I39)) -> 4861111.1 | E39: =IF(C39=0,N38,IF(C39>1,L39)) -> 1059217.5 | F39: =IF(C39=0,N38,IF(C39>1,M39)) -> 5920328.6 | G39: =B39-B38 -> 29 | H39: =DATE(YEAR(B39),12,31)-DATE(YEAR(B39),1,1)+1 -> 366 | I39: =IF($L$5=A39,K39,IF($L$5>A39,I38)) -> 4861111.1 | J39: =SUM($I$8:I38) -> 1.5069444e+08 | K39: =$J$12-J39 -> 24305556 | L39: =ROUND(C39*umumiy_malumot!$B$85/H39,2)*G39 -> 1059217.5 | M39: =D39+E39 -> 5920328.6 | O39: =TEXT(R39,"ддд") -> Вт | P39: =IF(O39=$U$8,2,IF(O39=$V$8,1,0)) -> 0 | Q39: =DAY(umumiy_malumot!$B$79)+P39 -> 10 | R39: =IF(A39<=umumiy_malumot!$B$82,DATE(YEAR($B$8),MONTH($B$8)+A38,DAY(umumiy_malumot!$B$79)),0) -> 47036
A40: =1+A39 -> 33 | B40: =IF(A40<=umumiy_malumot!$B$82,DATE(YEAR(R40),MONTH(R40),DAY(IF(A40=umumiy_malumot!$B$82,umumiy_malumot!$B$67,IF(A40<umumiy_malumot!$B$82,(Q40),IF(A40>umumiy_malumot!$B$82,$H$56,0)))))) -> 47067 | C40: =C39-D39 -> 19444444 | D40: =IF(C40=0,L40,IF(C40>1,I40)) -> 4861111.1 | E40: =IF(C40=0,N39,IF(C40>1,L40)) -> 905813.49 | F40: =IF(C40=0,N39,IF(C40>1,M40)) -> 5766924.6 | G40: =B40-B39 -> 31 | H40: =DATE(YEAR(B40),12,31)-DATE(YEAR(B40),1,1)+1 -> 366 | I40: =IF($L$5=A40,K40,IF($L$5>A40,I39)) -> 4861111.1 | J40: =SUM($I$8:I39) -> 1.5555556e+08 | K40: =$J$12-J40 -> 19444444 | L40: =ROUND(C40*umumiy_malumot!$B$85/H40,2)*G40 -> 905813.49 | M40: =D40+E40 -> 5766924.6 | O40: =TEXT(R40,"ддд") -> Пт | P40: =IF(O40=$U$8,2,IF(O40=$V$8,1,0)) -> 0 | Q40: =DAY(umumiy_malumot!$B$79)+P40 -> 10 | R40: =IF(A40<=umumiy_malumot!$B$82,DATE(YEAR($B$8),MONTH($B$8)+A39,DAY(umumiy_malumot!$B$79)),0) -> 47067
A41: =1+A40 -> 34 | B41: =IF(A41<=umumiy_malumot!$B$82,DATE(YEAR(R41),MONTH(R41),DAY(IF(A41=umumiy_malumot!$B$82,umumiy_malumot!$B$67,IF(A41<umumiy_malumot!$B$82,(Q41),IF(A41>umumiy_malumot!$B$82,$H$56,0)))))) -> 47098 | C41: =C40-D40 -> 14583333 | D41: =IF(C41=0,L41,IF(C41>1,I41)) -> 4861111.1 | E41: =IF(C41=0,N40,IF(C41>1,L41)) -> 679360.35 | F41: =IF(C41=0,N40,IF(C41>1,M41)) -> 5540471.5 | G41: =B41-B40 -> 31 | H41: =DATE(YEAR(B41),12,31)-DATE(YEAR(B41),1,1)+1 -> 366 | I41: =IF($L$5=A41,K41,IF($L$5>A41,I40)) -> 4861111.1 | J41: =SUM($I$8:I40) -> 1.6041667e+08 | K41: =$J$12-J41 -> 14583333 | L41: =ROUND(C41*umumiy_malumot!$B$85/H41,2)*G41 -> 679360.35 | M41: =D41+E41 -> 5540471.5 | O41: =TEXT(R41,"ддд") -> Вс | P41: =IF(O41=$U$8,2,IF(O41=$V$8,1,0)) -> 1 | Q41: =DAY(umumiy_malumot!$B$79)+P41 -> 11 | R41: =IF(A41<=umumiy_malumot!$B$82,DATE(YEAR($B$8),MONTH($B$8)+A40,DAY(umumiy_malumot!$B$79)),0) -> 47097
A42: =1+A41 -> 35 | B42: =IF(A42<=umumiy_malumot!$B$82,DATE(YEAR(R42),MONTH(R42),DAY(IF(A42=umumiy_malumot!$B$82,umumiy_malumot!$B$67,IF(A42<umumiy_malumot!$B$82,(Q42),IF(A42>umumiy_malumot!$B$82,$H$56,0)))))) -> 47128 | C42: =C41-D41 -> 9722222.3 | D42: =IF(C42=0,L42,IF(C42>1,I42)) -> 4861111.1 | E42: =IF(C42=0,N41,IF(C42>1,L42)) -> 439497.6 | F42: =IF(C42=0,N41,IF(C42>1,M42)) -> 5300608.7 | G42: =B42-B41 -> 30 | H42: =DATE(YEAR(B42),12,31)-DATE(YEAR(B42),1,1)+1 -> 365 | I42: =IF($L$5=A42,K42,IF($L$5>A42,I41)) -> 4861111.1 | J42: =SUM($I$8:I41) -> 1.6527778e+08 | K42: =$J$12-J42 -> 9722222.3 | L42: =ROUND(C42*umumiy_malumot!$B$85/H42,2)*G42 -> 439497.6 | M42: =D42+E42 -> 5300608.7 | O42: =TEXT(R42,"ддд") -> Ср | P42: =IF(O42=$U$8,2,IF(O42=$V$8,1,0)) -> 0 | Q42: =DAY(umumiy_malumot!$B$79)+P42 -> 10 | R42: =IF(A42<=umumiy_malumot!$B$82,DATE(YEAR($B$8),MONTH($B$8)+A41,DAY(umumiy_malumot!$B$79)),0) -> 47128
A43: =1+A42 -> 36 | B43: =IF(A43<=umumiy_malumot!$B$82,DATE(YEAR(R43),MONTH(R43),DAY(IF(A43=umumiy_malumot!$B$82,umumiy_malumot!$B$67,IF(A43<umumiy_malumot!$B$82,(Q43),IF(A43>umumiy_malumot!$B$82,$H$56,0)))))) -> 47165 | C43: =C42-D42 -> 4861111.1 | D43: =IF(C43=0,L43,IF(C43>1,I43)) -> 4861111.1 | E43: =IF(C43=0,N42,IF(C43>1,L43)) -> 271023.52 | F43: =IF(C43=0,N42,IF(C43>1,M43)) -> 5132134.7 | G43: =B43-B42 -> 37 | H43: =DATE(YEAR(B43),12,31)-DATE(YEAR(B43),1,1)+1 -> 365 | I43: =IF($L$5=A43,K43,IF($L$5>A43,I42)) -> 4861111.1 | J43: =SUM($I$8:I42) -> 1.7013889e+08 | K43: =$J$12-J43 -> 4861111.1 | L43: =ROUND(C43*umumiy_malumot!$B$85/H43,2)*G43 -> 271023.52 | M43: =D43+E43 -> 5132134.7 | O43: =TEXT(R43,"ддд") -> Сб | P43: =IF(O43=$U$8,2,IF(O43=$V$8,1,0)) -> 2 | Q43: =DAY(umumiy_malumot!$B$79)+P43 -> 12 | R43: =IF(A43<=umumiy_malumot!$B$82,DATE(YEAR($B$8),MONTH($B$8)+A42,DAY(umumiy_malumot!$B$79)),0) -> 47159
... A55: =1+A54 -> 48 | B55: =IF(A55<=umumiy_malumot!$B$82,DATE(YEAR(R55),MONTH(R55),DAY(IF(A55=umumiy_malumot!$B$82,umumiy_malumot!$B$67,IF(A55<umumiy_malumot!$B$82,(Q55),IF(A55>umumiy_malumot!$B$82,$H$56,0)))))) -> FALSE | C55: =C54-D54 -> 1.3969839e-08 | D55: =IF(C55=0,L55,IF(C55>1,I55)) -> FALSE | E55: =IF(C55=0,N54,IF(C55>1,L55)) -> FALSE | F55: =IF(C55=0,N54,IF(C55>1,M55)) -> FALSE | G55: =B55-B54 -> 0 | H55: =DATE(YEAR(B55),12,31)-DATE(YEAR(B55),1,1)+1 -> 366 | I55: =IF($L$5=A55,K55,IF($L$5>A55,I54)) -> FALSE | J55: =SUM($I$8:I54) -> 175000000 | K55: =$J$12-J55 -> 0 | L55: =ROUND(C55*umumiy_malumot!$B$85/H55,2)*G55 -> 0 | M55: =D55+E55 -> 0 | O55: =TEXT(R55,"ддд") -> Сб | P55: =IF(O55=$U$8,2,IF(O55=$V$8,1,0)) -> 2 | Q55: =DAY(umumiy_malumot!$B$79)+P55 -> 12 | R55: =IF(A55<=umumiy_malumot!$B$82,DATE(YEAR($B$8),MONTH($B$8)+A54,DAY(umumiy_malumot!$B$79)),0) -> 0
B56: ИТОГО | D56: =SUM(D8:D55) -> 175000000 | E56: =SUM(E8:E55) -> 1.4660531e+08 | F56: =SUM(F8:F55) -> 3.2160531e+08
A58: *В случае осуществления погашения платежей по кредиту в даты, отличные от указанных в графике погашения, сумма платежа меняется на сумму процентов, которые начисляются на сумму остатка долга по микрозайму в соответствии с п.п. 2.2. настоящего договора.
A60: =#REF! -> #REF! | D60: =#REF! -> #REF!
A62: =#REF! -> #REF! | D62: =#REF! -> #REF!
A63: =#REF! -> #REF! | D63: =#REF! -> #REF!
A64: =#REF! -> #REF! | D64: ="паспорт серии "&umumiy_malumot!B16&", "&umumiy_malumot!B20&"" -> паспорт серии AE 5547691, IIV 27256 tomonidan 22.12.2025 yilda berilgan
A65: =#REF! -> #REF!
A66: =#REF! -> #REF! | D66: =#REF! -> #REF!
A67: =#REF! -> #REF! | D67: =#REF! -> #REF!
A68: =#REF! -> #REF! | D68: =#REF! -> #REF!
A70: =#REF! -> #REF! | D70: =#REF! -> #REF!
A72: =#REF! -> #REF! | D72: =#REF! -> #REF!
D74: =#REF! -> #REF!

Sheet Данные для послед. Залога
A1: № | B1: - | E1: ФИО | F1: дата | L1: № договора | M1: Сог. Сумма | N1: сог. Сумма (пропис.)
A2: 1 | B2: ha | C2: yoq | D2: ha | E2: TULYAGANOV XODJIAKBAR IRGASHEVICH | F2: 44207 | G2: =MONTH(F2) -> 1 | H2: =IF(G2=$A$26,$A$28,IF(G2=$B$26,$B$28,IF(G2=$C$26,$C$28,IF(G2=$D$26,$D$28,IF(G2=$E$26,$E$28,IF(G2=$F$26,$F$28,IF(G2=$K$26,$K$28,IF(G2=$L$26,$L$28,IF(G2=$M$26,$M$28,IF(G2=$N$26,$N$28,IF(G2=$O$26,$O$28,IF(G2=$P$26,$P$28,0)))))))))))) -> yanvar | I2: =DAY(F2) -> 11 | J2: =YEAR(F2) -> 2021 | K2: =""&I2&" "&H2&" "&J2&" г." -> 11 yanvar 2021 г. | L2: 5 | M2: 15000000 | N2: on besh million | O2: ="- №"&L2&" от "&K2&", заключенного с ООО «Clever Mikrokredit Tashkiloti» и "&E2&", по согласованной залоговой стоимость - "&FIXED(M2)&" ("&N2&") сум." -> - №5 от 11 yanvar 2021 г., заключенного с ООО «Clever Mikrokredit Tashkiloti» и TULYAGANOV XODJIAKBAR IRGASHEVICH, по согласованной залоговой стоимость - 15 000 000,00 (on besh million) сум. | P2: =IF(D2=$B$2,O2,IF(D2=$C$2,$B$1)) -> - №5 от 11 yanvar 2021 г., заключенного с ООО «Clever Mikrokredit Tashkiloti» и TULYAGANOV XODJIAKBAR IRGASHEVICH, по согласованной залоговой стоимость - 15 000 000,00 (on besh million) сум. | W2: =""&P2&" "&P3&" "&P4&" "&P5&" "&P6&" "&P7&" "&P8&" "&P9&" "&P10&" "&P11&" "&P12&" "&P13&" "&P14&" "&P15&" "&P16&" "&P17&" "&P18&" "&P19&" "&P20&" "&P21&"" -> - №5 от 11 yanvar 2021 г., заключенного с ООО «Clever Mikrokredit Tashkiloti» и TULYAGANOV XODJIAKBAR IRGASHEVICH, по согласованной залоговой стоимость - 15 000 000,00 (on besh million) сум. - №386 от 6 noyabr 2019 г., заключенного с ООО «Clever Mikrokredit Tashkiloti» и YUNUSOVA ZALOXAT MIRSULTANOVNA, по согласованной залоговой стоимость - 15 000 000,00 (on besh million) сум. - №33 от 21 yanvar 2021 г., заключенного с ООО «Clever Mikrokredit Tashkiloti» и YUNUSOVA ZALOXAT MIRSULTANOVNA, по согласованной залоговой стоимость - 15 000 000,00 (on besh million) сум. 0 0 0 0 0 0 0 0 0 0 0 0 0 0 0 0 0
A3: 2 | D3: ha | E3: YUNUSOVA ZALOXAT MIRSULTANOVNA | F3: 43775 | G3: =MONTH(F3) -> 11 | H3: =IF(G3=$A$26,$A$28,IF(G3=$B$26,$B$28,IF(G3=$C$26,$C$28,IF(G3=$D$26,$D$28,IF(G3=$E$26,$E$28,IF(G3=$F$26,$F$28,IF(G3=$K$26,$K$28,IF(G3=$L$26,$L$28,IF(G3=$M$26,$M$28,IF(G3=$N$26,$N$28,IF(G3=$O$26,$O$28,IF(G3=$P$26,$P$28,0)))))))))))) -> noyabr | I3: =DAY(F3) -> 6 | J3: =YEAR(F3) -> 2019 | K3: =""&I3&" "&H3&" "&J3&" г." -> 6 noyabr 2019 г. | L3: 386 | M3: 15000000 | N3: on besh million | O3: ="- №"&L3&" от "&K3&", заключенного с ООО «Clever Mikrokredit Tashkiloti» и "&E3&", по согласованной залоговой стоимость - "&FIXED(M3)&" ("&N3&") сум." -> - №386 от 6 noyabr 2019 г., заключенного с ООО «Clever Mikrokredit Tashkiloti» и YUNUSOVA ZALOXAT MIRSULTANOVNA, по согласованной залоговой стоимость - 15 000 000,00 (on besh million) сум. | P3: =IF(D3=$B$2,O3,IF(D3=$C$2,$B$1)) -> - №386 от 6 noyabr 2019 г., заключенного с ООО «Clever Mikrokredit Tashkiloti» и YUNUSOVA ZALOXAT MIRSULTANOVNA, по согласованной залоговой стоимость - 15 000 000,00 (on besh million) сум.
A4: 3 | D4: ha | E4: YUNUSOVA ZALOXAT MIRSULTANOVNA | F4: 44217 | G4: =MONTH(F4) -> 1 | H4: =IF(G4=$A$26,$A$28,IF(G4=$B$26,$B$28,IF(G4=$C$26,$C$28,IF(G4=$D$26,$D$28,IF(G4=$E$26,$E$28,IF(G4=$F$26,$F$28,IF(G4=$K$26,$K$28,IF(G4=$L$26,$L$28,IF(G4=$M$26,$M$28,IF(G4=$N$26,$N$28,IF(G4=$O$26,$O$28,IF(G4=$P$26,$P$28,0)))))))))))) -> yanvar | I4: =DAY(F4) -> 21 | J4: =YEAR(F4) -> 2021 | K4: =""&I4&" "&H4&" "&J4&" г." -> 21 yanvar 2021 г. | L4: 33 | M4: 15000000 | N4: on besh million | O4: ="- №"&L4&" от "&K4&", заключенного с ООО «Clever Mikrokredit Tashkiloti» и "&E4&", по согласованной залоговой стоимость - "&FIXED(M4)&" ("&N4&") сум." -> - №33 от 21 yanvar 2021 г., заключенного с ООО «Clever Mikrokredit Tashkiloti» и YUNUSOVA ZALOXAT MIRSULTANOVNA, по согласованной залоговой стоимость - 15 000 000,00 (on besh million) сум. | P4: =IF(D4=$B$2,O4,IF(D4=$C$2,$B$1)) -> - №33 от 21 yanvar 2021 г., заключенного с ООО «Clever Mikrokredit Tashkiloti» и YUNUSOVA ZALOXAT MIRSULTANOVNA, по согласованной залоговой стоимость - 15 000 000,00 (on besh million) сум.
A5: 4 | D5: ha | G5: =MONTH(F5) -> 1 | H5: =IF(G5=$A$26,$A$28,IF(G5=$B$26,$B$28,IF(G5=$C$26,$C$28,IF(G5=$D$26,$D$28,IF(G5=$E$26,$E$28,IF(G5=$F$26,$F$28,IF(G5=$K$26,$K$28,IF(G5=$L$26,$L$28,IF(G5=$M$26,$M$28,IF(G5=$N$26,$N$28,IF(G5=$O$26,$O$28,IF(G5=$P$26,$P$28,0)))))))))))) -> yanvar | I5: =DAY(F5) -> 0 | J5: =YEAR(F5) -> 1900 | K5: =""&I5&" "&H5&" "&J5&" г." -> 0 yanvar 1900 г. | P5: =IF(D5=$B$2,O5,IF(D5=$C$2,$B$1)) -> 0
A6: 5 | D6: ha | G6: =MONTH(F6) -> 1 | H6: =IF(G6=$A$26,$A$28,IF(G6=$B$26,$B$28,IF(G6=$C$26,$C$28,IF(G6=$D$26,$D$28,IF(G6=$E$26,$E$28,IF(G6=$F$26,$F$28,IF(G6=$K$26,$K$28,IF(G6=$L$26,$L$28,IF(G6=$M$26,$M$28,IF(G6=$N$26,$N$28,IF(G6=$O$26,$O$28,IF(G6=$P$26,$P$28,0)))))))))))) -> yanvar | I6: =DAY(F6) -> 0 | J6: =YEAR(F6) -> 1900 | K6: =""&I6&" "&H6&" "&J6&" г." -> 0 yanvar 1900 г. | P6: =IF(D6=$B$2,O6,IF(D6=$C$2,$B$1)) -> 0
A7: 6 | D7: ha | G7: =MONTH(F7) -> 1 | H7: =IF(G7=$A$26,$A$28,IF(G7=$B$26,$B$28,IF(G7=$C$26,$C$28,IF(G7=$D$26,$D$28,IF(G7=$E$26,$E$28,IF(G7=$F$26,$F$28,IF(G7=$K$26,$K$28,IF(G7=$L$26,$L$28,IF(G7=$M$26,$M$28,IF(G7=$N$26,$N$28,IF(G7=$O$26,$O$28,IF(G7=$P$26,$P$28,0)))))))))))) -> yanvar | I7: =DAY(F7) -> 0 | J7: =YEAR(F7) -> 1900 | K7: =""&I7&" "&H7&" "&J7&" г." -> 0 yanvar 1900 г. | P7: =IF(D7=$B$2,O7,IF(D7=$C$2,$B$1)) -> 0
A8: 7 | D8: ha | G8: =MONTH(F8) -> 1 | H8: =IF(G8=$A$26,$A$28,IF(G8=$B$26,$B$28,IF(G8=$C$26,$C$28,IF(G8=$D$26,$D$28,IF(G8=$E$26,$E$28,IF(G8=$F$26,$F$28,IF(G8=$K$26,$K$28,IF(G8=$L$26,$L$28,IF(G8=$M$26,$M$28,IF(G8=$N$26,$N$28,IF(G8=$O$26,$O$28,IF(G8=$P$26,$P$28,0)))))))))))) -> yanvar | I8: =DAY(F8) -> 0 | J8: =YEAR(F8) -> 1900 | K8: =""&I8&" "&H8&" "&J8&" г." -> 0 yanvar 1900 г. | P8: =IF(D8=$B$2,O8,IF(D8=$C$2,$B$1)) -> 0
A9: 8 | D9: ha | G9: =MONTH(F9) -> 1 | H9: =IF(G9=$A$26,$A$28,IF(G9=$B$26,$B$28,IF(G9=$C$26,$C$28,IF(G9=$D$26,$D$28,IF(G9=$E$26,$E$28,IF(G9=$F$26,$F$28,IF(G9=$K$26,$K$28,IF(G9=$L$26,$L$28,IF(G9=$M$26,$M$28,IF(G9=$N$26,$N$28,IF(G9=$O$26,$O$28,IF(G9=$P$26,$P$28,0)))))))))))) -> yanvar | I9: =DAY(F9) -> 0 | J9: =YEAR(F9) -> 1900 | K9: =""&I9&" "&H9&" "&J9&" г." -> 0 yanvar 1900 г. | P9: =IF(D9=$B$2,O9,IF(D9=$C$2,$B$1)) -> 0
A10: 9 | D10: ha | G10: =MONTH(F10) -> 1 | H10: =IF(G10=$A$26,$A$28,IF(G10=$B$26,$B$28,IF(G10=$C$26,$C$28,IF(G10=$D$26,$D$28,IF(G10=$E$26,$E$28,IF(G10=$F$26,$F$28,IF(G10=$K$26,$K$28,IF(G10=$L$26,$L$28,IF(G10=$M$26,$M$28,IF(G10=$N$26,$N$28,IF(G10=$O$26,$O$28,IF(G10=$P$26,$P$28,0)))))))))))) -> yanvar | I10: =DAY(F10) -> 0 | J10: =YEAR(F10) -> 1900 | K10: =""&I10&" "&H10&" "&J10&" г." -> 0 yanvar 1900 г. | P10: =IF(D10=$B$2,O10,IF(D10=$C$2,$B$1)) -> 0
A11: 10 | D11: ha | G11: =MONTH(F11) -> 1 | H11: =IF(G11=$A$26,$A$28,IF(G11=$B$26,$B$28,IF(G11=$C$26,$C$28,IF(G11=$D$26,$D$28,IF(G11=$E$26,$E$28,IF(G11=$F$26,$F$28,IF(G11=$K$26,$K$28,IF(G11=$L$26,$L$28,IF(G11=$M$26,$M$28,IF(G11=$N$26,$N$28,IF(G11=$O$26,$O$28,IF(G11=$P$26,$P$28,0)))))))))))) -> yanvar | I11: =DAY(F11) -> 0 | J11: =YEAR(F11) -> 1900 | K11: =""&I11&" "&H11&" "&J11&" г." -> 0 yanvar 1900 г. | P11: =IF(D11=$B$2,O11,IF(D11=$C$2,$B$1)) -> 0
