Workbook
Name mos: '[1]Общие данные'!$C$23:$D$23
Name mulk: '[1]Общие данные'!$C$24:$W$24

Sheet protokol
A1: =""&umumiy_malumot!B147&" mikromoliya tashkiloti Kredit qo‘mitasining yig‘ilishi" -> «PULLOL BUSINESS MIKROMOLIYA TASHKILOTI» MChJ mikromoliya tashkiloti Kredit qo‘mitasining yig‘ilishi
A2: =""&I7&" protokolidan ko'chirma" -> №43 protokolidan ko'chirma
A3: Toshkent shahri | F3: =umumiy_malumot!B68 -> 2 fevral 2026 y.
C4: KUN TARTIBI:
A5: =" "&I8&"."&umumiy_malumot!B5&" ga "&umumiy_malumot!B65&" berish masalasini ko‘rib chiqish to‘g‘risida." -> 1.SIMONYAN VADIM ROMANOVICH ga Mikroqarz berish masalasini ko‘rib chiqish to‘g‘risida.
A7: =" "&I9&" masala yuzasidan: «PULLOL BUSINESS MIKROMOLIYA TASHKILOTI» MChJ kredit bo‘yicha menejeri "&umumiy_malumot!B5&"ga "&FIXED(umumiy_malumot!B75)&" ("&umumiy_malumot!B76&") so‘m miqdorida, muddati "&umumiy_malumot!B81&" ("&umumiy_malumot!B82&") oyga va yillik "&umumiy_malumot!B85&"% ("&umumiy_malumot!B86&") foiz miqdorida "&umumiy_malumot!B65&" berich bo‘yicha "&umumiy_malumot!B5&"ning kredit arizasi va "&umumiy_malumot!B147&"ning xulosasi bilan ishtirokchilarni tanishtirdi." -> Birinchi masala yuzasidan: «PULLOL BUSINESS MIKROMOLIYA TASHKILOTI» MChJ kredit bo‘yicha menejeri SIMONYAN VADIM ROMANOVICHga 50 000 000,00 (Ellik million so'm) so‘m miqdorida, muddati 24 (yigirma to'rt) oyga va yillik 50% (Ellik ) foiz miqdorida Mikroqarz berich bo‘yicha SIMONYAN VADIM ROMANOVICHning kredit arizasi va «PULLOL BUSINESS MIKROMOLIYA TASHKILOTI» MChJning xulosasi bilan ishtirokchilarni tanishtirdi. | H7: Protokol raqami | I7: =umumiy_malumot!B1 -> №43
H8: Savol raqami | I8: 1 | J8: 1 | K8: 2 | L8: 3 | M8: 4 | N8: 5 | O8: 6 | P8: 7 | Q8: 8 | R8: 9 | S8: 10 | T8: 11 | U8: 12 | V8: 13 | W8: 14 | X8: 15 | Y8: 16 | Z8: 17 | AA8: 18 | AB8: 19 | AC8: 20 | AD8: 21 | AE8: 22 | AF8: 23 | AG8: 24 | AH8: 25
H9: Savol raqami qol bilan | I9: =IF(I8=J8,J9,IF(I8=K8,K9,IF(I8=L8,L9,IF(I8=M8,M9,IF(I8=N8,N9,IF(I8=O8,O9,IF(I8=P8,P9,IF(I8=Q8,Q9,IF(I8=R8,R9,IF(I8=S8,S9,IF(I8=T8,T9,IF(I8=U8,U9,IF(I8=V8,V9,IF(I8=W8,W9,IF(I8=X8,X9,IF(I8=Y8,Y9,IF(I8=Z8,Z9,IF(I8=AA8,AA9,IF(I8=AB8,AB9,IF(I8=AC8,AC9,IF(I8=AD8,AD9,IF(I8=AE8,AE9,IF(I8=AF8,AF9,IF(I8=AG8,AG9,IF(I8=AH8,AH9))))))))))))))))))))))))) -> Birinchi | J9: Birinchi | K9: Ikkinchi | L9: Uchinchi | M9: To'rtinchi | N9: Beshinchi | O9: O'ltinchi | P9: Yettinchi | Q9: Sakkizinchi | R9: Tuqqizinchi | S9: O'ninchi | T9: O'n birinchi | U9: O'n ikkinchi | V9: O'n uchinchi | W9: O'n to'rtinchi | X9: O'n beshinchi | Y9: O'n oltinchi | Z9: O'n yettinchi | AA9: O'n sakkizinchi | AB9: O'n tuqqizinchi | AC9: Yigirmanchi | AD9: Yigirma birinchi | AE9: Yigizma ikkinchi | AF9: Yigirma uchinchi | AG9: Yigirma to'rtinchi | AH9: Yigirma beshinchi
A14: =""&umumiy_malumot!B65&" ta’minoti:" -> Mikroqarz ta’minoti:
A16: =xulosa!A18:F18 -> Egalik huquqi SIMONYAN VADIM ROMANOVICHga tegishli bo'lgan umumiy yer maydoni, (m2) - 166, qurilish osti maydoni - 87, umumiy foydali maydoni - 48.67 va yashash maydoni - 30.84 Yakka tartibdagi uy-joy, TOSHKENT SHAHAR YUNUSOBOD TUMANI OTCHOPAR-1 MFY KARIM ZARIPOV KO'CHASI 8-6 UY
D17: masala yuzasidan berilgan ma’lumotlarni muhokama qilib, Kredit qo‘mitasi a’zolariga taqdim etilgan zarur hujjatlarni o‘rganib, majlisda ishtirok etgan Kredit qo‘mitasi a’zolarining taklif va mulohazalarini inobatga olgan holda | E17: =""&umumiy_malumot!B147&" kredit qo‘mitasi" -> «PULLOL BUSINESS MIKROMOLIYA TASHKILOTI» MChJ kredit qo‘mitasi | F17: =CONCATENATE(D17,E17) -> masala yuzasidan berilgan ma’lumotlarni muhokama qilib, Kredit qo‘mitasi a’zolariga taqdim etilgan zarur hujjatlarni o‘rganib, majlisda ishtirok etgan Kredit qo‘mitasi a’zolarining taklif va mulohazalarini inobatga olgan holda «PULLOL BUSINESS MIKROMOLIYA TASHKILOTI» MChJ kredit qo‘mitasi
A18: =CONCATENATE(I9,F17) -> Birinchi masala yuzasidan berilgan ma’lumotlarni muhokama qilib, Kredit qo‘mitasi a’zolariga taqdim etilgan zarur hujjatlarni o‘rganib, majlisda ishtirok etgan Kredit qo‘mitasi a’zolarining taklif va mulohazalarini inobatga olgan holda «PULLOL BUSINESS MIKROMOLIYA TASHKILOTI» MChJ kredit qo‘mitasi
A19: QAROR QILADI:
A20: =" "&umumiy_malumot!B5&"ga quyidagi shartlarda "&umumiy_malumot!B65&" berish masalasi ma’qullansin:" -> SIMONYAN VADIM ROMANOVICHga quyidagi shartlarda Mikroqarz berish masalasi ma’qullansin:
A21: ="1. "&umumiy_malumot!B65&" summasi: "&FIXED(umumiy_malumot!B75)&" ("&umumiy_malumot!B76&") so'm." -> 1. Mikroqarz summasi: 50 000 000,00 (Ellik million so'm) so'm.
A22: ="2. "&umumiy_malumot!B65&" muddati: "&umumiy_malumot!B81&" ("&umumiy_malumot!B82&") oy " -> 2. Mikroqarz muddati: 24 (yigirma to'rt) oy
A23: ="3. "&umumiy_malumot!B65&"dan foydalanganlik uchun foiz stavkasi:yillik "&umumiy_malumot!B85&"% ("&umumiy_malumot!B86&") foiz." -> 3. Mikroqarzdan foydalanganlik uchun foiz stavkasi:yillik 50% (Ellik ) foiz.
A24: ="4. "&umumiy_malumot!B65&" bo‘yicha asosiy qarz va foizlarni to‘lash:" -> 4. Mikroqarz bo‘yicha asosiy qarz va foizlarni to‘lash:
A25: =kredit_ariza!A19:D19 -> - Mikroqarz shartnomasi bo'yicha har oy annuitet to'lovlari amalga oshiriladi
A26: ="5. "&umumiy_malumot!B65&" bo‘yicha garov "&xulosa!A29:F29&"" -> 5. Mikroqarz bo‘yicha garov - SIMONYAN VADIM ROMANOVICH ga mulk huquqi asosida tegishli ko'chmas mulk shaklida Yakka tartibdagi uy-joy, manzili: TOSHKENT SHAHAR YUNUSOBOD TUMANI OTCHOPAR-1 MFY KARIM ZARIPOV KO'CHASI 8-6 UY, quyidagi tafsilotlarga muvofiq:
A27: =dalolatnoma!A47 -> Nomi | B27: =dalolatnoma!B47 -> Umumiy yer maydoni, (m2) | C27: =dalolatnoma!C47 -> Qurilish osti maydoni, (m2) | D27: =dalolatnoma!D47 -> Umumiy foydali maydoni, (m2) | E27: =dalolatnoma!E47 -> Yashash maydoni, (m2) | F27: =dalolatnoma!F47 -> Kelishilgan garov qiymati, so'm
A28: =dalolatnoma!A48 -> Yakka tartibdagi uy-joy | B28: =dalolatnoma!B48 -> 166 | C28: =dalolatnoma!C48 -> 87 | D28: =dalolatnoma!D48 -> 48.67 | E28: =dalolatnoma!E48 -> 30.84 | F28: =dalolatnoma!F48 -> 70 000 000,00 (yetmish million so'm)
A29: =dalolatnoma!A22:F22 -> -* avtotransport egasi: SIMONYAN VADIM ROMANOVICH
A30: =dalolatnoma!A23:F23 -> -* texnik pasport:
A31: =dalolatnoma!A24:F24 -> -* roʻyxatdan oʻtgan manzili/garaj manzili: TOSHKENT SHAHAR YUNUSOBOD TUMANI OTCHOPAR-1 MFY KARIM ZARIPOV KO'CHASI 8-6 UY
A32: =dalolatnoma!A25:F25 -> -* davlat raqami:
A33: =dalolatnoma!A50 -> Наименование | C33: =dalolatnoma!C50 -> Полезная площадь | D33: =dalolatnoma!D50 -> Жилая площадь | E33: =dalolatnoma!E50 -> Общая площадь | F33: =dalolatnoma!F50 -> Согласованная залоговая стоимость, сум
A34: =dalolatnoma!A51 -> Yashash xona | C34: =dalolatnoma!C51 -> 3 | D34: =dalolatnoma!D51 -> 18.82 | E34: =dalolatnoma!E51 -> 0 | F34: =""&FIXED(umumiy_malumot!C136,2)&" ("&umumiy_malumot!B137&")" -> 70 000 000,00 (yetmish million so'm)
A35: =dalolatnoma!A52 -> 0 | C35: =dalolatnoma!C52 -> 0 | D35: =dalolatnoma!D52 -> 0 | E35: =dalolatnoma!E52 -> 0
A36: =dalolatnoma!A53 -> Umumiy maydon | C36: =dalolatnoma!C53 -> 43.96 | D36: =dalolatnoma!D53 -> 18.82 | E36: =dalolatnoma!E53 -> 43.96
A37: =dalolatnoma!A54 -> 0 | C37: =dalolatnoma!C54 -> 0 | D37: =dalolatnoma!D54 -> 0 | E37: =dalolatnoma!E54 -> 0
A38: =dalolatnoma!A55 -> 0 | C38: =dalolatnoma!C55 -> 0 | D38: =dalolatnoma!D55 -> 0 | E38: =dalolatnoma!E55 -> 0
A39: =dalolatnoma!A56 -> 0 | C39: =dalolatnoma!C56 -> 0 | D39: =dalolatnoma!D56 -> 0 | E39: =dalolatnoma!E56 -> 0
A40: =dalolatnoma!A57 -> 0 | C40: =dalolatnoma!C57 -> 0 | D40: =dalolatnoma!D57 -> 0 | E40: =dalolatnoma!E57 -> 0
A41: =dalolatnoma!A58 -> 0 | C41: =dalolatnoma!C58 -> 0 | D41: =dalolatnoma!D58 -> 0 | E41: =dalolatnoma!E58 -> 0
A42: =dalolatnoma!A59 -> 0 | C42: =dalolatnoma!C59 -> 0 | D42: =dalolatnoma!D59 -> 0 | E42: =dalolatnoma!E59 -> 0
A43: =dalolatnoma!A60 -> 0 | C43: =dalolatnoma!C60 -> 0 | D43: =dalolatnoma!D60 -> 0 | E43: =dalolatnoma!E60 -> 0
A44: =dalolatnoma!A61 -> 0 | C44: =dalolatnoma!C61 -> 0 | D44: =dalolatnoma!D61 -> 0 | E44: =dalolatnoma!E61 -> 0
A45: =dalolatnoma!A62 -> JAMI | C45: =dalolatnoma!C62 -> 43.96 | D45: =dalolatnoma!D62 -> 18.82 | E45: =dalolatnoma!E62 -> 43.96 | F45: =FIXED(umumiy_malumot!C136,2) -> 70 000 000,00
A46: =dalolatnoma!A39:F39 -> -* ko'chmas mulk egasi: SIMONYAN VADIM ROMANOVICH
A47: =dalolatnoma!A40:F40 -> -* reestr raqami: №1726266/R-A5552339
A48: =dalolatnoma!A41:F41 -> -* kadastr raqami: 07.01.2025 y. №10:07:04:02:02:7296/06
A49: =dalolatnoma!A42:F42 -> -* manzil: TOSHKENT SHAHAR YUNUSOBOD TUMANI OTCHOPAR-1 MFY KARIM ZARIPOV KO'CHASI 8-6 UY
A51: 6. Boshqa shartlar – ko'chmas mulk vositasi shaklida garov ta'minlangandan keyin mikroqarz berish.
A53: Qaror bir ovozdan qabul qilindi.
A54: ="1. "&umumiy_malumot!B151&"" -> 1. Obidov Abdullo Shokir o'g'li
A55: ="2. "&umumiy_malumot!B159&"" -> 2. Akramov R.N.
A56: ="3. "&umumiy_malumot!B161&"" -> 3. Eshbekov S.O.

Sheet График дифференц
E1: Приложение №1
F2: ="к договору микрозайма "&umumiy_malumot!B74&"" -> к договору микрозайма 2 fevral 2026 y.dan №43
A4: График погашения
L5: =umumiy_malumot!B81 -> 24
A6: № | B6: Дата погашения | C6: Остаток основного долга | D6: Сумма погашения, сум
D7: основного долга | E7: процентов* | F7: всего*
A8: 1 | B8: =umumiy_malumot!B79 -> 46101 | C8: =umumiy_malumot!B75 -> 50000000 | D8: =IF(IF(C8=0,L8,IF(C8>1,I8))="",0,(IF(C8=0,L8,IF(C8>1,I8)))) -> 2083333.3 | E8: =IF(C8=0,N6,IF(C8>1,L8)) -> 3465753.6 | F8: =IF(C8=0,O6,IF(C8>1,M8)) -> 5549087 | G8: =B8-umumiy_malumot!B67 -> 46 | H8: =DATE(YEAR(B8),12,31)-DATE(YEAR(B8),1,1)+1 -> 365 | I8: =IF(umumiy_malumot!B83=0,ROUND(C8/L5,2),"") -> 2083333.3 | L8: =ROUND(C8*umumiy_malumot!$B$84/H8,2)*G8 -> 3465753.6 | M8: =D8+E8 -> 5549087 | O8: =TEXT(B8,"ддд") -> Пт | P8: =IF(O8=$U$8,2,IF(O8=$V$8,1,0)) -> 0 | Q8: =DAY(umumiy_malumot!$B$78)+P8 -> 20 | S8: Чт | T8: Пт | U8: Сб | V8: Вс
A9: 2 | B9: =IF(A9<=umumiy_malumot!$B$81,DATE(YEAR(R9),MONTH(R9),DAY(R9)+P9),0) -> 46132 | C9: =C8-D8 -> 47916667 | D9: =IF(C9=0,L9,IF(C9>1,I9)) -> 2083333.3 | E9: =IF(C9=0,N8,IF(C9>1,L9)) -> 2238299.2 | F9: =IF(C9=0,N8,IF(C9>1,M9)) -> 4321632.5 | G9: =B9-B8 -> 31 | H9: =DATE(YEAR(B9),12,31)-DATE(YEAR(B9),1,1)+1 -> 365 | I9: =IF(I8="",ROUND(C8/(L5-1),2),I8) -> 2083333.3 | L9: =ROUND(C9*umumiy_malumot!$B$84/H9,2)*G9 -> 2238299.2 | M9: =D9+E9 -> 4321632.5 | O9: =TEXT(R9,"ддд") -> Пн | P9: =IF(O9=$U$8,2,IF(O9=$V$8,1,0)) -> 0 | Q9: =DAY(umumiy_malumot!$B$78)+P9 -> 20 | R9: =IF(A9<=umumiy_malumot!$B$81,DATE(YEAR($B$8),MONTH($B$8)+A8,DAY(umumiy_malumot!$B$78)),0) -> 46132
A10: 3 | B10: =IF(A10<=umumiy_malumot!$B$81,DATE(YEAR(R10),MONTH(R10),DAY(R10)+P10),0) -> 46162 | C10: =C9-D9 -> 45833333 | D10: =IF(C10=0,L10,IF(C10>1,I10)) -> 2083333.3 | E10: =IF(C10=0,N9,IF(C10>1,L10)) -> 2071917.9 | F10: =IF(C10=0,N9,IF(C10>1,M10)) -> 4155251.2 | G10: =B10-B9 -> 30 | H10: =DATE(YEAR(B10),12,31)-DATE(YEAR(B10),1,1)+1 -> 365 | I10: =I9 -> 2083333.3 | L10: =ROUND(C10*umumiy_malumot!$B$84/H10,2)*G10 -> 2071917.9 | M10: =D10+E10 -> 4155251.2 | O10: =TEXT(R10,"ддд") -> Ср | P10: =IF(O10=$U$8,2,IF(O10=$V$8,1,0)) -> 0 | Q10: =DAY(umumiy_malumot!$B$78)+P10 -> 20 | R10: =IF(A10<=umumiy_malumot!$B$81,DATE(YEAR($B$8),MONTH($B$8)+A9,DAY(umumiy_malumot!$B$78)),0) -> 46162
A11: 4 | B11: =IF(A11<=umumiy_malumot!$B$81,DATE(YEAR(R11),MONTH(R11),DAY(R11)+P11),0) -> 46195 | C11: =C10-D10 -> 43750000 | D11: =IF(C11=0,L11,IF(C11>1,I11)) -> 2083333.3 | E11: =IF(C11=0,N10,IF(C11>1,L11)) -> 2175513.8 | F11: =IF(C11=0,N10,IF(C11>1,M11)) -> 4258847.1 | G11: =B11-B10 -> 33 | H11: =DATE(YEAR(B11),12,31)-DATE(YEAR(B11),1,1)+1 -> 365 | I11: =I10 -> 2083333.3 | L11: =ROUND(C11*umumiy_malumot!$B$84/H11,2)*G11 -> 2175513.8 | M11: =D11+E11 -> 4258847.1 | O11: =TEXT(R11,"ддд") -> Сб | P11: =IF(O11=$U$8,2,IF(O11=$V$8,1,0)) -> 2 | Q11: =DAY(umumiy_malumot!$B$78)+P11 -> 22 | R11: =IF(A11<=umumiy_malumot!$B$81,DATE(YEAR($B$8),MONTH($B$8)+A10,DAY(umumiy_malumot!$B$78)),0) -> 46193
A12: 5 | B12: =IF(A12<=umumiy_malumot!$B$81,DATE(YEAR(R12),MONTH(R12),DAY(R12)+P12),0) -> 46223 | C12: =C11-D11 -> 41666667 | D12: =IF(C12=0,L12,IF(C12>1,I12)) -> 2083333.3 | E12: =IF(C12=0,N11,IF(C12>1,L12)) -> 1757990.9 | F12: =IF(C12=0,N11,IF(C12>1,M12)) -> 3841324.2 | G12: =B12-B11 -> 28 | H12: =DATE(YEAR(B12),12,31)-DATE(YEAR(B12),1,1)+1 -> 365 | I12: =I11 -> 2083333.3 | J12: =umumiy_malumot!B75 -> 50000000 | L12: =ROUND(C12*umumiy_malumot!$B$84/H12,2)*G12 -> 1757990.9 | M12: =D12+E12 -> 3841324.2 | O12: =TEXT(R12,"ддд") -> Пн | P12: =IF(O12=$U$8,2,IF(O12=$V$8,1,0)) -> 0 | Q12: =DAY(umumiy_malumot!$B$78)+P12 -> 20 | R12: =IF(A12<=umumiy_malumot!$B$81,DATE(YEAR($B$8),MONTH($B$8)+A11,DAY(umumiy_malumot!$B$78)),0) -> 46223
A13: 6 | B13: =IF(A13<=umumiy_malumot!$B$81,DATE(YEAR(R13),MONTH(R13),DAY(IF(A13=umumiy_malumot!$B$81,umumiy_malumot!$B$67,IF(A13<umumiy_malumot!$B$81,(Q13),IF(A13>umumiy_malumot!$B$81,$H$56,0)))))) -> 46254 | C13: =C12-D12 -> 39583333 | D13: =IF(C13=0,L13,IF(C13>1,I13)) -> 2083333.3 | E13: =IF(C13=0,N12,IF(C13>1,L13)) -> 1849029.7 | F13: =IF(C13=0,N12,IF(C13>1,M13)) -> 3932363 | G13: =B13-B12 -> 31 | H13: =DATE(YEAR(B13),12,31)-DATE(YEAR(B13),1,1)+1 -> 365 | I13: =IF(L5=H1,K13,IF(L5>H1,I12)) -> 2083333.3 | J13: =SUM($I$8:I12) -> 10416667 | K13: =$J$12-J13 -> 39583333 | L13: =ROUND(C13*umumiy_malumot!$B$84/H13,2)*G13 -> 1849029.7 | M13: =D13+E13 -> 3932363 | O13: =TEXT(R13,"ддд") -> Чт | P13: =IF(O13=$U$8,2,IF(O13=$V$8,1,0)) -> 0 | Q13: =DAY(umumiy_malumot!$B$78)+P13 -> 20 | R13: =IF(A13<=umumiy_malumot!$B$81,DATE(YEAR($B$8),MONTH($B$8)+A12,DAY(umumiy_malumot!$B$78)),0) -> 46254
A14: 7 | B14: =IF(A14<=umumiy_malumot!$B$81,DATE(YEAR(R14),MONTH(R14),DAY(IF(A14=umumiy_malumot!$B$81,umumiy_malumot!$B$67,IF(A14<umumiy_malumot!$B$81,(Q14),IF(A14>umumiy_malumot!$B$81,$H$56,0)))))) -> 46286 | C14: =C13-D13 -> 37500000 | D14: =IF(C14=0,L14,IF(C14>1,I14)) -> 2083333.3 | E14: =IF(C14=0,N13,IF(C14>1,L14)) -> 1808219.2 | F14: =IF(C14=0,N13,IF(C14>1,M14)) -> 3891552.5 | G14: =B14-B13 -> 32 | H14: =DATE(YEAR(B14),12,31)-DATE(YEAR(B14),1,1)+1 -> 365 | I14: =IF($L$5=A14,K14,IF($L$5>A14,I13)) -> 2083333.3 | J14: =SUM($I$8:I13) -> 12500000 | K14: =$J$12-J14 -> 37500000 | L14: =ROUND(C14*umumiy_malumot!$B$84/H14,2)*G14 -> 1808219.2 | M14: =D14+E14 -> 3891552.5 | O14: =TEXT(R14,"ддд") -> Вс | P14: =IF(O14=$U$8,2,IF(O14=$V$8,1,0)) -> 1 | Q14: =DAY(umumiy_malumot!$B$78)+P14 -> 21 | R14: =IF(A14<=umumiy_malumot!$B$81,DATE(YEAR($B$8),MONTH($B$8)+A13,DAY(umumiy_malumot!$B$78)),0) -> 46285
A15: 8 | B15: =IF(A15<=umumiy_malumot!$B$81,DATE(YEAR(R15),MONTH(R15),DAY(IF(A15=umumiy_malumot!$B$81,umumiy_malumot!$B$67,IF(A15<umumiy_malumot!$B$81,(Q15),IF(A15>umumiy_malumot!$B$81,$H$56,0)))))) -> 46315 | C15: =C14-D14 -> 35416667 | D15: =IF(C15=0,L15,IF(C15>1,I15)) -> 2083333.3 | E15: =IF(C15=0,N14,IF(C15>1,L15)) -> 1547659.8 | F15: =IF(C15=0,N14,IF(C15>1,M15)) -> 3630993.2 | G15: =B15-B14 -> 29 | H15: =DATE(YEAR(B15),12,31)-DATE(YEAR(B15),1,1)+1 -> 365 | I15: =IF($L$5=A15,K15,IF($L$5>A15,I14)) -> 2083333.3 | J15: =SUM($I$8:I14) -> 14583333 | K15: =$J$12-J15 -> 35416667 | L15: =ROUND(C15*umumiy_malumot!$B$84/H15,2)*G15 -> 1547659.8 | M15: =D15+E15 -> 3630993.2 | O15: =TEXT(R15,"ддд") -> Вт | P15: =IF(O15=$U$8,2,IF(O15=$V$8,1,0)) -> 0 | Q15: =DAY(umumiy_malumot!$B$78)+P15 -> 20 | R15: =IF(A15<=umumiy_malumot!$B$81,DATE(YEAR($B$8),MONTH($B$8)+A14,DAY(umumiy_malumot!$B$78)),0) -> 46315
A16: 9 | B16: =IF(A16<=umumiy_malumot!$B$81,DATE(YEAR(R16),MONTH(R16),DAY(IF(A16=umumiy_malumot!$B$81,umumiy_malumot!$B$67,IF(A16<umumiy_malumot!$B$81,(Q16),IF(A16>umumiy_malumot!$B$81,$H$56,0)))))) -> 46346 | C16: =C15-D15 -> 33333333 | D16: =IF(C16=0,L16,IF(C16>1,I16)) -> 2083333.3 | E16: =IF(C16=0,N15,IF(C16>1,L16)) -> 1557077.6 | F16: =IF(C16=0,N15,IF(C16>1,M16)) -> 3640410.9 | G16: =B16-B15 -> 31 | H16: =DATE(YEAR(B16),12,31)-DATE(YEAR(B16),1,1)+1 -> 365 | I16: =IF($L$5=A16,K16,IF($L$5>A16,I15)) -> 2083333.3 | J16: =SUM($I$8:I15) -> 16666667 | K16: =$J$12-J16 -> 33333333 | L16: =ROUND(C16*umumiy_malumot!$B$84/H16,2)*G16 -> 1557077.6 | M16: =D16+E16 -> 3640410.9 | O16: =TEXT(R16,"ддд") -> Пт | P16: =IF(O16=$U$8,2,IF(O16=$V$8,1,0)) -> 0 | Q16: =DAY(umumiy_malumot!$B$78)+P16 -> 20 | R16: =IF(A16<=umumiy_malumot!$B$81,DATE(YEAR($B$8),MONTH($B$8)+A15,DAY(umumiy_malumot!$B$78)),0) -> 46346
A17: 10 | B17: =IF(A17<=umumiy_malumot!$B$81,DATE(YEAR(R17),MONTH(R17),DAY(IF(A17=umumiy_malumot!$B$81,umumiy_malumot!$B$67,IF(A17<umumiy_malumot!$B$81,(Q17),IF(A17>umumiy_malumot!$B$81,$H$56,0)))))) -> 46377 | C17: =C16-D16 -> 31250000 | D17: =IF(C17=0,L17,IF(C17>1,I17)) -> 2083333.3 | E17: =IF(C17=0,N16,IF(C17>1,L17)) -> 1459760.2 | F17: =IF(C17=0,N16,IF(C17>1,M17)) -> 3543093.6 | G17: =B17-B16 -> 31 | H17: =DATE(YEAR(B17),12,31)-DATE(YEAR(B17),1,1)+1 -> 365 | I17: =IF($L$5=A17,K17,IF($L$5>A17,I16)) -> 2083333.3 | J17: =SUM($I$8:I16) -> 18750000 | K17: =$J$12-J17 -> 31250000 | L17: =ROUND(C17*umumiy_malumot!$B$84/H17,2)*G17 -> 1459760.2 | M17: =D17+E17 -> 3543093.6 | O17: =TEXT(R17,"ддд") -> Вс | P17: =IF(O17=$U$8,2,IF(O17=$V$8,1,0)) -> 1 | Q17: =DAY(umumiy_malumot!$B$78)+P17 -> 21 | R17: =IF(A17<=umumiy_malumot!$B$81,DATE(YEAR($B$8),MONTH($B$8)+A16,DAY(umumiy_malumot!$B$78)),0) -> 46376
A18: 11 | B18: =IF(A18<=umumiy_malumot!$B$81,DATE(YEAR(R18),MONTH(R18),DAY(IF(A18=umumiy_malumot!$B$81,umumiy_malumot!$B$67,IF(A18<umumiy_malumot!$B$81,(Q18),IF(A18>umumiy_malumot!$B$81,$H$56,0)))))) -> 46407 | C18: =C17-D17 -> 29166667 | D18: =IF(C18=0,L18,IF(C18>1,I18)) -> 2083333.3 | E18: =IF(C18=0,N17,IF(C18>1,L18)) -> 1318493.1 | F18: =IF(C18=0,N17,IF(C18>1,M18)) -> 3401826.4 | G18: =B18-B17 -> 30 | H18: =DATE(YEAR(B18),12,31)-DATE(YEAR(B18),1,1)+1 -> 365 | I18: =IF($L$5=A18,K18,IF($L$5>A18,I17)) -> 2083333.3 | J18: =SUM($I$8:I17) -> 20833333 | K18: =$J$12-J18 -> 29166667 | L18: =ROUND(C18*umumiy_malumot!$B$84/H18,2)*G18 -> 1318493.1 | M18: =D18+E18 -> 3401826.4 | O18: =TEXT(R18,"ддд") -> Ср | P18: =IF(O18=$U$8,2,IF(O18=$V$8,1,0)) -> 0 | Q18: =DAY(umumiy_malumot!$B$78)+P18 -> 20 | R18: =IF(A18<=umumiy_malumot!$B$81,DATE(YEAR($B$8),MONTH($B$8)+A17,DAY(umumiy_malumot!$B$78)),0) -> 46407
A19: 12 | B19: =IF(A19<=umumiy_malumot!$B$81,DATE(YEAR(R19),MONTH(R19),DAY(IF(A19=umumiy_malumot!$B$81,umumiy_malumot!$B$67,IF(A19<umumiy_malumot!$B$81,(Q19),IF(A19>umumiy_malumot!$B$81,$H$56,0)))))) -> 46440 | C19: =C18-D18 -> 27083333 | D19: =IF(C19=0,L19,IF(C19>1,I19)) -> 2083333.3 | E19: =IF(C19=0,N18,IF(C19>1,L19)) -> 1346746.5 | F19: =IF(C19=0,N18,IF(C19>1,M19)) -> 3430079.8 | G19: =B19-B18 -> 33 | H19: =DATE(YEAR(B19),12,31)-DATE(YEAR(B19),1,1)+1 -> 365 | I19: =IF($L$5=A19,K19,IF($L$5>A19,I18)) -> 2083333.3 | J19: =SUM($I$8:I18) -> 22916667 | K19: =$J$12-J19 -> 27083333 | L19: =ROUND(C19*umumiy_malumot!$B$84/H19,2)*G19 -> 1346746.5 | M19: =D19+E19 -> 3430079.8 | O19: =TEXT(R19,"ддд") -> Сб | P19: =IF(O19=$U$8,2,IF(O19=$V$8,1,0)) -> 2 | Q19: =DAY(umumiy_malumot!$B$78)+P19 -> 22 | R19: =IF(A19<=umumiy_malumot!$B$81,DATE(YEAR($B$8),MONTH($B$8)+A18,DAY(umumiy_malumot!$B$78)),0) -> 46438
A20: 13 | B20: =IF(A20<=umumiy_malumot!$B$81,DATE(YEAR(R20),MONTH(R20),DAY(IF(A20=umumiy_malumot!$B$81,umumiy_malumot!$B$67,IF(A20<umumiy_malumot!$B$81,(Q20),IF(A20>umumiy_malumot!$B$81,$H$56,0)))))) -> 46468 | C20: =C19-D19 -> 25000000 | D20: =IF(C20=0,L20,IF(C20>1,I20)) -> 2083333.3 | E20: =IF(C20=0,N19,IF(C20>1,L20)) -> 1054794.4 | F20: =IF(C20=0,N19,IF(C20>1,M20)) -> 3138127.8 | G20: =B20-B19 -> 28 | H20: =DATE(YEAR(B20),12,31)-DATE(YEAR(B20),1,1)+1 -> 365 | I20: =IF($L$5=A20,K20,IF($L$5>A20,I19)) -> 2083333.3 | J20: =SUM($I$8:I19) -> 25000000 | K20: =$J$12-J20 -> 25000000 | L20: =ROUND(C20*umumiy_malumot!$B$84/H20,2)*G20 -> 1054794.4 | M20: =D20+E20 -> 3138127.8 | O20: =TEXT(R20,"ддд") -> Сб | P20: =IF(O20=$U$8,2,IF(O20=$V$8,1,0)) -> 2 | Q20: =DAY(umumiy_malumot!$B$78)+P20 -> 22 | R20: =IF(A20<=umumiy_malumot!$B$81,DATE(YEAR($B$8),MONTH($B$8)+A19,DAY(umumiy_malumot!$B$78)),0) -> 46466
A21: 14 | B21: =IF(A21<=umumiy_malumot!$B$81,DATE(YEAR(R21),MONTH(R21),DAY(IF(A21=umumiy_malumot!$B$81,umumiy_malumot!$B$67,IF(A21<umumiy_malumot!$B$81,(Q21),IF(A21>umumiy_malumot!$B$81,$H$56,0)))))) -> 46497 | C21: =C20-D20 -> 22916667 | D21: =IF(C21=0,L21,IF(C21>1,I21)) -> 2083333.3 | E21: =IF(C21=0,N20,IF(C21>1,L21)) -> 1001426.8 | F21: =IF(C21=0,N20,IF(C21>1,M21)) -> 3084760.2 | G21: =B21-B20 -> 29 | H21: =DATE(YEAR(B21),12,31)-DATE(YEAR(B21),1,1)+1 -> 365 | I21: =IF($L$5=A21,K21,IF($L$5>A21,I20)) -> 2083333.3 | J21: =SUM($I$8:I20) -> 27083333 | K21: =$J$12-J21 -> 22916667 | L21: =ROUND(C21*umumiy_malumot!$B$84/H21,2)*G21 -> 1001426.8 | M21: =D21+E21 -> 3084760.2 | O21: =TEXT(R21,"ддд") -> Вт | P21: =IF(O21=$U$8,2,IF(O21=$V$8,1,0)) -> 0 | Q21: =DAY(umumiy_malumot!$B$78)+P21 -> 20 | R21: =IF(A21<=umumiy_malumot!$B$81,DATE(YEAR($B$8),MONTH($B$8)+A20,DAY(umumiy_malumot!$B$78)),0) -> 46497
A22: 15 | B22: =IF(A22<=umumiy_malumot!$B$81,DATE(YEAR(R22),MONTH(R22),DAY(IF(A22=umumiy_malumot!$B$81,umumiy_malumot!$B$67,IF(A22<umumiy_malumot!$B$81,(Q22),IF(A22>umumiy_malumot!$B$81,$H$56,0)))))) -> 46527 | C22: =C21-D21 -> 20833333 | D22: =IF(C22=0,L22,IF(C22>1,I22)) -> 2083333.3 | E22: =IF(C22=0,N21,IF(C22>1,L22)) -> 941780.7 | F22: =IF(C22=0,N21,IF(C22>1,M22)) -> 3025114 | G22: =B22-B21 -> 30 | H22: =DATE(YEAR(B22),12,31)-DATE(YEAR(B22),1,1)+1 -> 365 | I22: =IF($L$5=A22,K22,IF($L$5>A22,I21)) -> 2083333.3 | J22: =SUM($I$8:I21) -> 29166667 | K22: =$J$12-J22 -> 20833333 | L22: =ROUND(C22*umumiy_malumot!$B$84/H22,2)*G22 -> 941780.7 | M22: =D22+E22 -> 3025114 | O22: =TEXT(R22,"ддд") -> Чт | P22: =IF(O22=$U$8,2,IF(O22=$V$8,1,0)) -> 0 | Q22: =DAY(umumiy_malumot!$B$78)+P22 -> 20 | R22: =IF(A22<=umumiy_malumot!$B$81,DATE(YEAR($B$8),MONTH($B$8)+A21,DAY(umumiy_malumot!$B$78)),0) -> 46527
A23: 16 | B23: =IF(A23<=umumiy_malumot!$B$81,DATE(YEAR(R23),MONTH(R23),DAY(IF(A23=umumiy_malumot!$B$81,umumiy_malumot!$B$67,IF(A23<umumiy_malumot!$B$81,(Q23),IF(A23>umumiy_malumot!$B$81,$H$56,0)))))) -> 46559 | C23: =C22-D22 -> 18750000 | D23: =IF(C23=0,L23,IF(C23>1,I23)) -> 2083333.3 | E23: =IF(C23=0,N22,IF(C23>1,L23)) -> 904109.44 | F23: =IF(C23=0,N22,IF(C23>1,M23)) -> 2987442.8 | G23: =B23-B22 -> 32 | H23: =DATE(YEAR(B23),12,31)-DATE(YEAR(B23),1,1)+1 -> 365 | I23: =IF($L$5=A23,K23,IF($L$5>A23,I22)) -> 2083333.3 | J23: =SUM($I$8:I22) -> 31250000 | K23: =$J$12-J23 -> 18750000 | L23: =ROUND(C23*umumiy_malumot!$B$84/H23,2)*G23 -> 904109.44 | M23: =D23+E23 -> 2987442.8 | O23: =TEXT(R23,"ддд") -> Вс | P23: =IF(O23=$U$8,2,IF(O23=$V$8,1,0)) -> 1 | Q23: =DAY(umumiy_malumot!$B$78)+P23 -> 21 | R23: =IF(A23<=umumiy_malumot!$B$81,DATE(YEAR($B$8),MONTH($B$8)+A22,DAY(umumiy_malumot!$B$78)),0) -> 46558
A24: 17 | B24: =IF(A24<=umumiy_malumot!$B$81,DATE(YEAR(R24),MONTH(R24),DAY(IF(A24=umumiy_malumot!$B$81,umumiy_malumot!$B$67,IF(A24<umumiy_malumot!$B$81,(Q24),IF(A24>umumiy_malumot!$B$81,$H$56,0)))))) -> 46588 | C24: =C23-D23 -> 16666667 | D24: =IF(C24=0,L24,IF(C24>1,I24)) -> 2083333.3 | E24: =IF(C24=0,N23,IF(C24>1,L24)) -> 728310.64 | F24: =IF(C24=0,N23,IF(C24>1,M24)) -> 2811644 | G24: =B24-B23 -> 29 | H24: =DATE(YEAR(B24),12,31)-DATE(YEAR(B24),1,1)+1 -> 365 | I24: =IF($L$5=A24,K24,IF($L$5>A24,I23)) -> 2083333.3 | J24: =SUM($I$8:I23) -> 33333333 | K24: =$J$12-J24 -> 16666667 | L24: =ROUND(C24*umumiy_malumot!$B$84/H24,2)*G24 -> 728310.64 | M24: =D24+E24 -> 2811644 | O24: =TEXT(R24,"ддд") -> Вт | P24: =IF(O24=$U$8,2,IF(O24=$V$8,1,0)) -> 0 | Q24: =DAY(umumiy_malumot!$B$78)+P24 -> 20 | R24: =IF(A24<=umumiy_malumot!$B$81,DATE(YEAR($B$8),MONTH($B$8)+A23,DAY(umumiy_malumot!$B$78)),0) -> 46588
A25: 18 | B25: =IF(A25<=umumiy_malumot!$B$81,DATE(YEAR(R25),MONTH(R25),DAY(IF(A25=umumiy_malumot!$B$81,umumiy_malumot!$B$67,IF(A25<umumiy_malumot!$B$81,(Q25),IF(A25>umumiy_malumot!$B$81,$H$56,0)))))) -> 46619 | C25: =C24-D24 -> 14583333 | D25: =IF(C25=0,L25,IF(C25>1,I25)) -> 2083333.3 | E25: =IF(C25=0,N24,IF(C25>1,L25)) -> 681221.59 | F25: =IF(C25=0,N24,IF(C25>1,M25)) -> 2764554.9 | G25: =B25-B24 -> 31 | H25: =DATE(YEAR(B25),12,31)-DATE(YEAR(B25),1,1)+1 -> 365 | I25: =IF($L$5=A25,K25,IF($L$5>A25,I24)) -> 2083333.3 | J25: =SUM($I$8:I24) -> 35416667 | K25: =$J$12-J25 -> 14583333 | L25: =ROUND(C25*umumiy_malumot!$B$84/H25,2)*G25 -> 681221.59 | M25: =D25+E25 -> 2764554.9 | O25: =TEXT(R25,"ддд") -> Пт | P25: =IF(O25=$U$8,2,IF(O25=$V$8,1,0)) -> 0 | Q25: =DAY(umumiy_malumot!$B$78)+P25 -> 20 | R25: =IF(A25<=umumiy_malumot!$B$81,DATE(YEAR($B$8),MONTH($B$8)+A24,DAY(umumiy_malumot!$B$78)),0) -> 46619
... A31: 24 | B31: =IF(A31<=umumiy_malumot!$B$81,DATE(YEAR(R31),MONTH(R31),DAY(IF(A31=umumiy_malumot!$B$81,umumiy_malumot!$B$67,IF(A31<umumiy_malumot!$B$81,(Q31),IF(A31>umumiy_malumot!$B$81,$H$56,0)))))) -> 46785 | C31: =C30-D30 -> 2083333.4 | D31: =IF(C31=0,L31,IF(C31>1,I31)) -> 2083333.4 | E31: =IF(C31=0,N30,IF(C31>1,L31)) -> 40698.97 | F31: =IF(C31=0,N30,IF(C31>1,M31)) -> 2124032.4 | G31: =B31-B30 -> 13 | H31: =DATE(YEAR(B31),12,31)-DATE(YEAR(B31),1,1)+1 -> 366 | I31: =IF($L$5=A31,K31,IF($L$5>A31,I30)) -> 2083333.4 | J31: =SUM($I$8:I30) -> 47916667 | K31: =$J$12-J31 -> 2083333.4 | L31: =ROUND(C31*umumiy_malumot!$B$84/H31,2)*G31 -> 40698.97 | M31: =D31+E31 -> 2124032.4 | O31: =TEXT(R31,"ддд") -> Вс | P31: =IF(O31=$U$8,2,IF(O31=$V$8,1,0)) -> 1 | Q31: =DAY(umumiy_malumot!$B$78)+P31 -> 21 | R31: =IF(A31<=umumiy_malumot!$B$81,DATE(YEAR($B$8),MONTH($B$8)+A30,DAY(umumiy_malumot!$B$78)),0) -> 46803
A32: =1+A31 -> 25 | B32: =IF(A32<=umumiy_malumot!$B$81,DATE(YEAR(R32),MONTH(R32),DAY(IF(A32=umumiy_malumot!$B$81,umumiy_malumot!$B$67,IF(A32<umumiy_malumot!$B$81,(Q32),IF(A32>umumiy_malumot!$B$81,$H$56,0)))))) -> FALSE | C32: =C31-D31 -> 0 | D32: =IF(C32=0,L32,IF(C32>1,I32)) -> 0 | E32: =IF(C32=0,N31,IF(C32>1,L32)) -> 0 | F32: =IF(C32=0,N31,IF(C32>1,M32)) -> 0 | G32: =B32-B31 -> -46785 | H32: =DATE(YEAR(B32),12,31)-DATE(YEAR(B32),1,1)+1 -> 366 | I32: =IF($L$5=A32,K32,IF($L$5>A32,I31)) -> FALSE | J32: =SUM($I$8:I31) -> 50000000 | K32: =$J$12-J32 -> 0 | L32: =ROUND(C32*umumiy_malumot!$B$84/H32,2)*G32 -> 0 | M32: =D32+E32 -> 0 | O32: =TEXT(R32,"ддд") -> Сб | P32: =IF(O32=$U$8,2,IF(O32=$V$8,1,0)) -> 2 | Q32: =DAY(umumiy_malumot!$B$78)+P32 -> 22 | R32: =IF(A32<=umumiy_malumot!$B$81,DATE(YEAR($B$8),MONTH($B$8)+A31,DAY(umumiy_malumot!$B$78)),0) -> 0
A33: =1+A32 -> 26 | B33: =IF(A33<=umumiy_malumot!$B$81,DATE(YEAR(R33),MONTH(R33),DAY(IF(A33=umumiy_malumot!$B$81,umumiy_malumot!$B$67,IF(A33<umumiy_malumot!$B$81,(Q33),IF(A33>umumiy_malumot!$B$81,$H$56,0)))))) -> FALSE | C33: =C32-D32 -> 0 | D33: =IF(C33=0,L33,IF(C33>1,I33)) -> 0 | E33: =IF(C33=0,N32,IF(C33>1,L33)) -> 0 | F33: =IF(C33=0,N32,IF(C33>1,M33)) -> 0 | G33: =B33-B32 -> 0 | H33: =DATE(YEAR(B33),12,31)-DATE(YEAR(B33),1,1)+1 -> 366 | I33: =IF($L$5=A33,K33,IF($L$5>A33,I32)) -> FALSE | J33: =SUM($I$8:I32) -> 50000000 | K33: =$J$12-J33 -> 0 | L33: =ROUND(C33*umumiy_malumot!$B$84/H33,2)*G33 -> 0 | M33: =D33+E33 -> 0 | O33: =TEXT(R33,"ддд") -> Сб | P33: =IF(O33=$U$8,2,IF(O33=$V$8,1,0)) -> 2 | Q33: =DAY(umumiy_malumot!$B$78)+P33 -> 22 | R33: =IF(A33<=umumiy_malumot!$B$81,DATE(YEAR($B$8),MONTH($B$8)+A32,DAY(umumiy_malumot!$B$78)),0) -> 0
A34: =1+A33 -> 27 | B34: =IF(A34<=umumiy_malumot!$B$81,DATE(YEAR(R34),MONTH(R34),DAY(IF(A34=umumiy_malumot!$B$81,umumiy_malumot!$B$67,IF(A34<umumiy_malumot!$B$81,(Q34),IF(A34>umumiy_malumot!$B$81,$H$56,0)))))) -> FALSE | C34: =C33-D33 -> 0 | D34: =IF(C34=0,L34,IF(C34>1,I34)) -> 0 | E34: =IF(C34=0,N33,IF(C34>1,L34)) -> 0 | F34: =IF(C34=0,N33,IF(C34>1,M34)) -> 0 | G34: =B34-B33 -> 0 | H34: =DATE(YEAR(B34),12,31)-DATE(YEAR(B34),1,1)+1 -> 366 | I34: =IF($L$5=A34,K34,IF($L$5>A34,I33)) -> FALSE | J34: =SUM($I$8:I33) -> 50000000 | K34: =$J$12-J34 -> 0 | L34: =ROUND(C34*umumiy_malumot!$B$84/H34,2)*G34 -> 0 | M34: =D34+E34 -> 0 | O34: =TEXT(R34,"ддд") -> Сб | P34: =IF(O34=$U$8,2,IF(O34=$V$8,1,0)) -> 2 | Q34: =DAY(umumiy_malumot!$B$78)+P34 -> 22 | R34: =IF(A34<=umumiy_malumot!$B$81,DATE(YEAR($B$8),MONTH($B$8)+A33,DAY(umumiy_malumot!$B$78)),0) -> 0
A35: =1+A34 -> 28 | B35: =IF(A35<=umumiy_malumot!$B$81,DATE(YEAR(R35),MONTH(R35),DAY(IF(A35=umumiy_malumot!$B$81,umumiy_malumot!$B$67,IF(A35<umumiy_malumot!$B$81,(Q35),IF(A35>umumiy_malumot!$B$81,$H$56,0)))))) -> FALSE | C35: =C34-D34 -> 0 | D35: =IF(C35=0,L35,IF(C35>1,I35)) -> 0 | E35: =IF(C35=0,N34,IF(C35>1,L35)) -> 0 | F35: =IF(C35=0,N34,IF(C35>1,M35)) -> 0 | G35: =B35-B34 -> 0 | H35: =DATE(YEAR(B35),12,31)-DATE(YEAR(B35),1,1)+1 -> 366 | I35: =IF($L$5=A35,K35,IF($L$5>A35,I34)) -> FALSE | J35: =SUM($I$8:I34) -> 50000000 | K35: =$J$12-J35 -> 0 | L35: =ROUND(C35*umumiy_malumot!$B$84/H35,2)*G35 -> 0 | M35: =D35+E35 -> 0 | O35: =TEXT(R35,"ддд") -> Сб | P35: =IF(O35=$U$8,2,IF(O35=$V$8,1,0)) -> 2 | Q35: =DAY(umumiy_malumot!$B$78)+P35 -> 22 | R35: =IF(A35<=umumiy_malumot!$B$81,DATE(YEAR($B$8),MONTH($B$8)+A34,DAY(umumiy_malumot!$B$78)),0) -> 0
A36: =1+A35 -> 29 | B36: =IF(A36<=umumiy_malumot!$B$81,DATE(YEAR(R36),MONTH(R36),DAY(IF(A36=umumiy_malumot!$B$81,umumiy_malumot!$B$67,IF(A36<umumiy_malumot!$B$81,(Q36),IF(A36>umumiy_malumot!$B$81,$H$56,0)))))) -> FALSE | C36: =C35-D35 -> 0 | D36: =IF(C36=0,L36,IF(C36>1,I36)) -> 0 | E36: =IF(C36=0,N35,IF(C36>1,L36)) -> 0 | F36: =IF(C36=0,N35,IF(C36>1,M36)) -> 0 | G36: =B36-B35 -> 0 | H36: =DATE(YEAR(B36),12,31)-DATE(YEAR(B36),1,1)+1 -> 366 | I36: =IF($L$5=A36,K36,IF($L$5>A36,I35)) -> FALSE | J36: =SUM($I$8:I35) -> 50000000 | K36: =$J$12-J36 -> 0 | L36: =ROUND(C36*umumiy_malumot!$B$84/H36,2)*G36 -> 0 | M36: =D36+E36 -> 0 | O36: =TEXT(R36,"ддд") -> Сб | P36: =IF(O36=$U$8,2,IF(O36=$V$8,1,0)) -> 2 | Q36: =DAY(umumiy_malumot!$B$78)+P36 -> 22 | R36: =IF(A36<=umumiy_malumot!$B$81,DATE(YEAR($B$8),MONTH($B$8)+A35,DAY(umumiy_malumot!$B$78)),0) -> 0
A37: =1+A36 -> 30 | B37: =IF(A37<=umumiy_malumot!$B$81,DATE(YEAR(R37),MONTH(R37),DAY(IF(A37=umumiy_malumot!$B$81,umumiy_malumot!$B$67,IF(A37<umumiy_malumot!$B$81,(Q37),IF(A37>umumiy_malumot!$B$81,$H$56,0)))))) -> FALSE | C37: =C36-D36 -> 0 | D37: =IF(C37=0,L37,IF(C37>1,I37)) -> 0 | E37: =IF(C37=0,N36,IF(C37>1,L37)) -> 0 | F37: =IF(C37=0,N36,IF(C37>1,M37)) -> 0 | G37: =B37-B36 -> 0 | H37: =DATE(YEAR(B37),12,31)-DATE(YEAR(B37),1,1)+1 -> 366 | I37: =IF($L$5=A37,K37,IF($L$5>A37,I36)) -> FALSE | J37: =SUM($I$8:I36) -> 50000000 | K37: =$J$12-J37 -> 0 | L37: =ROUND(C37*umumiy_malumot!$B$84/H37,2)*G37 -> 0 | M37: =D37+E37 -> 0 | O37: =TEXT(R37,"ддд") -> Сб | P37: =IF(O37=$U$8,2,IF(O37=$V$8,1,0)) -> 2 | Q37: =DAY(umumiy_malumot!$B$78)+P37 -> 22 | R37: =IF(A37<=umumiy_malumot!$B$81,DATE(YEAR($B$8),MONTH($B$8)+A36,DAY(umumiy_malumot!$B$78)),0) -> 0
A38: =1+A37 -> 31 | B38: =IF(A38<=umumiy_malumot!$B$81,DATE(YEAR(R38),MONTH(R38),DAY(IF(A38=umumiy_malumot!$B$81,umumiy_malumot!$B$67,IF(A38<umumiy_malumot!$B$81,(Q38),IF(A38>umumiy_malumot!$B$81,$H$56,0)))))) -> FALSE | C38: =C37-D37 -> 0 | D38: =IF(C38=0,L38,IF(C38>1,I38)) -> 0 | E38: =IF(C38=0,N37,IF(C38>1,L38)) -> 0 | F38: =IF(C38=0,N37,IF(C38>1,M38)) -> 0 | G38: =B38-B37 -> 0 | H38: =DATE(YEAR(B38),12,31)-DATE(YEAR(B38),1,1)+1 -> 366 | I38: =IF($L$5=A38,K38,IF($L$5>A38,I37)) -> FALSE | J38: =SUM($I$8:I37) -> 50000000 | K38: =$J$12-J38 -> 0 | L38: =ROUND(C38*umumiy_malumot!$B$84/H38,2)*G38 -> 0 | M38: =D38+E38 -> 0 | O38: =TEXT(R38,"ддд") -> Сб | P38: =IF(O38=$U$8,2,IF(O38=$V$8,1,0)) -> 2 | Q38: =DAY(umumiy_malumot!$B$78)+P38 -> 22 | R38: =IF(A38<=umumiy_malumot!$B$81,DATE(YEAR($B$8),MONTH($B$8)+A37,DAY(umumiy_malumot!$B$78)),0) -> 0
A39: =1+A38 -> 32 | B39: =IF(A39<=umumiy_malumot!$B$81,DATE(YEAR(R39),MONTH(R39),DAY(IF(A39=umumiy_malumot!$B$81,umumiy_malumot!$B$67,IF(A39<umumiy_malumot!$B$81,(Q39),IF(A39>umumiy_malumot!$B$81,$H$56,0)))))) -> FALSE | C39: =C38-D38 -> 0 | D39: =IF(C39=0,L39,IF(C39>1,I39)) -> 0 | E39: =IF(C39=0,N38,IF(C39>1,L39)) -> 0 | F39: =IF(C39=0,N38,IF(C39>1,M39)) -> 0 | G39: =B39-B38 -> 0 | H39: =DATE(YEAR(B39),12,31)-DATE(YEAR(B39),1,1)+1 -> 366 | I39: =IF($L$5=A39,K39,IF($L$5>A39,I38)) -> FALSE | J39: =SUM($I$8:I38) -> 50000000 | K39: =$J$12-J39 -> 0 | L39: =ROUND(C39*umumiy_malumot!$B$84/H39,2)*G39 -> 0 | M39: =D39+E39 -> 0 | O39: =TEXT(R39,"ддд") -> Сб | P39: =IF(O39=$U$8,2,IF(O39=$V$8,1,0)) -> 2 | Q39: =DAY(umumiy_malumot!$B$78)+P39 -> 22 | R39: =IF(A39<=umumiy_malumot!$B$81,DATE(YEAR($B$8),MONTH($B$8)+A38,DAY(umumiy_malumot!$B$78)),0) -> 0
A40: =1+A39 -> 33 | B40: =IF(A40<=umumiy_malumot!$B$81,DATE(YEAR(R40),MONTH(R40),DAY(IF(A40=umumiy_malumot!$B$81,umumiy_malumot!$B$67,IF(A40<umumiy_malumot!$B$81,(Q40),IF(A40>umumiy_malumot!$B$81,$H$56,0)))))) -> FALSE | C40: =C39-D39 -> 0 | D40: =IF(C40=0,L40,IF(C40>1,I40)) -> 0 | E40: =IF(C40=0,N39,IF(C40>1,L40)) -> 0 | F40: =IF(C40=0,N39,IF(C40>1,M40)) -> 0 | G40: =B40-B39 -> 0 | H40: =DATE(YEAR(B40),12,31)-DATE(YEAR(B40),1,1)+1 -> 366 | I40: =IF($L$5=A40,K40,IF($L$5>A40,I39)) -> FALSE | J40: =SUM($I$8:I39) -> 50000000 | K40: =$J$12-J40 -> 0 | L40: =ROUND(C40*umumiy_malumot!$B$84/H40,2)*G40 -> 0 | M40: =D40+E40 -> 0 | O40: =TEXT(R40,"ддд") -> Сб | P40: =IF(O40=$U$8,2,IF(O40=$V$8,1,0)) -> 2 | Q40: =DAY(umumiy_malumot!$B$78)+P40 -> 22 | R40: =IF(A40<=umumiy_malumot!$B$81,DATE(YEAR($B$8),MONTH($B$8)+A39,DAY(umumiy_malumot!$B$78)),0) -> 0
A41: =1+A40 -> 34 | B41: =IF(A41<=umumiy_malumot!$B$81,DATE(YEAR(R41),MONTH(R41),DAY(IF(A41=umumiy_malumot!$B$81,umumiy_malumot!$B$67,IF(A41<umumiy_malumot!$B$81,(Q41),IF(A41>umumiy_malumot!$B$81,$H$56,0)))))) -> FALSE | C41: =C40-D40 -> 0 | D41: =IF(C41=0,L41,IF(C41>1,I41)) -> 0 | E41: =IF(C41=0,N40,IF(C41>1,L41)) -> 0 | F41: =IF(C41=0,N40,IF(C41>1,M41)) -> 0 | G41: =B41-B40 -> 0 | H41: =DATE(YEAR(B41),12,31)-DATE(YEAR(B41),1,1)+1 -> 366 | I41: =IF($L$5=A41,K41,IF($L$5>A41,I40)) -> FALSE | J41: =SUM($I$8:I40) -> 50000000 | K41: =$J$12-J41 -> 0 | L41: =ROUND(C41*umumiy_malumot!$B$84/H41,2)*G41 -> 0 | M41: =D41+E41 -> 0 | O41: =TEXT(R41,"ддд") -> Сб | P41: =IF(O41=$U$8,2,IF(O41=$V$8,1,0)) -> 2 | Q41: =DAY(umumiy_malumot!$B$78)+P41 -> 22 | R41: =IF(A41<=umumiy_malumot!$B$81,DATE(YEAR($B$8),MONTH($B$8)+A40,DAY(umumiy_malumot!$B$78)),0) -> 0
A42: =1+A41 -> 35 | B42: =IF(A42<=umumiy_malumot!$B$81,DATE(YEAR(R42),MONTH(R42),DAY(IF(A42=umumiy_malumot!$B$81,umumiy_malumot!$B$67,IF(A42<umumiy_malumot!$B$81,(Q42),IF(A42>umumiy_malumot!$B$81,$H$56,0)))))) -> FALSE | C42: =C41-D41 -> 0 | D42: =IF(C42=0,L42,IF(C42>1,I42)) -> 0 | E42: =IF(C42=0,N41,IF(C42>1,L42)) -> 0 | F42: =IF(C42=0,N41,IF(C42>1,M42)) -> 0 | G42: =B42-B41 -> 0 | H42: =DATE(YEAR(B42),12,31)-DATE(YEAR(B42),1,1)+1 -> 366 | I42: =IF($L$5=A42,K42,IF($L$5>A42,I41)) -> FALSE | J42: =SUM($I$8:I41) -> 50000000 | K42: =$J$12-J42 -> 0 | L42: =ROUND(C42*umumiy_malumot!$B$84/H42,2)*G42 -> 0 | M42: =D42+E42 -> 0 | O42: =TEXT(R42,"ддд") -> Сб | P42: =IF(O42=$U$8,2,IF(O42=$V$8,1,0)) -> 2 | Q42: =DAY(umumiy_malumot!$B$78)+P42 -> 22 | R42: =IF(A42<=umumiy_malumot!$B$81,DATE(YEAR($B$8),MONTH($B$8)+A41,DAY(umumiy_malumot!$B$78)),0) -> 0
A43: =1+A42 -> 36 | B43: =IF(A43<=umumiy_malumot!$B$81,DATE(YEAR(R43),MONTH(R43),DAY(IF(A43=umumiy_malumot!$B$81,umumiy_malumot!$B$67,IF(A43<umumiy_malumot!$B$81,(Q43),IF(A43>umumiy_malumot!$B$81,$H$56,0)))))) -> FALSE | C43: =C42-D42 -> 0 | D43: =IF(C43=0,L43,IF(C43>1,I43)) -> 0 | E43: =IF(C43=0,N42,IF(C43>1,L43)) -> 0 | F43: =IF(C43=0,N42,IF(C43>1,M43)) -> 0 | G43: =B43-B42 -> 0 | H43: =DATE(YEAR(B43),12,31)-DATE(YEAR(B43),1,1)+1 -> 366 | I43: =IF($L$5=A43,K43,IF($L$5>A43,I42)) -> FALSE | J43: =SUM($I$8:I42) -> 50000000 | K43: =$J$12-J43 -> 0 | L43: =ROUND(C43*umumiy_malumot!$B$84/H43,2)*G43 -> 0 | M43: =D43+E43 -> 0 | O43: =TEXT(R43,"ддд") -> Сб | P43: =IF(O43=$U$8,2,IF(O43=$V$8,1,0)) -> 2 | Q43: =DAY(umumiy_malumot!$B$78)+P43 -> 22 | R43: =IF(A43<=umumiy_malumot!$B$81,DATE(YEAR($B$8),MONTH($B$8)+A42,DAY(umumiy_malumot!$B$78)),0) -> 0
... A55: =1+A54 -> 48 | B55: =IF(A55<=umumiy_malumot!$B$81,DATE(YEAR(R55),MONTH(R55),DAY(IF(A55=umumiy_malumot!$B$81,umumiy_malumot!$B$67,IF(A55<umumiy_malumot!$B$81,(Q55),IF(A55>umumiy_malumot!$B$81,$H$56,0)))))) -> FALSE | C55: =C54-D54 -> 0 | D55: =IF(C55=0,L55,IF(C55>1,I55)) -> 0 | E55: =IF(C55=0,N54,IF(C55>1,L55)) -> 0 | F55: =IF(C55=0,N54,IF(C55>1,M55)) -> 0 | G55: =B55-B54 -> 0 | H55: =DATE(YEAR(B55),12,31)-DATE(YEAR(B55),1,1)+1 -> 366 | I55: =IF($L$5=A55,K55,IF($L$5>A55,I54)) -> FALSE | J55: =SUM($I$8:I54) -> 50000000 | K55: =$J$12-J55 -> 0 | L55: =ROUND(C55*umumiy_malumot!$B$84/H55,2)*G55 -> 0 | M55: =D55+E55 -> 0 | O55: =TEXT(R55,"ддд") -> Сб | P55: =IF(O55=$U$8,2,IF(O55=$V$8,1,0)) -> 2 | Q55: =DAY(umumiy_malumot!$B$78)+P55 -> 22 | R55: =IF(A55<=umumiy_malumot!$B$81,DATE(YEAR($B$8),MONTH($B$8)+A54,DAY(umumiy_malumot!$B$78)),0) -> 0
B56: ИТОГО | D56: =SUM(D8:D55) -> 50000000 | E56: =SUM(E8:E55) -> 29875784 | F56: =SUM(F8:F55) -> 79875784
A58: *В случае осуществления погашения платежей по кредиту в даты, отличные от указанных в графике погашения, сумма платежа меняется на сумму процентов, которые начисляются на сумму остатка долга по микрозайму в соответствии с п.п. 2.2. настоящего договора.
A60: =#REF! -> #REF! | D60: =#REF! -> #REF!
A62: =#REF! -> #REF! | D62: =#REF! -> #REF!
A63: =#REF! -> #REF! | D63: =#REF! -> #REF!
A64: =#REF! -> #REF! | D64: ="паспорт серии "&umumiy_malumot!B16&", "&umumiy_malumot!B20&"" -> паспорт серии AD 3925702, IIV 26266 tomonidan 12.07.2023 yilda berilgan
A65: =#REF! -> #REF!
A66: =#REF! -> #REF! | D66: =#REF! -> #REF!
A67: =#REF! -> #REF! | D67: =#REF! -> #REF!
A68: =#REF! -> #REF! | D68: =#REF! -> #REF!
A70: =#REF! -> #REF! | D70: =#REF! -> #REF!
A72: =#REF! -> #REF! | D72: =#REF! -> #REF!
D74: =#REF! -> #REF!

Sheet Данные для послед. Залога
A1: № | B1: - | E1: ФИО | F1: дата | L1: № договора | M1: Сог. Сумма | N1: сог. Сумма (пропис.)
A2: 1 | B2: ha | C2: yoq | D2: ha | E2: TULYAGANOV XODJIAKBAR IRGASHEVICH | F2: 44207 | G2: =MONTH(F2) -> 1 | H2: =IF(G2=$A$26,$A$28,IF(G2=$B$26,$B$28,IF(G2=$C$26,$C$28,IF(G2=$D$26,$D$28,IF(G2=$E$26,$E$28,IF(G2=$F$26,$F$28,IF(G2=$K$26,$K$28,IF(G2=$L$26,$L$28,IF(G2=$M$26,$M$28,IF(G2=$N$26,$N$28,IF(G2=$O$26,$O$28,IF(G2=$P$26,$P$28,0)))))))))))) -> yanvar | I2: =DAY(F2) -> 11 | J2: =YEAR(F2) -> 2021 | K2: =""&I2&" "&H2&" "&J2&" г." -> 11 yanvar 2021 г. | L2: 5 | M2: 15000000 | N2: on besh million | O2: ="- №"&L2&" от "&K2&", заключенного с ООО «Clever Mikrokredit Tashkiloti» и "&E2&", по согласованной залоговой стоимость - "&FIXED(M2)&" ("&N2&") сум." -> - №5 от 11 yanvar 2021 г., заключенного с ООО «Clever Mikrokredit Tashkiloti» и TULYAGANOV XODJIAKBAR IRGASHEVICH, по согласованной залоговой стоимость - 15 000 000,00 (on besh million) сум. | P2: =IF(D2=$B$2,O2,IF(D2=$C$2,$B$1)) -> - №5 от 11 yanvar 2021 г., заключенного с ООО «Clever Mikrokredit Tashkiloti» и TULYAGANOV XODJIAKBAR IRGASHEVICH, по согласованной залоговой стоимость - 15 000 000,00 (on besh million) сум. | W2: =""&P2&" "&P3&" "&P4&" "&P5&" "&P6&" "&P7&" "&P8&" "&P9&" "&P10&" "&P11&" "&P12&" "&P13&" "&P14&" "&P15&" "&P16&" "&P17&" "&P18&" "&P19&" "&P20&" "&P21&"" -> - №5 от 11 yanvar 2021 г., заключенного с ООО «Clever Mikrokredit Tashkiloti» и TULYAGANOV XODJIAKBAR IRGASHEVICH, по согласованной залоговой стоимость - 15 000 000,00 (on besh million) сум. - №386 от 6 noyabr 2019 г., заключенного с ООО «Clever Mikrokredit Tashkiloti» и YUNUSOVA ZALOXAT MIRSULTANOVNA, по согласованной залоговой стоимость - 15 000 000,00 (on besh million) сум. - №33 от 21 yanvar 2021 г., заключенного с ООО «Clever Mikrokredit Tashkiloti» и YUNUSOVA ZALOXAT MIRSULTANOVNA, по согласованной залоговой стоимость - 15 000 000,00 (on besh million) сум. 0 0 0 0 0 0 0 0 0 0 0 0 0 0 0 0 0
A3: 2 | D3: ha | E3: YUNUSOVA ZALOXAT MIRSULTANOVNA | F3: 43775 | G3: =MONTH(F3) -> 11 | H3: =IF(G3=$A$26,$A$28,IF(G3=$B$26,$B$28,IF(G3=$C$26,$C$28,IF(G3=$D$26,$D$28,IF(G3=$E$26,$E$28,IF(G3=$F$26,$F$28,IF(G3=$K$26,$K$28,IF(G3=$L$26,$L$28,IF(G3=$M$26,$M$28,IF(G3=$N$26,$N$28,IF(G3=$O$26,$O$28,IF(G3=$P$26,$P$28,0)))))))))))) -> noyabr | I3: =DAY(F3) -> 6 | J3: =YEAR(F3) -> 2019 | K3: =""&I3&" "&H3&" "&J3&" г." -> 6 noyabr 2019 г. | L3: 386 | M3: 15000000 | N3: on besh million | O3: ="- №"&L3&" от "&K3&", заключенного с ООО «Clever Mikrokredit Tashkiloti» и "&E3&", по согласованной залоговой стоимость - "&FIXED(M3)&" ("&N3&") сум." -> - №386 от 6 noyabr 2019 г., заключенного с ООО «Clever Mikrokredit Tashkiloti» и YUNUSOVA ZALOXAT MIRSULTANOVNA, по согласованной залоговой стоимость - 15 000 000,00 (on besh million) сум. | P3: =IF(D3=$B$2,O3,IF(D3=$C$2,$B$1)) -> - №386 от 6 noyabr 2019 г., заключенного с ООО «Clever Mikrokredit Tashkiloti» и YUNUSOVA ZALOXAT MIRSULTANOVNA, по согласованной залоговой стоимость - 15 000 000,00 (on besh million) сум.
A4: 3 | D4: ha | E4: YUNUSOVA ZALOXAT MIRSULTANOVNA | F4: 44217 | G4: =MONTH(F4) -> 1 | H4: =IF(G4=$A$26,$A$28,IF(G4=$B$26,$B$28,IF(G4=$C$26,$C$28,IF(G4=$D$26,$D$28,IF(G4=$E$26,$E$28,IF(G4=$F$26,$F$28,IF(G4=$K$26,$K$28,IF(G4=$L$26,$L$28,IF(G4=$M$26,$M$28,IF(G4=$N$26,$N$28,IF(G4=$O$26,$O$28,IF(G4=$P$26,$P$28,0)))))))))))) -> yanvar | I4: =DAY(F4) -> 21 | J4: =YEAR(F4) -> 2021 | K4: =""&I4&" "&H4&" "&J4&" г." -> 21 yanvar 2021 г. | L4: 33 | M4: 15000000 | N4: on besh million | O4: ="- №"&L4&" от "&K4&", заключенного с ООО «Clever Mikrokredit Tashkiloti» и "&E4&", по согласованной залоговой стоимость - "&FIXED(M4)&" ("&N4&") сум." -> - №33 от 21 yanvar 2021 г., заключенного с ООО «Clever Mikrokredit Tashkiloti» и YUNUSOVA ZALOXAT MIRSULTANOVNA, по согласованной залоговой стоимость - 15 000 000,00 (on besh million) сум. | P4: =IF(D4=$B$2,O4,IF(D4=$C$2,$B$1)) -> - №33 от 21 yanvar 2021 г., заключенного с ООО «Clever Mikrokredit Tashkiloti» и YUNUSOVA ZALOXAT MIRSULTANOVNA, по согласованной залоговой стоимость - 15 000 000,00 (on besh million) сум.
A5: 4 | D5: ha | G5: =MONTH(F5) -> 1 | H5: =IF(G5=$A$26,$A$28,IF(G5=$B$26,$B$28,IF(G5=$C$26,$C$28,IF(G5=$D$26,$D$28,IF(G5=$E$26,$E$28,IF(G5=$F$26,$F$28,IF(G5=$K$26,$K$28,IF(G5=$L$26,$L$28,IF(G5=$M$26,$M$28,IF(G5=$N$26,$N$28,IF(G5=$O$26,$O$28,IF(G5=$P$26,$P$28,0)))))))))))) -> yanvar | I5: =DAY(F5) -> 0 | J5: =YEAR(F5) -> 1900 | K5: =""&I5&" "&H5&" "&J5&" г." -> 0 yanvar 1900 г. | P5: =IF(D5=$B$2,O5,IF(D5=$C$2,$B$1)) -> 0
A6: 5 | D6: ha | G6: =MONTH(F6) -> 1 | H6: =IF(G6=$A$26,$A$28,IF(G6=$B$26,$B$28,IF(G6=$C$26,$C$28,IF(G6=$D$26,$D$28,IF(G6=$E$26,$E$28,IF(G6=$F$26,$F$28,IF(G6=$K$26,$K$28,IF(G6=$L$26,$L$28,IF(G6=$M$26,$M$28,IF(G6=$N$26,$N$28,IF(G6=$O$26,$O$28,IF(G6=$P$26,$P$28,0)))))))))))) -> yanvar | I6: =DAY(F6) -> 0 | J6: =YEAR(F6) -> 1900 | K6: =""&I6&" "&H6&" "&J6&" г." -> 0 yanvar 1900 г. | P6: =IF(D6=$B$2,O6,IF(D6=$C$2,$B$1)) -> 0
A7: 6 | D7: ha | G7: =MONTH(F7) -> 1 | H7: =IF(G7=$A$26,$A$28,IF(G7=$B$26,$B$28,IF(G7=$C$26,$C$28,IF(G7=$D$26,$D$28,IF(G7=$E$26,$E$28,IF(G7=$F$26,$F$28,IF(G7=$K$26,$K$28,IF(G7=$L$26,$L$28,IF(G7=$M$26,$M$28,IF(G7=$N$26,$N$28,IF(G7=$O$26,$O$28,IF(G7=$P$26,$P$28,0)))))))))))) -> yanvar | I7: =DAY(F7) -> 0 | J7: =YEAR(F7) -> 1900 | K7: =""&I7&" "&H7&" "&J7&" г." -> 0 yanvar 1900 г. | P7: =IF(D7=$B$2,O7,IF(D7=$C$2,$B$1)) -> 0
A8: 7 | D8: ha | G8: =MONTH(F8) -> 1 | H8: =IF(G8=$A$26,$A$28,IF(G8=$B$26,$B$28,IF(G8=$C$26,$C$28,IF(G8=$D$26,$D$28,IF(G8=$E$26,$E$28,IF(G8=$F$26,$F$28,IF(G8=$K$26,$K$28,IF(G8=$L$26,$L$28,IF(G8=$M$26,$M$28,IF(G8=$N$26,$N$28,IF(G8=$O$26,$O$28,IF(G8=$P$26,$P$28,0)))))))))))) -> yanvar | I8: =DAY(F8) -> 0 | J8: =YEAR(F8) -> 1900 | K8: =""&I8&" "&H8&" "&J8&" г." -> 0 yanvar 1900 г. | P8: =IF(D8=$B$2,O8,IF(D8=$C$2,$B$1)) -> 0
A9: 8 | D9: ha | G9: =MONTH(F9) -> 1 | H9: =IF(G9=$A$26,$A$28,IF(G9=$B$26,$B$28,IF(G9=$C$26,$C$28,IF(G9=$D$26,$D$28,IF(G9=$E$26,$E$28,IF(G9=$F$26,$F$28,IF(G9=$K$26,$K$28,IF(G9=$L$26,$L$28,IF(G9=$M$26,$M$28,IF(G9=$N$26,$N$28,IF(G9=$O$26,$O$28,IF(G9=$P$26,$P$28,0)))))))))))) -> yanvar | I9: =DAY(F9) -> 0 | J9: =YEAR(F9) -> 1900 | K9: =""&I9&" "&H9&" "&J9&" г." -> 0 yanvar 1900 г. | P9: =IF(D9=$B$2,O9,IF(D9=$C$2,$B$1)) -> 0
A10: 9 | D10: ha | G10: =MONTH(F10) -> 1 | H10: =IF(G10=$A$26,$A$28,IF(G10=$B$26,$B$28,IF(G10=$C$26,$C$28,IF(G10=$D$26,$D$28,IF(G10=$E$26,$E$28,IF(G10=$F$26,$F$28,IF(G10=$K$26,$K$28,IF(G10=$L$26,$L$28,IF(G10=$M$26,$M$28,IF(G10=$N$26,$N$28,IF(G10=$O$26,$O$28,IF(G10=$P$26,$P$28,0)))))))))))) -> yanvar | I10: =DAY(F10) -> 0 | J10: =YEAR(F10) -> 1900 | K10: =""&I10&" "&H10&" "&J10&" г." -> 0 yanvar 1900 г. | P10: =IF(D10=$B$2,O10,IF(D10=$C$2,$B$1)) -> 0
A11: 10 | D11: ha | G11: =MONTH(F11) -> 1 | H11: =IF(G11=$A$26,$A$28,IF(G11=$B$26,$B$28,IF(G11=$C$26,$C$28,IF(G11=$D$26,$D$28,IF(G11=$E$26,$E$28,IF(G11=$F$26,$F$28,IF(G11=$K$26,$K$28,IF(G11=$L$26,$L$28,IF(G11=$M$26,$M$28,IF(G11=$N$26,$N$28,IF(G11=$O$26,$O$28,IF(G11=$P$26,$P$28,0)))))))))))) -> yanvar | I11: =DAY(F11) -> 0 | J11: =YEAR(F11) -> 1900 | K11: =""&I11&" "&H11&" "&J11&" г." -> 0 yanvar 1900 г. | P11: =IF(D11=$B$2,O11,IF(D11=$C$2,$B$1)) -> 0
A12: 11 | D12: ha | G12: =MONTH(F12) -> 1 | H12: =IF(G12=$A$26,$A$28,IF(G12=$B$26,$B$28,IF(G12=$C$26,$C$28,IF(G12=$D$26,$D$28,IF(G12=$E$26,$E$28,IF(G12=$F$26,$F$28,IF(G12=$K$26,$K$28,IF(G12=$L$26,$L$28,IF(G12=$M$26,$M$28,IF(G12=$N$26,$N$28,IF(G12=$O$26,$O$28,IF(G12=$P$26,$P$28,0)))))))))))) -> yanvar | I12: =DAY(F12) -> 0 | J12: =YEAR(F12) -> 1900 | K12: =""&I12&" "&H12&" "&J12&" г." -> 0 yanvar 1900 г. | P12: =IF(D12=$B$2,O12,IF(D12=$C$2,$B$1)) -> 0
A13: 12 | D13: ha | G13: =MONTH(F13) -> 1 | H13: =IF(G13=$A$26,$A$28,IF(G13=$B$26,$B$28,IF(G13=$C$26,$C$28,IF(G13=$D$26,$D$28,IF(G13=$E$26,$E$28,IF(G13=$F$26,$F$28,IF(G13=$K$26,$K$28,IF(G13=$L$26,$L$28,IF(G13=$M$26,$M$28,IF(G13=$N$26,$N$28,IF(G13=$O$26,$O$28,IF(G13=$P$26,$P$28,0)))))))))))) -> yanvar | I13: =DAY(F13) -> 0 | J13: =YEAR(F13) -> 1900 | K13: =""&I13&" "&H13&" "&J13&" г." -> 0 yanvar 1900 г. | P13: =IF(D13=$B$2,O13,IF(D13=$C$2,$B$1)) -> 0
A14: 13 | D14: ha | G14: =MONTH(F14) -> 1 | H14: =IF(G14=$A$26,$A$28,IF(G14=$B$26,$B$28,IF(G14=$C$26,$C$28,IF(G14=$D$26,$D$28,IF(G14=$E$26,$E$28,IF(G14=$F$26,$F$28,IF(G14=$K$26,$K$28,IF(G14=$L$26,$L$28,IF(G14=$M$26,$M$28,IF(G14=$N$26,$N$28,IF(G14=$O$26,$O$28,IF(G14=$P$26,$P$28,0)))))))))))) -> yanvar | I14: =DAY(F14) -> 0 | J14: =YEAR(F14) -> 1900 | K14: =""&I14&" "&H14&" "&J14&" г." -> 0 yanvar 1900 г. | P14: =IF(D14=$B$2,O14,IF(D14=$C$2,$B$1)) -> 0
A15: 14 | D15: ha | G15: =MONTH(F15) -> 1 | H15: =IF(G15=$A$26,$A$28,IF(G15=$B$26,$B$28,IF(G15=$C$26,$C$28,IF(G15=$D$26,$D$28,IF(G15=$E$26,$E$28,IF(G15=$F$26,$F$28,IF(G15=$K$26,$K$28,IF(G15=$L$26,$L$28,IF(G15=$M$26,$M$28,IF(G15=$N$26,$N$28,IF(G15=$O$26,$O$28,IF(G15=$P$26,$P$28,0)))))))))))) -> yanvar | I15: =DAY(F15) -> 0 | J15: =YEAR(F15) -> 1900 | K15: =""&I15&" "&H15&" "&J15&" г." -> 0 yanvar 1900 г. | P15: =IF(D15=$B$2,O15,IF(D15=$C$2,$B$1)) -> 0
A16: 15 | D16: ha | G16: =MONTH(F16) -> 1 | H16: =IF(G16=$A$26,$A$28,IF(G16=$B$26,$B$28,IF(G16=$C$26,$C$28,IF(G16=$D$26,$D$28,IF(G16=$E$26,$E$28,IF(G16=$F$26,$F$28,IF(G16=$K$26,$K$28,IF(G16=$L$26,$L$28,IF(G16=$M$26,$M$28,IF(G16=$N$26,$N$28,IF(G16=$O$26,$O$28,IF(G16=$P$26,$P$28,0)))))))))))) -> yanvar | I16: =DAY(F16) -> 0 | J16: =YEAR(F16) -> 1900 | K16: =""&I16&" "&H16&" "&J16&" г." -> 0 yanvar 1900 г. | P16: =IF(D16=$B$2,O16,IF(D16=$C$2,$B$1)) -> 0
... A21: 20 | D21: ha | G21: =MONTH(F21) -> 1 | H21: =IF(G21=$A$26,$A$28,IF(G21=$B$26,$B$28,IF(G21=$C$26,$C$28,IF(G21=$D$26,$D$28,IF(G21=$E$26,$E$28,IF(G21=$F$26,$F$28,IF(G21=$K$26,$K$28,IF(G21=$L$26,$L$28,IF(G21=$M$26,$M$28,IF(G21=$N$26,$N$28,IF(G21=$O$26,$O$28,IF(G21=$P$26,$P$28,0)))))))))))) -> yanvar | I21: =DAY(F21) -> 0 | J21: =YEAR(F21) -> 1900 | K21: =""&I21&" "&H21&" "&J21&" г." -> 0 yanvar 1900 г. | P21: =IF(D21=$B$2,O21,IF(D21=$C$2,$B$1)) -> 0
M22: =SUM(M2:M21)+umumiy_malumot!B136 -> 115000000 | Q22: ottiz yetti million besh yuz ming
A25: =MONTH(F2) -> 1 | B25: =IF(A25=A26,A28,IF(A25=B26,B28,IF(A25=C26,C28,IF(A25=D26,D28,IF(A25=E26,E28,IF(A25=F26,F28,IF(A25=K26,K28,IF(A25=L26,L28,IF(A25=M26,M28,IF(A25=N26,N28,IF(A25=O26,O28,IF(A25=#REF!,#REF!,)))))))))))) -> yanvar | C25: =DAY(F2) -> 11 | D25: =YEAR(F2) -> 2021
A26: 1 | B26: 2 | C26: 3 | D26: 4 | E26: 5 | F26: 6 | K26: 7 | L26: 8 | M26: 9 | N26: 10 | O26: 11 | P26: 12
A28: yanvar | B28: fevral | C28: mart | D28: aprel | E28: may | F28: iyun | K28: июля | L28: avgust | M28: sentyabr | N28: oktyabr | O28: noyabr | P28: dekabr
A29: yanvar | B29: fevral | C29: mart | D29: aprel | E29: may | F29: iyun | K29: июль | L29: avgust | M29: sentyabr | N29: oktyabr | O29: noyabr | P29: dekabr

Sheet umumiy_malumot
A1: =CONCATENATE(B65," olish uchun ariza") -> Mikroqarz olish uchun ariza | B1: №43
A2: =CONCATENATE(B65," olish uchun ariza sanasi QO’L BILAN KIRITILADI") -> Mikroqarz olish uchun ariza sanasi QO’L BILAN KIRITILADI | B2: 02.02.2026 | D2: =180+B2 -> 46235
A4: Qarz oluvchi bo’yicha ma’lumotlar
A5: Ariza beruvchining FISh (kim? – Ibragimov Rustam Sadikovich) | B5: SIMONYAN VADIM ROMANOVICH
A6: agar o’zgarishlar bo’lgan bo’lsa oldingi FISh (Sadikov Rustam Sadikovich yoki yo’q) | B6: yo’q | C6: ha | D6: yo’q
A7: Ariza beruvchining FISh (kim? – Ibragimov R.S.) | B7: SIMONYAN V. R.
A8: FISh (ariza kimdan? – Ibragimov Rustam Sadikovichdan) | B8: =B5 -> SIMONYAN VADIM ROMANOVICH
A9: FISh (kimdan? – Ibragimov R.S.dan) | B9: =B7 -> SIMONYAN V. R.
A10: FISh (kimga? – Ibragimov Rustam Sadikovichga) | B10: =B8 -> SIMONYAN VADIM ROMANOVICH
A11: FISh (kimga? – Ibragimov R.S.ga) | B11: =B9 -> SIMONYAN V. R.
A12: FISh (kim bilan? – Ibragimov Rustam Sadikovich bilan) | B12: =B10 -> SIMONYAN VADIM ROMANOVICH
A13: FISh (kim bilan? – Ibragimov R.S. bilan) | B13: =B11 -> SIMONYAN V. R.
A14: Fuqaroligi (O’zbekiston Respublikasi) | B14: O’zbekiston Respublikasi
A15: Tug’ilgan sanasi (01.10.2011 yil) | B15: 14.12.1968 yil
A16: Pasport seriyasi (СА №1234567) | B16: AD 3925702
B17: IIV 26266 | D17: =TEXT(C17,"ДД.ММ.ГГГГ") -> 00.01.1900
B18: 45119 | C18: =TEXT(B18,"ДД.ММ.ГГГГ") -> 12.07.2023
B19: =DATE(YEAR(B18)+10,MONTH(B18),DAY(B18)-1) -> 48771 | C19: =TEXT(B19,"ДД.ММ.ГГГГ") -> 11.07.2033
A20: Kim va qachon berilgan (Toshkent shahri Chilonzor IIB tomonidan 2011 yil __.____) | B20: =""&B17&" tomonidan "&C18&" yilda berilgan" -> IIV 26266 tomonidan 12.07.2023 yilda berilgan | C20: =""&B17&" tomonidan "&C18&" yilda berilgan" -> IIV 26266 tomonidan 12.07.2023 yilda berilgan
A21: Pasportni amal qilish muddati (01.10.2011 yilgacha / yoki muddatsiz) | B21: =""&C19&" y." -> 11.07.2033 y. | C21: =""&C19&" yilgacha" -> 11.07.2033 yilgacha
A22: doimiy ro’yhatdan o’tgan joyi (Toshkent sh., Mirobod tumani, Nukus ko’chasi, 1 uy, 1 honadon) | B22: TOSHKENT SHAHAR YUNUSOBOD TUMANI OTCHOPAR-1 MFY KARIM ZARIPOV KO'CHASI 8-6 UY
A23: doimiy ro’yhatdan o’tgan joyi haqiqatdagi turar joyi bilan mos keladi/mos kelmaydi | B23: mos keladi | C23: mos keladi | D23: mos kelmaydi
A24: Ro’yhatdan o’tish joyida yashash asosi | B24: Mulk huquqi | C24: Mulk huquqi | D24: ijara | E24: служебная | F24: другое | G24: -
A25: Telefon raqami kod bilan ((99871) 277 77 77) | B25: 93 554 55 99 MIJOZ
A26: Mo’ljal | B26: CHINOBOD SANATORIY SANTINI
B27: =IF(B23="mos keladi",B22,B28) -> TOSHKENT SHAHAR YUNUSOBOD TUMANI OTCHOPAR-1 MFY KARIM ZARIPOV KO'CHASI 8-6 UY
A28: Haqiqatdagi yashash joyi (Toshkent sh., Mirobod tumani, Nukus ko’chasi, 1 uy, 1 honadon) | B28: TOSHKENT SHAHAR YUNUSOBOD TUMANI OTCHOPAR-1 MFY KARIM ZARIPOV KO'CHASI 8-6 UY
A29: Haqiqatdagi yashash joyida turish asosi | B29: Mulk huquqi | C29: Mulk huquqi | D29: ijara | E29: xizmat | F29: boshqa | G29: -
A30: Mijozning jinsi | B30: erkak | C30: erkak | D30: ayol
A31: Tug’ilgan joyi (Toshkent) | B31: TOSHKENT
A32: Fuqaroligi (O’zbekiston Respublikasi) | B32: O’zbekiston Respublikasi
A33: Telefon raqami kod bilan ((99871) 277 77 77) | B33: =B25 -> 93 554 55 99 MIJOZ
B34: =IF(B23="mos keladi",B26,B35) -> CHINOBOD SANATORIY SANTINI
A35: Mo’ljal
A36: Oilaviy ahvoli
A37: Oila a'zolari soni (jami):
A38: Ma’lumoti
A39: Mutaxassisligi
A40: Ish telefoni raqami kod bilan ((99890) 3270000) | B40: =B33 -> 93 554 55 99 MIJOZ
A41: Mobil telefon raqami kod bilan ((99890) 3270000) | B41: 99 899 80 88 JIYANI
A42: Ish telefoni raqami kod bilan ((99890) 3270000) | B42: 71 212 15 05 UY
A43: Mobil telefon raqami kod bilan ((99890) 3270000)
A44: Asosiy ish joyi | B44: Yakka tartibdagi tadbirkor | C44: Yakka tartibdagi tadbirkor | D44: O'Z O'ZINI BAND QILGAN FUQARO
B45: =IF(B44=D44,CONCATENATE("MA'LUMOTNOMA ",B47,B46),C44) -> Yakka tartibdagi tadbirkor
A46: O'Z O'ZINI BAND QILGAN BO'LSA, MA'LUMOTNOMA KIRITING
C47: (MA'LUMOTNOMA №
A48: AGAR O'Z O'ZINI BAND QILGAN FUQARO BO'LSA FAOLIYAT TURINI KIRITING
A49: Lavozimi | B49: =IF(B44=C44,C44,B48) -> Yakka tartibdagi tadbirkor
A50: Tashkilotning haqiqiy manzili (Toshkent sh., Mirobod tumani, Nukus ko’chasi, 1 uy, 1 honadon)
A51: Mo’ljal
A52: Ish staji, sanasidan (01.10.2011 yildan)
A53: Umumiy mehnat staji (3 yil/ 5 yil)
A54: Ish joyi telefon raqami
A55: Mijozning STIRi
A56: Mijozning unikal kodi | B56: 990000__
A57: QARZ OLUVCHINING ISH JOYI, LAVOZIMI VA O'RTACHA OYLIK DAROMADI
A58: Ish joyi | B58: =IF(B44=C44,C44,CONCATENATE(B44," ",B47)) -> Yakka tartibdagi tadbirkor
A59: Lavozimi | B59: =B49 -> Yakka tartibdagi tadbirkor
A60: O’rtacha oylik daromadi | B60: 10000000
A61: Mijozning boshqa daromadlari | B61: 5000000
A62: Ishning davomiyligi | B62: =B53 -> 0
A63: Ish joyidan ma’lumotnomaning raqami va sanasi
A64: Kredit bo’yicha parametrlar | C64: Mikrokredit | D64: Mikroqarz
A65: Kredit turi | B65: =IF(B75>100000001,"Mikrokredit",IF(B75<100000001,"Mikroqarz",0)) -> Mikroqarz | C65: =DATE(YEAR(B67),MONTH(B67)+B81,DAY(B67)) -> 46785
A66: Kredit shartnomasi raqami | B66: =B1 -> №43 | C66: =MONTH(C65) -> 2 | D66: =IF(C66=C68,C70,IF(C66=D68,D70,IF(C66=E68,E70,IF(C66=F68,F70,IF(C66=G68,G70,IF(C66=H68,H70,IF(C66=I68,I70,IF(C66=J68,J70,IF(C66=K68,K70,IF(C66=L68,L70,IF(C66=M68,M70,IF(C66=N68,N70,)))))))))))) -> fevral | E66: =DAY(C65) -> 2 | F66: =YEAR(C65) -> 2028 | G66: =MONTH(C65) -> 2 | H66: =IF(C66=C68,C71,IF(C66=D68,D71,IF(C66=E68,E71,IF(C66=F68,F71,IF(C66=G68,G71,IF(C66=H68,H71,IF(C66=I68,I71,IF(C66=J68,J71,IF(C66=K68,K71,IF(C66=L68,L71,IF(C66=M68,M71,IF(C66=N68,N71,)))))))))))) -> fevral | I66: =YEAR(C65) -> 2028
A67: Kredit shartnomasi sanasi (14.10.2011) | B67: =B2 -> 02.02.2026 | C67: =MONTH(B67) -> 2 | D67: =IF(C67=C68,C70,IF(C67=D68,D70,IF(C67=E68,E70,IF(C67=F68,F70,IF(C67=G68,G70,IF(C67=H68,H70,IF(C67=I68,I70,IF(C67=J68,J70,IF(C67=K68,K70,IF(C67=L68,L70,IF(C67=M68,M70,IF(C67=N68,N70,)))))))))))) -> fevral | E67: =DAY(B67) -> 2 | F67: =YEAR(B67) -> 2026 | G67: =MONTH(B67) -> 2 | H67: =IF(C67=C68,C71,IF(C67=D68,D71,IF(C67=E68,E71,IF(C67=F68,F71,IF(C67=G68,G71,IF(C67=H68,H71,IF(C67=I68,I71,IF(C67=J68,J71,IF(C67=K68,K71,IF(C67=L68,L71,IF(C67=M68,M71,IF(C67=N68,N71,)))))))))))) -> fevral | I67: =YEAR(B67) -> 2026
A68: Kredit shartnomasi sanasi (14.10.2011 y.) | B68: =""&E67&" "&D67&" "&F67&" y." -> 2 fevral 2026 y. | C68: 1 | D68: 2 | E68: 3 | F68: 4 | G68: 5 | H68: 6 | I68: 7 | J68: 8 | K68: 9 | L68: 10 | M68: 11 | N68: 12
B69: =""&E67&" "&H67&" "&F67&" y." -> 2 fevral 2026 y.
B70: =B68 -> 2 fevral 2026 y. | C70: yanvar | D70: fevral | E70: mart | F70: aprel | G70: may | H70: iyun | I70: iyul | J70: avgust | K70: sentabr | L70: oktabr | M70: noyabr | N70: dekabr
B71: =B69 -> 2 fevral 2026 y. | C71: yanvar | D71: fevral | E71: mart | F71: aprel | G71: may | H71: iyun | I71: iyul | J71: avgust | K71: sentabr | L71: oktabr | M71: noyabr | N71: dekabr
A72: Tugash sanasi QO’L BILAN KIRITILADI | B72: =""&E66&" "&D66&" "&F66&" y." -> 2 fevral 2028 y.
B73: =""&E66&" "&H66&" "&F66&" y." -> 2 fevral 2028 y.
A74: Kredit shartnomasi raqami va sanasi | B74: =""&B68&"dan "&B66&"" -> 2 fevral 2026 y.dan №43
A75: =CONCATENATE(B65," miqdori (summasi)") -> Mikroqarz miqdori (summasi) | B75: 50000000 | C75: Uzbek tilida
A76: QO’L BILAN KIRITILADI | B76: =C76 -> Ellik million so'm | C76: =UPPER(LEFT(SUBSTITUTE(SUBSTITUTE(SUBSTITUTE(TRIM(SUBSTITUTE(SUBSTITUTE(SUBSTITUTE(SUBSTITUTE(SUBSTITUTE(SUBSTITUTE(SUBSTITUTE(SUBSTITUTE(SUBSTITUTE(SUBSTITUTE(SUBSTITUTE(SUBSTITUTE(SUBSTITUTE(SUBSTITUTE(SUBSTITUTE(SUBSTITUTE(SUBSTITUTE(SUBSTITUTE(SUBSTITUTE(SUBSTITUTE(SUBSTITUTE(SUBSTITUTE(SUBSTITUTE(SUBSTITUTE(SUBSTITUTE(SUBSTITUTE(SUBSTITUTE(SUBSTITUTE(SUBSTITUTE(SUBSTITUTE(SUBSTITUTE(SUBSTITUTE(SUBSTITUTE(SUBSTITUTE(SUBSTITUTE(SUBSTITUTE(SUBSTITUTE(SUBSTITUTE(SUBSTITUTE(SUBSTITUTE(SUBSTITUTE(SUBSTITUTE(SUBSTITUTE(SUBSTITUTE(SUBSTITUTE(SUBSTITUTE(SUBSTITUTE(SUBSTITUTE(IF(LEN(ROUNDDOWN(B75,0))>6,ROMAN(MID(ROUNDDOWN(B75,0),1,LEN(ROUNDDOWN(B75,0))-6)+0)&" million "&ROMAN(MID(ROUNDDOWN(B75,0),LEN(ROUNDDOWN(B75,0))-5,3)+0)&" ming "&ROMAN(MID(ROUNDDOWN(B75,0),LEN(ROUNDDOWN(B75,0))-2,3)+0)&" so'm",IF(LEN(ROUNDDOWN(B75,0))>3,ROMAN(MID(ROUNDDOWN(B75,0),1,LEN(ROUNDDOWN(B75,0))-3)+0)&" ming "&ROMAN(MID(ROUNDDOWN(B75,0),LEN(ROUNDDOWN(B75,0))-2,3)+0)&" so'm",ROMAN(ROUNDDOWN(B75,0))&" so'm")),"DCCC"," sakkiz yuz"),"DCC"," yetti yuz"),"DC"," olti yuz"),"CD"," to'rt yuz"),"XC"," to'qson"),"CCC"," uch yuz"),"CC"," ikki yuz"),"D"," besh yuz"),"CM"," to'qqiz yuz"),"C"," yuz"),"XL"," qiriq"),"LXXX"," sakson"),"LXX"," yetmish"),"LX"," oltmish"),"L"," ellik"),"XXX"," o'ttiz"),"XX"," yigirma"),"XIX"," o'n tiqqiz"),"XVIII"," o'n sakkiz"),"XVII"," o'n yetti"),"XVI"," o'n olti"),"XV"," o'n besh"),"XIV"," o'n to'rt"),"XIII"," o'n uch"),"XII"," o'n ikki"),"XI"," o'n bir"),"IX"," to'qqiz"),"X"," o'n"),"VIII"," sakkiz"),"VII"," yetti"),"VI"," olti"),"IV"," to'rt"),"V"," besh"),"III"," uch"),"II"," ikki"),"I"," bir"),"bir ming","bir ming"),"ikki ming","ikki ming"),"uch ming","uch ming"),"to'rt ming","to'rt ming"),"bir million","bir million"),"ikki million","ikki million"),"uch million","uch million"),"to'rt million","to'rt million"),"bir so'm","bir so'm"),"ikki so'm","ikki so'm"),"uch so'm","uch so'm"),"to'rt so'm","to'rt so'm")),"ming million","million"),"ming million","million"),"ming million","million"),1))&MID(SUBSTITUTE(SUBSTITUTE(SUBSTITUTE(TRIM(SUBSTITUTE(SUBSTITUTE(SUBSTITUTE(SUBSTITUTE(SUBSTITUTE(SUBSTITUTE(SUBSTITUTE(SUBSTITUTE(SUBSTITUTE(SUBSTITUTE(SUBSTITUTE(SUBSTITUTE(SUBSTITUTE(SUBSTITUTE(SUBSTITUTE(SUBSTITUTE(SUBSTITUTE(SUBSTITUTE(SUBSTITUTE(SUBSTITUTE(SUBSTITUTE(SUBSTITUTE(SUBSTITUTE(SUBSTITUTE(SUBSTITUTE(SUBSTITUTE(SUBSTITUTE(SUBSTITUTE(SUBSTITUTE(SUBSTITUTE(SUBSTITUTE(SUBSTITUTE(SUBSTITUTE(SUBSTITUTE(SUBSTITUTE(SUBSTITUTE(SUBSTITUTE(SUBSTITUTE(SUBSTITUTE(SUBSTITUTE(SUBSTITUTE(SUBSTITUTE(SUBSTITUTE(SUBSTITUTE(SUBSTITUTE(SUBSTITUTE(SUBSTITUTE(SUBSTITUTE(IF(LEN(ROUNDDOWN(B75,0))>6,ROMAN(MID(ROUNDDOWN(B75,0),1,LEN(ROUNDDOWN(B75,0))-6)+0)&" million "&ROMAN(MID(ROUNDDOWN(B75,0),LEN(ROUNDDOWN(B75,0))-5,3)+0)&" "&ROMAN(MID(ROUNDDOWN(B75,0),LEN(ROUNDDOWN(B75,0))-2,3)+0)&" so'm",IF(LEN(ROUNDDOWN(B75,0))>3,ROMAN(MID(ROUNDDOWN(B75,0),1,LEN(ROUNDDOWN(B75,0))-3)+0)&" ming "&ROMAN(MID(ROUNDDOWN(B75,0),LEN(ROUNDDOWN(B75,0))-2,3)+0)&" so'm",ROMAN(ROUNDDOWN(B75,0))&" so'm")),"DCCC"," sakkiz yuz"),"DCC"," yetti yuz"),"DC"," olti yuz"),"CD"," to'rt yuz"),"XC"," to'qson"),"CCC"," uch yuz"),"CC"," ikki yuz"),"D"," besh yuz"),"CM"," to'qqiz yuz"),"C"," yuz"),"XL"," qirq"),"LXXX"," sakson"),"LXX"," yetmish"),"LX"," oltmish"),"L"," ellik"),"XXX"," o'ttiz"),"XX"," yigirma"),"XIX"," o'n to'qqiz"),"XVIII"," o'n sakkiz"),"XVII"," o'n yetti"),"XVI"," o'n olti"),"XV"," o'n besh"),"XIV"," o'n to'rt"),"XIII"," o'n uch"),"XII"," o'n ikki"),"XI"," o'n bir"),"IX"," to'qqiz"),"X"," o'n"),"VIII"," sakkiz"),"VII"," yetti"),"VI"," olti"),"IV"," to'rt"),"V"," besh"),"III"," uch"),"II"," ikki"),"I"," bir"),"bir ming","bir ming"),"ikki ming","ikki ming"),"uch ming","uch ming"),"to'rt ming","to'rt ming"),"bir million","bir million"),"ikki million","ikki million"),"uch million","uch million"),"to'rt million","to'rt million"),"bir so'm","bir so'm"),"ikki so'm","ikki so'm"),"uch so'm","uch so'm"),"to'rt so'm","to'rt so'm")),"ming million","million"),"ming million","million"),"ming million","million"),2,200)&"" -> Ellik million so'm
A77: Grafik turi | B77: annuitet | C77: differensial | D77: annuitet
A78: =CONCATENATE(B65,"ni to'lash sanasi (14.10.2011)") -> Mikroqarzni to'lash sanasi (14.10.2011) | B78: 20 | C78: =DATE(YEAR(B67),MONTH(B67)+1,DAY(B78)) -> 46101 | D78: Пн | E78: Вт | F78: Ср | G78: Чт | H78: Пт | I78: Сб | J78: Вс
A79: =CONCATENATE(B65,"ni to'lash sanasi (14.10.2011 y.) QO’L BILAN KIRITILADI") -> Mikroqarzni to'lash sanasi (14.10.2011 y.) QO’L BILAN KIRITILADI | B79: =DATE(YEAR(B67),MONTH(B67)+1,DAY(B78+C80)) -> 46101 | C79: =TEXT(C78,"ддд") -> Пт | D79: Пн | E79: Вт | F79: Ср | G79: Чт | H79: Пт | I79: Сб | J79: Вс
A80: Mikroqarzni to'lash sanasi (14.10.2011 y.) QO’L BILAN KIRITILADI | B80: =B79 -> 46101 | C80: =IF(C79=I79,2,IF(C79=J79,1,0)) -> 0
A81: =CONCATENATE(B65," muddati") -> Mikroqarz muddati | B81: 24 | C81: 6 | D81: 12 | E81: 16 | F81: 18 | G81: 24 | H81: 28 | I81: 30 | J81: 36 | M81: 48
A82: =CONCATENATE(B65," muddati QO’L BILAN KIRITILADI") -> Mikroqarz muddati QO’L BILAN KIRITILADI | B82: =IF(B81=C81,"olti",IF(B81=D81,"o'n ikki",IF(B81=E81,"o'n sakkiz",IF(B81=F81,"o'n sakkiz",IF(B81=G81,"yigirma to'rt",IF(B81=H81,"yigirma sakkiz",IF(B81=I81,"o'ttiz",IF(B81=J81,"o'ttiz olti",IF(B81=M81,"qirq sakkiz",0))))))))) -> yigirma to'rt | C82: o'lti | D82: o'n ikki | E82: o'n olti | F82: o'n sakkiz | G82: yigirma to'rt | H82: yigirma sakkiz | I82: o'ttiz | J82: o'ttiz olti | M82: qirq sakkiz
A83: Imtiyozli davr | B83: 0 | BJ83: 1 | BK83: 0
A84: =CONCATENATE(B65," stavkasi") -> Mikroqarz stavkasi | B84: 0.55
A85: =CONCATENATE(B65," stavkasi") -> Mikroqarz stavkasi | B85: 50
A86: =CONCATENATE(B65," stavkasi (so’z bilan)") -> Mikroqarz stavkasi (so’z bilan) | B86: =UPPER(LEFT(SUBSTITUTE(SUBSTITUTE(SUBSTITUTE(TRIM(SUBSTITUTE(SUBSTITUTE(SUBSTITUTE(SUBSTITUTE(SUBSTITUTE(SUBSTITUTE(SUBSTITUTE(SUBSTITUTE(SUBSTITUTE(SUBSTITUTE(SUBSTITUTE(SUBSTITUTE(SUBSTITUTE(SUBSTITUTE(SUBSTITUTE(SUBSTITUTE(SUBSTITUTE(SUBSTITUTE(SUBSTITUTE(SUBSTITUTE(SUBSTITUTE(SUBSTITUTE(SUBSTITUTE(SUBSTITUTE(SUBSTITUTE(SUBSTITUTE(SUBSTITUTE(SUBSTITUTE(SUBSTITUTE(SUBSTITUTE(SUBSTITUTE(SUBSTITUTE(SUBSTITUTE(SUBSTITUTE(SUBSTITUTE(SUBSTITUTE(SUBSTITUTE(SUBSTITUTE(SUBSTITUTE(SUBSTITUTE(SUBSTITUTE(SUBSTITUTE(SUBSTITUTE(SUBSTITUTE(SUBSTITUTE(SUBSTITUTE(SUBSTITUTE(SUBSTITUTE(IF(LEN(ROUNDDOWN(B85,0))>6,ROMAN(MID(ROUNDDOWN(B85,0),1,LEN(ROUNDDOWN(B85,0))-6)+0)&" million "&ROMAN(MID(ROUNDDOWN(B85,0),LEN(ROUNDDOWN(B85,0))-5,3)+0)&" ming "&ROMAN(MID(ROUNDDOWN(B85,0),LEN(ROUNDDOWN(B85,0))-2,3)+0)&"",IF(LEN(ROUNDDOWN(B85,0))>3,ROMAN(MID(ROUNDDOWN(B85,0),1,LEN(ROUNDDOWN(B85,0))-3)+0)&" ming "&ROMAN(MID(ROUNDDOWN(B85,0),LEN(ROUNDDOWN(B85,0))-2,3)+0)&"",ROMAN(ROUNDDOWN(B85,0))&"")),"DCCC"," sakkiz yuz"),"DCC"," yetti yuz"),"DC"," olti yuz"),"CD"," to'rt yuz"),"XC"," to'qson"),"CCC"," uch yuz"),"CC"," ikki yuz"),"D"," besh yuz"),"CM"," to'qqiz yuz"),"C"," yuz"),"XL"," qiriq"),"LXXX"," sakson"),"LXX"," yetmish"),"LX"," oltmish"),"L"," ellik"),"XXX"," o'ttiz"),"XX"," yigirma"),"XIX"," o'n tiqqiz"),"XVIII"," o'n sakkiz"),"XVII"," o'n yetti"),"XVI"," o'n olti"),"XV"," o'n besh"),"XIV"," o'n to'rt"),"XIII"," o'n uch"),"XII"," o'n ikki"),"XI"," o'n bir"),"IX"," to'qqiz"),"X"," o'n"),"VIII"," sakkiz"),"VII"," yetti"),"VI"," olti"),"IV"," to'rt"),"V"," besh"),"III"," uch"),"II"," ikki"),"I"," bir"),"bir ming","bir ming"),"ikki ming","ikki ming"),"uch ming","uch ming"),"to'rt ming","to'rt ming"),"bir million","bir million"),"ikki million","ikki million"),"uch million","uch million"),"to'rt million","to'rt million"),"bir","bir"),"ikki","ikki"),"uch","uch"),"to'rt","to'rt")),"ming million","million"),"ming million","million"),"ming million","million"),1))&MID(SUBSTITUTE(SUBSTITUTE(SUBSTITUTE(TRIM(SUBSTITUTE(SUBSTITUTE(SUBSTITUTE(SUBSTITUTE(SUBSTITUTE(SUBSTITUTE(SUBSTITUTE(SUBSTITUTE(SUBSTITUTE(SUBSTITUTE(SUBSTITUTE(SUBSTITUTE(SUBSTITUTE(SUBSTITUTE(SUBSTITUTE(SUBSTITUTE(SUBSTITUTE(SUBSTITUTE(SUBSTITUTE(SUBSTITUTE(SUBSTITUTE(SUBSTITUTE(SUBSTITUTE(SUBSTITUTE(SUBSTITUTE(SUBSTITUTE(SUBSTITUTE(SUBSTITUTE(SUBSTITUTE(SUBSTITUTE(SUBSTITUTE(SUBSTITUTE(SUBSTITUTE(SUBSTITUTE(SUBSTITUTE(SUBSTITUTE(SUBSTITUTE(SUBSTITUTE(SUBSTITUTE(SUBSTITUTE(SUBSTITUTE(SUBSTITUTE(SUBSTITUTE(SUBSTITUTE(SUBSTITUTE(SUBSTITUTE(SUBSTITUTE(SUBSTITUTE(IF(LEN(ROUNDDOWN(B85,0))>6,ROMAN(MID(ROUNDDOWN(B85,0),1,LEN(ROUNDDOWN(B85,0))-6)+0)&" million "&ROMAN(MID(ROUNDDOWN(B85,0),LEN(ROUNDDOWN(B85,0))-5,3)+0)&" "&ROMAN(MID(ROUNDDOWN(B85,0),LEN(ROUNDDOWN(B85,0))-2,3)+0)&"",IF(LEN(ROUNDDOWN(B85,0))>3,ROMAN(MID(ROUNDDOWN(B85,0),1,LEN(ROUNDDOWN(B85,0))-3)+0)&" ming "&ROMAN(MID(ROUNDDOWN(B85,0),LEN(ROUNDDOWN(B85,0))-2,3)+0)&"",ROMAN(ROUNDDOWN(B85,0))&"")),"DCCC"," sakkiz yuz"),"DCC"," yetti yuz"),"DC"," olti yuz"),"CD"," to'rt yuz"),"XC"," to'qson"),"CCC"," uch yuz"),"CC"," ikki yuz"),"D"," besh yuz"),"CM"," to'qqiz yuz"),"C"," yuz"),"XL"," qirq"),"LXXX"," sakson"),"LXX"," yetmish"),"LX"," oltmish"),"L"," ellik"),"XXX"," o'ttiz"),"XX"," yigirma"),"XIX"," o'n to'qqiz"),"XVIII"," o'n sakkiz"),"XVII"," o'n yetti"),"XVI"," o'n olti"),"XV"," o'n besh"),"XIV"," o'n to'rt"),"XIII"," o'n uch"),"XII"," o'n ikki"),"XI"," o'n bir"),"IX"," to'qqiz"),"X"," o'n"),"VIII"," sakkiz"),"VII"," yetti"),"VI"," olti"),"IV"," to'rt"),"V"," besh"),"III"," uch"),"II"," ikki"),"I"," bir"),"bir ming","bir ming"),"ikki ming","ikki ming"),"uch ming","uch ming"),"to'rt ming","to'rt ming"),"bir million","bir million"),"ikki million","ikki million"),"uch million","uch million"),"to'rt million","to'rt million"),"bir","bir"),"ikki","ikki"),"uch","uch"),"to'rt","to'rt")),"ming million","million"),"ming million","million"),"ming million","million"),2,200)&" "&SUBSTITUTE(SUBSTITUTE(SUBSTITUTE(SUBSTITUTE(SUBSTITUTE(SUBSTITUTE(SUBSTITUTE(SUBSTITUTE(RIGHT(TEXT(B85," "),2)&"","1","1"),"2","2"),"3","3"),"4","4"),"11","11"),"12","12"),"13","13"),"14","14") -> Ellik | C86: =UPPER(LEFT(SUBSTITUTE(SUBSTITUTE(SUBSTITUTE(TRIM(SUBSTITUTE(SUBSTITUTE(SUBSTITUTE(SUBSTITUTE(SUBSTITUTE(SUBSTITUTE(SUBSTITUTE(SUBSTITUTE(SUBSTITUTE(SUBSTITUTE(SUBSTITUTE(SUBSTITUTE(SUBSTITUTE(SUBSTITUTE(SUBSTITUTE(SUBSTITUTE(SUBSTITUTE(SUBSTITUTE(SUBSTITUTE(SUBSTITUTE(SUBSTITUTE(SUBSTITUTE(SUBSTITUTE(SUBSTITUTE(SUBSTITUTE(SUBSTITUTE(SUBSTITUTE(SUBSTITUTE(SUBSTITUTE(SUBSTITUTE(SUBSTITUTE(SUBSTITUTE(SUBSTITUTE(SUBSTITUTE(SUBSTITUTE(SUBSTITUTE(SUBSTITUTE(SUBSTITUTE(SUBSTITUTE(SUBSTITUTE(SUBSTITUTE(SUBSTITUTE(SUBSTITUTE(SUBSTITUTE(SUBSTITUTE(SUBSTITUTE(SUBSTITUTE(SUBSTITUTE(IF(LEN(ROUNDDOWN(B85,0))>6,ROMAN(MID(ROUNDDOWN(B85,0),1,LEN(ROUNDDOWN(B85,0))-6)+0)&" million "&ROMAN(MID(ROUNDDOWN(B85,0),LEN(ROUNDDOWN(B85,0))-5,3)+0)&" ming "&ROMAN(MID(ROUNDDOWN(B85,0),LEN(ROUNDDOWN(B85,0))-2,3)+0)&"",IF(LEN(ROUNDDOWN(B85,0))>3,ROMAN(MID(ROUNDDOWN(B85,0),1,LEN(ROUNDDOWN(B85,0))-3)+0)&" ming "&ROMAN(MID(ROUNDDOWN(B85,0),LEN(ROUNDDOWN(B85,0))-2,3)+0)&"",ROMAN(ROUNDDOWN(B85,0))&"")),"DCCC"," sakkiz yuz"),"DCC"," yetti yuz"),"DC"," olti yuz"),"CD"," to'rt yuz"),"XC"," to'qson"),"CCC"," uch yuz"),"CC"," ikki yuz"),"D"," besh yuz"),"CM"," to'qqiz yuz"),"C"," yuz"),"XL"," qiriq"),"LXXX"," sakson"),"LXX"," yetmish"),"LX"," oltmish"),"L"," ellik"),"XXX"," o'ttiz"),"XX"," yigirma"),"XIX"," o'n tiqqiz"),"XVIII"," o'n sakkiz"),"XVII"," o'n yetti"),"XVI"," o'n olti"),"XV"," o'n besh"),"XIV"," o'n to'rt"),"XIII"," o'n uch"),"XII"," o'n ikki"),"XI"," o'n bir"),"IX"," to'qqiz"),"X"," o'n"),"VIII"," sakkiz"),"VII"," yetti"),"VI"," olti"),"IV"," to'rt"),"V"," besh"),"III"," uch"),"II"," ikki"),"I"," bir"),"bir ming","bir ming"),"ikki ming","ikki ming"),"uch ming","uch ming"),"to'rt ming","to'rt ming"),"bir million","bir million"),"ikki million","ikki million"),"uch million","uch million"),"to'rt million","to'rt million"),"bir","bir"),"ikki","ikki"),"uch","uch"),"to'rt","to'rt")),"ming million","million"),"ming million","million"),"ming million","million"),1))&MID(SUBSTITUTE(SUBSTITUTE(SUBSTITUTE(TRIM(SUBSTITUTE(SUBSTITUTE(SUBSTITUTE(SUBSTITUTE(SUBSTITUTE(SUBSTITUTE(SUBSTITUTE(SUBSTITUTE(SUBSTITUTE(SUBSTITUTE(SUBSTITUTE(SUBSTITUTE(SUBSTITUTE(SUBSTITUTE(SUBSTITUTE(SUBSTITUTE(SUBSTITUTE(SUBSTITUTE(SUBSTITUTE(SUBSTITUTE(SUBSTITUTE(SUBSTITUTE(SUBSTITUTE(SUBSTITUTE(SUBSTITUTE(SUBSTITUTE(SUBSTITUTE(SUBSTITUTE(SUBSTITUTE(SUBSTITUTE(SUBSTITUTE(SUBSTITUTE(SUBSTITUTE(SUBSTITUTE(SUBSTITUTE(SUBSTITUTE(SUBSTITUTE(SUBSTITUTE(SUBSTITUTE(SUBSTITUTE(SUBSTITUTE(SUBSTITUTE(SUBSTITUTE(SUBSTITUTE(SUBSTITUTE(SUBSTITUTE(SUBSTITUTE(SUBSTITUTE(IF(LEN(ROUNDDOWN(B85,0))>6,ROMAN(MID(ROUNDDOWN(B85,0),1,LEN(ROUNDDOWN(B85,0))-6)+0)&" million "&ROMAN(MID(ROUNDDOWN(B85,0),LEN(ROUNDDOWN(B85,0))-5,3)+0)&" "&ROMAN(MID(ROUNDDOWN(B85,0),LEN(ROUNDDOWN(B85,0))-2,3)+0)&"",IF(LEN(ROUNDDOWN(B85,0))>3,ROMAN(MID(ROUNDDOWN(B85,0),1,LEN(ROUNDDOWN(B85,0))-3)+0)&" ming "&ROMAN(MID(ROUNDDOWN(B85,0),LEN(ROUNDDOWN(B85,0))-2,3)+0)&"",ROMAN(ROUNDDOWN(B85,0))&"")),"DCCC"," sakkiz yuz"),"DCC"," yetti yuz"),"DC"," olti yuz"),"CD"," to'rt yuz"),"XC"," to'qson"),"CCC"," uch yuz"),"CC"," ikki yuz"),"D"," besh yuz"),"CM"," to'qqiz yuz"),"C"," yuz"),"XL"," qirq"),"LXXX"," sakson"),"LXX"," yetmish"),"LX"," oltmish"),"L"," ellik"),"XXX"," o'ttiz"),"XX"," yigirma"),"XIX"," o'n to'qqiz"),"XVIII"," o'n sakkiz"),"XVII"," o'n yetti"),"XVI"," o'n olti"),"XV"," o'n besh"),"XIV"," o'n to'rt"),"XIII"," o'n uch"),"XII"," o'n ikki"),"XI"," o'n bir"),"IX"," to'qqiz"),"X"," o'n"),"VIII"," sakkiz"),"VII"," yetti"),"VI"," olti"),"IV"," to'rt"),"V"," besh"),"III"," uch"),"II"," ikki"),"I"," bir"),"bir ming","bir ming"),"ikki ming","ikki ming"),"uch ming","uch ming"),"to'rt ming","to'rt ming"),"bir million","bir million"),"ikki million","ikki million"),"uch million","uch million"),"to'rt million","to'rt million"),"bir","bir"),"ikki","ikki"),"uch","uch"),"to'rt","to'rt")),"ming million","million"),"ming million","million"),"ming million","million"),2,200)&" "&SUBSTITUTE(SUBSTITUTE(SUBSTITUTE(SUBSTITUTE(SUBSTITUTE(SUBSTITUTE(SUBSTITUTE(SUBSTITUTE(RIGHT(TEXT(B85," "),2)&"","1","1"),"2","2"),"3","3"),"4","4"),"11","11"),"12","12"),"13","13"),"14","14") -> Ellik
A87: =CONCATENATE("Muddati o'tgan ",B65," bo’yicha stavka") -> Muddati o'tgan Mikroqarz bo’yicha stavka | B87: 1.55
A88: QO’L BILAN KIRITILADI | B88: 155
A89: =CONCATENATE("Muddati o'tgan ",B65," bo’yicha stavka") -> Muddati o'tgan Mikroqarz bo’yicha stavka | B89: bir yuz ellik besh | C89: bir yuz ellik besh | D89: besh
A90: Oylik to'lov | B90: =IF(B77=C77,LARGE(grafik!F9:F26,1),ROUND(PMT(B84/12,B81,-B75,0),-3)) -> 3478000
A91: GAROV BO’YICHA MA’LUMOTLAR
B92: Birlamchi | C92: Birlamchi | D92: navbatdagi garov
A93: Garovga beruvchi mulkdormi? | B93: Ha | C93: Ha | D93: yo’q
A94: Agar garovga beruvchi qarz oluvchi bo'lmasa, garovga kim qo'yganligini ko'rsating | B94: Garovga beruvchining o’zi | C94: Garovga beruvchining o’zi | D94: Bosh ishonchnoma bo’yicha boshqa shaxs
A95: Bosh ishonchnoma bo’yicha bo’lsa FIShni ko’rsating
A96: Bosh ishonchnoma bo’yicha bo’lsa FIShni ko’rsating qisqacha
A97: ISHONCHNOMA BO’YICHA MA’LUMOTLAR
A98: Notarius manzili (Toshkent shahri, Olmazor tumani)
A99: Kim tomonidan berilgan (Notariusning FISh – Eshkabilov X.B.)
A100: Ishonchnoma reestr raqami
A101: Ishonchnoma berilgan sana
...

Sheet График аннуитет.
E1: Приложение №1
F2: ="к договору микрозайма "&umumiy_malumot!B74&"" -> к договору микрозайма 2 fevral 2026 y.dan №43
A4: График погашения
A6: № | B6: Дата погашения | C6: Остаток основного долга | D6: Сумма погашения, сум
D7: основного долга | E7: процентов* | F7: всего*
A8: 1 | B8: ='График дифференц'!B8 -> 46101 | C8: =umumiy_malumot!B75 -> 50000000 | D8: =IF(A8<umumiy_malumot!$B$81,'График аннуитет.'!F8-'График аннуитет.'!E8,'График аннуитет.'!C8) -> 12246.38 | E8: =ROUND(C8*umumiy_malumot!$B$84/H8,2)*'График аннуитет.'!G8 -> 3465753.6 | F8: =umumiy_malumot!B90 -> 3478000 | G8: =B8-umumiy_malumot!B67 -> 46 | H8: =DATE(YEAR(B8),12,31)-DATE(YEAR(B8),1,1)+1 -> 365
A9: 2 | B9: ='График дифференц'!B9 -> 46132 | C9: =C8-D8 -> 49987754 | D9: =IF(A9<umumiy_malumot!$B$81,'График аннуитет.'!F9-'График аннуитет.'!E9,'График аннуитет.'!C9) -> 1142955.7 | E9: =ROUND(C9*umumiy_malumot!$B$84/H9,2)*'График аннуитет.'!G9 -> 2335044.3 | F9: =IF(A9<umumiy_malumot!$B$81,'График аннуитет.'!F8,'График аннуитет.'!D9+'График аннуитет.'!E9) -> 3478000 | G9: =B9-B8 -> 31 | H9: =DATE(YEAR(B9),12,31)-DATE(YEAR(B9),1,1)+1 -> 365
A10: 3 | B10: ='График дифференц'!B10 -> 46162 | C10: =C9-D9 -> 48844798 | D10: =IF(A10<umumiy_malumot!$B$81,'График аннуитет.'!F10-'График аннуитет.'!E10,'График аннуитет.'!C10) -> 1269947.5 | E10: =ROUND(C10*umumiy_malumot!$B$84/H10,2)*'График аннуитет.'!G10 -> 2208052.5 | F10: =IF(A10<umumiy_malumot!$B$81,'График аннуитет.'!F9,'График аннуитет.'!D10+'График аннуитет.'!E10) -> 3478000 | G10: =B10-B9 -> 30 | H10: =DATE(YEAR(B10),12,31)-DATE(YEAR(B10),1,1)+1 -> 365
A11: 4 | B11: ='График дифференц'!B11 -> 46195 | C11: =C10-D10 -> 47574850 | D11: =IF(A11<umumiy_malumot!$B$81,'График аннуитет.'!F11-'График аннуитет.'!E11,'График аннуитет.'!C11) -> 1112291.7 | E11: =ROUND(C11*umumiy_malumot!$B$84/H11,2)*'График аннуитет.'!G11 -> 2365708.3 | F11: =IF(A11<umumiy_malumot!$B$81,'График аннуитет.'!F10,'График аннуитет.'!D11+'График аннуитет.'!E11) -> 3478000 | G11: =B11-B10 -> 33 | H11: =DATE(YEAR(B11),12,31)-DATE(YEAR(B11),1,1)+1 -> 365
A12: 5 | B12: ='График дифференц'!B12 -> 46223 | C12: =C11-D11 -> 46462559 | D12: =IF(A12<umumiy_malumot!$B$81,'График аннуитет.'!F12-'График аннуитет.'!E12,'График аннуитет.'!C12) -> 1517662 | E12: =ROUND(C12*umumiy_malumot!$B$84/H12,2)*'График аннуитет.'!G12 -> 1960338 | F12: =IF(A12<umumiy_malumot!$B$81,'График аннуитет.'!F11,'График аннуитет.'!D12+'График аннуитет.'!E12) -> 3478000 | G12: =B12-B11 -> 28 | H12: =DATE(YEAR(B12),12,31)-DATE(YEAR(B12),1,1)+1 -> 365
A13: 6 | B13: ='График дифференц'!B13 -> 46254 | C13: =C12-D12 -> 44944897 | D13: =IF(A13<umumiy_malumot!$B$81,'График аннуитет.'!F13-'График аннуитет.'!E13,'График аннуитет.'!C13) -> 1378519.1 | E13: =ROUND(C13*umumiy_malumot!$B$84/H13,2)*'График аннуитет.'!G13 -> 2099480.9 | F13: =IF(A13<umumiy_malumot!$B$81,'График аннуитет.'!F12,'График аннуитет.'!D13+'График аннуитет.'!E13) -> 3478000 | G13: =B13-B12 -> 31 | H13: =DATE(YEAR(B13),12,31)-DATE(YEAR(B13),1,1)+1 -> 365
A14: 7 | B14: ='График дифференц'!B14 -> 46286 | C14: =C13-D13 -> 43566378 | D14: =IF(A14<umumiy_malumot!$B$81,'График аннуитет.'!F14-'График аннуитет.'!E14,'График аннуитет.'!C14) -> 1377265 | E14: =ROUND(C14*umumiy_malumot!$B$84/H14,2)*'График аннуитет.'!G14 -> 2100735 | F14: =IF(A14<umumiy_malumot!$B$81,'График аннуитет.'!F13,'График аннуитет.'!D14+'График аннуитет.'!E14) -> 3478000 | G14: =B14-B13 -> 32 | H14: =DATE(YEAR(B14),12,31)-DATE(YEAR(B14),1,1)+1 -> 365
A15: 8 | B15: ='График дифференц'!B15 -> 46315 | C15: =C14-D14 -> 42189113 | D15: =IF(A15<umumiy_malumot!$B$81,'График аннуитет.'!F15-'График аннуитет.'!E15,'График аннуитет.'!C15) -> 1634393.4 | E15: =ROUND(C15*umumiy_malumot!$B$84/H15,2)*'График аннуитет.'!G15 -> 1843606.6 | F15: =IF(A15<umumiy_malumot!$B$81,'График аннуитет.'!F14,'График аннуитет.'!D15+'График аннуитет.'!E15) -> 3478000 | G15: =B15-B14 -> 29 | H15: =DATE(YEAR(B15),12,31)-DATE(YEAR(B15),1,1)+1 -> 365
A16: 9 | B16: ='График дифференц'!B16 -> 46346 | C16: =C15-D15 -> 40554719 | D16: =IF(A16<umumiy_malumot!$B$81,'График аннуитет.'!F16-'График аннуитет.'!E16,'График аннуитет.'!C16) -> 1583594.7 | E16: =ROUND(C16*umumiy_malumot!$B$84/H16,2)*'График аннуитет.'!G16 -> 1894405.3 | F16: =IF(A16<umumiy_malumot!$B$81,'График аннуитет.'!F15,'График аннуитет.'!D16+'График аннуитет.'!E16) -> 3478000 | G16: =B16-B15 -> 31 | H16: =DATE(YEAR(B16),12,31)-DATE(YEAR(B16),1,1)+1 -> 365
A17: 10 | B17: ='График дифференц'!B17 -> 46377 | C17: =C16-D16 -> 38971125 | D17: =IF(A17<umumiy_malumot!$B$81,'График аннуитет.'!F17-'График аннуитет.'!E17,'График аннуитет.'!C17) -> 1657568.1 | E17: =ROUND(C17*umumiy_malumot!$B$84/H17,2)*'График аннуитет.'!G17 -> 1820431.9 | F17: =IF(A17<umumiy_malumot!$B$81,'График аннуитет.'!F16,'График аннуитет.'!D17+'График аннуитет.'!E17) -> 3478000 | G17: =B17-B16 -> 31 | H17: =DATE(YEAR(B17),12,31)-DATE(YEAR(B17),1,1)+1 -> 365
A18: 11 | B18: ='График дифференц'!B18 -> 46407 | C18: =C17-D17 -> 37313556 | D18: =IF(A18<umumiy_malumot!$B$81,'График аннуитет.'!F18-'График аннуитет.'!E18,'График аннуитет.'!C18) -> 1791222.7 | E18: =ROUND(C18*umumiy_malumot!$B$84/H18,2)*'График аннуитет.'!G18 -> 1686777.3 | F18: =IF(A18<umumiy_malumot!$B$81,'График аннуитет.'!F17,'График аннуитет.'!D18+'График аннуитет.'!E18) -> 3478000 | G18: =B18-B17 -> 30 | H18: =DATE(YEAR(B18),12,31)-DATE(YEAR(B18),1,1)+1 -> 365
A19: 12 | B19: ='График дифференц'!B19 -> 46440 | C19: =C18-D18 -> 35522334 | D19: =IF(A19<umumiy_malumot!$B$81,'График аннуитет.'!F19-'График аннуитет.'!E19,'График аннуитет.'!C19) -> 1711615.6 | E19: =ROUND(C19*umumiy_malumot!$B$84/H19,2)*'График аннуитет.'!G19 -> 1766384.4 | F19: =IF(A19<umumiy_malumot!$B$81,'График аннуитет.'!F18,'График аннуитет.'!D19+'График аннуитет.'!E19) -> 3478000 | G19: =B19-B18 -> 33 | H19: =DATE(YEAR(B19),12,31)-DATE(YEAR(B19),1,1)+1 -> 365
A20: 13 | B20: ='График дифференц'!B20 -> 46468 | C20: =C19-D19 -> 33810718 | D20: =IF(A20<umumiy_malumot!$B$81,'График аннуитет.'!F20-'График аннуитет.'!E20,'График аннуитет.'!C20) -> 2051465.5 | E20: =ROUND(C20*umumiy_malumot!$B$84/H20,2)*'График аннуитет.'!G20 -> 1426534.5 | F20: =IF(A20<umumiy_malumot!$B$81,'График аннуитет.'!F19,'График аннуитет.'!D20+'График аннуитет.'!E20) -> 3478000 | G20: =B20-B19 -> 28 | H20: =DATE(YEAR(B20),12,31)-DATE(YEAR(B20),1,1)+1 -> 365
... A31: 24 | B31: ='График дифференц'!B31 -> 46785 | C31: =C30-D30 -> 6760860.8 | D31: =IF(A31<umumiy_malumot!$B$81,'График аннуитет.'!F31-'График аннуитет.'!E31,'График аннуитет.'!C31) -> 6760860.8 | E31: =ROUND(C31*umumiy_malumot!$B$84/H31,2)*'График аннуитет.'!G31 -> 132076.88 | F31: =IF(A31<umumiy_malumot!$B$81,'График аннуитет.'!F30,'График аннуитет.'!D31+'График аннуитет.'!E31) -> 6892937.7 | G31: =B31-B30 -> 13 | H31: =DATE(YEAR(B31),12,31)-DATE(YEAR(B31),1,1)+1 -> 366
A32: =1+A31 -> 25 | B32: ='График дифференц'!B32 -> FALSE | C32: =C31-D31 -> 0 | D32: =IF(A32<umumiy_malumot!$B$81,'График аннуитет.'!F32-'График аннуитет.'!E32,'График аннуитет.'!C32) -> 0 | E32: =ROUND(C32*umumiy_malumot!$B$84/H32,2)*'График аннуитет.'!G32 -> 0 | F32: =IF(A32<umumiy_malumot!$B$81,'График аннуитет.'!F31,'График аннуитет.'!D32+'График аннуитет.'!E32) -> 0 | G32: =B32-B31 -> -46785 | H32: =DATE(YEAR(B32),12,31)-DATE(YEAR(B32),1,1)+1 -> 366
A33: =1+A32 -> 26 | B33: ='График дифференц'!B33 -> FALSE | C33: =C32-D32 -> 0 | D33: =IF(A33<umumiy_malumot!$B$81,'График аннуитет.'!F33-'График аннуитет.'!E33,'График аннуитет.'!C33) -> 0 | E33: =ROUND(C33*umumiy_malumot!$B$84/H33,2)*'График аннуитет.'!G33 -> 0 | F33: =IF(A33<umumiy_malumot!$B$81,'График аннуитет.'!F32,'График аннуитет.'!D33+'График аннуитет.'!E33) -> 0 | G33: =B33-B32 -> 0 | H33: =DATE(YEAR(B33),12,31)-DATE(YEAR(B33),1,1)+1 -> 366
A34: =1+A33 -> 27 | B34: ='График дифференц'!B34 -> FALSE | C34: =C33-D33 -> 0 | D34: =IF(A34<umumiy_malumot!$B$81,'График аннуитет.'!F34-'График аннуитет.'!E34,'График аннуитет.'!C34) -> 0 | E34: =ROUND(C34*umumiy_malumot!$B$84/H34,2)*'График аннуитет.'!G34 -> 0 | F34: =IF(A34<umumiy_malumot!$B$81,'График аннуитет.'!F33,'График аннуитет.'!D34+'График аннуитет.'!E34) -> 0 | G34: =B34-B33 -> 0 | H34: =DATE(YEAR(B34),12,31)-DATE(YEAR(B34),1,1)+1 -> 366
A35: =1+A34 -> 28 | B35: ='График дифференц'!B35 -> FALSE | C35: =C34-D34 -> 0 | D35: =IF(A35<umumiy_malumot!$B$81,'График аннуитет.'!F35-'График аннуитет.'!E35,'График аннуитет.'!C35) -> 0 | E35: =ROUND(C35*umumiy_malumot!$B$84/H35,2)*'График аннуитет.'!G35 -> 0 | F35: =IF(A35<umumiy_malumot!$B$81,'График аннуитет.'!F34,'График аннуитет.'!D35+'График аннуитет.'!E35) -> 0 | G35: =B35-B34 -> 0 | H35: =DATE(YEAR(B35),12,31)-DATE(YEAR(B35),1,1)+1 -> 366
A36: =1+A35 -> 29 | B36: ='График дифференц'!B36 -> FALSE | C36: =C35-D35 -> 0 | D36: =IF(A36<umumiy_malumot!$B$81,'График аннуитет.'!F36-'График аннуитет.'!E36,'График аннуитет.'!C36) -> 0 | E36: =ROUND(C36*umumiy_malumot!$B$84/H36,2)*'График аннуитет.'!G36 -> 0 | F36: =IF(A36<umumiy_malumot!$B$81,'График аннуитет.'!F35,'График аннуитет.'!D36+'График аннуитет.'!E36) -> 0 | G36: =B36-B35 -> 0 | H36: =DATE(YEAR(B36),12,31)-DATE(YEAR(B36),1,1)+1 -> 366
A37: =1+A36 -> 30 | B37: ='График дифференц'!B37 -> FALSE | C37: =C36-D36 -> 0 | D37: =IF(A37<umumiy_malumot!$B$81,'График аннуитет.'!F37-'График аннуитет.'!E37,'График аннуитет.'!C37) -> 0 | E37: =ROUND(C37*umumiy_malumot!$B$84/H37,2)*'График аннуитет.'!G37 -> 0 | F37: =IF(A37<umumiy_malumot!$B$81,'График аннуитет.'!F36,'График аннуитет.'!D37+'График аннуитет.'!E37) -> 0 | G37: =B37-B36 -> 0 | H37: =DATE(YEAR(B37),12,31)-DATE(YEAR(B37),1,1)+1 -> 366
A38: =1+A37 -> 31 | B38: ='График дифференц'!B38 -> FALSE | C38: =C37-D37 -> 0 | D38: =IF(A38<umumiy_malumot!$B$81,'График аннуитет.'!F38-'График аннуитет.'!E38,'График аннуитет.'!C38) -> 0 | E38: =ROUND(C38*umumiy_malumot!$B$84/H38,2)*'График аннуитет.'!G38 -> 0 | F38: =IF(A38<umumiy_malumot!$B$81,'График аннуитет.'!F37,'График аннуитет.'!D38+'График аннуитет.'!E38) -> 0 | G38: =B38-B37 -> 0 | H38: =DATE(YEAR(B38),12,31)-DATE(YEAR(B38),1,1)+1 -> 366
A39: =1+A38 -> 32 | B39: ='График дифференц'!B39 -> FALSE | C39: =C38-D38 -> 0 | D39: =IF(A39<umumiy_malumot!$B$81,'График аннуитет.'!F39-'График аннуитет.'!E39,'График аннуитет.'!C39) -> 0 | E39: =ROUND(C39*umumiy_malumot!$B$84/H39,2)*'График аннуитет.'!G39 -> 0 | F39: =IF(A39<umumiy_malumot!$B$81,'График аннуитет.'!F38,'График аннуитет.'!D39+'График аннуитет.'!E39) -> 0 | G39: =B39-B38 -> 0 | H39: =DATE(YEAR(B39),12,31)-DATE(YEAR(B39),1,1)+1 -> 366
A40: =1+A39 -> 33 | B40: ='График дифференц'!B40 -> FALSE | C40: =C39-D39 -> 0 | D40: =IF(A40<umumiy_malumot!$B$81,'График аннуитет.'!F40-'График аннуитет.'!E40,'График аннуитет.'!C40) -> 0 | E40: =ROUND(C40*umumiy_malumot!$B$84/H40,2)*'График аннуитет.'!G40 -> 0 | F40: =IF(A40<umumiy_malumot!$B$81,'График аннуитет.'!F39,'График аннуитет.'!D40+'График аннуитет.'!E40) -> 0 | G40: =B40-B39 -> 0 | H40: =DATE(YEAR(B40),12,31)-DATE(YEAR(B40),1,1)+1 -> 366
A41: =1+A40 -> 34 | B41: ='График дифференц'!B41 -> FALSE | C41: =C40-D40 -> 0 | D41: =IF(A41<umumiy_malumot!$B$81,'График аннуитет.'!F41-'График аннуитет.'!E41,'График аннуитет.'!C41) -> 0 | E41: =ROUND(C41*umumiy_malumot!$B$84/H41,2)*'График аннуитет.'!G41 -> 0 | F41: =IF(A41<umumiy_malumot!$B$81,'График аннуитет.'!F40,'График аннуитет.'!D41+'График аннуитет.'!E41) -> 0 | G41: =B41-B40 -> 0 | H41: =DATE(YEAR(B41),12,31)-DATE(YEAR(B41),1,1)+1 -> 366
A42: =1+A41 -> 35 | B42: ='График дифференц'!B42 -> FALSE | C42: =C41-D41 -> 0 | D42: =IF(A42<umumiy_malumot!$B$81,'График аннуитет.'!F42-'График аннуитет.'!E42,'График аннуитет.'!C42) -> 0 | E42: =ROUND(C42*umumiy_malumot!$B$84/H42,2)*'График аннуитет.'!G42 -> 0 | F42: =IF(A42<umumiy_malumot!$B$81,'График аннуитет.'!F41,'График аннуитет.'!D42+'График аннуитет.'!E42) -> 0 | G42: =B42-B41 -> 0 | H42: =DATE(YEAR(B42),12,31)-DATE(YEAR(B42),1,1)+1 -> 366
A43: =1+A42 -> 36 | B43: ='График дифференц'!B43 -> FALSE | C43: =C42-D42 -> 0 | D43: =IF(A43<umumiy_malumot!$B$81,'График аннуитет.'!F43-'График аннуитет.'!E43,'График аннуитет.'!C43) -> 0 | E43: =ROUND(C43*umumiy_malumot!$B$84/H43,2)*'График аннуитет.'!G43 -> 0 | F43: =IF(A43<umumiy_malumot!$B$81,'График аннуитет.'!F42,'График аннуитет.'!D43+'График аннуитет.'!E43) -> 0 | G43: =B43-B42 -> 0 | H43: =DATE(YEAR(B43),12,31)-DATE(YEAR(B43),1,1)+1 -> 366
A44: =1+A43 -> 37 | B44: ='График дифференц'!B44 -> FALSE
A45: =1+A44 -> 38 | B45: ='График дифференц'!B45 -> FALSE
A46: =1+A45 -> 39 | B46: ='График дифференц'!B46 -> FALSE
A47: =1+A46 -> 40 | B47: ='График дифференц'!B47 -> FALSE
A48: =1+A47 -> 41 | B48: ='График дифференц'!B48 -> FALSE
A49: =1+A48 -> 42 | B49: ='График дифференц'!B49 -> FALSE
A50: =1+A49 -> 43 | B50: ='График дифференц'!B50 -> FALSE
A51: =1+A50 -> 44 | B51: ='График дифференц'!B51 -> FALSE
A52: =1+A51 -> 45 | B52: ='График дифференц'!B52 -> FALSE
A53: =1+A52 -> 46 | B53: ='График дифференц'!B53 -> FALSE
A54: =1+A53 -> 47 | B54: ='График дифференц'!B54 -> FALSE
A55: =1+A54 -> 48 | B55: ='График дифференц'!B55 -> FALSE
B56: ИТОГО | D56: =SUM(D8:D55) -> 50000000 | E56: =SUM(E8:E55) -> 36886938 | F56: =SUM(F8:F55) -> 86886938
A58: *В случае осуществления погашения платежей по кредиту в даты, отличные от указанных в графике погашения, сумма платежа меняется на сумму процентов, которые начисляются на сумму остатка долга по микрозайму в соответствии с п.п. 2.2. настоящего договора.
A60: =#REF! -> #REF! | D60: =#REF! -> #REF!
A62: =#REF! -> #REF! | D62: =#REF! -> #REF!
A63: =#REF! -> #REF! | D63: =#REF! -> #REF!
A64: =#REF! -> #REF! | D64: ="паспорт серии "&umumiy_malumot!B16&", "&umumiy_malumot!B20&"" -> паспорт серии AD 3925702, IIV 26266 tomonidan 12.07.2023 yilda berilgan
A65: =#REF! -> #REF!
A66: =#REF! -> #REF! | D66: =#REF! -> #REF!
A67: =#REF! -> #REF! | D67: =#REF! -> #REF!
A68: =#REF! -> #REF! | D68: =#REF! -> #REF!
A70: =#REF! -> #REF! | D70: =#REF! -> #REF!
A72: =#REF! -> #REF! | D72: =#REF! -> #REF!

Sheet mijoz_anketasi
A1: MIJOZNING ANKETASI
A2: Anketa kredit menejeri tomonidan mijozning javoblarini kiritish orqali to'ldiriladi, kerak bo'lganda, Mijoz tomonidan tanlangan javob variantlarini belgilash orqali amalga oshiriladi
A3: 1. MIJOZ HAQIDA MA'LUMOTLAR:
A4: =xulosa!A4:F4 -> Mijozning to'liq ismi sharifi: SIMONYAN VADIM ROMANOVICH
A5: =xulosa!A5:F5 -> Tug'ilgan sanasi: 14.12.1968 yil
A6: =xulosa!A6:F6 -> Pasport seriyasi AD 3925702 IIV 26266 tomonidan 12.07.2023 yilda berilgan, amal qilish muddati - 11.07.2033 y.
A7: ="Fuqaroligi: "&umumiy_malumot!B32&"" -> Fuqaroligi: O’zbekiston Respublikasi
A8: =xulosa!A7:F7 -> Ro‘yxatdan o‘tgan manzili: TOSHKENT SHAHAR YUNUSOBOD TUMANI OTCHOPAR-1 MFY KARIM ZARIPOV KO'CHASI 8-6 UY, mo'ljal: CHINOBOD SANATORIY SANTINI
A9: =IF(umumiy_malumot!B23="mos keladi"," ",mijoz_anketasi!A10:F10)
A10: ="Haqiqatdan yashash joy manzili: "&umumiy_malumot!B28&"" -> Haqiqatdan yashash joy manzili: TOSHKENT SHAHAR YUNUSOBOD TUMANI OTCHOPAR-1 MFY KARIM ZARIPOV KO'CHASI 8-6 UY
A11: =xulosa!A8:F8 -> Ish joyi: lavozimi Yakka tartibdagi tadbirkorda Yakka tartibdagi tadbirkor
A12: 2. Mijoz bilan ulanich uchun aloqa ma'lumotlari:
A13: ="Uy telefoni raqami: "&umumiy_malumot!B40&"" -> Uy telefoni raqami: 93 554 55 99 MIJOZ
A14: ="Uyali telefon raqami: "&umumiy_malumot!B41&"" -> Uyali telefon raqami: 99 899 80 88 JIYANI
A15: ="Uyali telefon raqami: "&umumiy_malumot!B42&"" -> Uyali telefon raqami: 71 212 15 05 UY
A16: ="Uyali telefon raqami: "&umumiy_malumot!B42&"" -> Uyali telefon raqami: 71 212 15 05 UY
A17: ="Ish telefoni raqami: "&umumiy_malumot!B43&"" -> Ish telefoni raqami:
A18: 3. MIJOZNING ISH JOYI HAQIDA MA'LUMOT:
A19: ="Muassasa nomlanishi:"&umumiy_malumot!B58&"" -> Muassasa nomlanishi:Yakka tartibdagi tadbirkor
A20: ="Ro‘yxatdan o‘tish manzili:"&umumiy_malumot!B46&"" -> Ro‘yxatdan o‘tish manzili:
A21: ="Lavozimi: "&umumiy_malumot!B59&"" -> Lavozimi: Yakka tartibdagi tadbirkor
A22: 4. MIJOZNING OYLIK DAROMADLARI VA XARAJATLARI HAQIDA MA'LUMOT
A23: Daromad manbalari | B23: Mijoz | C23: Turmush o'rtog'i | D23: Boshqa oila a'zolari | E23: Xarajatlar | F23: Мiqdori
A24: ish haqi (asosiy ish) | B24: =umumiy_malumot!B60 -> 10000000 | C24: 0 | D24: 0 | E24: uy-joy va kommunal xizmatlar uchun to'lov | F24: 700000
A25: ish haqi (o‘rindoshlik) | B25: 0 | C25: 0 | D25: 0 | E25: oilaviy xarajatlar | F25: 500000
A26: boshqa daromadlar | B26: =umumiy_malumot!B61 -> 5000000 | C26: 0 | D26: 0 | E26: boshqa xarajatlar | F26: 600000
A27: JAMI | B27: =B24+B25+B26 -> 15000000 | C27: =SUM(C24:C26) -> 0 | D27: =SUM(D24:D26) -> 0 | F27: =SUM(F24:F26) -> 1800000
A28: ="Men, "&umumiy_malumot!B5&", ushbu anketada ko‘rsatilgan barcha ma'lumotlar anketa to'ldirilgan sanada to'g'ri va aniq ekanligini tasdiqlayman." -> Men, SIMONYAN VADIM ROMANOVICH, ushbu anketada ko‘rsatilgan barcha ma'lumotlar anketa to'ldirilgan sanada to'g'ri va aniq ekanligini tasdiqlayman.
A29: ="Men, "&umumiy_malumot!B5&", quyidagilarni tan olaman va roziman::" -> Men, SIMONYAN VADIM ROMANOVICH, quyidagilarni tan olaman va roziman::
A30: ="1. Ushbu anketada ko‘rsatilgan har qanday ma’lumot "&umumiy_malumot!B147&", uning xodimlari va huquqiy vorislari tomonidan istalgan manbaa va ma’lumotlardan foydalangan holda istalgan vaqtda tekshirilishi va qayta tekshirilishi mumkin." -> 1. Ushbu anketada ko‘rsatilgan har qanday ma’lumot «PULLOL BUSINESS MIKROMOLIYA TASHKILOTI» MChJ, uning xodimlari va huquqiy vorislari tomonidan istalgan manbaa va ma’lumotlardan foydalangan holda istalgan vaqtda tekshirilishi va qayta tekshirilishi mumkin.
A31: ="2. Mazkur anketaning "&umumiy_malumot!B147&" tomonidan qabul qilinishi menga "&umumiy_malumot!B65&" berish majburiyatini yuklamaydi." -> 2. Mazkur anketaning «PULLOL BUSINESS MIKROMOLIYA TASHKILOTI» MChJ tomonidan qabul qilinishi menga Mikroqarz berish majburiyatini yuklamaydi.
A32: Men, _________________________________________________________________ (to'liq ismi sharifi), ushbu anketadagi barcha ma'lumotlar anketa to'ldirilgan sanada to'g'ri ekanligini tasdiqlayman va ushbu anketaning 1- va 2-bandlarini tan olaman va ularga rozilik bildiraman. Mazkur anketaning 4-bo'limida ko'rsatilgan daromadlarim haqidagi ma'lumotlarni qabul qilishingizni va moliyaviy tahlilda foydalanishingizni so’rayman.
A34: Mijozning to'liq ismi sharifi | D34: Sana | E34: Imzo
D35: =umumiy_malumot!B2 -> 02.02.2026

Sheet anketa
A2: ANKETA
E3: =umumiy_malumot!B68 -> 2 fevral 2026 y.
A5: Mijozning to'liq ismi sharifi | C5: =umumiy_malumot!B8 -> SIMONYAN VADIM ROMANOVICH
A7: Siz ommaviy mansabdor shaxsmisiz? | D7: Ha
D8: Yo'q
A9: Yaqin qarindoshlaringiz orasida ommaviy mansabdor shaxslar bormi? | D9: Ha
D10: Yo'q
A11: Do'stlaringiz yoki yaqinlaringizdan birontasi ommaviy mansabdor shaxsmi? | D11: Ha
D12: Yo'q
A13: Yuqoridagi savollardan biriga «Ha» deb javob bergan bo'lsangiz, javobingizni qisqacha tushuntirib bering:
A18: Siz bank amaliyotlarini amalga oshirishda uchinchi shaxsning manfaatlarini ifodalaysizmi? | D18: Ha
D19: Yo'q
A20: Agar oldingi savolga «HA» deb javob bergan bo'lsangiz, bank operatsiyalarini bajarich uchun ishonchnomangiz bormi? | D20: Ha
D21: Yo'q
A23: Agar oldingi savolga «YO'Q» deb javob bergan bo'lsangiz, javobingizni qisqacha tushuntirib bering:
A28: Ommaviy mansabdor shaxslar — doimiy, vaqtincha yoki maxsus vakolatli organ tomonidan tayinlangan yoki saylangan, tashkiliy-maʼmuriy funktsiyalarni bajaruvchi hamda xorijiy davlatning qonun chiqaruvchi, ijro etuvchi, maʼmuriy yoki sud organida yoxud xalqaro tashkilotda yuridik ahamiyatga molik harakatlarni amalga oshirishga vakolatli shaxslar, shuningdek xorijiy davlatlar korxonalarining yuqori martabali rahbarlari, taniqli siyosatchilar va xorijiy davlatlar siyosiy partiyalarining taniqli a'zolari.
A30: Anketadagi barcha ma'lumotlar to'g'ri, agar o'zgarishlar bo'lsa, men bu haqida xabardor qilish majburiyatini o'z zimmamga olaman.
A33: =C5 -> SIMONYAN VADIM ROMANOVICH

Sheet kredit_ariza
C1: =""&umumiy_malumot!B147&"ning "&umumiy_malumot!A150&"i" -> «PULLOL BUSINESS MIKROMOLIYA TASHKILOTI» MChJning Direktori
D2: =""&umumiy_malumot!B150&"ga" -> Obidov A. Sh.ga
A4: =""&umumiy_malumot!C64&" olish uchun Ariza" -> Mikrokredit olish uchun Ariza
A6: =""&umumiy_malumot!B28&".-da yashovchi O‘zbekiston Respublikasi fuqarosi "&umumiy_malumot!B8&"dan. " -> TOSHKENT SHAHAR YUNUSOBOD TUMANI OTCHOPAR-1 MFY KARIM ZARIPOV KO'CHASI 8-6 UY.-da yashovchi O‘zbekiston Respublikasi fuqarosi SIMONYAN VADIM ROMANOVICHdan.
A7: ="Tug'ilgan kuni: "&umumiy_malumot!B15&"" -> Tug'ilgan kuni: 14.12.1968 yil
A8: ="Pasport seriyasi: "&umumiy_malumot!B16&" "&umumiy_malumot!B20&"" -> Pasport seriyasi: AD 3925702 IIV 26266 tomonidan 12.07.2023 yilda berilgan
A9: ="Asosiy ish joyi : "&umumiy_malumot!B58&"" -> Asosiy ish joyi : Yakka tartibdagi tadbirkor
A10: ="Lavozimi: "&umumiy_malumot!B59&"" -> Lavozimi: Yakka tartibdagi tadbirkor
A11: ="O’rtacha oylik daromadi: "&FIXED(mijoz_anketasi!B27,2)&" so'm." -> O’rtacha oylik daromadi: 15 000 000,00 so'm.
A12: ="Menga quyidagi shartlarda "&umumiy_malumot!B65&" berishingizni so’rayman:" -> Menga quyidagi shartlarda Mikroqarz berishingizni so’rayman:
A13: =""&umumiy_malumot!B65&" summasi: "&FIXED(umumiy_malumot!B75,2)&" ("&umumiy_malumot!B76&") so'm." -> Mikroqarz summasi: 50 000 000,00 (Ellik million so'm) so'm.
A14: =""&umumiy_malumot!B65&" muddati: "&umumiy_malumot!B81&" ("&umumiy_malumot!B82&") oy." -> Mikroqarz muddati: 24 (yigirma to'rt) oy.
A15: =""&umumiy_malumot!B65&"dan foydalanganlik uchun foiz stavkasi: yillik "&umumiy_malumot!B85&"% ("&umumiy_malumot!B86&") foiz" -> Mikroqarzdan foydalanganlik uchun foiz stavkasi: yillik 50% (Ellik ) foiz
A16: =""&umumiy_malumot!C65&" bo'yicha asosiy qarz va foizlarni to'lash:" -> 46785 bo'yicha asosiy qarz va foizlarni to'lash:
A17: =" - "&umumiy_malumot!B65&" shartnomasi bo'yicha har oy differensial to'lovlari amalga oshiriladi" -> - Mikroqarz shartnomasi bo'yicha har oy differensial to'lovlari amalga oshiriladi
A18: =" - "&umumiy_malumot!B65&" shartnomasi bo'yicha har oy annuitet to'lovlari amalga oshiriladi" -> - Mikroqarz shartnomasi bo'yicha har oy annuitet to'lovlari amalga oshiriladi
A19: =IF(umumiy_malumot!B77=umumiy_malumot!C77,kredit_ariza!A17:D17,IF(umumiy_malumot!B77=umumiy_malumot!D77,kredit_ariza!A18:D18)) -> - Mikroqarz shartnomasi bo'yicha har oy annuitet to'lovlari amalga oshiriladi
A20: =IF(DAY(umumiy_malumot!E67)<15," "," Oxirgi yakuniy to'lov "&umumiy_malumot!B65&" shartnomasi tuzilgan kundan boshlab oxirgi oyning oxirgi kunida amalga oshiriladi")
A21: =""&umumiy_malumot!B65&" ta’minoti::" -> Mikroqarz ta’minoti::
A22: =IF(umumiy_malumot!B103="Avtotransport",A26,A23) -> Egalik huquqi SIMONYAN VADIM ROMANOVICHga tegishli bo'lgan umumiy yer maydoni, (m2) - 166, qurilish osti maydoni - 87, umumiy foydali maydoni - 48.67 va yashash maydoni - 30.84 Yakka tartibdagi uy-joy, TOSHKENT SHAHAR YUNUSOBOD TUMANI OTCHOPAR-1 MFY KARIM ZARIPOV KO'CHASI 8-6 UY
A23: =IF(umumiy_malumot!B92=umumiy_malumot!C92,A25,IF(umumiy_malumot!B92=umumiy_malumot!D92,A24,0)) -> Egalik huquqi SIMONYAN VADIM ROMANOVICHga tegishli bo'lgan umumiy yer maydoni, (m2) - 166, qurilish osti maydoni - 87, umumiy foydali maydoni - 48.67 va yashash maydoni - 30.84 Yakka tartibdagi uy-joy, TOSHKENT SHAHAR YUNUSOBOD TUMANI OTCHOPAR-1 MFY KARIM ZARIPOV KO'CHASI 8-6 UY
A24: =" - Navbatdagi garov (ipoteka) Egalik huquqi asosida "&umumiy_malumot!C117&"ga "&umumiy_malumot!C126&", umumiy maydoni - "&umumiy_malumot!C130&" va qurilish osti maydoni - "&umumiy_malumot!C133&", manzili: "&umumiy_malumot!C123&"." -> - Navbatdagi garov (ipoteka) Egalik huquqi asosida SIMONYAN VADIM ROMANOVICHga Yakka tartibdagi uy-joy, umumiy maydoni - 48.67 va qurilish osti maydoni - 87, manzili: TOSHKENT SHAHAR YUNUSOBOD TUMANI OTCHOPAR-1 MFY KARIM ZARIPOV KO'CHASI 8-6 UY.
A25: =" Egalik huquqi "&umumiy_malumot!C117&"ga tegishli bo'lgan "&umumiy_malumot!D134&" - "&umumiy_malumot!C134&", "&umumiy_malumot!D133&" - "&umumiy_malumot!C133&", "&umumiy_malumot!D130&" - "&umumiy_malumot!C130&" va "&umumiy_malumot!D131&" - "&umumiy_malumot!C131&" "&umumiy_malumot!C126&", "&umumiy_malumot!C123&" " -> Egalik huquqi SIMONYAN VADIM ROMANOVICHga tegishli bo'lgan umumiy yer maydoni, (m2) - 166, qurilish osti maydoni - 87, umumiy foydali maydoni - 48.67 va yashash maydoni - 30.84 Yakka tartibdagi uy-joy, TOSHKENT SHAHAR YUNUSOBOD TUMANI OTCHOPAR-1 MFY KARIM ZARIPOV KO'CHASI 8-6 UY
A26: =IF(umumiy_malumot!B92=umumiy_malumot!C92,kredit_ariza!A28:D28,IF(umumiy_malumot!B92=umumiy_malumot!D92,kredit_ariza!A27:D27,0)) -> Egalik huquqi SIMONYAN VADIM ROMANOVICHga tegishli bo'lgan garovga olingan avtomobil markasi , rangi - , ishlab chiqarilgan yili - , davlat raqam belgisi , kuzov turi - , kuzov raqami , dvigatel raqami , shassi raqami -
A27: =" Egalik huquqi "&umumiy_malumot!B117&"ga tegishli bo'lgan "&umumiy_malumot!B125&", "&umumiy_malumot!B133&", davlat raqam belgisi "&umumiy_malumot!B126&", "&umumiy_malumot!B127&", "&umumiy_malumot!B130&" avtotransport vositasi " -> Egalik huquqi SIMONYAN VADIM ROMANOVICHga tegishli bo'lgan , rangi - , ishlab chiqarilgan yili - , davlat raqam belgisi , kuzov turi - , kuzov raqami , dvigatel raqami , shassi raqami - avtotransport vositasi
A28: =" Egalik huquqi "&umumiy_malumot!B117&"ga tegishli bo'lgan garovga olingan avtomobil markasi "&umumiy_malumot!B125&", "&umumiy_malumot!B133&", davlat raqam belgisi "&umumiy_malumot!B126&", "&umumiy_malumot!B127&", "&umumiy_malumot!B130&"" -> Egalik huquqi SIMONYAN VADIM ROMANOVICHga tegishli bo'lgan garovga olingan avtomobil markasi , rangi - , ishlab chiqarilgan yili - , davlat raqam belgisi , kuzov turi - , kuzov raqami , dvigatel raqami , shassi raqami -
A30: ="Mazkur ariza bilan "&umumiy_malumot!B147&"ga men va soʻralayotgan "&umumiy_malumot!B65&" boʻyicha barcha zarur maʼlumotlarni quyida ko’rsatilgan tashkilotlarga taqdim etish va olishga roziligimni bildirib, ushbu amaliyotlarni o’tkazish uchun huquq beraman:" -> Mazkur ariza bilan «PULLOL BUSINESS MIKROMOLIYA TASHKILOTI» MChJga men va soʻralayotgan Mikroqarz boʻyicha barcha zarur maʼlumotlarni quyida ko’rsatilgan tashkilotlarga taqdim etish va olishga roziligimni bildirib, ushbu amaliyotlarni o’tkazish uchun huquq beraman:
A31: □ O‘zbekiston Respublikasi Markaziy banki huzuridagi kredit axborotining davlat reestri;
A32: □ Kredit-axborot tahliliy markazi «O‘zbekiston Respublikasi kredit byurosi» MChJ;
A33: □ Garov reestri taqdim etilgan garov mulki haqida.
A34: ="Ariza berilgan sana: "&TEXT(umumiy_malumot!B2,"ДД.ММ.ГГГГ")&"y." -> Ariza berilgan sana: 02.02.2026y.
A36: Ariza berilgan kuniga barcha ma'lumotlar ishonchligini tasdiqlab, ushbu arizani imzolayman
A39: =umumiy_malumot!B5 -> SIMONYAN VADIM ROMANOVICH | D39: P________________
D40: (imzo)

Sheet majburiyatnoma
A3: MAJBURIYATNOMA
A4: =" Men, fuqaro "&umumiy_malumot!B5&" "&umumiy_malumot!B149&" bilan "&umumiy_malumot!B69&" sanasidagi "&umumiy_malumot!B66&"-sonli shartnomaning garov ta'minoti sifatida taqdim etilayotgan "&umumiy_malumot!C125&" ko'chmas mulkni qonunga xilof ravishda o‘zlashtirmaslikka, yashirmaslikka, nobud qilmaslikka yoki unga shikast yetkazmaslik majburiyatini olaman." -> Men, fuqaro SIMONYAN VADIM ROMANOVICH «PULLOL BUSINESS MIKROMOLIYA TASHKILOTI» MChJ bilan 2 fevral 2026 y. sanasidagi №43-sonli shartnomaning garov ta'minoti sifatida taqdim etilayotgan Yakka tartibdagi uy-joy ko'chmas mulkni qonunga xilof ravishda o‘zlashtirmaslikka, yashirmaslikka, nobud qilmaslikka yoki unga shikast yetkazmaslik majburiyatini olaman.
A5: Ushbu majburiyatlarimni bajarmagan taqdirimda O'zbekiston Respublikasi jinoyat kodeksining 233-moddasi talablari asosida javobgarlik tog'risida ogohlantrildim.
A7: =umumiy_malumot!B5 -> SIMONYAN VADIM ROMANOVICH | B7: Imzo_____________
A9: =umumiy_malumot!C105 -> 0 | B9: Imzo_____________
A11: ="sana: "&TEXT(umumiy_malumot!B2,"ДД.ММ.ГГГГ")&" y." -> sana: 02.02.2026 y.

Sheet xulosa
A1: =""&umumiy_malumot!B147&" mikromoliya tashkilotining Xulosasi" -> «PULLOL BUSINESS MIKROMOLIYA TASHKILOTI» MChJ mikromoliya tashkilotining Xulosasi
A3: MIJOZ HAQIDA MA'LUMOTLAR
A4: ="Mijozning to'liq ismi sharifi: "&umumiy_malumot!B5&"" -> Mijozning to'liq ismi sharifi: SIMONYAN VADIM ROMANOVICH
A5: ="Tug'ilgan sanasi: "&umumiy_malumot!B15&"" -> Tug'ilgan sanasi: 14.12.1968 yil
A6: ="Pasport seriyasi "&umumiy_malumot!B16&" "&umumiy_malumot!B20&", amal qilish muddati - "&umumiy_malumot!B21&"" -> Pasport seriyasi AD 3925702 IIV 26266 tomonidan 12.07.2023 yilda berilgan, amal qilish muddati - 11.07.2033 y.
A7: ="Ro‘yxatdan o‘tgan manzili: "&umumiy_malumot!B28&", mo'ljal: "&umumiy_malumot!B26&"" -> Ro‘yxatdan o‘tgan manzili: TOSHKENT SHAHAR YUNUSOBOD TUMANI OTCHOPAR-1 MFY KARIM ZARIPOV KO'CHASI 8-6 UY, mo'ljal: CHINOBOD SANATORIY SANTINI
A8: ="Ish joyi: "&umumiy_malumot!B52&" lavozimi "&umumiy_malumot!B49&"da "&umumiy_malumot!B44&"" -> Ish joyi: lavozimi Yakka tartibdagi tadbirkorda Yakka tartibdagi tadbirkor
A10: ="Mijoz tomonidan so’ralgan "&umumiy_malumot!B65&" shartlari:" -> Mijoz tomonidan so’ralgan Mikroqarz shartlari:
A11: =kredit_ariza!A13 -> Mikroqarz summasi: 50 000 000,00 (Ellik million so'm) so'm.
A12: =kredit_ariza!A14:D14 -> Mikroqarz muddati: 24 (yigirma to'rt) oy.
A13: =kredit_ariza!A15:D15 -> Mikroqarzdan foydalanganlik uchun foiz stavkasi: yillik 50% (Ellik ) foiz
A14: =kredit_ariza!A16:D16 -> 46785 bo'yicha asosiy qarz va foizlarni to'lash:
A15: =kredit_ariza!A19:D19 -> - Mikroqarz shartnomasi bo'yicha har oy annuitet to'lovlari amalga oshiriladi
A16: =kredit_ariza!A20:D20
A17: =kredit_ariza!A21:D21 -> Mikroqarz ta’minoti::
A18: =kredit_ariza!A22:D22 -> Egalik huquqi SIMONYAN VADIM ROMANOVICHga tegishli bo'lgan umumiy yer maydoni, (m2) - 166, qurilish osti maydoni - 87, umumiy foydali maydoni - 48.67 va yashash maydoni - 30.84 Yakka tartibdagi uy-joy, TOSHKENT SHAHAR YUNUSOBOD TUMANI OTCHOPAR-1 MFY KARIM ZARIPOV KO'CHASI 8-6 UY
A19: Mijozning moliyaviy holati
A20: ="Anketaga muvofiq "&umumiy_malumot!B9&"ning o‘rtacha oylik daromadi "&FIXED(mijoz_anketasi!B27)&" so‘mni tashkil etdi." -> Anketaga muvofiq SIMONYAN V. R.ning o‘rtacha oylik daromadi 15 000 000,00 so‘mni tashkil etdi.
A21: ="Mijozning o'rtacha oylik xarajatlari "&FIXED(mijoz_anketasi!F27)&" so'mni tashkil etdi" -> Mijozning o'rtacha oylik xarajatlari 1 800 000,00 so'mni tashkil etdi
A22: =IF(umumiy_malumot!B77=umumiy_malumot!C77,xulosa!A23:F23,xulosa!A24:F24) -> Mikrokredit bo‘yicha oylik annuitet to‘lovi miqdori 3 478 000,00 so‘mni tashkil etadi.
A23: =""&umumiy_malumot!C64&" shartnomasi bo'yicha birinchi oy uchun to'lov "&FIXED(umumiy_malumot!B90)&" so'mni tashkil etadi." -> Mikrokredit shartnomasi bo'yicha birinchi oy uchun to'lov 3 478 000,00 so'mni tashkil etadi.
A24: =""&umumiy_malumot!C64&" bo‘yicha oylik "&umumiy_malumot!B77&" to‘lovi miqdori "&FIXED(umumiy_malumot!B90)&" so‘mni tashkil etadi." -> Mikrokredit bo‘yicha oylik annuitet to‘lovi miqdori 3 478 000,00 so‘mni tashkil etadi.
A25: Mijoz quyidagi majburiyatlarga ega: "TOShKENT Sh., "UZSАNOАTQURILIShBАNKI" АTB BOSh OFISI 6 452 222.00, TOShKENT Sh., "АGROBАNK" АTB TOShKENT ShАXАR FILIАLI 11 979 900.00, TOShKENT Sh., "TBC BANK" АKTSIYADORLIK TIJORАT BАNKI 2 325 840.00, TOShKENT Sh., "ANOR BANK" АKTSIYADORLIK JАMIYATI 41 026 583.00, Alif Moliya 789 360.00., Ayni paytda muddati o'tgan qarzdorligi mavjud emas. O‘rtacha oylik to‘lov 4 208 626.10 so‘mni tashkil qiladi.
A26: =""&umumiy_malumot!B65&" bo’yicha ta’minot:" -> Mikroqarz bo’yicha ta’minot:
A27: =" - "&umumiy_malumot!B117&" ga mulk huquqi asosida tegishli avtotransport vositasi "&umumiy_malumot!B125&" , quyidagi tafsilotlarga muvofiq:" -> - SIMONYAN VADIM ROMANOVICH ga mulk huquqi asosida tegishli avtotransport vositasi , quyidagi tafsilotlarga muvofiq:
A28: =" - "&umumiy_malumot!C117&" ga mulk huquqi asosida tegishli ko'chmas mulk shaklida "&umumiy_malumot!C126&", manzili: "&umumiy_malumot!C123&", quyidagi tafsilotlarga muvofiq:" -> - SIMONYAN VADIM ROMANOVICH ga mulk huquqi asosida tegishli ko'chmas mulk shaklida Yakka tartibdagi uy-joy, manzili: TOSHKENT SHAHAR YUNUSOBOD TUMANI OTCHOPAR-1 MFY KARIM ZARIPOV KO'CHASI 8-6 UY, quyidagi tafsilotlarga muvofiq:
A29: =IF(umumiy_malumot!B103="Avtotransport",xulosa!A27:F27,xulosa!A28:F28) -> - SIMONYAN VADIM ROMANOVICH ga mulk huquqi asosida tegishli ko'chmas mulk shaklida Yakka tartibdagi uy-joy, manzili: TOSHKENT SHAHAR YUNUSOBOD TUMANI OTCHOPAR-1 MFY KARIM ZARIPOV KO'CHASI 8-6 UY, quyidagi tafsilotlarga muvofiq:
A30: Nomi | B30: Umumiy yer maydoni, m² | C30: Qurilish osti maydoni, m² | D30: Yashash maydoni, m² | E30: Umumiy foydali maydoni, m² | F30: Kelishilgan garov qiymati, so'm
A31: =umumiy_malumot!C125 -> Yakka tartibdagi uy-joy | B31: =umumiy_malumot!C134 -> 166 | C31: =umumiy_malumot!C133 -> 87 | D31: =umumiy_malumot!C131 -> 30.84 | E31: =umumiy_malumot!C130 -> 48.67 | F31: =""&FIXED(umumiy_malumot!B136)&" ("&umumiy_malumot!B137&")" -> 70 000 000,00 (yetmish million so'm)
A32: ="-* avtotransport vositasining mulkdori: "&umumiy_malumot!B117&"" -> -* avtotransport vositasining mulkdori: SIMONYAN VADIM ROMANOVICH
A33: ="-* texpasport raqami:: "&umumiy_malumot!B124&"" -> -* texpasport raqami::
A34: ="-* roʻyxatdan oʻtgan manzili/garaj manzili: "&umumiy_malumot!B122&"" -> -* roʻyxatdan oʻtgan manzili/garaj manzili: TOSHKENT SHAHAR YUNUSOBOD TUMANI OTCHOPAR-1 MFY KARIM ZARIPOV KO'CHASI 8-6 UY
A35: ="-* davlat raqami: "&umumiy_malumot!B126&"" -> -* davlat raqami:
A37: Nomi | C37: Yer uchastkasining foydalanish maydoni, m² | D37: Yashash maydoni, m² | E37: Umumiy maydoni, m² | F37: Kelishilgan garov qiymati, so'm
A38: =dalolatnoma!A51 -> Yashash xona | C38: =dalolatnoma!C51 -> 3 | D38: 18.82 | E38: 43.96 | F38: =""&FIXED(umumiy_malumot!C136,2)&" ("&umumiy_malumot!C137&")" -> 70 000 000,00 (yetmish million so'm)
A39: =dalolatnoma!A52 -> 0 | C39: =dalolatnoma!C52 -> 0 | D39: =dalolatnoma!D52 -> 0 | E39: =dalolatnoma!E52 -> 0
A40: =dalolatnoma!A53 -> Umumiy maydon | C40: 43.96 | D40: 18.82 | E40: 43.96
A41: =dalolatnoma!A54 -> 0 | C41: =dalolatnoma!C54 -> 0 | D41: =dalolatnoma!D54 -> 0 | E41: =dalolatnoma!E54 -> 0
A42: =dalolatnoma!A55 -> 0 | C42: =dalolatnoma!C55 -> 0 | D42: =dalolatnoma!D55 -> 0 | E42: =dalolatnoma!E55 -> 0
A43: =dalolatnoma!A56 -> 0 | C43: =dalolatnoma!C56 -> 0 | D43: =dalolatnoma!D56 -> 0 | E43: =dalolatnoma!E56 -> 0
A44: =dalolatnoma!A57 -> 0 | C44: =dalolatnoma!C57 -> 0 | D44: =dalolatnoma!D57 -> 0 | E44: =dalolatnoma!E57 -> 0
A45: =dalolatnoma!A58 -> 0 | C45: =dalolatnoma!C58 -> 0 | D45: =dalolatnoma!D58 -> 0 | E45: =dalolatnoma!E58 -> 0
A46: =dalolatnoma!A59 -> 0 | C46: =dalolatnoma!C59 -> 0 | D46: =dalolatnoma!D59 -> 0 | E46: =dalolatnoma!E59 -> 0
A47: =dalolatnoma!A60 -> 0 | C47: =dalolatnoma!C60 -> 0 | D47: =dalolatnoma!D60 -> 0 | E47: =dalolatnoma!E60 -> 0
A48: =dalolatnoma!A61 -> 0 | C48: =dalolatnoma!C61 -> 0 | D48: =dalolatnoma!D61 -> 0 | E48: =dalolatnoma!E61 -> 0
A49: =dalolatnoma!A62 -> JAMI | C49: =C40 -> 43.96 | D49: =D38 -> 18.82 | E49: =E40 -> 43.96 | F49: =dalolatnoma!F62 -> 70 000 000,00
A50: ="-* ko'chmas mulk egasi: "&umumiy_malumot!C117&"" -> -* ko'chmas mulk egasi: SIMONYAN VADIM ROMANOVICH
A51: ="-* reestr raqami: "&umumiy_malumot!C124&"" -> -* reestr raqami: №1726266/R-A5552339
A52: ="-* kadastr raqami: "&umumiy_malumot!C127&"" -> -* kadastr raqami: 07.01.2025 y. №10:07:04:02:02:7296/06
A53: ="-* manzili: "&umumiy_malumot!C123&"" -> -* manzili: TOSHKENT SHAHAR YUNUSOBOD TUMANI OTCHOPAR-1 MFY KARIM ZARIPOV KO'CHASI 8-6 UY
A55: =""&umumiy_malumot!B147&" mikromoliya tashkilotining Xulosasi" -> «PULLOL BUSINESS MIKROMOLIYA TASHKILOTI» MChJ mikromoliya tashkilotining Xulosasi
A56: =""&umumiy_malumot!B147&" kredit qo‘mitasining xulosasiga quyidagi shartlarda "&umumiy_malumot!B10&"ga "&umumiy_malumot!B65&" berish masalasi kiritiladi:" -> «PULLOL BUSINESS MIKROMOLIYA TASHKILOTI» MChJ kredit qo‘mitasining xulosasiga quyidagi shartlarda SIMONYAN VADIM ROMANOVICHga Mikroqarz berish masalasi kiritiladi:
A57: =A11 -> Mikroqarz summasi: 50 000 000,00 (Ellik million so'm) so'm.
A58: =A12 -> Mikroqarz muddati: 24 (yigirma to'rt) oy.
A59: =A13 -> Mikroqarzdan foydalanganlik uchun foiz stavkasi: yillik 50% (Ellik ) foiz
A60: =A14 -> 46785 bo'yicha asosiy qarz va foizlarni to'lash:
A61: =A15 -> - Mikroqarz shartnomasi bo'yicha har oy annuitet to'lovlari amalga oshiriladi
A62: =A16
A63: =A17 -> Mikroqarz ta’minoti::
A64: =A18 -> Egalik huquqi SIMONYAN VADIM ROMANOVICHga tegishli bo'lgan umumiy yer maydoni, (m2) - 166, qurilish osti maydoni - 87, umumiy foydali maydoni - 48.67 va yashash maydoni - 30.84 Yakka tartibdagi uy-joy, TOSHKENT SHAHAR YUNUSOBOD TUMANI OTCHOPAR-1 MFY KARIM ZARIPOV KO'CHASI 8-6 UY
A66: =""&umumiy_malumot!B147&" mikromoliya tashkilotining xulosasi "&TEXT(umumiy_malumot!B2,"ДД.ММ.ГГГГ")&" y. tayyorlangan" -> «PULLOL BUSINESS MIKROMOLIYA TASHKILOTI» MChJ mikromoliya tashkilotining xulosasi 02.02.2026 y. tayyorlangan
A69: =umumiy_malumot!A161 -> Kredit bo'yicha menejer | F69: =umumiy_malumot!B161 -> Eshbekov S.O.
A71: =""&umumiy_malumot!B147&" mikromoliya tashkilotining Kredit qo‘mitasi a’zolari "&umumiy_malumot!B147&" mikromoliya tashkilotining xulosasi va Mijoz tomonidan taqdim etilgan ma’lumotlar bilan tanishdilar:" -> «PULLOL BUSINESS MIKROMOLIYA TASHKILOTI» MChJ mikromoliya tashkilotining Kredit qo‘mitasi a’zolari «PULLOL BUSINESS MIKROMOLIYA TASHKILOTI» MChJ mikromoliya tashkilotining xulosasi va Mijoz tomonidan taqdim etilgan ma’lumotlar bilan tanishdilar:
A73: =umumiy_malumot!B150 -> Obidov A. Sh.
A75: =umumiy_malumot!B160 -> Omanlikov O.O.
A77: =umumiy_malumot!B159 -> Akramov R.N.

Sheet shartnoma
A1: =""&umumiy_malumot!B65&" shartnoma "&umumiy_malumot!B66&"" -> Mikroqarz shartnoma №43
A3: ="Toshkent shahri "&umumiy_malumot!B70&"" -> Toshkent shahri 2 fevral 2026 y.
A5: =""&umumiy_malumot!B147&", bundan buyon «Mikromoliya tashkiloti» deb nomlanuvchi, Ustav va 14.08.2023 yildagi 27-13/968-sonli Litsenziya asosida faoliyat yurituvchi "&umumiy_malumot!A150&" "&umumiy_malumot!B150&" bir tomondan va o‘z manfaati yo‘lida hamda o‘z nomidan harakat qiluvchi O‘zbekiston Respublikasi fuqarosi "&umumiy_malumot!B5&" (pasport raqami "&umumiy_malumot!B16&", "&umumiy_malumot!C20&" ), bundan buyon «Qarz oluvchi» deb nomlanuvchi, boshqa tomondan, birgalikda “Tomonlar” yoki alohida “Tomon” deb nomlanuvchilar, Qarz oluvchi tomonidan "&TEXT(umumiy_malumot!B2,"ДД.ММ.ГГГГ")&" yil,"&umumiy_malumot!B65&" olish uchun ariza berilganligini hisobga olib, ushbu "&umumiy_malumot!B65&" shartnomasini (bundan keyin – «Shartnoma») quyidagilar haqida tuzdilar:" -> «PULLOL BUSINESS MIKROMOLIYA TASHKILOTI» MChJ, bundan buyon «Mikromoliya tashkiloti» deb nomlanuvchi, Ustav va 14.08.2023 yildagi 27-13/968-sonli Litsenziya asosida faoliyat yurituvchi Direktor Obidov A. Sh. bir tomondan va o‘z manfaati yo‘lida hamda o‘z nomidan harakat qiluvchi O‘zbekiston Respublikasi fuqarosi SIMONYAN VADIM ROMANOVICH (pasport raqami AD 3925702, IIV 26266 tomonidan 12.07.2023 yilda berilgan ), bundan buyon «Qarz oluvchi» deb nomlanuvchi, boshqa tomondan, birgalikda “Tomonlar” yoki alohida “Tomon” deb nomlanuvchilar, Qarz oluvchi tomonidan 02.02.2026 yil,Mikroqarz olish uchun ariza berilganligini hisobga olib, ushbu Mikroqarz shartnomasini (bundan keyin – «Shartnoma») quyidagilar haqida tuzdilar:
A7: 1. SHARTNOMA PREDMETI
A8: ="1.1. Mikromoliya tashkiloti Qarz oluvchiga umumiy miqdori "&FIXED(umumiy_malumot!B75,2)&" ("&umumiy_malumot!B76&") bo‘lgan "&umumiy_malumot!B65&"ni "&umumiy_malumot!B71&" dan "&umumiy_malumot!B73&" gacha bo'lgan muddatga naqd pul va/yoki o'tkazmasi shaklida ajratadi." -> 1.1. Mikromoliya tashkiloti Qarz oluvchiga umumiy miqdori 50 000 000,00 (Ellik million so'm) bo‘lgan Mikroqarzni 2 fevral 2026 y. dan 2 fevral 2028 y. gacha bo'lgan muddatga naqd pul va/yoki o'tkazmasi shaklida ajratadi.
A9: ="1.2. Qarz oluvchi to‘lovlilik, muddatlilik va ta’minlanganlik tamoyillariga amal qilgan holda "&umumiy_malumot!B65&"dan foydalanish majburiyatini o‘z zimmasiga oladi." -> 1.2. Qarz oluvchi to‘lovlilik, muddatlilik va ta’minlanganlik tamoyillariga amal qilgan holda Mikroqarzdan foydalanish majburiyatini o‘z zimmasiga oladi.
A11: ="2. "&umumiy_malumot!D64&" BERISH VA QAYTARISH TARTIBI" -> 2. Mikroqarz BERISH VA QAYTARISH TARTIBI
A12: ="2.1. Ushbu Shartnomaning 1.1.-bandida ko‘rsatilgan summa miqdoridagi "&umumiy_malumot!B65&" Mikromoliya tashkiloti kassasidan naqd pul shaklida va/yoki plastik kartaga o‘tkazish yuli bilan beriladi." -> 2.1. Ushbu Shartnomaning 1.1.-bandida ko‘rsatilgan summa miqdoridagi Mikroqarz Mikromoliya tashkiloti kassasidan naqd pul shaklida va/yoki plastik kartaga o‘tkazish yuli bilan beriladi.
A13: ="2.2. "&umumiy_malumot!B65&" berish ushbu Shartnoma tuzilgan va Qarz oluvchi tomonidan ushbu shartnomaning 3-bo‘limiga muvofiq garov ta'minoti ta'minlangandan so‘ng 10 kalendar kundan kechiktirmay amalga oshiriladi." -> 2.2. Mikroqarz berish ushbu Shartnoma tuzilgan va Qarz oluvchi tomonidan ushbu shartnomaning 3-bo‘limiga muvofiq garov ta'minoti ta'minlangandan so‘ng 10 kalendar kundan kechiktirmay amalga oshiriladi.
A14: ="2.3. "&umumiy_malumot!B65&" Qarz oluvchi tomonidan ushbu Shartnomaning ajralmas qismi hisoblanadigan 1-ilovasida ko‘rsatilgan to‘lov jadvalida (bundan keyin - To‘lov jadvali) belgilangan miqdor, tartib va muddatlarda qaytariladi." -> 2.3. Mikroqarz Qarz oluvchi tomonidan ushbu Shartnomaning ajralmas qismi hisoblanadigan 1-ilovasida ko‘rsatilgan to‘lov jadvalida (bundan keyin - To‘lov jadvali) belgilangan miqdor, tartib va muddatlarda qaytariladi.
A15: ="2.4. Mikromoliya tashkiloti, "&umumiy_malumot!B65&" berilgan vaqtdan boshlab, "&umumiy_malumot!B65&" miqdorining qoldiq summasiga "&umumiy_malumot!B85&"% ("&umumiy_malumot!C86&") foiz yillik va yiliga 365/366 kunlik hisobidan foizlar hisoblaydi. To'lov jadvaliga muvofiq asosiy qarz bo'yicha navbatdagi to'lov buzilgan hollarda, "&"foiz stavkasi oshiriladi va Mikromoliya tashkiloti "&umumiy_malumot!B65&"ning muddati o'tgan asosiy qarz summasiga yillik "&umumiy_malumot!B88&"% ("&umumiy_malumot!B89&") foiz miqdorida foizlar hisoblaydi." -> 2.4. Mikromoliya tashkiloti, Mikroqarz berilgan vaqtdan boshlab, Mikroqarz miqdorining qoldiq summasiga 50% (Ellik ) foiz yillik va yiliga 365/366 kunlik hisobidan foizlar hisoblaydi. To'lov jadvaliga muvofiq asosiy qarz bo'yicha navbatdagi to'lov buzilgan hollarda, foiz stavkasi oshiriladi va Mikromoliya tashkiloti Mikroqarzning muddati o'tgan asosiy qarz summasiga yillik 155% (bir yuz ellik besh) foiz miqdorida foizlar hisoblaydi.
A16: 2.4.1 Qarz oluvchining xisob raqamlaridan shartnomaning 4.1.2 bandida ko‘rsatilgan tartibda yechib olingan pul mablag‘lari yechib olinganidan so‘ng mijoz tomonidan kredit qarzdorligini so‘ndirish uchun bank kassalari orqali to‘langan pul mablag‘lari yoki mijoz tomonidan kredit qarzdorligini so‘ndirish uchun bank kassalari orqali to‘langandan so‘ng qarz oluvchining xisob raqamlaridan shartnomaning 4.1.2 bandida ko‘rsatilgan tartibda yechib olingan pul mablag‘larining bir oylik kredit to‘lovini so‘ndirishga yo‘naltirilgan miqdoridan ortiqcha qismi qarz oluvchining to‘lov amalga oshirilgan kundan boshlab 3 bank ish kuni ichida yo‘llagan arizasiga asosan qarz oluvchiga qaytarilishi mumkun. 2.5. Foizlar To‘lov jadvaliga muvofiq asosiy qarzni qaytarish uchun belgilangan sanada to‘lanadi. 2.5.1 Qarz oluvchi tomonidan shartnomaning 2.4 bandida ko‘rsatilgan muddatda ortiqcha to‘langan pul mablag‘larini qaytarish to‘g‘risida ariza berilmagan taqdirda to‘langan ortiqcha pul mablag‘lari mijozning asosiy qarzdorligini so‘ndirishga yo‘naltiriladi.
A17: =CONCATENATE(C17,H17,I17) -> 2.6 Qarz oluvchi tomonidan to‘lov jadvalida ko‘rsatilgan muddatdan oldin xamda to‘lov jadvalida ko‘rsatilgan oylik kredit qarzdorligini so‘ndirish miqdoridan ko‘p miqdorda to‘lovni amalga oshirib, to‘langan pul mablag‘larini asosiy kredit qarzdorligini so‘ndirishga yo‘naltirilishini so‘ralganda qarz oluvchining kredit qarzdorligini so‘ndirish uchun to‘lagan pul mablag‘laridan kredit qarzdorligi to‘langan oy uchun to‘lov jadvali bo‘yicha so‘ndirilishi lozim bo‘lgan foiz qarzdorligi summasi, to‘lov jadvalida foiz qarzdorligi so‘ndirilishi ko‘rsatilgan muddatga qadar tashkilotning xisob raqamida saqlanib to‘lov jadvalida ko‘rsatilgan sanada oylik foiz qarzdorligini so‘ndirishga yo‘naltiriladi. 2.6.1. Qarz oluvchi tomonidan olingan Mikroqarzni va undan foydalanganlik uchun foizlarni qaytarish bo‘yicha muddati o‘tgan qarzdorlik hosil bo‘lganda Qarz oluvchi tomonidan ko‘rsatilgan qarzdorlikni to‘lash hisobiga to‘lanadigan summalar quyidagi tartibda hisobga olinadi: | C17: 2.6 Qarz oluvchi tomonidan to‘lov jadvalida ko‘rsatilgan muddatdan oldin xamda to‘lov jadvalida ko‘rsatilgan oylik kredit qarzdorligini so‘ndirish miqdoridan ko‘p miqdorda to‘lovni amalga oshirib, to‘langan pul mablag‘larini asosiy kredit qarzdorligini so‘ndirishga yo‘naltirilishini so‘ralganda qarz oluvchining kredit qarzdorligini so‘ndirish uchun to‘lagan pul mablag‘laridan kredit qarzdorligi to‘langan oy uchun to‘lov jadvali bo‘yicha so‘ndirilishi lozim bo‘lgan foiz qarzdorligi summasi, to‘lov jadvalida foiz qarzdorligi so‘ndirilishi ko‘rsatilgan muddatga qadar tashkilotning xisob raqamida saqlanib to‘lov jadvalida ko‘rsatilgan sanada oylik foiz qarzdorligini so‘ndirishga yo‘naltiriladi. 2.6.1. Qarz oluvchi tomonidan olingan | H17: =umumiy_malumot!B65 -> Mikroqarz | I17: ni va undan foydalanganlik uchun foizlarni qaytarish bo‘yicha muddati o‘tgan qarzdorlik hosil bo‘lganda Qarz oluvchi tomonidan ko‘rsatilgan qarzdorlikni to‘lash hisobiga to‘lanadigan summalar quyidagi tartibda hisobga olinadi:
A18: - jarima sanksiyalarni to‘lash; - to‘lov muddati o‘tgan foizlarni to‘lash; - to‘lov muddati o‘tgan asosiy qarzni to‘lash; - muddatli qarz bo‘yicha hisoblangan foizlarni to‘lash; - muddatli asosiy qarzni to‘lash; - Mikromoliya tashkilotning boshqa zararlarini qoplash.
A19: ="2.7. Qarz oluvchi Mikromoliya tashkilotining "&umumiy_malumot!B65&" bo‘yicha asosiy summasi, hisoblangan foizlarni, penya va boshqa moliyaviy talablarini ham naqd pul shaklida, ham naqdsiz shaklda qaytarib beradi." -> 2.7. Qarz oluvchi Mikromoliya tashkilotining Mikroqarz bo‘yicha asosiy summasi, hisoblangan foizlarni, penya va boshqa moliyaviy talablarini ham naqd pul shaklida, ham naqdsiz shaklda qaytarib beradi.
A20: ="2.8. Qarz oluvchi "&umumiy_malumot!B65&" miqdorini muddatidan oldin qaytarish, shuningdek, bu haqida Mikromoliya tashkilotini albatta ogohlantirgan holda ulardan aniq foydalangan muddat uchun hisoblangan foizlarni to‘lash huquqiga ega." -> 2.8. Qarz oluvchi Mikroqarz miqdorini muddatidan oldin qaytarish, shuningdek, bu haqida Mikromoliya tashkilotini albatta ogohlantirgan holda ulardan aniq foydalangan muddat uchun hisoblangan foizlarni to‘lash huquqiga ega.
A21: =CONCATENATE(C21,H21,I21) -> 2.9. Qarz oluvchi jismoniy shaxslarning kreditlar (Mikroqarzlar) bo‘yicha qarz yukini hisoblash tartibi, qarz yukining ruxsat etilgan miqdori, shuningdek qarz yuki o‘sishini cheklash to‘g‘risidagi Nizomga muvofiq (O’zbekiston Respublikasi Adliya vazirligi tomonidan 19.12.2019 y. 3205-son bilan ro‘yxatga olingan Markaziy bank Boshqaruvining 28.09.2019 y. 24/5-son qarori bilan tasdiqlangan), qarz yuki ko‘rsatkichi har bir qarz oluvchiga qarz beruvchi tomonidan Mikroqarz ajratishda uning summasi va qarz oluvchining amaldagi kredit (Mikroqarz) shartnomalari bo‘yicha asosiy qarz qoldig‘i yig‘indisi bazaviy hisoblash miqdorining 50 baravaridan oshganda hisoblanadi. | C21: ="2.9. Qarz oluvchi jismoniy shaxslarning kreditlar ("&umumiy_malumot!B65&"lar) bo‘yicha qarz yukini hisoblash tartibi, qarz yukining ruxsat etilgan miqdori, shuningdek qarz yuki o‘sishini cheklash to‘g‘risidagi Nizomga muvofiq (O’zbekiston Respublikasi Adliya vazirligi tomonidan 19.12.2019 y. 3205-son bilan ro‘yxatga " -> 2.9. Qarz oluvchi jismoniy shaxslarning kreditlar (Mikroqarzlar) bo‘yicha qarz yukini hisoblash tartibi, qarz yukining ruxsat etilgan miqdori, shuningdek qarz yuki o‘sishini cheklash to‘g‘risidagi Nizomga muvofiq (O’zbekiston Respublikasi Adliya vazirligi tomonidan 19.12.2019 y. 3205-son bilan ro‘yxatga | H21: ="olingan Markaziy bank Boshqaruvining 28.09.2019 y. 24/5-son qarori bilan tasdiqlangan), qarz yuki ko‘rsatkichi har bir qarz oluvchiga qarz beruvchi tomonidan "&umumiy_malumot!B65&" ajratishda uning summasi va " -> olingan Markaziy bank Boshqaruvining 28.09.2019 y. 24/5-son qarori bilan tasdiqlangan), qarz yuki ko‘rsatkichi har bir qarz oluvchiga qarz beruvchi tomonidan Mikroqarz ajratishda uning summasi va | I21: ="qarz oluvchining amaldagi kredit ("&umumiy_malumot!B65&") shartnomalari bo‘yicha asosiy qarz qoldig‘i yig‘indisi bazaviy hisoblash miqdorining 50 baravaridan oshganda hisoblanadi." -> qarz oluvchining amaldagi kredit (Mikroqarz) shartnomalari bo‘yicha asosiy qarz qoldig‘i yig‘indisi bazaviy hisoblash miqdorining 50 baravaridan oshganda hisoblanadi.
A22: ="3. "&umumiy_malumot!D64&" TA'MINOTI BO‘YICHA " -> 3. Mikroqarz TA'MINOTI BO‘YICHA
A23: ="3.1. Ushbu Shartnoma bo‘yicha taqdim etilgan "&umumiy_malumot!B65&" quyidagi garov bilan ta'minlanadi:" -> 3.1. Ushbu Shartnoma bo‘yicha taqdim etilgan Mikroqarz quyidagi garov bilan ta'minlanadi:
A24: =IF(umumiy_malumot!B103=umumiy_malumot!C103,shartnoma!A28,IF(umumiy_malumot!B103=umumiy_malumot!D103,shartnoma!A25,0)) -> 3.1.1. Mikromoliya tashkiloti va Qarz oluvchi tomonidan 2026 yil 2 fevralda imzolangan 1-sonli Garov predmeti qiymatini tasdiqlash dalolatnomasiga muvofiq TOSHKENT SHAHAR YUNUSOBOD TUMANI OTCHOPAR-1 MFY KARIM ZARIPOV KO'CHASI 8-6 UY manzilida joylashgan, umumiy yer maydoni - 166, qurilish osti maydoni- 87, umumiy foydali maydoni - 48.67 yashash maydoni - 30.84 bo'lgan, Yakka tartibdagi uy-joy - ko'rinishidagi ko'chmas mulk (bundan keyin “Garov predmeti”), egalik huquqiga ko'ra SIMONYAN VADIM ROMANOVICHga tegishli va kelishilgan garov qiymati 2026 yil 2 fevralda imzolangan 1-sonli Garov predmeti qiymatini tasdiqlash dalolatnomasiga muvofiq 70 000 000,00 (yetmish million so'm) so'mni tashkil qiladi. Garovning aniq shartlari tegishli tarzda notarial tasdiqlangan garov shartnomasi bilan belgilangan.
A25: =IF(umumiy_malumot!B92=umumiy_malumot!C92,shartnoma!A27,IF(umumiy_malumot!B92=umumiy_malumot!D92,shartnoma!A26,0)) -> 3.1.1. Mikromoliya tashkiloti va Qarz oluvchi tomonidan 2026 yil 2 fevralda imzolangan 1-sonli Garov predmeti qiymatini tasdiqlash dalolatnomasiga muvofiq TOSHKENT SHAHAR YUNUSOBOD TUMANI OTCHOPAR-1 MFY KARIM ZARIPOV KO'CHASI 8-6 UY manzilida joylashgan, umumiy yer maydoni - 166, qurilish osti maydoni- 87, umumiy foydali maydoni - 48.67 yashash maydoni - 30.84 bo'lgan, Yakka tartibdagi uy-joy - ko'rinishidagi ko'chmas mulk (bundan keyin “Garov predmeti”), egalik huquqiga ko'ra SIMONYAN VADIM ROMANOVICHga tegishli va kelishilgan garov qiymati 2026 yil 2 fevralda imzolangan 1-sonli Garov predmeti qiymatini tasdiqlash dalolatnomasiga muvofiq 70 000 000,00 (yetmish million so'm) so'mni tashkil qiladi. Garovning aniq shartlari tegishli tarzda notarial tasdiqlangan garov shartnomasi bilan belgilangan.
A26: ="3.1.1. "&umumiy_malumot!N126&" tomonidan "&umumiy_malumot!B143&" yil "&umumiy_malumot!B145&" "&umumiy_malumot!B144&"da imzolangan 1-sonli navbatdagi garov predmeti qiymatini tasdiqlash dalolatnomasiga muvofiq "&umumiy_malumot!C123&" manzilida joylashgan, "&umumiy_malumot!E126&" bo'lgan, "&umumiy_malumot!E125&" ko'rinishidagi ko'chmas mulk (bundan keyin “navbatdagi garov predmeti”), egalik huquqiga ko'ra "&umumiy_malumot!C117&"ga tegishli va kelishilgan garov qiymati "&umumiy_malumot!B143&" yil "&umumiy_malumot!B145&" "&umumiy_malumot!B144&"da imzolangan 1-sonli Garov predmeti qiymatini tasdiqlash dalolatnomasiga muvofiq "&FIXED(umumiy_malumot!B136,2)&" ("&umumiy_malumot!B138&") so'mni tashkil qiladi. Garovning aniq shartlari tegishli tarzda notarial tasdiqlangan garov shartnomasi bilan belgilangan." -> 3.1.1. Mikromoliya tashkiloti va Qarz oluvchi tomonidan 2026 yil 2 fevralda imzolangan 1-sonli navbatdagi garov predmeti qiymatini tasdiqlash dalolatnomasiga muvofiq TOSHKENT SHAHAR YUNUSOBOD TUMANI OTCHOPAR-1 MFY KARIM ZARIPOV KO'CHASI 8-6 UY manzilida joylashgan, umumiy yer maydoni - 166, qurilish osti maydoni- 87, umumiy foydali maydoni - 48.67 yashash maydoni - 30.84 bo'lgan, Yakka tartibdagi uy-joy - ko'rinishidagi ko'chmas mulk (bundan keyin “navbatdagi garov predmeti”), egalik huquqiga ko'ra SIMONYAN VADIM ROMANOVICHga tegishli va kelishilgan garov qiymati 2026 yil 2 fevralda imzolangan 1-sonli Garov predmeti qiymatini tasdiqlash dalolatnomasiga muvofiq 70 000 000,00 (yetmish million so'm) so'mni tashkil qiladi. Garovning aniq shartlari tegishli tarzda notarial tasdiqlangan garov shartnomasi bilan belgilangan.
A27: ="3.1.1. "&umumiy_malumot!N126&" tomonidan "&umumiy_malumot!B143&" yil "&umumiy_malumot!B145&" "&umumiy_malumot!B144&"da imzolangan 1-sonli Garov predmeti qiymatini tasdiqlash dalolatnomasiga muvofiq "&umumiy_malumot!C123&" manzilida joylashgan, "&umumiy_malumot!E126&" bo'lgan, "&umumiy_malumot!E125&" ko'rinishidagi ko'chmas mulk (bundan keyin “Garov predmeti”), egalik huquqiga ko'ra "&umumiy_malumot!C117&"ga tegishli va kelishilgan garov qiymati "&umumiy_malumot!B143&" yil "&umumiy_malumot!B145&" "&umumiy_malumot!B144&"da imzolangan 1-sonli Garov predmeti qiymatini tasdiqlash dalolatnomasiga muvofiq "&FIXED(umumiy_malumot!B136,2)&" ("&umumiy_malumot!B138&") so'mni tashkil qiladi. Garovning aniq shartlari tegishli tarzda notarial tasdiqlangan garov shartnomasi bilan belgilangan." -> 3.1.1. Mikromoliya tashkiloti va Qarz oluvchi tomonidan 2026 yil 2 fevralda imzolangan 1-sonli Garov predmeti qiymatini tasdiqlash dalolatnomasiga muvofiq TOSHKENT SHAHAR YUNUSOBOD TUMANI OTCHOPAR-1 MFY KARIM ZARIPOV KO'CHASI 8-6 UY manzilida joylashgan, umumiy yer maydoni - 166, qurilish osti maydoni- 87, umumiy foydali maydoni - 48.67 yashash maydoni - 30.84 bo'lgan, Yakka tartibdagi uy-joy - ko'rinishidagi ko'chmas mulk (bundan keyin “Garov predmeti”), egalik huquqiga ko'ra SIMONYAN VADIM ROMANOVICHga tegishli va kelishilgan garov qiymati 2026 yil 2 fevralda imzolangan 1-sonli Garov predmeti qiymatini tasdiqlash dalolatnomasiga muvofiq 70 000 000,00 (yetmish million so'm) so'mni tashkil qiladi. Garovning aniq shartlari tegishli tarzda notarial tasdiqlangan garov shartnomasi bilan belgilangan.
A28: =IF(umumiy_malumot!B92=umumiy_malumot!C92,A29,IF(umumiy_malumot!B92=umumiy_malumot!D92,A30,0)) -> 3.1.1. Mikromoliya tashkiloti va Qarz oluvchi tomonidan 2026 yil 2 fevralda imzolangan 1-sonli garov predmeti qiymatini tasdiqlash dalolatnomasiga muvofiq rangli, ishlab chiqarilgan yili – yil, dvigatel raqami , shassi - , kuzov turi - , kuzov raqami №, davlat raqam belgisi bo'lgan rusumli avtomashinasi (bundan keyin “Garov predmeti”), egalik huquqiga ega SIMONYAN VADIM ROMANOVICHga tegishli va kelishilgan garov qiymati 2026 yil 2 fevralda imzolangan 1-sonli Garov predmeti qiymatini tasdiqlash dalolatnomasiga muvifiq 70 000 000,00 (yetmish million so'm) so'mni tashkil qiladi. Garov garovining aniq shartlari tegishli notarial rasmiylashtirilgan garov shartnomasi bilan belgilanadi.
A29: ="3.1.1. "&umumiy_malumot!N126&" tomonidan "&umumiy_malumot!B143&" yil "&umumiy_malumot!B145&" "&umumiy_malumot!B144&"da imzolangan 1-sonli garov predmeti qiymatini tasdiqlash dalolatnomasiga muvofiq "&umumiy_malumot!B134&" rangli, ishlab chiqarilgan yili – "&umumiy_malumot!B135&" yil, dvigatel raqami "&umumiy_malumot!B131&", shassi - "&umumiy_malumot!B132&", kuzov turi - "&umumiy_malumot!B128&", kuzov raqami №"&umumiy_malumot!B129&", davlat raqam belgisi "&umumiy_malumot!B126&" bo'lgan "&umumiy_malumot!B125&" rusumli avtomashinasi (bundan keyin “Garov predmeti”), egalik huquqiga ega "&umumiy_malumot!B117&"ga tegishli va kelishilgan garov qiymati "&umumiy_malumot!B143&" yil "&umumiy_malumot!B145&" "&umumiy_malumot!B144&"da imzolangan 1-sonli Garov predmeti qiymatini tasdiqlash dalolatnomasiga muvifiq "&FIXED(umumiy_malumot!B136,2)&" ("&umumiy_malumot!B138&") so'mni tashkil qiladi. Garov garovining aniq shartlari tegishli notarial rasmiylashtirilgan garov shartnomasi bilan belgilanadi." -> 3.1.1. Mikromoliya tashkiloti va Qarz oluvchi tomonidan 2026 yil 2 fevralda imzolangan 1-sonli garov predmeti qiymatini tasdiqlash dalolatnomasiga muvofiq rangli, ishlab chiqarilgan yili – yil, dvigatel raqami , shassi - , kuzov turi - , kuzov raqami №, davlat raqam belgisi bo'lgan rusumli avtomashinasi (bundan keyin “Garov predmeti”), egalik huquqiga ega SIMONYAN VADIM ROMANOVICHga tegishli va kelishilgan garov qiymati 2026 yil 2 fevralda imzolangan 1-sonli Garov predmeti qiymatini tasdiqlash dalolatnomasiga muvifiq 70 000 000,00 (yetmish million so'm) so'mni tashkil qiladi. Garov garovining aniq shartlari tegishli notarial rasmiylashtirilgan garov shartnomasi bilan belgilanadi.
A30: ="3.1.1. "&umumiy_malumot!N126&" tomonidan "&umumiy_malumot!B143&" yil "&umumiy_malumot!B145&" "&umumiy_malumot!B144&"da imzolangan 1-sonli navbatdagi garov predmeti qiymatini tasdiqlash dalolatnomasiga muvofiq "&umumiy_malumot!B134&" rangli, ishlab chiqarilgan yili – "&umumiy_malumot!B135&" yil, dvigatel raqami "&umumiy_malumot!B131&", shassi - "&umumiy_malumot!B132&", kuzov turi - "&umumiy_malumot!B128&", kuzov raqami №"&umumiy_malumot!B129&", davlat raqam belgisi "&umumiy_malumot!B126&" bo'lgan "&umumiy_malumot!B125&" rusumli avtomashinasi (bundan keyin “navbatdagi garov predmeti”), egalik huquqiga ega "&umumiy_malumot!B117&"ga tegishli va kelishilgan garov qiymati "&umumiy_malumot!B143&" yil "&umumiy_malumot!B145&" "&umumiy_malumot!B144&"da imzolangan 1-sonli Garov predmeti qiymatini tasdiqlash dalolatnomasiga muvifiq "&FIXED(umumiy_malumot!B136,2)&" ("&umumiy_malumot!B138&") so'mni tashkil qiladi. Garov garovining aniq shartlari tegishli notarial rasmiylashtirilgan garov shartnomasi bilan belgilanadi." -> 3.1.1. Mikromoliya tashkiloti va Qarz oluvchi tomonidan 2026 yil 2 fevralda imzolangan 1-sonli navbatdagi garov predmeti qiymatini tasdiqlash dalolatnomasiga muvofiq rangli, ishlab chiqarilgan yili – yil, dvigatel raqami , shassi - , kuzov turi - , kuzov raqami №, davlat raqam belgisi bo'lgan rusumli avtomashinasi (bundan keyin “navbatdagi garov predmeti”), egalik huquqiga ega SIMONYAN VADIM ROMANOVICHga tegishli va kelishilgan garov qiymati 2026 yil 2 fevralda imzolangan 1-sonli Garov predmeti qiymatini tasdiqlash dalolatnomasiga muvifiq 70 000 000,00 (yetmish million so'm) so'mni tashkil qiladi. Garov garovining aniq shartlari tegishli notarial rasmiylashtirilgan garov shartnomasi bilan belgilanadi.
A31: =CONCATENATE(A32,B32) -> 3.2. Qonun hujjatlariga muvofiq rasmiylashtirilgan, “Garov predmeti” hisoblangan notarial tasdiqlangan garov shartnomasi, shu jumladan “Garov predmeti”ga taʼqiq quyilganligi tasdiqlovchi xujjat Qarz oluvchi tomonidan ushbu shartnoma tuzilgandan so‘ng 10 bank kuni mobaynida Mikromoliya tashkilotiga taqdim etilishi lozim. Garov shartnomasi belgilangan muddatda taqdim etilmagan hollarda, Mikromoliya tashkiloti Qarz oluvchining manziliga yozma bildirishnoma yuborish orqali Mikroqarz berishni rad etish va / yoki ushbu shartnomani bir tomonlama bekor qilish huquqiga egadir. Bunda ushbu shartnoma Qarz oluvchi tomonidan talabnoma olingan vaqtda yoki talabnoma pochta xizmati orqali yuborilgandan keyin uchinchi kuni bekor qilingan hisoblanadi.
A32: 3.2. Qonun hujjatlariga muvofiq rasmiylashtirilgan, “Garov predmeti” hisoblangan notarial tasdiqlangan garov shartnomasi, shu jumladan “Garov predmeti”ga taʼqiq quyilganligi tasdiqlovchi xujjat Qarz oluvchi tomonidan ushbu shartnoma tuzilgandan so‘ng 10 bank kuni mobaynida | B32: =CONCATENATE(A33,B33) -> Mikromoliya tashkilotiga taqdim etilishi lozim. Garov shartnomasi belgilangan muddatda taqdim etilmagan hollarda, Mikromoliya tashkiloti Qarz oluvchining manziliga yozma bildirishnoma yuborish orqali Mikroqarz berishni rad etish va / yoki ushbu shartnomani bir tomonlama bekor qilish huquqiga egadir. Bunda ushbu shartnoma Qarz oluvchi tomonidan talabnoma olingan vaqtda yoki talabnoma pochta xizmati orqali yuborilgandan keyin uchinchi kuni bekor qilingan hisoblanadi.
A33: =" Mikromoliya tashkilotiga taqdim etilishi lozim. Garov shartnomasi belgilangan muddatda taqdim etilmagan hollarda, Mikromoliya tashkiloti Qarz oluvchining manziliga yozma bildirishnoma yuborish orqali "&umumiy_malumot!B65&"" -> Mikromoliya tashkilotiga taqdim etilishi lozim. Garov shartnomasi belgilangan muddatda taqdim etilmagan hollarda, Mikromoliya tashkiloti Qarz oluvchining manziliga yozma bildirishnoma yuborish orqali Mikroqarz | B33: berishni rad etish va / yoki ushbu shartnomani bir tomonlama bekor qilish huquqiga egadir. Bunda ushbu shartnoma Qarz oluvchi tomonidan talabnoma olingan vaqtda yoki talabnoma pochta xizmati orqali yuborilgandan keyin uchinchi kuni bekor qilingan hisoblanadi.
A34: 3.3. Asosiy qarzni, foizlar yoki ushbu shartnoma bo‘yicha belgilangan muddatdan kechiktirilganligi bo‘yicha penyalarni qaytarish muddati kechiktirilishi yuzaga kelganda va/yoki ushbu shartnoma bo‘yicha boshqa majburiyatlar buzilishi holatlarida Mikromoliya tashkiloti O‘zbekiston Respublikasining amaldagi qonunchiligiga muvofiq qarzni undirish uchun qaytarib olinmaydigan va muqarrar tartibda unidirishni garov ob'ektiga qaratish huquqiga ega bo‘ladi.
A35: 3.4. O‘zbekiston Respublikasi "Garov to‘g‘risida" gi Qonunining 27-moddasiga muvofiq Garov predmeti sug‘urtalanmaydi. Lekin Mikromoliya tashkiloti Qarz oluvchidan Mikromoliya tashkiloti foydasiga Garov obʼektini ushbu Shartnomaning to‘liq amal qilish muddatiga har turli xavflardan sug‘urta qilishni talab qilish huquqiga ega. Bunda, sug‘urta xavflari ro‘yxati, shuningdek, sug‘urta kompaniyasi Mikromoliya tashkilotining xohishiga ko‘ra belgilanadi. Sug‘urta hodisasi yuz berganda Foyda oluvchi Mikromoliya tashkiloti bo‘lishi kerak.
A37: 4. MIKROMOLIYA TASHKILOTINING HUQUQ VA MAJBURIYATLARI
A38: 4.1. Mikromoliya tashkiloti quyidagi huquqlarga ega:
A39: =CONCATENATE(C39,H39) -> 4.1.1. Ushbu Shartnomada ko‘rsatilgan asoslar bo‘yicha Qarz oluvchiga Shartnomada ko‘zda tutilgan Mikroqarz summasini berilishini to‘liq yoki qisman rad etish. 4.1.2 “Mikromoliya Tashkiloti” qarz oluvchining nomidagi barcha plastik kartalaridan, xozirgi kunda mavjud va bundan so‘ng ochiladigan barcha xisob raqamlaridan (talab qilib olguncha, depozit jamg‘arib boriladigan plastik va boshqa istalgan xisob raqamlaridan) kredit to‘lovini kredit qaytarish jadvaliga asosan oyning kredit qarzdorligi qaytarilishi ko‘rsatilgan kuni akseptsiz tarzda yechib olish xuquqiga ega. | C39: ="4.1.1. Ushbu Shartnomada ko‘rsatilgan asoslar bo‘yicha Qarz oluvchiga Shartnomada ko‘zda tutilgan "&umumiy_malumot!B65&"" -> 4.1.1. Ushbu Shartnomada ko‘rsatilgan asoslar bo‘yicha Qarz oluvchiga Shartnomada ko‘zda tutilgan Mikroqarz | H39: summasini berilishini to‘liq yoki qisman rad etish. 4.1.2 “Mikromoliya Tashkiloti” qarz oluvchining nomidagi barcha plastik kartalaridan, xozirgi kunda mavjud va bundan so‘ng ochiladigan barcha xisob raqamlaridan (talab qilib olguncha, depozit jamg‘arib boriladigan plastik va boshqa istalgan xisob raqamlaridan) kredit to‘lovini kredit qaytarish jadvaliga asosan oyning kredit qarzdorligi qaytarilishi ko‘rsatilgan kuni akseptsiz tarzda yechib olish xuquqiga ega.
A40: ="4.1.2.1. "&umumiy_malumot!C64&" bo‘yicha qolgan barcha qarzdorlik, foiz to‘lovlarining muddatidan oldin qaytarilishini talab qilish, shuningdek, quyidagi holatlardan biri yuzaga kelganda undirishni garov ta'minotiga qaratish:" -> 4.1.2.1. Mikrokredit bo‘yicha qolgan barcha qarzdorlik, foiz to‘lovlarining muddatidan oldin qaytarilishini talab qilish, shuningdek, quyidagi holatlardan biri yuzaga kelganda undirishni garov ta'minotiga qaratish:
A41: a) ta'minotisiz qarzdorlik yuzaga kelganda;
A42: ="b) "&umumiy_malumot!B65&" summasiga hisoblanadigan asosiy qarz bo‘yicha muddati o‘tgan qarzdorlik va/yoki foizlarning yuzaga kelishi;" -> b) Mikroqarz summasiga hisoblanadigan asosiy qarz bo‘yicha muddati o‘tgan qarzdorlik va/yoki foizlarning yuzaga kelishi;
A43: с) Qarz oluvchini qonun hujjatlarida belgilangan tartibda to‘lov qobiliyatiga ega emas, muomalaga layoqatli emas yoki muomalaga layoqati cheklangan deb e'lon qilish;
A44: d) Mikromoliya tashkilotiga ushbu Shartnomaning 3.1.-bandida ko‘zda tutilgan hisobotlar, axborotlar va boshqa ma'lumotlarni o‘z vaqtida taqdim etmaslik, shuningdek, moliya-xo‘jalik faoliyat va daromad to‘g‘risidagi hisobotning ishonchsizligi holatlari aniqlanganda;
A45: e) Qarz oluvchi tomonidan ushbu shartnoma shartlariga amal qilmaslik;
A46: ="f) Qarz oluvchi "&umumiy_malumot!B65&" summasini olish uchun Mikromoliya tashkilotiga "&umumiy_malumot!B65&" taqdim etilishi to‘g‘risida ijobiy qaror qabul qilinishi uchun muhim hisoblangan masalalar bo‘yicha yolg‘on yoki to‘liq bo‘lmagan ma'lumotlarni taqdim etganligi aniqlanganda." -> f) Qarz oluvchi Mikroqarz summasini olish uchun Mikromoliya tashkilotiga Mikroqarz taqdim etilishi to‘g‘risida ijobiy qaror qabul qilinishi uchun muhim hisoblangan masalalar bo‘yicha yolg‘on yoki to‘liq bo‘lmagan ma'lumotlarni taqdim etganligi aniqlanganda.
A47: 4.1.3. Ushbu shartnomaning amal qilish jarayonida Qarz oluvchining moliyaviy holatini tekshirish va Qarz oluvchi tomonidan o‘z zimmasiga olgan majburiyatlarning bajarilishini nazorat qilish.
A48: 4.1.4. Qarz oluvchi tomonidan yoki ushbu Shartnoma bo‘yicha uchinchi shaxs tomonidan ta'minot sifatida garovga qo‘yilgan mol-mulkning tegishli holatdaligi va ulardan foydalanish bo‘yicha tekshiruvlar o‘tkazish.
A49: 4.1.5. Garovga qo‘yuvchi tomonidan garovga qo‘yilgan mol-mulk buzilgan yoki belgilangan maqsadda foydalanish uchun yaroqsiz holga kelganda, bu esa Mikromoliya tashkilotining ushbu Shartnoma bo‘yicha moliyaviy talablarini qondirishga qodir bo‘lgan bozor qiymatiga ma'lum darajada ta'sir ko‘rsatganda, yoki uchinchi shaxsning (kafil) moliyaviy holatining yomonlashuvi sababli ushbu Shartnomadan kelib chiqqan majburiyatlar bo‘yicha javob berish qobiliyatiga ega bo‘lmay qolgan holatlarda Qarz oluvchidan ta'minotning qo‘shimcha turini taqdim etish yoki almashtirishni talab qilish.
A50: 4.1.6. Qonun hujjatlariga muvofiq, Qarz oluvchi tomonidan ushbu Shartnoma bo‘yicha asosiy qarz, foizlar, penya va boshqa pul majburiyatlarini o‘z vaqtida to‘lamaslik holatlarida Qarz oluvchining bank hisobvaraqlaridagi pul mablag‘larini akseptsiz tartibda yechib olish to‘g‘risida to‘lov talabnomasini berish va bunga Qarz oluvchi qaytarib olinmaydigan va so‘zsiz rozilik bildiradi.
A51: ="4.1.7. Qarz oluvchini oldindan ogohlantirmasdan "&umumiy_malumot!B65&"ni qaytarish uchun haqiqatdan ham garov ta'minoti mavjudligini tekshirishni amalga oshirish." -> 4.1.7. Qarz oluvchini oldindan ogohlantirmasdan Mikroqarzni qaytarish uchun haqiqatdan ham garov ta'minoti mavjudligini tekshirishni amalga oshirish.
A52: 4.1.8. Ushbu shartnoma doirasida o‘z majburiyatlarini bajarish uchun uchinchi shaxslarga barcha zarur ma'lumotlarni yetkazish.
A53: 4.1.9. Istalgan vaqtda Qarz oluvchining avvaldan roziligini olmasdan turib ushbu Shartnoma bo‘yicha uchinchi tomonga da'vo qilish huquqini berish yoki uning foydasiga voz kechish.
A54: =CONCATENATE(C54,H54) -> 4.1.10. Qarz oluvchi taqdim etilgan Mikroqarzdan Shartnoma tuzilgan kundan boshlab 1 (bir) oy davomida foydalanmagan holatlarda, bu haqda Qarz oluvchini yozma ravishda xabardor qilib, Shartnoma bir tomonlama bekor qilish. Yozma xabarni jo‘natish sanasi uni taqdim etish yoki pochta orqali jo‘natish sanasi hisoblanadi. | C54: ="4.1.10. Qarz oluvchi taqdim etilgan "&umumiy_malumot!B65&"dan Shartnoma tuzilgan kundan boshlab 1 (bir) oy davomida foydalanmagan" -> 4.1.10. Qarz oluvchi taqdim etilgan Mikroqarzdan Shartnoma tuzilgan kundan boshlab 1 (bir) oy davomida foydalanmagan | H54: holatlarda, bu haqda Qarz oluvchini yozma ravishda xabardor qilib, Shartnoma bir tomonlama bekor qilish. Yozma xabarni jo‘natish sanasi uni taqdim etish yoki pochta orqali jo‘natish sanasi hisoblanadi.
A55: ="4.1.11. Oldingi "&umumiy_malumot!B65&" to‘liq to‘lanmagunga qadar yangi "&umumiy_malumot!B65&" berishni rad etish." -> 4.1.11. Oldingi Mikroqarz to‘liq to‘lanmagunga qadar yangi Mikroqarz berishni rad etish.
A57: 5. QARZ OLUVCHINING HUQUQ VA MAJBURIYATLARI
A58: 5.1. Qarz oluvchi quyidagi huquqlarga ega:
A59: ="5.1.1. Ushbu shartnomada nazarda tutilgan shartlar bo‘yicha "&umumiy_malumot!B65&" olish, shuningdek, Mikromoliya tashkiloti tomonidan ko‘rsatiladigan pullik xizmatlardan foydalanish." -> 5.1.1. Ushbu shartnomada nazarda tutilgan shartlar bo‘yicha Mikroqarz olish, shuningdek, Mikromoliya tashkiloti tomonidan ko‘rsatiladigan pullik xizmatlardan foydalanish.
A60: ="5.1.2. Shartnoma tuzilgan kundan boshlab 2 (ikki) hafta mobaynida Mikromoliya tashkilotiga bu haqda yozma xabarnoma yo‘llash orqali "&umumiy_malumot!B65&"ning foydalanilmagan summasidan voz kechish." -> 5.1.2. Shartnoma tuzilgan kundan boshlab 2 (ikki) hafta mobaynida Mikromoliya tashkilotiga bu haqda yozma xabarnoma yo‘llash orqali Mikroqarzning foydalanilmagan summasidan voz kechish.
A61: ="5.1.3. "&umumiy_malumot!C64&" xizmatlari ko‘rsatish qoidalari bilan tanishish." -> 5.1.3. Mikrokredit xizmatlari ko‘rsatish qoidalari bilan tanishish.
A62: ="5.1.4. O‘z huquq va majburiyatlari, shu jumladan "&umumiy_malumot!B65&" xizmatlari ko‘rsatish bilan bog‘liq barcha xarajatlar haqida aniq va to‘liq ma'lumot olish." -> 5.1.4. O‘z huquq va majburiyatlari, shu jumladan Mikroqarz xizmatlari ko‘rsatish bilan bog‘liq barcha xarajatlar haqida aniq va to‘liq ma'lumot olish.
A63: 5.1.5. Shartnoma bo‘yicha Mikromoliya tashkilotining majburiyatlarini bajarmaslik yoki tegishli darajada bajarmaslik natijasida yuzaga kelgan zararlarni qoplashni talab qilish.
A64: 5.2. Qarz oluvchining majburiyatlari:
A65: ="5.2.1. Mikromoliya tashkilotining birinchi talabi bilan zarur hujjatlar, shuningdek "&umumiy_malumot!B65&"dan foydalanishning butun davri davomida uning moliyaviy holati va to‘lash qobiliyatiga tegishli bo‘lgan ma'lumotlarni taqdim etish." -> 5.2.1. Mikromoliya tashkilotining birinchi talabi bilan zarur hujjatlar, shuningdek Mikroqarzdan foydalanishning butun davri davomida uning moliyaviy holati va to‘lash qobiliyatiga tegishli bo‘lgan ma'lumotlarni taqdim etish.
A66: 5.2.2. Ushbu shartnomada nazarda tutilgan hollarda garov ta'minotini almashtirish yoki qo‘shimcha ta'minot turini taqdim etish bo‘yicha Mikromoliya tashkiloti talablarini bajarish.
A67: ="5.2.3. To‘lov jadvaliga muvofiq "&umumiy_malumot!B65&", shuningdek hisoblangan foizlar to‘lovlarini amalga oshirish." -> 5.2.3. To‘lov jadvaliga muvofiq Mikroqarz, shuningdek hisoblangan foizlar to‘lovlarini amalga oshirish.
A68: =CONCATENATE(C68,H68) -> 5.2.4. Mikromoliya tashkiloti vakillariga o‘zlarining moliyaviy holati, yashash joyini tekshirishga, Mikromoliya tashkiloti foydasiga garovga qo‘yilgan mol-mulk saqlanishini tekshirishga ruxsat berish, shuningdek Qarz oluvchi ob'ektlaridan istalganiga tashrif buyurish va har qanday bino, inshoot, mol-mulk, asbob-uskunalar, tovarlar va xizmatlar, shuningdek ularning Mikroqarz mablag‘lari hisobiga moliyalashtirilgan hujjatlarni ko‘zdan kechirish va Mikromoliya tashkiloti tomonidan ushbu huquqni amalga oshirishga to‘sqinlik qilmaslik majburiyatini oladi. | C68: 5.2.4. Mikromoliya tashkiloti vakillariga o‘zlarining moliyaviy holati, yashash joyini tekshirishga, Mikromoliya tashkiloti foydasiga garovga qo‘yilgan mol-mulk saqlanishini tekshirishga ruxsat berish, shuningdek Qarz oluvchi ob'ektlaridan istalganiga tashrif buyurish va har qanday bino, inshoot, mol-mulk, asbob-uskunalar, tovarlar va xizmatlar, shuningdek ularning | H68: =" "&umumiy_malumot!B65&" mablag‘lari hisobiga moliyalashtirilgan hujjatlarni ko‘zdan kechirish va Mikromoliya tashkiloti tomonidan ushbu huquqni amalga oshirishga to‘sqinlik qilmaslik majburiyatini oladi." -> Mikroqarz mablag‘lari hisobiga moliyalashtirilgan hujjatlarni ko‘zdan kechirish va Mikromoliya tashkiloti tomonidan ushbu huquqni amalga oshirishga to‘sqinlik qilmaslik majburiyatini oladi.
A69: 5.2.5. Qarz oluvchining moliyaviy ahvoli yomonlashuvi va ushbu shartnoma bo‘yicha Qarz oluvchining Mikromoliya tashkiloti oldidagi majburiyatlarining bajarilmasligi va/yoki tegishli darajada bajarilmaslik xavfi yuzaga kelishiga olib keluvchi hech qanday majburiyat va choralarni o‘z zimmasiga olmaslik;
A70: ="5.2.6. Quyidagi holatlarda Mikromoliya tashkilotning birinchi talabi bilan "&umumiy_malumot!B65&" qaytarilishi bo‘yicha qo‘shimcha garov ta'minotini taqdim etish: " -> 5.2.6. Quyidagi holatlarda Mikromoliya tashkilotning birinchi talabi bilan Mikroqarz qaytarilishi bo‘yicha qo‘shimcha garov ta'minotini taqdim etish:
A71: - Qarz oluvchining moliyaviy holatining yomonlashuvi; - Garov ob'ekti va/yoki uning bir qismining yo‘q qilinishi, qiymatining pasayishi, qisman yoki to‘liq yo‘qotilishi; - qarz qaytarilmaslik xavfini ko‘paytiruvchi boshqa omillarning paydo bo‘lishi;
A72: ="5.2.7. Sud qarori asosida Qarz oluvchi – jismoniy shaxsning muomalaga layoqatsizligi yoki muomalaga layoqati cheklangan yoxud to‘lash qobiliyatiga ega emasligi (bankrotligi) tan olinganda, uning vasiysi yoki homiysi "&umumiy_malumot!B65&"ning asosiy summa bo‘yicha qarzdorlikni "&umumiy_malumot!B65&"dan aniq foydalanish muddati uchun foizlar bilan kechiktirmasdan to‘liq to‘lashi shart." -> 5.2.7. Sud qarori asosida Qarz oluvchi – jismoniy shaxsning muomalaga layoqatsizligi yoki muomalaga layoqati cheklangan yoxud to‘lash qobiliyatiga ega emasligi (bankrotligi) tan olinganda, uning vasiysi yoki homiysi Mikroqarzning asosiy summa bo‘yicha qarzdorlikni Mikroqarzdan aniq foydalanish muddati uchun foizlar bilan kechiktirmasdan to‘liq to‘lashi shart.
A73: ="5.2.8. Mikromoliya tashkilotining "&umumiy_malumot!B65&" umumiy summasi va hisoblangan foizlarni muddatidan oldin qaytarish to‘g‘risidagi talabini kechiktirmasdan bajarish." -> 5.2.8. Mikromoliya tashkilotining Mikroqarz umumiy summasi va hisoblangan foizlarni muddatidan oldin qaytarish to‘g‘risidagi talabini kechiktirmasdan bajarish. | H73: "&'Общие данные'!B59&"
A74: =CONCATENATE(C74,H74) -> 5.2.9. Mikromoliya tashkilotining talabi bo‘yicha Mikromoliya tashkiloti ko‘rgan, shu jumladan Mikroqarz bo‘yicha (asosiy qarz, foizlar va boshqalar) qarzdorlikni majburiy va/yoki muddatidan oldin qaytarish bo‘yicha qabul qilingan choralar bilan bog‘liq bo‘lgan barcha xarajatlari va zararlarni qoplash, shuningdek ushbu shartnoma doirasida unidruvni taqdim etilgan garov ta'minotiga qaratish. | C74: ="5.2.9. Mikromoliya tashkilotining talabi bo‘yicha Mikromoliya tashkiloti ko‘rgan, shu jumladan "&umumiy_malumot!B65&" bo‘yicha (asosiy qarz, foizlar va boshqalar)" -> 5.2.9. Mikromoliya tashkilotining talabi bo‘yicha Mikromoliya tashkiloti ko‘rgan, shu jumladan Mikroqarz bo‘yicha (asosiy qarz, foizlar va boshqalar) | H74: qarzdorlikni majburiy va/yoki muddatidan oldin qaytarish bo‘yicha qabul qilingan choralar bilan bog‘liq bo‘lgan barcha xarajatlari va zararlarni qoplash, shuningdek ushbu shartnoma doirasida unidruvni taqdim etilgan garov ta'minotiga qaratish.
A76: 6. TOMONLARNING JAVOBGARLIGI
A77: =CONCATENATE(C77,H77) -> 6.1. Mikromoliya tashkiloti tomonidan Qarz oluvchiga pul mablag‘larini ajratib berish bo‘yicha o‘z zimmasiga olgan majburiyatlarning Shartnomaning 1.1.-bandida keltirilgan summa va muddatlarda bajarilmaslik yoki tegishli tarzda bajarilmaslik holatlarida Mikromoliya tashkiloti muddatidan o‘tgan har bir kalendar kun uchun kechiktirilgan to‘lov summasining 0,1% miqdorida, biroq ushbu Shartnomaning 1.1.-bandida ko‘rsatilgan Mikroqarz miqdori umumiy summasining 50% dan ko‘p bo‘lmagan miqdorda penya ko‘rinishidagi neustoyka to‘lash majburiyatini o‘z zimmasiga oladi. | C77: 6.1. Mikromoliya tashkiloti tomonidan Qarz oluvchiga pul mablag‘larini ajratib berish bo‘yicha o‘z zimmasiga olgan majburiyatlarning Shartnomaning 1.1.-bandida keltirilgan summa va muddatlarda bajarilmaslik yoki tegishli tarzda bajarilmaslik holatlarida Mikromoliya tashkiloti muddatidan o‘tgan har bir kalendar kun uchun kechiktirilgan to‘lov summasining 0,1% miqdorida, biroq ushbu Shartnomaning 1.1.-bandida ko‘rsatilgan | H77: =""&umumiy_malumot!B65&" miqdori umumiy summasining 50% dan ko‘p bo‘lmagan miqdorda penya ko‘rinishidagi neustoyka to‘lash majburiyatini o‘z zimmasiga oladi." -> Mikroqarz miqdori umumiy summasining 50% dan ko‘p bo‘lmagan miqdorda penya ko‘rinishidagi neustoyka to‘lash majburiyatini o‘z zimmasiga oladi.
A78: 6.2. Jarima sanksiyalarni to‘lash Tomonlarni ushbu Shartnomada ko‘zda tutilgan zimmalaridagi majburiyatlarini bajarishdan ozod qilmaydi.
A79: 6.3. Tomonlarning ushbu Shartnomada nazarda tutilmagan javobgarligi O‘zbekiston Respublikasining amaldagi qonunchiligiga muvofiq belgilanadi.
A80: 6.4. Tomonlar O‘zbekiston Respublikasi Fuqarolik kodeksining 325-moddasiga muvofiq aybdor tomondan yetkazilgan zararni neustoykadan tashqari to‘la hajmda undirish huquqiga egadirlar.
A82: 7. FORS-MAJOR
A83: 7.1. Agar Tomonlar ular zimmasidagi majburiyatlarni tegishli darajada bajarishi yengib bo‘lmas kuch (fors-major) oqibatida mumkin bo‘lmay qolgan bo‘lsa, ya'ni aniq vaqt davri davomida aniq sharoitlarda favqulodda va oldini olib bo‘lmaydigan holatlar ekanligini isbotlay olmasalar, Shartnoma bo‘yicha o‘z majburiyatlarini bajarmagan yoki tegishli darajada bajarmagan Tomon uning shartlarini bajarishda javobgar hisoblanadi. Ushbu Shartnoma Tomonlari yengilmas kuch holatlariga quyidagilarni kiritadi: tabiiy ofat (zilzila, suv toshqini, chaqmoq chaqishi, vulqon otilishi, sel kelishi, ko‘chki, sunami va hokazo), Shartnoma bo‘yicha majburiyatlar bajarilish joyida temperatura – harorat, shamol kuchi va yog‘ingarchilik darajasining inson hayotiy faoliyati normasidan ortiq bo‘lishi; hokimiyat va boshqaruv organlari moratoriysi; qonuniy belgilangan tartibda tashkil etilgan ish tashlashlar va majburiyatlarning tegishli darajada bajarilishi uchun Shartnoma Tomonlari tarafidan yengib bo‘lmas kuch sifatida belgilangan boshqa holatlar.
A84: 7.2. Fors-major holati ta'sirida qolgan Tomon, bunday holatlar yuzaga kelgan kundan boshlab 7 (etti) kalendar kundan kechiktirmasdan boshqa Tomonni xabardor qilishi shart.
A85: 7.3. Fors-major holati boshlanganligi to‘g‘risida xabar qilmaslik yoki o‘z vaqtida xabar bermaslik fors-major holati boshlanganda Shartnoma bo‘yicha o‘z majburiyatlarini bajarish imkoniyatiga vaj qilib keltirish huquqiga ega emas.
A86: 7.4. Fors-major holati boshlanganligini vaj qilib ko‘rsatish huquqidan mahrum etilgan Tomon amaldagi qonun hujjatlariga muvofiq javobgar bo‘ladi.
A88: 8. NIZOLARNI HAL QILISH TARTIBI
A89: 8.1. Ushbu Shartnomadan kelib chiqadigan tomonlar o‘rtasidagi barcha nizolar va undan kelib chiqadigan majburiyatlar, shu jumladan shartnoma bajarilmasligi oqibatida yuzaga kelgan bajarilishi, o‘zgartirilishi, bekor qilinishi, tugatilishi Mikromoliya tashkilot joylashgan yerdagi taalluqli sudda yoki «CONSILIO» Mas'uliyati cheklangan jamiyat qoshidagi Hakamlik sudida, O‘zbekiston Respublikasining amaldagi qonun hujjatlari va uning reglamentiga muvofiq Hakamlik sudi raisi tomonidan tayinlangan, yakka tartibdagi hakamlik sudyasi tomonidan, sud ishlarini sud majlisi bayonnomasi tuzmasdan ko‘rib chiqilishi kerak bo‘ladi. U yoki bu sudga murojaat qilish huquqi da'vogarda qoladi.
A90: Qarzni undirish va garovdagi mol-mulkiga qaratish ham sud tartibida, ham suddan tashqari tartibda, shu jumladan notariusning ijro yozuvini olish yo‘li bilan amalga oshirilishi mumkin.
A91: ="8.2. Mikromoliya tashkiloti sud organlariga murojaat qilganidan keyin Qarz oluvchi tomonidan "&umumiy_malumot!B65&" bo‘yicha muddati o‘tgan qarzdorlikning to‘lanishi Mikromoliya tashkilotning "&umumiy_malumot!B65&" bo‘yicha qarzdorlikni muddatidan avval undirish, shu jumladan undiruvni garovdagi mol-mulkka qaratish yo‘li bilan undirish huquqidan mahrum qilmaydi." -> 8.2. Mikromoliya tashkiloti sud organlariga murojaat qilganidan keyin Qarz oluvchi tomonidan Mikroqarz bo‘yicha muddati o‘tgan qarzdorlikning to‘lanishi Mikromoliya tashkilotning Mikroqarz bo‘yicha qarzdorlikni muddatidan avval undirish, shu jumladan undiruvni garovdagi mol-mulkka qaratish yo‘li bilan undirish huquqidan mahrum qilmaydi.
A93: 9. SHARTNOMA SHARTLARI VA AMAL QILISH MUDDATI
A94: 9.1. Ushbu Shartnoma Tomonlar tarafidan imzolangandan keyin kuchga kiradi.
A95: ="9.2. Shartnomaning amal qilish muddati Qarz oluvchi "&umumiy_malumot!B65&"ni to‘liq qaytargan, hisoblangan foizlar, penya va boshqa pul majburiyatlarini to‘lagan kunda yakunlanadi." -> 9.2. Shartnomaning amal qilish muddati Qarz oluvchi Mikroqarzni to‘liq qaytargan, hisoblangan foizlar, penya va boshqa pul majburiyatlarini to‘lagan kunda yakunlanadi.
A96: 9.3. Ushbu Shartnomaga kiritiladigan barcha o‘zgartirish va qo‘shimchalar, ushbu Shartnomada kelishilgan holatlardan tashqari, ikkala Tomon tarafidan qo‘shimcha bitimni yozma shaklda imzolagan holda amalga oshiriladi.
A98: 10. SHAXSIY MA'LUMOTLARNI QAYTA ISHLASH
A99: 10.1. Ushbu shartnomani tuzish bilan, Qarz oluvchi Mikromoliya tashkilotiga uning shaxsiy ma'lumotlari, shu jumladan, familiyasi, ismi, otasining ismi, pasport ma'lumotlari (shu jumladan, pasport raqami, berilgan vaqti va sanasi, ro‘yxatdan o‘tgan manzili va boshqalar); aloqaga chiqish uchun ma'lumotlar (shu jumladan, telefon raqami, e-mail, pochta manzili va boshqalar); STIR, ushbu shartnoma maqsadiga tegishli bo‘lgan boshqa ma'lumotlarni har qanday maqsadda ishlov berishga rozilik beradi.
A100: 10.2. Rozilik, shu jumladan shahsiy ma'lumotlar bilan quyidagi harakatlarni amalga oshirishga beriladi: yig‘ish, tizimlashtirish, to‘plash, saqlash, aniqlashtirish (yangilash, o‘zgartirish), foydalanish; O‘zbekiston Respublikasi qonun hujjatlarida nazarda tutilgan hollar va darajada tarqatish, shu jumladan davlat organlari va boshqa tashkilotlarga taqdim etish, shaxsiy ma'lumotlarning egasizlantirish, blokirovka va yo‘q qilish.
A101: 10.3. Qarz oluvchi, shuningdek, Mikromoliya tashkiloti shartnoma doirasida olingan ma'lumotlarni kredit byurosi va garov reestri, skoring kompaniyasi, uyali aloqa operatori, sug‘urta kompaniyasi, reklama ishlab chiqaruvchilari va tarqatuvchilari, shuningdek Mikromoliya tashkilotining boshqa hamkorlariga taqdim etishga roziligini bildiradi.
A103: 11. BOSHQA SHARTLAR
A104: 11.1. Ushbu shartnoma kuchga kirganidan keyin, o‘zaro munosabatlarga aloqador barcha yozishmalar yoki kelishuvlar, o‘z kuchini yo‘qotadi.
A105: 11.2. Ushbu shartnomani bajarish, o‘zgartirish va bekor qilish bilan bog‘liq barcha yozishma va xabarnomalar Tomonlarning ushbu shartnomaning yakuniy qismida ko‘rsatilgan pochta manzillariga yuboriladi.
A106: 11.3. Ushbu shartnomani bajarish uchun zarur bo‘lgan ismi (nomlanishi), ro‘yxatdan o‘tgan joyi, haqiqiy yashash joyi, manzili (joylashgan yeri), bank rekvizitlari va boshqa ma'lumotlar o‘zgargan holatlarda, Tomonlarning har biri bunday o‘zgarishlar amalga oshgan kundan boshlab 5 (besh) kalendar kun ichida boshqa Tomonni bunday o‘zgarishlar haqida yozma ravishda xabardor qilishi shart.
A107: 11.4. Ushbu bitimni amalga oshirish bilan, Qarz oluvchi kelishuvning muhimligi va uni tuzishning yuridik oqibatlarini to‘liq tushunib yetishi, shu sababli Shartnomani tuzish yanglishishlar, aldov, zo‘ravonlik, tahdidlar, yomon niyatli bitim yoki murakkab holatlar (tutqinlik) ta'sirida emasligini tasdiqlaydi.
A108: 11.5. Ushbu shartnomada ko‘zda tutilmagan holatlarda Tomonlar O‘zbekiston Respublikasining amaldagi qonunchiligiga amal qiladilar.
A109: 11.6. Qarz oluvchi Mikromoliya tashkilotining oldindan yozma roziligini olmasdan turib o‘z majburiyatlari yoki huquqlarini uchinchi shaxslarga o‘tkaza olmaydi.
... A113: 12. TOMONLARNING YURIDIK MANZILLARI VA REKVIZITLARI:
A115: «Mikromoliya tashkiloti» | B115: «Qarz oluvchi»
A117: =umumiy_malumot!B148 -> «PULLOL BUSINESS MIKROMOLIYA TASHKILOTI» MChJ | B117: =umumiy_malumot!B5 -> SIMONYAN VADIM ROMANOVICH
...

Sheet grafik
F3: =""&umumiy_malumot!B74&" "&umumiy_malumot!B65&" shartnomasiga 1 sonli ilova" -> 2 fevral 2026 y.dan №43 Mikroqarz shartnomasiga 1 sonli ilova
A5: To'lov jadvali
A7: № | B7: To'lov muddati | C7: Asosiy qarz qoldig'i | D7: To'lov miqdori, so'm
D8: asosiy qarz | E8: foizlar | F8: jami*
A9: 1 | B9: ='График дифференц'!B8 -> 46101 | C9: =IF(umumiy_malumot!$B$77=umumiy_malumot!$C$77,'График дифференц'!C8,IF(umumiy_malumot!$B$77=umumiy_malumot!$D$77,'График аннуитет.'!C8)) -> 50000000 | D9: =IF(umumiy_malumot!$B$77=umumiy_malumot!$C$77,'График дифференц'!D8,IF(umumiy_malumot!$B$77=umumiy_malumot!$D$77,'График аннуитет.'!D8)) -> 12246.38 | E9: =IF(umumiy_malumot!$B$77=umumiy_malumot!$C$77,'График дифференц'!E8,IF(umumiy_malumot!$B$77=umumiy_malumot!$D$77,'График аннуитет.'!E8)) -> 3465753.6 | F9: =IF(umumiy_malumot!$B$77=umumiy_malumot!$C$77,'График дифференц'!F8,IF(umumiy_malumot!$B$77=umumiy_malumot!$D$77,'График аннуитет.'!F8)) -> 3478000
A10: 2 | B10: ='График дифференц'!B9 -> 46132 | C10: =IF(umumiy_malumot!$B$77=umumiy_malumot!$C$77,'График дифференц'!C9,IF(umumiy_malumot!$B$77=umumiy_malumot!$D$77,'График аннуитет.'!C9)) -> 49987754 | D10: =IF(umumiy_malumot!$B$77=umumiy_malumot!$C$77,'График дифференц'!D9,IF(umumiy_malumot!$B$77=umumiy_malumot!$D$77,'График аннуитет.'!D9)) -> 1142955.7 | E10: =IF(umumiy_malumot!$B$77=umumiy_malumot!$C$77,'График дифференц'!E9,IF(umumiy_malumot!$B$77=umumiy_malumot!$D$77,'График аннуитет.'!E9)) -> 2335044.3 | F10: =IF(umumiy_malumot!$B$77=umumiy_malumot!$C$77,'График дифференц'!F9,IF(umumiy_malumot!$B$77=umumiy_malumot!$D$77,'График аннуитет.'!F9)) -> 3478000
A11: 3 | B11: ='График дифференц'!B10 -> 46162 | C11: =IF(umumiy_malumot!$B$77=umumiy_malumot!$C$77,'График дифференц'!C10,IF(umumiy_malumot!$B$77=umumiy_malumot!$D$77,'График аннуитет.'!C10)) -> 48844798 | D11: =IF(umumiy_malumot!$B$77=umumiy_malumot!$C$77,'График дифференц'!D10,IF(umumiy_malumot!$B$77=umumiy_malumot!$D$77,'График аннуитет.'!D10)) -> 1269947.5 | E11: =IF(umumiy_malumot!$B$77=umumiy_malumot!$C$77,'График дифференц'!E10,IF(umumiy_malumot!$B$77=umumiy_malumot!$D$77,'График аннуитет.'!E10)) -> 2208052.5 | F11: =IF(umumiy_malumot!$B$77=umumiy_malumot!$C$77,'График дифференц'!F10,IF(umumiy_malumot!$B$77=umumiy_malumot!$D$77,'График аннуитет.'!F10)) -> 3478000
A12: 4 | B12: ='График дифференц'!B11 -> 46195 | C12: =IF(umumiy_malumot!$B$77=umumiy_malumot!$C$77,'График дифференц'!C11,IF(umumiy_malumot!$B$77=umumiy_malumot!$D$77,'График аннуитет.'!C11)) -> 47574850 | D12: =IF(umumiy_malumot!$B$77=umumiy_malumot!$C$77,'График дифференц'!D11,IF(umumiy_malumot!$B$77=umumiy_malumot!$D$77,'График аннуитет.'!D11)) -> 1112291.7 | E12: =IF(umumiy_malumot!$B$77=umumiy_malumot!$C$77,'График дифференц'!E11,IF(umumiy_malumot!$B$77=umumiy_malumot!$D$77,'График аннуитет.'!E11)) -> 2365708.3 | F12: =IF(umumiy_malumot!$B$77=umumiy_malumot!$C$77,'График дифференц'!F11,IF(umumiy_malumot!$B$77=umumiy_malumot!$D$77,'График аннуитет.'!F11)) -> 3478000 | H12: GRAFIKTA BO'SH JOY BO'LSA SKRIT' QILIB TASHLANG!!!
A13: 5 | B13: ='График дифференц'!B12 -> 46223 | C13: =IF(umumiy_malumot!$B$77=umumiy_malumot!$C$77,'График дифференц'!C12,IF(umumiy_malumot!$B$77=umumiy_malumot!$D$77,'График аннуитет.'!C12)) -> 46462559 | D13: =IF(umumiy_malumot!$B$77=umumiy_malumot!$C$77,'График дифференц'!D12,IF(umumiy_malumot!$B$77=umumiy_malumot!$D$77,'График аннуитет.'!D12)) -> 1517662 | E13: =IF(umumiy_malumot!$B$77=umumiy_malumot!$C$77,'График дифференц'!E12,IF(umumiy_malumot!$B$77=umumiy_malumot!$D$77,'График аннуитет.'!E12)) -> 1960338 | F13: =IF(umumiy_malumot!$B$77=umumiy_malumot!$C$77,'График дифференц'!F12,IF(umumiy_malumot!$B$77=umumiy_malumot!$D$77,'График аннуитет.'!F12)) -> 3478000
A14: 6 | B14: ='График дифференц'!B13 -> 46254 | C14: =IF(umumiy_malumot!$B$77=umumiy_malumot!$C$77,'График дифференц'!C13,IF(umumiy_malumot!$B$77=umumiy_malumot!$D$77,'График аннуитет.'!C13)) -> 44944897 | D14: =IF(umumiy_malumot!$B$77=umumiy_malumot!$C$77,'График дифференц'!D13,IF(umumiy_malumot!$B$77=umumiy_malumot!$D$77,'График аннуитет.'!D13)) -> 1378519.1 | E14: =IF(umumiy_malumot!$B$77=umumiy_malumot!$C$77,'График дифференц'!E13,IF(umumiy_malumot!$B$77=umumiy_malumot!$D$77,'График аннуитет.'!E13)) -> 2099480.9 | F14: =IF(umumiy_malumot!$B$77=umumiy_malumot!$C$77,'График дифференц'!F13,IF(umumiy_malumot!$B$77=umumiy_malumot!$D$77,'График аннуитет.'!F13)) -> 3478000
A15: 7 | B15: ='График дифференц'!B14 -> 46286 | C15: =IF(umumiy_malumot!$B$77=umumiy_malumot!$C$77,'График дифференц'!C14,IF(umumiy_malumot!$B$77=umumiy_malumot!$D$77,'График аннуитет.'!C14)) -> 43566378 | D15: =IF(umumiy_malumot!$B$77=umumiy_malumot!$C$77,'График дифференц'!D14,IF(umumiy_malumot!$B$77=umumiy_malumot!$D$77,'График аннуитет.'!D14)) -> 1377265 | E15: =IF(umumiy_malumot!$B$77=umumiy_malumot!$C$77,'График дифференц'!E14,IF(umumiy_malumot!$B$77=umumiy_malumot!$D$77,'График аннуитет.'!E14)) -> 2100735 | F15: =IF(umumiy_malumot!$B$77=umumiy_malumot!$C$77,'График дифференц'!F14,IF(umumiy_malumot!$B$77=umumiy_malumot!$D$77,'График аннуитет.'!F14)) -> 3478000
A16: 8 | B16: ='График дифференц'!B15 -> 46315 | C16: =IF(umumiy_malumot!$B$77=umumiy_malumot!$C$77,'График дифференц'!C15,IF(umumiy_malumot!$B$77=umumiy_malumot!$D$77,'График аннуитет.'!C15)) -> 42189113 | D16: =IF(umumiy_malumot!$B$77=umumiy_malumot!$C$77,'График дифференц'!D15,IF(umumiy_malumot!$B$77=umumiy_malumot!$D$77,'График аннуитет.'!D15)) -> 1634393.4 | E16: =IF(umumiy_malumot!$B$77=umumiy_malumot!$C$77,'График дифференц'!E15,IF(umumiy_malumot!$B$77=umumiy_malumot!$D$77,'График аннуитет.'!E15)) -> 1843606.6 | F16: =IF(umumiy_malumot!$B$77=umumiy_malumot!$C$77,'График дифференц'!F15,IF(umumiy_malumot!$B$77=umumiy_malumot!$D$77,'График аннуитет.'!F15)) -> 3478000
A17: 9 | B17: ='График дифференц'!B16 -> 46346 | C17: =IF(umumiy_malumot!$B$77=umumiy_malumot!$C$77,'График дифференц'!C16,IF(umumiy_malumot!$B$77=umumiy_malumot!$D$77,'График аннуитет.'!C16)) -> 40554719 | D17: =IF(umumiy_malumot!$B$77=umumiy_malumot!$C$77,'График дифференц'!D16,IF(umumiy_malumot!$B$77=umumiy_malumot!$D$77,'График аннуитет.'!D16)) -> 1583594.7 | E17: =IF(umumiy_malumot!$B$77=umumiy_malumot!$C$77,'График дифференц'!E16,IF(umumiy_malumot!$B$77=umumiy_malumot!$D$77,'График аннуитет.'!E16)) -> 1894405.3 | F17: =IF(umumiy_malumot!$B$77=umumiy_malumot!$C$77,'График дифференц'!F16,IF(umumiy_malumot!$B$77=umumiy_malumot!$D$77,'График аннуитет.'!F16)) -> 3478000
A18: 10 | B18: ='График дифференц'!B17 -> 46377 | C18: =IF(umumiy_malumot!$B$77=umumiy_malumot!$C$77,'График дифференц'!C17,IF(umumiy_malumot!$B$77=umumiy_malumot!$D$77,'График аннуитет.'!C17)) -> 38971125 | D18: =IF(umumiy_malumot!$B$77=umumiy_malumot!$C$77,'График дифференц'!D17,IF(umumiy_malumot!$B$77=umumiy_malumot!$D$77,'График аннуитет.'!D17)) -> 1657568.1 | E18: =IF(umumiy_malumot!$B$77=umumiy_malumot!$C$77,'График дифференц'!E17,IF(umumiy_malumot!$B$77=umumiy_malumot!$D$77,'График аннуитет.'!E17)) -> 1820431.9 | F18: =IF(umumiy_malumot!$B$77=umumiy_malumot!$C$77,'График дифференц'!F17,IF(umumiy_malumot!$B$77=umumiy_malumot!$D$77,'График аннуитет.'!F17)) -> 3478000
A19: 11 | B19: ='График дифференц'!B18 -> 46407 | C19: =IF(umumiy_malumot!$B$77=umumiy_malumot!$C$77,'График дифференц'!C18,IF(umumiy_malumot!$B$77=umumiy_malumot!$D$77,'График аннуитет.'!C18)) -> 37313556 | D19: =IF(umumiy_malumot!$B$77=umumiy_malumot!$C$77,'График дифференц'!D18,IF(umumiy_malumot!$B$77=umumiy_malumot!$D$77,'График аннуитет.'!D18)) -> 1791222.7 | E19: =IF(umumiy_malumot!$B$77=umumiy_malumot!$C$77,'График дифференц'!E18,IF(umumiy_malumot!$B$77=umumiy_malumot!$D$77,'График аннуитет.'!E18)) -> 1686777.3 | F19: =IF(umumiy_malumot!$B$77=umumiy_malumot!$C$77,'График дифференц'!F18,IF(umumiy_malumot!$B$77=umumiy_malumot!$D$77,'График аннуитет.'!F18)) -> 3478000
A20: 12 | B20: ='График дифференц'!B19 -> 46440 | C20: =IF(umumiy_malumot!$B$77=umumiy_malumot!$C$77,'График дифференц'!C19,IF(umumiy_malumot!$B$77=umumiy_malumot!$D$77,'График аннуитет.'!C19)) -> 35522334 | D20: =IF(umumiy_malumot!$B$77=umumiy_malumot!$C$77,'График дифференц'!D19,IF(umumiy_malumot!$B$77=umumiy_malumot!$D$77,'График аннуитет.'!D19)) -> 1711615.6 | E20: =IF(umumiy_malumot!$B$77=umumiy_malumot!$C$77,'График дифференц'!E19,IF(umumiy_malumot!$B$77=umumiy_malumot!$D$77,'График аннуитет.'!E19)) -> 1766384.4 | F20: =IF(umumiy_malumot!$B$77=umumiy_malumot!$C$77,'График дифференц'!F19,IF(umumiy_malumot!$B$77=umumiy_malumot!$D$77,'График аннуитет.'!F19)) -> 3478000
A21: 13 | B21: ='График дифференц'!B20 -> 46468 | C21: =IF(umumiy_malumot!$B$77=umumiy_malumot!$C$77,'График дифференц'!C20,IF(umumiy_malumot!$B$77=umumiy_malumot!$D$77,'График аннуитет.'!C20)) -> 33810718 | D21: =IF(umumiy_malumot!$B$77=umumiy_malumot!$C$77,'График дифференц'!D20,IF(umumiy_malumot!$B$77=umumiy_malumot!$D$77,'График аннуитет.'!D20)) -> 2051465.5 | E21: =IF(umumiy_malumot!$B$77=umumiy_malumot!$C$77,'График дифференц'!E20,IF(umumiy_malumot!$B$77=umumiy_malumot!$D$77,'График аннуитет.'!E20)) -> 1426534.5 | F21: =IF(umumiy_malumot!$B$77=umumiy_malumot!$C$77,'График дифференц'!F20,IF(umumiy_malumot!$B$77=umumiy_malumot!$D$77,'График аннуитет.'!F20)) -> 3478000
A22: 14 | B22: ='График дифференц'!B21 -> 46497 | C22: =IF(umumiy_malumot!$B$77=umumiy_malumot!$C$77,'График дифференц'!C21,IF(umumiy_malumot!$B$77=umumiy_malumot!$D$77,'График аннуитет.'!C21)) -> 31759253 | D22: =IF(umumiy_malumot!$B$77=umumiy_malumot!$C$77,'График дифференц'!D21,IF(umumiy_malumot!$B$77=umumiy_malumot!$D$77,'График аннуитет.'!D21)) -> 2090164.1 | E22: =IF(umumiy_malumot!$B$77=umumiy_malumot!$C$77,'График дифференц'!E21,IF(umumiy_malumot!$B$77=umumiy_malumot!$D$77,'График аннуитет.'!E21)) -> 1387835.9 | F22: =IF(umumiy_malumot!$B$77=umumiy_malumot!$C$77,'График дифференц'!F21,IF(umumiy_malumot!$B$77=umumiy_malumot!$D$77,'График аннуитет.'!F21)) -> 3478000
A23: 15 | B23: ='График дифференц'!B22 -> 46527 | C23: =IF(umumiy_malumot!$B$77=umumiy_malumot!$C$77,'График дифференц'!C22,IF(umumiy_malumot!$B$77=umumiy_malumot!$D$77,'График аннуитет.'!C22)) -> 29669088 | D23: =IF(umumiy_malumot!$B$77=umumiy_malumot!$C$77,'График дифференц'!D22,IF(umumiy_malumot!$B$77=umumiy_malumot!$D$77,'График аннуитет.'!D22)) -> 2136794.5 | E23: =IF(umumiy_malumot!$B$77=umumiy_malumot!$C$77,'График дифференц'!E22,IF(umumiy_malumot!$B$77=umumiy_malumot!$D$77,'График аннуитет.'!E22)) -> 1341205.5 | F23: =IF(umumiy_malumot!$B$77=umumiy_malumot!$C$77,'График дифференц'!F22,IF(umumiy_malumot!$B$77=umumiy_malumot!$D$77,'График аннуитет.'!F22)) -> 3478000
A24: 16 | B24: ='График дифференц'!B23 -> 46559 | C24: =IF(umumiy_malumot!$B$77=umumiy_malumot!$C$77,'График дифференц'!C23,IF(umumiy_malumot!$B$77=umumiy_malumot!$D$77,'График аннуитет.'!C23)) -> 27532294 | D24: =IF(umumiy_malumot!$B$77=umumiy_malumot!$C$77,'График дифференц'!D23,IF(umumiy_malumot!$B$77=umumiy_malumot!$D$77,'График аннуитет.'!D23)) -> 2150415.4 | E24: =IF(umumiy_malumot!$B$77=umumiy_malumot!$C$77,'График дифференц'!E23,IF(umumiy_malumot!$B$77=umumiy_malumot!$D$77,'График аннуитет.'!E23)) -> 1327584.6 | F24: =IF(umumiy_malumot!$B$77=umumiy_malumot!$C$77,'График дифференц'!F23,IF(umumiy_malumot!$B$77=umumiy_malumot!$D$77,'График аннуитет.'!F23)) -> 3478000
... A32: 24 | B32: ='График дифференц'!B31 -> 46785 | C32: =IF(umumiy_malumot!$B$77=umumiy_malumot!$C$77,'График дифференц'!C31,IF(umumiy_malumot!$B$77=umumiy_malumot!$D$77,'График аннуитет.'!C31)) -> 6760860.8 | D32: =IF(umumiy_malumot!$B$77=umumiy_malumot!$C$77,'График дифференц'!D31,IF(umumiy_malumot!$B$77=umumiy_malumot!$D$77,'График аннуитет.'!D31)) -> 6760860.8 | E32: =IF(umumiy_malumot!$B$77=umumiy_malumot!$C$77,'График дифференц'!E31,IF(umumiy_malumot!$B$77=umumiy_malumot!$D$77,'График аннуитет.'!E31)) -> 132076.88 | F32: =IF(umumiy_malumot!$B$77=umumiy_malumot!$C$77,'График дифференц'!F31,IF(umumiy_malumot!$B$77=umumiy_malumot!$D$77,'График аннуитет.'!F31)) -> 6892937.7
A33: =1+A32 -> 25 | B33: ='График дифференц'!B32 -> FALSE | C33: =IF(umumiy_malumot!$B$77=umumiy_malumot!$C$77,'График дифференц'!C32,IF(umumiy_malumot!$B$77=umumiy_malumot!$D$77,'График аннуитет.'!C32)) -> 0 | D33: =IF(umumiy_malumot!$B$77=umumiy_malumot!$C$77,'График дифференц'!D32,IF(umumiy_malumot!$B$77=umumiy_malumot!$D$77,'График аннуитет.'!D32)) -> 0 | E33: =IF(umumiy_malumot!$B$77=umumiy_malumot!$C$77,'График дифференц'!E32,IF(umumiy_malumot!$B$77=umumiy_malumot!$D$77,'График аннуитет.'!E32)) -> 0 | F33: =IF(umumiy_malumot!$B$77=umumiy_malumot!$C$77,'График дифференц'!F32,IF(umumiy_malumot!$B$77=umumiy_malumot!$D$77,'График аннуитет.'!F32)) -> 0
A34: =1+A33 -> 26 | B34: ='График дифференц'!B33 -> FALSE | C34: =IF(umumiy_malumot!$B$77=umumiy_malumot!$C$77,'График дифференц'!C33,IF(umumiy_malumot!$B$77=umumiy_malumot!$D$77,'График аннуитет.'!C33)) -> 0 | D34: =IF(umumiy_malumot!$B$77=umumiy_malumot!$C$77,'График дифференц'!D33,IF(umumiy_malumot!$B$77=umumiy_malumot!$D$77,'График аннуитет.'!D33)) -> 0 | E34: =IF(umumiy_malumot!$B$77=umumiy_malumot!$C$77,'График дифференц'!E33,IF(umumiy_malumot!$B$77=umumiy_malumot!$D$77,'График аннуитет.'!E33)) -> 0 | F34: =IF(umumiy_malumot!$B$77=umumiy_malumot!$C$77,'График дифференц'!F33,IF(umumiy_malumot!$B$77=umumiy_malumot!$D$77,'График аннуитет.'!F33)) -> 0
A35: =1+A34 -> 27 | B35: ='График дифференц'!B34 -> FALSE | C35: =IF(umumiy_malumot!$B$77=umumiy_malumot!$C$77,'График дифференц'!C34,IF(umumiy_malumot!$B$77=umumiy_malumot!$D$77,'График аннуитет.'!C34)) -> 0 | D35: =IF(umumiy_malumot!$B$77=umumiy_malumot!$C$77,'График дифференц'!D34,IF(umumiy_malumot!$B$77=umumiy_malumot!$D$77,'График аннуитет.'!D34)) -> 0 | E35: =IF(umumiy_malumot!$B$77=umumiy_malumot!$C$77,'График дифференц'!E34,IF(umumiy_malumot!$B$77=umumiy_malumot!$D$77,'График аннуитет.'!E34)) -> 0 | F35: =IF(umumiy_malumot!$B$77=umumiy_malumot!$C$77,'График дифференц'!F34,IF(umumiy_malumot!$B$77=umumiy_malumot!$D$77,'График аннуитет.'!F34)) -> 0
A36: =1+A35 -> 28 | B36: ='График дифференц'!B35 -> FALSE | C36: =IF(umumiy_malumot!$B$77=umumiy_malumot!$C$77,'График дифференц'!C35,IF(umumiy_malumot!$B$77=umumiy_malumot!$D$77,'График аннуитет.'!C35)) -> 0 | D36: =IF(umumiy_malumot!$B$77=umumiy_malumot!$C$77,'График дифференц'!D35,IF(umumiy_malumot!$B$77=umumiy_malumot!$D$77,'График аннуитет.'!D35)) -> 0 | E36: =IF(umumiy_malumot!$B$77=umumiy_malumot!$C$77,'График дифференц'!E35,IF(umumiy_malumot!$B$77=umumiy_malumot!$D$77,'График аннуитет.'!E35)) -> 0 | F36: =IF(umumiy_malumot!$B$77=umumiy_malumot!$C$77,'График дифференц'!F35,IF(umumiy_malumot!$B$77=umumiy_malumot!$D$77,'График аннуитет.'!F35)) -> 0
A37: =1+A36 -> 29 | B37: ='График дифференц'!B36 -> FALSE | C37: =IF(umumiy_malumot!$B$77=umumiy_malumot!$C$77,'График дифференц'!C36,IF(umumiy_malumot!$B$77=umumiy_malumot!$D$77,'График аннуитет.'!C36)) -> 0 | D37: =IF(umumiy_malumot!$B$77=umumiy_malumot!$C$77,'График дифференц'!D36,IF(umumiy_malumot!$B$77=umumiy_malumot!$D$77,'График аннуитет.'!D36)) -> 0 | E37: =IF(umumiy_malumot!$B$77=umumiy_malumot!$C$77,'График дифференц'!E36,IF(umumiy_malumot!$B$77=umumiy_malumot!$D$77,'График аннуитет.'!E36)) -> 0 | F37: =IF(umumiy_malumot!$B$77=umumiy_malumot!$C$77,'График дифференц'!F36,IF(umumiy_malumot!$B$77=umumiy_malumot!$D$77,'График аннуитет.'!F36)) -> 0
A38: =1+A37 -> 30 | B38: ='График дифференц'!B37 -> FALSE | C38: =IF(umumiy_malumot!$B$77=umumiy_malumot!$C$77,'График дифференц'!C37,IF(umumiy_malumot!$B$77=umumiy_malumot!$D$77,'График аннуитет.'!C37)) -> 0 | D38: =IF(umumiy_malumot!$B$77=umumiy_malumot!$C$77,'График дифференц'!D37,IF(umumiy_malumot!$B$77=umumiy_malumot!$D$77,'График аннуитет.'!D37)) -> 0 | E38: =IF(umumiy_malumot!$B$77=umumiy_malumot!$C$77,'График дифференц'!E37,IF(umumiy_malumot!$B$77=umumiy_malumot!$D$77,'График аннуитет.'!E37)) -> 0 | F38: =IF(umumiy_malumot!$B$77=umumiy_malumot!$C$77,'График дифференц'!F37,IF(umumiy_malumot!$B$77=umumiy_malumot!$D$77,'График аннуитет.'!F37)) -> 0
A39: =1+A38 -> 31 | B39: ='График дифференц'!B38 -> FALSE | C39: =IF(umumiy_malumot!$B$77=umumiy_malumot!$C$77,'График дифференц'!C38,IF(umumiy_malumot!$B$77=umumiy_malumot!$D$77,'График аннуитет.'!C38)) -> 0 | D39: =IF(umumiy_malumot!$B$77=umumiy_malumot!$C$77,'График дифференц'!D38,IF(umumiy_malumot!$B$77=umumiy_malumot!$D$77,'График аннуитет.'!D38)) -> 0 | E39: =IF(umumiy_malumot!$B$77=umumiy_malumot!$C$77,'График дифференц'!E38,IF(umumiy_malumot!$B$77=umumiy_malumot!$D$77,'График аннуитет.'!E38)) -> 0 | F39: =IF(umumiy_malumot!$B$77=umumiy_malumot!$C$77,'График дифференц'!F38,IF(umumiy_malumot!$B$77=umumiy_malumot!$D$77,'График аннуитет.'!F38)) -> 0
A40: =1+A39 -> 32 | B40: ='График дифференц'!B39 -> FALSE | C40: =IF(umumiy_malumot!$B$77=umumiy_malumot!$C$77,'График дифференц'!C39,IF(umumiy_malumot!$B$77=umumiy_malumot!$D$77,'График аннуитет.'!C39)) -> 0 | D40: =IF(umumiy_malumot!$B$77=umumiy_malumot!$C$77,'График дифференц'!D39,IF(umumiy_malumot!$B$77=umumiy_malumot!$D$77,'График аннуитет.'!D39)) -> 0 | E40: =IF(umumiy_malumot!$B$77=umumiy_malumot!$C$77,'График дифференц'!E39,IF(umumiy_malumot!$B$77=umumiy_malumot!$D$77,'График аннуитет.'!E39)) -> 0 | F40: =IF(umumiy_malumot!$B$77=umumiy_malumot!$C$77,'График дифференц'!F39,IF(umumiy_malumot!$B$77=umumiy_malumot!$D$77,'График аннуитет.'!F39)) -> 0
A41: =1+A40 -> 33 | B41: ='График дифференц'!B40 -> FALSE | C41: =IF(umumiy_malumot!$B$77=umumiy_malumot!$C$77,'График дифференц'!C40,IF(umumiy_malumot!$B$77=umumiy_malumot!$D$77,'График аннуитет.'!C40)) -> 0 | D41: =IF(umumiy_malumot!$B$77=umumiy_malumot!$C$77,'График дифференц'!D40,IF(umumiy_malumot!$B$77=umumiy_malumot!$D$77,'График аннуитет.'!D40)) -> 0 | E41: =IF(umumiy_malumot!$B$77=umumiy_malumot!$C$77,'График дифференц'!E40,IF(umumiy_malumot!$B$77=umumiy_malumot!$D$77,'График аннуитет.'!E40)) -> 0 | F41: =IF(umumiy_malumot!$B$77=umumiy_malumot!$C$77,'График дифференц'!F40,IF(umumiy_malumot!$B$77=umumiy_malumot!$D$77,'График аннуитет.'!F40)) -> 0
A42: =1+A41 -> 34 | B42: ='График дифференц'!B41 -> FALSE | C42: =IF(umumiy_malumot!$B$77=umumiy_malumot!$C$77,'График дифференц'!C41,IF(umumiy_malumot!$B$77=umumiy_malumot!$D$77,'График аннуитет.'!C41)) -> 0 | D42: =IF(umumiy_malumot!$B$77=umumiy_malumot!$C$77,'График дифференц'!D41,IF(umumiy_malumot!$B$77=umumiy_malumot!$D$77,'График аннуитет.'!D41)) -> 0 | E42: =IF(umumiy_malumot!$B$77=umumiy_malumot!$C$77,'График дифференц'!E41,IF(umumiy_malumot!$B$77=umumiy_malumot!$D$77,'График аннуитет.'!E41)) -> 0 | F42: =IF(umumiy_malumot!$B$77=umumiy_malumot!$C$77,'График дифференц'!F41,IF(umumiy_malumot!$B$77=umumiy_malumot!$D$77,'График аннуитет.'!F41)) -> 0
A43: =1+A42 -> 35 | B43: ='График дифференц'!B42 -> FALSE | C43: =IF(umumiy_malumot!$B$77=umumiy_malumot!$C$77,'График дифференц'!C42,IF(umumiy_malumot!$B$77=umumiy_malumot!$D$77,'График аннуитет.'!C42)) -> 0 | D43: =IF(umumiy_malumot!$B$77=umumiy_malumot!$C$77,'График дифференц'!D42,IF(umumiy_malumot!$B$77=umumiy_malumot!$D$77,'График аннуитет.'!D42)) -> 0 | E43: =IF(umumiy_malumot!$B$77=umumiy_malumot!$C$77,'График дифференц'!E42,IF(umumiy_malumot!$B$77=umumiy_malumot!$D$77,'График аннуитет.'!E42)) -> 0 | F43: =IF(umumiy_malumot!$B$77=umumiy_malumot!$C$77,'График дифференц'!F42,IF(umumiy_malumot!$B$77=umumiy_malumot!$D$77,'График аннуитет.'!F42)) -> 0
A44: =1+A43 -> 36 | B44: ='График дифференц'!B43 -> FALSE | C44: =IF(umumiy_malumot!$B$77=umumiy_malumot!$C$77,'График дифференц'!C43,IF(umumiy_malumot!$B$77=umumiy_malumot!$D$77,'График аннуитет.'!C43)) -> 0 | D44: =IF(umumiy_malumot!$B$77=umumiy_malumot!$C$77,'График дифференц'!D43,IF(umumiy_malumot!$B$77=umumiy_malumot!$D$77,'График аннуитет.'!D43)) -> 0 | E44: =IF(umumiy_malumot!$B$77=umumiy_malumot!$C$77,'График дифференц'!E43,IF(umumiy_malumot!$B$77=umumiy_malumot!$D$77,'График аннуитет.'!E43)) -> 0 | F44: =IF(umumiy_malumot!$B$77=umumiy_malumot!$C$77,'График дифференц'!F43,IF(umumiy_malumot!$B$77=umumiy_malumot!$D$77,'График аннуитет.'!F43)) -> 0
A45: =1+A44 -> 37 | B45: ='График дифференц'!B44 -> FALSE | C45: =IF(umumiy_malumot!$B$77=umumiy_malumot!$C$77,'График дифференц'!C44,IF(umumiy_malumot!$B$77=umumiy_malumot!$D$77,'График аннуитет.'!C44)) -> 0 | D45: =IF(umumiy_malumot!$B$77=umumiy_malumot!$C$77,'График дифференц'!D44,IF(umumiy_malumot!$B$77=umumiy_malumot!$D$77,'График аннуитет.'!D44)) -> 0 | E45: =IF(umumiy_malumot!$B$77=umumiy_malumot!$C$77,'График дифференц'!E44,IF(umumiy_malumot!$B$77=umumiy_malumot!$D$77,'График аннуитет.'!E44)) -> 0 | F45: =IF(umumiy_malumot!$B$77=umumiy_malumot!$C$77,'График дифференц'!F44,IF(umumiy_malumot!$B$77=umumiy_malumot!$D$77,'График аннуитет.'!F44)) -> 0
A46: =1+A45 -> 38 | B46: ='График дифференц'!B45 -> FALSE | C46: =IF(umumiy_malumot!$B$77=umumiy_malumot!$C$77,'График дифференц'!C45,IF(umumiy_malumot!$B$77=umumiy_malumot!$D$77,'График аннуитет.'!C57)) -> 0 | D46: =IF(umumiy_malumot!$B$77=umumiy_malumot!$C$77,'График дифференц'!D45,IF(umumiy_malumot!$B$77=umumiy_malumot!$D$77,'График аннуитет.'!D45)) -> 0 | E46: =IF(umumiy_malumot!$B$77=umumiy_malumot!$C$77,'График дифференц'!E45,IF(umumiy_malumot!$B$77=umumiy_malumot!$D$77,'График аннуитет.'!E45)) -> 0 | F46: =IF(umumiy_malumot!$B$77=umumiy_malumot!$C$77,'График дифференц'!F45,IF(umumiy_malumot!$B$77=umumiy_malumot!$D$77,'График аннуитет.'!F57)) -> 0
A47: =1+A46 -> 39 | B47: ='График дифференц'!B46 -> FALSE | C47: =IF(umumiy_malumot!$B$77=umumiy_malumot!$C$77,'График дифференц'!C46,IF(umumiy_malumot!$B$77=umumiy_malumot!$D$77,'График аннуитет.'!C58)) -> 0 | D47: =IF(umumiy_malumot!$B$77=umumiy_malumot!$C$77,'График дифференц'!D46,IF(umumiy_malumot!$B$77=umumiy_malumot!$D$77,'График аннуитет.'!D46)) -> 0 | E47: =IF(umumiy_malumot!$B$77=umumiy_malumot!$C$77,'График дифференц'!E46,IF(umumiy_malumot!$B$77=umumiy_malumot!$D$77,'График аннуитет.'!E46)) -> 0 | F47: =IF(umumiy_malumot!$B$77=umumiy_malumot!$C$77,'График дифференц'!F46,IF(umumiy_malumot!$B$77=umumiy_malumot!$D$77,'График аннуитет.'!F58)) -> 0
A48: =1+A47 -> 40 | B48: ='График дифференц'!B47 -> FALSE | C48: =IF(umumiy_malumot!$B$77=umumiy_malumot!$C$77,'График дифференц'!C47,IF(umumiy_malumot!$B$77=umumiy_malumot!$D$77,'График аннуитет.'!C59)) -> 0 | D48: =IF(umumiy_malumot!$B$77=umumiy_malumot!$C$77,'График дифференц'!D47,IF(umumiy_malumot!$B$77=umumiy_malumot!$D$77,'График аннуитет.'!D47)) -> 0 | E48: =IF(umumiy_malumot!$B$77=umumiy_malumot!$C$77,'График дифференц'!E47,IF(umumiy_malumot!$B$77=umumiy_malumot!$D$77,'График аннуитет.'!E47)) -> 0 | F48: =IF(umumiy_malumot!$B$77=umumiy_malumot!$C$77,'График дифференц'!F47,IF(umumiy_malumot!$B$77=umumiy_malumot!$D$77,'График аннуитет.'!F59)) -> 0
A49: =1+A48 -> 41 | B49: ='График дифференц'!B48 -> FALSE | C49: =IF(umumiy_malumot!$B$77=umumiy_malumot!$C$77,'График дифференц'!C48,IF(umumiy_malumot!$B$77=umumiy_malumot!$D$77,'График аннуитет.'!C60)) -> 0 | D49: =IF(umumiy_malumot!$B$77=umumiy_malumot!$C$77,'График дифференц'!D48,IF(umumiy_malumot!$B$77=umumiy_malumot!$D$77,'График аннуитет.'!D48)) -> 0 | E49: =IF(umumiy_malumot!$B$77=umumiy_malumot!$C$77,'График дифференц'!E48,IF(umumiy_malumot!$B$77=umumiy_malumot!$D$77,'График аннуитет.'!E48)) -> 0 | F49: =IF(umumiy_malumot!$B$77=umumiy_malumot!$C$77,'График дифференц'!F48,IF(umumiy_malumot!$B$77=umumiy_malumot!$D$77,'График аннуитет.'!F60)) -> 0
A50: =1+A49 -> 42 | B50: ='График дифференц'!B49 -> FALSE | C50: =IF(umumiy_malumot!$B$77=umumiy_malumot!$C$77,'График дифференц'!C49,IF(umumiy_malumot!$B$77=umumiy_malumot!$D$77,'График аннуитет.'!C61)) -> 0 | D50: =IF(umumiy_malumot!$B$77=umumiy_malumot!$C$77,'График дифференц'!D49,IF(umumiy_malumot!$B$77=umumiy_malumot!$D$77,'График аннуитет.'!D49)) -> 0 | E50: =IF(umumiy_malumot!$B$77=umumiy_malumot!$C$77,'График дифференц'!E49,IF(umumiy_malumot!$B$77=umumiy_malumot!$D$77,'График аннуитет.'!E49)) -> 0 | F50: =IF(umumiy_malumot!$B$77=umumiy_malumot!$C$77,'График дифференц'!F49,IF(umumiy_malumot!$B$77=umumiy_malumot!$D$77,'График аннуитет.'!F61)) -> 0
A51: =1+A50 -> 43 | B51: ='График дифференц'!B50 -> FALSE | C51: =IF(umumiy_malumot!$B$77=umumiy_malumot!$C$77,'График дифференц'!C50,IF(umumiy_malumot!$B$77=umumiy_malumot!$D$77,'График аннуитет.'!C62)) -> 0 | D51: =IF(umumiy_malumot!$B$77=umumiy_malumot!$C$77,'График дифференц'!D50,IF(umumiy_malumot!$B$77=umumiy_malumot!$D$77,'График аннуитет.'!D50)) -> 0 | E51: =IF(umumiy_malumot!$B$77=umumiy_malumot!$C$77,'График дифференц'!E50,IF(umumiy_malumot!$B$77=umumiy_malumot!$D$77,'График аннуитет.'!E50)) -> 0 | F51: =IF(umumiy_malumot!$B$77=umumiy_malumot!$C$77,'График дифференц'!F50,IF(umumiy_malumot!$B$77=umumiy_malumot!$D$77,'График аннуитет.'!F62)) -> 0
A52: =1+A51 -> 44 | B52: ='График дифференц'!B51 -> FALSE | C52: =IF(umumiy_malumot!$B$77=umumiy_malumot!$C$77,'График дифференц'!C51,IF(umumiy_malumot!$B$77=umumiy_malumot!$D$77,'График аннуитет.'!C63)) -> 0 | D52: =IF(umumiy_malumot!$B$77=umumiy_malumot!$C$77,'График дифференц'!D51,IF(umumiy_malumot!$B$77=umumiy_malumot!$D$77,'График аннуитет.'!D51)) -> 0 | E52: =IF(umumiy_malumot!$B$77=umumiy_malumot!$C$77,'График дифференц'!E51,IF(umumiy_malumot!$B$77=umumiy_malumot!$D$77,'График аннуитет.'!E51)) -> 0 | F52: =IF(umumiy_malumot!$B$77=umumiy_malumot!$C$77,'График дифференц'!F51,IF(umumiy_malumot!$B$77=umumiy_malumot!$D$77,'График аннуитет.'!F63)) -> 0
A53: =1+A52 -> 45 | B53: ='График дифференц'!B52 -> FALSE | C53: =IF(umumiy_malumot!$B$77=umumiy_malumot!$C$77,'График дифференц'!C52,IF(umumiy_malumot!$B$77=umumiy_malumot!$D$77,'График аннуитет.'!C64)) -> 0 | D53: =IF(umumiy_malumot!$B$77=umumiy_malumot!$C$77,'График дифференц'!D52,IF(umumiy_malumot!$B$77=umumiy_malumot!$D$77,'График аннуитет.'!D52)) -> 0 | E53: =IF(umumiy_malumot!$B$77=umumiy_malumot!$C$77,'График дифференц'!E52,IF(umumiy_malumot!$B$77=umumiy_malumot!$D$77,'График аннуитет.'!E52)) -> 0 | F53: =IF(umumiy_malumot!$B$77=umumiy_malumot!$C$77,'График дифференц'!F52,IF(umumiy_malumot!$B$77=umumiy_malumot!$D$77,'График аннуитет.'!F64)) -> 0
A54: =1+A53 -> 46 | B54: ='График дифференц'!B53 -> FALSE | C54: =IF(umumiy_malumot!$B$77=umumiy_malumot!$C$77,'График дифференц'!C53,IF(umumiy_malumot!$B$77=umumiy_malumot!$D$77,'График аннуитет.'!C65)) -> 0 | D54: =IF(umumiy_malumot!$B$77=umumiy_malumot!$C$77,'График дифференц'!D53,IF(umumiy_malumot!$B$77=umumiy_malumot!$D$77,'График аннуитет.'!D53)) -> 0 | E54: =IF(umumiy_malumot!$B$77=umumiy_malumot!$C$77,'График дифференц'!E53,IF(umumiy_malumot!$B$77=umumiy_malumot!$D$77,'График аннуитет.'!E53)) -> 0 | F54: =IF(umumiy_malumot!$B$77=umumiy_malumot!$C$77,'График дифференц'!F53,IF(umumiy_malumot!$B$77=umumiy_malumot!$D$77,'График аннуитет.'!F65)) -> 0
A55: =1+A54 -> 47 | B55: ='График дифференц'!B54 -> FALSE | C55: =IF(umumiy_malumot!$B$77=umumiy_malumot!$C$77,'График дифференц'!C54,IF(umumiy_malumot!$B$77=umumiy_malumot!$D$77,'График аннуитет.'!C66)) -> 0 | D55: =IF(umumiy_malumot!$B$77=umumiy_malumot!$C$77,'График дифференц'!D54,IF(umumiy_malumot!$B$77=umumiy_malumot!$D$77,'График аннуитет.'!D54)) -> 0 | E55: =IF(umumiy_malumot!$B$77=umumiy_malumot!$C$77,'График дифференц'!E54,IF(umumiy_malumot!$B$77=umumiy_malumot!$D$77,'График аннуитет.'!E54)) -> 0 | F55: =IF(umumiy_malumot!$B$77=umumiy_malumot!$C$77,'График дифференц'!F54,IF(umumiy_malumot!$B$77=umumiy_malumot!$D$77,'График аннуитет.'!F66)) -> 0
A56: =1+A55 -> 48 | B56: ='График дифференц'!B55 -> FALSE | C56: =IF(umumiy_malumot!$B$77=umumiy_malumot!$C$77,'График дифференц'!C55,IF(umumiy_malumot!$B$77=umumiy_malumot!$D$77,'График аннуитет.'!C67)) -> 0 | D56: =IF(umumiy_malumot!$B$77=umumiy_malumot!$C$77,'График дифференц'!D55,IF(umumiy_malumot!$B$77=umumiy_malumot!$D$77,'График аннуитет.'!D55)) -> 0 | E56: =IF(umumiy_malumot!$B$77=umumiy_malumot!$C$77,'График дифференц'!E55,IF(umumiy_malumot!$B$77=umumiy_malumot!$D$77,'График аннуитет.'!E55)) -> 0 | F56: =IF(umumiy_malumot!$B$77=umumiy_malumot!$C$77,'График дифференц'!F55,IF(umumiy_malumot!$B$77=umumiy_malumot!$D$77,'График аннуитет.'!F67)) -> 0
B57: JAMI | D57: =IF(umumiy_malumot!$B$77=umumiy_malumot!$C$77,'График дифференц'!D56,IF(umumiy_malumot!$B$77=umumiy_malumot!$D$77,'График аннуитет.'!D56)) -> 50000000 | E57: =IF(umumiy_malumot!$B$77=umumiy_malumot!$C$77,'График дифференц'!E56,IF(umumiy_malumot!$B$77=umumiy_malumot!$D$77,'График аннуитет.'!E56)) -> 36886938 | F57: =SUM(F9:F56) -> 86886938
A59: ="*"&umumiy_malumot!C64&" bo‘yicha to‘lovlar to‘lov jadvalida ko‘rsatilmagan sanalarda to‘langan taqdirda, to‘lov summasi mikroqarz shartnomasining 2.4.-bandiga muvofiq "&umumiy_malumot!B65&" qoldig‘iga hisoblangan foizlar summasiga o‘zgartiriladi." -> *Mikrokredit bo‘yicha to‘lovlar to‘lov jadvalida ko‘rsatilmagan sanalarda to‘langan taqdirda, to‘lov summasi mikroqarz shartnomasining 2.4.-bandiga muvofiq Mikroqarz qoldig‘iga hisoblangan foizlar summasiga o‘zgartiriladi.
A61: «Mikromoliya tashkiloti » | D61: «Qarz oluvchi»
A63: =shartnoma!A117 -> «PULLOL BUSINESS MIKROMOLIYA TASHKILOTI» MChJ | D63: =shartnoma!B117 -> SIMONYAN VADIM ROMANOVICH
A64: =shartnoma!A119 -> Manzil: Toshkent shahri, Yakkasaroy tumani, Rakat ko'chasi, 10-uy, 18 xonadon | D64: =shartnoma!B119 -> Manzil: TOSHKENT SHAHAR YUNUSOBOD TUMANI OTCHOPAR-1 MFY KARIM ZARIPOV KO'CHASI 8-6 UY
A65: =shartnoma!A120 -> h/r: № 20208000405643889001 | D65: =shartnoma!B121 -> pasport seriyasi: AD 3925702, IIV 26266 tomonidan 12.07.2023 yilda berilgan
A66: =shartnoma!A121 -> MFO: №01088 в ATB “Kapitalbank” Markaziy amaliyotlar bo'limi
A67: =shartnoma!A122 -> STIR: 310430149 | D67: =shartnoma!B122 -> Tel: 93 554 55 99 MIJOZ
A68: =shartnoma!A123 -> Tel: (97) 714 14 14 | D68: =shartnoma!B123 -> 99 899 80 88 JIYANI
A69: =shartnoma!A124 -> (71) 555 10 02 17 | D69: =shartnoma!B124 -> 71 212 15 05 UY
D70: =IF(shartnoma!B125=0,"",shartnoma!B125)
A71: =shartnoma!A126 -> Direktor | D71: =shartnoma!B126 -> SIMONYAN V. R. __________________
A73: =shartnoma!A129 -> Obidov A. Sh. ________________

Sheet garov_ariza
B6: =umumiy_malumot!B148 -> «PULLOL BUSINESS MIKROMOLIYA TASHKILOTI» MChJ
B7: =""&umumiy_malumot!A150&"i "&umumiy_malumot!B150&"ga" -> Direktori Obidov A. Sh.ga
B8: =""&umumiy_malumot!C105&"dan" -> dan
B9: =umumiy_malumot!B111 -> SIMONYAN VADIM ROMANOVICH
B10: =umumiy_malumot!C111 -> SIMONYAN VADIM ROMANOVICH
B11: dan
A13: =IF(umumiy_malumot!B103="Avtotransport",A14,A15) -> SIMONYAN VADIM ROMANOVICH tomonidan so’ralayotgan 24 (yigirma to'rt) oy muddatga, 50 000 000 (Ellik million so'm) miqdoridagi Mikroqarzning ta’minoti sifatida menga mulk huquqi asosida tegishli bo’lgan Yakka tartibdagi uy-joy, umumiy maydoni 48.67 va yashash maydoni 87 TOSHKENT SHAHAR YUNUSOBOD TUMANI OTCHOPAR-1 MFY KARIM ZARIPOV KO'CHASI 8-6 UY manzilda joylashgan ko'chmas mulkni qabul qilishingizni so’rayman:
A14: =""&umumiy_malumot!B12&" tomonidan so’ralayotgan "&umumiy_malumot!B81&" ("&umumiy_malumot!B82&") oy muddatga, "&FIXED(umumiy_malumot!B75,0)&" ("&umumiy_malumot!B76&") miqdoridagi "&umumiy_malumot!B65&"ning ta’minoti sifatida menga mulk huquqi asosida tegishli bo’lgan "&umumiy_malumot!B125&", "&umumiy_malumot!B127&", "&umumiy_malumot!B130&", "&umumiy_malumot!B133&", avtotransport vositasini qabul qilishingizni so’rayman:" -> SIMONYAN VADIM ROMANOVICH tomonidan so’ralayotgan 24 (yigirma to'rt) oy muddatga, 50 000 000 (Ellik million so'm) miqdoridagi Mikroqarzning ta’minoti sifatida menga mulk huquqi asosida tegishli bo’lgan , kuzov turi - , kuzov raqami , dvigatel raqami , shassi raqami - , rangi - , ishlab chiqarilgan yili - , avtotransport vositasini qabul qilishingizni so’rayman:
A15: =""&umumiy_malumot!B12&" tomonidan so’ralayotgan "&umumiy_malumot!B81&" ("&umumiy_malumot!B82&") oy muddatga, "&FIXED(umumiy_malumot!B75,0)&" ("&umumiy_malumot!B76&") miqdoridagi "&umumiy_malumot!B65&"ning ta’minoti sifatida menga mulk huquqi asosida tegishli bo’lgan "&umumiy_malumot!C126&", umumiy maydoni "&umumiy_malumot!C130&" va yashash maydoni "&umumiy_malumot!C133&" "&umumiy_malumot!C123&" manzilda joylashgan ko'chmas mulkni qabul qilishingizni so’rayman:" -> SIMONYAN VADIM ROMANOVICH tomonidan so’ralayotgan 24 (yigirma to'rt) oy muddatga, 50 000 000 (Ellik million so'm) miqdoridagi Mikroqarzning ta’minoti sifatida menga mulk huquqi asosida tegishli bo’lgan Yakka tartibdagi uy-joy, umumiy maydoni 48.67 va yashash maydoni 87 TOSHKENT SHAHAR YUNUSOBOD TUMANI OTCHOPAR-1 MFY KARIM ZARIPOV KO'CHASI 8-6 UY manzilda joylashgan ko'chmas mulkni qabul qilishingizni so’rayman:
B18: Sana:
A19: =umumiy_malumot!C106 -> 0 | B19: =umumiy_malumot!B2 -> 02.02.2026
A20: =IF(umumiy_malumot!B93="yo’q",CONCATENATE(A24," ",A28,A22),"")
A22: =" xususiy faoliyat ko'rsatuvchi notarius tomonidan "&umumiy_malumot!B98&" "&umumiy_malumot!B99&" berilgan ishonchnomaga asosan " -> xususiy faoliyat ko'rsatuvchi notarius tomonidan berilgan ishonchnomaga asosan
A24: ="№"&umumiy_malumot!B100& "" -> №
A25: =umumiy_malumot!B102 -> 00.01.1900
A26: =TEXT(A25,"ДД.ММ.ГГГГ") -> 00.01.1900
A27: . sanasidan
A28: =CONCATENATE(A26,A27) -> 00.01.1900. sanasidan

Sheet dalolatnoma
A2: ="GAROV PREDMETI QIYMATINI KELISHISH №"&umumiy_malumot!B141&" SONLI DALOLATNOMASI " -> GAROV PREDMETI QIYMATINI KELISHISH №1 SONLI DALOLATNOMASI
A4: Toshkent shahri | F4: =umumiy_malumot!B142 -> 2 fevral 2026 y.
A6: =IF(umumiy_malumot!B103="ko'chmas mulk",dalolatnoma!A10:F10,dalolatnoma!A10:F10) -> «PULLOL BUSINESS MIKROMOLIYA TASHKILOTI» MChJning (1-tomon) vakili bo‘lgan Direktor Obidov A. Sh., O‘zbekiston Respublikasi fuqarosi va garovga beruvchi SIMONYAN VADIM ROMANOVICH (2-tomon) o’rtalarida, 2 fevral 2026 y.dan №43-sonli Mikrokredit shartnomasiga muvofiq 1-tomon 2-tomonga berilgan Mikroqarz bo‘yicha ta’minot sifatida taqdim etilgan, 2-tomonga mulk huquqi asosida tegishli bo‘lgan mulkning garov qiymatini kelishish muzokaralari o’tkazildi.
A7: =IF(umumiy_malumot!B93="ha",dalolatnoma!A9:F9,dalolatnoma!A8:F8) -> «PULLOL BUSINESS MIKROMOLIYA TASHKILOTI» MChJning (1-tomon) vakili bo‘lgan Direktor Obidov A. Sh., va O‘zbekiston Respublikasi fuqarosi SIMONYAN VADIM ROMANOVICH (2-tomon) va garov egasi SIMONYAN VADIM ROMANOVICH (3-tomon) 2 fevral 2026 y.dan №43 Mikrokredit shartnomasiga muvofiq 1-tomon 2-tomonga berilgan Mikroqarz bo‘yicha ta’minot sifatida taqdim etilgan, 2-tomonga mulk huquqi asosida tegishli bo‘lgan mulkning garov qiymatini kelishish muzokaralari o’tkazildi.
A8: =""&umumiy_malumot!B147&"ning (1-tomon) vakili bo‘lgan "&umumiy_malumot!A150&" "&umumiy_malumot!B150&", va O‘zbekiston Respublikasi fuqarosi "&umumiy_malumot!B5&" (2-tomon) va garov egasi "&umumiy_malumot!C117&" (3-tomon) "&umumiy_malumot!B74&" "&umumiy_malumot!C64&" shartnomasiga muvofiq 1-tomon 2-tomonga berilgan "&umumiy_malumot!B65&" bo‘yicha ta’minot sifatida taqdim etilgan, 2-tomonga mulk huquqi asosida tegishli bo‘lgan mulkning garov qiymatini kelishish muzokaralari o’tkazildi. " -> «PULLOL BUSINESS MIKROMOLIYA TASHKILOTI» MChJning (1-tomon) vakili bo‘lgan Direktor Obidov A. Sh., va O‘zbekiston Respublikasi fuqarosi SIMONYAN VADIM ROMANOVICH (2-tomon) va garov egasi SIMONYAN VADIM ROMANOVICH (3-tomon) 2 fevral 2026 y.dan №43 Mikrokredit shartnomasiga muvofiq 1-tomon 2-tomonga berilgan Mikroqarz bo‘yicha ta’minot sifatida taqdim etilgan, 2-tomonga mulk huquqi asosida tegishli bo‘lgan mulkning garov qiymatini kelishish muzokaralari o’tkazildi.
A9: =""&umumiy_malumot!B147&"ning (1-tomon) vakili bo‘lgan "&umumiy_malumot!A150&" "&umumiy_malumot!B150&", va O‘zbekiston Respublikasi fuqarosi "&umumiy_malumot!B5&" (2-tomon) va garov egasi "&umumiy_malumot!C117&" (3-tomon) "&umumiy_malumot!B74&" "&umumiy_malumot!C64&" shartnomasiga muvofiq 1-tomon 2-tomonga berilgan "&umumiy_malumot!B65&" bo‘yicha ta’minot sifatida taqdim etilgan, 2-tomonga mulk huquqi asosida tegishli bo‘lgan mulkning garov qiymatini kelishish muzokaralari o’tkazildi. " -> «PULLOL BUSINESS MIKROMOLIYA TASHKILOTI» MChJning (1-tomon) vakili bo‘lgan Direktor Obidov A. Sh., va O‘zbekiston Respublikasi fuqarosi SIMONYAN VADIM ROMANOVICH (2-tomon) va garov egasi SIMONYAN VADIM ROMANOVICH (3-tomon) 2 fevral 2026 y.dan №43 Mikrokredit shartnomasiga muvofiq 1-tomon 2-tomonga berilgan Mikroqarz bo‘yicha ta’minot sifatida taqdim etilgan, 2-tomonga mulk huquqi asosida tegishli bo‘lgan mulkning garov qiymatini kelishish muzokaralari o’tkazildi.
A10: =IF(umumiy_malumot!B93="ha",dalolatnoma!A12:F12,dalolatnoma!A11:F11) -> «PULLOL BUSINESS MIKROMOLIYA TASHKILOTI» MChJning (1-tomon) vakili bo‘lgan Direktor Obidov A. Sh., O‘zbekiston Respublikasi fuqarosi va garovga beruvchi SIMONYAN VADIM ROMANOVICH (2-tomon) o’rtalarida, 2 fevral 2026 y.dan №43-sonli Mikrokredit shartnomasiga muvofiq 1-tomon 2-tomonga berilgan Mikroqarz bo‘yicha ta’minot sifatida taqdim etilgan, 2-tomonga mulk huquqi asosida tegishli bo‘lgan mulkning garov qiymatini kelishish muzokaralari o’tkazildi.
A11: =""&umumiy_malumot!B147&"ning (1-tomon) vakili bo‘lgan "&umumiy_malumot!A150&" "&umumiy_malumot!B150&", O‘zbekiston Respublikasi fuqarosi "&umumiy_malumot!B5&" (2-tomon) va garovga beruvchi O‘zbekiston Respublikasi fuqarosi "&umumiy_malumot!B117&" (3-tomon) o’rtalarida, "&umumiy_malumot!B74&"-sonli "&umumiy_malumot!C64&" shartnomasiga muvofiq 1-tomon 2-tomonga berilgan "&umumiy_malumot!B65&" bo‘yicha ta’minot sifatida taqdim etilgan, 3-tomonga mulk huquqi asosida tegishli bo‘lgan mulkning garov qiymatini kelishish muzokaralari o’tkazildi." -> «PULLOL BUSINESS MIKROMOLIYA TASHKILOTI» MChJning (1-tomon) vakili bo‘lgan Direktor Obidov A. Sh., O‘zbekiston Respublikasi fuqarosi SIMONYAN VADIM ROMANOVICH (2-tomon) va garovga beruvchi O‘zbekiston Respublikasi fuqarosi SIMONYAN VADIM ROMANOVICH (3-tomon) o’rtalarida, 2 fevral 2026 y.dan №43-sonli Mikrokredit shartnomasiga muvofiq 1-tomon 2-tomonga berilgan Mikroqarz bo‘yicha ta’minot sifatida taqdim etilgan, 3-tomonga mulk huquqi asosida tegishli bo‘lgan mulkning garov qiymatini kelishish muzokaralari o’tkazildi.
A12: =""&umumiy_malumot!B147&"ning (1-tomon) vakili bo‘lgan "&umumiy_malumot!A150&" "&umumiy_malumot!B150&", O‘zbekiston Respublikasi fuqarosi va garovga beruvchi "&umumiy_malumot!B5&" (2-tomon) o’rtalarida, "&umumiy_malumot!B74&"-sonli "&umumiy_malumot!C64&" shartnomasiga muvofiq 1-tomon 2-tomonga berilgan "&umumiy_malumot!B65&" bo‘yicha ta’minot sifatida taqdim etilgan, 2-tomonga mulk huquqi asosida tegishli bo‘lgan mulkning garov qiymatini kelishish muzokaralari o’tkazildi." -> «PULLOL BUSINESS MIKROMOLIYA TASHKILOTI» MChJning (1-tomon) vakili bo‘lgan Direktor Obidov A. Sh., O‘zbekiston Respublikasi fuqarosi va garovga beruvchi SIMONYAN VADIM ROMANOVICH (2-tomon) o’rtalarida, 2 fevral 2026 y.dan №43-sonli Mikrokredit shartnomasiga muvofiq 1-tomon 2-tomonga berilgan Mikroqarz bo‘yicha ta’minot sifatida taqdim etilgan, 2-tomonga mulk huquqi asosida tegishli bo‘lgan mulkning garov qiymatini kelishish muzokaralari o’tkazildi.
A13: ="Garov predmeti sifatida "&umumiy_malumot!B125&", 3-tomonga egalik huquqi tegishli bo'lgan, quyidagi tafsilotlarga ega avtotransport vositasi taqdim etiladi:" -> Garov predmeti sifatida , 3-tomonga egalik huquqi tegishli bo'lgan, quyidagi tafsilotlarga ega avtotransport vositasi taqdim etiladi:
A14: ="Garov predmeti sifatida "&umumiy_malumot!B125&", 2-tomonga egalik huquqi tegishli bo'lgan, quyidagi tafsilotlarga ega avtotransport vositasi taqdim etiladi:" -> Garov predmeti sifatida , 2-tomonga egalik huquqi tegishli bo'lgan, quyidagi tafsilotlarga ega avtotransport vositasi taqdim etiladi:
A15: =IF(umumiy_malumot!B93="ha",dalolatnoma!A14:F14,dalolatnoma!A13:F13) -> Garov predmeti sifatida , 2-tomonga egalik huquqi tegishli bo'lgan, quyidagi tafsilotlarga ega avtotransport vositasi taqdim etiladi:
A16: ="Garov predmeti sifatida "&umumiy_malumot!C126&", 2-tomonga egalik huquqi tegishli bo'lgan, quyidagi tafsilotlarga ega ko'chmas mulk taqdim etiladi:" -> Garov predmeti sifatida Yakka tartibdagi uy-joy, 2-tomonga egalik huquqi tegishli bo'lgan, quyidagi tafsilotlarga ega ko'chmas mulk taqdim etiladi:
A17: ="Garov predmeti sifatida "&umumiy_malumot!C126&", 3-tomonga egalik huquqi tegishli bo'lgan, quyidagi tafsilotlarga ega ko'chmas mulk taqdim etiladi:" -> Garov predmeti sifatida Yakka tartibdagi uy-joy, 3-tomonga egalik huquqi tegishli bo'lgan, quyidagi tafsilotlarga ega ko'chmas mulk taqdim etiladi:
A18: =IF(umumiy_malumot!B93="ha",dalolatnoma!A16:F16,dalolatnoma!A17:F17) -> Garov predmeti sifatida Yakka tartibdagi uy-joy, 2-tomonga egalik huquqi tegishli bo'lgan, quyidagi tafsilotlarga ega ko'chmas mulk taqdim etiladi:
A19: =IF(umumiy_malumot!B103="Avtotransport",dalolatnoma!A15:F15,dalolatnoma!A18:F18) -> Garov predmeti sifatida Yakka tartibdagi uy-joy, 2-tomonga egalik huquqi tegishli bo'lgan, quyidagi tafsilotlarga ega ko'chmas mulk taqdim etiladi:
A20: Nomi | B20: Umumiy yer maydoni, (m2) | D20: Qurilish osti maydoni, (m2) | E20: Umumiy foydali maydoni, (m2) | F20: Yashash maydoni, (m2)
A21: =umumiy_malumot!C125 -> Yakka tartibdagi uy-joy | B21: =umumiy_malumot!C134 -> 166 | D21: =umumiy_malumot!C133 -> 87 | E21: =umumiy_malumot!C130 -> 48.67 | F21: =umumiy_malumot!C131 -> 30.84
A22: ="-* avtotransport egasi: "&umumiy_malumot!B117&"" -> -* avtotransport egasi: SIMONYAN VADIM ROMANOVICH
A23: ="-* texnik pasport: "&umumiy_malumot!B124&"" -> -* texnik pasport:
A24: ="-* roʻyxatdan oʻtgan manzili/garaj manzili: "&umumiy_malumot!B122&"" -> -* roʻyxatdan oʻtgan manzili/garaj manzili: TOSHKENT SHAHAR YUNUSOBOD TUMANI OTCHOPAR-1 MFY KARIM ZARIPOV KO'CHASI 8-6 UY
A25: ="-* davlat raqami: "&umumiy_malumot!B126&"" -> -* davlat raqami:
A27: Nomi | D27: Umumiy foydali maydoni | E27: Yashash maydoni | F27: Umumiy maydoni
A28: Yashash xona | D28: 3 | E28: 18.82
A29: Umumiy maydon | D29: 43.96 | E29: 18.82 | F29: 43.96
E30: 0 | F30: =D30+E30 -> 0
E31: 0 | F31: =D31+E31 -> 0
E32: 0 | F32: =D32+E32 -> 0
E33: 0 | F33: =D33+E33 -> 0
F34: =D34+E34 -> 0
E35: 0 | F35: =D35+E35 -> 0
F36: =D36+E36 -> 0
F37: =D37+E37 -> 0
A38: JAMI | D38: =D29 -> 43.96 | E38: =E28 -> 18.82 | F38: =F29 -> 43.96
A39: ="-* ko'chmas mulk egasi: "&umumiy_malumot!C117&"" -> -* ko'chmas mulk egasi: SIMONYAN VADIM ROMANOVICH
A40: ="-* reestr raqami: "&umumiy_malumot!C124&"" -> -* reestr raqami: №1726266/R-A5552339
A41: ="-* kadastr raqami: "&umumiy_malumot!C127&"" -> -* kadastr raqami: 07.01.2025 y. №10:07:04:02:02:7296/06
A42: ="-* manzil: "&umumiy_malumot!C123&"" -> -* manzil: TOSHKENT SHAHAR YUNUSOBOD TUMANI OTCHOPAR-1 MFY KARIM ZARIPOV KO'CHASI 8-6 UY
A44: =IF(umumiy_malumot!B93="ha",dalolatnoma!A46:F46,dalolatnoma!A45:F45) -> Tomonlar o’rtasida o’tkazilgan muzokaralar natijalariga ko‘ra, 2-tomon ta’minot sifatida quyidagi tafsilotlarga ega bo’lgan garov predmetini taqdim etadi, 1-tomon esa ushbu garov predmetini 2 fevral 2026 y.dan №43 Mikrokredit shartnomasi bo‘yicha berilgan Mikroqarz bo‘yicha 70 000 000,00 (yetmish million so'm) so’m bo‘lgan kelishilgan garov qiymatida qabul qiladi::
A45: ="Tomonlar o’rtasida o’tkazilgan muzokaralar natijalariga ko‘ra, 2-tomon ta’minot sifatida quyidagi tafsilotlarga ega bo’lgan garov predmetini taqdim etadi, 1-tomon esa ushbu garov predmetini "&umumiy_malumot!B74&" "&umumiy_malumot!B65&" shartnomasi bo‘yicha berilgan "&umumiy_malumot!B65&" bo‘yicha "&FIXED(umumiy_malumot!B136,2)&" ("&umumiy_malumot!B137&") so’m bo‘lgan kelishilgan garov qiymatida qabul qiladi::" -> Tomonlar o’rtasida o’tkazilgan muzokaralar natijalariga ko‘ra, 2-tomon ta’minot sifatida quyidagi tafsilotlarga ega bo’lgan garov predmetini taqdim etadi, 1-tomon esa ushbu garov predmetini 2 fevral 2026 y.dan №43 Mikroqarz shartnomasi bo‘yicha berilgan Mikroqarz bo‘yicha 70 000 000,00 (yetmish million so'm) so’m bo‘lgan kelishilgan garov qiymatida qabul qiladi::
A46: ="Tomonlar o’rtasida o’tkazilgan muzokaralar natijalariga ko‘ra, 2-tomon ta’minot sifatida quyidagi tafsilotlarga ega bo’lgan garov predmetini taqdim etadi, 1-tomon esa ushbu garov predmetini "&umumiy_malumot!B74&" "&umumiy_malumot!C64&" shartnomasi bo‘yicha berilgan "&umumiy_malumot!B65&" bo‘yicha "&FIXED(umumiy_malumot!B136,2)&" ("&umumiy_malumot!B137&") so’m bo‘lgan kelishilgan garov qiymatida qabul qiladi::" -> Tomonlar o’rtasida o’tkazilgan muzokaralar natijalariga ko‘ra, 2-tomon ta’minot sifatida quyidagi tafsilotlarga ega bo’lgan garov predmetini taqdim etadi, 1-tomon esa ushbu garov predmetini 2 fevral 2026 y.dan №43 Mikrokredit shartnomasi bo‘yicha berilgan Mikroqarz bo‘yicha 70 000 000,00 (yetmish million so'm) so’m bo‘lgan kelishilgan garov qiymatida qabul qiladi::
A47: Nomi | B47: =B20 -> Umumiy yer maydoni, (m2) | C47: =D20 -> Qurilish osti maydoni, (m2) | D47: =E20 -> Umumiy foydali maydoni, (m2) | E47: =F20 -> Yashash maydoni, (m2) | F47: Kelishilgan garov qiymati, so'm
A48: =A21 -> Yakka tartibdagi uy-joy | B48: =B21 -> 166 | C48: =D21 -> 87 | D48: =E21 -> 48.67 | E48: =F21 -> 30.84 | F48: =""&FIXED(umumiy_malumot!B136,2)&" ("&umumiy_malumot!B137&")" -> 70 000 000,00 (yetmish million so'm)
A50: Наименование | C50: Полезная площадь | D50: Жилая площадь | E50: Общая площадь | F50: Согласованная залоговая стоимость, сум
A51: =A28 -> Yashash xona | C51: =D28 -> 3 | D51: =E28 -> 18.82 | E51: =F28 -> 0 | F51: =""&FIXED(umumiy_malumot!C136,2)&" ("&umumiy_malumot!B137&")" -> 70 000 000,00 (yetmish million so'm)
A53: =A29 -> Umumiy maydon | C53: =D29 -> 43.96 | D53: =E29 -> 18.82 | E53: =F29 -> 43.96
A54: =A30 -> 0 | C54: =D30 -> 0 | D54: =E30 -> 0 | E54: =F30 -> 0
A55: =A31 -> 0 | C55: =D31 -> 0 | D55: =E31 -> 0 | E55: =F31 -> 0
A56: =A32 -> 0 | C56: =D32 -> 0 | D56: =E32 -> 0 | E56: =F32 -> 0
A57: =A33 -> 0 | C57: =D33 -> 0 | D57: =E33 -> 0 | E57: =F33 -> 0
A58: =A34 -> 0 | C58: =D34 -> 0 | D58: =E34 -> 0 | E58: =F34 -> 0
A59: =A35 -> 0 | C59: =D35 -> 0 | D59: =E35 -> 0 | E59: =F35 -> 0
A60: =A36 -> 0 | C60: =D36 -> 0 | D60: =E36 -> 0 | E60: =F36 -> 0
A61: =A37 -> 0 | C61: =D37 -> 0 | D61: =E37 -> 0 | E61: =F37 -> 0
A62: =A38 -> JAMI | C62: =D38 -> 43.96 | D62: =E38 -> 18.82 | E62: =F38 -> 43.96 | F62: =FIXED(umumiy_malumot!C136,2) -> 70 000 000,00
